Workbook

Sheet Main
A1: Indice | C1: Fecha de liq | D1: =TODAY()+3 -> 46068 | V1: MEP | W1: =I15 -> 1438.6
A2: Caución
A3: FX
A4: Favoritos | C4: Caución | D4: Moneda | E4: Plazo | F4: Tasa | G4: Bid | H4: Ask | I4: VWAP | K4: Ticker | L4: Variación | M4: Tasa | O4: LECAPS | P4: Ticker | Q4: TEM | R4: Vencimiento | S4: Variación | T4: TNA | U4: Días a vencimiento | V4: Bid | W4: Ask | X4: Bid Volume | Y4: Ask Volume | Z4: Total Volume | AA4: Tasa directa | AB4: MEP BE | AD4: Soberanos HD | AE4: Ticker | AF4: TIR | AG4: MD | AH4: Bid | AI4: Ask | AJ4: Bid Volume | AK4: Ask Volume | AL4: Total Volume | AM4: Variación | AO4: Empresa | AP4: Ticker | AQ4: TIR | AR4: MD | AS4: Vto | AT4: Bid Price | AU4: Ask Price | AV4: Bid Volume | AW4: Ask volume | AX4: Total volume | AY4: Variación | AZ4: Periodicidad | BA4: Lamina minima | BB4: Tipo
A5: LECAPs | D5: USD | E5: 1 | F5: =VLOOKUP(E5,Caucho!$E$2:$N$65,3,FALSE) -> 0.0101 | G5: =VLOOKUP(E5,Caucho!$E$2:$N$65,7,FALSE) -> 0.0097 | H5: =VLOOKUP(E5,Caucho!$E$2:$N$65,8,FALSE) -> 0.0101 | I5: =VLOOKUP(E5,Caucho!$E$2:$N$65,10,FALSE) -> 0.010170026 | K5: LECAPs | L5: =AVERAGE(Tabla11[Variación]) -> 0.0023285714 | M5: =AVERAGE(Tabla11[TEM]) -> 0.027271311 | AE5: AE38D | AF5: {=INDIRECT("'" & Tabla9[[#This Row],[Ticker]] & "'!K4")} -> 0.092724559 | AG5: {=INDIRECT("'" & Tabla9[[#This Row],[Ticker]] & "'!K3")} -> 4.9172261 | AH5: {=_xll.PrecioBD(Tabla9[[#This Row],[Ticker]],"24","BID","N")} -> 81.47 | AI5: {=_xll.PrecioBD(Tabla9[[#This Row],[Ticker]],"24","ASK","N")} -> 81.48 | AJ5: {=_xll.PrecioBD(Tabla9[[#This Row],[Ticker]],24,"QUANTITY BID","N")} -> 2193 | AK5: {=_xll.PrecioBD(Tabla9[[#This Row],[Ticker]],24,"QUANTITY ASK","N")} -> 994 | AL5: {=_xll.PrecioBD(Tabla9[[#This Row],[Ticker]],24,"VOLUME AMOUNT","N")} -> 1057046.4 | AM5: {=_xll.PrecioBD(Tabla9[[#This Row],[Ticker]],24,"IMBALANCE","N")} -> -0.0014 | AP5: RUCDD | AQ5: {=INDIRECT("'" & AP5 & "'!K4")} -> 0.088503292 | AR5: {=INDIRECT("'" & AP5 & "'!K3")} -> 3.3903709 | AS5: 47822 | AT5: {=_xll.PrecioBD(AP5,"24","BID","N")} -> 105.4 | AU5: {=_xll.PrecioBD(AP5,"24","ASK","N")} -> 105.7 | AV5: {=_xll.PrecioBD(AP5,24,"QUANTITY BID","N")} -> 1812 | AW5: {=_xll.PrecioBD(AP5,24,"QUANTITY ASK","N")} -> 1064 | AX5: {=_xll.PrecioBD(AP5,24,"VOLUME AMOUNT","N")} -> 18647.88 | AY5: {=_xll.PrecioBD(AP5,24,"IMBALANCE","N")} -> 0.0061 | AZ5: Semestral | BA5: 1 | BB5: Sinkable
A6: Soberanos HD | D6: USD | E6: 7 | F6: =VLOOKUP(E6,Caucho!$E$2:$N$65,3,FALSE) -> 0.015 | G6: =VLOOKUP(E6,Caucho!$E$2:$N$65,7,FALSE) -> 0.0125 | H6: =VLOOKUP(E6,Caucho!$E$2:$N$65,8,FALSE) -> 0.015 | I6: =VLOOKUP(E6,Caucho!$E$2:$N$65,10,FALSE) -> 0.016787804 | K6: Soberanos HD | L6: =AVERAGE(Tabla9[Variación]) -> 0.0017 | M6: =AVERAGE(Tabla9[TIR]) -> 0.080722115 | P6: S27F6 | Q6: {=INDIRECT("'" & P6 & "'!J6")} -> 0.031282205 | R6: {=INDIRECT("'" & P6& "'!B3")} -> 46080 | S6: {=_xll.PrecioBD(P6,24,"IMBALANCE","N")} -> 0.0002 | T6: {=INDIRECT("'" & Tabla11[[#This Row],[Ticker]]& "'!J5")} -> 0.37188975 | U6: =Tabla11[[#This Row],[Vencimiento]]-$D$1 -> 12 | V6: {=_xll.PrecioBD(Tabla11[[#This Row],[Ticker]],"24","BID","N")} -> 124.315 | W6: {=_xll.PrecioBD(Tabla11[[#This Row],[Ticker]],"24","ASK","N")} -> 124.32 | X6: {=_xll.PrecioBD(Tabla11[[#This Row],[Ticker]],24,"QUANTITY BID","N")} -> 31951733 | Y6: {=_xll.PrecioBD(Tabla11[[#This Row],[Ticker]],24,"QUANTITY ASK","N")} -> 11705293 | Z6: {=_xll.PrecioBD(Tabla11[[#This Row],[Ticker]],24,"VOLUME AMOUNT","N")} -> 9.2597273e+09 | AA6: =Tabla11[[#This Row],[TNA]]/365*Tabla11[[#This Row],[Días a vencimiento]] -> 0.012226512 | AB6: =$I$15*(1+Tabla11[[#This Row],[TNA]]/365*Tabla11[[#This Row],[Días a vencimiento]]) -> 1456.189 | AE6: AL35D | AF6: {=INDIRECT("'" & Tabla9[[#This Row],[Ticker]] & "'!K4")} -> 0.091228488 | AG6: {=INDIRECT("'" & Tabla9[[#This Row],[Ticker]] & "'!K3")} -> 5.6582089 | AH6: {=_xll.PrecioBD(Tabla9[[#This Row],[Ticker]],"24","BID","N")} -> 78.77 | AI6: {=_xll.PrecioBD(Tabla9[[#This Row],[Ticker]],"24","ASK","N")} -> 78.83 | AJ6: {=_xll.PrecioBD(Tabla9[[#This Row],[Ticker]],24,"QUANTITY BID","N")} -> 3062 | AK6: {=_xll.PrecioBD(Tabla9[[#This Row],[Ticker]],24,"QUANTITY ASK","N")} -> 1738 | AL6: {=_xll.PrecioBD(Tabla9[[#This Row],[Ticker]],24,"VOLUME AMOUNT","N")} -> 605208.73 | AM6: {=_xll.PrecioBD(Tabla9[[#This Row],[Ticker]],24,"IMBALANCE","N")} -> -0.0007 | AP6: DNC7D | AQ6: {=INDIRECT("'" & AP6 & "'!K4")} -> 0.085928509 | AR6: {=INDIRECT("'" & AP6 & "'!K3")} -> 2.9700447 | AS6: 47780 | AT6: {=_xll.PrecioBD(AP6,"24","BID","N")} -> 107 | AU6: {=_xll.PrecioBD(AP6,"24","ASK","N")} -> 107.15 | AV6: {=_xll.PrecioBD(AP6,24,"QUANTITY BID","N")} -> 7300 | AW6: {=_xll.PrecioBD(AP6,24,"QUANTITY ASK","N")} -> 2300 | AX6: {=_xll.PrecioBD(AP6,24,"VOLUME AMOUNT","N")} -> 94696 | AY6: {=_xll.PrecioBD(AP6,24,"IMBALANCE","N")} -> 0 | AZ6: Semestral | BA6: 1000 | BB6: Sinkable
A7: Ons NY | D7: USD | E7: 31 | F7: =VLOOKUP(E7,Caucho!$E$2:$N$65,3,FALSE) -> #N/A | G7: =VLOOKUP(E7,Caucho!$E$2:$N$65,7,FALSE) -> #N/A | H7: =VLOOKUP(E7,Caucho!$E$2:$N$65,8,FALSE) -> #N/A | I7: =VLOOKUP(E7,Caucho!$E$2:$N$65,10,FALSE) -> #N/A | K7: ONs | L7: =AVERAGE(Tabla1[Variación]) -> 0.000325 | M7: =AVERAGE(AQ2:AQ19) -> 0.074338263 | P7: S16M6 | Q7: {=INDIRECT("'" & P7 & "'!J6")} -> 0.029721472 | R7: {=INDIRECT("'" & P7& "'!B3")} -> 46097 | S7: {=_xll.PrecioBD(P7,24,"IMBALANCE","N")} -> 0.0012 | T7: {=INDIRECT("'" & Tabla11[[#This Row],[Ticker]]& "'!J5")} -> 0.35641332 | U7: =Tabla11[[#This Row],[Vencimiento]]-$D$1 -> 29 | V7: {=_xll.PrecioBD(Tabla11[[#This Row],[Ticker]],"24","BID","N")} -> 101.725 | W7: {=_xll.PrecioBD(Tabla11[[#This Row],[Ticker]],"24","ASK","N")} -> 101.74 | X7: {=_xll.PrecioBD(Tabla11[[#This Row],[Ticker]],24,"QUANTITY BID","N")} -> 100 | Y7: {=_xll.PrecioBD(Tabla11[[#This Row],[Ticker]],24,"QUANTITY ASK","N")} -> 27975415 | Z7: {=_xll.PrecioBD(Tabla11[[#This Row],[Ticker]],24,"VOLUME AMOUNT","N")} -> 2.344682e+10 | AA7: =Tabla11[[#This Row],[TNA]]/365*Tabla11[[#This Row],[Días a vencimiento]] -> 0.028317771 | AB7: =$I$15*(1+Tabla11[[#This Row],[TNA]]/365*Tabla11[[#This Row],[Días a vencimiento]]) -> 1479.3379 | AE7: AL41D | AF7: {=INDIRECT("'" & Tabla9[[#This Row],[Ticker]] & "'!K4")} -> 0.090390292 | AG7: {=INDIRECT("'" & Tabla9[[#This Row],[Ticker]] & "'!K3")} -> 6.2109542 | AH7: {=_xll.PrecioBD(Tabla9[[#This Row],[Ticker]],"24","BID","N")} -> 74.13 | AI7: {=_xll.PrecioBD(Tabla9[[#This Row],[Ticker]],"24","ASK","N")} -> 74.15 | AJ7: {=_xll.PrecioBD(Tabla9[[#This Row],[Ticker]],24,"QUANTITY BID","N")} -> 1680 | AK7: {=_xll.PrecioBD(Tabla9[[#This Row],[Ticker]],24,"QUANTITY ASK","N")} -> 7910 | AL7: {=_xll.PrecioBD(Tabla9[[#This Row],[Ticker]],24,"VOLUME AMOUNT","N")} -> 92177.52 | AM7: {=_xll.PrecioBD(Tabla9[[#This Row],[Ticker]],24,"IMBALANCE","N")} -> 0.0027 | AP7: TLCTD | AQ7: {=INDIRECT("'" & AP7 & "'!K4")} -> 0.076098976 | AR7: {=INDIRECT("'" & AP7 & "'!K3")} -> 6.4927935 | AS7: 49695 | AT7: {=_xll.PrecioBD(AP7,"24","BID","N")} -> 107.1 | AU7: {=_xll.PrecioBD(AP7,"24","ASK","N")} -> 107.45 | AV7: {=_xll.PrecioBD(AP7,24,"QUANTITY BID","N")} -> 14542 | AW7: {=_xll.PrecioBD(AP7,24,"QUANTITY ASK","N")} -> 1000 | AX7: {=_xll.PrecioBD(AP7,24,"VOLUME AMOUNT","N")} -> 93632.85 | AY7: {=_xll.PrecioBD(AP7,24,"IMBALANCE","N")} -> 0.0004 | BA7: 0 | BB7: 0
A8: CEDEARs | D8: ARS | E8: 1 | F8: =VLOOKUP(E8,Caucho!$E$66:$N$141,3,FALSE) -> 0.298 | G8: =VLOOKUP(E8,Caucho!$E$66:$N$141,7,FALSE) -> 0.298 | H8: =VLOOKUP(E8,Caucho!$E$66:$N$141,8,FALSE) -> 0.299 | I8: =VLOOKUP(E8,Caucho!$E$66:$N$141,10,FALSE) -> 0.27311917 | K8: VXX | L8: {=_xll.PrecioBD(K8,24,"IMBALANCE","N")} -> 0 | P8: S17A6 | Q8: {=INDIRECT("'" & P8 & "'!J6")} -> 0.029462418 | R8: {=INDIRECT("'" & P8& "'!B3")} -> 46129 | S8: {=_xll.PrecioBD(P8,24,"IMBALANCE","N")} -> 0.0011 | T8: {=INDIRECT("'" & Tabla11[[#This Row],[Ticker]]& "'!J5")} -> 0.35878603 | U8: =Tabla11[[#This Row],[Vencimiento]]-$D$1 -> 61 | V8: {=_xll.PrecioBD(Tabla11[[#This Row],[Ticker]],"24","BID","N")} -> 103.899 | W8: {=_xll.PrecioBD(Tabla11[[#This Row],[Ticker]],"24","ASK","N")} -> 103.9 | X8: {=_xll.PrecioBD(Tabla11[[#This Row],[Ticker]],24,"QUANTITY BID","N")} -> 384989 | Y8: {=_xll.PrecioBD(Tabla11[[#This Row],[Ticker]],24,"QUANTITY ASK","N")} -> 499610894 | Z8: {=_xll.PrecioBD(Tabla11[[#This Row],[Ticker]],24,"VOLUME AMOUNT","N")} -> 9.3694606e+10 | AA8: =Tabla11[[#This Row],[TNA]]/365*Tabla11[[#This Row],[Días a vencimiento]] -> 0.059961501 | AB8: =$I$15*(1+Tabla11[[#This Row],[TNA]]/365*Tabla11[[#This Row],[Días a vencimiento]]) -> 1524.8606 | AE8: GD41D | AF8: {=INDIRECT("'" & Tabla9[[#This Row],[Ticker]] & "'!K4")} -> 0.088145849 | AG8: {=INDIRECT("'" & Tabla9[[#This Row],[Ticker]] & "'!K3")} -> 6.2475791 | AH8: {=_xll.PrecioBD(Tabla9[[#This Row],[Ticker]],"24","BID","N")} -> 75.11 | AI8: {=_xll.PrecioBD(Tabla9[[#This Row],[Ticker]],"24","ASK","N")} -> 75.15 | AJ8: {=_xll.PrecioBD(Tabla9[[#This Row],[Ticker]],24,"QUANTITY BID","N")} -> 10 | AK8: {=_xll.PrecioBD(Tabla9[[#This Row],[Ticker]],24,"QUANTITY ASK","N")} -> 10 | AL8: {=_xll.PrecioBD(Tabla9[[#This Row],[Ticker]],24,"VOLUME AMOUNT","N")} -> 167503.41 | AM8: {=_xll.PrecioBD(Tabla9[[#This Row],[Ticker]],24,"IMBALANCE","N")} -> 0.0018 | AP8: TLCPD | AQ8: {=INDIRECT("'" & AP8 & "'!K4")} -> 0.077443376 | AR8: {=INDIRECT("'" & AP8 & "'!K3")} -> 4.9623155 | AS8: 48726 | AT8: {=_xll.PrecioBD(AP8,"24","BID","N")} -> 111.2 | AU8: {=_xll.PrecioBD(AP8,"24","ASK","N")} -> 111.3 | AV8: {=_xll.PrecioBD(AP8,24,"QUANTITY BID","N")} -> 53310 | AW8: {=_xll.PrecioBD(AP8,24,"QUANTITY ASK","N")} -> 71456 | AX8: {=_xll.PrecioBD(AP8,24,"VOLUME AMOUNT","N")} -> 182321.69 | AY8: {=_xll.PrecioBD(AP8,24,"IMBALANCE","N")} -> -0.0017 | AZ8: Semestral | BA8: 1 | BB8: Sinkable
A9: Panel Lider | D9: ARS | E9: 7 | F9: =VLOOKUP(E9,Caucho!$E$66:$N$141,3,FALSE) -> 0.31 | G9: =VLOOKUP(E9,Caucho!$E$66:$N$141,7,FALSE) -> 0.31 | H9: =VLOOKUP(E9,Caucho!$E$66:$N$141,8,FALSE) -> 0.32 | I9: =VLOOKUP(E9,Caucho!$E$66:$N$141,10,FALSE) -> 0.29870893 | K9: DIA | L9: {=_xll.PrecioBD(K9,24,"IMBALANCE","N")} -> -0.0059 | P9: S30A6 | Q9: {=INDIRECT("'" & P9 & "'!J6")} -> 0.027674298 | R9: {=INDIRECT("'" & P9& "'!B3")} -> 46142 | S9: {=_xll.PrecioBD(P9,24,"IMBALANCE","N")} -> 0.0033 | T9: {=INDIRECT("'" & Tabla11[[#This Row],[Ticker]]& "'!J5")} -> 0.33870213 | U9: =Tabla11[[#This Row],[Vencimiento]]-$D$1 -> 74 | V9: {=_xll.PrecioBD(Tabla11[[#This Row],[Ticker]],"24","BID","N")} -> 119.28 | W9: {=_xll.PrecioBD(Tabla11[[#This Row],[Ticker]],"24","ASK","N")} -> 119.298 | X9: {=_xll.PrecioBD(Tabla11[[#This Row],[Ticker]],24,"QUANTITY BID","N")} -> 5045581 | Y9: {=_xll.PrecioBD(Tabla11[[#This Row],[Ticker]],24,"QUANTITY ASK","N")} -> 50000000 | Z9: {=_xll.PrecioBD(Tabla11[[#This Row],[Ticker]],24,"VOLUME AMOUNT","N")} -> 7.636687e+08 | AA9: =Tabla11[[#This Row],[TNA]]/365*Tabla11[[#This Row],[Días a vencimiento]] -> 0.068668377 | AB9: =$I$15*(1+Tabla11[[#This Row],[TNA]]/365*Tabla11[[#This Row],[Días a vencimiento]]) -> 1537.3863 | AE9: AL30D | AF9: {=INDIRECT("'" & Tabla9[[#This Row],[Ticker]] & "'!K4")} -> 0.078818211 | AG9: {=INDIRECT("'" & Tabla9[[#This Row],[Ticker]] & "'!K3")} -> 2.1828813 | AH9: {=_xll.PrecioBD(Tabla9[[#This Row],[Ticker]],"24","BID","N")} -> 62.15 | AI9: {=_xll.PrecioBD(Tabla9[[#This Row],[Ticker]],"24","ASK","N")} -> 62.17 | AJ9: {=_xll.PrecioBD(Tabla9[[#This Row],[Ticker]],24,"QUANTITY BID","N")} -> 32567 | AK9: {=_xll.PrecioBD(Tabla9[[#This Row],[Ticker]],24,"QUANTITY ASK","N")} -> 181686 | AL9: {=_xll.PrecioBD(Tabla9[[#This Row],[Ticker]],24,"VOLUME AMOUNT","N")} -> 30904047 | AM9: {=_xll.PrecioBD(Tabla9[[#This Row],[Ticker]],24,"IMBALANCE","N")} -> 0.0014 | AP9: MGCRD | AQ9: {=INDIRECT("'" & AP9 & "'!K4")} -> 0.073805109 | AR9: {=INDIRECT("'" & AP9 & "'!K3")} -> 7.5792451 | AS9: 50360 | AT9: {=_xll.PrecioBD(AP9,"24","BID","N")} -> 105.8 | AU9: {=_xll.PrecioBD(AP9,"24","ASK","N")} -> 105.9 | AV9: {=_xll.PrecioBD(AP9,24,"QUANTITY BID","N")} -> 10000 | AW9: {=_xll.PrecioBD(AP9,24,"QUANTITY ASK","N")} -> 10000 | AX9: {=_xll.PrecioBD(AP9,24,"VOLUME AMOUNT","N")} -> 95320 | AY9: {=_xll.PrecioBD(AP9,24,"IMBALANCE","N")} -> 0 | AZ9: Semestral | BA9: 1 | BB9: Sinkable
A10: Panel General | D10: ARS | E10: 31 | F10: =VLOOKUP(E10,Caucho!$E$66:$N$141,3,FALSE) -> #N/A | G10: =VLOOKUP(E10,Caucho!$E$66:$N$141,7,FALSE) -> #N/A | H10: =VLOOKUP(E10,Caucho!$E$66:$N$141,8,FALSE) -> #N/A | I10: =VLOOKUP(E10,Caucho!$E$66:$N$141,10,FALSE) -> #N/A | K10: ILF | L10: {=_xll.PrecioBD(K10,24,"IMBALANCE","N")} -> -0.0054 | P10: S29Y6 | Q10: {=INDIRECT("'" & P10 & "'!J6")} -> 0.027605885 | R10: {=INDIRECT("'" & P10& "'!B3")} -> 46171 | S10: {=_xll.PrecioBD(P10,24,"IMBALANCE","N")} -> 0.0045 | T10: {=INDIRECT("'" & Tabla11[[#This Row],[Ticker]]& "'!J5")} -> 0.34232156 | U10: =Tabla11[[#This Row],[Vencimiento]]-$D$1 -> 103 | V10: {=_xll.PrecioBD(Tabla11[[#This Row],[Ticker]],"24","BID","N")} -> 120.534 | W10: {=_xll.PrecioBD(Tabla11[[#This Row],[Ticker]],"24","ASK","N")} -> 120.6 | X10: {=_xll.PrecioBD(Tabla11[[#This Row],[Ticker]],24,"QUANTITY BID","N")} -> 27325 | Y10: {=_xll.PrecioBD(Tabla11[[#This Row],[Ticker]],24,"QUANTITY ASK","N")} -> 2007190865 | Z10: {=_xll.PrecioBD(Tabla11[[#This Row],[Ticker]],24,"VOLUME AMOUNT","N")} -> 3.5023139e+09 | AA10: =Tabla11[[#This Row],[TNA]]/365*Tabla11[[#This Row],[Días a vencimiento]] -> 0.096600332 | AB10: =$I$15*(1+Tabla11[[#This Row],[TNA]]/365*Tabla11[[#This Row],[Días a vencimiento]]) -> 1577.5692 | AE10: GD35D | AF10: {=INDIRECT("'" & Tabla9[[#This Row],[Ticker]] & "'!K4")} -> 0.087667724 | AG10: {=INDIRECT("'" & Tabla9[[#This Row],[Ticker]] & "'!K3")} -> 5.6843481 | AH10: {=_xll.PrecioBD(Tabla9[[#This Row],[Ticker]],"24","BID","N")} -> 80.31 | AI10: {=_xll.PrecioBD(Tabla9[[#This Row],[Ticker]],"24","ASK","N")} -> 80.37 | AJ10: {=_xll.PrecioBD(Tabla9[[#This Row],[Ticker]],24,"QUANTITY BID","N")} -> 137 | AK10: {=_xll.PrecioBD(Tabla9[[#This Row],[Ticker]],24,"QUANTITY ASK","N")} -> 3508 | AL10: {=_xll.PrecioBD(Tabla9[[#This Row],[Ticker]],24,"VOLUME AMOUNT","N")} -> 830868.13 | AM10: {=_xll.PrecioBD(Tabla9[[#This Row],[Ticker]],24,"IMBALANCE","N")} -> 0.0002 | AP10: YM34D | AQ10: {=INDIRECT("'" & AP10 & "'!K4")} -> 0.072391567 | AR10: {=INDIRECT("'" & AP10 & "'!K3")} -> 5.2896143 | AS10: 48961 | AT10: {=_xll.PrecioBD(AP10,"24","BID","N")} -> 106.8 | AU10: {=_xll.PrecioBD(AP10,"24","ASK","N")} -> 106.85 | AV10: {=_xll.PrecioBD(AP10,24,"QUANTITY BID","N")} -> 259 | AW10: {=_xll.PrecioBD(AP10,24,"QUANTITY ASK","N")} -> 5249 | AX10: {=_xll.PrecioBD(AP10,24,"VOLUME AMOUNT","N")} -> 337639.59 | AY10: {=_xll.PrecioBD(AP10,24,"IMBALANCE","N")} -> 0.0009 | AZ10: Semestral | BA10: 100 | BB10: Sinkable
A11: Factor Alfa | K11: VEA | L11: {=_xll.PrecioBD(K11,24,"IMBALANCE","N")} -> -0.0068 | P11: T30J6 | Q11: {=INDIRECT("'" & P11 & "'!J6")} -> 0.02750658 | R11: {=INDIRECT("'" & P11& "'!B3")} -> 46203 | S11: {=_xll.PrecioBD(P11,24,"IMBALANCE","N")} -> 0.005 | T11: {=INDIRECT("'" & Tabla11[[#This Row],[Ticker]]& "'!J5")} -> 0.3460404 | U11: =Tabla11[[#This Row],[Vencimiento]]-$D$1 -> 135 | V11: {=_xll.PrecioBD(Tabla11[[#This Row],[Ticker]],"24","BID","N")} -> 128.4 | W11: {=_xll.PrecioBD(Tabla11[[#This Row],[Ticker]],"24","ASK","N")} -> 128.45 | X11: {=_xll.PrecioBD(Tabla11[[#This Row],[Ticker]],24,"QUANTITY BID","N")} -> 476694981 | Y11: {=_xll.PrecioBD(Tabla11[[#This Row],[Ticker]],24,"QUANTITY ASK","N")} -> 8857601 | Z11: {=_xll.PrecioBD(Tabla11[[#This Row],[Ticker]],24,"VOLUME AMOUNT","N")} -> 4.0167256e+09 | AA11: =Tabla11[[#This Row],[TNA]]/365*Tabla11[[#This Row],[Días a vencimiento]] -> 0.12798754 | AB11: =$I$15*(1+Tabla11[[#This Row],[TNA]]/365*Tabla11[[#This Row],[Días a vencimiento]]) -> 1622.7229 | AE11: GD38D | AF11: {=INDIRECT("'" & Tabla9[[#This Row],[Ticker]] & "'!K4")} -> 0.086429152 | AG11: {=INDIRECT("'" & Tabla9[[#This Row],[Ticker]] & "'!K3")} -> 4.9862373 | AH11: {=_xll.PrecioBD(Tabla9[[#This Row],[Ticker]],"24","BID","N")} -> 83.81 | AI11: {=_xll.PrecioBD(Tabla9[[#This Row],[Ticker]],"24","ASK","N")} -> 83.95 | AJ11: {=_xll.PrecioBD(Tabla9[[#This Row],[Ticker]],24,"QUANTITY BID","N")} -> 186 | AK11: {=_xll.PrecioBD(Tabla9[[#This Row],[Ticker]],24,"QUANTITY ASK","N")} -> 1924 | AL11: {=_xll.PrecioBD(Tabla9[[#This Row],[Ticker]],24,"VOLUME AMOUNT","N")} -> 60922.11 | AM11: {=_xll.PrecioBD(Tabla9[[#This Row],[Ticker]],24,"IMBALANCE","N")} -> -0.0001 | AP11: TSC4D | AQ11: {=INDIRECT("'" & AP11 & "'!K4")} -> 0.072250578 | AR11: {=INDIRECT("'" & AP11 & "'!K3")} -> 2.0743719 | AS11: 49633 | AT11: {=_xll.PrecioBD(AP11,"24","BID","N")} -> 106.3 | AU11: {=_xll.PrecioBD(AP11,"24","ASK","N")} -> 106.4 | AV11: {=_xll.PrecioBD(AP11,24,"QUANTITY BID","N")} -> 9000 | AW11: {=_xll.PrecioBD(AP11,24,"QUANTITY ASK","N")} -> 11000 | AX11: {=_xll.PrecioBD(AP11,24,"VOLUME AMOUNT","N")} -> 73414 | AY11: {=_xll.PrecioBD(AP11,24,"IMBALANCE","N")} -> -0.0028 | AZ11: Semestral | BA11: 100 | BB11: Sinkable
C12: {=_xll.TiposCambioBD()} -> TIPO CAMBIO | D12: VENCIMIENTO | E12: ESPECIE | F12: SIMBOLO | G12: COMPRA | H12: VENTA | I12: ULTIMO | K12: Factor Alfa | L12: =Tabla68[[#Totals],[Columna2]] -> -0.007959 | P12: S31L6 | Q12: {=INDIRECT("'" & P12 & "'!J6")} -> 0.027560332 | R12: {=INDIRECT("'" & P12& "'!B3")} -> 46234 | S12: {=_xll.PrecioBD(P12,24,"IMBALANCE","N")} -> 0.0044 | T12: {=INDIRECT("'" & Tabla11[[#This Row],[Ticker]]& "'!J5")} -> 0.35169518 | U12: =Tabla11[[#This Row],[Vencimiento]]-$D$1 -> 166 | V12: {=_xll.PrecioBD(Tabla11[[#This Row],[Ticker]],"24","BID","N")} -> 101.449 | W12: {=_xll.PrecioBD(Tabla11[[#This Row],[Ticker]],"24","ASK","N")} -> 101.45 | X12: {=_xll.PrecioBD(Tabla11[[#This Row],[Ticker]],24,"QUANTITY BID","N")} -> 2107027 | Y12: {=_xll.PrecioBD(Tabla11[[#This Row],[Ticker]],24,"QUANTITY ASK","N")} -> 79925697 | Z12: {=_xll.PrecioBD(Tabla11[[#This Row],[Ticker]],24,"VOLUME AMOUNT","N")} -> 5.3673613e+09 | AA12: =Tabla11[[#This Row],[TNA]]/365*Tabla11[[#This Row],[Días a vencimiento]] -> 0.15994904 | AB12: =$I$15*(1+Tabla11[[#This Row],[TNA]]/365*Tabla11[[#This Row],[Días a vencimiento]]) -> 1668.7027 | AE12: AL29D | AF12: {=INDIRECT("'" & Tabla9[[#This Row],[Ticker]] & "'!K4")} -> 0.069797418 | AG12: {=INDIRECT("'" & Tabla9[[#This Row],[Ticker]] & "'!K3")} -> 1.763296 | AH12: {=_xll.PrecioBD(Tabla9[[#This Row],[Ticker]],"24","BID","N")} -> 62.95 | AI12: {=_xll.PrecioBD(Tabla9[[#This Row],[Ticker]],"24","ASK","N")} -> 62.99 | AJ12: {=_xll.PrecioBD(Tabla9[[#This Row],[Ticker]],24,"QUANTITY BID","N")} -> 3186 | AK12: {=_xll.PrecioBD(Tabla9[[#This Row],[Ticker]],24,"QUANTITY ASK","N")} -> 23053 | AL12: {=_xll.PrecioBD(Tabla9[[#This Row],[Ticker]],24,"VOLUME AMOUNT","N")} -> 326258.52 | AM12: {=_xll.PrecioBD(Tabla9[[#This Row],[Ticker]],24,"IMBALANCE","N")} -> 0.0035 | AP12: IRCPD | AQ12: {=INDIRECT("'" & AP12 & "'!K4")} -> 0.072679135 | AR12: {=INDIRECT("'" & AP12 & "'!K3")} -> 5.8033839 | AS12: 49399 | AT12: {=_xll.PrecioBD(AP12,"24","BID","N")} -> 108.05 | AU12: {=_xll.PrecioBD(AP12,"24","ASK","N")} -> 108.2 | AV12: {=_xll.PrecioBD(AP12,24,"QUANTITY BID","N")} -> 4865 | AW12: {=_xll.PrecioBD(AP12,24,"QUANTITY ASK","N")} -> 3931 | AX12: {=_xll.PrecioBD(AP12,24,"VOLUME AMOUNT","N")} -> 88043.04 | AY12: {=_xll.PrecioBD(AP12,24,"IMBALANCE","N")} -> -0.0009 | AZ12: Semestral | BA12: 10000 | BB12: Bullet
K13: IEMG | L13: {=_xll.PrecioBD(K13,24,"IMBALANCE","N")} -> -0.0075 | P13: S31G6 | Q13: {=INDIRECT("'" & P13 & "'!J6")} -> 0.02832805 | R13: {=INDIRECT("'" & P13& "'!B3")} -> 46265 | S13: {=_xll.PrecioBD(P13,24,"IMBALANCE","N")} -> 0 | T13: {=INDIRECT("'" & Tabla11[[#This Row],[Ticker]]& "'!J5")} -> 0.36744879 | U13: =Tabla11[[#This Row],[Vencimiento]]-$D$1 -> 197 | V13: {=_xll.PrecioBD(Tabla11[[#This Row],[Ticker]],"24","BID","N")} -> 107.056 | W13: {=_xll.PrecioBD(Tabla11[[#This Row],[Ticker]],"24","ASK","N")} -> 107.25 | X13: {=_xll.PrecioBD(Tabla11[[#This Row],[Ticker]],24,"QUANTITY BID","N")} -> 3569286 | Y13: {=_xll.PrecioBD(Tabla11[[#This Row],[Ticker]],24,"QUANTITY ASK","N")} -> 4610951 | Z13: {=_xll.PrecioBD(Tabla11[[#This Row],[Ticker]],24,"VOLUME AMOUNT","N")} -> 43791501 | AA13: =Tabla11[[#This Row],[TNA]]/365*Tabla11[[#This Row],[Días a vencimiento]] -> 0.19832168 | AB13: =$I$15*(1+Tabla11[[#This Row],[TNA]]/365*Tabla11[[#This Row],[Días a vencimiento]]) -> 1723.9055 | AE13: GD30D | AF13: {=INDIRECT("'" & Tabla9[[#This Row],[Ticker]] & "'!K4")} -> 0.067136118 | AG13: {=INDIRECT("'" & Tabla9[[#This Row],[Ticker]] & "'!K3")} -> 2.2121439 | AH13: {=_xll.PrecioBD(Tabla9[[#This Row],[Ticker]],"24","BID","N")} -> 63.69 | AI13: {=_xll.PrecioBD(Tabla9[[#This Row],[Ticker]],"24","ASK","N")} -> 63.73 | AJ13: {=_xll.PrecioBD(Tabla9[[#This Row],[Ticker]],24,"QUANTITY BID","N")} -> 7690 | AK13: {=_xll.PrecioBD(Tabla9[[#This Row],[Ticker]],24,"QUANTITY ASK","N")} -> 20079 | AL13: {=_xll.PrecioBD(Tabla9[[#This Row],[Ticker]],24,"VOLUME AMOUNT","N")} -> 440541.78 | AM13: {=_xll.PrecioBD(Tabla9[[#This Row],[Ticker]],24,"IMBALANCE","N")} -> 0.0028 | AP13: MGCOD | AQ13: {=INDIRECT("'" & AP13 & "'!K4")} -> 0.071567294 | AR13: {=INDIRECT("'" & AP13 & "'!K3")} -> 6.3016378 | AS13: 49294 | AT13: {=_xll.PrecioBD(AP13,"24","BID","N")} -> 106.25 | AU13: {=_xll.PrecioBD(AP13,"24","ASK","N")} -> 106.75 | AV13: {=_xll.PrecioBD(AP13,24,"QUANTITY BID","N")} -> 10000 | AW13: {=_xll.PrecioBD(AP13,24,"QUANTITY ASK","N")} -> 10000 | AX13: {=_xll.PrecioBD(AP13,24,"VOLUME AMOUNT","N")} -> 510315 | AY13: {=_xll.PrecioBD(AP13,24,"IMBALANCE","N")} -> -0.0004 | AZ13: Semestral | BA13: 1000 | BB13: Bullet
D14: 2026-02-09 | E14: GD30/GD30C | F14: GD30/GD30C (CI) | G14: 1477.9 | H14: 1480 | I14: 1478.8 | K14: XLE | L14: {=_xll.PrecioBD(K14,24,"IMBALANCE","N")} -> -0.0078 | P14: S30O6 | Q14: {=INDIRECT("'" & P14 & "'!J6")} -> 0.026089853 | R14: {=INDIRECT("'" & P14& "'!B3")} -> 46325 | S14: {=_xll.PrecioBD(P14,24,"IMBALANCE","N")} -> 0.0048 | T14: {=INDIRECT("'" & Tabla11[[#This Row],[Ticker]]& "'!J5")} -> 0.34527031 | U14: =Tabla11[[#This Row],[Vencimiento]]-$D$1 -> 257 | V14: {=_xll.PrecioBD(Tabla11[[#This Row],[Ticker]],"24","BID","N")} -> 108.558 | W14: {=_xll.PrecioBD(Tabla11[[#This Row],[Ticker]],"24","ASK","N")} -> 108.824 | X14: {=_xll.PrecioBD(Tabla11[[#This Row],[Ticker]],24,"QUANTITY BID","N")} -> 324899 | Y14: {=_xll.PrecioBD(Tabla11[[#This Row],[Ticker]],24,"QUANTITY ASK","N")} -> 5000000 | Z14: {=_xll.PrecioBD(Tabla11[[#This Row],[Ticker]],24,"VOLUME AMOUNT","N")} -> 24525398 | AA14: =Tabla11[[#This Row],[TNA]]/365*Tabla11[[#This Row],[Días a vencimiento]] -> 0.24310814 | AB14: =$I$15*(1+Tabla11[[#This Row],[TNA]]/365*Tabla11[[#This Row],[Días a vencimiento]]) -> 1788.3353 | AE14: GD29D | AF14: {=INDIRECT("'" & Tabla9[[#This Row],[Ticker]] & "'!K4")} -> 0.05488334 | AG14: {=INDIRECT("'" & Tabla9[[#This Row],[Ticker]] & "'!K3")} -> 1.7893463 | AH14: {=_xll.PrecioBD(Tabla9[[#This Row],[Ticker]],"24","BID","N")} -> 64.51 | AI14: {=_xll.PrecioBD(Tabla9[[#This Row],[Ticker]],"24","ASK","N")} -> 64.63 | AJ14: {=_xll.PrecioBD(Tabla9[[#This Row],[Ticker]],24,"QUANTITY BID","N")} -> 468 | AK14: {=_xll.PrecioBD(Tabla9[[#This Row],[Ticker]],24,"QUANTITY ASK","N")} -> 3934 | AL14: {=_xll.PrecioBD(Tabla9[[#This Row],[Ticker]],24,"VOLUME AMOUNT","N")} -> 36642.35 | AM14: {=_xll.PrecioBD(Tabla9[[#This Row],[Ticker]],24,"IMBALANCE","N")} -> 0.0068 | AP14: VSCVD | AQ14: {=INDIRECT("'" & AP14 & "'!K4")} -> 0.071171436 | AR14: {=INDIRECT("'" & AP14 & "'!K3")} -> 4.8284439 | AS14: 48740 | AT14: {=_xll.PrecioBD(AP14,"24","BID","N")} -> 108.85 | AU14: {=_xll.PrecioBD(AP14,"24","ASK","N")} -> 109.1 | AV14: {=_xll.PrecioBD(AP14,24,"QUANTITY BID","N")} -> 2000 | AW14: {=_xll.PrecioBD(AP14,24,"QUANTITY ASK","N")} -> 31000 | AX14: {=_xll.PrecioBD(AP14,24,"VOLUME AMOUNT","N")} -> 311679 | AY14: {=_xll.PrecioBD(AP14,24,"IMBALANCE","N")} -> 0.0022 | AZ14: Semestral | BA14: 1000 | BB14: Bullet
D15: 2026-02-09 | E15: GD30/GD30D | F15: GD30/GD30D (CI) | G15: 1437.2 | H15: 1440 | I15: 1438.6 | K15: MEP | L15: =$D$20 -> -0.009377494 | P15: S30N6 | Q15: {=INDIRECT("'" & P15 & "'!J6")} -> 0.026730211 | R15: {=INDIRECT("'" & P15& "'!B3")} -> 46356 | S15: {=_xll.PrecioBD(P15,24,"IMBALANCE","N")} -> 0.0028 | T15: {=INDIRECT("'" & Tabla11[[#This Row],[Ticker]]& "'!J5")} -> 0.3595906 | U15: =Tabla11[[#This Row],[Vencimiento]]-$D$1 -> 288 | V15: {=_xll.PrecioBD(Tabla11[[#This Row],[Ticker]],"24","BID","N")} -> 101.27 | W15: {=_xll.PrecioBD(Tabla11[[#This Row],[Ticker]],"24","ASK","N")} -> 101.314 | X15: {=_xll.PrecioBD(Tabla11[[#This Row],[Ticker]],24,"QUANTITY BID","N")} -> 5000000 | Y15: {=_xll.PrecioBD(Tabla11[[#This Row],[Ticker]],24,"QUANTITY ASK","N")} -> 5000000 | Z15: {=_xll.PrecioBD(Tabla11[[#This Row],[Ticker]],24,"VOLUME AMOUNT","N")} -> 3.5053028e+08 | AA15: =Tabla11[[#This Row],[TNA]]/365*Tabla11[[#This Row],[Días a vencimiento]] -> 0.28373176 | AB15: =$I$15*(1+Tabla11[[#This Row],[TNA]]/365*Tabla11[[#This Row],[Días a vencimiento]]) -> 1846.7765 | AP15: PLC5D | AQ15: {=INDIRECT("'" & AP15 & "'!K4")} -> 0.069972578 | AR15: {=INDIRECT("'" & AP15 & "'!K3")} -> 4.186849 | AS15: 47987 | AT15: {=_xll.PrecioBD(AP15,"24","BID","N")} -> 107.25 | AU15: {=_xll.PrecioBD(AP15,"24","ASK","N")} -> 107.35 | AV15: {=_xll.PrecioBD(AP15,24,"QUANTITY BID","N")} -> 20000 | AW15: {=_xll.PrecioBD(AP15,24,"QUANTITY ASK","N")} -> 20000 | AX15: {=_xll.PrecioBD(AP15,24,"VOLUME AMOUNT","N")} -> 121221 | AY15: {=_xll.PrecioBD(AP15,24,"IMBALANCE","N")} -> 0.0004 | AZ15: Semestral | BA15: 1 | BB15: Sinkable
D16: 2026-02-09 | E16: MAE | F16: Dolar Mayorista Bancos - Argentina | G16: 1423 | H16: 1432 | I16: 1432 | K16: SPY | L16: {=_xll.PrecioBD(K16,24,"IMBALANCE","N")} -> -0.0107 | P16: T15E7 | Q16: {=INDIRECT("'" & P16 & "'!J6")} -> 0.027068654 | R16: {=INDIRECT("'" & P16& "'!B3")} -> 46402 | S16: {=_xll.PrecioBD(P16,24,"IMBALANCE","N")} -> 0.002 | T16: {=INDIRECT("'" & Tabla11[[#This Row],[Ticker]]& "'!J5")} -> 0.37245733 | U16: =Tabla11[[#This Row],[Vencimiento]]-$D$1 -> 334 | V16: {=_xll.PrecioBD(Tabla11[[#This Row],[Ticker]],"24","BID","N")} -> 120.1 | W16: {=_xll.PrecioBD(Tabla11[[#This Row],[Ticker]],"24","ASK","N")} -> 120.15 | X16: {=_xll.PrecioBD(Tabla11[[#This Row],[Ticker]],24,"QUANTITY BID","N")} -> 50769775 | Y16: {=_xll.PrecioBD(Tabla11[[#This Row],[Ticker]],24,"QUANTITY ASK","N")} -> 15000000 | Z16: {=_xll.PrecioBD(Tabla11[[#This Row],[Ticker]],24,"VOLUME AMOUNT","N")} -> 6.8889e+09 | AA16: =Tabla11[[#This Row],[TNA]]/365*Tabla11[[#This Row],[Días a vencimiento]] -> 0.34082397 | AB16: =$I$15*(1+Tabla11[[#This Row],[TNA]]/365*Tabla11[[#This Row],[Días a vencimiento]]) -> 1928.9093 | AE16: Spread | AF16: Delta | AP16: PLC4D | AQ16: {=INDIRECT("'" & AP16 & "'!K4")} -> 0.073068348 | AR16: {=INDIRECT("'" & AP16 & "'!K3")} -> 4.7958835 | AS16: 48364 | AT16: {=_xll.PrecioBD(AP16,"24","BID","N")} -> 108.1 | AU16: {=_xll.PrecioBD(AP16,"24","ASK","N")} -> 108.35 | AV16: {=_xll.PrecioBD(AP16,24,"QUANTITY BID","N")} -> 4000 | AW16: {=_xll.PrecioBD(AP16,24,"QUANTITY ASK","N")} -> 48000 | AX16: {=_xll.PrecioBD(AP16,24,"VOLUME AMOUNT","N")} -> 121382.5 | AY16: {=_xll.PrecioBD(AP16,24,"IMBALANCE","N")} -> 0 | AZ16: Semestral | BA16: 0 | BB16: 0
D17: 2026-02-09 | E17: USB | F17: Dolar Banco Nacion Billete - Argentina | G17: 1395 | H17: 1445 | I17: 1445 | K17: IBIT | L17: {=_xll.PrecioBD(K17,24,"IMBALANCE","N")} -> -0.0114 | P17: T30A7 | Q17: {=INDIRECT("'" & P17 & "'!J6")} -> 0.027111167 | R17: {=INDIRECT("'" & P17& "'!B3")} -> 46507 | S17: {=_xll.PrecioBD(P17,24,"IMBALANCE","N")} -> 0 | T17: {=INDIRECT("'" & Tabla11[[#This Row],[Ticker]]& "'!J5")} -> 0.39177649 | U17: =Tabla11[[#This Row],[Vencimiento]]-$D$1 -> 439 | V17: {=_xll.PrecioBD(Tabla11[[#This Row],[Ticker]],"24","BID","N")} -> 108.65 | W17: {=_xll.PrecioBD(Tabla11[[#This Row],[Ticker]],"24","ASK","N")} -> 108.7 | X17: {=_xll.PrecioBD(Tabla11[[#This Row],[Ticker]],24,"QUANTITY BID","N")} -> 142099074 | Y17: {=_xll.PrecioBD(Tabla11[[#This Row],[Ticker]],24,"QUANTITY ASK","N")} -> 141132 | Z17: {=_xll.PrecioBD(Tabla11[[#This Row],[Ticker]],24,"VOLUME AMOUNT","N")} -> 9.7208279e+08 | AA17: =Tabla11[[#This Row],[TNA]]/365*Tabla11[[#This Row],[Días a vencimiento]] -> 0.47120515 | AB17: =$I$15*(1+Tabla11[[#This Row],[TNA]]/365*Tabla11[[#This Row],[Días a vencimiento]]) -> 2116.4757 | AE17: AL29/GD29 | AF17: {=_xll.PrecioBD("GD29D",24,"ASK","N")/_xll.PrecioBD("AL29D",24,"ASK","N")-1} -> 0.026035879 | AP17: VSCTD | AQ17: {=INDIRECT("'" & AP17 & "'!K4")} -> 0.070167872 | AR17: {=INDIRECT("'" & AP17 & "'!K3")} -> 6.3325003 | AS17: 49653 | AT17: {=_xll.PrecioBD(AP17,"24","BID","N")} -> 106 | AU17: {=_xll.PrecioBD(AP17,"24","ASK","N")} -> 106.05 | AV17: {=_xll.PrecioBD(AP17,24,"QUANTITY BID","N")} -> 30000 | AW17: {=_xll.PrecioBD(AP17,24,"QUANTITY ASK","N")} -> 75000 | AX17: {=_xll.PrecioBD(AP17,24,"VOLUME AMOUNT","N")} -> 31830 | AY17: {=_xll.PrecioBD(AP17,24,"IMBALANCE","N")} -> -0.0004 | AZ17: Semestral | BA17: 10000 | BB17: Bullet
D18: 2026-02-09 | E18: USD | F18: Dolar x Peso Argentino BNA | G18: 1423 | H18: 1432 | I18: 1432 | K18: URA | L18: {=_xll.PrecioBD(K18,24,"IMBALANCE","N")} -> -0.0145 | P18: T31Y7 | Q18: {=INDIRECT("'" & P18 & "'!J6")} -> 0.025395019 | R18: {=INDIRECT("'" & P18& "'!B3")} -> 46538 | S18: {=_xll.PrecioBD(P18,24,"IMBALANCE","N")} -> 0.0024 | T18: {=INDIRECT("'" & Tabla11[[#This Row],[Ticker]]& "'!J5")} -> 0.36756352 | U18: =Tabla11[[#This Row],[Vencimiento]]-$D$1 -> 470 | V18: {=_xll.PrecioBD(Tabla11[[#This Row],[Ticker]],"24","BID","N")} -> 102.95 | W18: {=_xll.PrecioBD(Tabla11[[#This Row],[Ticker]],"24","ASK","N")} -> 103 | X18: {=_xll.PrecioBD(Tabla11[[#This Row],[Ticker]],24,"QUANTITY BID","N")} -> 401063 | Y18: {=_xll.PrecioBD(Tabla11[[#This Row],[Ticker]],24,"QUANTITY ASK","N")} -> 610108 | Z18: {=_xll.PrecioBD(Tabla11[[#This Row],[Ticker]],24,"VOLUME AMOUNT","N")} -> 2.4139405e+08 | AA18: =Tabla11[[#This Row],[TNA]]/365*Tabla11[[#This Row],[Días a vencimiento]] -> 0.47330097 | AB18: =$I$15*(1+Tabla11[[#This Row],[TNA]]/365*Tabla11[[#This Row],[Días a vencimiento]]) -> 2119.4907 | AE18: AL30/GD30 | AF18: {=_xll.PrecioBD("GD30D",24,"ASK","N")/_xll.PrecioBD("AL30D",24,"ASK","N")-1} -> 0.025092488 | AP18: YMCXD | AQ18: {=INDIRECT("'" & AP18 & "'!K4")} -> 0.070133516 | AR18: {=INDIRECT("'" & AP18 & "'!K3")} -> 3.8873354 | AS18: 48102 | AT18: {=_xll.PrecioBD(AP18,"24","BID","N")} -> 111.35 | AU18: {=_xll.PrecioBD(AP18,"24","ASK","N")} -> 111.45 | AV18: {=_xll.PrecioBD(AP18,24,"QUANTITY BID","N")} -> 1048 | AW18: {=_xll.PrecioBD(AP18,24,"QUANTITY ASK","N")} -> 11028 | AX18: {=_xll.PrecioBD(AP18,24,"VOLUME AMOUNT","N")} -> 278428.4 | AY18: {=_xll.PrecioBD(AP18,24,"IMBALANCE","N")} -> -0.0022 | AZ18: Semestral | BA18: 1 | BB18: Sinkable
D19: MEP | E19: CCL | F19: MEP/Oficial | K19: GLD | L19: {=_xll.PrecioBD(K19,24,"IMBALANCE","N")} -> -0.0115 | P19: T30J7 | Q19: {=INDIRECT("'" & P19 & "'!J6")} -> 0.020262212 | R19: {=INDIRECT("'" & P19& "'!B3")} -> 46568 | S19: {=_xll.PrecioBD(P19,24,"IMBALANCE","N")} -> 0.0009 | T19: {=INDIRECT("'" & Tabla11[[#This Row],[Ticker]]& "'!J5")} -> 0.28515079 | U19: =Tabla11[[#This Row],[Vencimiento]]-$D$1 -> 500 | V19: {=_xll.PrecioBD(Tabla11[[#This Row],[Ticker]],"24","BID","N")} -> 103.4 | W19: {=_xll.PrecioBD(Tabla11[[#This Row],[Ticker]],"24","ASK","N")} -> 104.45 | X19: {=_xll.PrecioBD(Tabla11[[#This Row],[Ticker]],24,"QUANTITY BID","N")} -> 84662 | Y19: {=_xll.PrecioBD(Tabla11[[#This Row],[Ticker]],24,"QUANTITY ASK","N")} -> 948843 | Z19: {=_xll.PrecioBD(Tabla11[[#This Row],[Ticker]],24,"VOLUME AMOUNT","N")} -> 2.6572571e+08 | AA19: =Tabla11[[#This Row],[TNA]]/365*Tabla11[[#This Row],[Días a vencimiento]] -> 0.39061752 | AB19: =$I$15*(1+Tabla11[[#This Row],[TNA]]/365*Tabla11[[#This Row],[Días a vencimiento]]) -> 2000.5423 | AE19: AL35/GD35 | AF19: {=_xll.PrecioBD("GD35D",24,"ASK","N")/_xll.PrecioBD("AL35D",24,"ASK","N")-1} -> 0.01953571 | AP19: YFCJD | AQ19: {=INDIRECT("'" & AP19 & "'!K4")} -> 0.069892356 | AR19: {=INDIRECT("'" & AP19 & "'!K3")} -> 4.4359847 | AS19: 48503 | AT19: {=_xll.PrecioBD(AP19,"24","BID","N")} -> 106.9 | AU19: {=_xll.PrecioBD(AP19,"24","ASK","N")} -> 107.25 | AV19: {=_xll.PrecioBD(AP19,24,"QUANTITY BID","N")} -> 1000 | AW19: {=_xll.PrecioBD(AP19,24,"QUANTITY ASK","N")} -> 5000 | AX19: {=_xll.PrecioBD(AP19,24,"VOLUME AMOUNT","N")} -> 14959.5 | AY19: {=_xll.PrecioBD(AP19,24,"IMBALANCE","N")} -> 0 | AZ19: Semestral | BA19: 1000 | BB19: Sinkable
D20: {=(1+_xll.PrecioBD("AL30","CI","IMBALANCE","N"))/(1+_xll.PrecioBD("AL30D","CI","IMBALANCE","N"))-1} -> -0.009377494 | E20: {=(1+_xll.PrecioBD("AL30","CI","IMBALANCE","N"))/(1+_xll.PrecioBD("AL30C","CI","IMBALANCE","N"))-1} -> -0.0073970412 | F20: =I15/I18-1 -> 0.0046089215 | K20: IWM | L20: {=_xll.PrecioBD(K20,24,"IMBALANCE","N")} -> -0.0153 | AE20: AE38/GD38 | AF20: {=_xll.PrecioBD("GD38D",24,"ASK","N")/_xll.PrecioBD("AE38D",24,"ASK","N")-1} -> 0.030314188 | AP20: GN49D | AQ20: {=INDIRECT("'" & AP20 & "'!K4")} -> 0.070659539 | AR20: {=INDIRECT("'" & AP20 & "'!K3")} -> 5.1788799 | AS20: 48915 | AT20: {=_xll.PrecioBD(AP20,"24","BID","N")} -> 104.9 | AU20: {=_xll.PrecioBD(AP20,"24","ASK","N")} -> 105.9 | AV20: {=_xll.PrecioBD(AP20,24,"QUANTITY BID","N")} -> 1000 | AW20: {=_xll.PrecioBD(AP20,24,"QUANTITY ASK","N")} -> 15000 | AX20: {=_xll.PrecioBD(AP20,24,"VOLUME AMOUNT","N")} -> 37930.5 | AY20: {=_xll.PrecioBD(AP20,24,"IMBALANCE","N")} -> 0.0057 | AZ20: Semestral | BA20: 1000 | BB20: Bullet
K21: COPX | L21: {=_xll.PrecioBD(K21,24,"IMBALANCE","N")} -> -0.0151 | P21: MEP | Q21: =W1 -> 1438.6 | AE21: AL41/GD41 | AF21: {=_xll.PrecioBD("GD41D",24,"ASK","N")/_xll.PrecioBD("AL41D",24,"ASK","N")-1} -> 0.013486177 | AP21: TLCMD | AQ21: {=INDIRECT("'" & AP21 & "'!K4")} -> 0.068281874 | AR21: {=INDIRECT("'" & AP21 & "'!K3")} -> 3.6058106 | AS21: 48047 | AT21: {=_xll.PrecioBD(AP21,"24","BID","N")} -> 111.05 | AU21: {=_xll.PrecioBD(AP21,"24","ASK","N")} -> 111.2 | AV21: {=_xll.PrecioBD(AP21,24,"QUANTITY BID","N")} -> 7000 | AW21: {=_xll.PrecioBD(AP21,24,"QUANTITY ASK","N")} -> 12000 | AX21: {=_xll.PrecioBD(AP21,24,"VOLUME AMOUNT","N")} -> 194210 | AY21: {=_xll.PrecioBD(AP21,24,"IMBALANCE","N")} -> -0.0035 | AZ21: Semestral | BA21: 1000 | BB21: Sinkable
D22: Plazo fijo | E22: Caucho - PF | F22: Lecap - PF | K22: Merval | L22: ='Indices BYMA'!H5 -> -0.0226 | Q22: Rendimiento en USD para los diferentes MEP | AP22: YMCJD | AQ22: {=INDIRECT("'" & AP22 & "'!K4")} -> 0.066920939 | AR22: {=INDIRECT("'" & AP22 & "'!K3")} -> 4.9308554 | AS22: 48852 | AT22: {=_xll.PrecioBD(AP22,"24","BID","N")} -> 104.6 | AU22: {=_xll.PrecioBD(AP22,"24","ASK","N")} -> 104.75 | AV22: {=_xll.PrecioBD(AP22,24,"QUANTITY BID","N")} -> 1083 | AW22: {=_xll.PrecioBD(AP22,24,"QUANTITY ASK","N")} -> 986 | AX22: {=_xll.PrecioBD(AP22,24,"VOLUME AMOUNT","N")} -> 198024.03 | AY22: {=_xll.PrecioBD(AP22,24,"IMBALANCE","N")} -> 0.0028 | AZ22: Semestral | BA22: 10000 | BB22: Bullet
D23: 0.25 | E23: =G8-D23 -> 0.048 | F23: =AVERAGE(T6:T19)-D23 -> 0.10393616 | K23: USO | L23: {=_xll.PrecioBD(K23,24,"IMBALANCE","N")} -> -0.0226 | Q23: Ticker | R23: 1450 | S23: 1500 | T23: 1550 | U23: 1600 | V23: 1650 | W23: 1700 | X23: 1750 | Y23: 1800 | Z23: 1850 | AP23: TTCDD | AQ23: {=INDIRECT("'" & AP23 & "'!K4")} -> 0.06647186 | AR23: {=INDIRECT("'" & AP23 & "'!K3")} -> 3.86195 | AS23: 47791 | AT23: {=_xll.PrecioBD(AP23,"24","BID","N")} -> 106.3 | AU23: {=_xll.PrecioBD(AP23,"24","ASK","N")} -> 106.45 | AV23: {=_xll.PrecioBD(AP23,24,"QUANTITY BID","N")} -> 33000 | AW23: {=_xll.PrecioBD(AP23,24,"QUANTITY ASK","N")} -> 1000 | AX23: {=_xll.PrecioBD(AP23,24,"VOLUME AMOUNT","N")} -> 117155.5 | AY23: {=_xll.PrecioBD(AP23,24,"IMBALANCE","N")} -> -0.0004 | AZ23: Semestral | BA23: 1 | BB23: Sinkable
D24: https://www.bcra.gob.ar/plazos-fijos-online/ | K24: SLV | L24: {=_xll.PrecioBD(K24,24,"IMBALANCE","N")} -> -0.0281 | AP24: TSC3D | AQ24: {=INDIRECT("'" & AP24 & "'!K4")} -> 0.065198669 | AR24: {=INDIRECT("'" & AP24 & "'!K3")} -> 4.3559699 | AS24: 48053 | AT24: {=_xll.PrecioBD(AP24,"24","BID","N")} -> 109.4 | AU24: {=_xll.PrecioBD(AP24,"24","ASK","N")} -> 109.95 | AV24: {=_xll.PrecioBD(AP24,24,"QUANTITY BID","N")} -> 10000 | AW24: {=_xll.PrecioBD(AP24,24,"QUANTITY ASK","N")} -> 10000 | AX24: {=_xll.PrecioBD(AP24,24,"VOLUME AMOUNT","N")} -> 10920 | AY24: {=_xll.PrecioBD(AP24,24,"IMBALANCE","N")} -> -0.0022 | AZ24: Semestral | BA24: 1000 | BB24: Bullet
Q25: S27F6 | R25: =AB6/$R$23-1 -> 0.0042683005 | S25: =AB6/$S$23-1 -> -0.029207309 | T25: =AB6/$T$23-1 -> -0.060523203 | U25: =AB6/$U$23-1 -> -0.089881853 | V25: =AB6/$V$23-1 -> -0.11746119 | W25: =AB6/$W$23-1 -> -0.14341821 | X25: =AB6/$X$23-1 -> -0.16789198 | Y25: =AB6/$Y$23-1 -> -0.19100609 | Z25: =AB6/$Z$23-1 -> -0.21287079 | AP25: MGCMD | AQ25: {=INDIRECT("'" & AP25 & "'!K4")} -> 0.064246032 | AR25: {=INDIRECT("'" & AP25 & "'!K3")} -> 4.365162 | AS25: 48101 | AT25: {=_xll.PrecioBD(AP25,"24","BID","N")} -> 110.6 | AU25: {=_xll.PrecioBD(AP25,"24","ASK","N")} -> 111 | AV25: {=_xll.PrecioBD(AP25,24,"QUANTITY BID","N")} -> 10000 | AW25: {=_xll.PrecioBD(AP25,24,"QUANTITY ASK","N")} -> 10000 | AX25: {=_xll.PrecioBD(AP25,24,"VOLUME AMOUNT","N")} -> 0 | AY25: {=_xll.PrecioBD(AP25,24,"IMBALANCE","N")} -> 0 | AZ25: Semestral | BA25: 1000 | BB25: Sinkable
C26: CEDEARs | D26: Ticker | E26: Precio | F26: Total volume | G26: Variación | I26: Panel Lider | J26: Ticker | K26: Precio | L26: Total volume | M26: Variación | Q26: S16M6 | R26: =AB7/$R$23-1 -> 0.020233048 | S26: =AB7/$S$23-1 -> -0.01377472 | T26: =AB7/$T$23-1 -> -0.045588439 | U26: =AB7/$U$23-1 -> -0.0754138 | V26: =AB7/$V$23-1 -> -0.10343156 | W26: =AB7/$W$23-1 -> -0.12980122 | X26: =AB7/$X$23-1 -> -0.15466405 | Y26: =AB7/$Y$23-1 -> -0.1781456 | Z26: =AB7/$Z$23-1 -> -0.20035788 | AP26: TTCAD | AQ26: {=INDIRECT("'" & AP26 & "'!K4")} -> 0.063613895 | AR26: {=INDIRECT("'" & AP26 & "'!K3")} -> 4.7503804 | AS26: 48601 | AT26: {=_xll.PrecioBD(AP26,"24","BID","N")} -> 106 | AU26: {=_xll.PrecioBD(AP26,"24","ASK","N")} -> 107.1 | AV26: {=_xll.PrecioBD(AP26,24,"QUANTITY BID","N")} -> 10000 | AW26: {=_xll.PrecioBD(AP26,24,"QUANTITY ASK","N")} -> 16000 | AX26: {=_xll.PrecioBD(AP26,24,"VOLUME AMOUNT","N")} -> 0 | AY26: {=_xll.PrecioBD(AP26,24,"IMBALANCE","N")} -> 0 | AZ26: Semestral | BA26: 1000 | BB26: Sinkable
D27: MU | E27: {=_xll.PrecioBD(D27,24,"ASK","N")} -> 123650 | F27: {=_xll.PrecioBD(D27,24,"VOLUME AMOUNT","N")} -> 8568427575 | G27: {=_xll.PrecioBD(D27,24,"IMBALANCE","N")} -> 0.0189 | J27: TGNO4 | K27: {=_xll.PrecioBD(J27,24,"ASK","N")} -> 4545 | L27: {=_xll.PrecioBD(J27,24,"VOLUME AMOUNT","N")} -> 2.6566524e+08 | M27: {=_xll.PrecioBD(J27,24,"IMBALANCE","N")} -> 0.0022 | Q27: S17A6 | R27: =AB8/$R$23-1 -> 0.051627993 | S27: =AB8/$S$23-1 -> 0.016573727 | T27: =AB8/$T$23-1 -> -0.016218974 | U27: =AB8/$U$23-1 -> -0.046962131 | V27: =AB8/$V$23-1 -> -0.075842067 | W27: =AB8/$W$23-1 -> -0.10302318 | X27: =AB8/$X$23-1 -> -0.12865109 | Y27: =AB8/$Y$23-1 -> -0.15285523 | Z27: =AB8/$Z$23-1 -> -0.17575103 | AP27: PNXCD | AQ27: {=INDIRECT("'" & AP27 & "'!K4")} -> 0.062183937 | AR27: {=INDIRECT("'" & AP27 & "'!K3")} -> 4.134957 | AS27: 48334 | AT27: {=_xll.PrecioBD(AP27,"24","BID","N")} -> 112.35 | AU27: {=_xll.PrecioBD(AP27,"24","ASK","N")} -> 112.9 | AV27: {=_xll.PrecioBD(AP27,24,"QUANTITY BID","N")} -> 1000 | AW27: {=_xll.PrecioBD(AP27,24,"QUANTITY ASK","N")} -> 7000 | AX27: {=_xll.PrecioBD(AP27,24,"VOLUME AMOUNT","N")} -> 23591 | AY27: {=_xll.PrecioBD(AP27,24,"IMBALANCE","N")} -> 0.0057 | AZ27: Semestral | BA27: 1 | BB27: Sinkable
D28: MSFT | E28: {=_xll.PrecioBD(D28,24,"ASK","N")} -> 19630 | F28: {=_xll.PrecioBD(D28,24,"VOLUME AMOUNT","N")} -> 2172524600 | G28: {=_xll.PrecioBD(D28,24,"IMBALANCE","N")} -> -0.016 | J28: TXAR | K28: {=_xll.PrecioBD(J28,24,"ASK","N")} -> 700 | L28: {=_xll.PrecioBD(J28,24,"VOLUME AMOUNT","N")} -> 1.0039531e+08 | M28: {=_xll.PrecioBD(J28,24,"IMBALANCE","N")} -> -0.0007 | Q28: S30A6 | R28: =AB9/$R$23-1 -> 0.060266414 | S28: =AB9/$S$23-1 -> 0.0249242 | T28: =AB9/$T$23-1 -> -0.0081378706 | U28: =AB9/$U$23-1 -> -0.039133562 | V28: =AB9/$V$23-1 -> -0.068250727 | W28: =AB9/$W$23-1 -> -0.095655117 | X28: =AB9/$X$23-1 -> -0.12149354 | Y28: =AB9/$Y$23-1 -> -0.1458965 | Z28: =AB9/$Z$23-1 -> -0.16898038 | AP28: BACGD | AQ28: {=INDIRECT("'" & AP28 & "'!K4")} -> 0.058027127 | AR28: {=INDIRECT("'" & AP28 & "'!K3")} -> 2.9104947 | AS28: 47292 | AT28: {=_xll.PrecioBD(AP28,"24","BID","N")} -> 107.2 | AU28: {=_xll.PrecioBD(AP28,"24","ASK","N")} -> 108 | AV28: {=_xll.PrecioBD(AP28,24,"QUANTITY BID","N")} -> 6000 | AW28: {=_xll.PrecioBD(AP28,24,"QUANTITY ASK","N")} -> 11000 | AX28: {=_xll.PrecioBD(AP28,24,"VOLUME AMOUNT","N")} -> 20511.5 | AY28: {=_xll.PrecioBD(AP28,24,"IMBALANCE","N")} -> 0.0079 | AZ28: Semestral | BA28: 10000 | BB28: Bullet
D29: MELI | E29: {=_xll.PrecioBD(D29,24,"ASK","N")} -> 25300 | F29: {=_xll.PrecioBD(D29,24,"VOLUME AMOUNT","N")} -> 1713938220 | G29: {=_xll.PrecioBD(D29,24,"IMBALANCE","N")} -> 0.0148 | J29: ALUA | K29: {=_xll.PrecioBD(J29,24,"ASK","N")} -> 995 | L29: {=_xll.PrecioBD(J29,24,"VOLUME AMOUNT","N")} -> 1.870205e+08 | M29: {=_xll.PrecioBD(J29,24,"IMBALANCE","N")} -> -0.0015 | Q29: S29Y6 | R29: =AB10/$R$23-1 -> 0.087978766 | S29: =AB10/$S$23-1 -> 0.051712807 | T29: =AB10/$T$23-1 -> 0.017786587 | U29: =AB10/$U$23-1 -> -0.014019244 | V29: =AB10/$V$23-1 -> -0.043897448 | W29: =AB10/$W$23-1 -> -0.072018112 | X29: =AB10/$X$23-1 -> -0.09853188 | Y29: =AB10/$Y$23-1 -> -0.12357266 | Z29: =AB10/$Z$23-1 -> -0.14725989 | AP29: ARC1D | AQ29: {=INDIRECT("'" & AP29 & "'!K4")} -> 0.061365077 | AR29: {=INDIRECT("'" & AP29 & "'!K3")} -> 2.9687023 | AS29: 48061 | AT29: {=_xll.PrecioBD(AP29,"24","BID","N")} -> 106.15 | AU29: {=_xll.PrecioBD(AP29,"24","ASK","N")} -> 106.3 | AV29: {=_xll.PrecioBD(AP29,24,"QUANTITY BID","N")} -> 1000 | AW29: {=_xll.PrecioBD(AP29,24,"QUANTITY ASK","N")} -> 14000 | AX29: {=_xll.PrecioBD(AP29,24,"VOLUME AMOUNT","N")} -> 17005.5 | AY29: {=_xll.PrecioBD(AP29,24,"IMBALANCE","N")} -> 0.0037 | AZ29: Trimestral | BA29: 1000 | BB29: Sinkable
D30: VIST | E30: {=_xll.PrecioBD(D30,24,"ASK","N")} -> 27140 | F30: {=_xll.PrecioBD(D30,24,"VOLUME AMOUNT","N")} -> 1691423680 | G30: {=_xll.PrecioBD(D30,24,"IMBALANCE","N")} -> -0.0173 | J30: TRAN | K30: {=_xll.PrecioBD(J30,24,"ASK","N")} -> 4117.5 | L30: {=_xll.PrecioBD(J30,24,"VOLUME AMOUNT","N")} -> 245508190 | M30: {=_xll.PrecioBD(J30,24,"IMBALANCE","N")} -> -0.0042 | Q30: T30J6 | R30: =AB11/$R$23-1 -> 0.11911921 | S30: =AB11/$S$23-1 -> 0.081815235 | T30: =AB11/$T$23-1 -> 0.04691797 | U30: =AB11/$U$23-1 -> 0.014201783 | V30: =AB11/$V$23-1 -> -0.016531604 | W30: =AB11/$W$23-1 -> -0.045457145 | X30: =AB11/$X$23-1 -> -0.072729798 | Y30: =AB11/$Y$23-1 -> -0.098487304 | Z30: =AB11/$Z$23-1 -> -0.12285251 | AP30: BYCHD | AQ30: {=INDIRECT("'" & AP30 & "'!K4")} -> 0.05249463 | AR30: {=INDIRECT("'" & AP30 & "'!K3")} -> 2.3355305 | AS30: 47036 | AT30: {=_xll.PrecioBD(AP30,"24","BID","N")} -> 106.75 | AU30: {=_xll.PrecioBD(AP30,"24","ASK","N")} -> 109 | AV30: {=_xll.PrecioBD(AP30,24,"QUANTITY BID","N")} -> 20000 | AW30: {=_xll.PrecioBD(AP30,24,"QUANTITY ASK","N")} -> 2700 | AX30: {=_xll.PrecioBD(AP30,24,"VOLUME AMOUNT","N")} -> 0 | AY30: {=_xll.PrecioBD(AP30,24,"IMBALANCE","N")} -> 0 | AZ30: Semestral | BA30: 10000 | BB30: Bullet
D31: HUT | E31: {=_xll.PrecioBD(D31,24,"ASK","N")} -> 385900 | F31: {=_xll.PrecioBD(D31,24,"VOLUME AMOUNT","N")} -> 1174584275 | G31: {=_xll.PrecioBD(D31,24,"IMBALANCE","N")} -> -0.0183 | J31: IRSA | K31: {=_xll.PrecioBD(J31,24,"ASK","N")} -> 2325 | L31: {=_xll.PrecioBD(J31,24,"VOLUME AMOUNT","N")} -> 43247005 | M31: {=_xll.PrecioBD(J31,24,"IMBALANCE","N")} -> -0.0042 | Q31: S31L6 | R31: =AB12/$R$23-1 -> 0.15082942 | S31: =AB12/$S$23-1 -> 0.11246844 | T31: =AB12/$T$23-1 -> 0.076582361 | U31: =AB12/$U$23-1 -> 0.042939162 | V31: =AB12/$V$23-1 -> 0.011334945 | W31: =AB12/$W$23-1 -> -0.018410201 | X31: =AB12/$X$23-1 -> -0.046455623 | Y31: =AB12/$Y$23-1 -> -0.072942967 | Z31: =AB12/$Z$23-1 -> -0.097998563 | AP31: YMCID | AQ31: {=INDIRECT("'" & AP31 & "'!K4")} -> 0.050438944 | AR31: {=INDIRECT("'" & AP31 & "'!K3")} -> 1.7060416 | AS31: 47299 | AT31: {=_xll.PrecioBD(AP31,"24","BID","N")} -> 108 | AU31: {=_xll.PrecioBD(AP31,"24","ASK","N")} -> 108.15 | AV31: {=_xll.PrecioBD(AP31,24,"QUANTITY BID","N")} -> 37818 | AW31: {=_xll.PrecioBD(AP31,24,"QUANTITY ASK","N")} -> 932 | AX31: {=_xll.PrecioBD(AP31,24,"VOLUME AMOUNT","N")} -> 319465.78 | AY31: {=_xll.PrecioBD(AP31,24,"IMBALANCE","N")} -> -0.0023 | AZ31: Semestral | BA31: 1000 | BB31: Sinkable
D32: TSLA | E32: {=_xll.PrecioBD(D32,24,"ASK","N")} -> 41740 | F32: {=_xll.PrecioBD(D32,24,"VOLUME AMOUNT","N")} -> 1128756160 | G32: {=_xll.PrecioBD(D32,24,"IMBALANCE","N")} -> -0.008 | J32: BYMA | K32: {=_xll.PrecioBD(J32,24,"ASK","N")} -> 323 | L32: {=_xll.PrecioBD(J32,24,"VOLUME AMOUNT","N")} -> 3.2396257e+08 | M32: {=_xll.PrecioBD(J32,24,"IMBALANCE","N")} -> -0.0092 | Q32: S31G6 | R32: =AB13/$R$23-1 -> 0.18890037 | S32: =AB13/$S$23-1 -> 0.14927036 | T32: =AB13/$T$23-1 -> 0.11219712 | U32: =AB13/$U$23-1 -> 0.077440961 | V32: =AB13/$V$23-1 -> 0.044791235 | W32: =AB13/$W$23-1 -> 0.014062081 | X32: =AB13/$X$23-1 -> -0.014911122 | Y32: =AB13/$Y$23-1 -> -0.042274702 | Z32: =AB13/$Z$23-1 -> -0.068159169 | AP32: IRCFD | AQ32: {=INDIRECT("'" & AP32 & "'!K4")} -> 0.055855003 | AR32: {=INDIRECT("'" & AP32 & "'!K3")} -> 1.4147671 | AS32: 46926 | AT32: {=_xll.PrecioBD(AP32,"24","BID","N")} -> 68.62 | AU32: {=_xll.PrecioBD(AP32,"24","ASK","N")} -> 68.89 | AV32: {=_xll.PrecioBD(AP32,24,"QUANTITY BID","N")} -> 7216 | AW32: {=_xll.PrecioBD(AP32,24,"QUANTITY ASK","N")} -> 400 | AX32: {=_xll.PrecioBD(AP32,24,"VOLUME AMOUNT","N")} -> 22459.43 | AY32: {=_xll.PrecioBD(AP32,24,"IMBALANCE","N")} -> 0.0005 | AZ32: Semestral | BA32: 1000 | BB32: Bullet
D33: AMD | E33: {=_xll.PrecioBD(D33,24,"ASK","N")} -> 31120 | F33: {=_xll.PrecioBD(D33,24,"VOLUME AMOUNT","N")} -> 1014853820 | G33: {=_xll.PrecioBD(D33,24,"IMBALANCE","N")} -> -0.0101 | J33: TECO2 | K33: {=_xll.PrecioBD(J33,24,"ASK","N")} -> 3380 | L33: {=_xll.PrecioBD(J33,24,"VOLUME AMOUNT","N")} -> 5.8328943e+08 | M33: {=_xll.PrecioBD(J33,24,"IMBALANCE","N")} -> -0.0102 | Q33: S30O6 | R33: =AB14/$R$23-1 -> 0.23333472 | S33: =AB14/$S$23-1 -> 0.19222356 | T33: =AB14/$T$23-1 -> 0.15376473 | U33: =AB14/$U$23-1 -> 0.11770959 | V33: =AB14/$V$23-1 -> 0.083839598 | W33: =AB14/$W$23-1 -> 0.051961963 | X33: =AB14/$X$23-1 -> 0.021905907 | Y33: =AB14/$Y$23-1 -> -0.0064803684 | Z33: =AB14/$Z$23-1 -> -0.03333225 | AP33: CAC5D | AQ33: {=INDIRECT("'" & AP33 & "'!K4")} -> 0.059898403 | AR33: {=INDIRECT("'" & AP33 & "'!K3")} -> 1.141965 | AS33: 46990 | AT33: {=_xll.PrecioBD(AP33,"24","BID","N")} -> 80.61 | AU33: {=_xll.PrecioBD(AP33,"24","ASK","N")} -> 81.28 | AV33: {=_xll.PrecioBD(AP33,24,"QUANTITY BID","N")} -> 1351 | AW33: {=_xll.PrecioBD(AP33,24,"QUANTITY ASK","N")} -> 916 | AX33: {=_xll.PrecioBD(AP33,24,"VOLUME AMOUNT","N")} -> 32006.09 | AY33: {=_xll.PrecioBD(AP33,24,"IMBALANCE","N")} -> -0.01 | AZ33: Semestral | BA33: 1000 | BB33: Sinkable
D34: COIN | E34: {=_xll.PrecioBD(D34,24,"ASK","N")} -> 7910 | F34: {=_xll.PrecioBD(D34,24,"VOLUME AMOUNT","N")} -> 1010921675 | G34: {=_xll.PrecioBD(D34,24,"IMBALANCE","N")} -> -0.0561 | J34: VALO | K34: {=_xll.PrecioBD(J34,24,"ASK","N")} -> 582 | L34: {=_xll.PrecioBD(J34,24,"VOLUME AMOUNT","N")} -> 1.6812574e+09 | M34: {=_xll.PrecioBD(J34,24,"IMBALANCE","N")} -> -0.0127 | Q34: S30N6 | R34: =AB15/$R$23-1 -> 0.27363896 | S34: =AB15/$S$23-1 -> 0.23118432 | T34: =AB15/$T$23-1 -> 0.1914687 | U34: =AB15/$U$23-1 -> 0.1542353 | V34: =AB15/$V$23-1 -> 0.11925848 | W34: =AB15/$W$23-1 -> 0.086339109 | X34: =AB15/$X$23-1 -> 0.055300849 | Y34: =AB15/$Y$23-1 -> 0.025986936 | Z34: =AB15/$Z$23-1 -> -0.0017424404 | AP34: MTCGD | AQ34: {=INDIRECT("'" & AP34 & "'!K4")} -> 0.02873399 | AR34: {=INDIRECT("'" & AP34 & "'!K3")} -> 0.36070615 | AS34: 46203 | AT34: {=_xll.PrecioBD(AP34,"24","BID","N")} -> 104.3 | AU34: {=_xll.PrecioBD(AP34,"24","ASK","N")} -> 104.4 | AV34: {=_xll.PrecioBD(AP34,24,"QUANTITY BID","N")} -> 580 | AW34: {=_xll.PrecioBD(AP34,24,"QUANTITY ASK","N")} -> 2268 | AX34: {=_xll.PrecioBD(AP34,24,"VOLUME AMOUNT","N")} -> 17231.61 | AY34: {=_xll.PrecioBD(AP34,24,"IMBALANCE","N")} -> 0.0009 | AZ34: Trimestral | BA34: 2000 | BB34: Bullet
D35: SPY | E35: {=_xll.PrecioBD(D35,24,"ASK","N")} -> 50675 | F35: {=_xll.PrecioBD(D35,24,"VOLUME AMOUNT","N")} -> 1044567400 | G35: {=_xll.PrecioBD(D35,24,"IMBALANCE","N")} -> -0.0107 | J35: METR | K35: {=_xll.PrecioBD(J35,24,"ASK","N")} -> 2339 | L35: {=_xll.PrecioBD(J35,24,"VOLUME AMOUNT","N")} -> 325618803 | M35: {=_xll.PrecioBD(J35,24,"IMBALANCE","N")} -> -0.0131 | Q35: T15E7 | R35: =AB16/$R$23-1 -> 0.3302823 | S35: =AB16/$S$23-1 -> 0.28593955 | T35: =AB16/$T$23-1 -> 0.24445763 | U35: =AB16/$U$23-1 -> 0.20556833 | V35: =AB16/$V$23-1 -> 0.16903596 | W35: =AB16/$W$23-1 -> 0.13465255 | X35: =AB16/$X$23-1 -> 0.1022339 | Y35: =AB16/$Y$23-1 -> 0.071616295 | Z35: =AB16/$Z$23-1 -> 0.042653692 | AP35: YCAMD | AQ35: {=INDIRECT("'" & AP35 & "'!K4")} -> 0 | AR35: {=INDIRECT("'" & AP35 & "'!K3")} -> 0 | AS35: 46589 | AT35: {=_xll.PrecioBD(AP35,"24","BID","N")} -> 0 | AU35: {=_xll.PrecioBD(AP35,"24","ASK","N")} -> 105.3 | AV35: {=_xll.PrecioBD(AP35,24,"QUANTITY BID","N")} -> 0 | AW35: {=_xll.PrecioBD(AP35,24,"QUANTITY ASK","N")} -> 26000 | AX35: {=_xll.PrecioBD(AP35,24,"VOLUME AMOUNT","N")} -> 0 | AY35: {=_xll.PrecioBD(AP35,24,"IMBALANCE","N")} -> 0 | AZ35: Semestral | BA35: 1 | BB35: Sinkable
D36: JMIA | E36: {=_xll.PrecioBD(D36,24,"ASK","N")} -> 14290 | F36: {=_xll.PrecioBD(D36,24,"VOLUME AMOUNT","N")} -> 902736040 | G36: {=_xll.PrecioBD(D36,24,"IMBALANCE","N")} -> -0.0082 | J36: YPFD | K36: {=_xll.PrecioBD(J36,24,"ASK","N")} -> 56800 | L36: {=_xll.PrecioBD(J36,24,"VOLUME AMOUNT","N")} -> 4231933225 | M36: {=_xll.PrecioBD(J36,24,"IMBALANCE","N")} -> -0.0177 | Q36: T30A7 | R36: =AB17/$R$23-1 -> 0.45963841 | S36: =AB17/$S$23-1 -> 0.4109838 | T36: =AB17/$T$23-1 -> 0.36546819 | U36: =AB17/$U$23-1 -> 0.32279731 | V36: =AB17/$V$23-1 -> 0.28271254 | W36: =AB17/$W$23-1 -> 0.2449857 | X36: =AB17/$X$23-1 -> 0.20941468 | Y36: =AB17/$Y$23-1 -> 0.17581983 | Z36: =AB17/$Z$23-1 -> 0.14404092 | AP36: PNDCD | AQ36: {=INDIRECT("'" & AP36 & "'!K4")} -> 0.0024431378 | AR36: {=INDIRECT("'" & AP36 & "'!K3")} -> 0.68797658 | AS36: 46507 | AT36: {=_xll.PrecioBD(AP36,"24","BID","N")} -> 64 | AU36: {=_xll.PrecioBD(AP36,"24","ASK","N")} -> 65.37 | AV36: {=_xll.PrecioBD(AP36,24,"QUANTITY BID","N")} -> 3000 | AW36: {=_xll.PrecioBD(AP36,24,"QUANTITY ASK","N")} -> 5000 | AX36: {=_xll.PrecioBD(AP36,24,"VOLUME AMOUNT","N")} -> 0 | AY36: {=_xll.PrecioBD(AP36,24,"IMBALANCE","N")} -> 0 | AZ36: Semestral | BA36: 1 | BB36: Sinkable
D37: IBIT | E37: {=_xll.PrecioBD(D37,24,"ASK","N")} -> 5610 | F37: {=_xll.PrecioBD(D37,24,"VOLUME AMOUNT","N")} -> 796716555 | G37: {=_xll.PrecioBD(D37,24,"IMBALANCE","N")} -> -0.0114 | J37: CRES | K37: {=_xll.PrecioBD(J37,24,"ASK","N")} -> 1846 | L37: {=_xll.PrecioBD(J37,24,"VOLUME AMOUNT","N")} -> 109461415 | M37: {=_xll.PrecioBD(J37,24,"IMBALANCE","N")} -> -0.0196 | Q37: T31Y7 | R37: =AB18/$R$23-1 -> 0.46171775 | S37: =AB18/$S$23-1 -> 0.41299383 | T37: =AB18/$T$23-1 -> 0.36741338 | U37: =AB18/$U$23-1 -> 0.32468171 | V37: =AB18/$V$23-1 -> 0.28453984 | W37: =AB18/$W$23-1 -> 0.24675926 | X37: =AB18/$X$23-1 -> 0.21113757 | Y37: =AB18/$Y$23-1 -> 0.17749486 | Z37: =AB18/$Z$23-1 -> 0.14567067
D38: AAPL | E38: {=_xll.PrecioBD(D38,24,"ASK","N")} -> 19870 | F38: {=_xll.PrecioBD(D38,24,"VOLUME AMOUNT","N")} -> 765856910 | G38: {=_xll.PrecioBD(D38,24,"IMBALANCE","N")} -> -0.0264 | J38: BMA | K38: {=_xll.PrecioBD(J38,24,"ASK","N")} -> 13590 | L38: {=_xll.PrecioBD(J38,24,"VOLUME AMOUNT","N")} -> 1174789710 | M38: {=_xll.PrecioBD(J38,24,"IMBALANCE","N")} -> -0.0251 | Q38: T30J7 | R38: =AB19/$R$23-1 -> 0.37968437 | S38: =AB19/$S$23-1 -> 0.33369489 | T38: =AB19/$T$23-1 -> 0.29067247 | U38: =AB19/$U$23-1 -> 0.25033896 | V38: =AB19/$V$23-1 -> 0.2124499 | W38: =AB19/$W$23-1 -> 0.17678961 | X38: =AB19/$X$23-1 -> 0.14316705 | Y38: =AB19/$Y$23-1 -> 0.11141241 | Z38: =AB19/$Z$23-1 -> 0.081374233
D39: AMZN | E39: {=_xll.PrecioBD(D39,24,"ASK","N")} -> 2046 | F39: {=_xll.PrecioBD(D39,24,"VOLUME AMOUNT","N")} -> 760295075 | G39: {=_xll.PrecioBD(D39,24,"IMBALANCE","N")} -> -0.0284 | J39: PAMP | K39: {=_xll.PrecioBD(J39,24,"ASK","N")} -> 4940 | L39: {=_xll.PrecioBD(J39,24,"VOLUME AMOUNT","N")} -> 1222518355 | M39: {=_xll.PrecioBD(J39,24,"IMBALANCE","N")} -> -0.0256
D40: GOOGL | E40: {=_xll.PrecioBD(D40,24,"ASK","N")} -> 7860 | F40: {=_xll.PrecioBD(D40,24,"VOLUME AMOUNT","N")} -> 751712840 | G40: {=_xll.PrecioBD(D40,24,"IMBALANCE","N")} -> -0.0094 | J40: COME | K40: {=_xll.PrecioBD(J40,24,"ASK","N")} -> 51.5 | L40: {=_xll.PrecioBD(J40,24,"VOLUME AMOUNT","N")} -> 2.0281591e+08 | M40: {=_xll.PrecioBD(J40,24,"IMBALANCE","N")} -> -0.0284
D41: ORCL | E41: {=_xll.PrecioBD(D41,24,"ASK","N")} -> 76575 | F41: {=_xll.PrecioBD(D41,24,"VOLUME AMOUNT","N")} -> 547981075 | G41: {=_xll.PrecioBD(D41,24,"IMBALANCE","N")} -> -0.0084 | J41: SUPV | K41: {=_xll.PrecioBD(J41,24,"ASK","N")} -> 3347.5 | L41: {=_xll.PrecioBD(J41,24,"VOLUME AMOUNT","N")} -> 7.8219591e+08 | M41: {=_xll.PrecioBD(J41,24,"IMBALANCE","N")} -> -0.0339
D42: MSTR | E42: {=_xll.PrecioBD(D42,24,"ASK","N")} -> 9160 | F42: {=_xll.PrecioBD(D42,24,"VOLUME AMOUNT","N")} -> 543604925 | G42: {=_xll.PrecioBD(D42,24,"IMBALANCE","N")} -> -0.0255 | J42: LOMA | K42: {=_xll.PrecioBD(J42,24,"ASK","N")} -> 3435 | L42: {=_xll.PrecioBD(J42,24,"VOLUME AMOUNT","N")} -> 2.5454462e+08 | M42: {=_xll.PrecioBD(J42,24,"IMBALANCE","N")} -> -0.022 | Q42: banco central -> la actual
D43: ANF | E43: {=_xll.PrecioBD(D43,24,"ASK","N")} -> 138400 | F43: {=_xll.PrecioBD(D43,24,"VOLUME AMOUNT","N")} -> 532248700 | G43: {=_xll.PrecioBD(D43,24,"IMBALANCE","N")} -> 0.0145 | J43: EDN | K43: {=_xll.PrecioBD(J43,24,"ASK","N")} -> 2145 | L43: {=_xll.PrecioBD(J43,24,"VOLUME AMOUNT","N")} -> 130470167 | M43: {=_xll.PrecioBD(J43,24,"IMBALANCE","N")} -> -0.0285 | V43: Superior | W43: px dólar
D44: NVDA | E44: {=_xll.PrecioBD(D44,24,"ASK","N")} -> 11590 | F44: {=_xll.PrecioBD(D44,24,"VOLUME AMOUNT","N")} -> 522846230 | G44: {=_xll.PrecioBD(D44,24,"IMBALANCE","N")} -> -0.0169 | J44: TGSU2 | K44: {=_xll.PrecioBD(J44,24,"ASK","N")} -> 8950 | L44: {=_xll.PrecioBD(J44,24,"VOLUME AMOUNT","N")} -> 610401525 | M44: {=_xll.PrecioBD(J44,24,"IMBALANCE","N")} -> -0.0287 | Q44: Período | R44: Referencia | S44: Mediana | V44: 1608
D45: CSCO | E45: {=_xll.PrecioBD(D45,24,"ASK","N")} -> 22540 | F45: {=_xll.PrecioBD(D45,24,"VOLUME AMOUNT","N")} -> 518611820 | G45: {=_xll.PrecioBD(D45,24,"IMBALANCE","N")} -> -0.1118 | J45: GGAL | K45: {=_xll.PrecioBD(J45,24,"ASK","N")} -> 7365 | L45: {=_xll.PrecioBD(J45,24,"VOLUME AMOUNT","N")} -> 8491021305 | M45: {=_xll.PrecioBD(J45,24,"IMBALANCE","N")} -> -0.027 | Q45: 46053 | R45: var. % mensual | S45: 0.024 | T45: =+(1+S45)^(1/30)-1 -> 0.00079086345 | U45: 46082 | V45: =+V44+(1+T45) -> 1609.0008
D46: ASTS | E46: {=_xll.PrecioBD(D46,24,"ASK","N")} -> 8160 | F46: {=_xll.PrecioBD(D46,24,"VOLUME AMOUNT","N")} -> 514164175 | G46: {=_xll.PrecioBD(D46,24,"IMBALANCE","N")} -> -0.1533 | J46: BBAR | K46: {=_xll.PrecioBD(J46,24,"ASK","N")} -> 8675 | L46: {=_xll.PrecioBD(J46,24,"VOLUME AMOUNT","N")} -> 273700760 | M46: {=_xll.PrecioBD(J46,24,"IMBALANCE","N")} -> -0.0334 | Q46: 46081 | R46: var. % mensual | S46: 0.021 | T46: =+(1+S46)^(1/30)-1 -> 0.00069299131 | U46: =+U45+1 -> 46083 | V46: =+V45+(1+$T$45) -> 1610.0016
D47: RIOT | E47: {=_xll.PrecioBD(D47,24,"ASK","N")} -> 7305 | F47: {=_xll.PrecioBD(D47,24,"VOLUME AMOUNT","N")} -> 496293840 | G47: {=_xll.PrecioBD(D47,24,"IMBALANCE","N")} -> 0.0027 | J47: CEPU | K47: {=_xll.PrecioBD(J47,24,"ASK","N")} -> 2309 | L47: {=_xll.PrecioBD(J47,24,"VOLUME AMOUNT","N")} -> 419407719 | M47: {=_xll.PrecioBD(J47,24,"IMBALANCE","N")} -> -0.0367 | Q47: 46112 | R47: var. % mensual | S47: 0.022 | T47: =+(1+S47)^(1/30)-1 -> 0.00072564621 | U47: =+U46+1 -> 46084 | V47: =+V46+(1+$T$45) -> 1611.0024
D48: KO | E48: {=_xll.PrecioBD(D48,24,"ASK","N")} -> 23420 | F48: {=_xll.PrecioBD(D48,24,"VOLUME AMOUNT","N")} -> 484759920 | G48: {=_xll.PrecioBD(D48,24,"IMBALANCE","N")} -> 0.0094 | Q48: 46142 | R48: var. % mensual | S48: 0.019 | T48: =+(1+S48)^(1/30)-1 -> 0.00062758866 | U48: =+U47+1 -> 46085 | V48: =+V47+(1+$T$45) -> 1612.0032
D49: META | E49: {=_xll.PrecioBD(D49,24,"ASK","N")} -> 40060 | F49: {=_xll.PrecioBD(D49,24,"VOLUME AMOUNT","N")} -> 480688820 | G49: {=_xll.PrecioBD(D49,24,"IMBALANCE","N")} -> -0.0257 | Q49: 46173 | R49: var. % mensual | S49: 0.017 | T49: =+(1+S49)^(1/30)-1 -> 0.0005620618 | U49: =+U48+1 -> 46086 | V49: =+V48+(1+$T$45) -> 1613.004
D50: SLV | E50: {=_xll.PrecioBD(D50,24,"ASK","N")} -> 18300 | F50: {=_xll.PrecioBD(D50,24,"VOLUME AMOUNT","N")} -> 466500120 | G50: {=_xll.PrecioBD(D50,24,"IMBALANCE","N")} -> -0.0281 | Q50: 46203 | R50: var. % mensual | S50: 0.016 | T50: =+(1+S50)^(1/30)-1 -> 0.00052925164 | U50: =+U49+1 -> 46087 | V50: =+V49+(1+$T$45) -> 1614.0047
D51: TSM | E51: {=_xll.PrecioBD(D51,24,"ASK","N")} -> 61175 | F51: {=_xll.PrecioBD(D51,24,"VOLUME AMOUNT","N")} -> 458363850 | G51: {=_xll.PrecioBD(D51,24,"IMBALANCE","N")} -> -0.0077 | Q51: 46234 | R51: var. % mensual | S51: 0.015 | T51: =+(1+S51)^(1/30)-1 -> 0.00049641025 | U51: =+U50+1 -> 46088 | V51: =+V50+(1+$T$45) -> 1615.0055
D52: NFLX | E52: {=_xll.PrecioBD(D52,24,"ASK","N")} -> 2331 | F52: {=_xll.PrecioBD(D52,24,"VOLUME AMOUNT","N")} -> 426940746 | G52: {=_xll.PrecioBD(D52,24,"IMBALANCE","N")} -> -0.0547 | U52: =+U51+1 -> 46089 | V52: =+V51+(1+$T$45) -> 1616.0063
D53: EBAY | E53: {=_xll.PrecioBD(D53,24,"ASK","N")} -> 59950 | F53: {=_xll.PrecioBD(D53,24,"VOLUME AMOUNT","N")} -> 417858450 | G53: {=_xll.PrecioBD(D53,24,"IMBALANCE","N")} -> -0.0247 | I53: Panel General | J53: Ticker | K53: Precio | L53: Total volume | M53: Variación | U53: =+U52+1 -> 46090 | V53: =+V52+(1+$T$45) -> 1617.0071
D54: TRIP | E54: {=_xll.PrecioBD(D54,24,"ASK","N")} -> 7580 | F54: {=_xll.PrecioBD(D54,24,"VOLUME AMOUNT","N")} -> 409396930 | G54: {=_xll.PrecioBD(D54,24,"IMBALANCE","N")} -> -0.1556 | J54: DOME | K54: {=_xll.PrecioBD(J54,24,"ASK","N")} -> 90 | L54: {=_xll.PrecioBD(J54,24,"VOLUME AMOUNT","N")} -> 1134092.2 | M54: {=_xll.PrecioBD(J54,24,"IMBALANCE","N")} -> 0.0975 | U54: =+U53+1 -> 46091 | V54: =+V53+(1+$T$45) -> 1618.0079
D55: PLTR | E55: {=_xll.PrecioBD(D55,24,"ASK","N")} -> 63875 | F55: {=_xll.PrecioBD(D55,24,"VOLUME AMOUNT","N")} -> 412299825 | G55: {=_xll.PrecioBD(D55,24,"IMBALANCE","N")} -> -0.0426 | J55: GBAN | K55: {=_xll.PrecioBD(J55,24,"ASK","N")} -> 2295 | L55: {=_xll.PrecioBD(J55,24,"VOLUME AMOUNT","N")} -> 2590250 | M55: {=_xll.PrecioBD(J55,24,"IMBALANCE","N")} -> 0.0361 | U55: =+U54+1 -> 46092 | V55: =+V54+(1+$T$45) -> 1619.0087
D56: RGTI | E56: {=_xll.PrecioBD(D56,24,"ASK","N")} -> 11050 | F56: {=_xll.PrecioBD(D56,24,"VOLUME AMOUNT","N")} -> 395812010 | G56: {=_xll.PrecioBD(D56,24,"IMBALANCE","N")} -> -0.0994 | J56: CELU | K56: {=_xll.PrecioBD(J56,24,"ASK","N")} -> 336.5 | L56: {=_xll.PrecioBD(J56,24,"VOLUME AMOUNT","N")} -> 36839743 | M56: {=_xll.PrecioBD(J56,24,"IMBALANCE","N")} -> 0.0417 | U56: =+U55+1 -> 46093 | V56: =+V55+(1+$T$45) -> 1620.0095
D57: GLOB | E57: {=_xll.PrecioBD(D57,24,"ASK","N")} -> 4230 | F57: {=_xll.PrecioBD(D57,24,"VOLUME AMOUNT","N")} -> 391479450 | G57: {=_xll.PrecioBD(D57,24,"IMBALANCE","N")} -> -0.0835 | J57: FERR | K57: {=_xll.PrecioBD(J57,24,"ASK","N")} -> 25.8 | L57: {=_xll.PrecioBD(J57,24,"VOLUME AMOUNT","N")} -> 5538082.7 | M57: {=_xll.PrecioBD(J57,24,"IMBALANCE","N")} -> 0.0238 | U57: =+U56+1 -> 46094 | V57: =+V56+(1+$T$45) -> 1621.0103 | W57: 1460 | X57: t13f6 | Y57: 1457
D58: HWM | E58: {=_xll.PrecioBD(D58,24,"ASK","N")} -> 372425 | F58: {=_xll.PrecioBD(D58,24,"VOLUME AMOUNT","N")} -> 377900400 | G58: {=_xll.PrecioBD(D58,24,"IMBALANCE","N")} -> 0.0844 | J58: CTIO | K58: {=_xll.PrecioBD(J58,24,"ASK","N")} -> 2185 | L58: {=_xll.PrecioBD(J58,24,"VOLUME AMOUNT","N")} -> 51476300 | M58: {=_xll.PrecioBD(J58,24,"IMBALANCE","N")} -> 0.023 | U58: =+U57+1 -> 46095 | V58: =+V57+(1+$T$45) -> 1622.0111
D59: EWZ | E59: {=_xll.PrecioBD(D59,24,"ASK","N")} -> 28700 | F59: {=_xll.PrecioBD(D59,24,"VOLUME AMOUNT","N")} -> 367796520 | G59: {=_xll.PrecioBD(D59,24,"IMBALANCE","N")} -> -0.0089 | J59: CARC | K59: {=_xll.PrecioBD(J59,24,"ASK","N")} -> 27.8 | L59: {=_xll.PrecioBD(J59,24,"VOLUME AMOUNT","N")} -> 1842537.5 | M59: {=_xll.PrecioBD(J59,24,"IMBALANCE","N")} -> 0.0218 | U59: =+U58+1 -> 46096 | V59: =+V58+(1+$T$45) -> 1623.0119
D60: GLD | E60: {=_xll.PrecioBD(D60,24,"ASK","N")} -> 13670 | F60: {=_xll.PrecioBD(D60,24,"VOLUME AMOUNT","N")} -> 337748120 | G60: {=_xll.PrecioBD(D60,24,"IMBALANCE","N")} -> -0.0115 | J60: BPAT | K60: {=_xll.PrecioBD(J60,24,"ASK","N")} -> 2680 | L60: {=_xll.PrecioBD(J60,24,"VOLUME AMOUNT","N")} -> 13713095 | M60: {=_xll.PrecioBD(J60,24,"IMBALANCE","N")} -> 0.0209 | U60: =+U59+1 -> 46097 | V60: =+V59+(1+$T$45) -> 1624.0127
D61: VALE | E61: {=_xll.PrecioBD(D61,24,"ASK","N")} -> 12940 | F61: {=_xll.PrecioBD(D61,24,"VOLUME AMOUNT","N")} -> 328821340 | G61: {=_xll.PrecioBD(D61,24,"IMBALANCE","N")} -> 0.0125 | J61: RICH | K61: {=_xll.PrecioBD(J61,24,"ASK","N")} -> 1975 | L61: {=_xll.PrecioBD(J61,24,"VOLUME AMOUNT","N")} -> 5238745 | M61: {=_xll.PrecioBD(J61,24,"IMBALANCE","N")} -> 0.0207 | U61: =+U60+1 -> 46098 | V61: =+V60+(1+$T$45) -> 1625.0134
D62: SATL | E62: {=_xll.PrecioBD(D62,24,"ASK","N")} -> 4590 | F62: {=_xll.PrecioBD(D62,24,"VOLUME AMOUNT","N")} -> 325378470 | G62: {=_xll.PrecioBD(D62,24,"IMBALANCE","N")} -> -0.0473 | J62: BOLT | K62: {=_xll.PrecioBD(J62,24,"ASK","N")} -> 42.2 | L62: {=_xll.PrecioBD(J62,24,"VOLUME AMOUNT","N")} -> 5052512.9 | M62: {=_xll.PrecioBD(J62,24,"IMBALANCE","N")} -> 0.0144 | U62: =+U61+1 -> 46099 | V62: =+V61+(1+$T$45) -> 1626.0142
D63: BRKB | E63: {=_xll.PrecioBD(D63,24,"ASK","N")} -> 33680 | F63: {=_xll.PrecioBD(D63,24,"VOLUME AMOUNT","N")} -> 315273060 | G63: {=_xll.PrecioBD(D63,24,"IMBALANCE","N")} -> -0.0023 | J63: FIPL | K63: {=_xll.PrecioBD(J63,24,"ASK","N")} -> 233 | L63: {=_xll.PrecioBD(J63,24,"VOLUME AMOUNT","N")} -> 1721118 | M63: {=_xll.PrecioBD(J63,24,"IMBALANCE","N")} -> 0.0021 | U63: =+U62+1 -> 46100 | V63: =+V62+(1+$T$45) -> 1627.015
D64: PFE | E64: {=_xll.PrecioBD(D64,24,"ASK","N")} -> 10190 | F64: {=_xll.PrecioBD(D64,24,"VOLUME AMOUNT","N")} -> 310938990 | G64: {=_xll.PrecioBD(D64,24,"IMBALANCE","N")} -> -0.0048 | J64: OEST | K64: {=_xll.PrecioBD(J64,24,"ASK","N")} -> 920 | L64: {=_xll.PrecioBD(J64,24,"VOLUME AMOUNT","N")} -> 1965652.5 | M64: {=_xll.PrecioBD(J64,24,"IMBALANCE","N")} -> 0.0108 | U64: =+U63+1 -> 46101 | V64: =+V63+(1+$T$45) -> 1628.0158
D65: PBR | E65: {=_xll.PrecioBD(D65,24,"ASK","N")} -> 22860 | F65: {=_xll.PrecioBD(D65,24,"VOLUME AMOUNT","N")} -> 282650670 | G65: {=_xll.PrecioBD(D65,24,"IMBALANCE","N")} -> -0.0268 | J65: GAMI | K65: {=_xll.PrecioBD(J65,24,"ASK","N")} -> 217 | L65: {=_xll.PrecioBD(J65,24,"VOLUME AMOUNT","N")} -> 290138.5 | M65: {=_xll.PrecioBD(J65,24,"IMBALANCE","N")} -> 0.0092 | U65: =+U64+1 -> 46102 | V65: =+V64+(1+$T$45) -> 1629.0166
D66: ETHA | E66: {=_xll.PrecioBD(D66,24,"ASK","N")} -> 4330 | F66: {=_xll.PrecioBD(D66,24,"VOLUME AMOUNT","N")} -> 287885890 | G66: {=_xll.PrecioBD(D66,24,"IMBALANCE","N")} -> -0.004 | J66: GCLA | K66: {=_xll.PrecioBD(J66,24,"ASK","N")} -> 2970 | L66: {=_xll.PrecioBD(J66,24,"VOLUME AMOUNT","N")} -> 561305 | M66: {=_xll.PrecioBD(J66,24,"IMBALANCE","N")} -> 0.0084 | U66: =+U65+1 -> 46103 | V66: =+V65+(1+$T$45) -> 1630.0174
D67: HMY | E67: {=_xll.PrecioBD(D67,24,"ASK","N")} -> 31880 | F67: {=_xll.PrecioBD(D67,24,"VOLUME AMOUNT","N")} -> 281066980 | G67: {=_xll.PrecioBD(D67,24,"IMBALANCE","N")} -> 0.0056 | J67: HSAT | K67: {=_xll.PrecioBD(J67,24,"ASK","N")} -> 152.5 | L67: {=_xll.PrecioBD(J67,24,"VOLUME AMOUNT","N")} -> 14700 | M67: {=_xll.PrecioBD(J67,24,"IMBALANCE","N")} -> 0.0068 | U67: =+U66+1 -> 46104 | V67: =+V66+(1+$T$45) -> 1631.0182
D68: SPOT | E68: {=_xll.PrecioBD(D68,24,"ASK","N")} -> 23690 | F68: {=_xll.PrecioBD(D68,24,"VOLUME AMOUNT","N")} -> 272260640 | G68: {=_xll.PrecioBD(D68,24,"IMBALANCE","N")} -> -0.0751 | J68: MOLI | K68: {=_xll.PrecioBD(J68,24,"ASK","N")} -> 3110 | L68: {=_xll.PrecioBD(J68,24,"VOLUME AMOUNT","N")} -> 4893970 | M68: {=_xll.PrecioBD(J68,24,"IMBALANCE","N")} -> 0.0065 | U68: =+U67+1 -> 46105 | V68: =+V67+(1+$T$45) -> 1632.019
D69: UPST | E69: {=_xll.PrecioBD(D69,24,"ASK","N")} -> 9210 | F69: {=_xll.PrecioBD(D69,24,"VOLUME AMOUNT","N")} -> 273086770 | G69: {=_xll.PrecioBD(D69,24,"IMBALANCE","N")} -> -0.0804 | J69: GRIM | K69: {=_xll.PrecioBD(J69,24,"ASK","N")} -> 2700 | L69: {=_xll.PrecioBD(J69,24,"VOLUME AMOUNT","N")} -> 3548175 | M69: {=_xll.PrecioBD(J69,24,"IMBALANCE","N")} -> 0.0055 | U69: =+U68+1 -> 46106 | V69: =+V68+(1+$T$45) -> 1633.0198
... D75: NU | E75: {=_xll.PrecioBD(D75,24,"ASK","N")} -> 12690 | F75: {=_xll.PrecioBD(D75,24,"VOLUME AMOUNT","N")} -> 237418070 | G75: {=_xll.PrecioBD(D75,24,"IMBALANCE","N")} -> -0.017 | J75: SAMI | K75: {=_xll.PrecioBD(J75,24,"ASK","N")} -> 655 | L75: {=_xll.PrecioBD(J75,24,"VOLUME AMOUNT","N")} -> 25964389 | M75: {=_xll.PrecioBD(J75,24,"IMBALANCE","N")} -> -0.003 | U75: =+U74+1 -> 46112 | V75: =+V74+(1+$T$45) -> 1639.0245
D76: INTC | E76: {=_xll.PrecioBD(D76,24,"ASK","N")} -> 13970 | F76: {=_xll.PrecioBD(D76,24,"VOLUME AMOUNT","N")} -> 227714720 | G76: {=_xll.PrecioBD(D76,24,"IMBALANCE","N")} -> -0.0078 | J76: IRSA | K76: {=_xll.PrecioBD(J76,24,"ASK","N")} -> 2325 | L76: {=_xll.PrecioBD(J76,24,"VOLUME AMOUNT","N")} -> 43247005 | M76: {=_xll.PrecioBD(J76,24,"IMBALANCE","N")} -> -0.0042 | U76: =+U75+1 -> 46113 | V76: =+V74+(1+$T$46) -> 1639.0244
D77: BABA | E77: {=_xll.PrecioBD(D77,24,"ASK","N")} -> 26160 | F77: {=_xll.PrecioBD(D77,24,"VOLUME AMOUNT","N")} -> 227227400 | G77: {=_xll.PrecioBD(D77,24,"IMBALANCE","N")} -> -0.0354 | J77: AUSO | K77: {=_xll.PrecioBD(J77,24,"ASK","N")} -> 3890 | L77: {=_xll.PrecioBD(J77,24,"VOLUME AMOUNT","N")} -> 5172290 | M77: {=_xll.PrecioBD(J77,24,"IMBALANCE","N")} -> -0.0051 | U77: =+U76+1 -> 46114 | V77: =+V75+(1+$T$46) -> 1640.0252
D78: GFI | E78: {=_xll.PrecioBD(D78,24,"ASK","N")} -> 83650 | F78: {=_xll.PrecioBD(D78,24,"VOLUME AMOUNT","N")} -> 223823425 | G78: {=_xll.PrecioBD(D78,24,"IMBALANCE","N")} -> -0.0133 | J78: HAVA | K78: {=_xll.PrecioBD(J78,24,"ASK","N")} -> 5510 | L78: {=_xll.PrecioBD(J78,24,"VOLUME AMOUNT","N")} -> 6847030 | M78: {=_xll.PrecioBD(J78,24,"IMBALANCE","N")} -> -0.0054 | U78: =+U77+1 -> 46115 | V78: =+V76+(1+$T$46) -> 1640.0251
D79: LAR | E79: {=_xll.PrecioBD(D79,24,"ASK","N")} -> 10100 | F79: {=_xll.PrecioBD(D79,24,"VOLUME AMOUNT","N")} -> 222621840 | G79: {=_xll.PrecioBD(D79,24,"IMBALANCE","N")} -> -0.0462 | J79: RIGO | K79: {=_xll.PrecioBD(J79,24,"ASK","N")} -> 523 | L79: {=_xll.PrecioBD(J79,24,"VOLUME AMOUNT","N")} -> 73630 | M79: {=_xll.PrecioBD(J79,24,"IMBALANCE","N")} -> -0.0056 | U79: =+U78+1 -> 46116 | V79: =+V77+(1+$T$46) -> 1641.0259
D80: QQQ | E80: {=_xll.PrecioBD(D80,24,"ASK","N")} -> 44680 | F80: {=_xll.PrecioBD(D80,24,"VOLUME AMOUNT","N")} -> 270359140 | G80: {=_xll.PrecioBD(D80,24,"IMBALANCE","N")} -> -0.0158 | J80: MORI | K80: {=_xll.PrecioBD(J80,24,"ASK","N")} -> 33.9 | L80: {=_xll.PrecioBD(J80,24,"VOLUME AMOUNT","N")} -> 40102439 | M80: {=_xll.PrecioBD(J80,24,"IMBALANCE","N")} -> -0.0058 | U80: =+U79+1 -> 46117 | V80: =+V78+(1+$T$46) -> 1641.0258
D81: CRWV | E81: {=_xll.PrecioBD(D81,24,"ASK","N")} -> 5050 | F81: {=_xll.PrecioBD(D81,24,"VOLUME AMOUNT","N")} -> 189361540 | G81: {=_xll.PrecioBD(D81,24,"IMBALANCE","N")} -> -0.0276 | J81: INVJ | K81: {=_xll.PrecioBD(J81,24,"ASK","N")} -> 562 | L81: {=_xll.PrecioBD(J81,24,"VOLUME AMOUNT","N")} -> 39542601 | M81: {=_xll.PrecioBD(J81,24,"IMBALANCE","N")} -> -0.0089 | U81: =+U80+1 -> 46118 | V81: =+V79+(1+$T$46) -> 1642.0266
D82: LRCX | E82: {=_xll.PrecioBD(D82,24,"ASK","N")} -> 6185 | F82: {=_xll.PrecioBD(D82,24,"VOLUME AMOUNT","N")} -> 179955955 | G82: {=_xll.PrecioBD(D82,24,"IMBALANCE","N")} -> 0.0048 | J82: SEMI | K82: {=_xll.PrecioBD(J82,24,"ASK","N")} -> 19.9 | L82: {=_xll.PrecioBD(J82,24,"VOLUME AMOUNT","N")} -> 8639619.2 | M82: {=_xll.PrecioBD(J82,24,"IMBALANCE","N")} -> -0.0099 | U82: =+U81+1 -> 46119 | V82: =+V80+(1+$T$46) -> 1642.0265
D83: NIO | E83: {=_xll.PrecioBD(D83,24,"ASK","N")} -> 1858 | F83: {=_xll.PrecioBD(D83,24,"VOLUME AMOUNT","N")} -> 167422327 | G83: {=_xll.PrecioBD(D83,24,"IMBALANCE","N")} -> -0.0074 | J83: BHIP | K83: {=_xll.PrecioBD(J83,24,"ASK","N")} -> 488 | L83: {=_xll.PrecioBD(J83,24,"VOLUME AMOUNT","N")} -> 79231818 | M83: {=_xll.PrecioBD(J83,24,"IMBALANCE","N")} -> -0.0101 | U83: =+U82+1 -> 46120 | V83: =+V81+(1+$T$46) -> 1643.0273
D84: AMAT | E84: {=_xll.PrecioBD(D84,24,"ASK","N")} -> 98300 | F84: {=_xll.PrecioBD(D84,24,"VOLUME AMOUNT","N")} -> 161777000 | G84: {=_xll.PrecioBD(D84,24,"IMBALANCE","N")} -> -0.0264 | J84: CECO2 | K84: {=_xll.PrecioBD(J84,24,"ASK","N")} -> 443 | L84: {=_xll.PrecioBD(J84,24,"VOLUME AMOUNT","N")} -> 7147778 | M84: {=_xll.PrecioBD(J84,24,"IMBALANCE","N")} -> -0.0111 | U84: =+U83+1 -> 46121 | V84: =+V82+(1+$T$46) -> 1643.0272
D85: RBLX | E85: {=_xll.PrecioBD(D85,24,"ASK","N")} -> 46740 | F85: {=_xll.PrecioBD(D85,24,"VOLUME AMOUNT","N")} -> 161473625 | G85: {=_xll.PrecioBD(D85,24,"IMBALANCE","N")} -> -0.0771 | J85: CGPA2 | K85: {=_xll.PrecioBD(J85,24,"ASK","N")} -> 2595 | L85: {=_xll.PrecioBD(J85,24,"VOLUME AMOUNT","N")} -> 10085670 | M85: {=_xll.PrecioBD(J85,24,"IMBALANCE","N")} -> -0.0193 | U85: =+U84+1 -> 46122 | V85: =+V83+(1+$T$46) -> 1644.028
D86: LAC | E86: {=_xll.PrecioBD(D86,24,"ASK","N")} -> 6770 | F86: {=_xll.PrecioBD(D86,24,"VOLUME AMOUNT","N")} -> 160720440 | G86: {=_xll.PrecioBD(D86,24,"IMBALANCE","N")} -> -0.0357 | J86: LONG | K86: {=_xll.PrecioBD(J86,24,"ASK","N")} -> 20.95 | L86: {=_xll.PrecioBD(J86,24,"VOLUME AMOUNT","N")} -> 2018150 | M86: {=_xll.PrecioBD(J86,24,"IMBALANCE","N")} -> -0.0119 | U86: =+U85+1 -> 46123 | V86: =+V84+(1+$T$46) -> 1644.0279
D87: B | E87: {=_xll.PrecioBD(D87,24,"ASK","N")} -> 34860 | F87: {=_xll.PrecioBD(D87,24,"VOLUME AMOUNT","N")} -> 151970380 | G87: {=_xll.PrecioBD(D87,24,"IMBALANCE","N")} -> -0.0068 | J87: IEB | K87: {=_xll.PrecioBD(J87,24,"ASK","N")} -> 785 | L87: {=_xll.PrecioBD(J87,24,"VOLUME AMOUNT","N")} -> 49969306 | M87: {=_xll.PrecioBD(J87,24,"IMBALANCE","N")} -> -0.0138 | U87: =+U86+1 -> 46124 | V87: =+V85+(1+$T$46) -> 1645.0287
... D96: ADBE | E96: {=_xll.PrecioBD(D96,24,"ASK","N")} -> 8545 | F96: {=_xll.PrecioBD(D96,24,"VOLUME AMOUNT","N")} -> 123528280 | G96: {=_xll.PrecioBD(D96,24,"IMBALANCE","N")} -> -0.0166 | J96: LEDE | K96: {=_xll.PrecioBD(J96,24,"ASK","N")} -> 822.5 | L96: {=_xll.PrecioBD(J96,24,"VOLUME AMOUNT","N")} -> 6575062.5 | M96: {=_xll.PrecioBD(J96,24,"IMBALANCE","N")} -> -0.0447 | U96: =+U95+1 -> 46133 | V96: =+V94+(1+$T$46) -> 1649.0313
D97: GPRK | E97: {=_xll.PrecioBD(D97,24,"ASK","N")} -> 12470 | F97: {=_xll.PrecioBD(D97,24,"VOLUME AMOUNT","N")} -> 118308390 | G97: {=_xll.PrecioBD(D97,24,"IMBALANCE","N")} -> -0.0259 | U97: =+U96+1 -> 46134 | V97: =+V95+(1+$T$46) -> 1650.0321
D98: TXR | E98: {=_xll.PrecioBD(D98,24,"ASK","N")} -> 16480 | F98: {=_xll.PrecioBD(D98,24,"VOLUME AMOUNT","N")} -> 114937740 | G98: {=_xll.PrecioBD(D98,24,"IMBALANCE","N")} -> -0.0042 | U98: =+U97+1 -> 46135 | V98: =+V96+(1+$T$46) -> 1650.032
D99: MCD | E99: {=_xll.PrecioBD(D99,24,"ASK","N")} -> 20050 | F99: {=_xll.PrecioBD(D99,24,"VOLUME AMOUNT","N")} -> 110947950 | G99: {=_xll.PrecioBD(D99,24,"IMBALANCE","N")} -> 0.003 | U99: =+U98+1 -> 46136 | V99: =+V97+(1+$T$46) -> 1651.0328
D100: BAK | E100: {=_xll.PrecioBD(D100,24,"ASK","N")} -> 2937.5 | F100: {=_xll.PrecioBD(D100,24,"VOLUME AMOUNT","N")} -> 1.067115e+08 | G100: {=_xll.PrecioBD(D100,24,"IMBALANCE","N")} -> -0.0701 | U100: =+U99+1 -> 46137 | V100: =+V98+(1+$T$46) -> 1651.0327
D101: WMT | E101: {=_xll.PrecioBD(D101,24,"ASK","N")} -> 10830 | F101: {=_xll.PrecioBD(D101,24,"VOLUME AMOUNT","N")} -> 106240550 | G101: {=_xll.PrecioBD(D101,24,"IMBALANCE","N")} -> 0.0236 | U101: =+U100+1 -> 46138 | V101: =+V99+(1+$T$46) -> 1652.0335
D102: OKLO | E102: {=_xll.PrecioBD(D102,24,"ASK","N")} -> 3452.5 | F102: {=_xll.PrecioBD(D102,24,"VOLUME AMOUNT","N")} -> 1.0536006e+08 | G102: {=_xll.PrecioBD(D102,24,"IMBALANCE","N")} -> -0.0163 | U102: =+U101+1 -> 46139 | V102: =+V100+(1+$T$46) -> 1652.0334
D103: PKS | E103: {=_xll.PrecioBD(D103,24,"ASK","N")} -> 32660 | F103: {=_xll.PrecioBD(D103,24,"VOLUME AMOUNT","N")} -> 102732520 | G103: {=_xll.PrecioBD(D103,24,"IMBALANCE","N")} -> 0.0168 | U103: =+U102+1 -> 46140 | V103: =+V101+(1+$T$46) -> 1653.0342
D104: ASML | E104: {=_xll.PrecioBD(D104,24,"ASK","N")} -> 14390 | F104: {=_xll.PrecioBD(D104,24,"VOLUME AMOUNT","N")} -> 101493310 | G104: {=_xll.PrecioBD(D104,24,"IMBALANCE","N")} -> -0.0137 | U104: =+U103+1 -> 46141 | V104: =+V102+(1+$T$46) -> 1653.0341
D105: FXI | E105: {=_xll.PrecioBD(D105,24,"ASK","N")} -> 11430 | F105: {=_xll.PrecioBD(D105,24,"VOLUME AMOUNT","N")} -> 96877400 | G105: {=_xll.PrecioBD(D105,24,"IMBALANCE","N")} -> -0.0213
D106: CDE | E106: {=_xll.PrecioBD(D106,24,"ASK","N")} -> 33500 | F106: {=_xll.PrecioBD(D106,24,"VOLUME AMOUNT","N")} -> 96488620 | G106: {=_xll.PrecioBD(D106,24,"IMBALANCE","N")} -> 0.0005
D107: HOOD | E107: {=_xll.PrecioBD(D107,24,"ASK","N")} -> 3672.5 | F107: {=_xll.PrecioBD(D107,24,"VOLUME AMOUNT","N")} -> 92035868 | G107: {=_xll.PrecioBD(D107,24,"IMBALANCE","N")} -> -0.0696 | I107: Factor Alfa | J107: Ticker | K107: Precio | L107: Total volume | M107: Variación | N107: Columna1 | O107: Columna2
D108: STNE | E108: {=_xll.PrecioBD(D108,24,"ASK","N")} -> 8460 | F108: {=_xll.PrecioBD(D108,24,"VOLUME AMOUNT","N")} -> 87962620 | G108: {=_xll.PrecioBD(D108,24,"IMBALANCE","N")} -> -0.0321 | J108: F | K108: {=_xll.PrecioBD(J108,24,"ASK","N")} -> 20620 | L108: {=_xll.PrecioBD(J108,24,"VOLUME AMOUNT","N")} -> 30235230 | M108: {=_xll.PrecioBD(J108,24,"IMBALANCE","N")} -> 0.0182 | N108: 0.042 | O108: =Tabla68[[#This Row],[Columna1]]*Tabla68[[#This Row],[Variación]] -> 0.0007644
D109: IBM | E109: {=_xll.PrecioBD(D109,24,"ASK","N")} -> 25840 | F109: {=_xll.PrecioBD(D109,24,"VOLUME AMOUNT","N")} -> 85028760 | G109: {=_xll.PrecioBD(D109,24,"IMBALANCE","N")} -> -0.0465 | J109: MRK | K109: {=_xll.PrecioBD(J109,24,"ASK","N")} -> 35540 | L109: {=_xll.PrecioBD(J109,24,"VOLUME AMOUNT","N")} -> 17069620 | M109: {=_xll.PrecioBD(J109,24,"IMBALANCE","N")} -> 0.0137 | N109: 0.042 | O109: =Tabla68[[#This Row],[Columna1]]*Tabla68[[#This Row],[Variación]] -> 0.0005754
D110: ILF | E110: {=_xll.PrecioBD(D110,24,"ASK","N")} -> 9095 | F110: {=_xll.PrecioBD(D110,24,"VOLUME AMOUNT","N")} -> 84634925 | G110: {=_xll.PrecioBD(D110,24,"IMBALANCE","N")} -> -0.0054 | J110: KO | K110: {=_xll.PrecioBD(J110,24,"ASK","N")} -> 23420 | L110: {=_xll.PrecioBD(J110,24,"VOLUME AMOUNT","N")} -> 484759920 | M110: {=_xll.PrecioBD(J110,24,"IMBALANCE","N")} -> 0.0094 | N110: 0.042 | O110: =Tabla68[[#This Row],[Columna1]]*Tabla68[[#This Row],[Variación]] -> 0.0003948
D111: FCX | E111: {=_xll.PrecioBD(D111,24,"ASK","N")} -> 31260 | F111: {=_xll.PrecioBD(D111,24,"VOLUME AMOUNT","N")} -> 84207100 | G111: {=_xll.PrecioBD(D111,24,"IMBALANCE","N")} -> -0.0242 | J111: MO | K111: {=_xll.PrecioBD(J111,24,"ASK","N")} -> 24540 | L111: {=_xll.PrecioBD(J111,24,"VOLUME AMOUNT","N")} -> 33615640 | M111: {=_xll.PrecioBD(J111,24,"IMBALANCE","N")} -> 0.0074 | N111: 0.042 | O111: =Tabla68[[#This Row],[Columna1]]*Tabla68[[#This Row],[Variación]] -> 0.0003108
D112: XLF | E112: {=_xll.PrecioBD(D112,24,"ASK","N")} -> 38500 | F112: {=_xll.PrecioBD(D112,24,"VOLUME AMOUNT","N")} -> 83856120 | G112: {=_xll.PrecioBD(D112,24,"IMBALANCE","N")} -> -0.0138 | J112: SLB | K112: {=_xll.PrecioBD(J112,24,"ASK","N")} -> 25440 | L112: {=_xll.PrecioBD(J112,24,"VOLUME AMOUNT","N")} -> 7124100 | M112: {=_xll.PrecioBD(J112,24,"IMBALANCE","N")} -> 0.0087 | N112: 0.042 | O112: =Tabla68[[#This Row],[Columna1]]*Tabla68[[#This Row],[Variación]] -> 0.0003654
D113: CVX | E113: {=_xll.PrecioBD(D113,24,"ASK","N")} -> 16940 | F113: {=_xll.PrecioBD(D113,24,"VOLUME AMOUNT","N")} -> 80378980 | G113: {=_xll.PrecioBD(D113,24,"IMBALANCE","N")} -> -0.011 | J113: CAH | K113: {=_xll.PrecioBD(J113,24,"ASK","N")} -> 111450 | L113: {=_xll.PrecioBD(J113,24,"VOLUME AMOUNT","N")} -> 999475 | M113: {=_xll.PrecioBD(J113,24,"IMBALANCE","N")} -> 0.0024 | N113: 0.042 | O113: =Tabla68[[#This Row],[Columna1]]*Tabla68[[#This Row],[Variación]] -> 0.0001008
...

Sheet Hoja1
B3: ALUA | C3: 990,00 | D3: 1,12 | E3: -5,26 | F3: 1,02 | G3: 979,00 | H3: 990,00 | I3: 980,00 | J3: 1.030,00 | K3: 0.69513889 | L3: 729.547 | M3: 740.354.729,00
B4: BBAR | C4: 9.000,00 | D4: 1,60 | E4: -11,81 | F4: -2,74 | G4: 8.750,00 | H4: 8.920,00 | I4: 8.785,00 | J4: 9.125,00 | K4: 0.69513889 | L4: 234.589 | M4: 2.092.388.530,00
B5: BMA | C5: 13.750,00 | D5: 3,59 | E5: -9,35 | F5: 2,14 | G5: 13.380,00 | H5: 13.030,00 | I5: 13.030,00 | J5: 13.950,00 | K5: 0.69513889 | L5: 136.009 | M5: 1.861.423.320,00
B6: BYMA | C6: 329,75 | D6: -0,23 | E6: -1,79 | F6: 13,41 | G6: 330,50 | H6: 329,75 | I6: 329,25 | J6: 333,75 | K6: 0.69513889 | L6: 12.906.984 | M6: 4.282.852.453,00
B7: CEPU | C7: 2.343,00 | D7: 1,38 | E7: -9,46 | F7: -12,98 | G7: 2.322,00 | H7: 2.313,00 | I7: 2.300,00 | J7: 2.385,00 | K7: 0.69513889 | L7: 430.717 | M7: 1.015.226.332,00
B8: COME | C8: 51,60 | D8: 2,79 | E8: -15,13 | F8: -13,28 | G8: 50,20 | H8: 51,40 | I8: 50,50 | J8: 51,60 | K8: 0.69513889 | L8: 13.089.758 | M8: 671.076.788,00
B9: CRES | C9: 1.954,00 | D9: 0,84 | E9: -5,12 | F9: 0,42 | G9: 1.910,00 | H9: 1.980,00 | I9: 1.898,00 | J9: 2.000,00 | K9: 0.69513889 | L9: 312.668 | M9: 605.569.646,00
B10: EDN | C10: 2.057,00 | D10: 1,98 | E10: -12,02 | F10: -15,25 | G10: 2.017,00 | H10: 2.015,00 | I10: 2.015,00 | J10: 2.093,00 | K10: 0.68055556 | L10: 339.662 | M10: 699.986.421,00
B11: GGAL | C11: 7.515,00 | D11: 0,46 | E11: -10,65 | F11: -9,45 | G11: 7.480,43 | H11: 7.515,00 | I11: 7.350,00 | J11: 7.640,00 | K11: 0.69513889 | L11: 3.567.229 | M11: 26.616.044.485,00
B12: IRSA | C12: 2.375,00 | D12: - | E12: -9,87 | F12: -6,31 | G12: 2.375,00 | H12: 2.375,00 | I12: 2.355,00 | J12: 2.445,00 | K12: 0.69513889 | L12: 168.413 | M12: 404.590.690,00
B13: LOMA | C13: 3.330,00 | D13: 3,02 | E13: -7,38 | F13: -17,60 | G13: 3.227,50 | H13: 3.232,50 | I13: 3.232,50 | J13: 3.405,00 | K13: 0.69513889 | L13: 200.823 | M13: 666.762.465,00
B14: METR | C14: 2.280,00 | D14: 4,23 | E14: -2,34 | F14: -8,15 | G14: 2.245,00 | H14: 2.255,00 | I14: 2.255,00 | J14: 2.377,00 | K14: 0.69513889 | L14: 435.19 | M14: 1.012.517.298,00
B15: PAMP | C15: 4.920,00 | D15: 1,32 | E15: -4,41 | F15: -5,23 | G15: 4.920,00 | H15: 4.920,00 | I15: 4.900,00 | J15: 5.045,00 | K15: 0.69513889 | L15: 895.564 | M15: 4.465.168.188,00
B16: SUPV | C16: 3.245,00 | D16: 4,05 | E16: -11,01 | F16: -8,26 | G16: 3.147,50 | H16: 3.145,00 | I16: 3.145,00 | J16: 3.292,50 | K16: 0.69513889 | L16: 629.97 | M16: 2.039.917.058,00
B17: TECO2 | C17: 3.620,00 | D17: 3,95 | E17: -11,71 | F17: 2,62 | G17: 3.482,50 | H17: 3.605,00 | I17: 3.470,00 | J17: 3.670,00 | K17: 0.68055556 | L17: 71.928 | M17: 255.944.160,00
B18: TGNO4 | C18: 4.120,00 | D18: 3,65 | E18: -8,50 | F18: -15,92 | G18: 3.975,00 | H18: 4.090,00 | I18: 4.007,50 | J18: 4.182,50 | K18: 0.69513889 | L18: 211.601 | M18: 865.019.880,00
B19: TGSU2 | C19: 8.760,00 | D19: 2,00 | E19: -7,51 | F19: -3,46 | G19: 8.755,00 | H19: 8.760,00 | I19: 8.760,00 | J19: 9.130,00 | K19: 0.69513889 | L19: 159.019 | M19: 1.418.342.155,00
B20: TRAN | C20: 3.950,00 | D20: 3,56 | E20: 4,03 | F20: 11,81 | G20: 3.862,50 | H20: 3.865,00 | I20: 3.820,00 | J20: 4.000,00 | K20: 0.69513889 | L20: 379.215 | M20: 1.505.853.448,00
B21: TXAR | C21: 691,00 | D21: 1,10 | E21: -1,99 | F21: 2,83 | G21: 683,50 | H21: 691,00 | I21: 680,50 | J21: 701,50 | K21: 0.69513889 | L21: 684.823 | M21: 471.499.947,00
B22: VALO | C22: 585,00 | D22: 0,77 | E22: -5,08 | F22: 6,81 | G22: 583,50 | H22: 585,00 | I22: 585,00 | J22: 594,00 | K22: 0.69513889 | L22: 2.466.195 | M22: 1.449.781.104,00
B23: YPFD | C23: 56.500,00 | D23: 1,37 | E23: -4,19 | F23: 4,76 | G23: 56.425,00 | H23: 56.500,00 | I23: 56.500,00 | J23: 58.300,00 | K23: 0.69513889 | L23: 214.242 | M23: 12.369.784.400,00

Sheet Multi-mercado
A1: Ticker | B1: GD41D | C1: 24
B3: Cierre | C3: {=_xll.PrecioBD(B1,C1,"PREVIOUS","N")} -> 74.98 | D3: Último | E3: {=_xll.PrecioBD(B1,C1,"LAST","N")} -> 75.12 | F3: Var | G3: {=_xll.PrecioBD(B1,C1,"IMBALANCE","N")} -> 0.0018
B4: Vwap | C4: {=_xll.PrecioBD(B1,C1,"VWAP","N")} -> 75.037905 | D4: Nominales | E4: {=_xll.PrecioBD(B1,C1,"TRADE VOLUME","N")} -> 223225 | F4: Monto $ | G4: {=_xll.PrecioBD(B1,C1,"VOLUME AMOUNT","N")} -> 167503.41
B6: {=_xll.PrecioBD(B1,C1,"BID","N")} -> 75.11 | E6: {=_xll.PrecioBD(B1,C1,"ASK","N")} -> 75.15
A7: {=_xll.ProfundidadBD(B1,C1)} -> GD41D - 24hs | B7: ORD. | C7: CANT. | D7: PRECIO | E7: PRECIO | F7: CANT. | G7: ORD.
B8: 2 | C8: 763 | D8: 75.07 | E8: 75.15 | F8: 10 | G8: 1
B9: 1 | C9: 146 | D9: 75.02 | E9: 75.21 | F9: 559 | G9: 1
B10: 1 | C10: 632 | D10: 74.99 | E10: 75.22 | F10: 244 | G10: 1
B11: 1 | C11: 94 | D11: 74.95 | E11: 75.23 | F11: 960 | G11: 1
B12: 1 | C12: 8 | D12: 74.92 | E12: 75.24 | F12: 996 | G12: 1
I14: Pase
A15: Ticker | B15: =B1 -> GD41D | C15: CI | J15: Venta CI - Compra T1 | K15: Compra CI - Venta T1
I16: Arbitraje | J16: =D22/E8-1 -> -0.0011976048 | K16: =D8/E22-1 -> -0.0011974454
B17: Cierre | C17: {=_xll.PrecioBD(B15,C15,"PREVIOUS","N")} -> 74.95 | D17: Último | E17: {=_xll.PrecioBD(B15,C15,"LAST","N")} -> 75.16 | F17: Var | G17: {=_xll.PrecioBD(B15,C15,"IMBALANCE","N")} -> 0.0028 | I17: TNA | J17: =+J16*365 -> -0.43712575 | K17: =+K16*365 -> -0.43706759
B18: Vwap | C18: {=_xll.PrecioBD(B15,C15,"VWAP","N")} -> 75.070864 | D18: Nominales | E18: {=_xll.PrecioBD(B15,C15,"TRADE VOLUME","N")} -> 54350 | F18: Monto $ | G18: {=_xll.PrecioBD(B15,C15,"VOLUME AMOUNT","N")} -> 40801.02
B20: {=_xll.PrecioBD(B15,C15,"BID","N")} -> 75.1 | E20: {=_xll.PrecioBD(B15,C15,"ASK","N")} -> 75.16
A21: {=_xll.ProfundidadBD(B15,C15)} -> GD41D - CI | B21: ORD. | C21: CANT. | D21: PRECIO | E21: PRECIO | F21: CANT. | G21: ORD.
B22: 2 | C22: 1227 | D22: 75.06 | E22: 75.16 | F22: 10 | G22: 1
B23: 1 | C23: 10 | D23: 75.03 | E23: 75.21 | F23: 10 | G23: 1
B24: 1 | C24: 599 | D24: 74.95 | E24: 75.23 | F24: 5480 | G24: 1
B25: 1 | C25: 557 | D25: 74.93 | E25: 75.25 | F25: 159 | G25: 1
B26: 1 | C26: 2 | D26: 74.88 | E26: 75.26 | F26: 3720 | G26: 1

Sheet Indices BYMA
B3: {=_xll.IndicesBYMABD()} -> INDICES BYMA | C3: DESCRIPCION | D3: NOMBRE | E3: PRECIO | F3: MAXIMO | G3: MINIMO | H3: VARIACION | I3: CIERRE | J3: CIERRE ANTERIOR
C4: S&P BYMA Indice General | E4: 1.2083177e+08 | F4: 1.2476379e+08 | G4: 1.2079439e+08 | H4: -0.0207 | I4: 0 | J4: 1.2338569e+08
C5: S&P MERVAL | E5: 2949567.2 | F5: 3051946 | G5: 2948383.6 | H5: -0.0226 | I5: 0 | J5: 3017641.3
C6: S&P BYMA Construccion | E6: 43895.26 | F6: 45769.96 | G6: 43728.74 | H6: -0.0203 | I6: 0 | J6: 44806.34
C7: S&P BYMA CEDEAR Index | E7: 34712.41 | F7: 35283.66 | G7: 34710.36 | H7: -0.0149 | I7: 0 | J7: 35237.17
C8: S&P BYMA Ingenius Index | E8: 23678.1 | F8: 24173.33 | G8: 23654.2 | H8: -0.0205 | I8: 0 | J8: 24173.33
C9: S&P BYMA Energia | E9: 104946.17 | F9: 107722.98 | G9: 104439.2 | H9: -0.0185 | I9: 0 | J9: 106929.61
C10: S&P BYMA Bs Intermedios | E10: 50288.99 | F10: 51272.74 | G10: 50112.96 | H10: -0.0071 | I10: 0 | J10: 50646.76
C11: S&P BYMA Ind y Bs de Cap | E11: 46180.62 | F11: 47178.02 | G11: 46016.63 | H11: 0.0036 | I11: 0 | J11: 46016.63
C12: S&P BYMA Cons No Esencial | E12: 63004.83 | F12: 63999.08 | G12: 61451.65 | H12: -0.0109 | I12: 0 | J12: 63701.25
C13: S&P BYMA Consumo Masivo | E13: 86354.63 | F13: 88722.6 | G13: 86354.63 | H13: -0.0158 | I13: 0 | J13: 87737.9
C14: S&P BYMA Serv Financieros | E14: 82879.02 | F14: 86440.64 | G14: 82854.25 | H14: -0.0259 | I14: 0 | J14: 85080.46
C15: S&P BYMA Telecomunicacion | E15: 45802.18 | F15: 46420.68 | G15: 45710.39 | H15: 0.0014 | I15: 0 | J15: 45739.52
... C18: S&P BYMA Energia y Servicios Publicos | E18: 107781.18 | F18: 111096.07 | G18: 107403.24 | H18: -0.0208 | I18: 0 | J18: 110070.32
C22: {=_xll.IndicesIAMCBD()} -> INDICES IAMC | D22: FECHA | E22: CODIGO | F22: NOMBRE | G22: MONEDA | H22: CIERRE | I22: VARIANZA | J22: VARIACION | K22: CIERRE
J23: 0.0056 | K23: 981.42 | L23: 0.0056 | M23: =J23=L23 -> TRUE
D24: 2026-02-05 00:00:00.0 | E24: COR_DOL | F24: Subíndice de Bonos Cortos emitidos en dólares | G24: USD | H24: 1065.8267 | I24: 1.0028938 | J24: -0.0173 | K24: 2366.48 | L24: -0.0173 | M24: =J24=L24 -> TRUE
D25: 2026-02-05 00:00:00.0 | E25: COR_PES | F25: Subíndice de Bonos Cortos emitidos en pesos | G25: ARS | H25: 661145.69 | I25: 1.0021712 | J25: 0.0076 | K25: 24491.06 | L25: 0.0076 | M25: =J25=L25 -> TRUE
D26: 2026-02-05 00:00:00.0 | E26: COR_PES | F26: Subíndice de Bonos Cortos emitidos en pesos | G26: USD | H26: 2794.6276 | I26: 0.99772453 | J26: 0.0151 | K26: 48908.72 | L26: 0.0151 | M26: =J26=L26 -> TRUE
D27: 2026-02-05 00:00:00.0 | E27: IBONOS | F27: Indice de Bonos General | G27: ARS | H27: 920301.82 | I27: 1.0036901 | J27: -0.0012 | K27: 45819.57 | L27: -0.0012 | M27: =J27=L27 -> TRUE
D28: 2026-02-05 00:00:00.0 | E28: IBONOS | F28: Indice de Bonos General | G28: USD | H28: 1190.3695 | I28: 0.9992367 | J28: 0.0117 | K28: 17746.3 | L28: 0.0117 | M28: =J28=L28 -> TRUE
D29: 2026-02-05 00:00:00.0 | E29: LAR_DOL | F29: Subíndice de Bonos Largos emitidos en dólares | G29: ARS | H29: 754723.47 | I29: 1.0040412 | J29: 0.0004 | K29: 182127.25 | L29: 0.0004 | M29: =J29=L29 -> TRUE
D30: 2026-02-05 00:00:00.0 | E30: LAR_DOL | F30: Subíndice de Bonos Largos emitidos en dólares | G30: USD | H30: 1194.96 | I30: 0.99958629 | J30: 0 | K30: 3483 | L30: 0 | M30: =J30=L30 -> TRUE
D31: 2026-02-05 00:00:00.0 | E31: LAR_PES | F31: Subíndice de Bonos Largos emitidos en pesos | G31: ARS | H31: 142296.33 | I31: 1.0046702 | J31: 0.0002 | K31: 68858.28 | L31: 0.0002 | M31: =J31=L31 -> TRUE
D32: 2026-02-05 00:00:00.0 | E32: LAR_PES | F32: Subíndice de Bonos Largos emitidos en pesos | G32: USD | H32: 1044.4338 | I32: 1.0002125 | J32: 0 | K32: 8954.6 | L32: 0 | M32: =J32=L32 -> TRUE

Sheet Opciones
A1: =_xll.PanelOpcionesBD() -> OPCIONES | B1: SIMBOLO | C1: VTO. | D1: MONEDA | E1: C.CPRA. | F1: P.CPRA. | G1: P.VTA. | H1: C.VTA. | I1: APERTURA | J1: MINIMO | K1: MAXIMO | L1: ULTIMO | M1: CIERRE ANT. | N1: VAR. | O1: VOLUMEN | P1: VOL.MONTO | Q1: VWAP | R1: CIERRE | S1: HORA
B2: A30C80000A | C2: 24hs | D2: ARS | E2: 0 | F2: 0 | G2: 0 | H2: 0 | I2: 0 | J2: 0 | K2: 0 | L2: 0 | M2: 0 | N2: 0 | O2: 0 | P2: 0 | Q2: 0 | R2: 0
B3: A30C80000F | C3: 24hs | D3: ARS | E3: 0 | F3: 0 | G3: 0 | H3: 0 | I3: 0 | J3: 0 | K3: 0 | L3: 0 | M3: 0 | N3: 0 | O3: 0 | P3: 0 | Q3: 0 | R3: 0
B4: A30C80000M | C4: 24hs | D4: ARS | E4: 0 | F4: 0 | G4: 0 | H4: 0 | I4: 0 | J4: 0 | K4: 0 | L4: 0 | M4: 0 | N4: 0 | O4: 0 | P4: 0 | Q4: 0 | R4: 0
B5: A30C82000A | C5: 24hs | D5: ARS | E5: 0 | F5: 0 | G5: 0 | H5: 0 | I5: 0 | J5: 0 | K5: 0 | L5: 0 | M5: 0 | N5: 0 | O5: 0 | P5: 0 | Q5: 0 | R5: 0
B6: A30C82000F | C6: 24hs | D6: ARS | E6: 0 | F6: 0 | G6: 0 | H6: 0 | I6: 0 | J6: 0 | K6: 0 | L6: 0 | M6: 0 | N6: 0 | O6: 0 | P6: 0 | Q6: 0 | R6: 0
B7: A30C82000M | C7: 24hs | D7: ARS | E7: 0 | F7: 0 | G7: 0 | H7: 0 | I7: 0 | J7: 0 | K7: 0 | L7: 0 | M7: 0 | N7: 0 | O7: 0 | P7: 0 | Q7: 0 | R7: 0
B8: A30C84000A | C8: 24hs | D8: ARS | E8: 0 | F8: 0 | G8: 0 | H8: 0 | I8: 0 | J8: 0 | K8: 0 | L8: 0 | M8: 0 | N8: 0 | O8: 0 | P8: 0 | Q8: 0 | R8: 0
B9: A30C84000F | C9: 24hs | D9: ARS | E9: 0 | F9: 0 | G9: 0 | H9: 0 | I9: 0 | J9: 0 | K9: 0 | L9: 0 | M9: 0 | N9: 0 | O9: 0 | P9: 0 | Q9: 0 | R9: 0
B10: A30C84000M | C10: 24hs | D10: ARS | E10: 0 | F10: 0 | G10: 0 | H10: 0 | I10: 0 | J10: 0 | K10: 0 | L10: 0 | M10: 0 | N10: 0 | O10: 0 | P10: 0 | Q10: 0 | R10: 0
B11: A30C86000A | C11: 24hs | D11: ARS | E11: 0 | F11: 0 | G11: 0 | H11: 0 | I11: 0 | J11: 0 | K11: 0 | L11: 0 | M11: 0 | N11: 0 | O11: 0 | P11: 0 | Q11: 0 | R11: 0
B12: A30C86000F | C12: 24hs | D12: ARS | E12: 0 | F12: 0 | G12: 0 | H12: 0 | I12: 0 | J12: 0 | K12: 0 | L12: 0 | M12: 0 | N12: 0 | O12: 0 | P12: 0 | Q12: 0 | R12: 0
B13: A30C86000M | C13: 24hs | D13: ARS | E13: 0 | F13: 0 | G13: 0 | H13: 0 | I13: 0 | J13: 0 | K13: 0 | L13: 0 | M13: 0 | N13: 0 | O13: 0 | P13: 0 | Q13: 0 | R13: 0
... B212: ALUC750.FE | C212: 24hs | D212: ARS | E212: 0 | F212: 0 | G212: 0 | H212: 0 | I212: 0 | J212: 0 | K212: 0 | L212: 0 | M212: 0 | N212: 0 | O212: 0 | P212: 0 | Q212: 0 | R212: 0
B213: ALUC79704A | C213: 24hs | D213: ARS | E213: 20 | F213: 220 | G213: 247.53 | H213: 2 | I213: 260.56 | J213: 250.03 | K213: 260.56 | L213: 250.03 | M213: 0 | N213: 0 | O213: 10 | P213: 255295 | Q213: 255.295 | R213: 0 | S213: 11:34:58
B214: ALUC79704F | C214: 24hs | D214: ARS | E214: 10 | F214: 198 | G214: 207.11 | H214: 2 | I214: 204.75 | J214: 204.75 | K214: 204.75 | L214: 204.75 | M214: 189.067 | N214: 0.0829 | O214: 2 | P214: 40950 | Q214: 204.75 | R214: 0 | S214: 12:04:28
B215: ALUC800.AB | C215: 24hs | D215: ARS | E215: 0 | F215: 0 | G215: 0 | H215: 0 | I215: 0 | J215: 0 | K215: 0 | L215: 0 | M215: 0 | N215: 0 | O215: 0 | P215: 0 | Q215: 0 | R215: 0
B216: ALUC800.FE | C216: 24hs | D216: ARS | E216: 0 | F216: 0 | G216: 0 | H216: 0 | I216: 0 | J216: 0 | K216: 0 | L216: 0 | M216: 0 | N216: 0 | O216: 0 | P216: 0 | Q216: 0 | R216: 0
B217: ALUC800.JU | C217: 24hs | D217: ARS | E217: 0 | F217: 0 | G217: 0 | H217: 0 | I217: 0 | J217: 0 | K217: 0 | L217: 0 | M217: 0 | N217: 0 | O217: 0 | P217: 0 | Q217: 0 | R217: 0
B218: ALUC800.MA | C218: 24hs | D218: ARS | E218: 0 | F218: 0 | G218: 0 | H218: 0 | I218: 0 | J218: 0 | K218: 0 | L218: 0 | M218: 0 | N218: 0 | O218: 0 | P218: 0 | Q218: 0 | R218: 0
B219: ALUC84704A | C219: 24hs | D219: ARS | E219: 20 | F219: 205 | G219: 230 | H219: 39 | I219: 0 | J219: 0 | K219: 0 | L219: 0 | M219: 220 | N219: 0 | O219: 0 | P219: 0 | Q219: 0 | R219: 0
B220: ALUC84704F | C220: 24hs | D220: ARS | E220: 10 | F220: 148 | G220: 151.25 | H220: 5 | I220: 151.25 | J220: 151.25 | K220: 151.25 | L220: 151.25 | M220: 132.624 | N220: 0.1404 | O220: 790 | P220: 11948750 | Q220: 151.25 | R220: 0 | S220: 12:35:22
B221: ALUC850.AB | C221: 24hs | D221: ARS | E221: 0 | F221: 0 | G221: 0 | H221: 0 | I221: 0 | J221: 0 | K221: 0 | L221: 0 | M221: 0 | N221: 0 | O221: 0 | P221: 0 | Q221: 0 | R221: 0
B222: ALUC850.FE | C222: 24hs | D222: ARS | E222: 0 | F222: 0 | G222: 0 | H222: 0 | I222: 0 | J222: 0 | K222: 0 | L222: 0 | M222: 0 | N222: 0 | O222: 0 | P222: 0 | Q222: 0 | R222: 0
B223: ALUC850.JU | C223: 24hs | D223: ARS | E223: 0 | F223: 0 | G223: 0 | H223: 0 | I223: 0 | J223: 0 | K223: 0 | L223: 0 | M223: 0 | N223: 0 | O223: 0 | P223: 0 | Q223: 0 | R223: 0
B224: ALUC850.MA | C224: 24hs | D224: ARS | E224: 0 | F224: 0 | G224: 0 | H224: 0 | I224: 0 | J224: 0 | K224: 0 | L224: 0 | M224: 0 | N224: 0 | O224: 0 | P224: 0 | Q224: 0 | R224: 0
B225: ALUC89704F | C225: 24hs | D225: ARS | E225: 5 | F225: 85 | G225: 0 | H225: 0 | I225: 0 | J225: 0 | K225: 0 | L225: 0 | M225: 95 | N225: 0 | O225: 0 | P225: 0 | Q225: 0 | R225: 0
B226: ALUC900.AB | C226: 24hs | D226: ARS | E226: 0 | F226: 0 | G226: 0 | H226: 0 | I226: 0 | J226: 0 | K226: 0 | L226: 0 | M226: 0 | N226: 0 | O226: 0 | P226: 0 | Q226: 0 | R226: 0
B227: ALUC900.FE | C227: 24hs | D227: ARS | E227: 0 | F227: 0 | G227: 0 | H227: 0 | I227: 0 | J227: 0 | K227: 0 | L227: 0 | M227: 0 | N227: 0 | O227: 0 | P227: 0 | Q227: 0 | R227: 0
B228: ALUC900.JU | C228: 24hs | D228: ARS | E228: 0 | F228: 0 | G228: 0 | H228: 0 | I228: 0 | J228: 0 | K228: 0 | L228: 0 | M228: 0 | N228: 0 | O228: 0 | P228: 0 | Q228: 0 | R228: 0
B229: ALUC900.MA | C229: 24hs | D229: ARS | E229: 0 | F229: 0 | G229: 0 | H229: 0 | I229: 0 | J229: 0 | K229: 0 | L229: 0 | M229: 0 | N229: 0 | O229: 0 | P229: 0 | Q229: 0 | R229: 0
B230: ALUC94704F | C230: 24hs | D230: ARS | E230: 10 | F230: 48 | G230: 80 | H230: 50 | I230: 60 | J230: 60 | K230: 60 | L230: 60 | M230: 63 | N230: -0.0476 | O230: 4 | P230: 24000 | Q230: 60 | R230: 0 | S230: 11:44:31
B231: ALUC950.AB | C231: 24hs | D231: ARS | E231: 0 | F231: 0 | G231: 0 | H231: 0 | I231: 0 | J231: 0 | K231: 0 | L231: 0 | M231: 0 | N231: 0 | O231: 0 | P231: 0 | Q231: 0 | R231: 0
B232: ALUC950.FE | C232: 24hs | D232: ARS | E232: 0 | F232: 0 | G232: 0 | H232: 0 | I232: 0 | J232: 0 | K232: 0 | L232: 0 | M232: 0 | N232: 0 | O232: 0 | P232: 0 | Q232: 0 | R232: 0
B233: ALUC950.JU | C233: 24hs | D233: ARS | E233: 0 | F233: 0 | G233: 0 | H233: 0 | I233: 0 | J233: 0 | K233: 0 | L233: 0 | M233: 0 | N233: 0 | O233: 0 | P233: 0 | Q233: 0 | R233: 0
B234: ALUC950.MA | C234: 24hs | D234: ARS | E234: 0 | F234: 0 | G234: 0 | H234: 0 | I234: 0 | J234: 0 | K234: 0 | L234: 0 | M234: 0 | N234: 0 | O234: 0 | P234: 0 | Q234: 0 | R234: 0
B235: ALUC99704A | C235: 24hs | D235: ARS | E235: 0 | F235: 0 | G235: 0 | H235: 0 | I235: 0 | J235: 0 | K235: 0 | L235: 0 | M235: 0 | N235: 0 | O235: 0 | P235: 0 | Q235: 0 | R235: 0
B236: ALUC99704F | C236: 24hs | D236: ARS | E236: 4 | F236: 8.32 | G236: 63 | H236: 3 | I236: 0 | J236: 0 | K236: 0 | L236: 0 | M236: 29.999 | N236: 0 | O236: 0 | P236: 0 | Q236: 0 | R236: 0
B237: ALUV1000AB | C237: 24hs | D237: ARS | E237: 0 | F237: 0 | G237: 0 | H237: 0 | I237: 0 | J237: 0 | K237: 0 | L237: 0 | M237: 0 | N237: 0 | O237: 0 | P237: 0 | Q237: 0 | R237: 0
B238: ALUV1000FE | C238: 24hs | D238: ARS | E238: 0 | F238: 0 | G238: 0 | H238: 0 | I238: 0 | J238: 0 | K238: 0 | L238: 0 | M238: 0 | N238: 0 | O238: 0 | P238: 0 | Q238: 0 | R238: 0
B239: ALUV1000JU | C239: 24hs | D239: ARS | E239: 3 | F239: 37.8 | G239: 0 | H239: 0 | I239: 0 | J239: 0 | K239: 0 | L239: 0 | M239: 0 | N239: 0 | O239: 0 | P239: 0 | Q239: 0 | R239: 0
B240: ALUV1000MA | C240: 24hs | D240: ARS | E240: 0 | F240: 0 | G240: 0 | H240: 0 | I240: 0 | J240: 0 | K240: 0 | L240: 0 | M240: 0 | N240: 0 | O240: 0 | P240: 0 | Q240: 0 | R240: 0
B241: ALUV1047AB | C241: 24hs | D241: ARS | E241: 3 | F241: 53.2 | G241: 0 | H241: 0 | I241: 0 | J241: 0 | K241: 0 | L241: 0 | M241: 50 | N241: 0 | O241: 0 | P241: 0 | Q241: 0 | R241: 0
B242: ALUV1047FE | C242: 24hs | D242: ARS | E242: 10 | F242: 46 | G242: 94 | H242: 10 | I242: 0 | J242: 0 | K242: 0 | L242: 0 | M242: 32 | N242: 0 | O242: 0 | P242: 0 | Q242: 0 | R242: 0
... B637: BHIC280.FE | C637: 24hs | D637: ARS | E637: 0 | F637: 0 | G637: 0 | H637: 0 | I637: 0 | J637: 0 | K637: 0 | L637: 0 | M637: 0 | N637: 0 | O637: 0 | P637: 0 | Q637: 0 | R637: 0
B638: BHIC28927J | C638: 24hs | D638: ARS | E638: 0 | F638: 0 | G638: 259.999 | H638: 1 | I638: 245 | J638: 245 | K638: 245 | L638: 245 | M638: 250 | N638: -0.02 | O638: 1 | P638: 24500 | Q638: 245 | R638: 0 | S638: 12:04:27
B639: BHIC29471J | C639: 24hs | D639: ARS | E639: 0 | F639: 0 | G639: 0 | H639: 0 | I639: 0 | J639: 0 | K639: 0 | L639: 0 | M639: 0 | N639: 0 | O639: 0 | P639: 0 | Q639: 0 | R639: 0
B640: BHIC300.AB | C640: 24hs | D640: ARS | E640: 0 | F640: 0 | G640: 0 | H640: 0 | I640: 0 | J640: 0 | K640: 0 | L640: 0 | M640: 0 | N640: 0 | O640: 0 | P640: 0 | Q640: 0 | R640: 0
B641: BHIC300.FE | C641: 24hs | D641: ARS | E641: 0 | F641: 0 | G641: 0 | H641: 0 | I641: 0 | J641: 0 | K641: 0 | L641: 0 | M641: 0 | N641: 0 | O641: 0 | P641: 0 | Q641: 0 | R641: 0
B642: BHIC300.JU | C642: 24hs | D642: ARS | E642: 0 | F642: 0 | G642: 0 | H642: 0 | I642: 0 | J642: 0 | K642: 0 | L642: 0 | M642: 0 | N642: 0 | O642: 0 | P642: 0 | Q642: 0 | R642: 0
B643: BHIC300.MA | C643: 24hs | D643: ARS | E643: 0 | F643: 0 | G643: 0 | H643: 0 | I643: 0 | J643: 0 | K643: 0 | L643: 0 | M643: 0 | N643: 0 | O643: 0 | P643: 0 | Q643: 0 | R643: 0
B644: BHIC31456A | C644: 24hs | D644: ARS | E644: 0 | F644: 0 | G644: 0 | H644: 0 | I644: 0 | J644: 0 | K644: 0 | L644: 0 | M644: 0 | N644: 0 | O644: 0 | P644: 0 | Q644: 0 | R644: 0
B645: BHIC320.AB | C645: 24hs | D645: ARS | E645: 0 | F645: 0 | G645: 0 | H645: 0 | I645: 0 | J645: 0 | K645: 0 | L645: 0 | M645: 0 | N645: 0 | O645: 0 | P645: 0 | Q645: 0 | R645: 0
B646: BHIC320.FE | C646: 24hs | D646: ARS | E646: 0 | F646: 0 | G646: 0 | H646: 0 | I646: 0 | J646: 0 | K646: 0 | L646: 0 | M646: 0 | N646: 0 | O646: 0 | P646: 0 | Q646: 0 | R646: 0
B647: BHIC320.JU | C647: 24hs | D647: ARS | E647: 0 | F647: 0 | G647: 0 | H647: 0 | I647: 0 | J647: 0 | K647: 0 | L647: 0 | M647: 0 | N647: 0 | O647: 0 | P647: 0 | Q647: 0 | R647: 0
B648: BHIC320.MA | C648: 24hs | D648: ARS | E648: 0 | F648: 0 | G648: 0 | H648: 0 | I648: 0 | J648: 0 | K648: 0 | L648: 0 | M648: 0 | N648: 0 | O648: 0 | P648: 0 | Q648: 0 | R648: 0
B649: BHIC33456A | C649: 24hs | D649: ARS | E649: 0 | F649: 0 | G649: 0 | H649: 0 | I649: 0 | J649: 0 | K649: 0 | L649: 0 | M649: 0 | N649: 0 | O649: 0 | P649: 0 | Q649: 0 | R649: 0
B650: BHIC340.FE | C650: 24hs | D650: ARS | E650: 0 | F650: 0 | G650: 0 | H650: 0 | I650: 0 | J650: 0 | K650: 0 | L650: 0 | M650: 0 | N650: 0 | O650: 0 | P650: 0 | Q650: 0 | R650: 0
... B695: BHIC520.FE | C695: 24hs | D695: ARS | E695: 0 | F695: 0 | G695: 0 | H695: 0 | I695: 0 | J695: 0 | K695: 0 | L695: 0 | M695: 0 | N695: 0 | O695: 0 | P695: 0 | Q695: 0 | R695: 0
B696: BHIC520.JU | C696: 24hs | D696: ARS | E696: 1 | F696: 70 | G696: 81.8 | H696: 1 | I696: 57.7 | J696: 57.7 | K696: 70 | L696: 70 | M696: 55 | N696: 0.2727 | O696: 2 | P696: 12770 | Q696: 63.85 | R696: 0 | S696: 11:48:56
B697: BHIC520.MA | C697: 24hs | D697: ARS | E697: 0 | F697: 0 | G697: 0 | H697: 0 | I697: 0 | J697: 0 | K697: 0 | L697: 0 | M697: 0 | N697: 0 | O697: 0 | P697: 0 | Q697: 0 | R697: 0
B698: BHIC52927J | C698: 24hs | D698: ARS | E698: 2 | F698: 45 | G698: 94 | H698: 3 | I698: 0 | J698: 0 | K698: 0 | L698: 0 | M698: 47.6 | N698: 0 | O698: 0 | P698: 0 | Q698: 0 | R698: 0
B699: BHIC53471J | C699: 24hs | D699: ARS | E699: 0 | F699: 0 | G699: 0 | H699: 0 | I699: 0 | J699: 0 | K699: 0 | L699: 0 | M699: 0 | N699: 0 | O699: 0 | P699: 0 | Q699: 0 | R699: 0
B700: BHIC540.JU | C700: 24hs | D700: ARS | E700: 0 | F700: 0 | G700: 0 | H700: 0 | I700: 0 | J700: 0 | K700: 0 | L700: 0 | M700: 0 | N700: 0 | O700: 0 | P700: 0 | Q700: 0 | R700: 0
B701: BHIV13413F | C701: 24hs | D701: ARS | E701: 0 | F701: 0 | G701: 0 | H701: 0 | I701: 0 | J701: 0 | K701: 0 | L701: 0 | M701: 0 | N701: 0 | O701: 0 | P701: 0 | Q701: 0 | R701: 0
B702: BHIV13907A | C702: 24hs | D702: ARS | E702: 0 | F702: 0 | G702: 0 | H702: 0 | I702: 0 | J702: 0 | K702: 0 | L702: 0 | M702: 0 | N702: 0 | O702: 0 | P702: 0 | Q702: 0 | R702: 0
B703: BHIV13957F | C703: 24hs | D703: ARS | E703: 0 | F703: 0 | G703: 0 | H703: 0 | I703: 0 | J703: 0 | K703: 0 | L703: 0 | M703: 0 | N703: 0 | O703: 0 | P703: 0 | Q703: 0 | R703: 0
B704: BHIV14451A | C704: 24hs | D704: ARS | E704: 0 | F704: 0 | G704: 0 | H704: 0 | I704: 0 | J704: 0 | K704: 0 | L704: 0 | M704: 0 | N704: 0 | O704: 0 | P704: 0 | Q704: 0 | R704: 0
B705: BHIV14486F | C705: 24hs | D705: ARS | E705: 0 | F705: 0 | G705: 0 | H705: 0 | I705: 0 | J705: 0 | K705: 0 | L705: 0 | M705: 0 | N705: 0 | O705: 0 | P705: 0 | Q705: 0 | R705: 0
B706: BHIV1498AB | C706: 24hs | D706: ARS | E706: 0 | F706: 0 | G706: 0 | H706: 0 | I706: 0 | J706: 0 | K706: 0 | L706: 0 | M706: 0 | N706: 0 | O706: 0 | P706: 0 | Q706: 0 | R706: 0
B707: BHIV15002F | C707: 24hs | D707: ARS | E707: 0 | F707: 0 | G707: 0 | H707: 0 | I707: 0 | J707: 0 | K707: 0 | L707: 0 | M707: 0 | N707: 0 | O707: 0 | P707: 0 | Q707: 0 | R707: 0
B708: BHIV15496A | C708: 24hs | D708: ARS | E708: 0 | F708: 0 | G708: 0 | H708: 0 | I708: 0 | J708: 0 | K708: 0 | L708: 0 | M708: 0 | N708: 0 | O708: 0 | P708: 0 | Q708: 0 | R708: 0
... B1001: BYMC300.AB | C1001: 24hs | D1001: ARS | E1001: 0 | F1001: 0 | G1001: 0 | H1001: 0 | I1001: 0 | J1001: 0 | K1001: 0 | L1001: 0 | M1001: 0 | N1001: 0 | O1001: 0 | P1001: 0 | Q1001: 0 | R1001: 0
B1002: BYMC300.FE | C1002: 24hs | D1002: ARS | E1002: 9 | F1002: 26 | G1002: 47.99 | H1002: 9 | I1002: 26 | J1002: 26 | K1002: 26 | L1002: 26 | M1002: 26.5 | N1002: -0.0188 | O1002: 4 | P1002: 10400 | Q1002: 26 | R1002: 0 | S1002: 12:38:39
B1003: BYMC300.JU | C1003: 24hs | D1003: ARS | E1003: 0 | F1003: 0 | G1003: 0 | H1003: 0 | I1003: 0 | J1003: 0 | K1003: 0 | L1003: 0 | M1003: 0 | N1003: 0 | O1003: 0 | P1003: 0 | Q1003: 0 | R1003: 0
B1004: BYMC310.AB | C1004: 24hs | D1004: ARS | E1004: 25 | F1004: 44 | G1004: 46 | H1004: 81 | I1004: 46 | J1004: 46 | K1004: 46 | L1004: 46 | M1004: 44 | N1004: 0.0454 | O1004: 19 | P1004: 87400 | Q1004: 46 | R1004: 0 | S1004: 10:53:45
B1005: BYMC310.FE | C1005: 24hs | D1005: ARS | E1005: 8 | F1005: 10.58 | G1005: 22 | H1005: 50 | I1005: 0 | J1005: 0 | K1005: 0 | L1005: 0 | M1005: 24.5 | N1005: 0 | O1005: 0 | P1005: 0 | Q1005: 0 | R1005: 0
B1006: BYMC310.JU | C1006: 24hs | D1006: ARS | E1006: 0 | F1006: 0 | G1006: 0 | H1006: 0 | I1006: 0 | J1006: 0 | K1006: 0 | L1006: 0 | M1006: 0 | N1006: 0 | O1006: 0 | P1006: 0 | Q1006: 0 | R1006: 0
B1007: BYMC310.MA | C1007: 24hs | D1007: ARS | E1007: 0 | F1007: 0 | G1007: 0 | H1007: 0 | I1007: 0 | J1007: 0 | K1007: 0 | L1007: 0 | M1007: 0 | N1007: 0 | O1007: 0 | P1007: 0 | Q1007: 0 | R1007: 0
B1008: BYMC320.AB | C1008: 24hs | D1008: ARS | E1008: 0 | F1008: 0 | G1008: 0 | H1008: 0 | I1008: 0 | J1008: 0 | K1008: 0 | L1008: 0 | M1008: 0 | N1008: 0 | O1008: 0 | P1008: 0 | Q1008: 0 | R1008: 0
B1009: BYMC320.FE | C1009: 24hs | D1009: ARS | E1009: 10 | F1009: 6 | G1009: 12.99 | H1009: 5 | I1009: 0 | J1009: 0 | K1009: 0 | L1009: 0 | M1009: 11.46 | N1009: 0 | O1009: 0 | P1009: 0 | Q1009: 0 | R1009: 0
B1010: BYMC320.JU | C1010: 24hs | D1010: ARS | E1010: 0 | F1010: 0 | G1010: 0 | H1010: 0 | I1010: 0 | J1010: 0 | K1010: 0 | L1010: 0 | M1010: 0 | N1010: 0 | O1010: 0 | P1010: 0 | Q1010: 0 | R1010: 0
B1011: BYMC320.MA | C1011: 24hs | D1011: ARS | E1011: 0 | F1011: 0 | G1011: 0 | H1011: 0 | I1011: 0 | J1011: 0 | K1011: 0 | L1011: 0 | M1011: 0 | N1011: 0 | O1011: 0 | P1011: 0 | Q1011: 0 | R1011: 0
B1012: BYMC330.AB | C1012: 24hs | D1012: ARS | E1012: 6 | F1012: 13.88 | G1012: 0 | H1012: 0 | I1012: 0 | J1012: 0 | K1012: 0 | L1012: 0 | M1012: 0 | N1012: 0 | O1012: 0 | P1012: 0 | Q1012: 0 | R1012: 0
B1013: BYMC330.FE | C1013: 24hs | D1013: ARS | E1013: 0 | F1013: 0 | G1013: 0 | H1013: 0 | I1013: 0 | J1013: 0 | K1013: 0 | L1013: 0 | M1013: 9 | N1013: 0 | O1013: 0 | P1013: 0 | Q1013: 0 | R1013: 0
B1014: BYMC330.JU | C1014: 24hs | D1014: ARS | E1014: 0 | F1014: 0 | G1014: 0 | H1014: 0 | I1014: 0 | J1014: 0 | K1014: 0 | L1014: 0 | M1014: 0 | N1014: 0 | O1014: 0 | P1014: 0 | Q1014: 0 | R1014: 0
B1015: BYMC330.MA | C1015: 24hs | D1015: ARS | E1015: 0 | F1015: 0 | G1015: 0 | H1015: 0 | I1015: 0 | J1015: 0 | K1015: 0 | L1015: 0 | M1015: 0 | N1015: 0 | O1015: 0 | P1015: 0 | Q1015: 0 | R1015: 0
B1016: BYMC340.AB | C1016: 24hs | D1016: ARS | E1016: 10 | F1016: 20 | G1016: 26.4 | H1016: 252 | I1016: 25 | J1016: 25 | K1016: 25 | L1016: 25 | M1016: 25 | N1016: 0 | O1016: 50 | P1016: 125000 | Q1016: 25 | R1016: 0 | S1016: 10:47:18
B1017: BYMC340.FE | C1017: 24hs | D1017: ARS | E1017: 0 | F1017: 0 | G1017: 0 | H1017: 0 | I1017: 0 | J1017: 0 | K1017: 0 | L1017: 0 | M1017: 3.6 | N1017: 0 | O1017: 0 | P1017: 0 | Q1017: 0 | R1017: 0
B1018: BYMC340.JU | C1018: 24hs | D1018: ARS | E1018: 0 | F1018: 0 | G1018: 0 | H1018: 0 | I1018: 0 | J1018: 0 | K1018: 0 | L1018: 0 | M1018: 0 | N1018: 0 | O1018: 0 | P1018: 0 | Q1018: 0 | R1018: 0
B1019: BYMC340.MA | C1019: 24hs | D1019: ARS | E1019: 0 | F1019: 0 | G1019: 0 | H1019: 0 | I1019: 0 | J1019: 0 | K1019: 0 | L1019: 0 | M1019: 0 | N1019: 0 | O1019: 0 | P1019: 0 | Q1019: 0 | R1019: 0
B1020: BYMC350.AB | C1020: 24hs | D1020: ARS | E1020: 0 | F1020: 0 | G1020: 0 | H1020: 0 | I1020: 0 | J1020: 0 | K1020: 0 | L1020: 0 | M1020: 30 | N1020: 0 | O1020: 0 | P1020: 0 | Q1020: 0 | R1020: 0
B1021: BYMC350.FE | C1021: 24hs | D1021: ARS | E1021: 54 | F1021: 0.6 | G1021: 7 | H1021: 5 | I1021: 0 | J1021: 0 | K1021: 0 | L1021: 0 | M1021: 10 | N1021: 0 | O1021: 0 | P1021: 0 | Q1021: 0 | R1021: 0
B1022: BYMC350.JU | C1022: 24hs | D1022: ARS | E1022: 5 | F1022: 17.95 | G1022: 0 | H1022: 0 | I1022: 0 | J1022: 0 | K1022: 0 | L1022: 0 | M1022: 0 | N1022: 0 | O1022: 0 | P1022: 0 | Q1022: 0 | R1022: 0
B1023: BYMC350.MA | C1023: 24hs | D1023: ARS | E1023: 0 | F1023: 0 | G1023: 20 | H1023: 110 | I1023: 0 | J1023: 0 | K1023: 0 | L1023: 0 | M1023: 0 | N1023: 0 | O1023: 0 | P1023: 0 | Q1023: 0 | R1023: 0
B1024: BYMC360.AB | C1024: 24hs | D1024: ARS | E1024: 0 | F1024: 0 | G1024: 0 | H1024: 0 | I1024: 0 | J1024: 0 | K1024: 0 | L1024: 0 | M1024: 15 | N1024: 0 | O1024: 0 | P1024: 0 | Q1024: 0 | R1024: 0
B1025: BYMC360.FE | C1025: 24hs | D1025: ARS | E1025: 101 | F1025: 0.3 | G1025: 1 | H1025: 1999 | I1025: 0 | J1025: 0 | K1025: 0 | L1025: 0 | M1025: 6 | N1025: 0 | O1025: 0 | P1025: 0 | Q1025: 0 | R1025: 0
B1026: BYMC360.JU | C1026: 24hs | D1026: ARS | E1026: 6 | F1026: 15.04 | G1026: 0 | H1026: 0 | I1026: 0 | J1026: 0 | K1026: 0 | L1026: 0 | M1026: 0 | N1026: 0 | O1026: 0 | P1026: 0 | Q1026: 0 | R1026: 0
B1027: BYMC360.MA | C1027: 24hs | D1027: ARS | E1027: 0 | F1027: 0 | G1027: 0 | H1027: 0 | I1027: 0 | J1027: 0 | K1027: 0 | L1027: 0 | M1027: 0 | N1027: 0 | O1027: 0 | P1027: 0 | Q1027: 0 | R1027: 0
B1028: BYMC370.AB | C1028: 24hs | D1028: ARS | E1028: 15 | F1028: 2.192 | G1028: 18 | H1028: 20 | I1028: 0 | J1028: 0 | K1028: 0 | L1028: 0 | M1028: 0 | N1028: 0 | O1028: 0 | P1028: 0 | Q1028: 0 | R1028: 0
...

Sheet Caucho
A1: {=_xll.PanelCaucionesBD("S")} -> CAUCIONES | B1: SIMBOLO | C1: ESPECIE | D1: MONEDA | E1: PLAZO | F1: VTO. | G1: TASA | H1: CANT.OPER | I1: MONTO | J1: M.TOM | K1: T.TOM | L1: T.COL | M1: M.COL | N1: VWAP
B2: DOLAR-0203-U-CT-USD | C2: DOLAR | D2: USD | E2: 18 | F2: 2026-03-02 | G2: 0 | H2: 0 | I2: 0 | J2: 0 | K2: 0 | L2: 0.035 | M2: 700 | N2: 0
B3: DOLAR-0206-U-CT-USD | C3: DOLAR | D3: USD | E3: 110 | F3: 2026-06-02 | G3: 0 | H3: 0 | I3: 0 | J3: 0 | K3: 0 | L3: 0 | M3: 0 | N3: 0
B4: DOLAR-0303-U-CT-USD | C4: DOLAR | D4: USD | E4: 19 | F4: 2026-03-03 | G4: 0 | H4: 0 | I4: 0 | J4: 105000 | K4: 0.008 | L4: 0.03 | M4: 119473 | N4: 0
B5: DOLAR-0403-U-CT-USD | C5: DOLAR | D5: USD | E5: 20 | F5: 2026-03-04 | G5: 0.01 | H5: 1 | I5: 2001.1 | J5: 48000 | K5: 0.01 | L5: 0.03 | M5: 84343 | N5: 0.01
B6: DOLAR-0405-U-CT-USD | C6: DOLAR | D6: USD | E6: 81 | F6: 2026-05-04 | G6: 0 | H6: 0 | I6: 0 | J6: 0 | K6: 0 | L6: 0 | M6: 0 | N6: 0
B7: DOLAR-0406-U-CT-USD | C7: DOLAR | D7: USD | E7: 112 | F7: 2026-06-04 | G7: 0 | H7: 0 | I7: 0 | J7: 0 | K7: 0 | L7: 0 | M7: 0 | N7: 0
B8: DOLAR-0503-U-CT-USD | C8: DOLAR | D8: USD | E8: 21 | F8: 2026-03-05 | G8: 0.025 | H8: 1 | I8: 1007.45 | J8: 0 | K8: 0 | L8: 0.035 | M8: 17286 | N8: 0.025
B9: DOLAR-0505-U-CT-USD | C9: DOLAR | D9: USD | E9: 82 | F9: 2026-05-05 | G9: 0 | H9: 0 | I9: 0 | J9: 0 | K9: 0 | L9: 0 | M9: 0 | N9: 0
B10: DOLAR-0506-U-CT-USD | C10: DOLAR | D10: USD | E10: 113 | F10: 2026-06-05 | G10: 0 | H10: 0 | I10: 0 | J10: 0 | K10: 0 | L10: 0 | M10: 0 | N10: 0
B11: DOLAR-0603-U-CT-USD | C11: DOLAR | D11: USD | E11: 22 | F11: 2026-03-06 | G11: 0.03 | H11: 1 | I11: 500.9 | J11: 4111 | K11: 0.017 | L11: 0.028 | M11: 16766 | N11: 0.03
B12: DOLAR-0604-U-CT-USD | C12: DOLAR | D12: USD | E12: 53 | F12: 2026-04-06 | G12: 0 | H12: 0 | I12: 0 | J12: 0 | K12: 0 | L12: 0 | M12: 0 | N12: 0
B13: DOLAR-0605-U-CT-USD | C13: DOLAR | D13: USD | E13: 83 | F13: 2026-05-06 | G13: 0 | H13: 0 | I13: 0 | J13: 0 | K13: 0 | L13: 0 | M13: 0 | N13: 0
... B147: PESOS-3103-U-CT-ARS | C147: PESOS | D147: ARS | E147: 50 | F147: 2026-03-31 | G147: 0 | H147: 0 | I147: 0 | J147: 30000000 | K147: 0.2 | L147: 0 | M147: 0 | N147: 0

Sheet ONs Argentina
G1: Comision | H1: 1
G2: Dia de liquidacion | H2: =Main!D1 -> 46068
B4: Empresa | C4: Ticker | D4: TIR | E4: Precio | F4: Sin comision | G4: MD | H4: Vto | I4: Ask volume | J4: Total volume | K4: Ley | L4: Periodicidad | M4: Lamina minima | N4: Tipo
B5: Central Puerto | C5: NPCAD | D5: =NPCAD!K4 -> #NUM! | E5: =F5*$H$1 -> 0 | F5: {=_xll.PrecioBD(ONs_NY_2[[#This Row],[Ticker]],24,"ASK","N")} -> 0 | G5: =NPCAD!K3 -> #NUM! | I5: {=_xll.PrecioBD(ONs_NY_2[[#This Row],[Ticker]],24,"QUANTITY ASK","N")} -> 0 | J5: {=_xll.PrecioBD(ONs_NY_2[[#This Row],[Ticker]],24,"VOLUME AMOUNT","N")} -> 0 | U5: Genneia | V5: GN40D | W5: =GN40D!AQ4 -> 0 | X5: =Y5*$H$1 -> #REF! | Y5: =VLOOKUP(V5,#REF!,5,0) -> #REF! | Z5: =GN40D!AQ3 -> 0 | AA5: =VLOOKUP(V5,#REF!,3,0) -> #REF! | AB5: Argentina | AC5: =VLOOKUP(V5,#REF!,9,0) -> #REF! | AD5: 1 | AE5: =VLOOKUP(V5,#REF!,10,0) -> #REF! | AF5: =NOMINAL(W5,2) -> #NUM! | AG5: =(1 +W5 )^(1/12) - 1 -> 0
B6: Tecpetrol | C6: TTC7D | D6: =TTC7D!K4 -> #NUM! | E6: =F6*$H$1 -> 0 | F6: {=_xll.PrecioBD(ONs_NY_2[[#This Row],[Ticker]],24,"ASK","N")} -> 0 | G6: =TTC7D!K3 -> #NUM! | I6: {=_xll.PrecioBD(ONs_NY_2[[#This Row],[Ticker]],24,"QUANTITY ASK","N")} -> 0 | J6: {=_xll.PrecioBD(ONs_NY_2[[#This Row],[Ticker]],24,"VOLUME AMOUNT","N")} -> 0
B7: PCR | C7: PQCSD | D7: =PQCSD!K4 -> 0.080271211 | E7: =F7*$H$1 -> 104.5 | F7: {=_xll.PrecioBD(ONs_NY_2[[#This Row],[Ticker]],24,"ASK","N")} -> 104.5 | G7: =PQCSD!K3 -> 3.9113121 | I7: {=_xll.PrecioBD(ONs_NY_2[[#This Row],[Ticker]],24,"QUANTITY ASK","N")} -> 586 | J7: {=_xll.PrecioBD(ONs_NY_2[[#This Row],[Ticker]],24,"VOLUME AMOUNT","N")} -> 23560.29
B8: CNH Industrial | C8: CICAD | D8: =CICAD!K4 -> 0.074706891 | E8: =F8*$H$1 -> 102.95 | F8: {=_xll.PrecioBD(ONs_NY_2[[#This Row],[Ticker]],24,"ASK","N")} -> 102.95 | G8: =CICAD!K3 -> 2.0445698 | I8: {=_xll.PrecioBD(ONs_NY_2[[#This Row],[Ticker]],24,"QUANTITY ASK","N")} -> 5887 | J8: {=_xll.PrecioBD(ONs_NY_2[[#This Row],[Ticker]],24,"VOLUME AMOUNT","N")} -> 2019.31
B9: Edenor | C9: DNC5D | D9: =DNC5D!K4 -> 0.077970263 | E9: =F9*$H$1 -> 104.35 | F9: {=_xll.PrecioBD(ONs_NY_2[[#This Row],[Ticker]],24,"ASK","N")} -> 104.35 | G9: =DNC5D!K3 -> 2.2046588 | I9: {=_xll.PrecioBD(ONs_NY_2[[#This Row],[Ticker]],24,"QUANTITY ASK","N")} -> 2243 | J9: {=_xll.PrecioBD(ONs_NY_2[[#This Row],[Ticker]],24,"VOLUME AMOUNT","N")} -> 38683
B10: Oiltanking | C10: OT42D | D10: =OT42D!K4 -> 0.069239083 | E10: =F10*$H$1 -> 104.9 | F10: {=_xll.PrecioBD(ONs_NY_2[[#This Row],[Ticker]],24,"ASK","N")} -> 104.9 | G10: =OT42D!K3 -> 3.324312 | I10: {=_xll.PrecioBD(ONs_NY_2[[#This Row],[Ticker]],24,"QUANTITY ASK","N")} -> 643 | J10: {=_xll.PrecioBD(ONs_NY_2[[#This Row],[Ticker]],24,"VOLUME AMOUNT","N")} -> 1806.83
B11: Pecom | C11: MCC2D | D11: =MCC2D!K4 -> 0.072359821 | E11: =F11*$H$1 -> 102 | F11: {=_xll.PrecioBD(ONs_NY_2[[#This Row],[Ticker]],24,"ASK","N")} -> 102 | G11: =MCC2D!K3 -> 1.197278 | I11: {=_xll.PrecioBD(ONs_NY_2[[#This Row],[Ticker]],24,"QUANTITY ASK","N")} -> 361 | J11: {=_xll.PrecioBD(ONs_NY_2[[#This Row],[Ticker]],24,"VOLUME AMOUNT","N")} -> 1463.69
B12: YPF | C12: YM39D | D12: =YM39D!K4 -> 0.069491431 | E12: =F12*$H$1 -> 108.25 | F12: {=_xll.PrecioBD(ONs_NY_2[[#This Row],[Ticker]],24,"ASK","N")} -> 108.25 | G12: =YM39D!K3 -> 3.6456075 | I12: {=_xll.PrecioBD(ONs_NY_2[[#This Row],[Ticker]],24,"QUANTITY ASK","N")} -> 13658 | J12: {=_xll.PrecioBD(ONs_NY_2[[#This Row],[Ticker]],24,"VOLUME AMOUNT","N")} -> 369801.7
B13: CNH Industrial | C13: CIC9D | D13: =CIC9D!K4 -> 0.078243551 | E13: =F13*$H$1 -> 102.6 | F13: {=_xll.PrecioBD(ONs_NY_2[[#This Row],[Ticker]],24,"ASK","N")} -> 102.6 | G13: =CIC9D!K3 -> 1.1577742 | I13: {=_xll.PrecioBD(ONs_NY_2[[#This Row],[Ticker]],24,"QUANTITY ASK","N")} -> 400 | J13: {=_xll.PrecioBD(ONs_NY_2[[#This Row],[Ticker]],24,"VOLUME AMOUNT","N")} -> 20.28
B14: Oleoductos del Valle | C14: OLC6D | D14: =OLC6D!K4 -> 0.069483241 | E14: =F14*$H$1 -> 103.4 | F14: {=_xll.PrecioBD(ONs_NY_2[[#This Row],[Ticker]],24,"ASK","N")} -> 103.4 | G14: =OLC6D!K3 -> 2.853648 | I14: {=_xll.PrecioBD(ONs_NY_2[[#This Row],[Ticker]],24,"QUANTITY ASK","N")} -> 1999 | J14: {=_xll.PrecioBD(ONs_NY_2[[#This Row],[Ticker]],24,"VOLUME AMOUNT","N")} -> 1.03
B15: Edenor | C15: DNC3D | D15: =DNC3D!K4 -> 0.063942155 | E15: =F15*$H$1 -> 104.8 | F15: {=_xll.PrecioBD(ONs_NY_2[[#This Row],[Ticker]],24,"ASK","N")} -> 104.8 | G15: =DNC3D!K3 -> 0.72155423 | I15: {=_xll.PrecioBD(ONs_NY_2[[#This Row],[Ticker]],24,"QUANTITY ASK","N")} -> 3732 | J15: {=_xll.PrecioBD(ONs_NY_2[[#This Row],[Ticker]],24,"VOLUME AMOUNT","N")} -> 37435.61
B16: Pluspetrol | C16: PLC2D | D16: =PLC2D!K4 -> 0.065168622 | E16: =F16*$H$1 -> 106 | F16: {=_xll.PrecioBD(ONs_NY_2[[#This Row],[Ticker]],24,"ASK","N")} -> 106 | G16: =PLC2D!K3 -> 3.3224971 | I16: {=_xll.PrecioBD(ONs_NY_2[[#This Row],[Ticker]],24,"QUANTITY ASK","N")} -> 151867 | J16: {=_xll.PrecioBD(ONs_NY_2[[#This Row],[Ticker]],24,"VOLUME AMOUNT","N")} -> 7303.64
B17: John Deere | C17: HJCID | D17: =HJCID!K4 -> 0.062810048 | E17: =F17*$H$1 -> 103.25 | F17: {=_xll.PrecioBD(ONs_NY_2[[#This Row],[Ticker]],24,"ASK","N")} -> 103.25 | G17: =HJCID!K3 -> 1.1871123 | I17: {=_xll.PrecioBD(ONs_NY_2[[#This Row],[Ticker]],24,"QUANTITY ASK","N")} -> 1200 | J17: {=_xll.PrecioBD(ONs_NY_2[[#This Row],[Ticker]],24,"VOLUME AMOUNT","N")} -> 0
B18: IRSA | C18: IRCOD | D18: =IRCOD!K4 -> 0.064771667 | E18: =F18*$H$1 -> 103.3 | F18: {=_xll.PrecioBD(ONs_NY_2[[#This Row],[Ticker]],24,"ASK","N")} -> 103.3 | G18: =IRCOD!K3 -> 3.191004 | I18: {=_xll.PrecioBD(ONs_NY_2[[#This Row],[Ticker]],24,"QUANTITY ASK","N")} -> 54 | J18: {=_xll.PrecioBD(ONs_NY_2[[#This Row],[Ticker]],24,"VOLUME AMOUNT","N")} -> 33925.2
B19: Pan American | C19: PN36D | D19: =PN36D!K4 -> 0.066803226 | E19: =F19*$H$1 -> 105.05 | F19: {=_xll.PrecioBD(ONs_NY_2[[#This Row],[Ticker]],24,"ASK","N")} -> 105.05 | G19: =PN36D!K3 -> 4.5838272 | I19: {=_xll.PrecioBD(ONs_NY_2[[#This Row],[Ticker]],24,"QUANTITY ASK","N")} -> 517 | J19: {=_xll.PrecioBD(ONs_NY_2[[#This Row],[Ticker]],24,"VOLUME AMOUNT","N")} -> 36630.06
B20: Oleoductos del Valle | C20: OLC5D | D20: =OLC5D!K4 -> 0.062944308 | E20: =F20*$H$1 -> 105 | F20: {=_xll.PrecioBD(ONs_NY_2[[#This Row],[Ticker]],24,"ASK","N")} -> 105 | G20: =OLC5D!K3 -> 2.0804195 | I20: {=_xll.PrecioBD(ONs_NY_2[[#This Row],[Ticker]],24,"QUANTITY ASK","N")} -> 442 | J20: {=_xll.PrecioBD(ONs_NY_2[[#This Row],[Ticker]],24,"VOLUME AMOUNT","N")} -> 1945.42
B21: Pan American | C21: PN35D | D21: =PN35D!K4 -> 0.062485078 | E21: =F21*$H$1 -> 105.4 | F21: {=_xll.PrecioBD(ONs_NY_2[[#This Row],[Ticker]],24,"ASK","N")} -> 105.4 | G21: =PN35D!K3 -> 3.0860682 | I21: {=_xll.PrecioBD(ONs_NY_2[[#This Row],[Ticker]],24,"QUANTITY ASK","N")} -> 1444 | J21: {=_xll.PrecioBD(ONs_NY_2[[#This Row],[Ticker]],24,"VOLUME AMOUNT","N")} -> 37075.01
B22: Central Puerto | C22: NPCCD | D22: =NPCCD!K4 -> 0.064410672 | E22: =F22*$H$1 -> 108.95 | F22: {=_xll.PrecioBD(ONs_NY_2[[#This Row],[Ticker]],24,"ASK","N")} -> 108.95 | G22: =NPCCD!K3 -> 2.9532458 | I22: {=_xll.PrecioBD(ONs_NY_2[[#This Row],[Ticker]],24,"QUANTITY ASK","N")} -> 1028 | J22: {=_xll.PrecioBD(ONs_NY_2[[#This Row],[Ticker]],24,"VOLUME AMOUNT","N")} -> 1174.94
B23: Tecpetrol | C23: TTC9D | D23: =TTC9D!K4 -> 0.059581831 | E23: =F23*$H$1 -> 105.15 | F23: {=_xll.PrecioBD(ONs_NY_2[[#This Row],[Ticker]],24,"ASK","N")} -> 105.15 | G23: =TTC9D!K3 -> 3.1739941 | I23: {=_xll.PrecioBD(ONs_NY_2[[#This Row],[Ticker]],24,"QUANTITY ASK","N")} -> 196959 | J23: {=_xll.PrecioBD(ONs_NY_2[[#This Row],[Ticker]],24,"VOLUME AMOUNT","N")} -> 5508.17
B24: Vista Energy | C24: VSCRD | D24: =VSCRD!K4 -> 0.066487238 | E24: =F24*$H$1 -> 107.05 | F24: {=_xll.PrecioBD(ONs_NY_2[[#This Row],[Ticker]],24,"ASK","N")} -> 107.05 | G24: =VSCRD!K3 -> 3.7897722 | I24: {=_xll.PrecioBD(ONs_NY_2[[#This Row],[Ticker]],24,"QUANTITY ASK","N")} -> 1000 | J24: {=_xll.PrecioBD(ONs_NY_2[[#This Row],[Ticker]],24,"VOLUME AMOUNT","N")} -> 59349.18
B25: YPF | C25: YM40D | D25: =YM40D!K4 -> 0.059923461 | E25: =F25*$H$1 -> 105.45 | F25: {=_xll.PrecioBD(ONs_NY_2[[#This Row],[Ticker]],24,"ASK","N")} -> 105.45 | G25: =YM40D!K3 -> 2.2566844 | I25: {=_xll.PrecioBD(ONs_NY_2[[#This Row],[Ticker]],24,"QUANTITY ASK","N")} -> 901 | J25: {=_xll.PrecioBD(ONs_NY_2[[#This Row],[Ticker]],24,"VOLUME AMOUNT","N")} -> 6102.02
B26: Pluspetrol | C26: PLC3D | D26: =PLC3D!K4 -> 0.051562974 | E26: =F26*$H$1 -> 104.75 | F26: {=_xll.PrecioBD(ONs_NY_2[[#This Row],[Ticker]],24,"ASK","N")} -> 104.75 | G26: =PLC3D!K3 -> 2.0265942 | I26: {=_xll.PrecioBD(ONs_NY_2[[#This Row],[Ticker]],24,"QUANTITY ASK","N")} -> 1000 | J26: {=_xll.PrecioBD(ONs_NY_2[[#This Row],[Ticker]],24,"VOLUME AMOUNT","N")} -> 6066.68
B27: Profertil | C27: PFC2D | D27: =PFC2D!K4 -> 0.060127088 | E27: =F27*$H$1 -> 102.55 | F27: {=_xll.PrecioBD(ONs_NY_2[[#This Row],[Ticker]],24,"ASK","N")} -> 102.55 | G27: =PFC2D!K3 -> 1.3174273 | I27: {=_xll.PrecioBD(ONs_NY_2[[#This Row],[Ticker]],24,"QUANTITY ASK","N")} -> 3571 | J27: {=_xll.PrecioBD(ONs_NY_2[[#This Row],[Ticker]],24,"VOLUME AMOUNT","N")} -> 1975.19
B28: Telecom | C28: TLCOD | D28: =TLCOD!K4 -> 0.063440326 | E28: =F28*$H$1 -> 103.4 | F28: {=_xll.PrecioBD(ONs_NY_2[[#This Row],[Ticker]],24,"ASK","N")} -> 103.4 | G28: =TLCOD!K3 -> 2.4694928 | I28: {=_xll.PrecioBD(ONs_NY_2[[#This Row],[Ticker]],24,"QUANTITY ASK","N")} -> 1845 | J28: {=_xll.PrecioBD(ONs_NY_2[[#This Row],[Ticker]],24,"VOLUME AMOUNT","N")} -> 11187.98
B29: Vista Energy | C29: VSCPD | D29: =VSCPD!K4 -> 0.06054078 | E29: =F29*$H$1 -> 106.85 | F29: {=_xll.PrecioBD(ONs_NY_2[[#This Row],[Ticker]],24,"ASK","N")} -> 106.85 | G29: =VSCPD!K3 -> 2.1741238 | I29: {=_xll.PrecioBD(ONs_NY_2[[#This Row],[Ticker]],24,"QUANTITY ASK","N")} -> 4132 | J29: {=_xll.PrecioBD(ONs_NY_2[[#This Row],[Ticker]],24,"VOLUME AMOUNT","N")} -> 59.84
B30: Pan American | C30: PN41D | D30: =PN41D!K4 -> 0.063427529 | E30: =F30*$H$1 -> 107.45 | F30: {=_xll.PrecioBD(ONs_NY_2[[#This Row],[Ticker]],24,"ASK","N")} -> 107.45 | G30: =PN41D!K3 -> 2.9790174 | I30: {=_xll.PrecioBD(ONs_NY_2[[#This Row],[Ticker]],24,"QUANTITY ASK","N")} -> 2198 | J30: {=_xll.PrecioBD(ONs_NY_2[[#This Row],[Ticker]],24,"VOLUME AMOUNT","N")} -> 30139.36
B31: OilTanking | C31: OTS2D | D31: =OTS2D!K4 -> 0.058720216 | E31: =F31*$H$1 -> 101.85 | F31: {=_xll.PrecioBD(ONs_NY_2[[#This Row],[Ticker]],24,"ASK","N")} -> 101.85 | G31: =OTS2D!K3 -> 1.1125311 | I31: {=_xll.PrecioBD(ONs_NY_2[[#This Row],[Ticker]],24,"QUANTITY ASK","N")} -> 755 | J31: {=_xll.PrecioBD(ONs_NY_2[[#This Row],[Ticker]],24,"VOLUME AMOUNT","N")} -> 0
B32: Arcor | C32: RCCRD | D32: =RCCRD!K4 -> 0.04593794 | E32: =F32*$H$1 -> 104.4 | F32: {=_xll.PrecioBD(ONs_NY_2[[#This Row],[Ticker]],24,"ASK","N")} -> 104.4 | G32: =RCCRD!K3 -> 1.1564905 | I32: {=_xll.PrecioBD(ONs_NY_2[[#This Row],[Ticker]],24,"QUANTITY ASK","N")} -> 2000 | J32: {=_xll.PrecioBD(ONs_NY_2[[#This Row],[Ticker]],24,"VOLUME AMOUNT","N")} -> 6327.97
B33: Scania | C33: SBC1D | D33: =SBC1D!K4 -> 0.053650096 | E33: =F33*$H$1 -> 106 | F33: {=_xll.PrecioBD(ONs_NY_2[[#This Row],[Ticker]],24,"ASK","N")} -> 106 | G33: =SBC1D!K3 -> 0.75490111 | I33: {=_xll.PrecioBD(ONs_NY_2[[#This Row],[Ticker]],24,"QUANTITY ASK","N")} -> 1500 | J33: {=_xll.PrecioBD(ONs_NY_2[[#This Row],[Ticker]],24,"VOLUME AMOUNT","N")} -> 812.09
B34: YPF | C34: YM38D | D34: =YM38D!K4 -> 0.053336343 | E34: =F34*$H$1 -> 103.6 | F34: {=_xll.PrecioBD(ONs_NY_2[[#This Row],[Ticker]],24,"ASK","N")} -> 103.6 | G34: =YM38D!K3 -> 1.3294178 | I34: {=_xll.PrecioBD(ONs_NY_2[[#This Row],[Ticker]],24,"QUANTITY ASK","N")} -> 282 | J34: {=_xll.PrecioBD(ONs_NY_2[[#This Row],[Ticker]],24,"VOLUME AMOUNT","N")} -> 26682.81
B35: Aluar | C35: LMS7D | D35: =LMS7D!K4 -> 0.050817385 | E35: =F35*$H$1 -> 94.85 | F35: {=_xll.PrecioBD(ONs_NY_2[[#This Row],[Ticker]],24,"ASK","N")} -> 94.85 | G35: =LMS7D!K3 -> 1.3138462 | I35: {=_xll.PrecioBD(ONs_NY_2[[#This Row],[Ticker]],24,"QUANTITY ASK","N")} -> 1000 | J35: {=_xll.PrecioBD(ONs_NY_2[[#This Row],[Ticker]],24,"VOLUME AMOUNT","N")} -> 0
B36: YPF | C36: YM41D | D36: =YM41D!K4 -> 0.024837407 | E36: =F36*$H$1 -> 103.75 | F36: {=_xll.PrecioBD(ONs_NY_2[[#This Row],[Ticker]],24,"ASK","N")} -> 103.75 | G36: =YM41D!K3 -> 0.86369055 | I36: {=_xll.PrecioBD(ONs_NY_2[[#This Row],[Ticker]],24,"QUANTITY ASK","N")} -> 1340 | J36: {=_xll.PrecioBD(ONs_NY_2[[#This Row],[Ticker]],24,"VOLUME AMOUNT","N")} -> 639.7
B37: YPF | C37: YM37D | D37: =YM37D!K4 -> 0.049661407 | E37: =F37*$H$1 -> 102.65 | F37: {=_xll.PrecioBD(ONs_NY_2[[#This Row],[Ticker]],24,"ASK","N")} -> 102.65 | G37: =YM37D!K3 -> 1.1525749 | I37: {=_xll.PrecioBD(ONs_NY_2[[#This Row],[Ticker]],24,"QUANTITY ASK","N")} -> 88 | J37: {=_xll.PrecioBD(ONs_NY_2[[#This Row],[Ticker]],24,"VOLUME AMOUNT","N")} -> 9951.37
B38: Camuzzi | C38: ZZC1D | D38: =ZZC1D!K4 -> 0.069887504 | E38: =F38*$H$1 -> 104.9 | F38: {=_xll.PrecioBD(ONs_NY_2[[#This Row],[Ticker]],24,"ASK","N")} -> 104.9 | G38: =ZZC1D!K3 -> 0.93074827 | I38: {=_xll.PrecioBD(ONs_NY_2[[#This Row],[Ticker]],24,"QUANTITY ASK","N")} -> 162 | J38: {=_xll.PrecioBD(ONs_NY_2[[#This Row],[Ticker]],24,"VOLUME AMOUNT","N")} -> 3823.34
B39: Tecpetrol | C39: TTCBD | D39: =TTCBD!K4 -> 0.049716279 | E39: =F39*$H$1 -> 104.65 | F39: {=_xll.PrecioBD(ONs_NY_2[[#This Row],[Ticker]],24,"ASK","N")} -> 104.65 | G39: =TTCBD!K3 -> 1.5419295 | I39: {=_xll.PrecioBD(ONs_NY_2[[#This Row],[Ticker]],24,"QUANTITY ASK","N")} -> 4459 | J39: {=_xll.PrecioBD(ONs_NY_2[[#This Row],[Ticker]],24,"VOLUME AMOUNT","N")} -> 521
B40: Vista Energy | C40: VSCWD | D40: =VSCWD!K4 -> 0.041663954 | E40: =F40*$H$1 -> 102.65 | F40: {=_xll.PrecioBD(ONs_NY_2[[#This Row],[Ticker]],24,"ASK","N")} -> 102.65 | G40: =VSCWD!K3 -> 1.103154 | I40: {=_xll.PrecioBD(ONs_NY_2[[#This Row],[Ticker]],24,"QUANTITY ASK","N")} -> 837 | J40: {=_xll.PrecioBD(ONs_NY_2[[#This Row],[Ticker]],24,"VOLUME AMOUNT","N")} -> 6191.64
B41: Balanz | C41: NBS1D | D41: =NBS1D!K4 -> 0.03046681 | E41: =F41*$H$1 -> 100.7 | F41: {=_xll.PrecioBD(ONs_NY_2[[#This Row],[Ticker]],24,"ASK","N")} -> 100.7 | G41: =NBS1D!K3 -> 0.30653803 | I41: {=_xll.PrecioBD(ONs_NY_2[[#This Row],[Ticker]],24,"QUANTITY ASK","N")} -> 8000 | J41: {=_xll.PrecioBD(ONs_NY_2[[#This Row],[Ticker]],24,"VOLUME AMOUNT","N")} -> 28003
B42: Pan American | C42: PN42D | D42: =PN42D!K4 -> 0.053087613 | E42: =F42*$H$1 -> 102.8 | F42: {=_xll.PrecioBD(ONs_NY_2[[#This Row],[Ticker]],24,"ASK","N")} -> 102.8 | G42: =PN42D!K3 -> 1.1006715 | I42: {=_xll.PrecioBD(ONs_NY_2[[#This Row],[Ticker]],24,"QUANTITY ASK","N")} -> 1000 | J42: {=_xll.PrecioBD(ONs_NY_2[[#This Row],[Ticker]],24,"VOLUME AMOUNT","N")} -> 0
B43: IRSA | C43: IRCJD | D43: =IRCJDD!K4 -> 0.045801052 | E43: =F43*$H$1 -> 105.75 | F43: {=_xll.PrecioBD(ONs_NY_2[[#This Row],[Ticker]],24,"ASK","N")} -> 105.75 | G43: =IRCJDD!K3 -> 0.96448739 | I43: {=_xll.PrecioBD(ONs_NY_2[[#This Row],[Ticker]],24,"QUANTITY ASK","N")} -> 2075 | J43: {=_xll.PrecioBD(ONs_NY_2[[#This Row],[Ticker]],24,"VOLUME AMOUNT","N")} -> 640.94
B44: Pan American | C44: PN38D | D44: =PN38D!K4 -> 0.038571939 | E44: =F44*$H$1 -> 103.9 | F44: {=_xll.PrecioBD(ONs_NY_2[[#This Row],[Ticker]],24,"ASK","N")} -> 103.9 | G44: =PN38D!K3 -> 1.4124417 | I44: {=_xll.PrecioBD(ONs_NY_2[[#This Row],[Ticker]],24,"QUANTITY ASK","N")} -> 1770 | J44: {=_xll.PrecioBD(ONs_NY_2[[#This Row],[Ticker]],24,"VOLUME AMOUNT","N")} -> 19049.7
B45: Arcor | C45: RC2CD | D45: ='RC2CD'!K4 -> 0.040278199 | E45: =F45*$H$1 -> 103.4 | F45: {=_xll.PrecioBD(ONs_NY_2[[#This Row],[Ticker]],24,"ASK","N")} -> 103.4 | G45: ='RC2CD'!K3 -> 0.6117854 | I45: {=_xll.PrecioBD(ONs_NY_2[[#This Row],[Ticker]],24,"QUANTITY ASK","N")} -> 5698 | J45: {=_xll.PrecioBD(ONs_NY_2[[#This Row],[Ticker]],24,"VOLUME AMOUNT","N")} -> 11152.73
B46: Aluar | C46: LMS8D | D46: =LMS8D!K4 -> 0.025215623 | E46: =F46*$H$1 -> 103.7 | F46: {=_xll.PrecioBD(ONs_NY_2[[#This Row],[Ticker]],24,"ASK","N")} -> 103.7 | G46: =LMS8D!K3 -> 0.69651517 | I46: {=_xll.PrecioBD(ONs_NY_2[[#This Row],[Ticker]],24,"QUANTITY ASK","N")} -> 1450 | J46: {=_xll.PrecioBD(ONs_NY_2[[#This Row],[Ticker]],24,"VOLUME AMOUNT","N")} -> 612
B47: YPF | C47: YMCVD | D47: =YMCVO!K4 -> 0.036735794 | E47: =F47*$H$1 -> 101.95 | F47: {=_xll.PrecioBD(ONs_NY_2[[#This Row],[Ticker]],24,"ASK","N")} -> 101.95 | G47: =YMCVO!K3 -> 0.27344948 | I47: {=_xll.PrecioBD(ONs_NY_2[[#This Row],[Ticker]],24,"QUANTITY ASK","N")} -> 690 | J47: {=_xll.PrecioBD(ONs_NY_2[[#This Row],[Ticker]],24,"VOLUME AMOUNT","N")} -> 317908.07
B48: YPF | C48: YMCVD | D48: =YMCVD!K4 -> 0.036735794 | E48: =F48*$H$1 -> 101.95 | F48: {=_xll.PrecioBD(ONs_NY_2[[#This Row],[Ticker]],24,"ASK","N")} -> 101.95 | G48: =YMCVD!K3 -> 0.27099425 | I48: {=_xll.PrecioBD(ONs_NY_2[[#This Row],[Ticker]],24,"QUANTITY ASK","N")} -> 690 | J48: {=_xll.PrecioBD(ONs_NY_2[[#This Row],[Ticker]],24,"VOLUME AMOUNT","N")} -> 317908.07
B49: CGC | C49: CP34D | D49: =CP34D!K4 -> -0.27108715 | E49: =F49*$H$1 -> 104.25 | F49: {=_xll.PrecioBD(ONs_NY_2[[#This Row],[Ticker]],24,"ASK","N")} -> 104.25 | G49: =CP34D!K3 -> 0.025671977 | I49: {=_xll.PrecioBD(ONs_NY_2[[#This Row],[Ticker]],24,"QUANTITY ASK","N")} -> 10050 | J49: {=_xll.PrecioBD(ONs_NY_2[[#This Row],[Ticker]],24,"VOLUME AMOUNT","N")} -> 0
B50: Loma Negra | C50: LOC3D | D50: =LOC3D!K4 -> -0.089319405 | E50: =F50*$H$1 -> 104.35 | F50: {=_xll.PrecioBD(ONs_NY_2[[#This Row],[Ticker]],24,"ASK","N")} -> 104.35 | G50: =LOC3D!K3 -> 0.068902557 | I50: {=_xll.PrecioBD(ONs_NY_2[[#This Row],[Ticker]],24,"QUANTITY ASK","N")} -> 1950 | J50: {=_xll.PrecioBD(ONs_NY_2[[#This Row],[Ticker]],24,"VOLUME AMOUNT","N")} -> 0
B51: Cresud | C51: CS38D | D51: =CS38D!K4 -> -0.6007571 | E51: =F51*$H$1 -> 105.45 | F51: {=_xll.PrecioBD(ONs_NY_2[[#This Row],[Ticker]],24,"ASK","N")} -> 105.45 | G51: =CS38D!K3 -> 0.069375882 | I51: {=_xll.PrecioBD(ONs_NY_2[[#This Row],[Ticker]],24,"QUANTITY ASK","N")} -> 959 | J51: {=_xll.PrecioBD(ONs_NY_2[[#This Row],[Ticker]],24,"VOLUME AMOUNT","N")} -> 60428.3
B52: YPF | C52: YMCQD | D52: =YMCQD!K4 -> #NUM! | E52: =F52*$H$1 -> 0 | F52: {=_xll.PrecioBD(ONs_NY_2[[#This Row],[Ticker]],24,"ASK","N")} -> 0 | G52: =YMCQD!K3 -> #NUM! | I52: {=_xll.PrecioBD(ONs_NY_2[[#This Row],[Ticker]],24,"QUANTITY ASK","N")} -> 0 | J52: {=_xll.PrecioBD(ONs_NY_2[[#This Row],[Ticker]],24,"VOLUME AMOUNT","N")} -> 0
C54: PECGD | E54: =F54*$H$1 -> 0 | F54: {=_xll.PrecioBD(ONs_NY_2[[#This Row],[Ticker]],24,"ASK","N")} -> 0 | I54: {=_xll.PrecioBD(ONs_NY_2[[#This Row],[Ticker]],24,"QUANTITY ASK","N")} -> 0 | J54: {=_xll.PrecioBD(ONs_NY_2[[#This Row],[Ticker]],24,"VOLUME AMOUNT","N")} -> 0

Sheet TY30P
A1: TY30P | B1: Fecha de Pago | C1: Interés | D1: Amortización | E1: Total
B2: =Main!D1 -> 46068 | E2: {=-_xll.PrecioBD(A1,"24","ASK","N")} -> -116.8 | J2: Periodo de intereses | K2: 0.5
A3: 2 | B3: 46174 | C3: 14.83 | D3: 0 | E3: =IF(B3<=$B$2,0,(C3+D3)) -> 14.83 | F3: =(E3*(B3-$B$2)/365)/(1+$K$4)^((B3-$B$2)/365)/-$E$2/(1+$K$4)^$K$2 -> 0.030472713 | J3: MDUR | K3: =SUM(F3:F102) -> 2.3260326
A4: 3 | B4: 46356 | C4: 15.08 | D4: 0 | E4: =IF(B4<=$B$2,0,(C4+D4)) -> 15.08 | F4: =(E4*(B4-$B$2)/365)/(1+$K$4)^((B4-$B$2)/365)/-$E$2/(1+$K$4)^$K$2 -> 0.074648916 | J4: TIR | K4: =XIRR(E2:E33,B2:B33) -> 0.2727874
A5: 4 | B5: 46538 | C5: 14.83 | D5: 0 | E5: =IF(B5<=$B$2,0,(C5+D5)) -> 14.83 | F5: =(E5*(B5-$B$2)/365)/(1+$K$4)^((B5-$B$2)/365)/-$E$2/(1+$K$4)^$K$2 -> 0.10622684
A6: 5 | B6: 46721 | C6: 15.08 | D6: 0 | E6: =IF(B6<=$B$2,0,(C6+D6)) -> 15.08 | F6: =(E6*(B6-$B$2)/365)/(1+$K$4)^((B6-$B$2)/365)/-$E$2/(1+$K$4)^$K$2 -> 0.13298061
A7: 6 | B7: 46904 | C7: 14.91 | D7: 0 | E7: =IF(B7<=$B$2,0,(C7+D7)) -> 14.91 | F7: =(E7*(B7-$B$2)/365)/(1+$K$4)^((B7-$B$2)/365)/-$E$2/(1+$K$4)^$K$2 -> 0.14915448
A8: 7 | B8: 47087 | C8: 15.08 | D8: 0 | E8: =IF(B8<=$B$2,0,(C8+D8)) -> 15.08 | F8: =(E8*(B8-$B$2)/365)/(1+$K$4)^((B8-$B$2)/365)/-$E$2/(1+$K$4)^$K$2 -> 0.16293203
A9: 8 | B9: 47269 | C9: 14.83 | D9: 0 | E9: =IF(B9<=$B$2,0,(C9+D9)) -> 14.83 | F9: =(E9*(B9-$B$2)/365)/(1+$K$4)^((B9-$B$2)/365)/-$E$2/(1+$K$4)^$K$2 -> 0.16744827
A10: 9 | B10: 47452 | C10: 15.08 | D10: 0 | E10: =IF(B10<=$B$2,0,(C10+D10)) -> 15.08 | F10: =(E10*(B10-$B$2)/365)/(1+$K$4)^((B10-$B$2)/365)/-$E$2/(1+$K$4)^$K$2 -> 0.17386514
A11: 10 | B11: 47633 | C11: 14.83 | D11: 100 | E11: =IF(B11<=$B$2,0,(C11+D11)) -> 114.83 | F11: =(E11*(B11-$B$2)/365)/(1+$K$4)^((B11-$B$2)/365)/-$E$2/(1+$K$4)^$K$2 -> 1.3283036
E12: =IF(B12<=$B$2,0,(C12+D12)) -> 0 | F12: =(E12*(B12-$B$2)/365)/(1+$K$4)^((B12-$B$2)/365)/-$E$2/(1+$K$4)^$K$2 -> 0
E13: =IF(B13<=$B$2,0,(C13+D13)) -> 0 | F13: =(E13*(B13-$B$2)/365)/(1+$K$4)^((B13-$B$2)/365)/-$E$2/(1+$K$4)^$K$2 -> 0
E14: =IF(B14<=$B$2,0,(C14+D14)) -> 0 | F14: =(E14*(B14-$B$2)/365)/(1+$K$4)^((B14-$B$2)/365)/-$E$2/(1+$K$4)^$K$2 -> 0
E15: =IF(B15<=$B$2,0,(C15+D15)) -> 0 | F15: =(E15*(B15-$B$2)/365)/(1+$K$4)^((B15-$B$2)/365)/-$E$2/(1+$K$4)^$K$2 -> 0
E16: =IF(B16<=$B$2,0,(C16+D16)) -> 0 | F16: =(E16*(B16-$B$2)/365)/(1+$K$4)^((B16-$B$2)/365)/-$E$2/(1+$K$4)^$K$2 -> 0
E17: =IF(B17<=$B$2,0,(C17+D17)) -> 0 | F17: =(E17*(B17-$B$2)/365)/(1+$K$4)^((B17-$B$2)/365)/-$E$2/(1+$K$4)^$K$2 -> 0
E18: =IF(B18<=$B$2,0,(C18+D18)) -> 0 | F18: =(E18*(B18-$B$2)/365)/(1+$K$4)^((B18-$B$2)/365)/-$E$2/(1+$K$4)^$K$2 -> 0
E19: =IF(B19<=$B$2,0,(C19+D19)) -> 0 | F19: =(E19*(B19-$B$2)/365)/(1+$K$4)^((B19-$B$2)/365)/-$E$2/(1+$K$4)^$K$2 -> 0
E20: =IF(B20<=$B$2,0,(C20+D20)) -> 0 | F20: =(E20*(B20-$B$2)/365)/(1+$K$4)^((B20-$B$2)/365)/-$E$2/(1+$K$4)^$K$2 -> 0
E21: =IF(B21<=$B$2,0,(C21+D21)) -> 0 | F21: =(E21*(B21-$B$2)/365)/(1+$K$4)^((B21-$B$2)/365)/-$E$2/(1+$K$4)^$K$2 -> 0
E22: =IF(B22<=$B$2,0,(C22+D22)) -> 0 | F22: =(E22*(B22-$B$2)/365)/(1+$K$4)^((B22-$B$2)/365)/-$E$2/(1+$K$4)^$K$2 -> 0
E23: =IF(B23<=$B$2,0,(C23+D23)) -> 0 | F23: =(E23*(B23-$B$2)/365)/(1+$K$4)^((B23-$B$2)/365)/-$E$2/(1+$K$4)^$K$2 -> 0
... E33: =IF(B33<=$B$2,0,(C33+D33)) -> 0 | F33: =(E33*(B33-$B$2)/365)/(1+$K$4)^((B33-$B$2)/365)/-$E$2/(1+$K$4)^$K$2 -> 0

Sheet T30J7
A1: T30J7 | B1: Fecha de Pago | C1: Interés | D1: Amortización | E1: Total
B2: =Main!D1 -> 46068 | E2: {=_xll.PrecioBD(A1,"24","ASK","N")} -> 104.45 | J2: Periodo de intereses | K2: 0.5
A3: 1 | B3: 46568 | C3: 45.25 | D3: 100 | E3: =IF(B3<=$B$2,0,(C3+D3)) -> 145.25 | F3: =(E3*(B3-$B$2)/365)/(1+#REF!)^((B3-$B$2)/365)/-$E$2/(1+#REF!)^$K$2 -> #REF! | J3: MDUR | K3: =SUM(F3:F102) -> #REF!
J4: =+(1+(E3/E2-1))^(365/(B3-B2))-1 -> 0.27215966 | K4: TIR
J5: =+(E3/E2-1)/(B3-B2)*365 -> 0.28515079 | K5: TNA
J6: =+(1+J4)^(1/12)-1 -> 0.020262212 | K6: TEM

Sheet T31Y7
A1: T31Y7 | B1: Fecha de Pago | C1: Interés | D1: Amortización | E1: Total
B2: =Main!D1 -> 46068 | E2: {=_xll.PrecioBD(A1,"24","ASK","N")} -> 103 | J2: Periodo de intereses | K2: 0.5
A3: 1 | B3: 46538 | C3: 51.75 | D3: 100 | E3: =IF(B3<=$B$2,0,(C3+D3)) -> 151.75 | F3: =(E3*(B3-$B$2)/365)/(1+#REF!)^((B3-$B$2)/365)/-$E$2/(1+#REF!)^$K$2 -> #REF! | J3: MDUR | K3: =SUM(F3:F102) -> #REF!
J4: =+(1+(E3/E2-1))^(365/(B3-B2))-1 -> 0.35112162 | K4: TIR
J5: =+(E3/E2-1)/(B3-B2)*365 -> 0.36756352 | K5: TNA
J6: =+(1+J4)^(1/12)-1 -> 0.025395019 | K6: TEM

Sheet T30A7
A1: T30A7 | B1: Fecha de Pago | C1: Interés | D1: Amortización | E1: Total
B2: =Main!D1 -> 46068 | E2: {=_xll.PrecioBD(A1,"24","ASK","N")} -> 108.7 | J2: Periodo de intereses | K2: 0.5
A3: 1 | B3: 46507 | C3: 59.92 | D3: 100 | E3: =IF(B3<=$B$2,0,(C3+D3)) -> 159.92 | F3: =(E3*(B3-$B$2)/365)/(1+#REF!)^((B3-$B$2)/365)/-$E$2/(1+#REF!)^$K$2 -> #REF! | J3: MDUR | K3: =SUM(F3:F102) -> #REF!
J4: =+(1+(E3/E2-1))^(365/(B3-B2))-1 -> 0.37850838 | K4: TIR
J5: =+(E3/E2-1)/(B3-B2)*365 -> 0.39177649 | K5: TNA
J6: =+(1+J4)^(1/12)-1 -> 0.027111167 | K6: TEM

Sheet T15E7
A1: T15E7 | B1: Fecha de Pago | C1: Interés | D1: Amortización | E1: Total
B2: =Main!D1 -> 46068 | E2: {=_xll.PrecioBD(A1,"24","ASK","N")} -> 120.15 | J2: Periodo de intereses | K2: 0.5
A3: 1 | B3: 46402 | C3: 61.1 | D3: 100 | E3: =IF(B3<=$B$2,0,(C3+D3)) -> 161.1 | F3: =(E3*(B3-$B$2)/365)/(1+#REF!)^((B3-$B$2)/365)/-$E$2/(1+#REF!)^$K$2 -> #REF! | J3: MDUR | K3: =SUM(F3:F102) -> #REF!
J4: =+(1+(E3/E2-1))^(365/(B3-B2))-1 -> 0.37782384 | K4: TIR
J5: =+(E3/E2-1)/(B3-B2)*365 -> 0.37245733 | K5: TNA
J6: =+(1+J4)^(1/12)-1 -> 0.027068654 | K6: TEM

Sheet S30N6
A1: S30N6 | B1: Fecha de Pago | C1: Interés | D1: Amortización | E1: Total
B2: =Main!D1 -> 46068 | E2: {=_xll.PrecioBD(A1,"24","ASK","N")} -> 101.314 | J2: Periodo de intereses | K2: 0.5
A3: 1 | B3: 46356 | C3: 30.06 | D3: 100 | E3: =IF(B3<=$B$2,0,(C3+D3)) -> 130.06 | F3: =(E3*(B3-$B$2)/365)/(1+#REF!)^((B3-$B$2)/365)/-$E$2/(1+#REF!)^$K$2 -> #REF! | J3: MDUR | K3: =SUM(F3:F102) -> #REF!
J4: =+(1+(E3/E2-1))^(365/(B3-B2))-1 -> 0.37238541 | K4: TIR
J5: =+(E3/E2-1)/(B3-B2)*365 -> 0.3595906 | K5: TNA
J6: =+(1+J4)^(1/12)-1 -> 0.026730211 | K6: TEM

Sheet S30O6
A1: S30O6 | B1: Fecha de Pago | C1: Interés | D1: Amortización | E1: Total
B2: =Main!D1 -> 46068 | E2: {=_xll.PrecioBD(A1,"24","ASK","N")} -> 108.824 | J2: Periodo de intereses | K2: 0.5
A3: 1 | B3: 46325 | C3: 35.28 | D3: 100 | E3: =IF(B3<=$B$2,0,(C3+D3)) -> 135.28 | F3: =(E3*(B3-$B$2)/365)/(1+#REF!)^((B3-$B$2)/365)/-$E$2/(1+#REF!)^$K$2 -> #REF! | J3: MDUR | K3: =SUM(F3:F102) -> #REF!
J4: =+(1+(E3/E2-1))^(365/(B3-B2))-1 -> 0.36214931 | K4: TIR
J5: =+(E3/E2-1)/(B3-B2)*365 -> 0.34527031 | K5: TNA
J6: =+(1+J4)^(1/12)-1 -> 0.026089853 | K6: TEM

Sheet S31G6
A1: S31G6 | B1: Fecha de Pago | C1: Interés | D1: Amortización | E1: Total
B2: =Main!D1 -> 46068 | E2: {=_xll.PrecioBD(A1,"24","ASK","N")} -> 107.25 | J2: Periodo de intereses | K2: 0.5
A3: 1 | B3: 46265 | C3: 28.52 | D3: 100 | E3: =IF(B3<=$B$2,0,(C3+D3)) -> 128.52 | F3: =(E3*(B3-$B$2)/365)/(1+#REF!)^((B3-$B$2)/365)/-$E$2/(1+#REF!)^$K$2 -> #REF! | J3: MDUR | K3: =SUM(F3:F102) -> #REF!
J4: =+(1+(E3/E2-1))^(365/(B3-B2))-1 -> 0.39823506 | K4: TIR
J5: =+(E3/E2-1)/(B3-B2)*365 -> 0.36744879 | K5: TNA
J6: =+(1+J4)^(1/12)-1 -> 0.02832805 | K6: TEM

Sheet S31L6
A1: S31L6 | B1: Fecha de Pago | C1: Interés | D1: Amortización | E1: Total
B2: =Main!D1 -> 46068 | E2: {=_xll.PrecioBD(A1,"24","ASK","N")} -> 101.45 | J2: Periodo de intereses | K2: 0.5
A3: 1 | B3: 46234 | C3: 17.67683 | D3: 100 | E3: =IF(B3<=$B$2,0,(C3+D3)) -> 117.67683 | F3: =(E3*(B3-$B$2)/365)/(1+#REF!)^((B3-$B$2)/365)/-$E$2/(1+#REF!)^$K$2 -> #REF! | J3: MDUR | K3: =SUM(F3:F102) -> #REF!
J4: =+(1+(E3/E2-1))^(365/(B3-B2))-1 -> 0.38575982 | K4: TIR
J5: =+(E3/E2-1)/(B3-B2)*365 -> 0.35169518 | K5: TNA
J6: =+(1+J4)^(1/12)-1 -> 0.027560332 | K6: TEM

Sheet T30J6
A1: T30J6 | B1: Fecha de Pago | C1: Interés | D1: Amortización | E1: Total
B2: =Main!D1 -> 46068 | E2: {=_xll.PrecioBD(A1,"24","ASK","N")} -> 128.45 | J2: Periodo de intereses | K2: 0.5
A3: 1 | B3: 46203 | C3: 44.89 | D3: 100 | E3: =IF(B3<=$B$2,0,(C3+D3)) -> 144.89 | F3: =(E3*(B3-$B$2)/365)/(1+#REF!)^((B3-$B$2)/365)/-$E$2/(1+#REF!)^$K$2 -> #REF! | J3: MDUR | K3: =SUM(F3:F102) -> #REF!
J4: =+(1+(E3/E2-1))^(365/(B3-B2))-1 -> 0.38489019 | K4: TIR
J5: =+(E3/E2-1)/(B3-B2)*365 -> 0.3460404 | K5: TNA
J6: =+(1+J4)^(1/12)-1 -> 0.02750658 | K6: TEM

Sheet S29Y6
A1: S29Y6 | B1: Fecha de Pago | C1: Interés | D1: Amortización | E1: Total
B2: =Main!D1 -> 46068 | E2: {=_xll.PrecioBD(A1,"24","ASK","N")} -> 120.6 | J2: Periodo de intereses | K2: 0.5
A3: 1 | B3: 46171 | C3: 32.25 | D3: 100 | E3: =IF(B3<=$B$2,0,(C3+D3)) -> 132.25 | F3: =(E3*(B3-$B$2)/365)/(1+#REF!)^((B3-$B$2)/365)/-$E$2/(1+#REF!)^$K$2 -> #REF! | J3: MDUR | K3: =SUM(F3:F102) -> #REF!
J4: =+(1+(E3/E2-1))^(365/(B3-B2))-1 -> 0.38649718 | K4: TIR
J5: =+(E3/E2-1)/(B3-B2)*365 -> 0.34232156 | K5: TNA
J6: =+(1+J4)^(1/12)-1 -> 0.027605885 | K6: TEM

Sheet S30A6
A1: S30A6 | B1: Fecha de Pago | C1: Interés | D1: Amortización | E1: Total
B2: =Main!D1 -> 46068 | E2: {=_xll.PrecioBD(A1,"24","ASK","N")} -> 119.298 | J2: Periodo de intereses | K2: 0.5
A3: 1 | B3: 46142 | C3: 27.49 | D3: 100 | E3: =IF(B3<=$B$2,0,(C3+D3)) -> 127.49 | F3: =(E3*(B3-$B$2)/365)/(1+#REF!)^((B3-$B$2)/365)/-$E$2/(1+#REF!)^$K$2 -> #REF! | J3: MDUR | K3: =SUM(F3:F102) -> #REF!
J4: =+(1+(E3/E2-1))^(365/(B3-B2))-1 -> 0.38760528 | K4: TIR
J5: =+(E3/E2-1)/(B3-B2)*365 -> 0.33870213 | K5: TNA
J6: =+(1+J4)^(1/12)-1 -> 0.027674298 | K6: TEM

Sheet S17A6
A1: S17A6 | B1: Fecha de Pago | C1: Interés | D1: Amortización | E1: Total
B2: =Main!D1 -> 46068 | E2: {=_xll.PrecioBD(A1,"24","ASK","N")} -> 103.9 | J2: Periodo de intereses | K2: 0.5
A3: 1 | B3: 46129 | C3: 10.13 | D3: 100 | E3: =IF(B3<=$B$2,0,(C3+D3)) -> 110.13 | F3: =(E3*(B3-$B$2)/365)/(1+#REF!)^((B3-$B$2)/365)/-$E$2/(1+#REF!)^$K$2 -> #REF! | J3: MDUR | K3: =SUM(F3:F102) -> #REF!
J4: =+(1+(E3/E2-1))^(365/(B3-B2))-1 -> 0.4168568 | K4: TIR
J5: =+(E3/E2-1)/(B3-B2)*365 -> 0.35878603 | K5: TNA
J6: =+(1+J4)^(1/12)-1 -> 0.029462418 | K6: TEM

Sheet S16M6
A1: S16M6 | B1: Fecha de Pago | C1: Interés | D1: Amortización | E1: Total
B2: =Main!D1 -> 46068 | E2: {=_xll.PrecioBD(A1,"24","ASK","N")} -> 101.74 | J2: Periodo de intereses | K2: 0.5
A3: 1 | B3: 46097 | C3: 4.62105 | D3: 100 | E3: =IF(B3<=$B$2,0,(C3+D3)) -> 104.62105 | F3: =(E3*(B3-$B$2)/365)/(1+#REF!)^((B3-$B$2)/365)/-$E$2/(1+#REF!)^$K$2 -> #REF! | J3: MDUR | K3: =SUM(F3:F102) -> #REF!
J4: =+(1+(E3/E2-1))^(365/(B3-B2))-1 -> 0.42114118 | K4: TIR
J5: =+(E3/E2-1)/(B3-B2)*365 -> 0.35641332 | K5: TNA
J6: =+(1+J4)^(1/12)-1 -> 0.029721472 | K6: TEM

Sheet S27F6
A1: S27F6 | B1: Fecha de Pago | C1: Interés | D1: Amortización | E1: Total
B2: =Main!D1 -> 46068 | E2: {=_xll.PrecioBD(A1,"24","ASK","N")} -> 124.32 | J2: Periodo de intereses | K2: 0.5
A3: 1 | B3: 46080 | C3: 25.84 | D3: 100 | E3: =IF(B3<=$B$2,0,(C3+D3)) -> 125.84 | F3: =(E3*(B3-$B$2)/365)/(1+#REF!)^((B3-$B$2)/365)/-$E$2/(1+#REF!)^$K$2 -> #REF! | J3: MDUR | K3: =SUM(F3:F102) -> #REF!
J4: =+(1+(E3/E2-1))^(365/(B3-B2))-1 -> 0.44720578 | K4: TIR
J5: =+(E3/E2-1)/(B3-B2)*365 -> 0.37188975 | K5: TNA
J6: =+(1+J4)^(1/12)-1 -> 0.031282205 | K6: TEM

Sheet T13F6
A1: T13F6 | B1: Fecha de Pago | C1: Interés | D1: Amortización | E1: Total
B2: =Main!D1 -> 46068 | E2: {=_xll.PrecioBD(A1,"24","ASK","N")} -> 0 | J2: Periodo de intereses | K2: 0.5
A3: 1 | B3: 46066 | C3: 44.97 | D3: 100 | E3: =IF(B3<=$B$2,0,(C3+D3)) -> 0 | F3: =(E3*(B3-$B$2)/365)/(1+#REF!)^((B3-$B$2)/365)/-$E$2/(1+#REF!)^$K$2 -> #REF! | J3: MDUR | K3: =SUM(F3:F102) -> #REF!
J4: =+(1+(E3/E2-1))^(365/(B3-B2))-1 -> #DIV/0! | K4: TIR
J5: =+(E3/E2-1)/(B3-B2)*365 -> #DIV/0! | K5: TNA
J6: =+(1+J4)^(1/12)-1 -> #DIV/0! | K6: TEM

Sheet GD41D
A1: GD41D | B1: Fecha de Pago | C1: Interés | D1: Amortización | E1: Total
B2: =Main!D1 -> 46068 | E2: {=-_xll.PrecioBD(A1,"24","ASK","N")} -> -75.15 | J2: Periodo de intereses | K2: 0.5
A3: 11 | B3: 46213 | C3: 1.76 | D3: 0 | E3: =IF(B3<=$B$2,0,(C3+D3)) -> 1.76 | F3: =(E3*(B3-$B$2)/365)/(1+$K$4)^((B3-$B$2)/365)/-$E$2/(1+$K$4)^$K$2 -> 0.0086246392 | J3: MDUR | K3: =SUM(F3:F102) -> 6.2475791
A4: 12 | B4: 46398 | C4: 1.76 | D4: 0 | E4: =IF(B4<=$B$2,0,(C4+D4)) -> 1.76 | F4: =(E4*(B4-$B$2)/365)/(1+$K$4)^((B4-$B$2)/365)/-$E$2/(1+$K$4)^$K$2 -> 0.01880581 | J4: TIR | K4: =XIRR(E2:E33,B2:B33) -> 0.088145849
A5: 13 | B5: 46580 | C5: 1.76 | D5: 0 | E5: =IF(B5<=$B$2,0,(C5+D5)) -> 1.76 | F5: =(E5*(B5-$B$2)/365)/(1+$K$4)^((B5-$B$2)/365)/-$E$2/(1+$K$4)^$K$2 -> 0.027974012
A6: 14 | B6: 46762 | C6: 1.73 | D6: 3.57 | E6: =IF(B6<=$B$2,0,(C6+D6)) -> 5.3 | F6: =(E6*(B6-$B$2)/365)/(1+$K$4)^((B6-$B$2)/365)/-$E$2/(1+$K$4)^$K$2 -> 0.1094748
A7: 15 | B7: 46944 | C7: 1.69 | D7: 3.57 | E7: =IF(B7<=$B$2,0,(C7+D7)) -> 5.26 | F7: =(E7*(B7-$B$2)/365)/(1+$K$4)^((B7-$B$2)/365)/-$E$2/(1+$K$4)^$K$2 -> 0.13148475
A8: 16 | B8: 47127 | C8: 1.62 | D8: 3.57 | E8: =IF(B8<=$B$2,0,(C8+D8)) -> 5.19 | F8: =(E8*(B8-$B$2)/365)/(1+$K$4)^((B8-$B$2)/365)/-$E$2/(1+$K$4)^$K$2 -> 0.15033325
A9: 17 | B9: 47309 | C9: 1.57 | D9: 3.57 | E9: =IF(B9<=$B$2,0,(C9+D9)) -> 5.14 | F9: =(E9*(B9-$B$2)/365)/(1+$K$4)^((B9-$B$2)/365)/-$E$2/(1+$K$4)^$K$2 -> 0.16727588
A10: 18 | B10: 47492 | C10: 2.08 | D10: 3.57 | E10: =IF(B10<=$B$2,0,(C10+D10)) -> 5.65 | F10: =(E10*(B10-$B$2)/365)/(1+$K$4)^((B10-$B$2)/365)/-$E$2/(1+$K$4)^$K$2 -> 0.20223813
A11: 19 | B11: 47674 | C11: 2.01 | D11: 3.57 | E11: =IF(B11<=$B$2,0,(C11+D11)) -> 5.58 | F11: =(E11*(B11-$B$2)/365)/(1+$K$4)^((B11-$B$2)/365)/-$E$2/(1+$K$4)^$K$2 -> 0.21596882
A12: 20 | B12: 47857 | C12: 1.9 | D12: 3.57 | E12: =IF(B12<=$B$2,0,(C12+D12)) -> 5.47 | F12: =(E12*(B12-$B$2)/365)/(1+$K$4)^((B12-$B$2)/365)/-$E$2/(1+$K$4)^$K$2 -> 0.22605555
A13: 21 | B13: 48039 | C13: 1.84 | D13: 3.57 | E13: =IF(B13<=$B$2,0,(C13+D13)) -> 5.41 | F13: =(E13*(B13-$B$2)/365)/(1+$K$4)^((B13-$B$2)/365)/-$E$2/(1+$K$4)^$K$2 -> 0.23616095
A14: 22 | B14: 48222 | C14: 1.73 | D14: 3.57 | E14: =IF(B14<=$B$2,0,(C14+D14)) -> 5.3 | F14: =(E14*(B14-$B$2)/365)/(1+$K$4)^((B14-$B$2)/365)/-$E$2/(1+$K$4)^$K$2 -> 0.24235499
A15: 23 | B15: 48407 | C15: 1.68 | D15: 3.57 | E15: =IF(B15<=$B$2,0,(C15+D15)) -> 5.25 | F15: =(E15*(B15-$B$2)/365)/(1+$K$4)^((B15-$B$2)/365)/-$E$2/(1+$K$4)^$K$2 -> 0.24976126
A16: 24 | B16: 48589 | C16: 1.55 | D16: 3.57 | E16: =IF(B16<=$B$2,0,(C16+D16)) -> 5.12 | F16: =(E16*(B16-$B$2)/365)/(1+$K$4)^((B16-$B$2)/365)/-$E$2/(1+$K$4)^$K$2 -> 0.25170107
... A33: 41 | B33: 51692 | C33: 0.09 | D33: 3.61 | E33: =IF(B33<=$B$2,0,(C33+D33)) -> 3.7 | F33: =(E33*(B33-$B$2)/365)/(1+$K$4)^((B33-$B$2)/365)/-$E$2/(1+$K$4)^$K$2 -> 0.1978785

Sheet AL41D
A1: AL41D | B1: Fecha de Pago | C1: Interés | D1: Amortización | E1: Total
B2: =Main!D1 -> 46068 | E2: {=-_xll.PrecioBD(A1,"24","ASK","N")} -> -74.15 | J2: Periodo de intereses | K2: 0.5
A3: 11 | B3: 46213 | C3: 1.76 | D3: 0 | E3: =IF(B3<=$B$2,0,(C3+D3)) -> 1.76 | F3: =(E3*(B3-$B$2)/365)/(1+$K$4)^((B3-$B$2)/365)/-$E$2/(1+$K$4)^$K$2 -> 0.0087248071 | J3: MDUR | K3: =SUM(F3:F102) -> 6.2109542
A4: 12 | B4: 46398 | C4: 1.76 | D4: 0 | E4: =IF(B4<=$B$2,0,(C4+D4)) -> 1.76 | F4: =(E4*(B4-$B$2)/365)/(1+$K$4)^((B4-$B$2)/365)/-$E$2/(1+$K$4)^$K$2 -> 0.019004366 | J4: TIR | K4: =XIRR(E2:E33,B2:B33) -> 0.090390292
A5: 13 | B5: 46580 | C5: 1.76 | D5: 0 | E5: =IF(B5<=$B$2,0,(C5+D5)) -> 1.76 | F5: =(E5*(B5-$B$2)/365)/(1+$K$4)^((B5-$B$2)/365)/-$E$2/(1+$K$4)^$K$2 -> 0.028240338
A6: 14 | B6: 46762 | C6: 1.73 | D6: 3.57 | E6: =IF(B6<=$B$2,0,(C6+D6)) -> 5.3 | F6: =(E6*(B6-$B$2)/365)/(1+$K$4)^((B6-$B$2)/365)/-$E$2/(1+$K$4)^$K$2 -> 0.11040356
A7: 15 | B7: 46944 | C7: 1.69 | D7: 3.57 | E7: =IF(B7<=$B$2,0,(C7+D7)) -> 5.26 | F7: =(E7*(B7-$B$2)/365)/(1+$K$4)^((B7-$B$2)/365)/-$E$2/(1+$K$4)^$K$2 -> 0.13246407
A8: 16 | B8: 47127 | C8: 1.62 | D8: 3.57 | E8: =IF(B8<=$B$2,0,(C8+D8)) -> 5.19 | F8: =(E8*(B8-$B$2)/365)/(1+$K$4)^((B8-$B$2)/365)/-$E$2/(1+$K$4)^$K$2 -> 0.15129658
A9: 17 | B9: 47309 | C9: 1.57 | D9: 3.57 | E9: =IF(B9<=$B$2,0,(C9+D9)) -> 5.14 | F9: =(E9*(B9-$B$2)/365)/(1+$K$4)^((B9-$B$2)/365)/-$E$2/(1+$K$4)^$K$2 -> 0.1681749
A10: 18 | B10: 47492 | C10: 2.08 | D10: 3.57 | E10: =IF(B10<=$B$2,0,(C10+D10)) -> 5.65 | F10: =(E10*(B10-$B$2)/365)/(1+$K$4)^((B10-$B$2)/365)/-$E$2/(1+$K$4)^$K$2 -> 0.20311511
A11: 19 | B11: 47674 | C11: 2.01 | D11: 3.57 | E11: =IF(B11<=$B$2,0,(C11+D11)) -> 5.58 | F11: =(E11*(B11-$B$2)/365)/(1+$K$4)^((B11-$B$2)/365)/-$E$2/(1+$K$4)^$K$2 -> 0.2166826
A12: 20 | B12: 47857 | C12: 1.9 | D12: 3.57 | E12: =IF(B12<=$B$2,0,(C12+D12)) -> 5.47 | F12: =(E12*(B12-$B$2)/365)/(1+$K$4)^((B12-$B$2)/365)/-$E$2/(1+$K$4)^$K$2 -> 0.22656848
A13: 21 | B13: 48039 | C13: 1.84 | D13: 3.57 | E13: =IF(B13<=$B$2,0,(C13+D13)) -> 5.41 | F13: =(E13*(B13-$B$2)/365)/(1+$K$4)^((B13-$B$2)/365)/-$E$2/(1+$K$4)^$K$2 -> 0.23645375
A14: 22 | B14: 48222 | C14: 1.73 | D14: 3.57 | E14: =IF(B14<=$B$2,0,(C14+D14)) -> 5.3 | F14: =(E14*(B14-$B$2)/365)/(1+$K$4)^((B14-$B$2)/365)/-$E$2/(1+$K$4)^$K$2 -> 0.24240491
A15: 23 | B15: 48407 | C15: 1.68 | D15: 3.57 | E15: =IF(B15<=$B$2,0,(C15+D15)) -> 5.25 | F15: =(E15*(B15-$B$2)/365)/(1+$K$4)^((B15-$B$2)/365)/-$E$2/(1+$K$4)^$K$2 -> 0.24955196
A16: 24 | B16: 48589 | C16: 1.55 | D16: 3.57 | E16: =IF(B16<=$B$2,0,(C16+D16)) -> 5.12 | F16: =(E16*(B16-$B$2)/365)/(1+$K$4)^((B16-$B$2)/365)/-$E$2/(1+$K$4)^$K$2 -> 0.25123188
... A33: 41 | B33: 51692 | C33: 0.09 | D33: 3.61 | E33: =IF(B33<=$B$2,0,(C33+D33)) -> 3.7 | F33: =(E33*(B33-$B$2)/365)/(1+$K$4)^((B33-$B$2)/365)/-$E$2/(1+$K$4)^$K$2 -> 0.19407996

Sheet GD38D
A1: GD38D | B1: Fecha de Pago | C1: Interés | D1: Amortización | E1: Total
B2: =Main!D1 -> 46068 | E2: {=-_xll.PrecioBD(A1,"24","ASK","N")} -> -83.95 | J2: Periodo de intereses | K2: 0.5
A3: 11 | B3: 46213 | C3: 2.51 | D3: 0 | E3: =IF(B3<=$B$2,0,(C3+D3)) -> 2.51 | F3: =(E3*(B3-$B$2)/365)/(1+$K$4)^((B3-$B$2)/365)/-$E$2/(1+$K$4)^$K$2 -> 0.011026191 | J3: MDUR | K3: =SUM(F3:F102) -> 4.9862373
A4: 12 | B4: 46398 | C4: 2.51 | D4: 0 | E4: =IF(B4<=$B$2,0,(C4+D4)) -> 2.51 | F4: =(E4*(B4-$B$2)/365)/(1+$K$4)^((B4-$B$2)/365)/-$E$2/(1+$K$4)^$K$2 -> 0.024061582 | J4: TIR | K4: =XIRR(E2:E26,B2:B26) -> 0.086429152
A5: 13 | B5: 46580 | C5: 2.51 | D5: 4.54 | E5: =IF(B5<=$B$2,0,(C5+D5)) -> 7.05 | F5: =(E5*(B5-$B$2)/365)/(1+$K$4)^((B5-$B$2)/365)/-$E$2/(1+$K$4)^$K$2 -> 0.10061071
A6: 14 | B6: 46762 | C6: 2.36 | D6: 4.54 | E6: =IF(B6<=$B$2,0,(C6+D6)) -> 6.9 | F6: =(E6*(B6-$B$2)/365)/(1+$K$4)^((B6-$B$2)/365)/-$E$2/(1+$K$4)^$K$2 -> 0.12806849
A7: 15 | B7: 46944 | C7: 2.27 | D7: 4.54 | E7: =IF(B7<=$B$2,0,(C7+D7)) -> 6.81 | F7: =(E7*(B7-$B$2)/365)/(1+$K$4)^((B7-$B$2)/365)/-$E$2/(1+$K$4)^$K$2 -> 0.15308533
A8: 16 | B8: 47127 | C8: 2.15 | D8: 4.54 | E8: =IF(B8<=$B$2,0,(C8+D8)) -> 6.69 | F8: =(E8*(B8-$B$2)/365)/(1+$K$4)^((B8-$B$2)/365)/-$E$2/(1+$K$4)^$K$2 -> 0.17440318
A9: 17 | B9: 47309 | C9: 2.06 | D9: 4.54 | E9: =IF(B9<=$B$2,0,(C9+D9)) -> 6.6 | F9: =(E9*(B9-$B$2)/365)/(1+$K$4)^((B9-$B$2)/365)/-$E$2/(1+$K$4)^$K$2 -> 0.19346244
A10: 18 | B10: 47492 | C10: 1.92 | D10: 4.54 | E10: =IF(B10<=$B$2,0,(C10+D10)) -> 6.46 | F10: =(E10*(B10-$B$2)/365)/(1+$K$4)^((B10-$B$2)/365)/-$E$2/(1+$K$4)^$K$2 -> 0.20843633
A11: 19 | B11: 47674 | C11: 1.83 | D11: 4.54 | E11: =IF(B11<=$B$2,0,(C11+D11)) -> 6.37 | F11: =(E11*(B11-$B$2)/365)/(1+$K$4)^((B11-$B$2)/365)/-$E$2/(1+$K$4)^$K$2 -> 0.22241522
A12: 20 | B12: 47857 | C12: 1.7 | D12: 4.54 | E12: =IF(B12<=$B$2,0,(C12+D12)) -> 6.24 | F12: =(E12*(B12-$B$2)/365)/(1+$K$4)^((B12-$B$2)/365)/-$E$2/(1+$K$4)^$K$2 -> 0.23282222
A13: 21 | B13: 48039 | C13: 1.6 | D13: 4.54 | E13: =IF(B13<=$B$2,0,(C13+D13)) -> 6.14 | F13: =(E13*(B13-$B$2)/365)/(1+$K$4)^((B13-$B$2)/365)/-$E$2/(1+$K$4)^$K$2 -> 0.24217712
A14: 22 | B14: 48222 | C14: 1.47 | D14: 4.54 | E14: =IF(B14<=$B$2,0,(C14+D14)) -> 6.01 | F14: =(E14*(B14-$B$2)/365)/(1+$K$4)^((B14-$B$2)/365)/-$E$2/(1+$K$4)^$K$2 -> 0.24851251
A15: 23 | B15: 48407 | C15: 1.39 | D15: 4.54 | E15: =IF(B15<=$B$2,0,(C15+D15)) -> 5.93 | F15: =(E15*(B15-$B$2)/365)/(1+$K$4)^((B15-$B$2)/365)/-$E$2/(1+$K$4)^$K$2 -> 0.25530876
A16: 24 | B16: 48589 | C16: 1.24 | D16: 4.54 | E16: =IF(B16<=$B$2,0,(C16+D16)) -> 5.78 | F16: =(E16*(B16-$B$2)/365)/(1+$K$4)^((B16-$B$2)/365)/-$E$2/(1+$K$4)^$K$2 -> 0.25735351
... A26: 34 | B26: 50416 | C26: 0.12 | D26: 4.66 | E26: =IF(B26<=$B$2,0,(C26+D26)) -> 4.78 | F26: =(E26*(B26-$B$2)/365)/(1+$K$4)^((B26-$B$2)/365)/-$E$2/(1+$K$4)^$K$2 -> 0.24240553

Sheet AE38D
A1: AE38D | B1: Fecha de Pago | C1: Interés | D1: Amortización | E1: Total
B2: =Main!D1 -> 46068 | E2: {=-_xll.PrecioBD(A1,"24","ASK","N")} -> -81.48 | J2: Periodo de intereses | K2: 0.5
A3: 11 | B3: 46213 | C3: 2.51 | D3: 0 | E3: =IF(B3<=$B$2,0,(C3+D3)) -> 2.51 | F3: =(E3*(B3-$B$2)/365)/(1+$K$4)^((B3-$B$2)/365)/-$E$2/(1+$K$4)^$K$2 -> 0.011301698 | J3: MDUR | K3: =SUM(F3:F102) -> 4.9172261
A4: 12 | B4: 46398 | C4: 2.51 | D4: 0 | E4: =IF(B4<=$B$2,0,(C4+D4)) -> 2.51 | F4: =(E4*(B4-$B$2)/365)/(1+$K$4)^((B4-$B$2)/365)/-$E$2/(1+$K$4)^$K$2 -> 0.024590679 | J4: TIR | K4: =XIRR(E2:E26,B2:B26) -> 0.092724559
A5: 13 | B5: 46580 | C5: 2.51 | D5: 4.54 | E5: =IF(B5<=$B$2,0,(C5+D5)) -> 7.05 | F5: =(E5*(B5-$B$2)/365)/(1+$K$4)^((B5-$B$2)/365)/-$E$2/(1+$K$4)^$K$2 -> 0.10252726
A6: 14 | B6: 46762 | C6: 2.36 | D6: 4.54 | E6: =IF(B6<=$B$2,0,(C6+D6)) -> 6.9 | F6: =(E6*(B6-$B$2)/365)/(1+$K$4)^((B6-$B$2)/365)/-$E$2/(1+$K$4)^$K$2 -> 0.13013264
A7: 15 | B7: 46944 | C7: 2.27 | D7: 4.54 | E7: =IF(B7<=$B$2,0,(C7+D7)) -> 6.81 | F7: =(E7*(B7-$B$2)/365)/(1+$K$4)^((B7-$B$2)/365)/-$E$2/(1+$K$4)^$K$2 -> 0.15510518
A8: 16 | B8: 47127 | C8: 2.15 | D8: 4.54 | E8: =IF(B8<=$B$2,0,(C8+D8)) -> 6.69 | F8: =(E8*(B8-$B$2)/365)/(1+$K$4)^((B8-$B$2)/365)/-$E$2/(1+$K$4)^$K$2 -> 0.17619316
A9: 17 | B9: 47309 | C9: 2.06 | D9: 4.54 | E9: =IF(B9<=$B$2,0,(C9+D9)) -> 6.6 | F9: =(E9*(B9-$B$2)/365)/(1+$K$4)^((B9-$B$2)/365)/-$E$2/(1+$K$4)^$K$2 -> 0.19488575
A10: 18 | B10: 47492 | C10: 1.92 | D10: 4.54 | E10: =IF(B10<=$B$2,0,(C10+D10)) -> 6.46 | F10: =(E10*(B10-$B$2)/365)/(1+$K$4)^((B10-$B$2)/365)/-$E$2/(1+$K$4)^$K$2 -> 0.20936244
A11: 19 | B11: 47674 | C11: 1.83 | D11: 4.54 | E11: =IF(B11<=$B$2,0,(C11+D11)) -> 6.37 | F11: =(E11*(B11-$B$2)/365)/(1+$K$4)^((B11-$B$2)/365)/-$E$2/(1+$K$4)^$K$2 -> 0.22276073
A12: 20 | B12: 47857 | C12: 1.7 | D12: 4.54 | E12: =IF(B12<=$B$2,0,(C12+D12)) -> 6.24 | F12: =(E12*(B12-$B$2)/365)/(1+$K$4)^((B12-$B$2)/365)/-$E$2/(1+$K$4)^$K$2 -> 0.23250939
A13: 21 | B13: 48039 | C13: 1.6 | D13: 4.54 | E13: =IF(B13<=$B$2,0,(C13+D13)) -> 6.14 | F13: =(E13*(B13-$B$2)/365)/(1+$K$4)^((B13-$B$2)/365)/-$E$2/(1+$K$4)^$K$2 -> 0.24115594
A14: 22 | B14: 48222 | C14: 1.47 | D14: 4.54 | E14: =IF(B14<=$B$2,0,(C14+D14)) -> 6.01 | F14: =(E14*(B14-$B$2)/365)/(1+$K$4)^((B14-$B$2)/365)/-$E$2/(1+$K$4)^$K$2 -> 0.24674879
A15: 23 | B15: 48407 | C15: 1.39 | D15: 4.54 | E15: =IF(B15<=$B$2,0,(C15+D15)) -> 5.93 | F15: =(E15*(B15-$B$2)/365)/(1+$K$4)^((B15-$B$2)/365)/-$E$2/(1+$K$4)^$K$2 -> 0.25275552
A16: 24 | B16: 48589 | C16: 1.24 | D16: 4.54 | E16: =IF(B16<=$B$2,0,(C16+D16)) -> 5.78 | F16: =(E16*(B16-$B$2)/365)/(1+$K$4)^((B16-$B$2)/365)/-$E$2/(1+$K$4)^$K$2 -> 0.25404685
... A26: 34 | B26: 50416 | C26: 0.12 | D26: 4.66 | E26: =IF(B26<=$B$2,0,(C26+D26)) -> 4.78 | F26: =(E26*(B26-$B$2)/365)/(1+$K$4)^((B26-$B$2)/365)/-$E$2/(1+$K$4)^$K$2 -> 0.23246953

Sheet GD35D
A1: GD35D | B1: Fecha de Pago | C1: Interés | D1: Amortización | E1: Total
B2: =Main!D1 -> 46068 | E2: {=-_xll.PrecioBD(A1,"24","ASK","N")} -> -80.37 | J2: Periodo de intereses | K2: 0.5
A3: 11 | B3: 46213 | C3: 2.07 | D3: 0 | E3: =IF(B3<=$B$2,0,(C3+D3)) -> 2.07 | F3: =(E3*(B3-$B$2)/365)/(1+$K$4)^((B3-$B$2)/365)/-$E$2/(1+$K$4)^$K$2 -> 0.00948866 | J3: MDUR | K3: =SUM(F3:F102) -> 5.6843481
A4: 12 | B4: 46398 | C4: 2.05 | D4: 0 | E4: =IF(B4<=$B$2,0,(C4+D4)) -> 2.05 | F4: =(E4*(B4-$B$2)/365)/(1+$K$4)^((B4-$B$2)/365)/-$E$2/(1+$K$4)^$K$2 -> 0.020494449 | J4: TIR | K4: =XIRR(E2:E26,B2:B26) -> 0.087667724
A5: 13 | B5: 46580 | C5: 2.1 | D5: 0 | E5: =IF(B5<=$B$2,0,(C5+D5)) -> 2.1 | F5: =(E5*(B5-$B$2)/365)/(1+$K$4)^((B5-$B$2)/365)/-$E$2/(1+$K$4)^$K$2 -> 0.031236299
A6: 14 | B6: 46762 | C6: 2.35 | D6: 0 | E6: =IF(B6<=$B$2,0,(C6+D6)) -> 2.35 | F6: =(E6*(B6-$B$2)/365)/(1+$K$4)^((B6-$B$2)/365)/-$E$2/(1+$K$4)^$K$2 -> 0.045435941
A7: 15 | B7: 46944 | C7: 2.38 | D7: 0 | E7: =IF(B7<=$B$2,0,(C7+D7)) -> 2.38 | F7: =(E7*(B7-$B$2)/365)/(1+$K$4)^((B7-$B$2)/365)/-$E$2/(1+$K$4)^$K$2 -> 0.055699992
A8: 16 | B8: 47127 | C8: 2.49 | D8: 0 | E8: =IF(B8<=$B$2,0,(C8+D8)) -> 2.49 | F8: =(E8*(B8-$B$2)/365)/(1+$K$4)^((B8-$B$2)/365)/-$E$2/(1+$K$4)^$K$2 -> 0.067541587
A9: 17 | B9: 47309 | C9: 2.51 | D9: 0 | E9: =IF(B9<=$B$2,0,(C9+D9)) -> 2.51 | F9: =(E9*(B9-$B$2)/365)/(1+$K$4)^((B9-$B$2)/365)/-$E$2/(1+$K$4)^$K$2 -> 0.076510903
A10: 18 | B10: 47492 | C10: 2.49 | D10: 0 | E10: =IF(B10<=$B$2,0,(C10+D10)) -> 2.49 | F10: =(E10*(B10-$B$2)/365)/(1+$K$4)^((B10-$B$2)/365)/-$E$2/(1+$K$4)^$K$2 -> 0.083500494
A11: 19 | B11: 47674 | C11: 2.51 | D11: 0 | E11: =IF(B11<=$B$2,0,(C11+D11)) -> 2.51 | F11: =(E11*(B11-$B$2)/365)/(1+$K$4)^((B11-$B$2)/365)/-$E$2/(1+$K$4)^$K$2 -> 0.091033417
A12: 20 | B12: 47857 | C12: 2.49 | D12: 10 | E12: =IF(B12<=$B$2,0,(C12+D12)) -> 12.49 | F12: =(E12*(B12-$B$2)/365)/(1+$K$4)^((B12-$B$2)/365)/-$E$2/(1+$K$4)^$K$2 -> 0.48378929
A13: 21 | B13: 48039 | C13: 2.26 | D13: 10 | E13: =IF(B13<=$B$2,0,(C13+D13)) -> 12.26 | F13: =(E13*(B13-$B$2)/365)/(1+$K$4)^((B13-$B$2)/365)/-$E$2/(1+$K$4)^$K$2 -> 0.50172118
A14: 22 | B14: 48222 | C14: 1.99 | D14: 10 | E14: =IF(B14<=$B$2,0,(C14+D14)) -> 11.99 | F14: =(E14*(B14-$B$2)/365)/(1+$K$4)^((B14-$B$2)/365)/-$E$2/(1+$K$4)^$K$2 -> 0.51410533
A15: 23 | B15: 48407 | C15: 1.78 | D15: 10 | E15: =IF(B15<=$B$2,0,(C15+D15)) -> 11.78 | F15: =(E15*(B15-$B$2)/365)/(1+$K$4)^((B15-$B$2)/365)/-$E$2/(1+$K$4)^$K$2 -> 0.52561124
A16: 24 | B16: 48589 | C16: 1.48 | D16: 10 | E16: =IF(B16<=$B$2,0,(C16+D16)) -> 11.48 | F16: =(E16*(B16-$B$2)/365)/(1+$K$4)^((B16-$B$2)/365)/-$E$2/(1+$K$4)^$K$2 -> 0.52942658
... A21: 29 | B21: 49500 | C21: 0.25 | D21: 10 | E21: =IF(B21<=$B$2,0,(C21+D21)) -> 10.25 | F21: =(E21*(B21-$B$2)/365)/(1+$K$4)^((B21-$B$2)/365)/-$E$2/(1+$K$4)^$K$2 -> 0.5217609

Sheet AL35D
A1: AL35D | B1: Fecha de Pago | C1: Interés | D1: Amortización | E1: Total
B2: =Main!D1 -> 46068 | E2: {=-_xll.PrecioBD(A1,"24","ASK","N")} -> -78.83 | J2: Periodo de intereses | K2: 0.5
A3: 11 | B3: 46213 | C3: 2.07 | D3: 0 | E3: =IF(B3<=$B$2,0,(C3+D3)) -> 2.07 | F3: =(E3*(B3-$B$2)/365)/(1+$K$4)^((B3-$B$2)/365)/-$E$2/(1+$K$4)^$K$2 -> 0.0096456991 | J3: MDUR | K3: =SUM(F3:F102) -> 5.6582089
A4: 12 | B4: 46398 | C4: 2.05 | D4: 0 | E4: =IF(B4<=$B$2,0,(C4+D4)) -> 2.05 | F4: =(E4*(B4-$B$2)/365)/(1+$K$4)^((B4-$B$2)/365)/-$E$2/(1+$K$4)^$K$2 -> 0.020799152 | J4: TIR | K4: =XIRR(E2:E26,B2:B26) -> 0.091228488
A5: 13 | B5: 46580 | C5: 2.1 | D5: 0 | E5: =IF(B5<=$B$2,0,(C5+D5)) -> 2.1 | F5: =(E5*(B5-$B$2)/365)/(1+$K$4)^((B5-$B$2)/365)/-$E$2/(1+$K$4)^$K$2 -> 0.031649085
A6: 14 | B6: 46762 | C6: 2.35 | D6: 0 | E6: =IF(B6<=$B$2,0,(C6+D6)) -> 2.35 | F6: =(E6*(B6-$B$2)/365)/(1+$K$4)^((B6-$B$2)/365)/-$E$2/(1+$K$4)^$K$2 -> 0.045961409
A7: 15 | B7: 46944 | C7: 2.38 | D7: 0 | E7: =IF(B7<=$B$2,0,(C7+D7)) -> 2.38 | F7: =(E7*(B7-$B$2)/365)/(1+$K$4)^((B7-$B$2)/365)/-$E$2/(1+$K$4)^$K$2 -> 0.056252413
A8: 16 | B8: 47127 | C8: 2.49 | D8: 0 | E8: =IF(B8<=$B$2,0,(C8+D8)) -> 2.49 | F8: =(E8*(B8-$B$2)/365)/(1+$K$4)^((B8-$B$2)/365)/-$E$2/(1+$K$4)^$K$2 -> 0.068099765
A9: 17 | B9: 47309 | C9: 2.51 | D9: 0 | E9: =IF(B9<=$B$2,0,(C9+D9)) -> 2.51 | F9: =(E9*(B9-$B$2)/365)/(1+$K$4)^((B9-$B$2)/365)/-$E$2/(1+$K$4)^$K$2 -> 0.077017586
A10: 18 | B10: 47492 | C10: 2.49 | D10: 0 | E10: =IF(B10<=$B$2,0,(C10+D10)) -> 2.49 | F10: =(E10*(B10-$B$2)/365)/(1+$K$4)^((B10-$B$2)/365)/-$E$2/(1+$K$4)^$K$2 -> 0.08391584
A11: 19 | B11: 47674 | C11: 2.51 | D11: 0 | E11: =IF(B11<=$B$2,0,(C11+D11)) -> 2.51 | F11: =(E11*(B11-$B$2)/365)/(1+$K$4)^((B11-$B$2)/365)/-$E$2/(1+$K$4)^$K$2 -> 0.091337257
A12: 20 | B12: 47857 | C12: 2.49 | D12: 10 | E12: =IF(B12<=$B$2,0,(C12+D12)) -> 12.49 | F12: =(E12*(B12-$B$2)/365)/(1+$K$4)^((B12-$B$2)/365)/-$E$2/(1+$K$4)^$K$2 -> 0.48460924
A13: 21 | B13: 48039 | C13: 2.26 | D13: 10 | E13: =IF(B13<=$B$2,0,(C13+D13)) -> 12.26 | F13: =(E13*(B13-$B$2)/365)/(1+$K$4)^((B13-$B$2)/365)/-$E$2/(1+$K$4)^$K$2 -> 0.50175314
A14: 22 | B14: 48222 | C14: 1.99 | D14: 10 | E14: =IF(B14<=$B$2,0,(C14+D14)) -> 11.99 | F14: =(E14*(B14-$B$2)/365)/(1+$K$4)^((B14-$B$2)/365)/-$E$2/(1+$K$4)^$K$2 -> 0.51329626
A15: 23 | B15: 48407 | C15: 1.78 | D15: 10 | E15: =IF(B15<=$B$2,0,(C15+D15)) -> 11.78 | F15: =(E15*(B15-$B$2)/365)/(1+$K$4)^((B15-$B$2)/365)/-$E$2/(1+$K$4)^$K$2 -> 0.52391543
A16: 24 | B16: 48589 | C16: 1.48 | D16: 10 | E16: =IF(B16<=$B$2,0,(C16+D16)) -> 11.48 | F16: =(E16*(B16-$B$2)/365)/(1+$K$4)^((B16-$B$2)/365)/-$E$2/(1+$K$4)^$K$2 -> 0.52685912
... A21: 29 | B21: 49500 | C21: 0.25 | D21: 10 | E21: =IF(B21<=$B$2,0,(C21+D21)) -> 10.25 | F21: =(E21*(B21-$B$2)/365)/(1+$K$4)^((B21-$B$2)/365)/-$E$2/(1+$K$4)^$K$2 -> 0.51501217

Sheet GD30D
A1: GD30D | B1: Fecha de Pago | C1: Interés | D1: Amortización | E1: Total
B2: =Main!D1 -> 46068 | E2: {=-_xll.PrecioBD(A1,"24","ASK","N")} -> -63.73 | J2: Periodo de intereses | K2: 0.5
A3: 11 | B3: 46213 | C3: 0.27 | D3: 8 | E3: =IF(B3<=$B$2,0,(C3+D3)) -> 8.27 | F3: =(E3*(B3-$B$2)/365)/(1+$K$4)^((B3-$B$2)/365)/-$E$2/(1+$K$4)^$K$2 -> 0.048631337 | J3: MDUR | K3: =SUM(F3:F102) -> 2.2121439
A4: 12 | B4: 46398 | C4: 0.24 | D4: 8 | E4: =IF(B4<=$B$2,0,(C4+D4)) -> 8.24 | F4: =(E4*(B4-$B$2)/365)/(1+$K$4)^((B4-$B$2)/365)/-$E$2/(1+$K$4)^$K$2 -> 0.10670399 | J4: TIR | K4: =XIRR(E2:E26,B2:B26) -> 0.067136118
A5: 13 | B5: 46580 | C5: 0.21 | D5: 8 | E5: =IF(B5<=$B$2,0,(C5+D5)) -> 8.21 | F5: =(E5*(B5-$B$2)/365)/(1+$K$4)^((B5-$B$2)/365)/-$E$2/(1+$K$4)^$K$2 -> 0.15969134
A6: 14 | B6: 46762 | C6: 0.42 | D6: 8 | E6: =IF(B6<=$B$2,0,(C6+D6)) -> 8.42 | F6: =(E6*(B6-$B$2)/365)/(1+$K$4)^((B6-$B$2)/365)/-$E$2/(1+$K$4)^$K$2 -> 0.2149159
A7: 15 | B7: 46944 | C7: 0.35 | D7: 8 | E7: =IF(B7<=$B$2,0,(C7+D7)) -> 8.35 | F7: =(E7*(B7-$B$2)/365)/(1+$K$4)^((B7-$B$2)/365)/-$E$2/(1+$K$4)^$K$2 -> 0.26044518
A8: 16 | B8: 47127 | C8: 0.28 | D8: 8 | E8: =IF(B8<=$B$2,0,(C8+D8)) -> 8.28 | F8: =(E8*(B8-$B$2)/365)/(1+$K$4)^((B8-$B$2)/365)/-$E$2/(1+$K$4)^$K$2 -> 0.30220627
A9: 17 | B9: 47309 | C9: 0.21 | D9: 8 | E9: =IF(B9<=$B$2,0,(C9+D9)) -> 8.21 | F9: =(E9*(B9-$B$2)/365)/(1+$K$4)^((B9-$B$2)/365)/-$E$2/(1+$K$4)^$K$2 -> 0.33995455
A10: 18 | B10: 47492 | C10: 0.14 | D10: 8 | E10: =IF(B10<=$B$2,0,(C10+D10)) -> 8.14 | F10: =(E10*(B10-$B$2)/365)/(1+$K$4)^((B10-$B$2)/365)/-$E$2/(1+$K$4)^$K$2 -> 0.37436199
A11: 19 | B11: 47674 | C11: 0.07 | D11: 8 | E11: =IF(B11<=$B$2,0,(C11+D11)) -> 8.07 | F11: =(E11*(B11-$B$2)/365)/(1+$K$4)^((B11-$B$2)/365)/-$E$2/(1+$K$4)^$K$2 -> 0.40523335

Sheet AL30D
A1: AL30D | B1: Fecha de Pago | C1: Interés | D1: Amortización | E1: Total
B2: =Main!D1 -> 46068 | E2: {=-_xll.PrecioBD(A1,"24","ASK","N")} -> -62.17 | J2: Periodo de intereses | K2: 0.5
A3: 11 | B3: 46213 | C3: 0.27 | D3: 8 | E3: =IF(B3<=$B$2,0,(C3+D3)) -> 8.27 | F3: =(E3*(B3-$B$2)/365)/(1+$K$4)^((B3-$B$2)/365)/-$E$2/(1+$K$4)^$K$2 -> 0.049366985 | J3: MDUR | K3: =SUM(F3:F102) -> 2.1828813
A4: 12 | B4: 46398 | C4: 0.24 | D4: 8 | E4: =IF(B4<=$B$2,0,(C4+D4)) -> 8.24 | F4: =(E4*(B4-$B$2)/365)/(1+$K$4)^((B4-$B$2)/365)/-$E$2/(1+$K$4)^$K$2 -> 0.10772201 | J4: TIR | K4: =XIRR(E2:E26,B2:B26) -> 0.078818211
A5: 13 | B5: 46580 | C5: 0.21 | D5: 8 | E5: =IF(B5<=$B$2,0,(C5+D5)) -> 8.21 | F5: =(E5*(B5-$B$2)/365)/(1+$K$4)^((B5-$B$2)/365)/-$E$2/(1+$K$4)^$K$2 -> 0.16034204
A6: 14 | B6: 46762 | C6: 0.42 | D6: 8 | E6: =IF(B6<=$B$2,0,(C6+D6)) -> 8.42 | F6: =(E6*(B6-$B$2)/365)/(1+$K$4)^((B6-$B$2)/365)/-$E$2/(1+$K$4)^$K$2 -> 0.21462329
A7: 15 | B7: 46944 | C7: 0.35 | D7: 8 | E7: =IF(B7<=$B$2,0,(C7+D7)) -> 8.35 | F7: =(E7*(B7-$B$2)/365)/(1+$K$4)^((B7-$B$2)/365)/-$E$2/(1+$K$4)^$K$2 -> 0.25868239
A8: 16 | B8: 47127 | C8: 0.28 | D8: 8 | E8: =IF(B8<=$B$2,0,(C8+D8)) -> 8.28 | F8: =(E8*(B8-$B$2)/365)/(1+$K$4)^((B8-$B$2)/365)/-$E$2/(1+$K$4)^$K$2 -> 0.29852679
A9: 17 | B9: 47309 | C9: 0.21 | D9: 8 | E9: =IF(B9<=$B$2,0,(C9+D9)) -> 8.21 | F9: =(E9*(B9-$B$2)/365)/(1+$K$4)^((B9-$B$2)/365)/-$E$2/(1+$K$4)^$K$2 -> 0.3339973
A10: 18 | B10: 47492 | C10: 0.14 | D10: 8 | E10: =IF(B10<=$B$2,0,(C10+D10)) -> 8.14 | F10: =(E10*(B10-$B$2)/365)/(1+$K$4)^((B10-$B$2)/365)/-$E$2/(1+$K$4)^$K$2 -> 0.36579953
A11: 19 | B11: 47674 | C11: 0.07 | D11: 8 | E11: =IF(B11<=$B$2,0,(C11+D11)) -> 8.07 | F11: =(E11*(B11-$B$2)/365)/(1+$K$4)^((B11-$B$2)/365)/-$E$2/(1+$K$4)^$K$2 -> 0.39382096

Sheet GD29D
A1: GD29D | B1: Fecha de Pago | C1: Interés | D1: Amortización | E1: Total
B2: =Main!D1 -> 46068 | E2: {=-_xll.PrecioBD(A1,"24","ASK","N")} -> -64.63 | J2: Periodo de intereses | K2: 0.5
A3: 11 | B3: 46213 | C3: 0.35 | D3: 10 | E3: =IF(B3<=$B$2,0,(C3+D3)) -> 10.35 | F3: =(E3*(B3-$B$2)/365)/(1+$K$4)^((B3-$B$2)/365)/-$E$2/(1+$K$4)^$K$2 -> 0.060640241 | J3: MDUR | K3: =SUM(F3:F102) -> 1.7893463
A4: 12 | B4: 46398 | C4: 0.3 | D4: 10 | E4: =IF(B4<=$B$2,0,(C4+D4)) -> 10.3 | F4: =(E4*(B4-$B$2)/365)/(1+$K$4)^((B4-$B$2)/365)/-$E$2/(1+$K$4)^$K$2 -> 0.13367266 | J4: TIR | K4: =XIRR(E2:E26,B2:B26) -> 0.05488334
A5: 13 | B5: 46580 | C5: 0.25 | D5: 10 | E5: =IF(B5<=$B$2,0,(C5+D5)) -> 10.25 | F5: =(E5*(B5-$B$2)/365)/(1+$K$4)^((B5-$B$2)/365)/-$E$2/(1+$K$4)^$K$2 -> 0.2009624
A6: 14 | B6: 46762 | C6: 0.2 | D6: 10 | E6: =IF(B6<=$B$2,0,(C6+D6)) -> 10.2 | F6: =(E6*(B6-$B$2)/365)/(1+$K$4)^((B6-$B$2)/365)/-$E$2/(1+$K$4)^$K$2 -> 0.26394303
A7: 15 | B7: 46944 | C7: 0.15 | D7: 10 | E7: =IF(B7<=$B$2,0,(C7+D7)) -> 10.15 | F7: =(E7*(B7-$B$2)/365)/(1+$K$4)^((B7-$B$2)/365)/-$E$2/(1+$K$4)^$K$2 -> 0.32281245
A8: 16 | B8: 47127 | C8: 0.1 | D8: 10 | E8: =IF(B8<=$B$2,0,(C8+D8)) -> 10.1 | F8: =(E8*(B8-$B$2)/365)/(1+$K$4)^((B8-$B$2)/365)/-$E$2/(1+$K$4)^$K$2 -> 0.37806237
A9: 17 | B9: 47309 | C9: 0.05 | D9: 10 | E9: =IF(B9<=$B$2,0,(C9+D9)) -> 10.05 | F9: =(E9*(B9-$B$2)/365)/(1+$K$4)^((B9-$B$2)/365)/-$E$2/(1+$K$4)^$K$2 -> 0.42925319

Sheet AL29D
A1: AL29D | B1: Fecha de Pago | C1: Interés | D1: Amortización | E1: Total
B2: =Main!D1 -> 46068 | E2: {=-_xll.PrecioBD(A1,"24","ASK","N")} -> -62.99 | J2: Periodo de intereses | K2: 0.5
A3: 11 | B3: 46213 | C3: 0.35 | D3: 10 | E3: =IF(B3<=$B$2,0,(C3+D3)) -> 10.35 | F3: =(E3*(B3-$B$2)/365)/(1+$K$4)^((B3-$B$2)/365)/-$E$2/(1+$K$4)^$K$2 -> 0.061440221 | J3: MDUR | K3: =SUM(F3:F102) -> 1.763296
A4: 12 | B4: 46398 | C4: 0.3 | D4: 10 | E4: =IF(B4<=$B$2,0,(C4+D4)) -> 10.3 | F4: =(E4*(B4-$B$2)/365)/(1+$K$4)^((B4-$B$2)/365)/-$E$2/(1+$K$4)^$K$2 -> 0.13447579 | J4: TIR | K4: =XIRR(E2:E26,B2:B26) -> 0.069797418
A5: 13 | B5: 46580 | C5: 0.25 | D5: 10 | E5: =IF(B5<=$B$2,0,(C5+D5)) -> 10.25 | F5: =(E5*(B5-$B$2)/365)/(1+$K$4)^((B5-$B$2)/365)/-$E$2/(1+$K$4)^$K$2 -> 0.20075952
A6: 14 | B6: 46762 | C6: 0.2 | D6: 10 | E6: =IF(B6<=$B$2,0,(C6+D6)) -> 10.2 | F6: =(E6*(B6-$B$2)/365)/(1+$K$4)^((B6-$B$2)/365)/-$E$2/(1+$K$4)^$K$2 -> 0.26183718
A7: 15 | B7: 46944 | C7: 0.15 | D7: 10 | E7: =IF(B7<=$B$2,0,(C7+D7)) -> 10.15 | F7: =(E7*(B7-$B$2)/365)/(1+$K$4)^((B7-$B$2)/365)/-$E$2/(1+$K$4)^$K$2 -> 0.31800298
A8: 16 | B8: 47127 | C8: 0.1 | D8: 10 | E8: =IF(B8<=$B$2,0,(C8+D8)) -> 10.1 | F8: =(E8*(B8-$B$2)/365)/(1+$K$4)^((B8-$B$2)/365)/-$E$2/(1+$K$4)^$K$2 -> 0.36981751
A9: 17 | B9: 47309 | C9: 0.05 | D9: 10 | E9: =IF(B9<=$B$2,0,(C9+D9)) -> 10.05 | F9: =(E9*(B9-$B$2)/365)/(1+$K$4)^((B9-$B$2)/365)/-$E$2/(1+$K$4)^$K$2 -> 0.41696283

Sheet MCC2D
A1: MCC2D | B1: Fecha de Pago | C1: Interés | D1: Amortización | E1: Total
B2: =Main!D1 -> 46068 | E2: =-VLOOKUP(A1,'ONs Argentina'!$C$5:$N$68,3,0) -> -102 | J2: Periodo de intereses | K2: 0.5
A3: 2 | B3: 46175 | C3: 3.74 | D3: 0 | E3: =IF(B3<=$B$2,0,(C3+D3)) -> 3.74 | F3: =(E3*(B3-$B$2)/365)/(1+$K$4)^((B3-$B$2)/365)/-$E$2/(1+$K$4)^$K$2 -> 0.010169456 | J3: MDUR | K3: =SUM(F3:F102) -> 1.197278
A4: 3 | B4: 46358 | C4: 3.76 | D4: 0 | E4: =IF(B4<=$B$2,0,(C4+D4)) -> 3.76 | F4: =(E4*(B4-$B$2)/365)/(1+$K$4)^((B4-$B$2)/365)/-$E$2/(1+$K$4)^$K$2 -> 0.026755703 | J4: TIR | K4: =XIRR(E2:E26,B2:B26) -> 0.072359821
A5: 4 | B5: 46540 | C5: 3.74 | D5: 100 | E5: =IF(B5<=$B$2,0,(C5+D5)) -> 103.74 | F5: =(E5*(B5-$B$2)/365)/(1+$K$4)^((B5-$B$2)/365)/-$E$2/(1+$K$4)^$K$2 -> 1.1603528
E9: =IF(B9<=$B$2,0,(C9+D9)) -> 0 | F9: =(E9*(B9-$B$2)/365)/(1+$K$4)^((B9-$B$2)/365)/-$E$2/(1+$K$4)^$K$2 -> 0

Sheet PFC2D
A1: PFC2D | B1: Fecha de Pago | C1: Interés | D1: Amortización | E1: Total
B2: =Main!D1 -> 46068 | E2: =-VLOOKUP(A1,'ONs Argentina'!$C$5:$N$68,3,0) -> -102.55 | J2: Periodo de intereses | K2: 0.5
A3: 2 | B3: 46217 | C3: 3.65 | D3: 0 | E3: =IF(B3<=$B$2,0,(C3+D3)) -> 3.65 | F3: =(E3*(B3-$B$2)/365)/(1+$K$4)^((B3-$B$2)/365)/-$E$2/(1+$K$4)^$K$2 -> 0.013779074 | J3: MDUR | K3: =SUM(F3:F102) -> 1.3174273
A4: 3 | B4: 46401 | C4: 3.71 | D4: 0 | E4: =IF(B4<=$B$2,0,(C4+D4)) -> 3.71 | F4: =(E4*(B4-$B$2)/365)/(1+$K$4)^((B4-$B$2)/365)/-$E$2/(1+$K$4)^$K$2 -> 0.030393161 | J4: TIR | K4: =XIRR(E2:E26,B2:B26) -> 0.060127088
A5: 4 | B5: 46582 | C5: 3.65 | D5: 100 | E5: =IF(B5<=$B$2,0,(C5+D5)) -> 103.65 | F5: =(E5*(B5-$B$2)/365)/(1+$K$4)^((B5-$B$2)/365)/-$E$2/(1+$K$4)^$K$2 -> 1.273255
E9: =IF(B9<=$B$2,0,(C9+D9)) -> 0 | F9: =(E9*(B9-$B$2)/365)/(1+$K$4)^((B9-$B$2)/365)/-$E$2/(1+$K$4)^$K$2 -> 0

Sheet YM38D
A1: YM38D | B1: Fecha de Pago | C1: Interés | D1: Amortización | E1: Total
B2: =Main!D1 -> 46068 | E2: {=-_xll.PrecioBD(A1,"24","ASK","N")} -> -103.6 | J2: Periodo de intereses | K2: 0.5
A3: 3 | B3: 46134 | C3: 1.85 | D3: 0 | E3: =IF(B3<=$B$2,0,(C3+D3)) -> 1.85 | F3: =(E3*(B3-$B$2)/365)/(1+$K$4)^((B3-$B$2)/365)/-$E$2/(1+$K$4)^$K$2 -> 0.0031167279 | J3: MDUR | K3: =SUM(F3:F102) -> 1.3294178
A4: 4 | B4: 46225 | C4: 1.87 | D4: 0 | E4: =IF(B4<=$B$2,0,(C4+D4)) -> 1.87 | F4: =(E4*(B4-$B$2)/365)/(1+$K$4)^((B4-$B$2)/365)/-$E$2/(1+$K$4)^$K$2 -> 0.0073977248 | J4: TIR | K4: =XIRR(E2:E26,B2:B26) -> 0.053336343
A5: 5 | B5: 46317 | C5: 1.89 | D5: 0 | E5: =IF(B5<=$B$2,0,(C5+D5)) -> 1.89 | F5: =(E5*(B5-$B$2)/365)/(1+$K$4)^((B5-$B$2)/365)/-$E$2/(1+$K$4)^$K$2 -> 0.011703882 | J5: ONS
A6: 6 | B6: 46409 | C6: 1.89 | D6: 0 | E6: =IF(B6<=$B$2,0,(C6+D6)) -> 1.89 | F6: =(E6*(B6-$B$2)/365)/(1+$K$4)^((B6-$B$2)/365)/-$E$2/(1+$K$4)^$K$2 -> 0.015819648
A7: 7 | B7: 46499 | C7: 1.85 | D7: 0 | E7: =IF(B7<=$B$2,0,(C7+D7)) -> 1.85 | F7: =(E7*(B7-$B$2)/365)/(1+$K$4)^((B7-$B$2)/365)/-$E$2/(1+$K$4)^$K$2 -> 0.019322582
A8: 8 | B8: 46590 | C8: 1.87 | D8: 100 | E8: =IF(B8<=$B$2,0,(C8+D8)) -> 101.87 | F8: =(E8*(B8-$B$2)/365)/(1+$K$4)^((B8-$B$2)/365)/-$E$2/(1+$K$4)^$K$2 -> 1.2720572
E9: =IF(B9<=$B$2,0,(C9+D9)) -> 0 | F9: =(E9*(B9-$B$2)/365)/(1+$K$4)^((B9-$B$2)/365)/-$E$2/(1+$K$4)^$K$2 -> 0

Sheet PN38D
A1: PN38D | B1: Fecha de Pago | C1: Interés | D1: Amortización | E1: Total
B2: =Main!D1 -> 46068 | E2: {=-_xll.PrecioBD(A1,"24","ASK","N")} -> -103.9 | J2: Periodo de intereses | K2: 0.5
A3: 2 | B3: 46064 | C3: 3.28 | D3: 0 | E3: =IF(B3<=$B$2,0,(C3+D3)) -> 0 | F3: =(E3*(B3-$B$2)/365)/(1+$K$4)^((B3-$B$2)/365)/-$E$2/(1+$K$4)^$K$2 -> 0 | J3: MDUR | K3: =SUM(F3:F102) -> 1.4124417
A4: 3 | B4: 46245 | C4: 3.22 | D4: 0 | E4: =IF(B4<=$B$2,0,(C4+D4)) -> 3.22 | F4: =(E4*(B4-$B$2)/365)/(1+$K$4)^((B4-$B$2)/365)/-$E$2/(1+$K$4)^$K$2 -> 0.014478775 | J4: TIR | K4: =XIRR(E2:E26,B2:B26) -> 0.038571939
A5: 4 | B5: 46429 | C5: 3.28 | D5: 0 | E5: =IF(B5<=$B$2,0,(C5+D5)) -> 3.28 | F5: =(E5*(B5-$B$2)/365)/(1+$K$4)^((B5-$B$2)/365)/-$E$2/(1+$K$4)^$K$2 -> 0.029511948 | J5: ONS
A6: 5 | B6: 46610 | C6: 3.22 | D6: 100 | E6: =IF(B6<=$B$2,0,(C6+D6)) -> 103.22 | F6: =(E6*(B6-$B$2)/365)/(1+$K$4)^((B6-$B$2)/365)/-$E$2/(1+$K$4)^$K$2 -> 1.3684509
E7: =IF(B7<=$B$2,0,(C7+D7)) -> 0 | F7: =(E7*(B7-$B$2)/365)/(1+$K$4)^((B7-$B$2)/365)/-$E$2/(1+$K$4)^$K$2 -> 0
E8: =IF(B8<=$B$2,0,(C8+D8)) -> 0 | F8: =(E8*(B8-$B$2)/365)/(1+$K$4)^((B8-$B$2)/365)/-$E$2/(1+$K$4)^$K$2 -> 0
E9: =IF(B9<=$B$2,0,(C9+D9)) -> 0 | F9: =(E9*(B9-$B$2)/365)/(1+$K$4)^((B9-$B$2)/365)/-$E$2/(1+$K$4)^$K$2 -> 0

Sheet SBC1D
A1: SBC1D | B1: Fecha de Pago | C1: Interés | D1: Amortización | E1: Total
B2: =Main!D1 -> 46068 | E2: {=-_xll.PrecioBD(A1,"24","ASK","N")} -> -106 | J2: Periodo de intereses | K2: 0.5
A3: 1 | B3: 46086 | C3: 3.62 | D3: 14 | E3: =IF(B3<=$B$2,0,(C3+D3)) -> 17.62 | F3: =(E3*(B3-$B$2)/365)/(1+$K$4)^((B3-$B$2)/365)/-$E$2/(1+$K$4)^$K$2 -> 0.0079654845 | J3: MDUR | K3: =SUM(F3:F102) -> 0.75490111
A4: 2 | B4: 46178 | C4: 1.92 | D4: 14 | E4: =IF(B4<=$B$2,0,(C4+D4)) -> 15.92 | F4: =(E4*(B4-$B$2)/365)/(1+$K$4)^((B4-$B$2)/365)/-$E$2/(1+$K$4)^$K$2 -> 0.043405903 | J4: TIR | K4: =XIRR(E2:E26,B2:B26) -> 0.053650096
A5: 3 | B5: 46272 | C5: 1.61 | D5: 14 | E5: =IF(B5<=$B$2,0,(C5+D5)) -> 15.61 | F5: =(E5*(B5-$B$2)/365)/(1+$K$4)^((B5-$B$2)/365)/-$E$2/(1+$K$4)^$K$2 -> 0.07787553 | J5: ONS
A6: 4 | B6: 46363 | C6: 1.28 | D6: 14 | E6: =IF(B6<=$B$2,0,(C6+D6)) -> 15.28 | F6: =(E6*(B6-$B$2)/365)/(1+$K$4)^((B6-$B$2)/365)/-$E$2/(1+$K$4)^$K$2 -> 0.10880648
A7: 5 | B7: 46451 | C7: 0.96 | D7: 14 | E7: =IF(B7<=$B$2,0,(C7+D7)) -> 14.96 | F7: =(E7*(B7-$B$2)/365)/(1+$K$4)^((B7-$B$2)/365)/-$E$2/(1+$K$4)^$K$2 -> 0.13657391
A8: 6 | B8: 46545 | C8: 0.67 | D8: 14 | E8: =IF(B8<=$B$2,0,(C8+D8)) -> 14.67 | F8: =(E8*(B8-$B$2)/365)/(1+$K$4)^((B8-$B$2)/365)/-$E$2/(1+$K$4)^$K$2 -> 0.16456625
A9: 7 | B9: 46636 | C9: 0.36 | D9: 16 | E9: =IF(B9<=$B$2,0,(C9+D9)) -> 16.36 | F9: =(E9*(B9-$B$2)/365)/(1+$K$4)^((B9-$B$2)/365)/-$E$2/(1+$K$4)^$K$2 -> 0.21570755

Sheet TTCBD
A1: TTCBD | B1: Fecha de Pago | C1: Interés | D1: Amortización | E1: Total
B2: =Main!D1 -> 46068 | E2: {=-_xll.PrecioBD(A1,"24","ASK","N")} -> -104.65 | J2: Periodo de intereses | K2: 0.5
A3: 1 | B3: 46128 | C3: 3.24 | D3: 0 | E3: =IF(B3<=$B$2,0,(C3+D3)) -> 3.24 | F3: =(E3*(B3-$B$2)/365)/(1+$K$4)^((B3-$B$2)/365)/-$E$2/(1+$K$4)^$K$2 -> 0.0049279276 | J3: MDUR | K3: =SUM(F3:F102) -> 1.5419295
A4: 2 | B4: 46311 | C4: 3.26 | D4: 0 | E4: =IF(B4<=$B$2,0,(C4+D4)) -> 3.26 | F4: =(E4*(B4-$B$2)/365)/(1+$K$4)^((B4-$B$2)/365)/-$E$2/(1+$K$4)^$K$2 -> 0.019598693 | J4: TIR | K4: =XIRR(E2:E26,B2:B26) -> 0.049716279
A5: 3 | B5: 46493 | C5: 3.24 | D5: 0 | E5: =IF(B5<=$B$2,0,(C5+D5)) -> 3.24 | F5: =(E5*(B5-$B$2)/365)/(1+$K$4)^((B5-$B$2)/365)/-$E$2/(1+$K$4)^$K$2 -> 0.033252941 | J5: ONS
A6: 4 | B6: 46678 | C6: 3.26 | D6: 100 | E6: =IF(B6<=$B$2,0,(C6+D6)) -> 103.26 | F6: =(E6*(B6-$B$2)/365)/(1+$K$4)^((B6-$B$2)/365)/-$E$2/(1+$K$4)^$K$2 -> 1.48415

Sheet TLCOD
A1: TLCOD | B1: Fecha de Pago | C1: Interés | D1: Amortización | E1: Total
B2: =Main!D1 -> 46068 | E2: {=-_xll.PrecioBD(A1,"24","ASK","N")} -> -103.4 | J2: Periodo de intereses | K2: 0.5
A3: 3 | B3: 46170 | C3: 3.47 | D3: 0 | E3: =IF(B3<=$B$2,0,(C3+D3)) -> 3.47 | F3: =(E3*(B3-$B$2)/365)/(1+$K$4)^((B3-$B$2)/365)/-$E$2/(1+$K$4)^$K$2 -> 0.0089391174 | J3: MDUR | K3: =SUM(F3:F102) -> 2.4694928
A4: 4 | B4: 46356 | C4: 3.53 | D4: 0 | E4: =IF(B4<=$B$2,0,(C4+D4)) -> 3.53 | F4: =(E4*(B4-$B$2)/365)/(1+$K$4)^((B4-$B$2)/365)/-$E$2/(1+$K$4)^$K$2 -> 0.024883959 | J4: TIR | K4: =XIRR(E2:E26,B2:B26) -> 0.063440326
A5: 5 | B5: 46535 | C5: 3.47 | D5: 0 | E5: =IF(B5<=$B$2,0,(C5+D5)) -> 3.47 | F5: =(E5*(B5-$B$2)/365)/(1+$K$4)^((B5-$B$2)/365)/-$E$2/(1+$K$4)^$K$2 -> 0.038485597 | J5: ONS
A6: 6 | B6: 46720 | C6: 3.53 | D6: 0 | E6: =IF(B6<=$B$2,0,(C6+D6)) -> 3.53 | F6: =(E6*(B6-$B$2)/365)/(1+$K$4)^((B6-$B$2)/365)/-$E$2/(1+$K$4)^$K$2 -> 0.052982768
A7: 7 | B7: 46902 | C7: 3.49 | D7: 0 | E7: =IF(B7<=$B$2,0,(C7+D7)) -> 3.49 | F7: =(E7*(B7-$B$2)/365)/(1+$K$4)^((B7-$B$2)/365)/-$E$2/(1+$K$4)^$K$2 -> 0.06498062
A8: 8 | B8: 47085 | C8: 3.53 | D8: 100 | E8: =IF(B8<=$B$2,0,(C8+D8)) -> 103.53 | F8: =(E8*(B8-$B$2)/365)/(1+$K$4)^((B8-$B$2)/365)/-$E$2/(1+$K$4)^$K$2 -> 2.2792207

Sheet PLC3D
A1: PLC3D | B1: Fecha de Pago | C1: Interés | D1: Amortización | E1: Total
B2: =Main!D1 -> 46068 | E2: {=-_xll.PrecioBD(A1,"24","ASK","N")} -> -104.75 | J2: Periodo de intereses | K2: 0.5
A3: 2 | B3: 46233 | C3: 3.6 | D3: 0 | E3: =IF(B3<=$B$2,0,(C3+D3)) -> 3.6 | F3: =(E3*(B3-$B$2)/365)/(1+$K$4)^((B3-$B$2)/365)/-$E$2/(1+$K$4)^$K$2 -> 0.014809867 | J3: MDUR | K3: =SUM(F3:F102) -> 2.0265942
A4: 3 | B4: 46419 | C4: 3.65 | D4: 0 | E4: =IF(B4<=$B$2,0,(C4+D4)) -> 3.65 | F4: =(E4*(B4-$B$2)/365)/(1+$K$4)^((B4-$B$2)/365)/-$E$2/(1+$K$4)^$K$2 -> 0.031134197 | J4: TIR | K4: =XIRR(E2:E26,B2:B26) -> 0.051562974
A5: 4 | B5: 46598 | C5: 3.6 | D5: 0 | E5: =IF(B5<=$B$2,0,(C5+D5)) -> 3.6 | F5: =(E5*(B5-$B$2)/365)/(1+$K$4)^((B5-$B$2)/365)/-$E$2/(1+$K$4)^$K$2 -> 0.045238459 | J5: ONS
A6: 5 | B6: 46783 | C6: 3.65 | D6: 0 | E6: =IF(B6<=$B$2,0,(C6+D6)) -> 3.65 | F6: =(E6*(B6-$B$2)/365)/(1+$K$4)^((B6-$B$2)/365)/-$E$2/(1+$K$4)^$K$2 -> 0.060319973
A7: 6 | B7: 46875 | C7: 1.81 | D7: 100 | E7: =IF(B7<=$B$2,0,(C7+D7)) -> 101.81 | F7: =(E7*(B7-$B$2)/365)/(1+$K$4)^((B7-$B$2)/365)/-$E$2/(1+$K$4)^$K$2 -> 1.8750917

Sheet OLC5D
A1: OLC5D | B1: Fecha de Pago | C1: Interés | D1: Amortización | E1: Total
B2: =Main!D1 -> 46068 | E2: {=-_xll.PrecioBD(A1,"24","ASK","N")} -> -105 | J2: Periodo de intereses | K2: 0.5
A3: 2 | B3: 46185 | C3: 3.93 | D3: 0 | E3: =IF(B3<=$B$2,0,(C3+D3)) -> 3.93 | F3: =(E3*(B3-$B$2)/365)/(1+$K$4)^((B3-$B$2)/365)/-$E$2/(1+$K$4)^$K$2 -> 0.01141151 | J3: MDUR | K3: =SUM(F3:F102) -> 2.0804195
A4: 3 | B4: 46370 | C4: 3.96 | D4: 0 | E4: =IF(B4<=$B$2,0,(C4+D4)) -> 3.96 | F4: =(E4*(B4-$B$2)/365)/(1+$K$4)^((B4-$B$2)/365)/-$E$2/(1+$K$4)^$K$2 -> 0.028775971 | J4: TIR | K4: =XIRR(E2:E26,B2:B26) -> 0.062944308
A5: 4 | B5: 46552 | C5: 3.93 | D5: 0 | E5: =IF(B5<=$B$2,0,(C5+D5)) -> 3.93 | F5: =(E5*(B5-$B$2)/365)/(1+$K$4)^((B5-$B$2)/365)/-$E$2/(1+$K$4)^$K$2 -> 0.044396305 | J5: ONS
A6: 5 | B6: 46734 | C6: 3.96 | D6: 0 | E6: =IF(B6<=$B$2,0,(C6+D6)) -> 3.96 | F6: =(E6*(B6-$B$2)/365)/(1+$K$4)^((B6-$B$2)/365)/-$E$2/(1+$K$4)^$K$2 -> 0.059711694
A7: 6 | B7: 46916 | C7: 3.96 | D7: 100 | E7: =IF(B7<=$B$2,0,(C7+D7)) -> 103.96 | F7: =(E7*(B7-$B$2)/365)/(1+$K$4)^((B7-$B$2)/365)/-$E$2/(1+$K$4)^$K$2 -> 1.936124

Sheet CICAD
A1: CICAD | B1: Fecha de Pago | C1: Interés | D1: Amortización | E1: Total
B2: =Main!D1 -> 46068 | E2: {=-_xll.PrecioBD(A1,"24","ASK","N")} -> -102.95 | J2: Periodo de intereses | K2: 0.5
A3: 1 | B3: 46176 | C3: 3.99 | D3: 0 | E3: =IF(B3<=$B$2,0,(C3+D3)) -> 3.99 | F3: =(E3*(B3-$B$2)/365)/(1+$K$4)^((B3-$B$2)/365)/-$E$2/(1+$K$4)^$K$2 -> 0.010828642 | J3: MDUR | K3: =SUM(F3:F102) -> 2.0445698
A4: 2 | B4: 46359 | C4: 4.01 | D4: 0 | E4: =IF(B4<=$B$2,0,(C4+D4)) -> 4.01 | F4: =(E4*(B4-$B$2)/365)/(1+$K$4)^((B4-$B$2)/365)/-$E$2/(1+$K$4)^$K$2 -> 0.028283088 | J4: TIR | K4: =XIRR(E2:E26,B2:B26) -> 0.074706891
A5: 3 | B5: 46541 | C5: 3.99 | D5: 0 | E5: =IF(B5<=$B$2,0,(C5+D5)) -> 3.99 | F5: =(E5*(B5-$B$2)/365)/(1+$K$4)^((B5-$B$2)/365)/-$E$2/(1+$K$4)^$K$2 -> 0.044128722 | J5: ONS
A6: 4 | B6: 46724 | C6: 4.01 | D6: 0 | E6: =IF(B6<=$B$2,0,(C6+D6)) -> 4.01 | F6: =(E6*(B6-$B$2)/365)/(1+$K$4)^((B6-$B$2)/365)/-$E$2/(1+$K$4)^$K$2 -> 0.059326352
A7: 5 | B7: 46909 | C7: 4.01 | D7: 100 | E7: =IF(B7<=$B$2,0,(C7+D7)) -> 104.01 | F7: =(E7*(B7-$B$2)/365)/(1+$K$4)^((B7-$B$2)/365)/-$E$2/(1+$K$4)^$K$2 -> 1.902003
E8: =IF(B8<=$B$2,0,(C8+D8)) -> 0 | F8: =(E8*(B8-$B$2)/365)/(1+$K$4)^((B8-$B$2)/365)/-$E$2/(1+$K$4)^$K$2 -> 0

Sheet YM40D
A1: YM40D | B1: Fecha de Pago | C1: Interés | D1: Amortización | E1: Total
B2: =Main!D1 -> 46068 | E2: {=-_xll.PrecioBD(A1,"24","ASK","N")} -> -105.45 | J2: Periodo de intereses | K2: 0.333
A3: 2 | B3: 46083 | C3: 1.89 | D3: 0 | E3: =IF(B3<=$B$2,0,(C3+D3)) -> 1.89 | F3: =(E3*(B3-$B$2)/365)/(1+$K$4)^((B3-$B$2)/365)/-$E$2/(1+$K$4)^$K$2 -> 0.00072070664 | J3: MDUR | K3: =SUM(F3:F102) -> 2.2566844
A4: 3 | B4: 46170 | C4: 1.83 | D4: 0 | E4: =IF(B4<=$B$2,0,(C4+D4)) -> 1.83 | F4: =(E4*(B4-$B$2)/365)/(1+$K$4)^((B4-$B$2)/365)/-$E$2/(1+$K$4)^$K$2 -> 0.0046798549 | J4: TIR | K4: =XIRR(E2:E26,B2:B26) -> 0.059923461
A5: 4 | B5: 46262 | C5: 1.89 | D5: 0 | E5: =IF(B5<=$B$2,0,(C5+D5)) -> 1.89 | F5: =(E5*(B5-$B$2)/365)/(1+$K$4)^((B5-$B$2)/365)/-$E$2/(1+$K$4)^$K$2 -> 0.0090588716 | J5: ONS
A6: 5 | B6: 46356 | C6: 1.89 | D6: 0 | E6: =IF(B6<=$B$2,0,(C6+D6)) -> 1.89 | F6: =(E6*(B6-$B$2)/365)/(1+$K$4)^((B6-$B$2)/365)/-$E$2/(1+$K$4)^$K$2 -> 0.013248167
A7: 6 | B7: 46447 | C7: 1.89 | D7: 0 | E7: =IF(B7<=$B$2,0,(C7+D7)) -> 1.89 | F7: =(E7*(B7-$B$2)/365)/(1+$K$4)^((B7-$B$2)/365)/-$E$2/(1+$K$4)^$K$2 -> 0.017183088
A8: 7 | B8: 46535 | C8: 1.83 | D8: 0 | E8: =IF(B8<=$B$2,0,(C8+D8)) -> 1.83 | F8: =(E8*(B8-$B$2)/365)/(1+$K$4)^((B8-$B$2)/365)/-$E$2/(1+$K$4)^$K$2 -> 0.020215039
A9: 8 | B9: 46629 | C9: 1.89 | D9: 0 | E9: =IF(B9<=$B$2,0,(C9+D9)) -> 1.89 | F9: =(E9*(B9-$B$2)/365)/(1+$K$4)^((B9-$B$2)/365)/-$E$2/(1+$K$4)^$K$2 -> 0.024707126
A10: 9 | B10: 46720 | C10: 1.89 | D10: 0 | E10: =IF(B10<=$B$2,0,(C10+D10)) -> 1.89 | F10: =(E10*(B10-$B$2)/365)/(1+$K$4)^((B10-$B$2)/365)/-$E$2/(1+$K$4)^$K$2 -> 0.028301253
A11: 10 | B11: 46811 | C11: 1.89 | D11: 0 | E11: =IF(B11<=$B$2,0,(C11+D11)) -> 1.89 | F11: =(E11*(B11-$B$2)/365)/(1+$K$4)^((B11-$B$2)/365)/-$E$2/(1+$K$4)^$K$2 -> 0.031786709
A12: 11 | B12: 46902 | C12: 1.85 | D12: 0 | E12: =IF(B12<=$B$2,0,(C12+D12)) -> 1.85 | F12: =(E12*(B12-$B$2)/365)/(1+$K$4)^((B12-$B$2)/365)/-$E$2/(1+$K$4)^$K$2 -> 0.034421628
A13: 12 | B13: 46993 | C13: 1.89 | D13: 100 | E13: =IF(B13<=$B$2,0,(C13+D13)) -> 101.89 | F13: =(E13*(B13-$B$2)/365)/(1+$K$4)^((B13-$B$2)/365)/-$E$2/(1+$K$4)^$K$2 -> 2.0723619

Sheet LMS7D
A1: LMS7D | B1: Fecha de Pago | C1: Interés | D1: Amortización | E1: Total
B2: =Main!D1 -> 46068 | E2: {=-_xll.PrecioBD(A1,"24","ASK","N")} -> -94.85 | J2: Periodo de intereses | K2: 0.333
A3: 9 | B3: 46125 | C3: 1.6 | D3: 8.33 | E3: =IF(B3<=$B$2,0,(C3+D3)) -> 9.93 | F3: =(E3*(B3-$B$2)/365)/(1+$K$4)^((B3-$B$2)/365)/-$E$2/(1+$K$4)^$K$2 -> 0.015957452 | J3: MDUR | K3: =SUM(F3:F102) -> 1.3138462
A4: 10 | B4: 46216 | C4: 1.47 | D4: 8.33 | E4: =IF(B4<=$B$2,0,(C4+D4)) -> 9.8 | F4: =(E4*(B4-$B$2)/365)/(1+$K$4)^((B4-$B$2)/365)/-$E$2/(1+$K$4)^$K$2 -> 0.040388727 | J4: TIR | K4: =XIRR(E2:E26,B2:B26) -> 0.050817385
A5: 11 | B5: 46308 | C5: 1.34 | D5: 8.33 | E5: =IF(B5<=$B$2,0,(C5+D5)) -> 9.67 | F5: =(E5*(B5-$B$2)/365)/(1+$K$4)^((B5-$B$2)/365)/-$E$2/(1+$K$4)^$K$2 -> 0.063824003 | J5: ONS
A6: 12 | B6: 46399 | C6: 1.19 | D6: 8.33 | E6: =IF(B6<=$B$2,0,(C6+D6)) -> 9.52 | F6: =(E6*(B6-$B$2)/365)/(1+$K$4)^((B6-$B$2)/365)/-$E$2/(1+$K$4)^$K$2 -> 0.085594172
A7: 13 | B7: 46489 | C7: 1.02 | D7: 8.33 | E7: =IF(B7<=$B$2,0,(C7+D7)) -> 9.35 | F7: =(E7*(B7-$B$2)/365)/(1+$K$4)^((B7-$B$2)/365)/-$E$2/(1+$K$4)^$K$2 -> 0.10562455
A8: 14 | B8: 46580 | C8: 0.89 | D8: 8.33 | E8: =IF(B8<=$B$2,0,(C8+D8)) -> 9.22 | F8: =(E8*(B8-$B$2)/365)/(1+$K$4)^((B8-$B$2)/365)/-$E$2/(1+$K$4)^$K$2 -> 0.12511373
A9: 15 | B9: 46672 | C9: 0.75 | D9: 8.33 | E9: =IF(B9<=$B$2,0,(C9+D9)) -> 9.08 | F9: =(E9*(B9-$B$2)/365)/(1+$K$4)^((B9-$B$2)/365)/-$E$2/(1+$K$4)^$K$2 -> 0.14354922
A10: 16 | B10: 46764 | C10: 0.6 | D10: 8.33 | E10: =IF(B10<=$B$2,0,(C10+D10)) -> 8.93 | F10: =(E10*(B10-$B$2)/365)/(1+$K$4)^((B10-$B$2)/365)/-$E$2/(1+$K$4)^$K$2 -> 0.16066183
A11: 17 | B11: 46855 | C11: 0.44 | D11: 8.33 | E11: =IF(B11<=$B$2,0,(C11+D11)) -> 8.77 | F11: =(E11*(B11-$B$2)/365)/(1+$K$4)^((B11-$B$2)/365)/-$E$2/(1+$K$4)^$K$2 -> 0.17622165
A12: 18 | B12: 46946 | C12: 0.3 | D12: 8.33 | E12: =IF(B12<=$B$2,0,(C12+D12)) -> 8.63 | F12: =(E12*(B12-$B$2)/365)/(1+$K$4)^((B12-$B$2)/365)/-$E$2/(1+$K$4)^$K$2 -> 0.1910835
A13: 19 | B13: 47038 | C13: 0.15 | D13: 8.37 | E13: =IF(B13<=$B$2,0,(C13+D13)) -> 8.52 | F13: =(E13*(B13-$B$2)/365)/(1+$K$4)^((B13-$B$2)/365)/-$E$2/(1+$K$4)^$K$2 -> 0.20582738

Sheet VSCPD
A1: VSCPD | B1: Fecha de Pago | C1: Interés | D1: Amortización | E1: Total
B2: =Main!D1 -> 46068 | E2: {=-_xll.PrecioBD(A1,"24","ASK","N")} -> -106.85 | J2: Periodo de intereses | K2: 0.5
A3: 4 | B3: 46146 | C3: 3.97 | D3: 0 | E3: =IF(B3<=$B$2,0,(C3+D3)) -> 3.97 | F3: =(E3*(B3-$B$2)/365)/(1+$K$4)^((B3-$B$2)/365)/-$E$2/(1+$K$4)^$K$2 -> 0.0076137545 | J3: MDUR | K3: =SUM(F3:F102) -> 2.1741238
A4: 5 | B4: 46329 | C4: 4.03 | D4: 0 | E4: =IF(B4<=$B$2,0,(C4+D4)) -> 4.03 | F4: =(E4*(B4-$B$2)/365)/(1+$K$4)^((B4-$B$2)/365)/-$E$2/(1+$K$4)^$K$2 -> 0.025110806 | J4: TIR | K4: =XIRR(E2:E26,B2:B26) -> 0.06054078
A5: 6 | B5: 46510 | C5: 3.97 | D5: 0 | E5: =IF(B5<=$B$2,0,(C5+D5)) -> 3.97 | F5: =(E5*(B5-$B$2)/365)/(1+$K$4)^((B5-$B$2)/365)/-$E$2/(1+$K$4)^$K$2 -> 0.040688258 | J5: ONS
A6: 7 | B6: 46694 | C6: 4.03 | D6: 25 | E6: =IF(B6<=$B$2,0,(C6+D6)) -> 29.03 | F6: =(E6*(B6-$B$2)/365)/(1+$K$4)^((B6-$B$2)/365)/-$E$2/(1+$K$4)^$K$2 -> 0.4090808
A7: 8 | B7: 46876 | C7: 2.99 | D7: 25 | E7: =IF(B7<=$B$2,0,(C7+D7)) -> 27.99 | F7: =(E7*(B7-$B$2)/365)/(1+$K$4)^((B7-$B$2)/365)/-$E$2/(1+$K$4)^$K$2 -> 0.49439409
A8: 9 | B8: 47060 | C8: 2.02 | D8: 25 | E8: =IF(B8<=$B$2,0,(C8+D8)) -> 27.02 | F8: =(E8*(B8-$B$2)/365)/(1+$K$4)^((B8-$B$2)/365)/-$E$2/(1+$K$4)^$K$2 -> 0.56883647
A9: 10 | B9: 47241 | C9: 0.99 | D9: 25 | E9: =IF(B9<=$B$2,0,(C9+D9)) -> 25.99 | F9: =(E9*(B9-$B$2)/365)/(1+$K$4)^((B9-$B$2)/365)/-$E$2/(1+$K$4)^$K$2 -> 0.62839964

Sheet OLC6D
A1: OLC6D | B1: Fecha de Pago | C1: Interés | D1: Amortización | E1: Total
B2: =Main!D1 -> 46068 | E2: {=-_xll.PrecioBD(A1,"24","ASK","N")} -> -103.4 | J2: Periodo de intereses | K2: 0.5
A3: 1 | B3: 46178 | C3: 3.75 | D3: 0 | E3: =IF(B3<=$B$2,0,(C3+D3)) -> 3.75 | F3: =(E3*(B3-$B$2)/365)/(1+$K$4)^((B3-$B$2)/365)/-$E$2/(1+$K$4)^$K$2 -> 0.010356939 | J3: MDUR | K3: =SUM(F3:F102) -> 2.853648
A4: 2 | B4: 46363 | C4: 3.75 | D4: 0 | E4: =IF(B4<=$B$2,0,(C4+D4)) -> 3.75 | F4: =(E4*(B4-$B$2)/365)/(1+$K$4)^((B4-$B$2)/365)/-$E$2/(1+$K$4)^$K$2 -> 0.026845649 | J4: TIR | K4: =XIRR(E2:E26,B2:B26) -> 0.069483241
A5: 3 | B5: 46545 | C5: 3.75 | D5: 0 | E5: =IF(B5<=$B$2,0,(C5+D5)) -> 3.75 | F5: =(E5*(B5-$B$2)/365)/(1+$K$4)^((B5-$B$2)/365)/-$E$2/(1+$K$4)^$K$2 -> 0.041978146 | J5: ONS
A6: 4 | B6: 46727 | C6: 3.75 | D6: 0 | E6: =IF(B6<=$B$2,0,(C6+D6)) -> 3.75 | F6: =(E6*(B6-$B$2)/365)/(1+$K$4)^((B6-$B$2)/365)/-$E$2/(1+$K$4)^$K$2 -> 0.056084553
A7: 5 | B7: 46909 | C7: 3.75 | D7: 0 | E7: =IF(B7<=$B$2,0,(C7+D7)) -> 3.75 | F7: =(E7*(B7-$B$2)/365)/(1+$K$4)^((B7-$B$2)/365)/-$E$2/(1+$K$4)^$K$2 -> 0.06921605
A8: 6 | B8: 47092 | C8: 3.75 | D8: 0 | E8: =IF(B8<=$B$2,0,(C8+D8)) -> 3.75 | F8: =(E8*(B8-$B$2)/365)/(1+$K$4)^((B8-$B$2)/365)/-$E$2/(1+$K$4)^$K$2 -> 0.081486153
A9: 7 | B9: 47274 | C9: 3.75 | D9: 100 | E9: =IF(B9<=$B$2,0,(C9+D9)) -> 103.75 | F9: =(E9*(B9-$B$2)/365)/(1+$K$4)^((B9-$B$2)/365)/-$E$2/(1+$K$4)^$K$2 -> 2.5676805

Sheet NPCCD
A1: NPCCD | B1: Fecha de Pago | C1: Interés | D1: Amortización | E1: Total
B2: =Main!D1 -> 46068 | E2: {=-_xll.PrecioBD(A1,"24","ASK","N")} -> -108.95 | J2: Periodo de intereses | K2: 0.5
A3: 1 | B3: 46078 | C3: 4.03 | D3: 0 | E3: =IF(B3<=$B$2,0,(C3+D3)) -> 4.03 | F3: =(E3*(B3-$B$2)/365)/(1+$K$4)^((B3-$B$2)/365)/-$E$2/(1+$K$4)^$K$2 -> 0.00098059036 | J3: MDUR | K3: =SUM(F3:F102) -> 2.9532458
A4: 2 | B4: 46259 | C4: 3.97 | D4: 0 | E4: =IF(B4<=$B$2,0,(C4+D4)) -> 3.97 | F4: =(E4*(B4-$B$2)/365)/(1+$K$4)^((B4-$B$2)/365)/-$E$2/(1+$K$4)^$K$2 -> 0.01788806 | J4: TIR | K4: =XIRR(E2:E26,B2:B26) -> 0.064410672
A5: 3 | B5: 46443 | C5: 4.03 | D5: 0 | E5: =IF(B5<=$B$2,0,(C5+D5)) -> 4.03 | F5: =(E5*(B5-$B$2)/365)/(1+$K$4)^((B5-$B$2)/365)/-$E$2/(1+$K$4)^$K$2 -> 0.034546946 | J5: ONS
A6: 4 | B6: 46624 | C6: 3.97 | D6: 0 | E6: =IF(B6<=$B$2,0,(C6+D6)) -> 3.97 | F6: =(E6*(B6-$B$2)/365)/(1+$K$4)^((B6-$B$2)/365)/-$E$2/(1+$K$4)^$K$2 -> 0.048921014
A7: 5 | B7: 46808 | C7: 4.03 | D7: 0 | E7: =IF(B7<=$B$2,0,(C7+D7)) -> 4.03 | F7: =(E7*(B7-$B$2)/365)/(1+$K$4)^((B7-$B$2)/365)/-$E$2/(1+$K$4)^$K$2 -> 0.064047311
A8: 6 | B8: 46990 | C8: 3.99 | D8: 0 | E8: =IF(B8<=$B$2,0,(C8+D8)) -> 3.99 | F8: =(E8*(B8-$B$2)/365)/(1+$K$4)^((B8-$B$2)/365)/-$E$2/(1+$K$4)^$K$2 -> 0.076586192
A9: 7 | B9: 47175 | C9: 4.03 | D9: 0 | E9: =IF(B9<=$B$2,0,(C9+D9)) -> 4.03 | F9: =(E9*(B9-$B$2)/365)/(1+$K$4)^((B9-$B$2)/365)/-$E$2/(1+$K$4)^$K$2 -> 0.089982703
A10: 8 | B10: 47357 | C10: 3.97 | D10: 100 | E10: =IF(B10<=$B$2,0,(C10+D10)) -> 103.97 | F10: =(E10*(B10-$B$2)/365)/(1+$K$4)^((B10-$B$2)/365)/-$E$2/(1+$K$4)^$K$2 -> 2.620293

Sheet PN41D
A1: PN41D | B1: Fecha de Pago | C1: Interés | D1: Amortización | E1: Total
B2: =Main!D1 -> 46068 | E2: {=-_xll.PrecioBD(A1,"24","ASK","N")} -> -107.45 | J2: Periodo de intereses | K2: 0.5
A3: 1 | B3: 46080 | C3: 3.78 | D3: 0 | E3: =IF(B3<=$B$2,0,(C3+D3)) -> 3.78 | F3: =(E3*(B3-$B$2)/365)/(1+$K$4)^((B3-$B$2)/365)/-$E$2/(1+$K$4)^$K$2 -> 0.0011192877 | J3: MDUR | K3: =SUM(F3:F102) -> 2.9790174
A4: 2 | B4: 46261 | C4: 3.72 | D4: 0 | E4: =IF(B4<=$B$2,0,(C4+D4)) -> 3.72 | F4: =(E4*(B4-$B$2)/365)/(1+$K$4)^((B4-$B$2)/365)/-$E$2/(1+$K$4)^$K$2 -> 0.017184019 | J4: TIR | K4: =XIRR(E2:E26,B2:B26) -> 0.063427529
A5: 3 | B5: 46447 | C5: 3.78 | D5: 0 | E5: =IF(B5<=$B$2,0,(C5+D5)) -> 3.78 | F5: =(E5*(B5-$B$2)/365)/(1+$K$4)^((B5-$B$2)/365)/-$E$2/(1+$K$4)^$K$2 -> 0.033231157 | J5: ONS
A6: 4 | B6: 46626 | C6: 3.72 | D6: 0 | E6: =IF(B6<=$B$2,0,(C6+D6)) -> 3.72 | F6: =(E6*(B6-$B$2)/365)/(1+$K$4)^((B6-$B$2)/365)/-$E$2/(1+$K$4)^$K$2 -> 0.046719023
A7: 5 | B7: 46811 | C7: 3.78 | D7: 0 | E7: =IF(B7<=$B$2,0,(C7+D7)) -> 3.78 | F7: =(E7*(B7-$B$2)/365)/(1+$K$4)^((B7-$B$2)/365)/-$E$2/(1+$K$4)^$K$2 -> 0.061271758
A8: 6 | B8: 46993 | C8: 3.74 | D8: 0 | E8: =IF(B8<=$B$2,0,(C8+D8)) -> 3.74 | F8: =(E8*(B8-$B$2)/365)/(1+$K$4)^((B8-$B$2)/365)/-$E$2/(1+$K$4)^$K$2 -> 0.073194037
A9: 7 | B9: 47176 | C9: 3.78 | D9: 0 | E9: =IF(B9<=$B$2,0,(C9+D9)) -> 3.78 | F9: =(E9*(B9-$B$2)/365)/(1+$K$4)^((B9-$B$2)/365)/-$E$2/(1+$K$4)^$K$2 -> 0.085921805
A10: 8 | B10: 47357 | C10: 3.72 | D10: 100 | E10: =IF(B10<=$B$2,0,(C10+D10)) -> 103.72 | F10: =(E10*(B10-$B$2)/365)/(1+$K$4)^((B10-$B$2)/365)/-$E$2/(1+$K$4)^$K$2 -> 2.6603763

Sheet PN35D
A1: PN35D | B1: Fecha de Pago | C1: Interés | D1: Amortización | E1: Total
B2: =Main!D1 -> 46068 | E2: {=-_xll.PrecioBD(A1,"24","ASK","N")} -> -105.4 | J2: Periodo de intereses | K2: 0.5
A3: 3 | B3: 46108 | C3: 3.47 | D3: 0 | E3: =IF(B3<=$B$2,0,(C3+D3)) -> 3.47 | F3: =(E3*(B3-$B$2)/365)/(1+$K$4)^((B3-$B$2)/365)/-$E$2/(1+$K$4)^$K$2 -> 0.0034770415 | J3: MDUR | K3: =SUM(F3:F102) -> 3.0860682
A4: 4 | B4: 46293 | C4: 3.53 | D4: 0 | E4: =IF(B4<=$B$2,0,(C4+D4)) -> 3.53 | F4: =(E4*(B4-$B$2)/365)/(1+$K$4)^((B4-$B$2)/365)/-$E$2/(1+$K$4)^$K$2 -> 0.019294606 | J4: TIR | K4: =XIRR(E2:E26,B2:B26) -> 0.062485078
A5: 5 | B5: 46475 | C5: 3.47 | D5: 0 | E5: =IF(B5<=$B$2,0,(C5+D5)) -> 3.47 | F5: =(E5*(B5-$B$2)/365)/(1+$K$4)^((B5-$B$2)/365)/-$E$2/(1+$K$4)^$K$2 -> 0.033287197 | J5: ONS
A6: 6 | B6: 46657 | C6: 3.53 | D6: 0 | E6: =IF(B6<=$B$2,0,(C6+D6)) -> 3.53 | F6: =(E6*(B6-$B$2)/365)/(1+$K$4)^((B6-$B$2)/365)/-$E$2/(1+$K$4)^$K$2 -> 0.047546437
A7: 7 | B7: 46839 | C7: 3.49 | D7: 0 | E7: =IF(B7<=$B$2,0,(C7+D7)) -> 3.49 | F7: =(E7*(B7-$B$2)/365)/(1+$K$4)^((B7-$B$2)/365)/-$E$2/(1+$K$4)^$K$2 -> 0.059701112
A8: 8 | B8: 47023 | C8: 3.53 | D8: 0 | E8: =IF(B8<=$B$2,0,(C8+D8)) -> 3.53 | F8: =(E8*(B8-$B$2)/365)/(1+$K$4)^((B8-$B$2)/365)/-$E$2/(1+$K$4)^$K$2 -> 0.072545603
A9: 9 | B9: 47204 | C9: 3.47 | D9: 0 | E9: =IF(B9<=$B$2,0,(C9+D9)) -> 3.47 | F9: =(E9*(B9-$B$2)/365)/(1+$K$4)^((B9-$B$2)/365)/-$E$2/(1+$K$4)^$K$2 -> 0.08231663
A10: 10 | B10: 47388 | C10: 3.53 | D10: 100 | E10: =IF(B10<=$B$2,0,(C10+D10)) -> 103.53 | F10: =(E10*(B10-$B$2)/365)/(1+$K$4)^((B10-$B$2)/365)/-$E$2/(1+$K$4)^$K$2 -> 2.7678995

Sheet IRCOD
A1: IRCOD | B1: Fecha de Pago | C1: Interés | D1: Amortización | E1: Total
B2: =Main!D1 -> 46068 | E2: {=-_xll.PrecioBD(A1,"24","ASK","N")} -> -103.3 | J2: Periodo de intereses | K2: 0.5
A3: 3 | B3: 46226 | C3: 3.6 | D3: 0 | E3: =IF(B3<=$B$2,0,(C3+D3)) -> 3.6 | F3: =(E3*(B3-$B$2)/365)/(1+$K$4)^((B3-$B$2)/365)/-$E$2/(1+$K$4)^$K$2 -> 0.014227856 | J3: MDUR | K3: =SUM(F3:F102) -> 3.191004
A4: 4 | B4: 46412 | C4: 3.65 | D4: 0 | E4: =IF(B4<=$B$2,0,(C4+D4)) -> 3.65 | F4: =(E4*(B4-$B$2)/365)/(1+$K$4)^((B4-$B$2)/365)/-$E$2/(1+$K$4)^$K$2 -> 0.030418765 | J4: TIR | K4: =XIRR(E2:E26,B2:B26) -> 0.064771667
A5: 5 | B5: 46591 | C5: 3.6 | D5: 0 | E5: =IF(B5<=$B$2,0,(C5+D5)) -> 3.6 | F5: =(E5*(B5-$B$2)/365)/(1+$K$4)^((B5-$B$2)/365)/-$E$2/(1+$K$4)^$K$2 -> 0.044231083 | J5: ONS
A6: 6 | B6: 46776 | C6: 3.65 | D6: 0 | E6: =IF(B6<=$B$2,0,(C6+D6)) -> 3.65 | F6: =(E6*(B6-$B$2)/365)/(1+$K$4)^((B6-$B$2)/365)/-$E$2/(1+$K$4)^$K$2 -> 0.058807752
A7: 7 | B7: 46958 | C7: 3.62 | D7: 0 | E7: =IF(B7<=$B$2,0,(C7+D7)) -> 3.62 | F7: =(E7*(B7-$B$2)/365)/(1+$K$4)^((B7-$B$2)/365)/-$E$2/(1+$K$4)^$K$2 -> 0.071058515
A8: 8 | B8: 47141 | C8: 3.65 | D8: 0 | E8: =IF(B8<=$B$2,0,(C8+D8)) -> 3.65 | F8: =(E8*(B8-$B$2)/365)/(1+$K$4)^((B8-$B$2)/365)/-$E$2/(1+$K$4)^$K$2 -> 0.083703681
A9: 9 | B9: 47322 | C9: 3.6 | D9: 0 | E9: =IF(B9<=$B$2,0,(C9+D9)) -> 3.6 | F9: =(E9*(B9-$B$2)/365)/(1+$K$4)^((B9-$B$2)/365)/-$E$2/(1+$K$4)^$K$2 -> 0.093526735
A10: 10 | B10: 47414 | C10: 1.83 | D10: 100 | E10: =IF(B10<=$B$2,0,(C10+D10)) -> 101.83 | F10: =(E10*(B10-$B$2)/365)/(1+$K$4)^((B10-$B$2)/365)/-$E$2/(1+$K$4)^$K$2 -> 2.7950296

Sheet TTC9D
A1: TTC9D | B1: Fecha de Pago | C1: Interés | D1: Amortización | E1: Total
B2: =Main!D1 -> 46068 | E2: {=-_xll.PrecioBD(A1,"24","ASK","N")} -> -105.15 | J2: Periodo de intereses | K2: 0.5
A3: 3 | B3: 46136 | C3: 3.39 | D3: 0 | E3: =IF(B3<=$B$2,0,(C3+D3)) -> 3.39 | F3: =(E3*(B3-$B$2)/365)/(1+$K$4)^((B3-$B$2)/365)/-$E$2/(1+$K$4)^$K$2 -> 0.0057724028 | J3: MDUR | K3: =SUM(F3:F102) -> 3.1739941
A4: 4 | B4: 46321 | C4: 3.41 | D4: 0 | E4: =IF(B4<=$B$2,0,(C4+D4)) -> 3.41 | F4: =(E4*(B4-$B$2)/365)/(1+$K$4)^((B4-$B$2)/365)/-$E$2/(1+$K$4)^$K$2 -> 0.020978938 | J4: TIR | K4: =XIRR(E2:E26,B2:B26) -> 0.059581831
A5: 5 | B5: 46503 | C5: 3.39 | D5: 0 | E5: =IF(B5<=$B$2,0,(C5+D5)) -> 3.39 | F5: =(E5*(B5-$B$2)/365)/(1+$K$4)^((B5-$B$2)/365)/-$E$2/(1+$K$4)^$K$2 -> 0.034838925 | J5: ONS
A6: 6 | B6: 46685 | C6: 3.41 | D6: 0 | E6: =IF(B6<=$B$2,0,(C6+D6)) -> 3.41 | F6: =(E6*(B6-$B$2)/365)/(1+$K$4)^((B6-$B$2)/365)/-$E$2/(1+$K$4)^$K$2 -> 0.048292814
A7: 7 | B7: 46867 | C7: 3.41 | D7: 0 | E7: =IF(B7<=$B$2,0,(C7+D7)) -> 3.41 | F7: =(E7*(B7-$B$2)/365)/(1+$K$4)^((B7-$B$2)/365)/-$E$2/(1+$K$4)^$K$2 -> 0.060759096
A8: 8 | B8: 47050 | C8: 3.41 | D8: 0 | E8: =IF(B8<=$B$2,0,(C8+D8)) -> 3.41 | F8: =(E8*(B8-$B$2)/365)/(1+$K$4)^((B8-$B$2)/365)/-$E$2/(1+$K$4)^$K$2 -> 0.072539462
A9: 9 | B9: 47232 | C9: 3.39 | D9: 0 | E9: =IF(B9<=$B$2,0,(C9+D9)) -> 3.39 | F9: =(E9*(B9-$B$2)/365)/(1+$K$4)^((B9-$B$2)/365)/-$E$2/(1+$K$4)^$K$2 -> 0.083047837
A10: 10 | B10: 47415 | C10: 3.41 | D10: 100 | E10: =IF(B10<=$B$2,0,(C10+D10)) -> 103.41 | F10: =(E10*(B10-$B$2)/365)/(1+$K$4)^((B10-$B$2)/365)/-$E$2/(1+$K$4)^$K$2 -> 2.8477647

Sheet OT42D
A1: OT42D | B1: Fecha de Pago | C1: Interés | D1: Amortización | E1: Total
B2: =Main!D1 -> 46068 | E2: {=-_xll.PrecioBD(A1,"24","ASK","N")} -> -104.9 | J2: Periodo de intereses | K2: 0.333
A3: 3 | B3: 46129 | C3: 1.97 | D3: 0 | E3: =IF(B3<=$B$2,0,(C3+D3)) -> 1.97 | F3: =(E3*(B3-$B$2)/365)/(1+$K$4)^((B3-$B$2)/365)/-$E$2/(1+$K$4)^$K$2 -> 0.0030351958 | J3: MDUR | K3: =SUM(F3:F102) -> 3.324312
A4: 4 | B4: 46220 | C4: 1.99 | D4: 0 | E4: =IF(B4<=$B$2,0,(C4+D4)) -> 1.99 | F4: =(E4*(B4-$B$2)/365)/(1+$K$4)^((B4-$B$2)/365)/-$E$2/(1+$K$4)^$K$2 -> 0.0075134348 | J4: TIR | K4: =XIRR(E2:E26,B2:B26) -> 0.069239083
A5: 5 | B5: 46314 | C5: 2.02 | D5: 0 | E5: =IF(B5<=$B$2,0,(C5+D5)) -> 2.02 | F5: =(E5*(B5-$B$2)/365)/(1+$K$4)^((B5-$B$2)/365)/-$E$2/(1+$K$4)^$K$2 -> 0.012132228 | J5: ONS
A6: 6 | B6: 46405 | C6: 2.02 | D6: 0 | E6: =IF(B6<=$B$2,0,(C6+D6)) -> 2.02 | F6: =(E6*(B6-$B$2)/365)/(1+$K$4)^((B6-$B$2)/365)/-$E$2/(1+$K$4)^$K$2 -> 0.016345062
A7: 7 | B7: 46496 | C7: 1.97 | D7: 0 | E7: =IF(B7<=$B$2,0,(C7+D7)) -> 1.97 | F7: =(E7*(B7-$B$2)/365)/(1+$K$4)^((B7-$B$2)/365)/-$E$2/(1+$K$4)^$K$2 -> 0.019909782
A8: 8 | B8: 46587 | C8: 1.99 | D8: 0 | E8: =IF(B8<=$B$2,0,(C8+D8)) -> 1.99 | F8: =(E8*(B8-$B$2)/365)/(1+$K$4)^((B8-$B$2)/365)/-$E$2/(1+$K$4)^$K$2 -> 0.023984361
A9: 9 | B9: 46678 | C9: 2.02 | D9: 0 | E9: =IF(B9<=$B$2,0,(C9+D9)) -> 2.02 | F9: =(E9*(B9-$B$2)/365)/(1+$K$4)^((B9-$B$2)/365)/-$E$2/(1+$K$4)^$K$2 -> 0.028141039
A10: 10 | B10: 46769 | C10: 2.02 | D10: 0 | E10: =IF(B10<=$B$2,0,(C10+D10)) -> 2.02 | F10: =(E10*(B10-$B$2)/365)/(1+$K$4)^((B10-$B$2)/365)/-$E$2/(1+$K$4)^$K$2 -> 0.031803837
A11: 11 | B11: 46860 | C11: 1.99 | D11: 0 | E11: =IF(B11<=$B$2,0,(C11+D11)) -> 1.99 | F11: =(E11*(B11-$B$2)/365)/(1+$K$4)^((B11-$B$2)/365)/-$E$2/(1+$K$4)^$K$2 -> 0.034812852
A12: 12 | B12: 46951 | C12: 1.99 | D12: 0 | E12: =IF(B12<=$B$2,0,(C12+D12)) -> 1.99 | F12: =(E12*(B12-$B$2)/365)/(1+$K$4)^((B12-$B$2)/365)/-$E$2/(1+$K$4)^$K$2 -> 0.038170367
A13: 13 | B13: 47043 | C13: 2.02 | D13: 0 | E13: =IF(B13<=$B$2,0,(C13+D13)) -> 2.02 | F13: =(E13*(B13-$B$2)/365)/(1+$K$4)^((B13-$B$2)/365)/-$E$2/(1+$K$4)^$K$2 -> 0.042066859
A14: 14 | B14: 47135 | C14: 2.02 | D14: 0 | E14: =IF(B14<=$B$2,0,(C14+D14)) -> 2.02 | F14: =(E14*(B14-$B$2)/365)/(1+$K$4)^((B14-$B$2)/365)/-$E$2/(1+$K$4)^$K$2 -> 0.04526593
A15: 15 | B15: 47225 | C15: 1.97 | D15: 0 | E15: =IF(B15<=$B$2,0,(C15+D15)) -> 1.97 | F15: =(E15*(B15-$B$2)/365)/(1+$K$4)^((B15-$B$2)/365)/-$E$2/(1+$K$4)^$K$2 -> 0.047085383
A16: 16 | B16: 47316 | C16: 1.99 | D16: 0 | E16: =IF(B16<=$B$2,0,(C16+D16)) -> 1.99 | F16: =(E16*(B16-$B$2)/365)/(1+$K$4)^((B16-$B$2)/365)/-$E$2/(1+$K$4)^$K$2 -> 0.050455137
A17: 17 | B17: 47408 | C17: 2.02 | D17: 0 | E17: =IF(B17<=$B$2,0,(C17+D17)) -> 2.02 | F17: =(E17*(B17-$B$2)/365)/(1+$K$4)^((B17-$B$2)/365)/-$E$2/(1+$K$4)^$K$2 -> 0.05407113
A18: 18 | B18: 47500 | C18: 2.02 | D18: 100 | E18: =IF(B18<=$B$2,0,(C18+D18)) -> 102.02 | F18: =(E18*(B18-$B$2)/365)/(1+$K$4)^((B18-$B$2)/365)/-$E$2/(1+$K$4)^$K$2 -> 2.8695194

Sheet PLC2D
A1: PLC2D | B1: Fecha de Pago | C1: Interés | D1: Amortización | E1: Total
B2: =Main!D1 -> 46068 | E2: {=-_xll.PrecioBD(A1,"24","ASK","N")} -> -106 | J2: Periodo de intereses | K2: 0.5
A3: 2 | B3: 46139 | C3: 3.74 | D3: 0 | E3: =IF(B3<=$B$2,0,(C3+D3)) -> 3.74 | F3: =(E3*(B3-$B$2)/365)/(1+$K$4)^((B3-$B$2)/365)/-$E$2/(1+$K$4)^$K$2 -> 0.0065688388 | J3: MDUR | K3: =SUM(F3:F102) -> 3.3224971
A4: 3 | B4: 46322 | C4: 3.76 | D4: 0 | E4: =IF(B4<=$B$2,0,(C4+D4)) -> 3.76 | F4: =(E4*(B4-$B$2)/365)/(1+$K$4)^((B4-$B$2)/365)/-$E$2/(1+$K$4)^$K$2 -> 0.022889351 | J4: TIR | K4: =XIRR(E2:E26,B2:B26) -> 0.065168622
A5: 4 | B5: 46504 | C5: 3.74 | D5: 0 | E5: =IF(B5<=$B$2,0,(C5+D5)) -> 3.74 | F5: =(E5*(B5-$B$2)/365)/(1+$K$4)^((B5-$B$2)/365)/-$E$2/(1+$K$4)^$K$2 -> 0.037870268 | J5: ONS
A6: 5 | B6: 46687 | C6: 3.76 | D6: 0 | E6: =IF(B6<=$B$2,0,(C6+D6)) -> 3.76 | F6: =(E6*(B6-$B$2)/365)/(1+$K$4)^((B6-$B$2)/365)/-$E$2/(1+$K$4)^$K$2 -> 0.05236873
A7: 6 | B7: 46870 | C7: 3.76 | D7: 0 | E7: =IF(B7<=$B$2,0,(C7+D7)) -> 3.76 | F7: =(E7*(B7-$B$2)/365)/(1+$K$4)^((B7-$B$2)/365)/-$E$2/(1+$K$4)^$K$2 -> 0.065736869
A8: 7 | B8: 47053 | C8: 3.76 | D8: 0 | E8: =IF(B8<=$B$2,0,(C8+D8)) -> 3.76 | F8: =(E8*(B8-$B$2)/365)/(1+$K$4)^((B8-$B$2)/365)/-$E$2/(1+$K$4)^$K$2 -> 0.07822114
A9: 8 | B9: 47235 | C9: 3.74 | D9: 0 | E9: =IF(B9<=$B$2,0,(C9+D9)) -> 3.74 | F9: =(E9*(B9-$B$2)/365)/(1+$K$4)^((B9-$B$2)/365)/-$E$2/(1+$K$4)^$K$2 -> 0.089324563
A10: 9 | B10: 47420 | C10: 3.76 | D10: 0 | E10: =IF(B10<=$B$2,0,(C10+D10)) -> 3.76 | F10: =(E10*(B10-$B$2)/365)/(1+$K$4)^((B10-$B$2)/365)/-$E$2/(1+$K$4)^$K$2 -> 0.10076182
A11: 10 | B11: 47511 | C11: 1.89 | D11: 100 | E11: =IF(B11<=$B$2,0,(C11+D11)) -> 101.89 | F11: =(E11*(B11-$B$2)/365)/(1+$K$4)^((B11-$B$2)/365)/-$E$2/(1+$K$4)^$K$2 -> 2.8687556
F12: =(E12*(B12-$B$2)/365)/(1+$K$4)^((B12-$B$2)/365)/-$E$2/(1+$K$4)^$K$2 -> 0
F13: =(E13*(B13-$B$2)/365)/(1+$K$4)^((B13-$B$2)/365)/-$E$2/(1+$K$4)^$K$2 -> 0
F14: =(E14*(B14-$B$2)/365)/(1+$K$4)^((B14-$B$2)/365)/-$E$2/(1+$K$4)^$K$2 -> 0
E15: =IF(B15<=$B$2,0,(C15+D15)) -> 0
E16: =IF(B16<=$B$2,0,(C16+D16)) -> 0
E17: =IF(B17<=$B$2,0,(C17+D17)) -> 0
E18: =IF(B18<=$B$2,0,(C18+D18)) -> 0

Sheet PQCSD
A1: PQCSD | B1: Fecha de Pago | C1: Interés | D1: Amortización | E1: Total
B2: =Main!D1 -> 46068 | E2: {=-_xll.PrecioBD(A1,"24","ASK","N")} -> -104.5 | J2: Periodo de intereses | K2: 0.5
A3: 2 | B3: 46070 | C3: 4.03 | D3: 0 | E3: =IF(B3<=$B$2,0,(C3+D3)) -> 4.03 | F3: =(E3*(B3-$B$2)/365)/(1+$K$4)^((B3-$B$2)/365)/-$E$2/(1+$K$4)^$K$2 -> 0.00020322435 | J3: MDUR | K3: =SUM(F3:F102) -> 3.9113121
A4: 3 | B4: 46252 | C4: 3.97 | D4: 0 | E4: =IF(B4<=$B$2,0,(C4+D4)) -> 3.97 | F4: =(E4*(B4-$B$2)/365)/(1+$K$4)^((B4-$B$2)/365)/-$E$2/(1+$K$4)^$K$2 -> 0.017722646 | J4: TIR | K4: =XIRR(E2:E26,B2:B26) -> 0.080271211
A5: 4 | B5: 46435 | C5: 4.03 | D5: 0 | E5: =IF(B5<=$B$2,0,(C5+D5)) -> 4.03 | F5: =(E5*(B5-$B$2)/365)/(1+$K$4)^((B5-$B$2)/365)/-$E$2/(1+$K$4)^$K$2 -> 0.034520654 | J5: ONS
A6: 5 | B6: 46616 | C6: 3.97 | D6: 0 | E6: =IF(B6<=$B$2,0,(C6+D6)) -> 3.97 | F6: =(E6*(B6-$B$2)/365)/(1+$K$4)^((B6-$B$2)/365)/-$E$2/(1+$K$4)^$K$2 -> 0.048870904
A7: 6 | B7: 46800 | C7: 4.03 | D7: 0 | E7: =IF(B7<=$B$2,0,(C7+D7)) -> 4.03 | F7: =(E7*(B7-$B$2)/365)/(1+$K$4)^((B7-$B$2)/365)/-$E$2/(1+$K$4)^$K$2 -> 0.063736942
A8: 7 | B8: 46982 | C8: 3.99 | D8: 0 | E8: =IF(B8<=$B$2,0,(C8+D8)) -> 3.99 | F8: =(E8*(B8-$B$2)/365)/(1+$K$4)^((B8-$B$2)/365)/-$E$2/(1+$K$4)^$K$2 -> 0.075818244
A9: 8 | B9: 47168 | C9: 4.03 | D9: 0 | E9: =IF(B9<=$B$2,0,(C9+D9)) -> 4.03 | F9: =(E9*(B9-$B$2)/365)/(1+$K$4)^((B9-$B$2)/365)/-$E$2/(1+$K$4)^$K$2 -> 0.088606262
A10: 9 | B10: 47347 | C10: 3.97 | D10: 0 | E10: =IF(B10<=$B$2,0,(C10+D10)) -> 3.97 | F10: =(E10*(B10-$B$2)/365)/(1+$K$4)^((B10-$B$2)/365)/-$E$2/(1+$K$4)^$K$2 -> 0.09771987
A11: 10 | B11: 47532 | C11: 4.03 | D11: 0 | E11: =IF(B11<=$B$2,0,(C11+D11)) -> 4.03 | F11: =(E11*(B11-$B$2)/365)/(1+$K$4)^((B11-$B$2)/365)/-$E$2/(1+$K$4)^$K$2 -> 0.10918724
A12: 11 | B12: 47715 | C12: 3.97 | D12: 0 | E12: =IF(B12<=$B$2,0,(C12+D12)) -> 3.97 | F12: =(E12*(B12-$B$2)/365)/(1+$K$4)^((B12-$B$2)/365)/-$E$2/(1+$K$4)^$K$2 -> 0.11641194
A13: 12 | B13: 47896 | C13: 4.03 | D13: 100 | E13: =IF(B13<=$B$2,0,(C13+D13)) -> 104.03 | F13: =(E13*(B13-$B$2)/365)/(1+$K$4)^((B13-$B$2)/365)/-$E$2/(1+$K$4)^$K$2 -> 3.2585141
F14: =(E14*(B14-$B$2)/365)/(1+$K$4)^((B14-$B$2)/365)/-$E$2/(1+$K$4)^$K$2 -> 0
E15: =IF(B15<=$B$2,0,(C15+D15)) -> 0
E16: =IF(B16<=$B$2,0,(C16+D16)) -> 0
E17: =IF(B17<=$B$2,0,(C17+D17)) -> 0
E18: =IF(B18<=$B$2,0,(C18+D18)) -> 0

Sheet VSCRD
A1: VSCRD | B1: Fecha de Pago | C1: Interés | D1: Amortización | E1: Total
B2: =Main!D1 -> 46068 | E2: {=-_xll.PrecioBD(A1,"24","ASK","N")} -> -107.05 | J2: Periodo de intereses | K2: 0.5
A3: 3 | B3: 46122 | C3: 3.81 | D3: 0 | E3: =IF(B3<=$B$2,0,(C3+D3)) -> 3.81 | F3: =(E3*(B3-$B$2)/365)/(1+$K$4)^((B3-$B$2)/365)/-$E$2/(1+$K$4)^$K$2 -> 0.0050503963 | J3: MDUR | K3: =SUM(F3:F102) -> 3.7897722
A4: 4 | B4: 46308 | C4: 3.84 | D4: 0 | E4: =IF(B4<=$B$2,0,(C4+D4)) -> 3.84 | F4: =(E4*(B4-$B$2)/365)/(1+$K$4)^((B4-$B$2)/365)/-$E$2/(1+$K$4)^$K$2 -> 0.0218929 | J4: TIR | K4: =XIRR(E2:E26,B2:B26) -> 0.066487238
A5: 5 | B5: 46489 | C5: 3.81 | D5: 0 | E5: =IF(B5<=$B$2,0,(C5+D5)) -> 3.81 | F5: =(E5*(B5-$B$2)/365)/(1+$K$4)^((B5-$B$2)/365)/-$E$2/(1+$K$4)^$K$2 -> 0.036906678 | J5: ONS
A6: 6 | B6: 46672 | C6: 3.84 | D6: 0 | E6: =IF(B6<=$B$2,0,(C6+D6)) -> 3.84 | F6: =(E6*(B6-$B$2)/365)/(1+$K$4)^((B6-$B$2)/365)/-$E$2/(1+$K$4)^$K$2 -> 0.051671363
A7: 7 | B7: 46853 | C7: 3.84 | D7: 0 | E7: =IF(B7<=$B$2,0,(C7+D7)) -> 3.84 | F7: =(E7*(B7-$B$2)/365)/(1+$K$4)^((B7-$B$2)/365)/-$E$2/(1+$K$4)^$K$2 -> 0.065045865
A8: 8 | B8: 47036 | C8: 3.84 | D8: 0 | E8: =IF(B8<=$B$2,0,(C8+D8)) -> 3.84 | F8: =(E8*(B8-$B$2)/365)/(1+$K$4)^((B8-$B$2)/365)/-$E$2/(1+$K$4)^$K$2 -> 0.077662124
A9: 9 | B9: 47218 | C9: 3.81 | D9: 0 | E9: =IF(B9<=$B$2,0,(C9+D9)) -> 3.81 | F9: =(E9*(B9-$B$2)/365)/(1+$K$4)^((B9-$B$2)/365)/-$E$2/(1+$K$4)^$K$2 -> 0.088651474
A10: 10 | B10: 47401 | C10: 3.84 | D10: 33 | E10: =IF(B10<=$B$2,0,(C10+D10)) -> 36.84 | F10: =(E10*(B10-$B$2)/365)/(1+$K$4)^((B10-$B$2)/365)/-$E$2/(1+$K$4)^$K$2 -> 0.96204811
A11: 11 | B11: 47583 | C11: 2.56 | D11: 0 | E11: =IF(B11<=$B$2,0,(C11+D11)) -> 2.56 | F11: =(E11*(B11-$B$2)/365)/(1+$K$4)^((B11-$B$2)/365)/-$E$2/(1+$K$4)^$K$2 -> 0.073580051
A12: 12 | B12: 47766 | C12: 2.57 | D12: 33 | E12: =IF(B12<=$B$2,0,(C12+D12)) -> 35.57 | F12: =(E12*(B12-$B$2)/365)/(1+$K$4)^((B12-$B$2)/365)/-$E$2/(1+$K$4)^$K$2 -> 1.1094632
A13: 13 | B13: 47948 | C13: 1.3 | D13: 0 | E13: =IF(B13<=$B$2,0,(C13+D13)) -> 1.3 | F13: =(E13*(B13-$B$2)/365)/(1+$K$4)^((B13-$B$2)/365)/-$E$2/(1+$K$4)^$K$2 -> 0.043476345
A14: 14 | B14: 48131 | C14: 1.3 | D14: 34 | E14: =IF(B14<=$B$2,0,(C14+D14)) -> 35.3 | F14: =(E14*(B14-$B$2)/365)/(1+$K$4)^((B14-$B$2)/365)/-$E$2/(1+$K$4)^$K$2 -> 1.2543237
E15: =IF(B15<=$B$2,0,(C15+D15)) -> 0
E16: =IF(B16<=$B$2,0,(C16+D16)) -> 0
E17: =IF(B17<=$B$2,0,(C17+D17)) -> 0
E18: =IF(B18<=$B$2,0,(C18+D18)) -> 0

Sheet PN36D
A1: PN36D | B1: Fecha de Pago | C1: Interés | D1: Amortización | E1: Total
B2: =Main!D1 -> 46068 | E2: {=-_xll.PrecioBD(A1,"24","ASK","N")} -> -105.05 | J2: Periodo de intereses | K2: 0.5
A3: 3 | B3: 46155 | C3: 3.6 | D3: 0 | E3: =IF(B3<=$B$2,0,(C3+D3)) -> 3.6 | F3: =(E3*(B3-$B$2)/365)/(1+$K$4)^((B3-$B$2)/365)/-$E$2/(1+$K$4)^$K$2 -> 0.0077874738 | J3: MDUR | K3: =SUM(F3:F102) -> 4.5838272
A4: 4 | B4: 46339 | C4: 3.65 | D4: 0 | E4: =IF(B4<=$B$2,0,(C4+D4)) -> 3.65 | F4: =(E4*(B4-$B$2)/365)/(1+$K$4)^((B4-$B$2)/365)/-$E$2/(1+$K$4)^$K$2 -> 0.023805616 | J4: TIR | K4: =XIRR(E2:E26,B2:B26) -> 0.066803226
A5: 5 | B5: 46520 | C5: 3.6 | D5: 0 | E5: =IF(B5<=$B$2,0,(C5+D5)) -> 3.6 | F5: =(E5*(B5-$B$2)/365)/(1+$K$4)^((B5-$B$2)/365)/-$E$2/(1+$K$4)^$K$2 -> 0.037925513 | J5: ONS
A6: 6 | B6: 46706 | C6: 3.65 | D6: 0 | E6: =IF(B6<=$B$2,0,(C6+D6)) -> 3.65 | F6: =(E6*(B6-$B$2)/365)/(1+$K$4)^((B6-$B$2)/365)/-$E$2/(1+$K$4)^$K$2 -> 0.052516117
A7: 7 | B7: 46888 | C7: 3.62 | D7: 0 | E7: =IF(B7<=$B$2,0,(C7+D7)) -> 3.62 | F7: =(E7*(B7-$B$2)/365)/(1+$K$4)^((B7-$B$2)/365)/-$E$2/(1+$K$4)^$K$2 -> 0.064818324
A8: 8 | B8: 47070 | C8: 3.65 | D8: 0 | E8: =IF(B8<=$B$2,0,(C8+D8)) -> 3.65 | F8: =(E8*(B8-$B$2)/365)/(1+$K$4)^((B8-$B$2)/365)/-$E$2/(1+$K$4)^$K$2 -> 0.077327198
A9: 9 | B9: 47252 | C9: 3.6 | D9: 0 | E9: =IF(B9<=$B$2,0,(C9+D9)) -> 3.6 | F9: =(E9*(B9-$B$2)/365)/(1+$K$4)^((B9-$B$2)/365)/-$E$2/(1+$K$4)^$K$2 -> 0.087261405
A10: 10 | B10: 47435 | C10: 3.65 | D10: 0 | E10: =IF(B10<=$B$2,0,(C10+D10)) -> 3.65 | F10: =(E10*(B10-$B$2)/365)/(1+$K$4)^((B10-$B$2)/365)/-$E$2/(1+$K$4)^$K$2 -> 0.098889174
A11: 11 | B11: 47616 | C11: 3.6 | D11: 0 | E11: =IF(B11<=$B$2,0,(C11+D11)) -> 3.6 | F11: =(E11*(B11-$B$2)/365)/(1+$K$4)^((B11-$B$2)/365)/-$E$2/(1+$K$4)^$K$2 -> 0.10696312
A12: 12 | B12: 47800 | C12: 3.65 | D12: 0 | E12: =IF(B12<=$B$2,0,(C12+D12)) -> 3.65 | F12: =(E12*(B12-$B$2)/365)/(1+$K$4)^((B12-$B$2)/365)/-$E$2/(1+$K$4)^$K$2 -> 0.11744751
A13: 13 | B13: 47981 | C13: 3.6 | D13: 0 | E13: =IF(B13<=$B$2,0,(C13+D13)) -> 3.6 | F13: =(E13*(B13-$B$2)/365)/(1+$K$4)^((B13-$B$2)/365)/-$E$2/(1+$K$4)^$K$2 -> 0.12390641
A14: 14 | B14: 48165 | C14: 3.65 | D14: 100 | E14: =IF(B14<=$B$2,0,(C14+D14)) -> 103.65 | F14: =(E14*(B14-$B$2)/365)/(1+$K$4)^((B14-$B$2)/365)/-$E$2/(1+$K$4)^$K$2 -> 3.7851794
E15: =IF(B15<=$B$2,0,(C15+D15)) -> 0
E16: =IF(B16<=$B$2,0,(C16+D16)) -> 0
E17: =IF(B17<=$B$2,0,(C17+D17)) -> 0
E18: =IF(B18<=$B$2,0,(C18+D18)) -> 0

Sheet HJCID
A1: HJCID | B1: Fecha de Pago | C1: Interés | D1: Amortización | E1: Total
