Workbook

Sheet Main
B1: Nombre | C1: Riesgo | D1: Theme | E1: Plazo
B2: Capital | C2: Alto | D2: Working capital | E2: Corto plazo
B4: Elite Income | C4: Medio | D4: Renta fija USD | E4: Largo plazo
B5: Premium Income | C5: Medio | D5: Flujo mensual | E5: Largo plazo
B7: Equilibrium | C7: Medio | D7: Diversificado | E7: Largo plazo
B9: Innova | C9: Extremo | D9: Innovación y teconología disruptiva | E9: Mediano plazo
B10: Future+ | C10: Alto | D10: Inicio de plan de retiro | E10: Largo plazo
B11: Factor alfa | C11: Extremo | D11: Equity cuantitativo | E11: Mediano plazo
B14: Tactical
B16: Value | C16: Alto | D16: Empresas baratas y de calidad | E16: Mediano
B17: Momentum | C17: Alto | D17: Empresas que han subido mucho | E17: Corto
B18: Skewness | C18: Alto | D18: Empresas que cayeron mucho | E18: Corto
B19: Low Volatility | C19: Alto | D19: Empresas con baja volatilidad | E19: Corto
B25: Todo en base a momentum
B26: Stop
B27: Target
B28: Google fianance que se de señal | C28: Tablero
B29: Todo lo que haya universo de activos
B30: Transicionar de a poco.
B54: EMB | C54: https://www,blackrock,com/cl/productos/239572/ishares-jp-morgan-usd-emerging-markets-bond-etf
B55: CEMB | C55: https://www,blackrock,com/cl/productos/239525/ishares-emerging-markets-corporate-bond-etf
B56: EMLC | C56: EMLC - J,P, Morgan EM Local Currency Bond ETF | Holdings & Performance | VanEck
B57: CME | C57: https://interactive,researchaffiliates,com/asset-allocation#!/?category=Multi-Country&currency=USD&model=ER&scale=Log&selected=60&tab=details&terms=Real&type=Government+T-Bills&vs=N4IgxgrgTlCmB2AXAygCwIYAdYGED2ANnlCAFzwQEEA0IqAlgCaMICCAzu7Iu2QNoBWAdQAcI6gEYA7ADZJU8dICckpcIBMABk3UtGzVN0SNEuevUaALCos6LE3QPXVLEh5YDMl3So9yPmgC6tAzMbJzcACoAnti8pHzBdEws8BxciDjoiLAA5sT0sPGJISkI%2BBBIUIXFIOhgILSMALYgSaGpFVXRMXH8SbAAHpjo8CyMvUX8IAAKAKKNIHMAiosASnMAkos4APIAsjtrOwBCiyvqiwBiABqLmwAyZwPDo%2BNZOfnVUwl8S6u0fYAVQekW2wT%2BG22tA2bWofz2h0BILBcL%2Bt0WABE5gA1NH-c6HQIvEZjWCMLqIKA9WI-P6Y2AAN1gRGwjHOzVgUFy9HguUW%2B0oiHoAFpKdS4SB2GAoBAAEZyrk49AECA-UBgLCwEVQbL0PAigi82BkUAEWAAM0QZB0IGquVQ1tImgAvrR8ozECL2KztUb4CbSGbLU7bfbHTa3eA4Ix6F6fXhsIbjaaQOarTbaOHQ1HMMREBbCPr2CLsFBC1BmqMwH6U0G0yHM3b6A6cy6XUA

Sheet Ons
I2: =IFERROR(__xludf.DUMMYFUNCTION("IMPORTRANGE(""https://docs.google.com/spreadsheets/d/1QFB2kh2cYM7XonEBR7QFtdA5P63irew36fgS54qRFHA/edit?pli=1&gid=720802488#gid=720802488"" , ""ONs NY!A:P"")"),45938.0) -> 45938 | AG2: =IFERROR(__xludf.DUMMYFUNCTION("IMPORTRANGE(""https://docs.google.com/spreadsheets/d/1Mr1-WgkgjeFEk5QNcL6PEK-ZeHJ0W4Ga3Q_OiCASfug/edit?gid=301422845#gid=301422845"" , ""ONs Argentina!A:L"")"),"") | AM2: =IFERROR(__xludf.DUMMYFUNCTION("""COMPUTED_VALUE"""),"Comision") -> Comision | AN2: =IFERROR(__xludf.DUMMYFUNCTION("""COMPUTED_VALUE"""),1.0) -> 1
J3: =IFERROR(__xludf.DUMMYFUNCTION("""COMPUTED_VALUE"""),"CORPORATIVOS LEY NY") -> CORPORATIVOS LEY NY | X3: =IFERROR(__xludf.DUMMYFUNCTION("""COMPUTED_VALUE"""),"Canje") -> Canje | AM3: =IFERROR(__xludf.DUMMYFUNCTION("""COMPUTED_VALUE"""),"Dia de liquidacion") -> Dia de liquidacion | AN3: =IFERROR(__xludf.DUMMYFUNCTION("""COMPUTED_VALUE"""),45939.0) -> 45939
B4: Conservador | J4: =IFERROR(__xludf.DUMMYFUNCTION("""COMPUTED_VALUE"""),"Ticker") -> Ticker | K4: =IFERROR(__xludf.DUMMYFUNCTION("""COMPUTED_VALUE"""),"Empresa") -> Empresa | L4: =IFERROR(__xludf.DUMMYFUNCTION("""COMPUTED_VALUE"""),"Vencimiento") -> Vencimiento | M4: =IFERROR(__xludf.DUMMYFUNCTION("""COMPUTED_VALUE"""),"Tasa") -> Tasa | N4: =IFERROR(__xludf.DUMMYFUNCTION("""COMPUTED_VALUE"""),"Precio") -> Precio | O4: =IFERROR(__xludf.DUMMYFUNCTION("""COMPUTED_VALUE"""),"TIR") -> TIR | P4: =IFERROR(__xludf.DUMMYFUNCTION("""COMPUTED_VALUE"""),"Var. Diaria%") -> Var. Diaria% | Q4: =IFERROR(__xludf.DUMMYFUNCTION("""COMPUTED_VALUE"""),"Duration") -> Duration | R4: =IFERROR(__xludf.DUMMYFUNCTION("""COMPUTED_VALUE"""),"Cupones") -> Cupones | S4: =IFERROR(__xludf.DUMMYFUNCTION("""COMPUTED_VALUE"""),"Tipo") -> Tipo | T4: =IFERROR(__xludf.DUMMYFUNCTION("""COMPUTED_VALUE"""),"Ley") -> Ley | U4: =IFERROR(__xludf.DUMMYFUNCTION("""COMPUTED_VALUE"""),"Lam Minima") -> Lam Minima | V4: =IFERROR(__xludf.DUMMYFUNCTION("""COMPUTED_VALUE"""),"Prox Cupón (días)") -> Prox Cupón (días) | W4: =IFERROR(__xludf.DUMMYFUNCTION("""COMPUTED_VALUE"""),"Paridad") -> Paridad
B5: =K5 -> Central Puerto | C5: TIR | D5: M,Duration | E5: Vto | F5: Inverse m,D | G5: Weight | H5: Lamina | J5: =IFERROR(__xludf.DUMMYFUNCTION("""COMPUTED_VALUE"""),"NPCBD") -> NPCBD | K5: =IFERROR(__xludf.DUMMYFUNCTION("""COMPUTED_VALUE"""),"Central Puerto") -> Central Puerto | L5: =IFERROR(__xludf.DUMMYFUNCTION("""COMPUTED_VALUE"""),45947.0) -> 45947 | M5: =IFERROR(__xludf.DUMMYFUNCTION("""COMPUTED_VALUE"""),0.1) -> 0.1 | N5: =IFERROR(__xludf.DUMMYFUNCTION("""COMPUTED_VALUE"""),106.2) -> 106.2 | O5: =IFERROR(__xludf.DUMMYFUNCTION("""COMPUTED_VALUE"""),-0.3692612611849655) -> -0.36926126 | P5: =IFERROR(__xludf.DUMMYFUNCTION("""COMPUTED_VALUE"""),0.0023) -> 0.0023 | Q5: =IFERROR(__xludf.DUMMYFUNCTION("""COMPUTED_VALUE"""),0.02500394606092653) -> 0.025003946 | R5: =IFERROR(__xludf.DUMMYFUNCTION("""COMPUTED_VALUE"""),"Semestral") -> Semestral | S5: =IFERROR(__xludf.DUMMYFUNCTION("""COMPUTED_VALUE"""),"Bullet") -> Bullet | T5: =IFERROR(__xludf.DUMMYFUNCTION("""COMPUTED_VALUE"""),"NY") -> NY | U5: =IFERROR(__xludf.DUMMYFUNCTION("""COMPUTED_VALUE"""),1000.0) -> 1000 | V5: =IFERROR(__xludf.DUMMYFUNCTION("""COMPUTED_VALUE"""),9.0) -> 9 | W5: =IFERROR(__xludf.DUMMYFUNCTION("""COMPUTED_VALUE"""),1.01276821192053) -> 1.0127682 | X5: =IFERROR(__xludf.DUMMYFUNCTION("""COMPUTED_VALUE"""),0.010267693436010417) -> 0.010267693 | AH5: =IFERROR(__xludf.DUMMYFUNCTION("""COMPUTED_VALUE"""),"Empresa") -> Empresa | AI5: =IFERROR(__xludf.DUMMYFUNCTION("""COMPUTED_VALUE"""),"Ticker") -> Ticker | AJ5: =IFERROR(__xludf.DUMMYFUNCTION("""COMPUTED_VALUE"""),"TIR") -> TIR | AK5: =IFERROR(__xludf.DUMMYFUNCTION("""COMPUTED_VALUE"""),"Precio") -> Precio | AL5: =IFERROR(__xludf.DUMMYFUNCTION("""COMPUTED_VALUE"""),"Sin comision") -> Sin comision | AM5: =IFERROR(__xludf.DUMMYFUNCTION("""COMPUTED_VALUE"""),"MD") -> MD | AN5: =IFERROR(__xludf.DUMMYFUNCTION("""COMPUTED_VALUE"""),"Vto") -> Vto | AO5: =IFERROR(__xludf.DUMMYFUNCTION("""COMPUTED_VALUE"""),"Ley") -> Ley | AP5: =IFERROR(__xludf.DUMMYFUNCTION("""COMPUTED_VALUE"""),"Periodicidad") -> Periodicidad | AQ5: =IFERROR(__xludf.DUMMYFUNCTION("""COMPUTED_VALUE"""),"Lamina minima") -> Lamina minima | AR5: =IFERROR(__xludf.DUMMYFUNCTION("""COMPUTED_VALUE"""),"Tipo") -> Tipo
B6: TLCPD | C6: =VLOOKUP(B6,$J$6:$W$36,6,0) -> 0.097477722 | D6: =VLOOKUP(B6,$J$6:$W$36,8,0) -> 5.213219 | E6: =VLOOKUP(B6,$J$6:$W$36,3,0) -> 48727 | F6: =1/D6 -> 0.19182006 | G6: =F6/$F$12 -> 0.17531045 | H6: =VLOOKUP(B6,$J$6:$W$36,12,0) -> 100 | J6: =IFERROR(__xludf.DUMMYFUNCTION("""COMPUTED_VALUE"""),"YMCHD") -> YMCHD | K6: =IFERROR(__xludf.DUMMYFUNCTION("""COMPUTED_VALUE"""),"YPF") -> YPF | L6: =IFERROR(__xludf.DUMMYFUNCTION("""COMPUTED_VALUE"""),46065.0) -> 46065 | M6: =IFERROR(__xludf.DUMMYFUNCTION("""COMPUTED_VALUE"""),0.04) -> 0.04 | N6: =IFERROR(__xludf.DUMMYFUNCTION("""COMPUTED_VALUE"""),16.36) -> 16.36 | O6: =IFERROR(__xludf.DUMMYFUNCTION("""COMPUTED_VALUE"""),-0.12221745916049007) -> -0.12221746 | P6: =IFERROR(__xludf.DUMMYFUNCTION("""COMPUTED_VALUE"""),0.0073) -> 0.0073 | Q6: =IFERROR(__xludf.DUMMYFUNCTION("""COMPUTED_VALUE"""),0.22299269945896666) -> 0.2229927 | R6: =IFERROR(__xludf.DUMMYFUNCTION("""COMPUTED_VALUE"""),"Trimestral") -> Trimestral | S6: =IFERROR(__xludf.DUMMYFUNCTION("""COMPUTED_VALUE"""),"Sinkable") -> Sinkable | T6: =IFERROR(__xludf.DUMMYFUNCTION("""COMPUTED_VALUE"""),"NY") -> NY | U6: =IFERROR(__xludf.DUMMYFUNCTION("""COMPUTED_VALUE"""),1.0) -> 1 | V6: =IFERROR(__xludf.DUMMYFUNCTION("""COMPUTED_VALUE"""),35.0) -> 35 | W6: =IFERROR(__xludf.DUMMYFUNCTION("""COMPUTED_VALUE"""),1.0485156389696602) -> 1.0485156
B7: BACGD | C7: =VLOOKUP(B7,$J$6:$W$36,6,0) -> 0.081859039 | D7: =VLOOKUP(B7,$J$6:$W$36,8,0) -> 3.2393086 | E7: =VLOOKUP(B7,$J$6:$W$36,3,0) -> 47292 | F7: =1/D7 -> 0.30870785 | G7: =F7/$F$12 -> 0.28213792 | H7: =VLOOKUP(B7,$J$6:$W$36,12,0) -> 1000 | J7: =IFERROR(__xludf.DUMMYFUNCTION("""COMPUTED_VALUE"""),"MTCGD") -> MTCGD | K7: =IFERROR(__xludf.DUMMYFUNCTION("""COMPUTED_VALUE"""),"Mastellone") -> Mastellone | L7: =IFERROR(__xludf.DUMMYFUNCTION("""COMPUTED_VALUE"""),46203.0) -> 46203 | M7: =IFERROR(__xludf.DUMMYFUNCTION("""COMPUTED_VALUE"""),0.1095) -> 0.1095 | N7: =IFERROR(__xludf.DUMMYFUNCTION("""COMPUTED_VALUE"""),101.5) -> 101.5 | O7: =IFERROR(__xludf.DUMMYFUNCTION("""COMPUTED_VALUE"""),0.09534594734110474) -> 0.095345947 | P7: =IFERROR(__xludf.DUMMYFUNCTION("""COMPUTED_VALUE"""),0.011899999999999999) -> 0.0119 | Q7: =IFERROR(__xludf.DUMMYFUNCTION("""COMPUTED_VALUE"""),0.7127086800293023) -> 0.71270868 | R7: =IFERROR(__xludf.DUMMYFUNCTION("""COMPUTED_VALUE"""),"Trimestral") -> Trimestral | S7: =IFERROR(__xludf.DUMMYFUNCTION("""COMPUTED_VALUE"""),"Bullet") -> Bullet | T7: =IFERROR(__xludf.DUMMYFUNCTION("""COMPUTED_VALUE"""),"NY") -> NY | U7: =IFERROR(__xludf.DUMMYFUNCTION("""COMPUTED_VALUE"""),1.0) -> 1 | V7: =IFERROR(__xludf.DUMMYFUNCTION("""COMPUTED_VALUE"""),83.0) -> 83 | W7: =IFERROR(__xludf.DUMMYFUNCTION("""COMPUTED_VALUE"""),1.0122290230494022) -> 1.012229 | AG7: =IFERROR(__xludf.DUMMYFUNCTION("""COMPUTED_VALUE"""),"Poco volumen") -> Poco volumen | AH7: =IFERROR(__xludf.DUMMYFUNCTION("""COMPUTED_VALUE"""),"Irsa") -> Irsa | AI7: =IFERROR(__xludf.DUMMYFUNCTION("""COMPUTED_VALUE"""),"IRCHD") -> IRCHD | AJ7: =IFERROR(__xludf.DUMMYFUNCTION("""COMPUTED_VALUE"""),"#NUM!") -> #NUM! | AK7: =IFERROR(__xludf.DUMMYFUNCTION("""COMPUTED_VALUE"""),104.5) -> 104.5 | AL7: =IFERROR(__xludf.DUMMYFUNCTION("""COMPUTED_VALUE"""),104.5) -> 104.5 | AM7: =IFERROR(__xludf.DUMMYFUNCTION("""COMPUTED_VALUE"""),"#NUM!") -> #NUM! | AN7: =IFERROR(__xludf.DUMMYFUNCTION("""COMPUTED_VALUE"""),"#N/A") -> #N/A | AO7: =IFERROR(__xludf.DUMMYFUNCTION("""COMPUTED_VALUE"""),"Argentina") -> Argentina | AP7: =IFERROR(__xludf.DUMMYFUNCTION("""COMPUTED_VALUE"""),"#N/A") -> #N/A | AQ7: =IFERROR(__xludf.DUMMYFUNCTION("""COMPUTED_VALUE"""),1.0) -> 1 | AR7: =IFERROR(__xludf.DUMMYFUNCTION("""COMPUTED_VALUE"""),"#N/A") -> #N/A
B8: IRCPD | C8: =VLOOKUP(B8,$J$6:$W$36,6,0) -> 0.080184559 | D8: =VLOOKUP(B8,$J$6:$W$36,8,0) -> 6.3420415 | E8: =VLOOKUP(B8,$J$6:$W$36,3,0) -> 49399 | F8: =1/D8 -> 0.15767793 | G8: =F8/$F$12 -> 0.14410687 | H8: =VLOOKUP(B8,$J$6:$W$36,12,0) -> 1 | J8: =IFERROR(__xludf.DUMMYFUNCTION("""COMPUTED_VALUE"""),"MGC9D") -> MGC9D | K8: =IFERROR(__xludf.DUMMYFUNCTION("""COMPUTED_VALUE"""),"Pampa Energia") -> Pampa Energia | L8: =IFERROR(__xludf.DUMMYFUNCTION("""COMPUTED_VALUE"""),46364.0) -> 46364 | M8: =IFERROR(__xludf.DUMMYFUNCTION("""COMPUTED_VALUE"""),0.095) -> 0.095 | N8: =IFERROR(__xludf.DUMMYFUNCTION("""COMPUTED_VALUE"""),71.2) -> 71.2 | O8: =IFERROR(__xludf.DUMMYFUNCTION("""COMPUTED_VALUE"""),0.04779948184699389) -> 0.047799482 | P8: =IFERROR(__xludf.DUMMYFUNCTION("""COMPUTED_VALUE"""),-0.0055000000000000005) -> -0.0055 | Q8: =IFERROR(__xludf.DUMMYFUNCTION("""COMPUTED_VALUE"""),0.6604825150010593) -> 0.66048251 | R8: =IFERROR(__xludf.DUMMYFUNCTION("""COMPUTED_VALUE"""),"Semestral") -> Semestral | S8: =IFERROR(__xludf.DUMMYFUNCTION("""COMPUTED_VALUE"""),"Sinkable") -> Sinkable | T8: =IFERROR(__xludf.DUMMYFUNCTION("""COMPUTED_VALUE"""),"NY") -> NY | U8: =IFERROR(__xludf.DUMMYFUNCTION("""COMPUTED_VALUE"""),1.0) -> 1 | V8: =IFERROR(__xludf.DUMMYFUNCTION("""COMPUTED_VALUE"""),61.0) -> 61 | W8: =IFERROR(__xludf.DUMMYFUNCTION("""COMPUTED_VALUE"""),1.029277921301921) -> 1.0292779 | X8: =IFERROR(__xludf.DUMMYFUNCTION("""COMPUTED_VALUE"""),"al30c") -> al30c | AG8: =IFERROR(__xludf.DUMMYFUNCTION("""COMPUTED_VALUE"""),"Poco volumen") -> Poco volumen | AH8: =IFERROR(__xludf.DUMMYFUNCTION("""COMPUTED_VALUE"""),"Pampa energia") -> Pampa energia | AI8: =IFERROR(__xludf.DUMMYFUNCTION("""COMPUTED_VALUE"""),"MGCJD") -> MGCJD | AJ8: =IFERROR(__xludf.DUMMYFUNCTION("""COMPUTED_VALUE"""),"#NUM!") -> #NUM! | AK8: =IFERROR(__xludf.DUMMYFUNCTION("""COMPUTED_VALUE"""),0.0) -> 0 | AL8: =IFERROR(__xludf.DUMMYFUNCTION("""COMPUTED_VALUE"""),0.0) -> 0 | AM8: =IFERROR(__xludf.DUMMYFUNCTION("""COMPUTED_VALUE"""),"#NUM!") -> #NUM! | AN8: =IFERROR(__xludf.DUMMYFUNCTION("""COMPUTED_VALUE"""),"#N/A") -> #N/A | AO8: =IFERROR(__xludf.DUMMYFUNCTION("""COMPUTED_VALUE"""),"Argentina") -> Argentina | AP8: =IFERROR(__xludf.DUMMYFUNCTION("""COMPUTED_VALUE"""),"#N/A") -> #N/A | AQ8: =IFERROR(__xludf.DUMMYFUNCTION("""COMPUTED_VALUE"""),1.0) -> 1 | AR8: =IFERROR(__xludf.DUMMYFUNCTION("""COMPUTED_VALUE"""),"#N/A") -> #N/A
B9: YM34D | C9: =VLOOKUP(B9,$J$6:$W$36,6,0) -> 0.086475232 | D9: =VLOOKUP(B9,$J$6:$W$36,8,0) -> 5.5734194 | E9: =VLOOKUP(B9,$J$6:$W$36,3,0) -> 48961 | F9: =1/D9 -> 0.17942307 | G9: =F9/$F$12 -> 0.16398044 | H9: =VLOOKUP(B9,$J$6:$W$36,12,0) -> 1 | J9: =IFERROR(__xludf.DUMMYFUNCTION("""COMPUTED_VALUE"""),"PNDCD") -> PNDCD | K9: =IFERROR(__xludf.DUMMYFUNCTION("""COMPUTED_VALUE"""),"Pan American Energy") -> Pan American Energy | L9: =IFERROR(__xludf.DUMMYFUNCTION("""COMPUTED_VALUE"""),46507.0) -> 46507 | M9: =IFERROR(__xludf.DUMMYFUNCTION("""COMPUTED_VALUE"""),0.0913) -> 0.0913 | N9: =IFERROR(__xludf.DUMMYFUNCTION("""COMPUTED_VALUE"""),86.5) -> 86.5 | O9: =IFERROR(__xludf.DUMMYFUNCTION("""COMPUTED_VALUE"""),0.03924871575088921) -> 0.039248716 | P9: =IFERROR(__xludf.DUMMYFUNCTION("""COMPUTED_VALUE"""),-0.017) -> -0.017 | Q9: =IFERROR(__xludf.DUMMYFUNCTION("""COMPUTED_VALUE"""),0.7822434263638092) -> 0.78224343 | R9: =IFERROR(__xludf.DUMMYFUNCTION("""COMPUTED_VALUE"""),"Semestral") -> Semestral | S9: =IFERROR(__xludf.DUMMYFUNCTION("""COMPUTED_VALUE"""),"Sinkable") -> Sinkable | T9: =IFERROR(__xludf.DUMMYFUNCTION("""COMPUTED_VALUE"""),"NY") -> NY | U9: =IFERROR(__xludf.DUMMYFUNCTION("""COMPUTED_VALUE"""),1000.0) -> 1000 | V9: =IFERROR(__xludf.DUMMYFUNCTION("""COMPUTED_VALUE"""),22.0) -> 22 | W9: =IFERROR(__xludf.DUMMYFUNCTION("""COMPUTED_VALUE"""),1.0386023893858438) -> 1.0386024 | X9: =IFERROR(__xludf.DUMMYFUNCTION("""COMPUTED_VALUE"""),"al30d") -> al30d | AH9: =IFERROR(__xludf.DUMMYFUNCTION("""COMPUTED_VALUE"""),"Pampa energia") -> Pampa energia | AI9: =IFERROR(__xludf.DUMMYFUNCTION("""COMPUTED_VALUE"""),"MGCHD") -> MGCHD | AJ9: =IFERROR(__xludf.DUMMYFUNCTION("""COMPUTED_VALUE"""),0.24190855575300954) -> 0.24190856 | AK9: =IFERROR(__xludf.DUMMYFUNCTION("""COMPUTED_VALUE"""),100.95) -> 100.95 | AL9: =IFERROR(__xludf.DUMMYFUNCTION("""COMPUTED_VALUE"""),100.95) -> 100.95 | AM9: =IFERROR(__xludf.DUMMYFUNCTION("""COMPUTED_VALUE"""),0.06391983923288115) -> 0.063919839 | AN9: =IFERROR(__xludf.DUMMYFUNCTION("""COMPUTED_VALUE"""),45965.0) -> 45965 | AO9: =IFERROR(__xludf.DUMMYFUNCTION("""COMPUTED_VALUE"""),"Argentina") -> Argentina | AP9: =IFERROR(__xludf.DUMMYFUNCTION("""COMPUTED_VALUE"""),"Semestral") -> Semestral | AQ9: =IFERROR(__xludf.DUMMYFUNCTION("""COMPUTED_VALUE"""),1.0) -> 1 | AR9: =IFERROR(__xludf.DUMMYFUNCTION("""COMPUTED_VALUE"""),"Bullet") -> Bullet
B10: TLCMD | C10: =VLOOKUP(B10,$J$6:$W$36,6,0) -> 0.092867481 | D10: =VLOOKUP(B10,$J$6:$W$36,8,0) -> 3.8979568 | E10: =VLOOKUP(B10,$J$6:$W$36,3,0) -> 48047 | F10: =1/D10 -> 0.25654466 | G10: =F10/$F$12 -> 0.23446432 | H10: =VLOOKUP(B10,$J$6:$W$36,12,0) -> 1000 | J10: =IFERROR(__xludf.DUMMYFUNCTION("""COMPUTED_VALUE"""),"YCAMD") -> YCAMD | K10: =IFERROR(__xludf.DUMMYFUNCTION("""COMPUTED_VALUE"""),"YPF") -> YPF | L10: =IFERROR(__xludf.DUMMYFUNCTION("""COMPUTED_VALUE"""),46589.0) -> 46589 | M10: =IFERROR(__xludf.DUMMYFUNCTION("""COMPUTED_VALUE"""),0.0695) -> 0.0695 | N10: =IFERROR(__xludf.DUMMYFUNCTION("""COMPUTED_VALUE"""),102.25) -> 102.25 | O10: =IFERROR(__xludf.DUMMYFUNCTION("""COMPUTED_VALUE"""),0.06619237840504184) -> 0.066192378 | P10: =IFERROR(__xludf.DUMMYFUNCTION("""COMPUTED_VALUE"""),0.0) -> 0 | Q10: =IFERROR(__xludf.DUMMYFUNCTION("""COMPUTED_VALUE"""),1.7036405613044903) -> 1.7036406 | R10: =IFERROR(__xludf.DUMMYFUNCTION("""COMPUTED_VALUE"""),"Semestral") -> Semestral | S10: =IFERROR(__xludf.DUMMYFUNCTION("""COMPUTED_VALUE"""),"Bullet") -> Bullet | T10: =IFERROR(__xludf.DUMMYFUNCTION("""COMPUTED_VALUE"""),"NY") -> NY | U10: =IFERROR(__xludf.DUMMYFUNCTION("""COMPUTED_VALUE"""),10000.0) -> 10000 | V10: =IFERROR(__xludf.DUMMYFUNCTION("""COMPUTED_VALUE"""),105.0) -> 105 | W10: =IFERROR(__xludf.DUMMYFUNCTION("""COMPUTED_VALUE"""),1.006948243790349) -> 1.0069482 | AG10: =IFERROR(__xludf.DUMMYFUNCTION("""COMPUTED_VALUE"""),"Poco volumen") -> Poco volumen | AH10: =IFERROR(__xludf.DUMMYFUNCTION("""COMPUTED_VALUE"""),"Arcor") -> Arcor | AI10: =IFERROR(__xludf.DUMMYFUNCTION("""COMPUTED_VALUE"""),"RCCMD") -> RCCMD | AJ10: =IFERROR(__xludf.DUMMYFUNCTION("""COMPUTED_VALUE"""),0.02144906447461636) -> 0.021449064 | AK10: =IFERROR(__xludf.DUMMYFUNCTION("""COMPUTED_VALUE"""),101.5) -> 101.5 | AL10: =IFERROR(__xludf.DUMMYFUNCTION("""COMPUTED_VALUE"""),101.5) -> 101.5 | AM10: =IFERROR(__xludf.DUMMYFUNCTION("""COMPUTED_VALUE"""),0.119275557329253) -> 0.11927556 | AN10: =IFERROR(__xludf.DUMMYFUNCTION("""COMPUTED_VALUE"""),45983.0) -> 45983 | AO10: =IFERROR(__xludf.DUMMYFUNCTION("""COMPUTED_VALUE"""),"Argentina") -> Argentina | AP10: =IFERROR(__xludf.DUMMYFUNCTION("""COMPUTED_VALUE"""),"Semestral") -> Semestral | AQ10: =IFERROR(__xludf.DUMMYFUNCTION("""COMPUTED_VALUE"""),1.0) -> 1 | AR10: =IFERROR(__xludf.DUMMYFUNCTION("""COMPUTED_VALUE"""),"Bullet") -> Bullet
J11: =IFERROR(__xludf.DUMMYFUNCTION("""COMPUTED_VALUE"""),"GNCXD") -> GNCXD | K11: =IFERROR(__xludf.DUMMYFUNCTION("""COMPUTED_VALUE"""),"Genneia") -> Genneia | L11: =IFERROR(__xludf.DUMMYFUNCTION("""COMPUTED_VALUE"""),46632.0) -> 46632 | M11: =IFERROR(__xludf.DUMMYFUNCTION("""COMPUTED_VALUE"""),0.0875) -> 0.0875 | N11: =IFERROR(__xludf.DUMMYFUNCTION("""COMPUTED_VALUE"""),40.89) -> 40.89 | O11: =IFERROR(__xludf.DUMMYFUNCTION("""COMPUTED_VALUE"""),0.07634798914958861) -> 0.076347989 | P11: =IFERROR(__xludf.DUMMYFUNCTION("""COMPUTED_VALUE"""),0.0070999999999999995) -> 0.0071 | Q11: =IFERROR(__xludf.DUMMYFUNCTION("""COMPUTED_VALUE"""),1.1154498500735563) -> 1.1154499 | R11: =IFERROR(__xludf.DUMMYFUNCTION("""COMPUTED_VALUE"""),"Semestral") -> Semestral | S11: =IFERROR(__xludf.DUMMYFUNCTION("""COMPUTED_VALUE"""),"Sinkable") -> Sinkable | T11: =IFERROR(__xludf.DUMMYFUNCTION("""COMPUTED_VALUE"""),"NY") -> NY | U11: =IFERROR(__xludf.DUMMYFUNCTION("""COMPUTED_VALUE"""),1000.0) -> 1000 | V11: =IFERROR(__xludf.DUMMYFUNCTION("""COMPUTED_VALUE"""),145.0) -> 145 | W11: =IFERROR(__xludf.DUMMYFUNCTION("""COMPUTED_VALUE"""),0.8105110292852472) -> 0.81051103 | AH11: =IFERROR(__xludf.DUMMYFUNCTION("""COMPUTED_VALUE"""),"Tarjeta Naranja") -> Tarjeta Naranja | AI11: =IFERROR(__xludf.DUMMYFUNCTION("""COMPUTED_VALUE"""),"TN63D") -> TN63D | AJ11: =IFERROR(__xludf.DUMMYFUNCTION("""COMPUTED_VALUE"""),"#NUM!") -> #NUM! | AK11: =IFERROR(__xludf.DUMMYFUNCTION("""COMPUTED_VALUE"""),101.25) -> 101.25 | AL11: =IFERROR(__xludf.DUMMYFUNCTION("""COMPUTED_VALUE"""),101.25) -> 101.25 | AM11: =IFERROR(__xludf.DUMMYFUNCTION("""COMPUTED_VALUE"""),"#NUM!") -> #NUM! | AN11: =IFERROR(__xludf.DUMMYFUNCTION("""COMPUTED_VALUE"""),45989.0) -> 45989 | AO11: =IFERROR(__xludf.DUMMYFUNCTION("""COMPUTED_VALUE"""),"Argentina") -> Argentina | AP11: =IFERROR(__xludf.DUMMYFUNCTION("""COMPUTED_VALUE"""),"Trimestral") -> Trimestral | AQ11: =IFERROR(__xludf.DUMMYFUNCTION("""COMPUTED_VALUE"""),1.0) -> 1 | AR11: =IFERROR(__xludf.DUMMYFUNCTION("""COMPUTED_VALUE"""),"Sinkable") -> Sinkable
F12: =SUM(F6:F11) -> 1.0941736 | J12: =IFERROR(__xludf.DUMMYFUNCTION("""COMPUTED_VALUE"""),"IRCFD") -> IRCFD | K12: =IFERROR(__xludf.DUMMYFUNCTION("""COMPUTED_VALUE"""),"Irsa") -> Irsa | L12: =IFERROR(__xludf.DUMMYFUNCTION("""COMPUTED_VALUE"""),46926.0) -> 46926 | M12: =IFERROR(__xludf.DUMMYFUNCTION("""COMPUTED_VALUE"""),0.0875) -> 0.0875 | N12: =IFERROR(__xludf.DUMMYFUNCTION("""COMPUTED_VALUE"""),69.79) -> 69.79 | O12: =IFERROR(__xludf.DUMMYFUNCTION("""COMPUTED_VALUE"""),0.060872134275639526) -> 0.060872134 | P12: =IFERROR(__xludf.DUMMYFUNCTION("""COMPUTED_VALUE"""),-0.0012) -> -0.0012 | Q12: =IFERROR(__xludf.DUMMYFUNCTION("""COMPUTED_VALUE"""),1.7631168587831665) -> 1.7631169 | R12: =IFERROR(__xludf.DUMMYFUNCTION("""COMPUTED_VALUE"""),"Semestral") -> Semestral | S12: =IFERROR(__xludf.DUMMYFUNCTION("""COMPUTED_VALUE"""),"Sinkable") -> Sinkable | T12: =IFERROR(__xludf.DUMMYFUNCTION("""COMPUTED_VALUE"""),"NY") -> NY | U12: =IFERROR(__xludf.DUMMYFUNCTION("""COMPUTED_VALUE"""),1.0) -> 1 | V12: =IFERROR(__xludf.DUMMYFUNCTION("""COMPUTED_VALUE"""),75.0) -> 75 | W12: =IFERROR(__xludf.DUMMYFUNCTION("""COMPUTED_VALUE"""),1.0459810730148655) -> 1.0459811 | AG12: =IFERROR(__xludf.DUMMYFUNCTION("""COMPUTED_VALUE"""),"Poco volumen") -> Poco volumen | AH12: =IFERROR(__xludf.DUMMYFUNCTION("""COMPUTED_VALUE"""),"Loma Negra") -> Loma Negra | AI12: =IFERROR(__xludf.DUMMYFUNCTION("""COMPUTED_VALUE"""),"LOC2D") -> LOC2D | AJ12: =IFERROR(__xludf.DUMMYFUNCTION("""COMPUTED_VALUE"""),0.16231005781614452) -> 0.16231006 | AK12: =IFERROR(__xludf.DUMMYFUNCTION("""COMPUTED_VALUE"""),100.2) -> 100.2 | AL12: =IFERROR(__xludf.DUMMYFUNCTION("""COMPUTED_VALUE"""),100.2) -> 100.2 | AM12: =IFERROR(__xludf.DUMMYFUNCTION("""COMPUTED_VALUE"""),0.18551071432542224) -> 0.18551071 | AN12: =IFERROR(__xludf.DUMMYFUNCTION("""COMPUTED_VALUE"""),"#N/A") -> #N/A | AO12: =IFERROR(__xludf.DUMMYFUNCTION("""COMPUTED_VALUE"""),"Argentina") -> Argentina | AP12: =IFERROR(__xludf.DUMMYFUNCTION("""COMPUTED_VALUE"""),"#N/A") -> #N/A | AQ12: =IFERROR(__xludf.DUMMYFUNCTION("""COMPUTED_VALUE"""),1.0) -> 1 | AR12: =IFERROR(__xludf.DUMMYFUNCTION("""COMPUTED_VALUE"""),"#N/A") -> #N/A
J13: =IFERROR(__xludf.DUMMYFUNCTION("""COMPUTED_VALUE"""),"CAC5D") -> CAC5D | K13: =IFERROR(__xludf.DUMMYFUNCTION("""COMPUTED_VALUE"""),"Capex") -> Capex | L13: =IFERROR(__xludf.DUMMYFUNCTION("""COMPUTED_VALUE"""),46990.0) -> 46990 | M13: =IFERROR(__xludf.DUMMYFUNCTION("""COMPUTED_VALUE"""),0.0925) -> 0.0925 | N13: =IFERROR(__xludf.DUMMYFUNCTION("""COMPUTED_VALUE"""),75.72) -> 75.72 | O13: =IFERROR(__xludf.DUMMYFUNCTION("""COMPUTED_VALUE"""),0.09544429307870247) -> 0.095444293 | P13: =IFERROR(__xludf.DUMMYFUNCTION("""COMPUTED_VALUE"""),-0.0076) -> -0.0076 | Q13: =IFERROR(__xludf.DUMMYFUNCTION("""COMPUTED_VALUE"""),1.5251915772927287) -> 1.5251916 | R13: =IFERROR(__xludf.DUMMYFUNCTION("""COMPUTED_VALUE"""),"Semestral") -> Semestral | S13: =IFERROR(__xludf.DUMMYFUNCTION("""COMPUTED_VALUE"""),"Sinkable") -> Sinkable | T13: =IFERROR(__xludf.DUMMYFUNCTION("""COMPUTED_VALUE"""),"NY") -> NY | U13: =IFERROR(__xludf.DUMMYFUNCTION("""COMPUTED_VALUE"""),1.0) -> 1 | V13: =IFERROR(__xludf.DUMMYFUNCTION("""COMPUTED_VALUE"""),140.0) -> 140 | W13: =IFERROR(__xludf.DUMMYFUNCTION("""COMPUTED_VALUE"""),0.855479941745002) -> 0.85547994 | AH13: =IFERROR(__xludf.DUMMYFUNCTION("""COMPUTED_VALUE"""),"YPF") -> YPF | AI13: =IFERROR(__xludf.DUMMYFUNCTION("""COMPUTED_VALUE"""),"YMCQD") -> YMCQD | AJ13: =IFERROR(__xludf.DUMMYFUNCTION("""COMPUTED_VALUE"""),0.0881540943546613) -> 0.088154094 | AK13: =IFERROR(__xludf.DUMMYFUNCTION("""COMPUTED_VALUE"""),100.4) -> 100.4 | AL13: =IFERROR(__xludf.DUMMYFUNCTION("""COMPUTED_VALUE"""),100.4) -> 100.4 | AM13: =IFERROR(__xludf.DUMMYFUNCTION("""COMPUTED_VALUE"""),0.32967463211111653) -> 0.32967463 | AN13: =IFERROR(__xludf.DUMMYFUNCTION("""COMPUTED_VALUE"""),46066.0) -> 46066 | AO13: =IFERROR(__xludf.DUMMYFUNCTION("""COMPUTED_VALUE"""),"Argentina") -> Argentina | AP13: =IFERROR(__xludf.DUMMYFUNCTION("""COMPUTED_VALUE"""),"Semestral") -> Semestral | AQ13: =IFERROR(__xludf.DUMMYFUNCTION("""COMPUTED_VALUE"""),1.0) -> 1 | AR13: =IFERROR(__xludf.DUMMYFUNCTION("""COMPUTED_VALUE"""),"Bullet") -> Bullet
J14: =IFERROR(__xludf.DUMMYFUNCTION("""COMPUTED_VALUE"""),"BYCHD") -> BYCHD | K14: =IFERROR(__xludf.DUMMYFUNCTION("""COMPUTED_VALUE"""),"Galicia") -> Galicia | L14: =IFERROR(__xludf.DUMMYFUNCTION("""COMPUTED_VALUE"""),47036.0) -> 47036 | M14: =IFERROR(__xludf.DUMMYFUNCTION("""COMPUTED_VALUE"""),0.0775) -> 0.0775 | N14: =IFERROR(__xludf.DUMMYFUNCTION("""COMPUTED_VALUE"""),105.8) -> 105.8 | O14: =IFERROR(__xludf.DUMMYFUNCTION("""COMPUTED_VALUE"""),0.07149077584364663) -> 0.071490776 | P14: =IFERROR(__xludf.DUMMYFUNCTION("""COMPUTED_VALUE"""),-0.0014000000000000002) -> -0.0014 | Q14: =IFERROR(__xludf.DUMMYFUNCTION("""COMPUTED_VALUE"""),2.6701754812302956) -> 2.6701755 | R14: =IFERROR(__xludf.DUMMYFUNCTION("""COMPUTED_VALUE"""),"Semestral") -> Semestral | S14: =IFERROR(__xludf.DUMMYFUNCTION("""COMPUTED_VALUE"""),"Bullet") -> Bullet | T14: =IFERROR(__xludf.DUMMYFUNCTION("""COMPUTED_VALUE"""),"NY") -> NY | U14: =IFERROR(__xludf.DUMMYFUNCTION("""COMPUTED_VALUE"""),2000.0) -> 2000 | V14: =IFERROR(__xludf.DUMMYFUNCTION("""COMPUTED_VALUE"""),2.0) -> 2 | W14: =IFERROR(__xludf.DUMMYFUNCTION("""COMPUTED_VALUE"""),1.0181098889349247) -> 1.0181099 | AG14: =IFERROR(__xludf.DUMMYFUNCTION("""COMPUTED_VALUE"""),"Poco volumen") -> Poco volumen | AH14: =IFERROR(__xludf.DUMMYFUNCTION("""COMPUTED_VALUE"""),"CGC") -> CGC | AI14: =IFERROR(__xludf.DUMMYFUNCTION("""COMPUTED_VALUE"""),"CP34D") -> CP34D | AJ14: =IFERROR(__xludf.DUMMYFUNCTION("""COMPUTED_VALUE"""),0.2934021780710768) -> 0.29340218 | AK14: =IFERROR(__xludf.DUMMYFUNCTION("""COMPUTED_VALUE"""),94.0) -> 94 | AL14: =IFERROR(__xludf.DUMMYFUNCTION("""COMPUTED_VALUE"""),94.0) -> 94 | AM14: =IFERROR(__xludf.DUMMYFUNCTION("""COMPUTED_VALUE"""),0.3300356913502398) -> 0.33003569 | AN14: =IFERROR(__xludf.DUMMYFUNCTION("""COMPUTED_VALUE"""),46076.0) -> 46076 | AO14: =IFERROR(__xludf.DUMMYFUNCTION("""COMPUTED_VALUE"""),"Argentina") -> Argentina | AP14: =IFERROR(__xludf.DUMMYFUNCTION("""COMPUTED_VALUE"""),"Semestral") -> Semestral | AQ14: =IFERROR(__xludf.DUMMYFUNCTION("""COMPUTED_VALUE"""),1.0) -> 1 | AR14: =IFERROR(__xludf.DUMMYFUNCTION("""COMPUTED_VALUE"""),"Bullet") -> Bullet
H15: =C8/D8 -> 0.012643336 | J15: =IFERROR(__xludf.DUMMYFUNCTION("""COMPUTED_VALUE"""),"BACGD") -> BACGD | K15: =IFERROR(__xludf.DUMMYFUNCTION("""COMPUTED_VALUE"""),"Banco Macro") -> Banco Macro | L15: =IFERROR(__xludf.DUMMYFUNCTION("""COMPUTED_VALUE"""),47292.0) -> 47292 | M15: =IFERROR(__xludf.DUMMYFUNCTION("""COMPUTED_VALUE"""),0.08) -> 0.08 | N15: =IFERROR(__xludf.DUMMYFUNCTION("""COMPUTED_VALUE"""),102.25) -> 102.25 | O15: =IFERROR(__xludf.DUMMYFUNCTION("""COMPUTED_VALUE"""),0.08185903892745386) -> 0.081859039 | P15: =IFERROR(__xludf.DUMMYFUNCTION("""COMPUTED_VALUE"""),0.0024) -> 0.0024 | Q15: =IFERROR(__xludf.DUMMYFUNCTION("""COMPUTED_VALUE"""),3.2393086080317754) -> 3.2393086 | R15: =IFERROR(__xludf.DUMMYFUNCTION("""COMPUTED_VALUE"""),"Semestral") -> Semestral | S15: =IFERROR(__xludf.DUMMYFUNCTION("""COMPUTED_VALUE"""),"Bullet") -> Bullet | T15: =IFERROR(__xludf.DUMMYFUNCTION("""COMPUTED_VALUE"""),"NY") -> NY | U15: =IFERROR(__xludf.DUMMYFUNCTION("""COMPUTED_VALUE"""),1000.0) -> 1000 | V15: =IFERROR(__xludf.DUMMYFUNCTION("""COMPUTED_VALUE"""),76.0) -> 76 | W15: =IFERROR(__xludf.DUMMYFUNCTION("""COMPUTED_VALUE"""),0.99853515625) -> 0.99853516 | AH15: =IFERROR(__xludf.DUMMYFUNCTION("""COMPUTED_VALUE"""),"Cresud") -> Cresud | AI15: =IFERROR(__xludf.DUMMYFUNCTION("""COMPUTED_VALUE"""),"CS38D") -> CS38D | AJ15: =IFERROR(__xludf.DUMMYFUNCTION("""COMPUTED_VALUE"""),0.09214149546043073) -> 0.092141495 | AK15: =IFERROR(__xludf.DUMMYFUNCTION("""COMPUTED_VALUE"""),101.75) -> 101.75 | AL15: =IFERROR(__xludf.DUMMYFUNCTION("""COMPUTED_VALUE"""),101.75) -> 101.75 | AM15: =IFERROR(__xludf.DUMMYFUNCTION("""COMPUTED_VALUE"""),0.37433901956556387) -> 0.37433902 | AN15: =IFERROR(__xludf.DUMMYFUNCTION("""COMPUTED_VALUE"""),"#N/A") -> #N/A | AO15: =IFERROR(__xludf.DUMMYFUNCTION("""COMPUTED_VALUE"""),"Argentina") -> Argentina | AP15: =IFERROR(__xludf.DUMMYFUNCTION("""COMPUTED_VALUE"""),"#N/A") -> #N/A | AQ15: =IFERROR(__xludf.DUMMYFUNCTION("""COMPUTED_VALUE"""),1.0) -> 1 | AR15: =IFERROR(__xludf.DUMMYFUNCTION("""COMPUTED_VALUE"""),"#N/A") -> #N/A
J16: =IFERROR(__xludf.DUMMYFUNCTION("""COMPUTED_VALUE"""),"YMCID") -> YMCID | K16: =IFERROR(__xludf.DUMMYFUNCTION("""COMPUTED_VALUE"""),"YPF") -> YPF | L16: =IFERROR(__xludf.DUMMYFUNCTION("""COMPUTED_VALUE"""),47299.0) -> 47299 | M16: =IFERROR(__xludf.DUMMYFUNCTION("""COMPUTED_VALUE"""),0.09) -> 0.09 | N16: =IFERROR(__xludf.DUMMYFUNCTION("""COMPUTED_VALUE"""),106.95) -> 106.95 | O16: =IFERROR(__xludf.DUMMYFUNCTION("""COMPUTED_VALUE"""),0.06887414421954087) -> 0.068874144 | P16: =IFERROR(__xludf.DUMMYFUNCTION("""COMPUTED_VALUE"""),0.0042) -> 0.0042 | Q16: =IFERROR(__xludf.DUMMYFUNCTION("""COMPUTED_VALUE"""),2.028662833438036) -> 2.0286628 | R16: =IFERROR(__xludf.DUMMYFUNCTION("""COMPUTED_VALUE"""),"Semestral") -> Semestral | S16: =IFERROR(__xludf.DUMMYFUNCTION("""COMPUTED_VALUE"""),"Sinkable") -> Sinkable | T16: =IFERROR(__xludf.DUMMYFUNCTION("""COMPUTED_VALUE"""),"NY") -> NY | U16: =IFERROR(__xludf.DUMMYFUNCTION("""COMPUTED_VALUE"""),1.0) -> 1 | V16: =IFERROR(__xludf.DUMMYFUNCTION("""COMPUTED_VALUE"""),83.0) -> 83 | W16: =IFERROR(__xludf.DUMMYFUNCTION("""COMPUTED_VALUE"""),1.0431602048280906) -> 1.0431602 | AG16: =IFERROR(__xludf.DUMMYFUNCTION("""COMPUTED_VALUE"""),"Poco volumen") -> Poco volumen | AH16: =IFERROR(__xludf.DUMMYFUNCTION("""COMPUTED_VALUE"""),"Loma Negra") -> Loma Negra | AI16: =IFERROR(__xludf.DUMMYFUNCTION("""COMPUTED_VALUE"""),"LOC3D") -> LOC3D | AJ16: =IFERROR(__xludf.DUMMYFUNCTION("""COMPUTED_VALUE"""),0.024811236223566707) -> 0.024811236 | AK16: =IFERROR(__xludf.DUMMYFUNCTION("""COMPUTED_VALUE"""),102.65) -> 102.65 | AL16: =IFERROR(__xludf.DUMMYFUNCTION("""COMPUTED_VALUE"""),102.65) -> 102.65 | AM16: =IFERROR(__xludf.DUMMYFUNCTION("""COMPUTED_VALUE"""),0.4140727275747961) -> 0.41407273 | AN16: =IFERROR(__xludf.DUMMYFUNCTION("""COMPUTED_VALUE"""),46092.0) -> 46092 | AO16: =IFERROR(__xludf.DUMMYFUNCTION("""COMPUTED_VALUE"""),"Argentina") -> Argentina | AP16: =IFERROR(__xludf.DUMMYFUNCTION("""COMPUTED_VALUE"""),"Semestral") -> Semestral | AQ16: =IFERROR(__xludf.DUMMYFUNCTION("""COMPUTED_VALUE"""),50.0) -> 50 | AR16: =IFERROR(__xludf.DUMMYFUNCTION("""COMPUTED_VALUE"""),"Bullet") -> Bullet
B17: Agresivo | J17: =IFERROR(__xludf.DUMMYFUNCTION("""COMPUTED_VALUE"""),"DNC7D") -> DNC7D | K17: =IFERROR(__xludf.DUMMYFUNCTION("""COMPUTED_VALUE"""),"Edenor") -> Edenor | L17: =IFERROR(__xludf.DUMMYFUNCTION("""COMPUTED_VALUE"""),47780.0) -> 47780 | M17: =IFERROR(__xludf.DUMMYFUNCTION("""COMPUTED_VALUE"""),0.0975) -> 0.0975 | N17: =IFERROR(__xludf.DUMMYFUNCTION("""COMPUTED_VALUE"""),100.45) -> 100.45 | O17: =IFERROR(__xludf.DUMMYFUNCTION("""COMPUTED_VALUE"""),0.11324817794294945) -> 0.11324818 | P17: =IFERROR(__xludf.DUMMYFUNCTION("""COMPUTED_VALUE"""),-0.0024) -> -0.0024 | Q17: =IFERROR(__xludf.DUMMYFUNCTION("""COMPUTED_VALUE"""),3.2704911426029253) -> 3.2704911 | R17: =IFERROR(__xludf.DUMMYFUNCTION("""COMPUTED_VALUE"""),"Semestral") -> Semestral | S17: =IFERROR(__xludf.DUMMYFUNCTION("""COMPUTED_VALUE"""),"Sinkable") -> Sinkable | T17: =IFERROR(__xludf.DUMMYFUNCTION("""COMPUTED_VALUE"""),"NY") -> NY | U17: =IFERROR(__xludf.DUMMYFUNCTION("""COMPUTED_VALUE"""),100.0) -> 100 | V17: =IFERROR(__xludf.DUMMYFUNCTION("""COMPUTED_VALUE"""),16.0) -> 16 | W17: =IFERROR(__xludf.DUMMYFUNCTION("""COMPUTED_VALUE"""),0.9607843137254902) -> 0.96078431 | AG17: =IFERROR(__xludf.DUMMYFUNCTION("""COMPUTED_VALUE"""),"Poco volumen") -> Poco volumen | AH17: =IFERROR(__xludf.DUMMYFUNCTION("""COMPUTED_VALUE"""),"Central Puerto") -> Central Puerto | AI17: =IFERROR(__xludf.DUMMYFUNCTION("""COMPUTED_VALUE"""),"NPCAD") -> NPCAD | AJ17: =IFERROR(__xludf.DUMMYFUNCTION("""COMPUTED_VALUE"""),0.01070915154750966) -> 0.010709152 | AK17: =IFERROR(__xludf.DUMMYFUNCTION("""COMPUTED_VALUE"""),103.0) -> 103 | AL17: =IFERROR(__xludf.DUMMYFUNCTION("""COMPUTED_VALUE"""),103.0) -> 103 | AM17: =IFERROR(__xludf.DUMMYFUNCTION("""COMPUTED_VALUE"""),0.42512694791096006) -> 0.42512695 | AN17: =IFERROR(__xludf.DUMMYFUNCTION("""COMPUTED_VALUE"""),46095.0) -> 46095 | AO17: =IFERROR(__xludf.DUMMYFUNCTION("""COMPUTED_VALUE"""),"Argentina") -> Argentina | AP17: =IFERROR(__xludf.DUMMYFUNCTION("""COMPUTED_VALUE"""),"Semestral") -> Semestral | AQ17: =IFERROR(__xludf.DUMMYFUNCTION("""COMPUTED_VALUE"""),1.0) -> 1 | AR17: =IFERROR(__xludf.DUMMYFUNCTION("""COMPUTED_VALUE"""),"Bullet") -> Bullet
B18: =B5 -> Central Puerto | C18: =C5 -> TIR | D18: M,Duration | E18: Vto | F18: M,Duration | G18: Weight | H18: Lamina | J18: =IFERROR(__xludf.DUMMYFUNCTION("""COMPUTED_VALUE"""),"RUCDD") -> RUCDD | K18: =IFERROR(__xludf.DUMMYFUNCTION("""COMPUTED_VALUE"""),"MSU Energy") -> MSU Energy | L18: =IFERROR(__xludf.DUMMYFUNCTION("""COMPUTED_VALUE"""),47822.0) -> 47822 | M18: =IFERROR(__xludf.DUMMYFUNCTION("""COMPUTED_VALUE"""),0.0975) -> 0.0975 | N18: =IFERROR(__xludf.DUMMYFUNCTION("""COMPUTED_VALUE"""),91.2) -> 91.2 | O18: =IFERROR(__xludf.DUMMYFUNCTION("""COMPUTED_VALUE"""),0.1381500807351918) -> 0.13815008 | P18: =IFERROR(__xludf.DUMMYFUNCTION("""COMPUTED_VALUE"""),-0.013999999999999999) -> -0.014 | Q18: =IFERROR(__xludf.DUMMYFUNCTION("""COMPUTED_VALUE"""),3.629989032153328) -> 3.629989 | R18: =IFERROR(__xludf.DUMMYFUNCTION("""COMPUTED_VALUE"""),"Semestral") -> Semestral | S18: =IFERROR(__xludf.DUMMYFUNCTION("""COMPUTED_VALUE"""),"Sinkable") -> Sinkable | T18: =IFERROR(__xludf.DUMMYFUNCTION("""COMPUTED_VALUE"""),"NY") -> NY | U18: =IFERROR(__xludf.DUMMYFUNCTION("""COMPUTED_VALUE"""),1.0) -> 1 | V18: =IFERROR(__xludf.DUMMYFUNCTION("""COMPUTED_VALUE"""),58.0) -> 58 | W18: =IFERROR(__xludf.DUMMYFUNCTION("""COMPUTED_VALUE"""),0.8819049921431162) -> 0.88190499 | AH18: =IFERROR(__xludf.DUMMYFUNCTION("""COMPUTED_VALUE"""),"Tecpetrol") -> Tecpetrol | AI18: =IFERROR(__xludf.DUMMYFUNCTION("""COMPUTED_VALUE"""),"TTC7D") -> TTC7D | AJ18: =IFERROR(__xludf.DUMMYFUNCTION("""COMPUTED_VALUE"""),0.07945945525153902) -> 0.079459455 | AK18: =IFERROR(__xludf.DUMMYFUNCTION("""COMPUTED_VALUE"""),101.85) -> 101.85 | AL18: =IFERROR(__xludf.DUMMYFUNCTION("""COMPUTED_VALUE"""),101.85) -> 101.85 | AM18: =IFERROR(__xludf.DUMMYFUNCTION("""COMPUTED_VALUE"""),0.50010985450224) -> 0.50010985 | AN18: =IFERROR(__xludf.DUMMYFUNCTION("""COMPUTED_VALUE"""),46134.0) -> 46134 | AO18: =IFERROR(__xludf.DUMMYFUNCTION("""COMPUTED_VALUE"""),"Argentina") -> Argentina | AP18: =IFERROR(__xludf.DUMMYFUNCTION("""COMPUTED_VALUE"""),"Semestral") -> Semestral | AQ18: =IFERROR(__xludf.DUMMYFUNCTION("""COMPUTED_VALUE"""),1.0) -> 1 | AR18: =IFERROR(__xludf.DUMMYFUNCTION("""COMPUTED_VALUE"""),"Bullet") -> Bullet
B19: DNC7D | C19: =VLOOKUP(B19,$K$6:$T$36,2,0) -> #N/A | D19: =VLOOKUP(B19,$K$6:$T$36,5,0) -> #N/A | E19: =VLOOKUP(B19,$K$6:$T$36,6,0) -> #N/A | F19: =D19 -> #N/A | G19: =F19/$G$23 -> #N/A | H19: =VLOOKUP(B19,$K$6:$T$36,9,0) -> #N/A | J19: =IFERROR(__xludf.DUMMYFUNCTION("""COMPUTED_VALUE"""),"TLCMD") -> TLCMD | K19: =IFERROR(__xludf.DUMMYFUNCTION("""COMPUTED_VALUE"""),"Telecom") -> Telecom | L19: =IFERROR(__xludf.DUMMYFUNCTION("""COMPUTED_VALUE"""),48047.0) -> 48047 | M19: =IFERROR(__xludf.DUMMYFUNCTION("""COMPUTED_VALUE"""),0.095) -> 0.095 | N19: =IFERROR(__xludf.DUMMYFUNCTION("""COMPUTED_VALUE"""),103.7) -> 103.7 | O19: =IFERROR(__xludf.DUMMYFUNCTION("""COMPUTED_VALUE"""),0.0928674814932401) -> 0.092867481 | P19: =IFERROR(__xludf.DUMMYFUNCTION("""COMPUTED_VALUE"""),-0.0028000000000000004) -> -0.0028 | Q19: =IFERROR(__xludf.DUMMYFUNCTION("""COMPUTED_VALUE"""),3.8979568160861335) -> 3.8979568 | R19: =IFERROR(__xludf.DUMMYFUNCTION("""COMPUTED_VALUE"""),"Semestral") -> Semestral | S19: =IFERROR(__xludf.DUMMYFUNCTION("""COMPUTED_VALUE"""),"Sinkable") -> Sinkable | T19: =IFERROR(__xludf.DUMMYFUNCTION("""COMPUTED_VALUE"""),"NY") -> NY | U19: =IFERROR(__xludf.DUMMYFUNCTION("""COMPUTED_VALUE"""),1000.0) -> 1000 | V19: =IFERROR(__xludf.DUMMYFUNCTION("""COMPUTED_VALUE"""),102.0) -> 102 | W19: =IFERROR(__xludf.DUMMYFUNCTION("""COMPUTED_VALUE"""),1.014773638501162) -> 1.0147736 | AH19: =IFERROR(__xludf.DUMMYFUNCTION("""COMPUTED_VALUE"""),"YPF") -> YPF | AI19: =IFERROR(__xludf.DUMMYFUNCTION("""COMPUTED_VALUE"""),"YMCVD") -> YMCVD | AJ19: =IFERROR(__xludf.DUMMYFUNCTION("""COMPUTED_VALUE"""),0.10739006387326) -> 0.10739006 | AK19: =IFERROR(__xludf.DUMMYFUNCTION("""COMPUTED_VALUE"""),101.1) -> 101.1 | AL19: =IFERROR(__xludf.DUMMYFUNCTION("""COMPUTED_VALUE"""),101.1) -> 101.1 | AM19: =IFERROR(__xludf.DUMMYFUNCTION("""COMPUTED_VALUE"""),0.580855070282137) -> 0.58085507 | AN19: =IFERROR(__xludf.DUMMYFUNCTION("""COMPUTED_VALUE"""),46168.0) -> 46168 | AO19: =IFERROR(__xludf.DUMMYFUNCTION("""COMPUTED_VALUE"""),"Argentina") -> Argentina | AP19: =IFERROR(__xludf.DUMMYFUNCTION("""COMPUTED_VALUE"""),"Trimestral") -> Trimestral | AQ19: =IFERROR(__xludf.DUMMYFUNCTION("""COMPUTED_VALUE"""),1.0) -> 1 | AR19: =IFERROR(__xludf.DUMMYFUNCTION("""COMPUTED_VALUE"""),"Bullet") -> Bullet
B20: TLCPD | C20: =VLOOKUP(B20,$K$6:$T$36,2,0) -> #N/A | D20: =VLOOKUP(B20,$K$6:$T$36,5,0) -> #N/A | E20: =VLOOKUP(B20,$K$6:$T$36,6,0) -> #N/A | F20: =D20 -> #N/A | G20: =F20/$G$23 -> #N/A | H20: =VLOOKUP(B20,$K$6:$T$36,9,0) -> #N/A | J20: =IFERROR(__xludf.DUMMYFUNCTION("""COMPUTED_VALUE"""),"TSC3D") -> TSC3D | K20: =IFERROR(__xludf.DUMMYFUNCTION("""COMPUTED_VALUE"""),"TGS") -> TGS | L20: =IFERROR(__xludf.DUMMYFUNCTION("""COMPUTED_VALUE"""),48053.0) -> 48053 | M20: =IFERROR(__xludf.DUMMYFUNCTION("""COMPUTED_VALUE"""),0.085) -> 0.085 | N20: =IFERROR(__xludf.DUMMYFUNCTION("""COMPUTED_VALUE"""),107.2) -> 107.2 | O20: =IFERROR(__xludf.DUMMYFUNCTION("""COMPUTED_VALUE"""),0.07462369421868527) -> 0.074623694 | P20: =IFERROR(__xludf.DUMMYFUNCTION("""COMPUTED_VALUE"""),-0.0046) -> -0.0046 | Q20: =IFERROR(__xludf.DUMMYFUNCTION("""COMPUTED_VALUE"""),4.690068652262308) -> 4.6900687 | R20: =IFERROR(__xludf.DUMMYFUNCTION("""COMPUTED_VALUE"""),"Semestral") -> Semestral | S20: =IFERROR(__xludf.DUMMYFUNCTION("""COMPUTED_VALUE"""),"Bullet") -> Bullet | T20: =IFERROR(__xludf.DUMMYFUNCTION("""COMPUTED_VALUE"""),"NY") -> NY | U20: =IFERROR(__xludf.DUMMYFUNCTION("""COMPUTED_VALUE"""),10000.0) -> 10000 | V20: =IFERROR(__xludf.DUMMYFUNCTION("""COMPUTED_VALUE"""),108.0) -> 108 | W20: =IFERROR(__xludf.DUMMYFUNCTION("""COMPUTED_VALUE"""),1.052858448485179) -> 1.0528584 | AH20: =IFERROR(__xludf.DUMMYFUNCTION("""COMPUTED_VALUE"""),"Balanz") -> Balanz | AI20: =IFERROR(__xludf.DUMMYFUNCTION("""COMPUTED_VALUE"""),"NBS1D") -> NBS1D | AJ20: =IFERROR(__xludf.DUMMYFUNCTION("""COMPUTED_VALUE"""),0.07488250269684493) -> 0.074882503 | AK20: =IFERROR(__xludf.DUMMYFUNCTION("""COMPUTED_VALUE"""),100.2) -> 100.2 | AL20: =IFERROR(__xludf.DUMMYFUNCTION("""COMPUTED_VALUE"""),100.2) -> 100.2 | AM20: =IFERROR(__xludf.DUMMYFUNCTION("""COMPUTED_VALUE"""),0.6311269643904209) -> 0.63112696 | AN20: =IFERROR(__xludf.DUMMYFUNCTION("""COMPUTED_VALUE"""),46179.0) -> 46179 | AO20: =IFERROR(__xludf.DUMMYFUNCTION("""COMPUTED_VALUE"""),"Argentina") -> Argentina | AP20: =IFERROR(__xludf.DUMMYFUNCTION("""COMPUTED_VALUE"""),"Cuatrimestral") -> Cuatrimestral | AQ20: =IFERROR(__xludf.DUMMYFUNCTION("""COMPUTED_VALUE"""),1.0) -> 1 | AR20: =IFERROR(__xludf.DUMMYFUNCTION("""COMPUTED_VALUE"""),"Bullet") -> Bullet
J21: =IFERROR(__xludf.DUMMYFUNCTION("""COMPUTED_VALUE"""),"ARC1D") -> ARC1D | K21: =IFERROR(__xludf.DUMMYFUNCTION("""COMPUTED_VALUE"""),"Aeropuertos 2000") -> Aeropuertos 2000 | L21: =IFERROR(__xludf.DUMMYFUNCTION("""COMPUTED_VALUE"""),48061.0) -> 48061 | M21: =IFERROR(__xludf.DUMMYFUNCTION("""COMPUTED_VALUE"""),0.085) -> 0.085 | N21: =IFERROR(__xludf.DUMMYFUNCTION("""COMPUTED_VALUE"""),106.75) -> 106.75 | O21: =IFERROR(__xludf.DUMMYFUNCTION("""COMPUTED_VALUE"""),0.0706169294415442) -> 0.070616929 | P21: =IFERROR(__xludf.DUMMYFUNCTION("""COMPUTED_VALUE"""),-0.0161) -> -0.0161 | Q21: =IFERROR(__xludf.DUMMYFUNCTION("""COMPUTED_VALUE"""),3.2122134385327046) -> 3.2122134 | R21: =IFERROR(__xludf.DUMMYFUNCTION("""COMPUTED_VALUE"""),"Trimestral") -> Trimestral | S21: =IFERROR(__xludf.DUMMYFUNCTION("""COMPUTED_VALUE"""),"Sinkable") -> Sinkable | T21: =IFERROR(__xludf.DUMMYFUNCTION("""COMPUTED_VALUE"""),"NY") -> NY | U21: =IFERROR(__xludf.DUMMYFUNCTION("""COMPUTED_VALUE"""),1000.0) -> 1000 | V21: =IFERROR(__xludf.DUMMYFUNCTION("""COMPUTED_VALUE"""),24.0) -> 24 | W21: =IFERROR(__xludf.DUMMYFUNCTION("""COMPUTED_VALUE"""),1.0503874379894225) -> 1.0503874 | AH21: =IFERROR(__xludf.DUMMYFUNCTION("""COMPUTED_VALUE"""),"Edenor") -> Edenor | AI21: =IFERROR(__xludf.DUMMYFUNCTION("""COMPUTED_VALUE"""),"DNC5D") -> DNC5D | AJ21: =IFERROR(__xludf.DUMMYFUNCTION("""COMPUTED_VALUE"""),0.08612137462589714) -> 0.086121375 | AK21: =IFERROR(__xludf.DUMMYFUNCTION("""COMPUTED_VALUE"""),104.3) -> 104.3 | AL21: =IFERROR(__xludf.DUMMYFUNCTION("""COMPUTED_VALUE"""),104.3) -> 104.3 | AM21: =IFERROR(__xludf.DUMMYFUNCTION("""COMPUTED_VALUE"""),2.441654856231381) -> 2.4416549 | AN21: =IFERROR(__xludf.DUMMYFUNCTION("""COMPUTED_VALUE"""),46970.0) -> 46970 | AO21: =IFERROR(__xludf.DUMMYFUNCTION("""COMPUTED_VALUE"""),"Argentina") -> Argentina | AP21: =IFERROR(__xludf.DUMMYFUNCTION("""COMPUTED_VALUE"""),"Semestral") -> Semestral | AQ21: =IFERROR(__xludf.DUMMYFUNCTION("""COMPUTED_VALUE"""),1.0) -> 1 | AR21: =IFERROR(__xludf.DUMMYFUNCTION("""COMPUTED_VALUE"""),"Bullet") -> Bullet
J22: =IFERROR(__xludf.DUMMYFUNCTION("""COMPUTED_VALUE"""),"MGCMD") -> MGCMD | K22: =IFERROR(__xludf.DUMMYFUNCTION("""COMPUTED_VALUE"""),"Pampa Energia") -> Pampa Energia | L22: =IFERROR(__xludf.DUMMYFUNCTION("""COMPUTED_VALUE"""),48101.0) -> 48101 | M22: =IFERROR(__xludf.DUMMYFUNCTION("""COMPUTED_VALUE"""),0.0795) -> 0.0795 | N22: =IFERROR(__xludf.DUMMYFUNCTION("""COMPUTED_VALUE"""),103.7) -> 103.7 | O22: =IFERROR(__xludf.DUMMYFUNCTION("""COMPUTED_VALUE"""),0.07441493850747857) -> 0.074414939 | P22: =IFERROR(__xludf.DUMMYFUNCTION("""COMPUTED_VALUE"""),0.0019) -> 0.0019 | Q22: =IFERROR(__xludf.DUMMYFUNCTION("""COMPUTED_VALUE"""),4.8671100069722595) -> 4.86711 | R22: =IFERROR(__xludf.DUMMYFUNCTION("""COMPUTED_VALUE"""),"Semestral") -> Semestral | S22: =IFERROR(__xludf.DUMMYFUNCTION("""COMPUTED_VALUE"""),"Bullet") -> Bullet | T22: =IFERROR(__xludf.DUMMYFUNCTION("""COMPUTED_VALUE"""),"NY") -> NY | U22: =IFERROR(__xludf.DUMMYFUNCTION("""COMPUTED_VALUE"""),10000.0) -> 10000 | V22: =IFERROR(__xludf.DUMMYFUNCTION("""COMPUTED_VALUE"""),153.0) -> 153 | W22: =IFERROR(__xludf.DUMMYFUNCTION("""COMPUTED_VALUE"""),0.9904134283633586) -> 0.99041343 | AH22: =IFERROR(__xludf.DUMMYFUNCTION("""COMPUTED_VALUE"""),"YPF") -> YPF | AI22: =IFERROR(__xludf.DUMMYFUNCTION("""COMPUTED_VALUE"""),"YM39D") -> YM39D | AJ22: =IFERROR(__xludf.DUMMYFUNCTION("""COMPUTED_VALUE"""),0.0877953320026665) -> 0.087795332 | AK22: =IFERROR(__xludf.DUMMYFUNCTION("""COMPUTED_VALUE"""),102.95) -> 102.95 | AL22: =IFERROR(__xludf.DUMMYFUNCTION("""COMPUTED_VALUE"""),102.95) -> 102.95 | AM22: =IFERROR(__xludf.DUMMYFUNCTION("""COMPUTED_VALUE"""),3.774346743823558) -> 3.7743467 | AN22: =IFERROR(__xludf.DUMMYFUNCTION("""COMPUTED_VALUE"""),47686.0) -> 47686 | AO22: =IFERROR(__xludf.DUMMYFUNCTION("""COMPUTED_VALUE"""),"Argentina") -> Argentina | AP22: =IFERROR(__xludf.DUMMYFUNCTION("""COMPUTED_VALUE"""),"Semestral") -> Semestral | AQ22: =IFERROR(__xludf.DUMMYFUNCTION("""COMPUTED_VALUE"""),100.0) -> 100 | AR22: =IFERROR(__xludf.DUMMYFUNCTION("""COMPUTED_VALUE"""),"Bullet") -> Bullet
G23: =SUM(F19:F22) -> #N/A | J23: =IFERROR(__xludf.DUMMYFUNCTION("""COMPUTED_VALUE"""),"YMCXD") -> YMCXD | K23: =IFERROR(__xludf.DUMMYFUNCTION("""COMPUTED_VALUE"""),"YPF") -> YPF | L23: =IFERROR(__xludf.DUMMYFUNCTION("""COMPUTED_VALUE"""),48102.0) -> 48102 | M23: =IFERROR(__xludf.DUMMYFUNCTION("""COMPUTED_VALUE"""),0.0875) -> 0.0875 | N23: =IFERROR(__xludf.DUMMYFUNCTION("""COMPUTED_VALUE"""),104.3) -> 104.3 | O23: =IFERROR(__xludf.DUMMYFUNCTION("""COMPUTED_VALUE"""),0.08058538599984179) -> 0.080585386 | P23: =IFERROR(__xludf.DUMMYFUNCTION("""COMPUTED_VALUE"""),0.0028000000000000004) -> 0.0028 | Q23: =IFERROR(__xludf.DUMMYFUNCTION("""COMPUTED_VALUE"""),4.382994151768527) -> 4.3829942 | R23: =IFERROR(__xludf.DUMMYFUNCTION("""COMPUTED_VALUE"""),"Semestral") -> Semestral | S23: =IFERROR(__xludf.DUMMYFUNCTION("""COMPUTED_VALUE"""),"Sinkable") -> Sinkable | T23: =IFERROR(__xludf.DUMMYFUNCTION("""COMPUTED_VALUE"""),"NY") -> NY | U23: =IFERROR(__xludf.DUMMYFUNCTION("""COMPUTED_VALUE"""),1.0) -> 1 | V23: =IFERROR(__xludf.DUMMYFUNCTION("""COMPUTED_VALUE"""),154.0) -> 154 | W23: =IFERROR(__xludf.DUMMYFUNCTION("""COMPUTED_VALUE"""),0.9918901069871879) -> 0.99189011
J24: =IFERROR(__xludf.DUMMYFUNCTION("""COMPUTED_VALUE"""),"PNXCD") -> PNXCD | K24: =IFERROR(__xludf.DUMMYFUNCTION("""COMPUTED_VALUE"""),"Pan American Energy") -> Pan American Energy | L24: =IFERROR(__xludf.DUMMYFUNCTION("""COMPUTED_VALUE"""),48334.0) -> 48334 | M24: =IFERROR(__xludf.DUMMYFUNCTION("""COMPUTED_VALUE"""),0.085) -> 0.085 | N24: =IFERROR(__xludf.DUMMYFUNCTION("""COMPUTED_VALUE"""),111.0) -> 111 | O24: =IFERROR(__xludf.DUMMYFUNCTION("""COMPUTED_VALUE"""),0.07017365195080114) -> 0.070173652 | P24: =IFERROR(__xludf.DUMMYFUNCTION("""COMPUTED_VALUE"""),-9.0E-4) -> -0.0009 | Q24: =IFERROR(__xludf.DUMMYFUNCTION("""COMPUTED_VALUE"""),4.458917181881186) -> 4.4589172 | R24: =IFERROR(__xludf.DUMMYFUNCTION("""COMPUTED_VALUE"""),"Semestral") -> Semestral | S24: =IFERROR(__xludf.DUMMYFUNCTION("""COMPUTED_VALUE"""),"Sinkable") -> Sinkable | T24: =IFERROR(__xludf.DUMMYFUNCTION("""COMPUTED_VALUE"""),"NY") -> NY | U24: =IFERROR(__xludf.DUMMYFUNCTION("""COMPUTED_VALUE"""),1000.0) -> 1000 | V24: =IFERROR(__xludf.DUMMYFUNCTION("""COMPUTED_VALUE"""),22.0) -> 22 | W24: =IFERROR(__xludf.DUMMYFUNCTION("""COMPUTED_VALUE"""),1.0691066698771972) -> 1.0691067
B25: 6-12 meses Conservador | J25: =IFERROR(__xludf.DUMMYFUNCTION("""COMPUTED_VALUE"""),"YFCJD") -> YFCJD | K25: =IFERROR(__xludf.DUMMYFUNCTION("""COMPUTED_VALUE"""),"YPF Luz") -> YPF Luz | L25: =IFERROR(__xludf.DUMMYFUNCTION("""COMPUTED_VALUE"""),48503.0) -> 48503 | M25: =IFERROR(__xludf.DUMMYFUNCTION("""COMPUTED_VALUE"""),0.0788) -> 0.0788 | N25: =IFERROR(__xludf.DUMMYFUNCTION("""COMPUTED_VALUE"""),102.8) -> 102.8 | O25: =IFERROR(__xludf.DUMMYFUNCTION("""COMPUTED_VALUE"""),0.08249727097335856) -> 0.082497271 | P25: =IFERROR(__xludf.DUMMYFUNCTION("""COMPUTED_VALUE"""),9.0E-4) -> 0.0009 | Q25: =IFERROR(__xludf.DUMMYFUNCTION("""COMPUTED_VALUE"""),4.74795016936165) -> 4.7479502 | R25: =IFERROR(__xludf.DUMMYFUNCTION("""COMPUTED_VALUE"""),"Semestral") -> Semestral | S25: =IFERROR(__xludf.DUMMYFUNCTION("""COMPUTED_VALUE"""),"Sinkable") -> Sinkable | T25: =IFERROR(__xludf.DUMMYFUNCTION("""COMPUTED_VALUE"""),"NY") -> NY | U25: =IFERROR(__xludf.DUMMYFUNCTION("""COMPUTED_VALUE"""),1000.0) -> 1000 | V25: =IFERROR(__xludf.DUMMYFUNCTION("""COMPUTED_VALUE"""),8.0) -> 8 | W25: =IFERROR(__xludf.DUMMYFUNCTION("""COMPUTED_VALUE"""),0.9898892633606163) -> 0.98988926
B26: =B13 | C26: TIR | D26: M,Duration | E26: Vto | F26: M,Duration | G26: Weight | H26: Lamina | J26: =IFERROR(__xludf.DUMMYFUNCTION("""COMPUTED_VALUE"""),"PLC4D") -> PLC4D | K26: =IFERROR(__xludf.DUMMYFUNCTION("""COMPUTED_VALUE"""),"Pluspetrol") -> Pluspetrol | L26: =IFERROR(__xludf.DUMMYFUNCTION("""COMPUTED_VALUE"""),48364.0) -> 48364 | M26: =IFERROR(__xludf.DUMMYFUNCTION("""COMPUTED_VALUE"""),0.085) -> 0.085 | N26: =IFERROR(__xludf.DUMMYFUNCTION("""COMPUTED_VALUE"""),104.75) -> 104.75 | O26: =IFERROR(__xludf.DUMMYFUNCTION("""COMPUTED_VALUE"""),0.08323104363093586) -> 0.083231044 | P26: =IFERROR(__xludf.DUMMYFUNCTION("""COMPUTED_VALUE"""),-0.004699999999999999) -> -0.0047 | Q26: =IFERROR(__xludf.DUMMYFUNCTION("""COMPUTED_VALUE"""),5.1114625564212) -> 5.1114626 | R26: =IFERROR(__xludf.DUMMYFUNCTION("""COMPUTED_VALUE"""),"Semestral") -> Semestral | S26: =IFERROR(__xludf.DUMMYFUNCTION("""COMPUTED_VALUE"""),"Bullet") -> Bullet | T26: =IFERROR(__xludf.DUMMYFUNCTION("""COMPUTED_VALUE"""),"NY") -> NY | U26: =IFERROR(__xludf.DUMMYFUNCTION("""COMPUTED_VALUE"""),1000.0) -> 1000 | V26: =IFERROR(__xludf.DUMMYFUNCTION("""COMPUTED_VALUE"""),53.0) -> 53 | W26: =IFERROR(__xludf.DUMMYFUNCTION("""COMPUTED_VALUE"""),1.015839663811217) -> 1.0158397
J27: =IFERROR(__xludf.DUMMYFUNCTION("""COMPUTED_VALUE"""),"TTCAD") -> TTCAD | K27: =IFERROR(__xludf.DUMMYFUNCTION("""COMPUTED_VALUE"""),"Tecpetrol") -> Tecpetrol | L27: =IFERROR(__xludf.DUMMYFUNCTION("""COMPUTED_VALUE"""),48601.0) -> 48601 | M27: =IFERROR(__xludf.DUMMYFUNCTION("""COMPUTED_VALUE"""),0.0763) -> 0.0763 | N27: =IFERROR(__xludf.DUMMYFUNCTION("""COMPUTED_VALUE"""),105.45) -> 105.45 | O27: =IFERROR(__xludf.DUMMYFUNCTION("""COMPUTED_VALUE"""),0.0697006756604922) -> 0.069700676 | P27: =IFERROR(__xludf.DUMMYFUNCTION("""COMPUTED_VALUE"""),0.0042) -> 0.0042 | Q27: =IFERROR(__xludf.DUMMYFUNCTION("""COMPUTED_VALUE"""),5.098153000107035) -> 5.098153 | R27: =IFERROR(__xludf.DUMMYFUNCTION("""COMPUTED_VALUE"""),"Semestral") -> Semestral | S27: =IFERROR(__xludf.DUMMYFUNCTION("""COMPUTED_VALUE"""),"Sinkable") -> Sinkable | T27: =IFERROR(__xludf.DUMMYFUNCTION("""COMPUTED_VALUE"""),"NY") -> NY | U27: =IFERROR(__xludf.DUMMYFUNCTION("""COMPUTED_VALUE"""),1000.0) -> 1000 | V27: =IFERROR(__xludf.DUMMYFUNCTION("""COMPUTED_VALUE"""),106.0) -> 106 | W27: =IFERROR(__xludf.DUMMYFUNCTION("""COMPUTED_VALUE"""),1.037145813625482) -> 1.0371458
J28: =IFERROR(__xludf.DUMMYFUNCTION("""COMPUTED_VALUE"""),"YMCJD") -> YMCJD | K28: =IFERROR(__xludf.DUMMYFUNCTION("""COMPUTED_VALUE"""),"YPF") -> YPF | L28: =IFERROR(__xludf.DUMMYFUNCTION("""COMPUTED_VALUE"""),48852.0) -> 48852 | M28: =IFERROR(__xludf.DUMMYFUNCTION("""COMPUTED_VALUE"""),0.07) -> 0.07 | N28: =IFERROR(__xludf.DUMMYFUNCTION("""COMPUTED_VALUE"""),95.21) -> 95.21 | O28: =IFERROR(__xludf.DUMMYFUNCTION("""COMPUTED_VALUE"""),0.08160710044950233) -> 0.0816071 | P28: =IFERROR(__xludf.DUMMYFUNCTION("""COMPUTED_VALUE"""),0.004699999999999999) -> 0.0047 | Q28: =IFERROR(__xludf.DUMMYFUNCTION("""COMPUTED_VALUE"""),5.275965287084322) -> 5.2759653 | R28: =IFERROR(__xludf.DUMMYFUNCTION("""COMPUTED_VALUE"""),"Semestral") -> Semestral | S28: =IFERROR(__xludf.DUMMYFUNCTION("""COMPUTED_VALUE"""),"Sinkable") -> Sinkable | T28: =IFERROR(__xludf.DUMMYFUNCTION("""COMPUTED_VALUE"""),"NY") -> NY | U28: =IFERROR(__xludf.DUMMYFUNCTION("""COMPUTED_VALUE"""),1.0) -> 1 | V28: =IFERROR(__xludf.DUMMYFUNCTION("""COMPUTED_VALUE"""),173.0) -> 173 | W28: =IFERROR(__xludf.DUMMYFUNCTION("""COMPUTED_VALUE"""),0.9504367357125031) -> 0.95043674
J29: =IFERROR(__xludf.DUMMYFUNCTION("""COMPUTED_VALUE"""),"TLCPD") -> TLCPD | K29: =IFERROR(__xludf.DUMMYFUNCTION("""COMPUTED_VALUE"""),"Telecom") -> Telecom | L29: =IFERROR(__xludf.DUMMYFUNCTION("""COMPUTED_VALUE"""),48727.0) -> 48727 | M29: =IFERROR(__xludf.DUMMYFUNCTION("""COMPUTED_VALUE"""),0.0925) -> 0.0925 | N29: =IFERROR(__xludf.DUMMYFUNCTION("""COMPUTED_VALUE"""),102.0) -> 102 | O29: =IFERROR(__xludf.DUMMYFUNCTION("""COMPUTED_VALUE"""),0.09747772156634352) -> 0.097477722 | P29: =IFERROR(__xludf.DUMMYFUNCTION("""COMPUTED_VALUE"""),-0.0048) -> -0.0048 | Q29: =IFERROR(__xludf.DUMMYFUNCTION("""COMPUTED_VALUE"""),5.213219007752955) -> 5.213219 | R29: =IFERROR(__xludf.DUMMYFUNCTION("""COMPUTED_VALUE"""),"Semestral") -> Semestral | S29: =IFERROR(__xludf.DUMMYFUNCTION("""COMPUTED_VALUE"""),"Sinkable") -> Sinkable | T29: =IFERROR(__xludf.DUMMYFUNCTION("""COMPUTED_VALUE"""),"NY") -> NY | U29: =IFERROR(__xludf.DUMMYFUNCTION("""COMPUTED_VALUE"""),100.0) -> 100 | V29: =IFERROR(__xludf.DUMMYFUNCTION("""COMPUTED_VALUE"""),51.0) -> 51 | W29: =IFERROR(__xludf.DUMMYFUNCTION("""COMPUTED_VALUE"""),0.9860497589924676) -> 0.98604976
J30: =IFERROR(__xludf.DUMMYFUNCTION("""COMPUTED_VALUE"""),"VSCVD") -> VSCVD | K30: =IFERROR(__xludf.DUMMYFUNCTION("""COMPUTED_VALUE"""),"Vista Energy") -> Vista Energy | L30: =IFERROR(__xludf.DUMMYFUNCTION("""COMPUTED_VALUE"""),48740.0) -> 48740 | M30: =IFERROR(__xludf.DUMMYFUNCTION("""COMPUTED_VALUE"""),0.085) -> 0.085 | N30: =IFERROR(__xludf.DUMMYFUNCTION("""COMPUTED_VALUE"""),106.0) -> 106 | O30: =IFERROR(__xludf.DUMMYFUNCTION("""COMPUTED_VALUE"""),0.08023538487148903) -> 0.080235385 | P30: =IFERROR(__xludf.DUMMYFUNCTION("""COMPUTED_VALUE"""),0.004699999999999999) -> 0.0047 | Q30: =IFERROR(__xludf.DUMMYFUNCTION("""COMPUTED_VALUE"""),5.14696178862725) -> 5.1469618 | R30: =IFERROR(__xludf.DUMMYFUNCTION("""COMPUTED_VALUE"""),"Semestral") -> Semestral | S30: =IFERROR(__xludf.DUMMYFUNCTION("""COMPUTED_VALUE"""),"Sinkable") -> Sinkable | T30: =IFERROR(__xludf.DUMMYFUNCTION("""COMPUTED_VALUE"""),"NY") -> NY | U30: =IFERROR(__xludf.DUMMYFUNCTION("""COMPUTED_VALUE"""),1000.0) -> 1000 | V30: =IFERROR(__xludf.DUMMYFUNCTION("""COMPUTED_VALUE"""),63.0) -> 63 | W30: =IFERROR(__xludf.DUMMYFUNCTION("""COMPUTED_VALUE"""),1.03055754351378) -> 1.0305575
F31: =SUM(F27:F30) -> 0 | J31: =IFERROR(__xludf.DUMMYFUNCTION("""COMPUTED_VALUE"""),"YM34D") -> YM34D | K31: =IFERROR(__xludf.DUMMYFUNCTION("""COMPUTED_VALUE"""),"YPF") -> YPF | L31: =IFERROR(__xludf.DUMMYFUNCTION("""COMPUTED_VALUE"""),48961.0) -> 48961 | M31: =IFERROR(__xludf.DUMMYFUNCTION("""COMPUTED_VALUE"""),0.0825) -> 0.0825 | N31: =IFERROR(__xludf.DUMMYFUNCTION("""COMPUTED_VALUE"""),100.7) -> 100.7 | O31: =IFERROR(__xludf.DUMMYFUNCTION("""COMPUTED_VALUE"""),0.08647523168979138) -> 0.086475232 | P31: =IFERROR(__xludf.DUMMYFUNCTION("""COMPUTED_VALUE"""),-0.0078000000000000005) -> -0.0078 | Q31: =IFERROR(__xludf.DUMMYFUNCTION("""COMPUTED_VALUE"""),5.573419365572477) -> 5.5734194 | R31: =IFERROR(__xludf.DUMMYFUNCTION("""COMPUTED_VALUE"""),"Semestral") -> Semestral | S31: =IFERROR(__xludf.DUMMYFUNCTION("""COMPUTED_VALUE"""),"Sinkable") -> Sinkable | T31: =IFERROR(__xludf.DUMMYFUNCTION("""COMPUTED_VALUE"""),"NY") -> NY | U31: =IFERROR(__xludf.DUMMYFUNCTION("""COMPUTED_VALUE"""),1.0) -> 1 | V31: =IFERROR(__xludf.DUMMYFUNCTION("""COMPUTED_VALUE"""),101.0) -> 101 | W31: =IFERROR(__xludf.DUMMYFUNCTION("""COMPUTED_VALUE"""),0.987981358842286) -> 0.98798136
B32: Simple | J32: =IFERROR(__xludf.DUMMYFUNCTION("""COMPUTED_VALUE"""),"MGCOD") -> MGCOD | K32: =IFERROR(__xludf.DUMMYFUNCTION("""COMPUTED_VALUE"""),"Pampa Energia") -> Pampa Energia | L32: =IFERROR(__xludf.DUMMYFUNCTION("""COMPUTED_VALUE"""),49294.0) -> 49294 | M32: =IFERROR(__xludf.DUMMYFUNCTION("""COMPUTED_VALUE"""),0.0788) -> 0.0788 | N32: =IFERROR(__xludf.DUMMYFUNCTION("""COMPUTED_VALUE"""),102.0) -> 102 | O32: =IFERROR(__xludf.DUMMYFUNCTION("""COMPUTED_VALUE"""),0.08104000521943708) -> 0.081040005 | P32: =IFERROR(__xludf.DUMMYFUNCTION("""COMPUTED_VALUE"""),-9.0E-4) -> -0.0009 | Q32: =IFERROR(__xludf.DUMMYFUNCTION("""COMPUTED_VALUE"""),6.576337094089589) -> 6.5763371 | R32: =IFERROR(__xludf.DUMMYFUNCTION("""COMPUTED_VALUE"""),"Semestral") -> Semestral | S32: =IFERROR(__xludf.DUMMYFUNCTION("""COMPUTED_VALUE"""),"Bullet") -> Bullet | T32: =IFERROR(__xludf.DUMMYFUNCTION("""COMPUTED_VALUE"""),"NY") -> NY | U32: =IFERROR(__xludf.DUMMYFUNCTION("""COMPUTED_VALUE"""),10000.0) -> 10000 | V32: =IFERROR(__xludf.DUMMYFUNCTION("""COMPUTED_VALUE"""),69.0) -> 69 | W32: =IFERROR(__xludf.DUMMYFUNCTION("""COMPUTED_VALUE"""),0.9577745825875172) -> 0.95777458
B33: Ticker | C33: =L33 -> 49399 | D33: M,Duration | E33: Vto | F33: Inverse m,D | G33: Weight | H33: Lamina | J33: =IFERROR(__xludf.DUMMYFUNCTION("""COMPUTED_VALUE"""),"IRCPD") -> IRCPD | K33: =IFERROR(__xludf.DUMMYFUNCTION("""COMPUTED_VALUE"""),"IRSA") -> IRSA | L33: =IFERROR(__xludf.DUMMYFUNCTION("""COMPUTED_VALUE"""),49399.0) -> 49399 | M33: =IFERROR(__xludf.DUMMYFUNCTION("""COMPUTED_VALUE"""),0.08) -> 0.08 | N33: =IFERROR(__xludf.DUMMYFUNCTION("""COMPUTED_VALUE"""),101.0) -> 101 | O33: =IFERROR(__xludf.DUMMYFUNCTION("""COMPUTED_VALUE"""),0.08018455933001999) -> 0.080184559 | P33: =IFERROR(__xludf.DUMMYFUNCTION("""COMPUTED_VALUE"""),-0.0044) -> -0.0044 | Q33: =IFERROR(__xludf.DUMMYFUNCTION("""COMPUTED_VALUE"""),6.342041482649829) -> 6.3420415 | R33: =IFERROR(__xludf.DUMMYFUNCTION("""COMPUTED_VALUE"""),"Semestral") -> Semestral | S33: =IFERROR(__xludf.DUMMYFUNCTION("""COMPUTED_VALUE"""),"Sinkable") -> Sinkable | T33: =IFERROR(__xludf.DUMMYFUNCTION("""COMPUTED_VALUE"""),"NY") -> NY | U33: =IFERROR(__xludf.DUMMYFUNCTION("""COMPUTED_VALUE"""),1.0) -> 1 | V33: =IFERROR(__xludf.DUMMYFUNCTION("""COMPUTED_VALUE"""),174.0) -> 174 | W33: =IFERROR(__xludf.DUMMYFUNCTION("""COMPUTED_VALUE"""),1.0079840319361277) -> 1.007984
B34: YM34D | C34: =VLOOKUP($B$34,$K$6:$T$36,2,0) -> #N/A | D34: =VLOOKUP($B$34,$K$6:$T$36,5,0) -> #N/A | E34: =VLOOKUP($B$34,$K$6:$T$36,6,0) -> #N/A | F34: =1/D34 -> #N/A | G34: =F34/$F$12 -> #N/A | H34: =VLOOKUP($B$34,$K$6:$T$36,9,0) -> #N/A | J34: =IFERROR(__xludf.DUMMYFUNCTION("""COMPUTED_VALUE"""),"VSCTD") -> VSCTD | K34: =IFERROR(__xludf.DUMMYFUNCTION("""COMPUTED_VALUE"""),"Vista Energy") -> Vista Energy | L34: =IFERROR(__xludf.DUMMYFUNCTION("""COMPUTED_VALUE"""),49653.0) -> 49653 | M34: =IFERROR(__xludf.DUMMYFUNCTION("""COMPUTED_VALUE"""),0.0763) -> 0.0763 | N34: =IFERROR(__xludf.DUMMYFUNCTION("""COMPUTED_VALUE"""),99.9) -> 99.9 | O34: =IFERROR(__xludf.DUMMYFUNCTION("""COMPUTED_VALUE"""),0.0818604390915039) -> 0.081860439 | P34: =IFERROR(__xludf.DUMMYFUNCTION("""COMPUTED_VALUE"""),-0.0044) -> -0.0044 | Q34: =IFERROR(__xludf.DUMMYFUNCTION("""COMPUTED_VALUE"""),6.5851280860201555) -> 6.5851281 | R34: =IFERROR(__xludf.DUMMYFUNCTION("""COMPUTED_VALUE"""),"Semestral") -> Semestral | S34: =IFERROR(__xludf.DUMMYFUNCTION("""COMPUTED_VALUE"""),"Sinkable") -> Sinkable | T34: =IFERROR(__xludf.DUMMYFUNCTION("""COMPUTED_VALUE"""),"NY") -> NY | U34: =IFERROR(__xludf.DUMMYFUNCTION("""COMPUTED_VALUE"""),10000.0) -> 10000 | V34: =IFERROR(__xludf.DUMMYFUNCTION("""COMPUTED_VALUE"""),63.0) -> 63 | W34: =IFERROR(__xludf.DUMMYFUNCTION("""COMPUTED_VALUE"""),0.9387535360851988) -> 0.93875354
F40: =SUM(F34:F39) -> #N/A

Sheet Soberanos
B2: Working Capital | C2: TIR | D2: M,D | E2: Inverse duration | F2: Weight
A3: Lecap | B3: S10N5 | C3: =VLOOKUP(B3,$J$11:$R$63,7,0) -> 0.64634307 | D3: =VLOOKUP(B3,$J$11:$R$63,9,0) -> 33 | F3: 0.333
A4: Lecap | B4: T15D5 | C4: =VLOOKUP(B4,$J$11:$R$63,7,0) -> 0.63515085 | D4: =VLOOKUP(B4,$J$11:$R$63,9,0) -> 68 | F4: 0.333
A5: Lecap | B5: S28N5 | C5: =VLOOKUP(B5,$J$11:$R$63,7,0) -> 0.66463931 | D5: =VLOOKUP(B5,$J$11:$R$63,9,0) -> 51 | F5: 0.333
I8: =IFERROR(__xludf.DUMMYFUNCTION("IMPORTRANGE(""https://docs.google.com/spreadsheets/d/1QFB2kh2cYM7XonEBR7QFtdA5P63irew36fgS54qRFHA/edit?gid=443985142#gid=443985142"" , ""Lecaps!A:L"")"),45938.0) -> 45938 | U8: =IFERROR(__xludf.DUMMYFUNCTION("IMPORTRANGE(""https://docs.google.com/spreadsheets/d/1QFB2kh2cYM7XonEBR7QFtdA5P63irew36fgS54qRFHA/edit?gid=443985142#gid=443985142"" , ""CER!A:L"")"),45938.0) -> 45938 | AG8: =IFERROR(__xludf.DUMMYFUNCTION("IMPORTRANGE(""https://docs.google.com/spreadsheets/d/1QFB2kh2cYM7XonEBR7QFtdA5P63irew36fgS54qRFHA/edit?gid=443985142#gid=443985142"" , ""Soberanos!A:L"")"),"") | AS8: =IFERROR(__xludf.DUMMYFUNCTION("IMPORTRANGE(""https://docs.google.com/spreadsheets/d/1QFB2kh2cYM7XonEBR7QFtdA5P63irew36fgS54qRFHA/edit?gid=443985142#gid=443985142"" , ""Bopreales!A:L"")"),45938.0) -> 45938
B9: Conservador | C9: TIR | D9: M,D | E9: Inverse duration | F9: Weight | J9: =IFERROR(__xludf.DUMMYFUNCTION("""COMPUTED_VALUE"""),"LECAPS") -> LECAPS | V9: =IFERROR(__xludf.DUMMYFUNCTION("""COMPUTED_VALUE"""),"BONOS CER") -> BONOS CER | AH9: =IFERROR(__xludf.DUMMYFUNCTION("""COMPUTED_VALUE"""),"SOBERANOS USD") -> SOBERANOS USD | AT9: =IFERROR(__xludf.DUMMYFUNCTION("""COMPUTED_VALUE"""),"BOPREALES") -> BOPREALES
A10: Lecap | B10: S31O5 | C10: =VLOOKUP(B10,$J$11:$R$63,7,0) -> 0.68548876 | D10: =VLOOKUP(B10,$J$11:$R$63,9,0) -> 23 | F10: 0.5 | J10: =IFERROR(__xludf.DUMMYFUNCTION("""COMPUTED_VALUE"""),"Ticker") -> Ticker | K10: =IFERROR(__xludf.DUMMYFUNCTION("""COMPUTED_VALUE"""),"Vencimiento") -> Vencimiento | L10: =IFERROR(__xludf.DUMMYFUNCTION("""COMPUTED_VALUE"""),"Precio") -> Precio | M10: =IFERROR(__xludf.DUMMYFUNCTION("""COMPUTED_VALUE"""),"Variación") -> Variación | N10: =IFERROR(__xludf.DUMMYFUNCTION("""COMPUTED_VALUE"""),"TEM") -> TEM | O10: =IFERROR(__xludf.DUMMYFUNCTION("""COMPUTED_VALUE"""),"Rendimiento") -> Rendimiento | P10: =IFERROR(__xludf.DUMMYFUNCTION("""COMPUTED_VALUE"""),"TNA") -> TNA | Q10: =IFERROR(__xludf.DUMMYFUNCTION("""COMPUTED_VALUE"""),"TIR") -> TIR | R10: =IFERROR(__xludf.DUMMYFUNCTION("""COMPUTED_VALUE"""),"Días") -> Días | S10: =IFERROR(__xludf.DUMMYFUNCTION("""COMPUTED_VALUE"""),"Fx B.E") -> Fx B.E | V10: =IFERROR(__xludf.DUMMYFUNCTION("""COMPUTED_VALUE"""),"Ticker") -> Ticker | W10: =IFERROR(__xludf.DUMMYFUNCTION("""COMPUTED_VALUE"""),"Vencimiento") -> Vencimiento | X10: =IFERROR(__xludf.DUMMYFUNCTION("""COMPUTED_VALUE"""),"Tasa") -> Tasa | Y10: =IFERROR(__xludf.DUMMYFUNCTION("""COMPUTED_VALUE"""),"Precio") -> Precio | Z10: =IFERROR(__xludf.DUMMYFUNCTION("""COMPUTED_VALUE"""),"TIR") -> TIR | AA10: =IFERROR(__xludf.DUMMYFUNCTION("""COMPUTED_VALUE"""),"Var. Diaria%") -> Var. Diaria% | AB10: =IFERROR(__xludf.DUMMYFUNCTION("""COMPUTED_VALUE"""),"Duration") -> Duration | AC10: =IFERROR(__xludf.DUMMYFUNCTION("""COMPUTED_VALUE"""),"Pago") -> Pago | AD10: =IFERROR(__xludf.DUMMYFUNCTION("""COMPUTED_VALUE"""),"Prox. Cupón (días)") -> Prox. Cupón (días) | AH10: =IFERROR(__xludf.DUMMYFUNCTION("""COMPUTED_VALUE"""),"Ticker") -> Ticker | AI10: =IFERROR(__xludf.DUMMYFUNCTION("""COMPUTED_VALUE"""),"Var. Diaria %") -> Var. Diaria % | AJ10: =IFERROR(__xludf.DUMMYFUNCTION("""COMPUTED_VALUE"""),"VTO") -> VTO | AK10: =IFERROR(__xludf.DUMMYFUNCTION("""COMPUTED_VALUE"""),"Precio") -> Precio | AL10: =IFERROR(__xludf.DUMMYFUNCTION("""COMPUTED_VALUE"""),"TIR") -> TIR | AM10: =IFERROR(__xludf.DUMMYFUNCTION("""COMPUTED_VALUE"""),"Spread X Ley") -> Spread X Ley | AN10: =IFERROR(__xludf.DUMMYFUNCTION("""COMPUTED_VALUE"""),"Current Yield") -> Current Yield | AO10: =IFERROR(__xludf.DUMMYFUNCTION("""COMPUTED_VALUE"""),"Duration") -> Duration | AP10: =IFERROR(__xludf.DUMMYFUNCTION("""COMPUTED_VALUE"""),"Pago") -> Pago | AQ10: =IFERROR(__xludf.DUMMYFUNCTION("""COMPUTED_VALUE"""),"Ley") -> Ley | AR10: =IFERROR(__xludf.DUMMYFUNCTION("""COMPUTED_VALUE"""),"Paridad") -> Paridad | AT10: =IFERROR(__xludf.DUMMYFUNCTION("""COMPUTED_VALUE"""),"Ticker") -> Ticker | AU10: =IFERROR(__xludf.DUMMYFUNCTION("""COMPUTED_VALUE"""),"Variación") -> Variación | AV10: =IFERROR(__xludf.DUMMYFUNCTION("""COMPUTED_VALUE"""),"VTO") -> VTO | AW10: =IFERROR(__xludf.DUMMYFUNCTION("""COMPUTED_VALUE"""),"Precio") -> Precio | AX10: =IFERROR(__xludf.DUMMYFUNCTION("""COMPUTED_VALUE"""),"TIR") -> TIR | AY10: =IFERROR(__xludf.DUMMYFUNCTION("""COMPUTED_VALUE"""),"Op de rescate") -> Op de rescate | AZ10: =IFERROR(__xludf.DUMMYFUNCTION("""COMPUTED_VALUE"""),"Current Yield") -> Current Yield | BA10: =IFERROR(__xludf.DUMMYFUNCTION("""COMPUTED_VALUE"""),"Duration") -> Duration | BB10: =IFERROR(__xludf.DUMMYFUNCTION("""COMPUTED_VALUE"""),"Pago") -> Pago | BC10: =IFERROR(__xludf.DUMMYFUNCTION("""COMPUTED_VALUE"""),"Prox Cupón (días)") -> Prox Cupón (días) | BD10: =IFERROR(__xludf.DUMMYFUNCTION("""COMPUTED_VALUE"""),"Ley") -> Ley
A11: Cer | B11: TX26 | C11: =VLOOKUP($B$11,$V$11:$AD$28,5,0) -> 0.3715077 | D11: =VLOOKUP($B$11,$V$11:$AD$28,7,0) -> 0.53330534 | F11: 0.5 | J11: =IFERROR(__xludf.DUMMYFUNCTION("""COMPUTED_VALUE"""),"T17O5") -> T17O5 | K11: =IFERROR(__xludf.DUMMYFUNCTION("""COMPUTED_VALUE"""),45947.0) -> 45947 | L11: =IFERROR(__xludf.DUMMYFUNCTION("""COMPUTED_VALUE"""),156.85) -> 156.85 | M11: =IFERROR(__xludf.DUMMYFUNCTION("""COMPUTED_VALUE"""),-3.0E-4) -> -0.0003 | N11: =IFERROR(__xludf.DUMMYFUNCTION("""COMPUTED_VALUE"""),0.049212628110962386) -> 0.049212628 | O11: =IFERROR(__xludf.DUMMYFUNCTION("""COMPUTED_VALUE"""),0.012893076100169987) -> 0.012893076 | P11: =IFERROR(__xludf.DUMMYFUNCTION("""COMPUTED_VALUE"""),0.5882465970702556) -> 0.5882466 | Q11: =IFERROR(__xludf.DUMMYFUNCTION("""COMPUTED_VALUE"""),0.7940698999295032) -> 0.7940699 | R11: =IFERROR(__xludf.DUMMYFUNCTION("""COMPUTED_VALUE"""),9.0) -> 9 | S11: =IFERROR(__xludf.DUMMYFUNCTION("""COMPUTED_VALUE"""),1547.6491484006044) -> 1547.6491 | T11: =IFERROR(__xludf.DUMMYFUNCTION("""COMPUTED_VALUE"""),9.0) -> 9 | V11: =IFERROR(__xludf.DUMMYFUNCTION("""COMPUTED_VALUE"""),"TZXO6") -> TZXO6 | W11: =IFERROR(__xludf.DUMMYFUNCTION("""COMPUTED_VALUE"""),46325.0) -> 46325 | X11: =IFERROR(__xludf.DUMMYFUNCTION("""COMPUTED_VALUE"""),"CER + 0%") -> CER + 0% | Y11: =IFERROR(__xludf.DUMMYFUNCTION("""COMPUTED_VALUE"""),101.0) -> 101 | Z11: =IFERROR(__xludf.DUMMYFUNCTION("""COMPUTED_VALUE"""),0.2841959468762413) -> 0.28419595 | AA11: =IFERROR(__xludf.DUMMYFUNCTION("""COMPUTED_VALUE"""),-0.0024) -> -0.0024 | AB11: =IFERROR(__xludf.DUMMYFUNCTION("""COMPUTED_VALUE"""),1.0682901648127028) -> 1.0682902 | AC11: =IFERROR(__xludf.DUMMYFUNCTION("""COMPUTED_VALUE"""),"No paga") -> No paga | AD11: =IFERROR(__xludf.DUMMYFUNCTION("""COMPUTED_VALUE"""),386.0) -> 386 | AH11: =IFERROR(__xludf.DUMMYFUNCTION("""COMPUTED_VALUE"""),"AL29D") -> AL29D | AI11: =IFERROR(__xludf.DUMMYFUNCTION("""COMPUTED_VALUE"""),0.021) -> 0.021 | AJ11: =IFERROR(__xludf.DUMMYFUNCTION("""COMPUTED_VALUE"""),47308.0) -> 47308 | AK11: =IFERROR(__xludf.DUMMYFUNCTION("""COMPUTED_VALUE"""),58.8) -> 58.8 | AL11: =IFERROR(__xludf.DUMMYFUNCTION("""COMPUTED_VALUE"""),0.19274955536228097) -> 0.19274956 | AM11: =IFERROR(__xludf.DUMMYFUNCTION("""COMPUTED_VALUE"""),"-") -> - | AN11: =IFERROR(__xludf.DUMMYFUNCTION("""COMPUTED_VALUE"""),0.016156462585034014) -> 0.016156463 | AO11: =IFERROR(__xludf.DUMMYFUNCTION("""COMPUTED_VALUE"""),1.772485729841569) -> 1.7724857 | AP11: =IFERROR(__xludf.DUMMYFUNCTION("""COMPUTED_VALUE"""),"Semestral") -> Semestral | AQ11: =IFERROR(__xludf.DUMMYFUNCTION("""COMPUTED_VALUE"""),"ARG") -> ARG | AR11: =IFERROR(__xludf.DUMMYFUNCTION("""COMPUTED_VALUE"""),0.7331264546159814) -> 0.73312645 | AT11: =IFERROR(__xludf.DUMMYFUNCTION("""COMPUTED_VALUE"""),"BPA7D") -> BPA7D | AU11: =IFERROR(__xludf.DUMMYFUNCTION("""COMPUTED_VALUE"""),-0.0285) -> -0.0285 | AV11: =IFERROR(__xludf.DUMMYFUNCTION("""COMPUTED_VALUE"""),46691.0) -> 46691 | AW11: =IFERROR(__xludf.DUMMYFUNCTION("""COMPUTED_VALUE"""),101.9) -> 101.9 | AX11: =IFERROR(__xludf.DUMMYFUNCTION("""COMPUTED_VALUE"""),0.05246435560071971) -> 0.052464356 | AY11: =IFERROR(__xludf.DUMMYFUNCTION("""COMPUTED_VALUE"""),45777.0) -> 45777 | AZ11: =IFERROR(__xludf.DUMMYFUNCTION("""COMPUTED_VALUE"""),0.05711481844946025) -> 0.057114818 | BA11: =IFERROR(__xludf.DUMMYFUNCTION("""COMPUTED_VALUE"""),1.7339419040655923) -> 1.7339419 | BB11: =IFERROR(__xludf.DUMMYFUNCTION("""COMPUTED_VALUE"""),"Semestral") -> Semestral | BC11: =IFERROR(__xludf.DUMMYFUNCTION("""COMPUTED_VALUE"""),23.0) -> 23 | BD11: =IFERROR(__xludf.DUMMYFUNCTION("""COMPUTED_VALUE"""),"ARG") -> ARG
D12: =SUM(D10:D11) -> 23.533305 | E12: =SUM(E10:E11) -> 0 | J12: =IFERROR(__xludf.DUMMYFUNCTION("""COMPUTED_VALUE"""),"S31O5") -> S31O5 | K12: =IFERROR(__xludf.DUMMYFUNCTION("""COMPUTED_VALUE"""),45961.0) -> 45961 | L12: =IFERROR(__xludf.DUMMYFUNCTION("""COMPUTED_VALUE"""),127.55) -> 127.55 | M12: =IFERROR(__xludf.DUMMYFUNCTION("""COMPUTED_VALUE"""),-0.005) -> -0.005 | N12: =IFERROR(__xludf.DUMMYFUNCTION("""COMPUTED_VALUE"""),0.05676114279184996) -> 0.056761143 | O12: =IFERROR(__xludf.DUMMYFUNCTION("""COMPUTED_VALUE"""),0.04131713053704433) -> 0.041317131 | P12: =IFERROR(__xludf.DUMMYFUNCTION("""COMPUTED_VALUE"""),0.6854887566373264) -> 0.68548876 | Q12: =IFERROR(__xludf.DUMMYFUNCTION("""COMPUTED_VALUE"""),0.9575739158045602) -> 0.95757392 | R12: =IFERROR(__xludf.DUMMYFUNCTION("""COMPUTED_VALUE"""),23.0) -> 23 | S12: =IFERROR(__xludf.DUMMYFUNCTION("""COMPUTED_VALUE"""),1591.079659163589) -> 1591.0797 | V12: =IFERROR(__xludf.DUMMYFUNCTION("""COMPUTED_VALUE"""),"TX26") -> TX26 | W12: =IFERROR(__xludf.DUMMYFUNCTION("""COMPUTED_VALUE"""),46335.0) -> 46335 | X12: =IFERROR(__xludf.DUMMYFUNCTION("""COMPUTED_VALUE"""),"CER + 2%") -> CER + 2% | Y12: =IFERROR(__xludf.DUMMYFUNCTION("""COMPUTED_VALUE"""),1440.0) -> 1440 | Z12: =IFERROR(__xludf.DUMMYFUNCTION("""COMPUTED_VALUE"""),0.37150769495312397) -> 0.3715077 | AA12: =IFERROR(__xludf.DUMMYFUNCTION("""COMPUTED_VALUE"""),-0.013600000000000001) -> -0.0136 | AB12: =IFERROR(__xludf.DUMMYFUNCTION("""COMPUTED_VALUE"""),0.5333053393151996) -> 0.53330534 | AC12: =IFERROR(__xludf.DUMMYFUNCTION("""COMPUTED_VALUE"""),"Semestral") -> Semestral | AD12: =IFERROR(__xludf.DUMMYFUNCTION("""COMPUTED_VALUE"""),32.0) -> 32 | AH12: =IFERROR(__xludf.DUMMYFUNCTION("""COMPUTED_VALUE"""),"AL30D") -> AL30D | AI12: =IFERROR(__xludf.DUMMYFUNCTION("""COMPUTED_VALUE"""),0.0058) -> 0.0058 | AJ12: =IFERROR(__xludf.DUMMYFUNCTION("""COMPUTED_VALUE"""),47673.0) -> 47673 | AK12: =IFERROR(__xludf.DUMMYFUNCTION("""COMPUTED_VALUE"""),55.1) -> 55.1 | AL12: =IFERROR(__xludf.DUMMYFUNCTION("""COMPUTED_VALUE"""),0.19046508064282572) -> 0.19046508 | AM12: =IFERROR(__xludf.DUMMYFUNCTION("""COMPUTED_VALUE"""),"-") -> - | AN12: =IFERROR(__xludf.DUMMYFUNCTION("""COMPUTED_VALUE"""),0.012522686025408347) -> 0.012522686 | AO12: =IFERROR(__xludf.DUMMYFUNCTION("""COMPUTED_VALUE"""),2.152767954241598) -> 2.152768 | AP12: =IFERROR(__xludf.DUMMYFUNCTION("""COMPUTED_VALUE"""),"Semestral") -> Semestral | AQ12: =IFERROR(__xludf.DUMMYFUNCTION("""COMPUTED_VALUE"""),"ARG") -> ARG | AR12: =IFERROR(__xludf.DUMMYFUNCTION("""COMPUTED_VALUE"""),0.687432421192714) -> 0.68743242 | AT12: =IFERROR(__xludf.DUMMYFUNCTION("""COMPUTED_VALUE"""),"BPB7D") -> BPB7D | AU12: =IFERROR(__xludf.DUMMYFUNCTION("""COMPUTED_VALUE"""),-5.0E-4) -> -0.0005 | AV12: =IFERROR(__xludf.DUMMYFUNCTION("""COMPUTED_VALUE"""),46691.0) -> 46691 | AW12: =IFERROR(__xludf.DUMMYFUNCTION("""COMPUTED_VALUE"""),97.2) -> 97.2 | AX12: =IFERROR(__xludf.DUMMYFUNCTION("""COMPUTED_VALUE"""),0.08193357534384128) -> 0.081933575 | AY12: =IFERROR(__xludf.DUMMYFUNCTION("""COMPUTED_VALUE"""),46142.0) -> 46142 | AZ12: =IFERROR(__xludf.DUMMYFUNCTION("""COMPUTED_VALUE"""),0.059876543209876544) -> 0.059876543 | BA12: =IFERROR(__xludf.DUMMYFUNCTION("""COMPUTED_VALUE"""),1.7277992393140498) -> 1.7277992 | BB12: =IFERROR(__xludf.DUMMYFUNCTION("""COMPUTED_VALUE"""),"Semestral") -> Semestral | BC12: =IFERROR(__xludf.DUMMYFUNCTION("""COMPUTED_VALUE"""),23.0) -> 23 | BD12: =IFERROR(__xludf.DUMMYFUNCTION("""COMPUTED_VALUE"""),"ARG") -> ARG
B13: Moderado | C13: TIR | D13: M,D | E13: Inverse duration | F13: Weight | J13: =IFERROR(__xludf.DUMMYFUNCTION("""COMPUTED_VALUE"""),"S10N5") -> S10N5 | K13: =IFERROR(__xludf.DUMMYFUNCTION("""COMPUTED_VALUE"""),45971.0) -> 45971 | L13: =IFERROR(__xludf.DUMMYFUNCTION("""COMPUTED_VALUE"""),115.95) -> 115.95 | M13: =IFERROR(__xludf.DUMMYFUNCTION("""COMPUTED_VALUE"""),-0.0017000000000000001) -> -0.0017 | N13: =IFERROR(__xludf.DUMMYFUNCTION("""COMPUTED_VALUE"""),0.053031850656973356) -> 0.053031851 | O13: =IFERROR(__xludf.DUMMYFUNCTION("""COMPUTED_VALUE"""),0.0566656942093029) -> 0.056665694 | P13: =IFERROR(__xludf.DUMMYFUNCTION("""COMPUTED_VALUE"""),0.6463430745748612) -> 0.64634307 | Q13: =IFERROR(__xludf.DUMMYFUNCTION("""COMPUTED_VALUE"""),0.875160038202293) -> 0.87516004 | R13: =IFERROR(__xludf.DUMMYFUNCTION("""COMPUTED_VALUE"""),33.0) -> 33 | S13: =IFERROR(__xludf.DUMMYFUNCTION("""COMPUTED_VALUE"""),1614.531484491492) -> 1614.5315 | T13: =IFERROR(__xludf.DUMMYFUNCTION("""COMPUTED_VALUE"""),33.0) -> 33 | V13: =IFERROR(__xludf.DUMMYFUNCTION("""COMPUTED_VALUE"""),"TZXO5") -> TZXO5 | W13: =IFERROR(__xludf.DUMMYFUNCTION("""COMPUTED_VALUE"""),45961.0) -> 45961 | X13: =IFERROR(__xludf.DUMMYFUNCTION("""COMPUTED_VALUE"""),"CER + 0%") -> CER + 0% | Y13: =IFERROR(__xludf.DUMMYFUNCTION("""COMPUTED_VALUE"""),128.05) -> 128.05 | Z13: =IFERROR(__xludf.DUMMYFUNCTION("""COMPUTED_VALUE"""),0.5709272368696042) -> 0.57092724 | AA13: =IFERROR(__xludf.DUMMYFUNCTION("""COMPUTED_VALUE"""),-0.0019) -> -0.0019 | AB13: =IFERROR(__xludf.DUMMYFUNCTION("""COMPUTED_VALUE"""),0.06108800893781527) -> 0.061088009 | AC13: =IFERROR(__xludf.DUMMYFUNCTION("""COMPUTED_VALUE"""),"No Paga") -> No Paga | AD13: =IFERROR(__xludf.DUMMYFUNCTION("""COMPUTED_VALUE"""),23.0) -> 23 | AH13: =IFERROR(__xludf.DUMMYFUNCTION("""COMPUTED_VALUE"""),"AE38D") -> AE38D | AI13: =IFERROR(__xludf.DUMMYFUNCTION("""COMPUTED_VALUE"""),0.0036) -> 0.0036 | AJ13: =IFERROR(__xludf.DUMMYFUNCTION("""COMPUTED_VALUE"""),50414.0) -> 50414 | AK13: =IFERROR(__xludf.DUMMYFUNCTION("""COMPUTED_VALUE"""),55.7) -> 55.7 | AL13: =IFERROR(__xludf.DUMMYFUNCTION("""COMPUTED_VALUE"""),0.17988135687852902) -> 0.17988136 | AM13: =IFERROR(__xludf.DUMMYFUNCTION("""COMPUTED_VALUE"""),"-") -> - | AN13: =IFERROR(__xludf.DUMMYFUNCTION("""COMPUTED_VALUE"""),0.08976660682226212) -> 0.089766607 | AO13: =IFERROR(__xludf.DUMMYFUNCTION("""COMPUTED_VALUE"""),4.580029465805991) -> 4.5800295 | AP13: =IFERROR(__xludf.DUMMYFUNCTION("""COMPUTED_VALUE"""),"Semestral") -> Semestral | AQ13: =IFERROR(__xludf.DUMMYFUNCTION("""COMPUTED_VALUE"""),"ARG") -> ARG | AR13: =IFERROR(__xludf.DUMMYFUNCTION("""COMPUTED_VALUE"""),0.5499725726823917) -> 0.54997257 | AT13: =IFERROR(__xludf.DUMMYFUNCTION("""COMPUTED_VALUE"""),"BPC7D") -> BPC7D | AU13: =IFERROR(__xludf.DUMMYFUNCTION("""COMPUTED_VALUE"""),0.0123) -> 0.0123 | AV13: =IFERROR(__xludf.DUMMYFUNCTION("""COMPUTED_VALUE"""),46691.0) -> 46691 | AW13: =IFERROR(__xludf.DUMMYFUNCTION("""COMPUTED_VALUE"""),90.5) -> 90.5 | AX13: =IFERROR(__xludf.DUMMYFUNCTION("""COMPUTED_VALUE"""),0.12825279003414802) -> 0.12825279 | AY13: =IFERROR(__xludf.DUMMYFUNCTION("""COMPUTED_VALUE"""),46507.0) -> 46507 | AZ13: =IFERROR(__xludf.DUMMYFUNCTION("""COMPUTED_VALUE"""),0.06430939226519337) -> 0.064309392 | BA13: =IFERROR(__xludf.DUMMYFUNCTION("""COMPUTED_VALUE"""),1.7182874975201892) -> 1.7182875 | BB13: =IFERROR(__xludf.DUMMYFUNCTION("""COMPUTED_VALUE"""),"Semestral") -> Semestral | BC13: =IFERROR(__xludf.DUMMYFUNCTION("""COMPUTED_VALUE"""),23.0) -> 23 | BD13: =IFERROR(__xludf.DUMMYFUNCTION("""COMPUTED_VALUE"""),"ARG") -> ARG
A14: Lecap | B14: S10N5 | C14: =VLOOKUP(B14,$J$11:$R$63,7,0) -> 0.64634307 | D14: =VLOOKUP(B14,$J$11:$R$63,9,0) -> 33 | F14: 0.5 | J14: =IFERROR(__xludf.DUMMYFUNCTION("""COMPUTED_VALUE"""),"S28N5") -> S28N5 | K14: =IFERROR(__xludf.DUMMYFUNCTION("""COMPUTED_VALUE"""),45989.0) -> 45989 | L14: =IFERROR(__xludf.DUMMYFUNCTION("""COMPUTED_VALUE"""),113.25) -> 113.25 | M14: =IFERROR(__xludf.DUMMYFUNCTION("""COMPUTED_VALUE"""),-0.01) -> -0.01 | N14: =IFERROR(__xludf.DUMMYFUNCTION("""COMPUTED_VALUE"""),0.053673242852413594) -> 0.053673243 | O14: =IFERROR(__xludf.DUMMYFUNCTION("""COMPUTED_VALUE"""),0.09104648063503151) -> 0.091046481 | P14: =IFERROR(__xludf.DUMMYFUNCTION("""COMPUTED_VALUE"""),0.6646393086357301) -> 0.66463931 | Q14: =IFERROR(__xludf.DUMMYFUNCTION("""COMPUTED_VALUE"""),0.8891034668892233) -> 0.88910347 | R14: =IFERROR(__xludf.DUMMYFUNCTION("""COMPUTED_VALUE"""),51.0) -> 51 | S14: =IFERROR(__xludf.DUMMYFUNCTION("""COMPUTED_VALUE"""),1667.0635790320018) -> 1667.0636 | T14: =IFERROR(__xludf.DUMMYFUNCTION("""COMPUTED_VALUE"""),51.0) -> 51 | V14: =IFERROR(__xludf.DUMMYFUNCTION("""COMPUTED_VALUE"""),"TX25") -> TX25 | W14: =IFERROR(__xludf.DUMMYFUNCTION("""COMPUTED_VALUE"""),45970.0) -> 45970 | X14: =IFERROR(__xludf.DUMMYFUNCTION("""COMPUTED_VALUE"""),"CER + 1,8%") -> CER + 1,8% | Y14: =IFERROR(__xludf.DUMMYFUNCTION("""COMPUTED_VALUE"""),1328.0) -> 1328 | Z14: =IFERROR(__xludf.DUMMYFUNCTION("""COMPUTED_VALUE"""),0.5656937845311887) -> 0.56569378 | AA14: =IFERROR(__xludf.DUMMYFUNCTION("""COMPUTED_VALUE"""),-0.0015) -> -0.0015 | AB14: =IFERROR(__xludf.DUMMYFUNCTION("""COMPUTED_VALUE"""),0.08606558321706692) -> 0.086065583 | AC14: =IFERROR(__xludf.DUMMYFUNCTION("""COMPUTED_VALUE"""),"Semestral") -> Semestral | AD14: =IFERROR(__xludf.DUMMYFUNCTION("""COMPUTED_VALUE"""),32.0) -> 32 | AH14: =IFERROR(__xludf.DUMMYFUNCTION("""COMPUTED_VALUE"""),"AL35D") -> AL35D | AI14: =IFERROR(__xludf.DUMMYFUNCTION("""COMPUTED_VALUE"""),-0.0019) -> -0.0019 | AJ14: =IFERROR(__xludf.DUMMYFUNCTION("""COMPUTED_VALUE"""),49499.0) -> 49499 | AK14: =IFERROR(__xludf.DUMMYFUNCTION("""COMPUTED_VALUE"""),55.37) -> 55.37 | AL14: =IFERROR(__xludf.DUMMYFUNCTION("""COMPUTED_VALUE"""),0.1573915117399444) -> 0.15739151 | AM14: =IFERROR(__xludf.DUMMYFUNCTION("""COMPUTED_VALUE"""),"-") -> - | AN14: =IFERROR(__xludf.DUMMYFUNCTION("""COMPUTED_VALUE"""),0.0744085244717356) -> 0.074408524 | AO14: =IFERROR(__xludf.DUMMYFUNCTION("""COMPUTED_VALUE"""),5.726816609168342) -> 5.7268166 | AP14: =IFERROR(__xludf.DUMMYFUNCTION("""COMPUTED_VALUE"""),"Semestral") -> Semestral | AQ14: =IFERROR(__xludf.DUMMYFUNCTION("""COMPUTED_VALUE"""),"ARG") -> ARG | AR14: =IFERROR(__xludf.DUMMYFUNCTION("""COMPUTED_VALUE"""),0.5479170400407257) -> 0.54791704 | AT14: =IFERROR(__xludf.DUMMYFUNCTION("""COMPUTED_VALUE"""),"BPD7D") -> BPD7D | AU14: =IFERROR(__xludf.DUMMYFUNCTION("""COMPUTED_VALUE"""),0.003) -> 0.003 | AV14: =IFERROR(__xludf.DUMMYFUNCTION("""COMPUTED_VALUE"""),46691.0) -> 46691 | AW14: =IFERROR(__xludf.DUMMYFUNCTION("""COMPUTED_VALUE"""),89.0) -> 89 | AX14: =IFERROR(__xludf.DUMMYFUNCTION("""COMPUTED_VALUE"""),0.13940657447047933) -> 0.13940657 | AY14: =IFERROR(__xludf.DUMMYFUNCTION("""COMPUTED_VALUE"""),"No") -> No | AZ14: =IFERROR(__xludf.DUMMYFUNCTION("""COMPUTED_VALUE"""),0.06539325842696629) -> 0.065393258 | BA14: =IFERROR(__xludf.DUMMYFUNCTION("""COMPUTED_VALUE"""),1.7160217808653322) -> 1.7160218 | BB14: =IFERROR(__xludf.DUMMYFUNCTION("""COMPUTED_VALUE"""),"Semestral") -> Semestral | BC14: =IFERROR(__xludf.DUMMYFUNCTION("""COMPUTED_VALUE"""),23.0) -> 23 | BD14: =IFERROR(__xludf.DUMMYFUNCTION("""COMPUTED_VALUE"""),"ARG") -> ARG
A15: Boncap | J15: =IFERROR(__xludf.DUMMYFUNCTION("""COMPUTED_VALUE"""),"T15D5") -> T15D5 | K15: =IFERROR(__xludf.DUMMYFUNCTION("""COMPUTED_VALUE"""),46006.0) -> 46006 | L15: =IFERROR(__xludf.DUMMYFUNCTION("""COMPUTED_VALUE"""),153.0) -> 153 | M15: =IFERROR(__xludf.DUMMYFUNCTION("""COMPUTED_VALUE"""),-0.009000000000000001) -> -0.009 | N15: =IFERROR(__xludf.DUMMYFUNCTION("""COMPUTED_VALUE"""),0.05061800586338472) -> 0.050618006 | O15: =IFERROR(__xludf.DUMMYFUNCTION("""COMPUTED_VALUE"""),0.11658933435350138) -> 0.11658933 | P15: =IFERROR(__xludf.DUMMYFUNCTION("""COMPUTED_VALUE"""),0.6351508513287761) -> 0.63515085 | Q15: =IFERROR(__xludf.DUMMYFUNCTION("""COMPUTED_VALUE"""),0.8235270728614773) -> 0.82352707 | R15: =IFERROR(__xludf.DUMMYFUNCTION("""COMPUTED_VALUE"""),68.0) -> 68 | S15: =IFERROR(__xludf.DUMMYFUNCTION("""COMPUTED_VALUE"""),1706.0917615103679) -> 1706.0918 | T15: =IFERROR(__xludf.DUMMYFUNCTION("""COMPUTED_VALUE"""),68.0) -> 68 | V15: =IFERROR(__xludf.DUMMYFUNCTION("""COMPUTED_VALUE"""),"TZXD5") -> TZXD5 | W15: =IFERROR(__xludf.DUMMYFUNCTION("""COMPUTED_VALUE"""),46006.0) -> 46006 | X15: =IFERROR(__xludf.DUMMYFUNCTION("""COMPUTED_VALUE"""),"CER + 0%") -> CER + 0% | Y15: =IFERROR(__xludf.DUMMYFUNCTION("""COMPUTED_VALUE"""),216.7) -> 216.7 | Z15: =IFERROR(__xludf.DUMMYFUNCTION("""COMPUTED_VALUE"""),0.48777642147192035) -> 0.48777642 | AA15: =IFERROR(__xludf.DUMMYFUNCTION("""COMPUTED_VALUE"""),-0.0132) -> -0.0132 | AB15: =IFERROR(__xludf.DUMMYFUNCTION("""COMPUTED_VALUE"""),0.18592270219788073) -> 0.1859227 | AC15: =IFERROR(__xludf.DUMMYFUNCTION("""COMPUTED_VALUE"""),"No paga ") -> No paga | AD15: =IFERROR(__xludf.DUMMYFUNCTION("""COMPUTED_VALUE"""),68.0) -> 68 | AH15: =IFERROR(__xludf.DUMMYFUNCTION("""COMPUTED_VALUE"""),"AL41D") -> AL41D | AI15: =IFERROR(__xludf.DUMMYFUNCTION("""COMPUTED_VALUE"""),0.0134) -> 0.0134 | AJ15: =IFERROR(__xludf.DUMMYFUNCTION("""COMPUTED_VALUE"""),51691.0) -> 51691 | AK15: =IFERROR(__xludf.DUMMYFUNCTION("""COMPUTED_VALUE"""),53.5) -> 53.5 | AL15: =IFERROR(__xludf.DUMMYFUNCTION("""COMPUTED_VALUE"""),0.14717033969427737) -> 0.14717034 | AM15: =IFERROR(__xludf.DUMMYFUNCTION("""COMPUTED_VALUE"""),"-") -> - | AN15: =IFERROR(__xludf.DUMMYFUNCTION("""COMPUTED_VALUE"""),0.06542056074766354) -> 0.065420561 | AO15: =IFERROR(__xludf.DUMMYFUNCTION("""COMPUTED_VALUE"""),5.907388513949509) -> 5.9073885 | AP15: =IFERROR(__xludf.DUMMYFUNCTION("""COMPUTED_VALUE"""),"Semestral") -> Semestral | AQ15: =IFERROR(__xludf.DUMMYFUNCTION("""COMPUTED_VALUE"""),"ARG") -> ARG | AR15: =IFERROR(__xludf.DUMMYFUNCTION("""COMPUTED_VALUE"""),0.5302571444303728) -> 0.53025714 | AT15: =IFERROR(__xludf.DUMMYFUNCTION("""COMPUTED_VALUE"""),"BPY6D") -> BPY6D | AU15: =IFERROR(__xludf.DUMMYFUNCTION("""COMPUTED_VALUE"""),0.0045000000000000005) -> 0.0045 | AV15: =IFERROR(__xludf.DUMMYFUNCTION("""COMPUTED_VALUE"""),46173.0) -> 46173 | AW15: =IFERROR(__xludf.DUMMYFUNCTION("""COMPUTED_VALUE"""),100.2) -> 100.2 | AX15: =IFERROR(__xludf.DUMMYFUNCTION("""COMPUTED_VALUE"""),0.03373977749126163) -> 0.033739777 | AY15: =IFERROR(__xludf.DUMMYFUNCTION("""COMPUTED_VALUE"""),"No") -> No | AZ15: =IFERROR(__xludf.DUMMYFUNCTION("""COMPUTED_VALUE"""),0.021956087824351298) -> 0.021956088 | BA15: =IFERROR(__xludf.DUMMYFUNCTION("""COMPUTED_VALUE"""),0.3960835650534009) -> 0.39608357 | BB15: =IFERROR(__xludf.DUMMYFUNCTION("""COMPUTED_VALUE"""),"Trimestral") -> Trimestral | BC15: =IFERROR(__xludf.DUMMYFUNCTION("""COMPUTED_VALUE"""),53.0) -> 53 | BD15: =IFERROR(__xludf.DUMMYFUNCTION("""COMPUTED_VALUE"""),"ARG") -> ARG
A16: Cer | B16: TZXD7 | C16: =VLOOKUP(B16,$V$11:$AD$28,5,0) -> 0.21174008 | D16: =VLOOKUP(B16,$V$11:$AD$28,7,0) -> 2.2010314 | F16: 0.5 | J16: =IFERROR(__xludf.DUMMYFUNCTION("""COMPUTED_VALUE"""),"T30E6") -> T30E6 | K16: =IFERROR(__xludf.DUMMYFUNCTION("""COMPUTED_VALUE"""),46052.0) -> 46052 | L16: =IFERROR(__xludf.DUMMYFUNCTION("""COMPUTED_VALUE"""),118.9) -> 118.9 | M16: =IFERROR(__xludf.DUMMYFUNCTION("""COMPUTED_VALUE"""),-0.012) -> -0.012 | N16: =IFERROR(__xludf.DUMMYFUNCTION("""COMPUTED_VALUE"""),0.04869932418647127) -> 0.048699324 | O16: =IFERROR(__xludf.DUMMYFUNCTION("""COMPUTED_VALUE"""),0.19614929497563938) -> 0.1961493 | P16: =IFERROR(__xludf.DUMMYFUNCTION("""COMPUTED_VALUE"""),0.6335795811160033) -> 0.63357958 | Q16: =IFERROR(__xludf.DUMMYFUNCTION("""COMPUTED_VALUE"""),0.7834202309888926) -> 0.78342023 | R16: =IFERROR(__xludf.DUMMYFUNCTION("""COMPUTED_VALUE"""),114.0) -> 114 | S16: =IFERROR(__xludf.DUMMYFUNCTION("""COMPUTED_VALUE"""),1827.6553383665894) -> 1827.6553 | T16: =IFERROR(__xludf.DUMMYFUNCTION("""COMPUTED_VALUE"""),114.0) -> 114 | V16: =IFERROR(__xludf.DUMMYFUNCTION("""COMPUTED_VALUE"""),"TZXM6") -> TZXM6 | W16: =IFERROR(__xludf.DUMMYFUNCTION("""COMPUTED_VALUE"""),46112.0) -> 46112 | X16: =IFERROR(__xludf.DUMMYFUNCTION("""COMPUTED_VALUE"""),"CER + 0%") -> CER + 0% | Y16: =IFERROR(__xludf.DUMMYFUNCTION("""COMPUTED_VALUE"""),162.1) -> 162.1 | Z16: =IFERROR(__xludf.DUMMYFUNCTION("""COMPUTED_VALUE"""),0.3589054196484936) -> 0.35890542 | AA16: =IFERROR(__xludf.DUMMYFUNCTION("""COMPUTED_VALUE"""),-0.0097) -> -0.0097 | AB16: =IFERROR(__xludf.DUMMYFUNCTION("""COMPUTED_VALUE"""),0.4795863613068127) -> 0.47958636 | AC16: =IFERROR(__xludf.DUMMYFUNCTION("""COMPUTED_VALUE"""),"No paga ") -> No paga | AD16: =IFERROR(__xludf.DUMMYFUNCTION("""COMPUTED_VALUE"""),174.0) -> 174 | AH16: =IFERROR(__xludf.DUMMYFUNCTION("""COMPUTED_VALUE"""),"GD29D") -> GD29D | AI16: =IFERROR(__xludf.DUMMYFUNCTION("""COMPUTED_VALUE"""),0.022099999999999998) -> 0.0221 | AJ16: =IFERROR(__xludf.DUMMYFUNCTION("""COMPUTED_VALUE"""),47308.0) -> 47308 | AK16: =IFERROR(__xludf.DUMMYFUNCTION("""COMPUTED_VALUE"""),61.5) -> 61.5 | AL16: =IFERROR(__xludf.DUMMYFUNCTION("""COMPUTED_VALUE"""),0.16296055455136033) -> 0.16296055 | AM16: =IFERROR(__xludf.DUMMYFUNCTION("""COMPUTED_VALUE"""),0.04591836734693877) -> 0.045918367 | AN16: =IFERROR(__xludf.DUMMYFUNCTION("""COMPUTED_VALUE"""),0.015447154471544714) -> 0.015447154 | AO16: =IFERROR(__xludf.DUMMYFUNCTION("""COMPUTED_VALUE"""),1.8066477675550248) -> 1.8066478 | AP16: =IFERROR(__xludf.DUMMYFUNCTION("""COMPUTED_VALUE"""),"Semestral") -> Semestral | AQ16: =IFERROR(__xludf.DUMMYFUNCTION("""COMPUTED_VALUE"""),"NY") -> NY | AR16: =IFERROR(__xludf.DUMMYFUNCTION("""COMPUTED_VALUE"""),0.7667904244707968) -> 0.76679042 | AT16: =IFERROR(__xludf.DUMMYFUNCTION("""COMPUTED_VALUE"""),"BPO8D") -> BPO8D | AU16: =IFERROR(__xludf.DUMMYFUNCTION("""COMPUTED_VALUE"""),"#N/A") -> #N/A | AV16: =IFERROR(__xludf.DUMMYFUNCTION("""COMPUTED_VALUE"""),47057.0) -> 47057 | AW16: =IFERROR(__xludf.DUMMYFUNCTION("""COMPUTED_VALUE"""),"#N/A") -> #N/A | AX16: =IFERROR(__xludf.DUMMYFUNCTION("""COMPUTED_VALUE"""),"#N/A") -> #N/A | AY16: =IFERROR(__xludf.DUMMYFUNCTION("""COMPUTED_VALUE"""),46873.0) -> 46873 | AZ16: =IFERROR(__xludf.DUMMYFUNCTION("""COMPUTED_VALUE"""),"#N/A") -> #N/A | BA16: =IFERROR(__xludf.DUMMYFUNCTION("""COMPUTED_VALUE"""),"#N/A") -> #N/A | BB16: =IFERROR(__xludf.DUMMYFUNCTION("""COMPUTED_VALUE"""),"Semestral") -> Semestral | BC16: =IFERROR(__xludf.DUMMYFUNCTION("""COMPUTED_VALUE"""),23.0) -> 23 | BD16: =IFERROR(__xludf.DUMMYFUNCTION("""COMPUTED_VALUE"""),"ARG") -> ARG
A17: Duales | J17: =IFERROR(__xludf.DUMMYFUNCTION("""COMPUTED_VALUE"""),"T13F6") -> T13F6 | K17: =IFERROR(__xludf.DUMMYFUNCTION("""COMPUTED_VALUE"""),46066.0) -> 46066 | L17: =IFERROR(__xludf.DUMMYFUNCTION("""COMPUTED_VALUE"""),118.5) -> 118.5 | M17: =IFERROR(__xludf.DUMMYFUNCTION("""COMPUTED_VALUE"""),-0.0079) -> -0.0079 | N17: =IFERROR(__xludf.DUMMYFUNCTION("""COMPUTED_VALUE"""),0.04877021996082309) -> 0.04877022 | O17: =IFERROR(__xludf.DUMMYFUNCTION("""COMPUTED_VALUE"""),0.22333894637954632) -> 0.22333895 | P17: =IFERROR(__xludf.DUMMYFUNCTION("""COMPUTED_VALUE"""),0.6418796490435781) -> 0.64187965 | Q17: =IFERROR(__xludf.DUMMYFUNCTION("""COMPUTED_VALUE"""),0.7848876650430072) -> 0.78488766 | R17: =IFERROR(__xludf.DUMMYFUNCTION("""COMPUTED_VALUE"""),128.0) -> 128 | S17: =IFERROR(__xludf.DUMMYFUNCTION("""COMPUTED_VALUE"""),1869.1997440234845) -> 1869.1997 | T17: =IFERROR(__xludf.DUMMYFUNCTION("""COMPUTED_VALUE"""),128.0) -> 128 | V17: =IFERROR(__xludf.DUMMYFUNCTION("""COMPUTED_VALUE"""),"TZX26") -> TZX26 | W17: =IFERROR(__xludf.DUMMYFUNCTION("""COMPUTED_VALUE"""),46203.0) -> 46203 | X17: =IFERROR(__xludf.DUMMYFUNCTION("""COMPUTED_VALUE"""),"CER + 0%") -> CER + 0% | Y17: =IFERROR(__xludf.DUMMYFUNCTION("""COMPUTED_VALUE"""),257.0) -> 257 | Z17: =IFERROR(__xludf.DUMMYFUNCTION("""COMPUTED_VALUE"""),0.32657520687025915) -> 0.32657521 | AA17: =IFERROR(__xludf.DUMMYFUNCTION("""COMPUTED_VALUE"""),-0.0077) -> -0.0077 | AB17: =IFERROR(__xludf.DUMMYFUNCTION("""COMPUTED_VALUE"""),0.7312544183053639) -> 0.73125442 | AC17: =IFERROR(__xludf.DUMMYFUNCTION("""COMPUTED_VALUE"""),"No paga") -> No paga | AD17: =IFERROR(__xludf.DUMMYFUNCTION("""COMPUTED_VALUE"""),265.0) -> 265 | AH17: =IFERROR(__xludf.DUMMYFUNCTION("""COMPUTED_VALUE"""),"GD30D") -> GD30D | AI17: =IFERROR(__xludf.DUMMYFUNCTION("""COMPUTED_VALUE"""),0.0078000000000000005) -> 0.0078 | AJ17: =IFERROR(__xludf.DUMMYFUNCTION("""COMPUTED_VALUE"""),47673.0) -> 47673 | AK17: =IFERROR(__xludf.DUMMYFUNCTION("""COMPUTED_VALUE"""),58.0) -> 58 | AL17: =IFERROR(__xludf.DUMMYFUNCTION("""COMPUTED_VALUE"""),0.16256102392911143) -> 0.16256102 | AM17: =IFERROR(__xludf.DUMMYFUNCTION("""COMPUTED_VALUE"""),0.05263157894736836) -> 0.052631579 | AN17: =IFERROR(__xludf.DUMMYFUNCTION("""COMPUTED_VALUE"""),0.01189655172413793) -> 0.011896552 | AO17: =IFERROR(__xludf.DUMMYFUNCTION("""COMPUTED_VALUE"""),2.202189891594076) -> 2.2021899 | AP17: =IFERROR(__xludf.DUMMYFUNCTION("""COMPUTED_VALUE"""),"Semestral") -> Semestral | AQ17: =IFERROR(__xludf.DUMMYFUNCTION("""COMPUTED_VALUE"""),"NY") -> NY | AR17: =IFERROR(__xludf.DUMMYFUNCTION("""COMPUTED_VALUE"""),0.7236130749396988) -> 0.72361307
E18: =SUM(E14:E17) -> 0 | J18: =IFERROR(__xludf.DUMMYFUNCTION("""COMPUTED_VALUE"""),"T30J6") -> T30J6 | K18: =IFERROR(__xludf.DUMMYFUNCTION("""COMPUTED_VALUE"""),46203.0) -> 46203 | L18: =IFERROR(__xludf.DUMMYFUNCTION("""COMPUTED_VALUE"""),101.6) -> 101.6 | M18: =IFERROR(__xludf.DUMMYFUNCTION("""COMPUTED_VALUE"""),-9.0E-4) -> -0.0009 | N18: =IFERROR(__xludf.DUMMYFUNCTION("""COMPUTED_VALUE"""),0.04116221073372195) -> 0.041162211 | O18: =IFERROR(__xludf.DUMMYFUNCTION("""COMPUTED_VALUE"""),0.4261391185356187) -> 0.42613912 | P18: =IFERROR(__xludf.DUMMYFUNCTION("""COMPUTED_VALUE"""),0.5891696146420486) -> 0.58916961 | Q18: =IFERROR(__xludf.DUMMYFUNCTION("""COMPUTED_VALUE"""),0.6335803301328389) -> 0.63358033 | R18: =IFERROR(__xludf.DUMMYFUNCTION("""COMPUTED_VALUE"""),265.0) -> 265 | S18: =IFERROR(__xludf.DUMMYFUNCTION("""COMPUTED_VALUE"""),2179.06810144308) -> 2179.0681 | T18: =IFERROR(__xludf.DUMMYFUNCTION("""COMPUTED_VALUE"""),265.0) -> 265 | V18: =IFERROR(__xludf.DUMMYFUNCTION("""COMPUTED_VALUE"""),"TX28") -> TX28 | W18: =IFERROR(__xludf.DUMMYFUNCTION("""COMPUTED_VALUE"""),47066.0) -> 47066 | X18: =IFERROR(__xludf.DUMMYFUNCTION("""COMPUTED_VALUE"""),"CER + 2,25%") -> CER + 2,25% | Y18: =IFERROR(__xludf.DUMMYFUNCTION("""COMPUTED_VALUE"""),1470.5) -> 1470.5 | Z18: =IFERROR(__xludf.DUMMYFUNCTION("""COMPUTED_VALUE"""),0.2580037133450019) -> 0.25800371 | AA18: =IFERROR(__xludf.DUMMYFUNCTION("""COMPUTED_VALUE"""),-0.0219) -> -0.0219 | AB18: =IFERROR(__xludf.DUMMYFUNCTION("""COMPUTED_VALUE"""),1.345510473399339) -> 1.3455105 | AC18: =IFERROR(__xludf.DUMMYFUNCTION("""COMPUTED_VALUE"""),"Semestral") -> Semestral | AD18: =IFERROR(__xludf.DUMMYFUNCTION("""COMPUTED_VALUE"""),32.0) -> 32 | AH18: =IFERROR(__xludf.DUMMYFUNCTION("""COMPUTED_VALUE"""),"GD46D") -> GD46D | AI18: =IFERROR(__xludf.DUMMYFUNCTION("""COMPUTED_VALUE"""),-0.0246) -> -0.0246 | AJ18: =IFERROR(__xludf.DUMMYFUNCTION("""COMPUTED_VALUE"""),53517.0) -> 53517 | AK18: =IFERROR(__xludf.DUMMYFUNCTION("""COMPUTED_VALUE"""),53.5) -> 53.5 | AL18: =IFERROR(__xludf.DUMMYFUNCTION("""COMPUTED_VALUE"""),0.15278818379835055) -> 0.15278818 | AM18: =IFERROR(__xludf.DUMMYFUNCTION("""COMPUTED_VALUE"""),"-") -> - | AN18: =IFERROR(__xludf.DUMMYFUNCTION("""COMPUTED_VALUE"""),0.07626168224299065) -> 0.076261682 | AO18: =IFERROR(__xludf.DUMMYFUNCTION("""COMPUTED_VALUE"""),5.106763566910554) -> 5.1067636 | AP18: =IFERROR(__xludf.DUMMYFUNCTION("""COMPUTED_VALUE"""),"Semestral") -> Semestral | AQ18: =IFERROR(__xludf.DUMMYFUNCTION("""COMPUTED_VALUE"""),"NY") -> NY
J19: =IFERROR(__xludf.DUMMYFUNCTION("""COMPUTED_VALUE"""),"T15E7") -> T15E7 | K19: =IFERROR(__xludf.DUMMYFUNCTION("""COMPUTED_VALUE"""),46402.0) -> 46402 | L19: =IFERROR(__xludf.DUMMYFUNCTION("""COMPUTED_VALUE"""),89.0) -> 89 | M19: =IFERROR(__xludf.DUMMYFUNCTION("""COMPUTED_VALUE"""),5.0E-4) -> 0.0005 | N19: =IFERROR(__xludf.DUMMYFUNCTION("""COMPUTED_VALUE"""),0.039198812664563265) -> 0.039198813 | O19: =IFERROR(__xludf.DUMMYFUNCTION("""COMPUTED_VALUE"""),0.8101547575804664) -> 0.81015476 | P19: =IFERROR(__xludf.DUMMYFUNCTION("""COMPUTED_VALUE"""),0.6386749168830891) -> 0.63867492 | Q19: =IFERROR(__xludf.DUMMYFUNCTION("""COMPUTED_VALUE"""),0.5964922304557778) -> 0.59649223 | R19: =IFERROR(__xludf.DUMMYFUNCTION("""COMPUTED_VALUE"""),464.0) -> 464 | S19: =IFERROR(__xludf.DUMMYFUNCTION("""COMPUTED_VALUE"""),2765.824483497268) -> 2765.8245 | T19: =IFERROR(__xludf.DUMMYFUNCTION("""COMPUTED_VALUE"""),464.0) -> 464 | V19: =IFERROR(__xludf.DUMMYFUNCTION("""COMPUTED_VALUE"""),"TZXD6") -> TZXD6 | W19: =IFERROR(__xludf.DUMMYFUNCTION("""COMPUTED_VALUE"""),46371.0) -> 46371 | X19: =IFERROR(__xludf.DUMMYFUNCTION("""COMPUTED_VALUE"""),"CER + 0%") -> CER + 0% | Y19: =IFERROR(__xludf.DUMMYFUNCTION("""COMPUTED_VALUE"""),175.25) -> 175.25 | Z19: =IFERROR(__xludf.DUMMYFUNCTION("""COMPUTED_VALUE"""),0.27250801147045145) -> 0.27250801 | AA19: =IFERROR(__xludf.DUMMYFUNCTION("""COMPUTED_VALUE"""),-0.0042) -> -0.0042 | AB19: =IFERROR(__xludf.DUMMYFUNCTION("""COMPUTED_VALUE"""),1.1952556328397295) -> 1.1952556 | AC19: =IFERROR(__xludf.DUMMYFUNCTION("""COMPUTED_VALUE"""),"No paga") -> No paga | AD19: =IFERROR(__xludf.DUMMYFUNCTION("""COMPUTED_VALUE"""),433.0) -> 433 | AH19: =IFERROR(__xludf.DUMMYFUNCTION("""COMPUTED_VALUE"""),"GD38D") -> GD38D | AI19: =IFERROR(__xludf.DUMMYFUNCTION("""COMPUTED_VALUE"""),0.0039000000000000003) -> 0.0039 | AJ19: =IFERROR(__xludf.DUMMYFUNCTION("""COMPUTED_VALUE"""),50414.0) -> 50414 | AK19: =IFERROR(__xludf.DUMMYFUNCTION("""COMPUTED_VALUE"""),63.24) -> 63.24 | AL19: =IFERROR(__xludf.DUMMYFUNCTION("""COMPUTED_VALUE"""),0.1484998533469977) -> 0.14849985 | AM19: =IFERROR(__xludf.DUMMYFUNCTION("""COMPUTED_VALUE"""),0.13536804308797135) -> 0.13536804 | AN19: =IFERROR(__xludf.DUMMYFUNCTION("""COMPUTED_VALUE"""),0.07906388361796331) -> 0.079063884 | AO19: =IFERROR(__xludf.DUMMYFUNCTION("""COMPUTED_VALUE"""),4.83916218495876) -> 4.8391622 | AP19: =IFERROR(__xludf.DUMMYFUNCTION("""COMPUTED_VALUE"""),"Semestral") -> Semestral | AQ19: =IFERROR(__xludf.DUMMYFUNCTION("""COMPUTED_VALUE"""),"NY") -> NY | AR19: =IFERROR(__xludf.DUMMYFUNCTION("""COMPUTED_VALUE"""),0.6244212835984642) -> 0.62442128
B20: Agresivo | C20: TIR | D20: M,D | E20: Duration | F20: Weight | J20: =IFERROR(__xludf.DUMMYFUNCTION("""COMPUTED_VALUE"""),"S29Y6") -> S29Y6 | K20: =IFERROR(__xludf.DUMMYFUNCTION("""COMPUTED_VALUE"""),46171.0) -> 46171 | L20: =IFERROR(__xludf.DUMMYFUNCTION("""COMPUTED_VALUE"""),96.699) -> 96.699 | M20: =IFERROR(__xludf.DUMMYFUNCTION("""COMPUTED_VALUE"""),-0.0031) -> -0.0031 | N20: =IFERROR(__xludf.DUMMYFUNCTION("""COMPUTED_VALUE"""),0.041106509742426356) -> 0.04110651 | O20: =IFERROR(__xludf.DUMMYFUNCTION("""COMPUTED_VALUE"""),0.3655132528865632) -> 0.36551325 | P20: =IFERROR(__xludf.DUMMYFUNCTION("""COMPUTED_VALUE"""),0.5750531780327396) -> 0.57505318 | Q20: =IFERROR(__xludf.DUMMYFUNCTION("""COMPUTED_VALUE"""),0.6325173456812241) -> 0.63251735 | R20: =IFERROR(__xludf.DUMMYFUNCTION("""COMPUTED_VALUE"""),233.0) -> 233 | S20: =IFERROR(__xludf.DUMMYFUNCTION("""COMPUTED_VALUE"""),2086.4348595375636) -> 2086.4349 | T20: =IFERROR(__xludf.DUMMYFUNCTION("""COMPUTED_VALUE"""),233.0) -> 233 | V20: =IFERROR(__xludf.DUMMYFUNCTION("""COMPUTED_VALUE"""),"TZX27") -> TZX27 | W20: =IFERROR(__xludf.DUMMYFUNCTION("""COMPUTED_VALUE"""),46568.0) -> 46568 | X20: =IFERROR(__xludf.DUMMYFUNCTION("""COMPUTED_VALUE"""),"CER + 0%") -> CER + 0% | Y20: =IFERROR(__xludf.DUMMYFUNCTION("""COMPUTED_VALUE"""),217.0) -> 217 | Z20: =IFERROR(__xludf.DUMMYFUNCTION("""COMPUTED_VALUE"""),0.2420751062170588) -> 0.24207511 | AA20: =IFERROR(__xludf.DUMMYFUNCTION("""COMPUTED_VALUE"""),-0.0149) -> -0.0149 | AB20: =IFERROR(__xludf.DUMMYFUNCTION("""COMPUTED_VALUE"""),1.7381800379366201) -> 1.73818 | AC20: =IFERROR(__xludf.DUMMYFUNCTION("""COMPUTED_VALUE"""),"No paga") -> No paga | AD20: =IFERROR(__xludf.DUMMYFUNCTION("""COMPUTED_VALUE"""),630.0) -> 630 | AH20: =IFERROR(__xludf.DUMMYFUNCTION("""COMPUTED_VALUE"""),"GD35D") -> GD35D | AI20: =IFERROR(__xludf.DUMMYFUNCTION("""COMPUTED_VALUE"""),0.0052) -> 0.0052 | AJ20: =IFERROR(__xludf.DUMMYFUNCTION("""COMPUTED_VALUE"""),49499.0) -> 49499 | AK20: =IFERROR(__xludf.DUMMYFUNCTION("""COMPUTED_VALUE"""),57.81) -> 57.81 | AL20: =IFERROR(__xludf.DUMMYFUNCTION("""COMPUTED_VALUE"""),0.14874852304018849) -> 0.14874852 | AM20: =IFERROR(__xludf.DUMMYFUNCTION("""COMPUTED_VALUE"""),0.04406718439588242) -> 0.044067184 | AN20: =IFERROR(__xludf.DUMMYFUNCTION("""COMPUTED_VALUE"""),0.07126794672202041) -> 0.071267947 | AO20: =IFERROR(__xludf.DUMMYFUNCTION("""COMPUTED_VALUE"""),5.780826054773654) -> 5.7808261 | AP20: =IFERROR(__xludf.DUMMYFUNCTION("""COMPUTED_VALUE"""),"Semestral") -> Semestral | AQ20: =IFERROR(__xludf.DUMMYFUNCTION("""COMPUTED_VALUE"""),"NY") -> NY | AR20: =IFERROR(__xludf.DUMMYFUNCTION("""COMPUTED_VALUE"""),0.5720622012778463) -> 0.5720622
B21: T13F6 | C21: =VLOOKUP(B21,$J$11:$R$63,7,0) -> 0.64187965 | D21: =VLOOKUP(B21,$J$11:$R$63,9,0) -> 128 | E21: =D21 -> 128 | F21: 0.5 | J21: =IFERROR(__xludf.DUMMYFUNCTION("""COMPUTED_VALUE"""),"TY30P") -> TY30P | K21: =IFERROR(__xludf.DUMMYFUNCTION("""COMPUTED_VALUE"""),47633.0) -> 47633 | L21: =IFERROR(__xludf.DUMMYFUNCTION("""COMPUTED_VALUE"""),87.9) -> 87.9 | M21: =IFERROR(__xludf.DUMMYFUNCTION("""COMPUTED_VALUE"""),0.011000000000000001) -> 0.011 | N21: =IFERROR(__xludf.DUMMYFUNCTION("""COMPUTED_VALUE"""),"-") -> - | O21: =IFERROR(__xludf.DUMMYFUNCTION("""COMPUTED_VALUE"""),1.8119453924914675) -> 1.8119454 | P21: =IFERROR(__xludf.DUMMYFUNCTION("""COMPUTED_VALUE"""),0.36824057252749753) -> 0.36824057 | Q21: =IFERROR(__xludf.DUMMYFUNCTION("""COMPUTED_VALUE"""),0.4447981800986797) -> 0.44479818 | R21: =IFERROR(__xludf.DUMMYFUNCTION("""COMPUTED_VALUE"""),1695.0) -> 1695 | S21: =IFERROR(__xludf.DUMMYFUNCTION("""COMPUTED_VALUE"""),4296.5096659502115) -> 4296.5097 | V21: =IFERROR(__xludf.DUMMYFUNCTION("""COMPUTED_VALUE"""),"TZXD7") -> TZXD7 | W21: =IFERROR(__xludf.DUMMYFUNCTION("""COMPUTED_VALUE"""),46736.0) -> 46736 | X21: =IFERROR(__xludf.DUMMYFUNCTION("""COMPUTED_VALUE"""),"CER + 0%") -> CER + 0% | Y21: =IFERROR(__xludf.DUMMYFUNCTION("""COMPUTED_VALUE"""),153.25) -> 153.25 | Z21: =IFERROR(__xludf.DUMMYFUNCTION("""COMPUTED_VALUE"""),0.2117400809344362) -> 0.21174008 | AA21: =IFERROR(__xludf.DUMMYFUNCTION("""COMPUTED_VALUE"""),-0.011200000000000002) -> -0.0112 | AB21: =IFERROR(__xludf.DUMMYFUNCTION("""COMPUTED_VALUE"""),2.2010314143470966) -> 2.2010314 | AC21: =IFERROR(__xludf.DUMMYFUNCTION("""COMPUTED_VALUE"""),"No paga") -> No paga | AD21: =IFERROR(__xludf.DUMMYFUNCTION("""COMPUTED_VALUE"""),798.0) -> 798 | AH21: =IFERROR(__xludf.DUMMYFUNCTION("""COMPUTED_VALUE"""),"GD41D") -> GD41D | AI21: =IFERROR(__xludf.DUMMYFUNCTION("""COMPUTED_VALUE"""),0.0045000000000000005) -> 0.0045 | AJ21: =IFERROR(__xludf.DUMMYFUNCTION("""COMPUTED_VALUE"""),51691.0) -> 51691 | AK21: =IFERROR(__xludf.DUMMYFUNCTION("""COMPUTED_VALUE"""),54.75) -> 54.75 | AL21: =IFERROR(__xludf.DUMMYFUNCTION("""COMPUTED_VALUE"""),0.14272381678498997) -> 0.14272382 | AM21: =IFERROR(__xludf.DUMMYFUNCTION("""COMPUTED_VALUE"""),0.02336448598130847) -> 0.023364486 | AN21: =IFERROR(__xludf.DUMMYFUNCTION("""COMPUTED_VALUE"""),0.0639269406392694) -> 0.063926941 | AO21: =IFERROR(__xludf.DUMMYFUNCTION("""COMPUTED_VALUE"""),5.964572755756893) -> 5.9645728 | AP21: =IFERROR(__xludf.DUMMYFUNCTION("""COMPUTED_VALUE"""),"Semestral") -> Semestral | AQ21: =IFERROR(__xludf.DUMMYFUNCTION("""COMPUTED_VALUE"""),"NY") -> NY | AR21: =IFERROR(__xludf.DUMMYFUNCTION("""COMPUTED_VALUE"""),0.5426463300479049) -> 0.54264633
V22: =IFERROR(__xludf.DUMMYFUNCTION("""COMPUTED_VALUE"""),"TZX28") -> TZX28 | W22: =IFERROR(__xludf.DUMMYFUNCTION("""COMPUTED_VALUE"""),46934.0) -> 46934 | X22: =IFERROR(__xludf.DUMMYFUNCTION("""COMPUTED_VALUE"""),"CER + 0%") -> CER + 0% | Y22: =IFERROR(__xludf.DUMMYFUNCTION("""COMPUTED_VALUE"""),188.4) -> 188.4 | Z22: =IFERROR(__xludf.DUMMYFUNCTION("""COMPUTED_VALUE"""),0.20790405608325158) -> 0.20790406 | AA22: =IFERROR(__xludf.DUMMYFUNCTION("""COMPUTED_VALUE"""),-0.0018) -> -0.0018 | AB22: =IFERROR(__xludf.DUMMYFUNCTION("""COMPUTED_VALUE"""),2.744193361873141) -> 2.7441934 | AC22: =IFERROR(__xludf.DUMMYFUNCTION("""COMPUTED_VALUE"""),"No paga") -> No paga | AD22: =IFERROR(__xludf.DUMMYFUNCTION("""COMPUTED_VALUE"""),996.0) -> 996
B23: TZXD7 | C23: =VLOOKUP(B23,$V$11:$AD$28,5,0) -> 0.21174008 | D23: =VLOOKUP(B23,$V$11:$AD$28,7,0) -> 2.2010314 | E23: =D23 -> 2.2010314 | F23: 0.5 | J23: =IFERROR(__xludf.DUMMYFUNCTION("""COMPUTED_VALUE"""),"BONOS DUALES") -> BONOS DUALES | V23: =IFERROR(__xludf.DUMMYFUNCTION("""COMPUTED_VALUE"""),"DICP") -> DICP | W23: =IFERROR(__xludf.DUMMYFUNCTION("""COMPUTED_VALUE"""),48944.0) -> 48944 | X23: =IFERROR(__xludf.DUMMYFUNCTION("""COMPUTED_VALUE"""),"CER + 5,83%") -> CER + 5,83% | Y23: =IFERROR(__xludf.DUMMYFUNCTION("""COMPUTED_VALUE"""),33000.0) -> 33000 | Z23: =IFERROR(__xludf.DUMMYFUNCTION("""COMPUTED_VALUE"""),0.1752807970402648) -> 0.1752808 | AA23: =IFERROR(__xludf.DUMMYFUNCTION("""COMPUTED_VALUE"""),-0.003) -> -0.003 | AB23: =IFERROR(__xludf.DUMMYFUNCTION("""COMPUTED_VALUE"""),3.068974711646165) -> 3.0689747 | AC23: =IFERROR(__xludf.DUMMYFUNCTION("""COMPUTED_VALUE"""),"Semestral") -> Semestral | AD23: =IFERROR(__xludf.DUMMYFUNCTION("""COMPUTED_VALUE"""),84.0) -> 84
A24: Duales | J24: =IFERROR(__xludf.DUMMYFUNCTION("""COMPUTED_VALUE"""),"Ticker") -> Ticker | K24: =IFERROR(__xludf.DUMMYFUNCTION("""COMPUTED_VALUE"""),"Vencimiento ") -> Vencimiento | L24: =IFERROR(__xludf.DUMMYFUNCTION("""COMPUTED_VALUE"""),"Precio") -> Precio | M24: =IFERROR(__xludf.DUMMYFUNCTION("""COMPUTED_VALUE"""),"Variación") -> Variación | N24: =IFERROR(__xludf.DUMMYFUNCTION("""COMPUTED_VALUE"""),"TEM Fija") -> TEM Fija | O24: =IFERROR(__xludf.DUMMYFUNCTION("""COMPUTED_VALUE"""),"TNA") -> TNA | P24: =IFERROR(__xludf.DUMMYFUNCTION("""COMPUTED_VALUE"""),"TEM Variable") -> TEM Variable | Q24: =IFERROR(__xludf.DUMMYFUNCTION("""COMPUTED_VALUE"""),"TNA") -> TNA | R24: =IFERROR(__xludf.DUMMYFUNCTION("""COMPUTED_VALUE"""),"Duration") -> Duration | S24: =IFERROR(__xludf.DUMMYFUNCTION("""COMPUTED_VALUE"""),"Fx B.E Fija") -> Fx B.E Fija | V24: =IFERROR(__xludf.DUMMYFUNCTION("""COMPUTED_VALUE"""),"PARP") -> PARP | W24: =IFERROR(__xludf.DUMMYFUNCTION("""COMPUTED_VALUE"""),50770.0) -> 50770 | X24: =IFERROR(__xludf.DUMMYFUNCTION("""COMPUTED_VALUE"""),"CER + 0%") -> CER + 0% | Y24: =IFERROR(__xludf.DUMMYFUNCTION("""COMPUTED_VALUE"""),18845.0) -> 18845 | Z24: =IFERROR(__xludf.DUMMYFUNCTION("""COMPUTED_VALUE"""),0.13741283729613815) -> 0.13741284 | AA24: =IFERROR(__xludf.DUMMYFUNCTION("""COMPUTED_VALUE"""),-0.0052) -> -0.0052 | AB24: =IFERROR(__xludf.DUMMYFUNCTION("""COMPUTED_VALUE"""),6.924285291221014) -> 6.9242853 | AC24: =IFERROR(__xludf.DUMMYFUNCTION("""COMPUTED_VALUE"""),"Semestral") -> Semestral | AD24: =IFERROR(__xludf.DUMMYFUNCTION("""COMPUTED_VALUE"""),-8.0) -> -8 | AH24: =IFERROR(__xludf.DUMMYFUNCTION("""COMPUTED_VALUE"""),"http") -> http
E25: =SUM(E21:E24) -> 130.20103 | J25: =IFERROR(__xludf.DUMMYFUNCTION("""COMPUTED_VALUE"""),"TTM26") -> TTM26 | K25: =IFERROR(__xludf.DUMMYFUNCTION("""COMPUTED_VALUE"""),46097.0) -> 46097 | L25: =IFERROR(__xludf.DUMMYFUNCTION("""COMPUTED_VALUE"""),117.0) -> 117 | M25: =IFERROR(__xludf.DUMMYFUNCTION("""COMPUTED_VALUE"""),0.006) -> 0.006 | N25: =IFERROR(__xludf.DUMMYFUNCTION("""COMPUTED_VALUE"""),0.02788737498280902) -> 0.027887375 | O25: =IFERROR(__xludf.DUMMYFUNCTION("""COMPUTED_VALUE"""),0.3601049004223998) -> 0.3601049 | P25: =IFERROR(__xludf.DUMMYFUNCTION("""COMPUTED_VALUE"""),0.04357139507931551) -> 0.043571395 | Q25: =IFERROR(__xludf.DUMMYFUNCTION("""COMPUTED_VALUE"""),0.5817906121013456) -> 0.58179061 | R25: =IFERROR(__xludf.DUMMYFUNCTION("""COMPUTED_VALUE"""),0.44166666666666665) -> 0.44166667 | S25: =IFERROR(__xludf.DUMMYFUNCTION("""COMPUTED_VALUE"""),1766.127468737626) -> 1766.1275 | V25: =IFERROR(__xludf.DUMMYFUNCTION("""COMPUTED_VALUE"""),"CUAP") -> CUAP | W25: =IFERROR(__xludf.DUMMYFUNCTION("""COMPUTED_VALUE"""),53327.0) -> 53327 | X25: =IFERROR(__xludf.DUMMYFUNCTION("""COMPUTED_VALUE"""),"CER + 3,31%") -> CER + 3,31% | Y25: =IFERROR(__xludf.DUMMYFUNCTION("""COMPUTED_VALUE"""),24400.0) -> 24400 | Z25: =IFERROR(__xludf.DUMMYFUNCTION("""COMPUTED_VALUE"""),0.08360587900015218) -> 0.083605879 | AA25: =IFERROR(__xludf.DUMMYFUNCTION("""COMPUTED_VALUE"""),-0.004) -> -0.004 | AB25: =IFERROR(__xludf.DUMMYFUNCTION("""COMPUTED_VALUE"""),10.554893835719417) -> 10.554894 | AC25: =IFERROR(__xludf.DUMMYFUNCTION("""COMPUTED_VALUE"""),"Semestral") -> Semestral | AD25: =IFERROR(__xludf.DUMMYFUNCTION("""COMPUTED_VALUE"""),84.0) -> 84
J26: =IFERROR(__xludf.DUMMYFUNCTION("""COMPUTED_VALUE"""),"TTJ26") -> TTJ26 | K26: =IFERROR(__xludf.DUMMYFUNCTION("""COMPUTED_VALUE"""),46203.0) -> 46203 | L26: =IFERROR(__xludf.DUMMYFUNCTION("""COMPUTED_VALUE"""),110.0) -> 110 | M26: =IFERROR(__xludf.DUMMYFUNCTION("""COMPUTED_VALUE"""),-0.0013) -> -0.0013 | N26: =IFERROR(__xludf.DUMMYFUNCTION("""COMPUTED_VALUE"""),0.03159027711135387) -> 0.031590277 | O26: =IFERROR(__xludf.DUMMYFUNCTION("""COMPUTED_VALUE"""),0.435251667894187) -> 0.43525167 | P26: =IFERROR(__xludf.DUMMYFUNCTION("""COMPUTED_VALUE"""),0.04458176331125441) -> 0.044581763 | Q26: =IFERROR(__xludf.DUMMYFUNCTION("""COMPUTED_VALUE"""),0.6468931642244389) -> 0.64689316 | R26: =IFERROR(__xludf.DUMMYFUNCTION("""COMPUTED_VALUE"""),0.7361111111111112) -> 0.73611111 | S26: =IFERROR(__xludf.DUMMYFUNCTION("""COMPUTED_VALUE"""),2008.966174123415) -> 2008.9662
B27: Conservador/Moderado | C27: TIR | D27: M,D | E27: Inverse duration | F27: Weight | J27: =IFERROR(__xludf.DUMMYFUNCTION("""COMPUTED_VALUE"""),"TTS26") -> TTS26 | K27: =IFERROR(__xludf.DUMMYFUNCTION("""COMPUTED_VALUE"""),46280.0) -> 46280 | L27: =IFERROR(__xludf.DUMMYFUNCTION("""COMPUTED_VALUE"""),102.55) -> 102.55 | M27: =IFERROR(__xludf.DUMMYFUNCTION("""COMPUTED_VALUE"""),-0.0139) -> -0.0139 | N27: =IFERROR(__xludf.DUMMYFUNCTION("""COMPUTED_VALUE"""),0.035285036993908836) -> 0.035285037 | O27: =IFERROR(__xludf.DUMMYFUNCTION("""COMPUTED_VALUE"""),0.5171408376978389) -> 0.51714084 | P27: =IFERROR(__xludf.DUMMYFUNCTION("""COMPUTED_VALUE"""),0.047204527084171444) -> 0.047204527 | Q27: =IFERROR(__xludf.DUMMYFUNCTION("""COMPUTED_VALUE"""),0.7377501921931121) -> 0.73775019 | R27: =IFERROR(__xludf.DUMMYFUNCTION("""COMPUTED_VALUE"""),0.95) -> 0.95 | S27: =IFERROR(__xludf.DUMMYFUNCTION("""COMPUTED_VALUE"""),2266.1580543416126) -> 2266.1581
A28: Bopreal | B28: BPD7D | C28: =VLOOKUP(B28,$AT$11:$BD$16,5,0) -> 0.13940657 | D28: =VLOOKUP(B28,$AT$11:$BD$16,8,0) -> 1.7160218 | E28: =1/D28 -> 0.58274319 | F28: =E28/$E$31 -> 0.46044792 | J28: =IFERROR(__xludf.DUMMYFUNCTION("""COMPUTED_VALUE"""),"TTD26") -> TTD26 | K28: =IFERROR(__xludf.DUMMYFUNCTION("""COMPUTED_VALUE"""),46371.0) -> 46371 | L28: =IFERROR(__xludf.DUMMYFUNCTION("""COMPUTED_VALUE"""),101.9) -> 101.9 | M28: =IFERROR(__xludf.DUMMYFUNCTION("""COMPUTED_VALUE"""),0.0029) -> 0.0029 | N28: =IFERROR(__xludf.DUMMYFUNCTION("""COMPUTED_VALUE"""),0.03233857594082834) -> 0.032338576 | O28: =IFERROR(__xludf.DUMMYFUNCTION("""COMPUTED_VALUE"""),0.4912209035592255) -> 0.4912209 | P28: =IFERROR(__xludf.DUMMYFUNCTION("""COMPUTED_VALUE"""),0.04363531094758377) -> 0.043635311 | Q28: =IFERROR(__xludf.DUMMYFUNCTION("""COMPUTED_VALUE"""),0.7179211245297211) -> 0.71792112 | R28: =IFERROR(__xludf.DUMMYFUNCTION("""COMPUTED_VALUE"""),1.2027777777777777) -> 1.2027778 | S28: =IFERROR(__xludf.DUMMYFUNCTION("""COMPUTED_VALUE"""),2416.2838952898246) -> 2416.2839
B29: AL30D | C29: =VLOOKUP(B29,$AH$10:$AQ$21,5,0) -> 0.19046508 | D29: =VLOOKUP(B29,$AH$10:$AQ$21,8,0) -> 2.152768 | E29: =1/D29 -> 0.46451825 | F29: =E29/$E$31 -> 0.36703383 | V29: =IFERROR(__xludf.DUMMYFUNCTION("""COMPUTED_VALUE"""),"Meses") -> Meses | W29: =IFERROR(__xludf.DUMMYFUNCTION("""COMPUTED_VALUE"""),"Infla B.E") -> Infla B.E | X29: =IFERROR(__xludf.DUMMYFUNCTION("""COMPUTED_VALUE"""),"REM") -> REM
B30: AE38D | C30: =VLOOKUP(B30,$AH$10:$AQ$21,5,0) -> 0.17988136 | D30: =VLOOKUP(B30,$AH$10:$AQ$21,8,0) -> 4.5800295 | E30: =1/D30 -> 0.21833921 | F30: =E30/$E$31 -> 0.17251825 | V30: =IFERROR(__xludf.DUMMYFUNCTION("""COMPUTED_VALUE"""),"Abril") -> Abril | W30: =IFERROR(__xludf.DUMMYFUNCTION("""COMPUTED_VALUE"""),0.018) -> 0.018 | X30: =IFERROR(__xludf.DUMMYFUNCTION("""COMPUTED_VALUE"""),0.032) -> 0.032
E31: =SUM(E28:E30) -> 1.2656006 | V31: =IFERROR(__xludf.DUMMYFUNCTION("""COMPUTED_VALUE"""),"Mayo") -> Mayo | W31: =IFERROR(__xludf.DUMMYFUNCTION("""COMPUTED_VALUE"""),0.01640478354227004) -> 0.016404784 | X31: =IFERROR(__xludf.DUMMYFUNCTION("""COMPUTED_VALUE"""),0.015) -> 0.015
V32: =IFERROR(__xludf.DUMMYFUNCTION("""COMPUTED_VALUE"""),"Junio") -> Junio | W32: =IFERROR(__xludf.DUMMYFUNCTION("""COMPUTED_VALUE"""),0.01640478354227004) -> 0.016404784 | X32: =IFERROR(__xludf.DUMMYFUNCTION("""COMPUTED_VALUE"""),0.018) -> 0.018
V33: =IFERROR(__xludf.DUMMYFUNCTION("""COMPUTED_VALUE"""),"Julio") -> Julio | W33: =IFERROR(__xludf.DUMMYFUNCTION("""COMPUTED_VALUE"""),0.01640478354227004) -> 0.016404784 | X33: =IFERROR(__xludf.DUMMYFUNCTION("""COMPUTED_VALUE"""),0.018) -> 0.018
V34: =IFERROR(__xludf.DUMMYFUNCTION("""COMPUTED_VALUE"""),"Agosto") -> Agosto | W34: =IFERROR(__xludf.DUMMYFUNCTION("""COMPUTED_VALUE"""),0.01640478354227004) -> 0.016404784 | X34: =IFERROR(__xludf.DUMMYFUNCTION("""COMPUTED_VALUE"""),0.017) -> 0.017
B35: Agresivo | C35: TEM | D35: M,D | E35: Duration | F35: Weight | V35: =IFERROR(__xludf.DUMMYFUNCTION("""COMPUTED_VALUE"""),"Septiembre") -> Septiembre | W35: =IFERROR(__xludf.DUMMYFUNCTION("""COMPUTED_VALUE"""),0.01640478354227004) -> 0.016404784 | X35: =IFERROR(__xludf.DUMMYFUNCTION("""COMPUTED_VALUE"""),0.017) -> 0.017
A36: Globales | B36: BPD7D | C36: =VLOOKUP(B36,$AT$11:$BD$16,5,0) -> 0.13940657 | D36: =VLOOKUP(B36,$AT$11:$BD$16,8,0) -> 1.7160218 | E36: =D36 -> 1.7160218 | F36: =E36/E39 -> 0.20310788 | V36: =IFERROR(__xludf.DUMMYFUNCTION("""COMPUTED_VALUE"""),"Octubre") -> Octubre | W36: =IFERROR(__xludf.DUMMYFUNCTION("""COMPUTED_VALUE"""),0.01640478354227004) -> 0.016404784 | X36: =IFERROR(__xludf.DUMMYFUNCTION("""COMPUTED_VALUE"""),0.017) -> 0.017
B37: AL30D | C37: =VLOOKUP(B37,$AH$10:$AQ$21,5,0) -> 0.19046508 | D37: =VLOOKUP(B37,$AH$10:$AQ$21,8,0) -> 2.152768 | E37: =D37 -> 2.152768 | F37: =E37/$E$39 -> 0.25480104 | V37: =IFERROR(__xludf.DUMMYFUNCTION("""COMPUTED_VALUE"""),"Noviembre") -> Noviembre | W37: =IFERROR(__xludf.DUMMYFUNCTION("""COMPUTED_VALUE"""),0.022306787880636447) -> 0.022306788 | X37: =IFERROR(__xludf.DUMMYFUNCTION("""COMPUTED_VALUE"""),0.015) -> 0.015
B38: AE38D | C38: =VLOOKUP(B38,$AH$10:$AQ$21,5,0) -> 0.17988136 | D38: =VLOOKUP(B38,$AH$10:$AQ$21,8,0) -> 4.5800295 | E38: =D38 -> 4.5800295 | F38: =E38/$E$39 -> 0.54209107 | V38: =IFERROR(__xludf.DUMMYFUNCTION("""COMPUTED_VALUE"""),"Diciembre") -> Diciembre | W38: =IFERROR(__xludf.DUMMYFUNCTION("""COMPUTED_VALUE"""),0.022306787880636447) -> 0.022306788 | X38: =IFERROR(__xludf.DUMMYFUNCTION("""COMPUTED_VALUE"""),0.017) -> 0.017
E39: =SUM(E36:E38) -> 8.4488192 | V39: =IFERROR(__xludf.DUMMYFUNCTION("""COMPUTED_VALUE"""),46023.0) -> 46023 | W39: =IFERROR(__xludf.DUMMYFUNCTION("""COMPUTED_VALUE"""),0.022306787880636447) -> 0.022306788 | X39: =IFERROR(__xludf.DUMMYFUNCTION("""COMPUTED_VALUE"""),0.016) -> 0.016
V40: =IFERROR(__xludf.DUMMYFUNCTION("""COMPUTED_VALUE"""),"Febrero") -> Febrero | W40: =IFERROR(__xludf.DUMMYFUNCTION("""COMPUTED_VALUE"""),0.0174991418089534) -> 0.017499142
V41: =IFERROR(__xludf.DUMMYFUNCTION("""COMPUTED_VALUE"""),"Marzo") -> Marzo | W41: =IFERROR(__xludf.DUMMYFUNCTION("""COMPUTED_VALUE"""),0.0174991418089534) -> 0.017499142
V42: =IFERROR(__xludf.DUMMYFUNCTION("""COMPUTED_VALUE"""),"Abril") -> Abril | W42: =IFERROR(__xludf.DUMMYFUNCTION("""COMPUTED_VALUE"""),0.0174991418089534) -> 0.017499142
V43: =IFERROR(__xludf.DUMMYFUNCTION("""COMPUTED_VALUE"""),"Mayo") -> Mayo | W43: =IFERROR(__xludf.DUMMYFUNCTION("""COMPUTED_VALUE"""),0.018537284608237226) -> 0.018537285
V44: =IFERROR(__xludf.DUMMYFUNCTION("""COMPUTED_VALUE"""),"Junio") -> Junio | W44: =IFERROR(__xludf.DUMMYFUNCTION("""COMPUTED_VALUE"""),0.018537284608237226) -> 0.018537285
B45: Simple | V45: =IFERROR(__xludf.DUMMYFUNCTION("""COMPUTED_VALUE"""),"Julio") -> Julio | W45: =IFERROR(__xludf.DUMMYFUNCTION("""COMPUTED_VALUE"""),0.018537284608237226) -> 0.018537285
B46: Ticker | C46: TIR | D46: M,D | E46: Inverse duration | F46: Weight | V46: =IFERROR(__xludf.DUMMYFUNCTION("""COMPUTED_VALUE"""),"Agosto") -> Agosto | W46: =IFERROR(__xludf.DUMMYFUNCTION("""COMPUTED_VALUE"""),0.018537284608237226) -> 0.018537285
A47: Conservador | B47: AL30D | C47: =VLOOKUP(B47,$AH$10:$AQ$21,5,0) -> 0.19046508 | D47: =VLOOKUP(B47,$AH$10:$AQ$21,8,0) -> 2.152768 | E47: =1/D47 -> 0.46451825 | F47: 1 | V47: =IFERROR(__xludf.DUMMYFUNCTION("""COMPUTED_VALUE"""),"Septiembre") -> Septiembre | W47: =IFERROR(__xludf.DUMMYFUNCTION("""COMPUTED_VALUE"""),0.018537284608237226) -> 0.018537285
A48: Moderado | B48: AL30D | C48: =VLOOKUP(B48,$AH$10:$AQ$21,5,0) -> 0.19046508 | D48: =VLOOKUP(B48,$AH$10:$AQ$21,8,0) -> 2.152768 | E48: =1/D48 -> 0.46451825 | F48: 1 | V48: =IFERROR(__xludf.DUMMYFUNCTION("""COMPUTED_VALUE"""),"Octubre") -> Octubre | W48: =IFERROR(__xludf.DUMMYFUNCTION("""COMPUTED_VALUE"""),0.018537284608237226) -> 0.018537285
A49: Agresivo | B49: AE38D | C49: =VLOOKUP(B49,$AH$10:$AQ$21,5,0) -> 0.17988136 | D49: =VLOOKUP(B49,$AH$10:$AQ$21,8,0) -> 4.5800295 | E49: =1/D49 -> 0.21833921 | F49: 1
V50: =IFERROR(__xludf.DUMMYFUNCTION("""COMPUTED_VALUE"""),2025.0) -> 2025 | X50: =IFERROR(__xludf.DUMMYFUNCTION("""COMPUTED_VALUE"""),0.273) -> 0.273

Sheet Tactical
B1: Capital | C1: 100000 | E1: Total risk | F1: 0.005 | H1: Risk USD units | J1: =C1*F1 -> 500
M2: Auxtin
B3: Ticker | C3: YTD | D3: Entry | E3: Exit | F3: Stop | G3: k * Days | H3: ATR | I3: ATR*K | J3: Price | K3: Contracts | L3: USD | M3: Signal
B4: HSBC | C4: 0.45 | F4: =J4-I4 -> 68.833615 | G4: 3 | H4: 0.888795 | I4: =H4*G4 -> 2.666385 | J4: =IFERROR(__xludf.DUMMYFUNCTION("GOOGLEFINANCE(B4)"),71.5) -> 71.5 | K4: =J4/I4 -> 26.815332 | L4: =K4*J4 -> 1917.2963
B5: BK | C5: 0.52 | F5: =J5-I5 -> 100.51002 | G5: 3 | H5: 1.829994 | I5: =H5*G5 -> 5.489982 | J5: =IFERROR(__xludf.DUMMYFUNCTION("GOOGLEFINANCE(B5)"),106.0) -> 106 | K5: =J5/I5 -> 19.307896 | L5: =K5*J5 -> 2046.6369
B6: SAN | C6: 0.8 | F6: =J6-I6 -> 9.591782 | G6: 3 | H6: 0.179406 | I6: =H6*G6 -> 0.538218 | J6: =IFERROR(__xludf.DUMMYFUNCTION("GOOGLEFINANCE(B6)"),10.13) -> 10.13 | K6: =J6/I6 -> 18.82137 | L6: =K6*J6 -> 190.66048
B7: CLS | C7: 2.92 | F7: =J7-I7 -> 219.0573 | G7: 3 | H7: 11.8909 | I7: =H7*G7 -> 35.6727 | J7: =IFERROR(__xludf.DUMMYFUNCTION("GOOGLEFINANCE(B7)"),254.73) -> 254.73 | K7: =J7/I7 -> 7.1407547 | L7: =K7*J7 -> 1818.9644
B8: GE | C8: 0.56 | F8: =J8-I8 -> 283.78907 | G8: 3 | H8: 6.276978 | I8: =H8*G8 -> 18.830934 | J8: =IFERROR(__xludf.DUMMYFUNCTION("GOOGLEFINANCE(B8)"),302.62) -> 302.62 | K8: =J8/I8 -> 16.070366 | L8: =K8*J8 -> 4863.2141
B9: VRSN | C9: 0.47 | F9: =J9-I9 -> 252.18964 | G9: 3 | H9: 5.256788 | I9: =H9*G9 -> 15.770364 | J9: =IFERROR(__xludf.DUMMYFUNCTION("GOOGLEFINANCE(B9)"),267.96) -> 267.96 | K9: =J9/I9 -> 16.991364 | L9: =K9*J9 -> 4553.006
B10: T | C10: 0.44 | F10: =J10-I10 -> 24.770826 | G10: 3 | H10: 0.493058 | I10: =H10*G10 -> 1.479174 | J10: =IFERROR(__xludf.DUMMYFUNCTION("GOOGLEFINANCE(B10)"),26.25) -> 26.25 | K10: =J10/I10 -> 17.746391 | L10: =K10*J10 -> 465.84276
B11: KGC | C11: 0.78 | F11: =J11-I11 -> 23.270385 | G11: 3 | H11: 0.673205 | I11: =H11*G11 -> 2.019615 | J11: =IFERROR(__xludf.DUMMYFUNCTION("GOOGLEFINANCE(B11)"),25.29) -> 25.29 | K11: =J11/I11 -> 12.522189 | L11: =K11*J11 -> 316.68615
B12: SNOW | C12: 0.96 | F12: =J12-I12 -> 225.04495 | G12: 3 | H12: 8.345017 | I12: =H12*G12 -> 25.035051 | J12: =IFERROR(__xludf.DUMMYFUNCTION("GOOGLEFINANCE(B12)"),250.08) -> 250.08 | K12: =J12/I12 -> 9.9891947 | L12: =K12*J12 -> 2498.0978
B13: PLTR | C13: 4.03 | F13: =J13-I13 -> 162.26184 | G13: 3 | H13: 7.039385 | I13: =H13*G13 -> 21.118155 | J13: =IFERROR(__xludf.DUMMYFUNCTION("GOOGLEFINANCE(B13)"),183.38) -> 183.38 | K13: =J13/I13 -> 8.6835237 | L13: =K13*J13 -> 1592.3846
B14: SCHW | C14: 0.52 | F14: =J14-I14 -> 88.262732 | G14: 3 | H14: 1.855756 | I14: =H14*G14 -> 5.567268 | J14: =IFERROR(__xludf.DUMMYFUNCTION("GOOGLEFINANCE(B14)"),93.83) -> 93.83 | K14: =J14/I14 -> 16.853868 | L14: =K14*J14 -> 1581.3984
B15: GILD | C15: 0.47 | F15: =J15-I15 -> 109.8474 | G15: 3 | H15: 2.824199 | I15: =H15*G15 -> 8.472597 | J15: =IFERROR(__xludf.DUMMYFUNCTION("GOOGLEFINANCE(B15)"),118.32) -> 118.32 | K15: =J15/I15 -> 13.965022 | L15: =K15*J15 -> 1652.3414
B16: ORCL | C16: 0.81 | F16: =J16-I16 -> 250.22963 | G16: 3 | H16: 12.68679 | I16: =H16*G16 -> 38.06037 | J16: =IFERROR(__xludf.DUMMYFUNCTION("GOOGLEFINANCE(B16)"),288.29) -> 288.29 | K16: =J16/I16 -> 7.5745454 | L16: =K16*J16 -> 2183.6657
B17: GLW | C17: 0.54 | F17: =J17-I17 -> 81.620617 | G17: 3 | H17: 1.816461 | I17: =H17*G17 -> 5.449383 | J17: =IFERROR(__xludf.DUMMYFUNCTION("GOOGLEFINANCE(B17)"),87.07) -> 87.07 | K17: =J17/I17 -> 15.977956 | L17: =K17*J17 -> 1391.2006
B18: BBVA | C18: 0.69 | F18: =J18-I18 -> 17.903486 | G18: 3 | H18: 0.338838 | I18: =H18*G18 -> 1.016514 | J18: =IFERROR(__xludf.DUMMYFUNCTION("GOOGLEFINANCE(B18)"),18.92) -> 18.92 | K18: =J18/I18 -> 18.612631 | L18: =K18*J18 -> 352.15098
B19: SPOT | C19: 0.83 | F19: =J19-I19 -> 606.71786 | G19: 3 | H19: 22.67738 | I19: =H19*G19 -> 68.03214 | J19: =IFERROR(__xludf.DUMMYFUNCTION("GOOGLEFINANCE(B19)"),674.75) -> 674.75 | K19: =J19/I19 -> 9.9181064 | L19: =K19*J19 -> 6692.2423
B20: MFG | C20: 0.48 | F20: =J20-I20 -> 6.106108 | G20: 3 | H20: 0.117964 | I20: =H20*G20 -> 0.353892 | J20: =IFERROR(__xludf.DUMMYFUNCTION("GOOGLEFINANCE(B20)"),6.46) -> 6.46 | K20: =J20/I20 -> 18.254157 | L20: =K20*J20 -> 117.92185
B21: RBLX | C21: 2.13 | F21: =J21-I21 -> 109.04907 | G21: 3 | H21: 5.543642 | I21: =H21*G21 -> 16.630926 | J21: =IFERROR(__xludf.DUMMYFUNCTION("GOOGLEFINANCE(B21)"),125.68) -> 125.68 | K21: =J21/I21 -> 7.5570055 | L21: =K21*J21 -> 949.76446
B22: SE | C22: 1 | F22: =J22-I22 -> 176.17659 | G22: 3 | H22: 5.637803 | I22: =H22*G22 -> 16.913409 | J22: =IFERROR(__xludf.DUMMYFUNCTION("GOOGLEFINANCE(B22)"),193.09) -> 193.09 | K22: =J22/I22 -> 11.416386 | L22: =K22*J22 -> 2204.3899
B23: NFLX | C23: 0.65 | F23: =J23-I23 -> 1133.6921 | G23: 3 | H23: 27.38929 | I23: =H23*G23 -> 82.16787 | J23: =IFERROR(__xludf.DUMMYFUNCTION("GOOGLEFINANCE(B23)"),1215.86) -> 1215.86 | K23: =J23/I23 -> 14.797268 | L23: =K23*J23 -> 17991.406
B24: UAL | C24: 1.01 | F24: =J24-I24 -> 88.333108 | G24: 3 | H24: 3.238964 | I24: =H24*G24 -> 9.716892 | J24: =IFERROR(__xludf.DUMMYFUNCTION("GOOGLEFINANCE(B24)"),98.05) -> 98.05 | K24: =J24/I24 -> 10.090675 | L24: =K24*J24 -> 989.39069
B25: GS | C25: 0.44 | F25: =J25-I25 -> 731.70679 | G25: 3 | H25: 15.90107 | I25: =H25*G25 -> 47.70321 | J25: =IFERROR(__xludf.DUMMYFUNCTION("GOOGLEFINANCE(B25)"),779.41) -> 779.41 | K25: =J25/I25 -> 16.338733 | L25: =K25*J25 -> 12734.572
B26: GFI | C26: 0.83 | F26: =J26-I26 -> 39.414136 | G26: 3 | H26: 1.325288 | I26: =H26*G26 -> 3.975864 | J26: =IFERROR(__xludf.DUMMYFUNCTION("GOOGLEFINANCE(B26)"),43.39) -> 43.39 | K26: =J26/I26 -> 10.913351 | L26: =K26*J26 -> 473.53031
B27: BCS | C27: 0.64 | F27: =J27-I27 -> 19.455644 | G27: 3 | H27: 0.341452 | I27: =H27*G27 -> 1.024356 | J27: =IFERROR(__xludf.DUMMYFUNCTION("GOOGLEFINANCE(B27)"),20.48) -> 20.48 | K27: =J27/I27 -> 19.993049 | L27: =K27*J27 -> 409.45765
B28: TWLO | C28: 1.06 | F28: =J28-I28 -> 101.12176 | G28: 3 | H28: 4.309412 | I28: =H28*G28 -> 12.928236 | J28: =IFERROR(__xludf.DUMMYFUNCTION("GOOGLEFINANCE(B28)"),114.05) -> 114.05 | K28: =J28/I28 -> 8.8217758 | L28: =K28*J28 -> 1006.1235
B29: C | C29: 0.53 | F29: =J29-I29 -> 90.485791 | G29: 3 | H29: 2.071403 | I29: =H29*G29 -> 6.214209 | J29: =IFERROR(__xludf.DUMMYFUNCTION("GOOGLEFINANCE(B29)"),96.7) -> 96.7 | K29: =J29/I29 -> 15.561112 | L29: =K29*J29 -> 1504.7595
B30: AVGO | C30: 0.82 | F30: =J30-I30 -> 311.91677 | G30: 3 | H30: 11.19441 | I30: =H30*G30 -> 33.58323 | J30: =IFERROR(__xludf.DUMMYFUNCTION("GOOGLEFINANCE(B30)"),345.5) -> 345.5 | K30: =J30/I30 -> 10.287873 | L30: =K30*J30 -> 3554.4601
B31: NVDA | C31: 0.49 | F31: =J31-I31 -> 174.24437 | G31: 3 | H31: 4.928543 | I31: =H31*G31 -> 14.785629 | J31: =IFERROR(__xludf.DUMMYFUNCTION("GOOGLEFINANCE(B31)"),189.03) -> 189.03 | K31: =J31/I31 -> 12.784711 | L31: =K31*J31 -> 2416.694
B32: VST | C32: 1.46 | F32: =J32-I32 -> 180.22578 | G32: 3 | H32: 8.538073 | I32: =H32*G32 -> 25.614219 | J32: =IFERROR(__xludf.DUMMYFUNCTION("GOOGLEFINANCE(B32)"),205.84) -> 205.84 | K32: =J32/I32 -> 8.0361615 | L32: =K32*J32 -> 1654.1635
B33: JOYY | C33: 0.52 | F33: =J33-I33 -> 53.69401 | G33: 3 | H33: 1.45533 | I33: =H33*G33 -> 4.36599 | J33: =IFERROR(__xludf.DUMMYFUNCTION("GOOGLEFINANCE(B33)"),58.06) -> 58.06 | K33: =J33/I33 -> 13.298244 | L33: =K33*J33 -> 772.09604
B34: EBAY | C34: 0.57 | F34: =J34-I34 -> 84.727779 | G34: 3 | H34: 2.457407 | I34: =H34*G34 -> 7.372221 | J34: =IFERROR(__xludf.DUMMYFUNCTION("GOOGLEFINANCE(B34)"),92.1) -> 92.1 | K34: =J34/I34 -> 12.492843 | L34: =K34*J34 -> 1150.5908

Sheet Capital
B4: Name | C4: Allocation
B5: Soberanos en pesos | C5: 1
A9: Security Analysis | B9: Modelo | C9: Corredor +/- 10% | D9: TAA
A10: =B5 -> Soberanos en pesos | B10: =C5 -> 1 | C10: 0 | D10: =C10+B10 -> 1
B13: =SUM(Tactical_19[Modelo]) -> 1 | C13: =SUM(Tactical_19[Corredor +/- 10%]) -> 0 | D13: =SUM(Tactical_19[TAA]) -> 1
C15: Weight
B16: =Soberanos!B3 -> S10N5 | C16: 0.3333
B17: =Soberanos!B4 -> T15D5 | C17: 0.3333
B18: =Soberanos!B5 -> S28N5 | C18: 0.3333
B21: =Ons!B11
C22: =SUM(C16:C21) -> 0.9999

Sheet Elite Income - Premium Income
B1: Desviación estándar esperada | C1: 0.11 | H1: Desviación estándar esperada | I1: 0.11
B2: TIR a vencimiento | C2: =E17 -> 0.085063088 | H2: TIR a vencimiento | I2: =K18 -> 0.076889887
A5: Security Analysis | B5: Modelo | C5: Corredor +/- 5% | D5: TAA | H5: Security Analysis | I5: Modelo | J5: Corredor +/- 5% | K5: TAA
A6: ONs ARG | B6: 1 | C6: -0.03 | D6: =C6+B6 -> 0.97 | H6: ONs ARG | I6: 1 | J6: -0.03 | K6: =J6+I6 -> 0.97
A7: Oro | B7: 0 | C7: 0.03 | D7: =C7+B7 -> 0.03 | H7: Oro | I7: 0 | J7: 0.03 | K7: =J7+I7 -> 0.03 | M7: Enero | N7: Febrero | O7: Marzo | P7: Abril | Q7: Mayo | R7: Junio | S7: Julio | T7: Agosto | U7: Septiembre | V7: Octubre | W7: Noviembre | X7: Diciembre
B8: =SUM(RE[Modelo]) -> 1 | C8: =SUM(RE[Corredor +/- 5%]) -> 0 | D8: =SUM(RE[TAA]) -> 1 | I8: =SUM(IP[Modelo]) -> 1 | J8: =SUM(IP[Corredor +/- 5%]) -> 0 | K8: =SUM(IP[TAA]) -> 1 | M8: YM34D | N8: IRCJD | O8: YMCXD | P8: VSCRD | Q8: TLCPD | R8: YMCID | S8: YM34D | T8: IRCJD | U8: YMCXD | V8: VSCRD | W8: TLCPD | X8: YMCID
P9: 6 | Q9: 8 | R9: 3 | S9: 11 | T9: 12 | U9: 2
A10: Columna 1 | B10: Ticker | C10: Weight | D10: TIR | E10: TIR PONDERADA | G10: Columna 1 | H10: Ticker | I10: Weight | J10: TIR | K10: TIR PONDERADA | N10: Ticker | O10: Weight | P10: TIR | Q10: Duration | R10: Vencimiento | S10: Ley | T10: Lam Mínima | U10: Empresa
B11: =Ons!B6 -> TLCPD | C11: =$D$6*Ons!G6 -> 0.17005114 | D11: =Ons!C6 -> 0.097477722 | E11: =D11*C11 -> 0.016576197 | H11: =N11 -> YM34D | I11: =O11*$K$6 -> 0.23825343 | J11: 0.08556618 | K11: =J11*I11 -> 0.020386436 | N11: =M8 -> YM34D | O11: =Q11/$Q$17 -> 0.24562209 | P11: =VLOOKUP($N$11,$N$34:$AB$63,P$9,0) -> 0.086475232 | Q11: =VLOOKUP($N$11,$N$34:$AB$63,Q$9,0) -> 5.5734194 | R11: =VLOOKUP($N$11,$N$34:$AB$63,R$9,0) -> 48961 | S11: =VLOOKUP($N$11,$N$34:$AB$63,S$9,0) -> NY | T11: =VLOOKUP($N$11,$N$34:$AB$63,T$9,0) -> 1 | U11: =VLOOKUP($N$11,$N$34:$AB$63,U$9,0) -> YPF
B12: =Ons!B7 -> BACGD | C12: =$D$6*Ons!G7 -> 0.27367378 | D12: =Ons!C7 -> 0.081859039 | E12: =D12*C12 -> 0.022402672 | H12: =N12 -> IRCJD | I12: =O12*$K$6 -> 0.057956963 | J12: 0.03878763 | K12: =J12*I12 -> 0.0022480132 | N12: =N8 -> IRCJD | O12: =Q12/$Q$17 -> 0.059749447 | P12: =VLOOKUP($N$12,$AF$34:$AS$69,P$9,0) -> 0.065666315 | Q12: =VLOOKUP($N$12,$AF$34:$AS$69,Q$9,0) -> 1.3557768 | R12: =VLOOKUP($N$12,$AF$34:$AS$69,R$9,0) -> 46446 | S12: =VLOOKUP($N$12,$AF$34:$AS$69,S$9,0) -> ARG | T12: =VLOOKUP($N$12,$AF$34:$AS$69,T$9,0) -> 100 | U12: =VLOOKUP($N$12,$AF$34:$AS$69,U$9,0) -> IRSA
B13: =Ons!B8 -> IRCPD | C13: =$D$6*Ons!G8 -> 0.13978367 | D13: =Ons!C8 -> 0.080184559 | E13: =D13*C13 -> 0.011208492 | H13: =N13 -> YMCXD | I13: =O13*$K$6 -> 0.18736494 | J13: 0.081142339 | K13: =J13*I13 -> 0.015203229 | N13: =O8 -> YMCXD | O13: =Q13/$Q$17 -> 0.19315973 | P13: =VLOOKUP($N$13,$N$34:$AB$63,P$9,0) -> 0.080585386 | Q13: =VLOOKUP($N$13,$N$34:$AB$63,Q$9,0) -> 4.3829942 | R13: =VLOOKUP($N$13,$N$34:$AB$63,R$9,0) -> 48102 | S13: =VLOOKUP($N$13,$N$34:$AB$63,S$9,0) -> NY | T13: =VLOOKUP($N$13,$N$34:$AB$63,T$9,0) -> 1 | U13: =VLOOKUP($N$13,$N$34:$AB$63,U$9,0) -> YPF
B14: =Ons!B9 -> YM34D | C14: =$D$6*Ons!G9 -> 0.15906103 | D14: =Ons!C9 -> 0.086475232 | E14: =D14*C14 -> 0.013754839 | H14: =N14 -> VSCRD | I14: =O14*$K$6 -> 0.17684754 | J14: 0.067511806 | K14: =J14*I14 -> 0.011939297 | N14: =P8 -> VSCRD | O14: =Q14/$Q$17 -> 0.18231705 | P14: =VLOOKUP($N$14,$AF$34:$AS$69,P$9,0) -> 0.072522769 | Q14: =VLOOKUP($N$14,$AF$34:$AS$69,Q$9,0) -> 4.1369625 | R14: =VLOOKUP($N$14,$AF$34:$AS$69,R$9,0) -> 48131 | S14: =VLOOKUP($N$14,$AF$34:$AS$69,S$9,0) -> ARG | T14: =VLOOKUP($N$14,$AF$34:$AS$69,T$9,0) -> 1 | U14: =VLOOKUP($N$14,$AF$34:$AS$69,U$9,0) -> Vista Energy
B15: =Ons!B10 -> TLCMD | C15: =$D$6*Ons!G10 -> 0.22743039 | D15: =Ons!C10 -> 0.092867481 | E15: =D15*C15 -> 0.021120887 | H15: =N15 -> TLCPD | I15: =O15*$K$6 -> 0.22285553 | J15: 0.092928222 | K15: =J15*I15 -> 0.020709568 | N15: =Q8 -> TLCPD | O15: =Q15/$Q$17 -> 0.22974796 | P15: =VLOOKUP($N$15,$N$34:$AB$63,P$9,0) -> 0.097477722 | Q15: =VLOOKUP($N$15,$N$34:$AB$63,Q$9,0) -> 5.213219 | R15: =VLOOKUP($N$15,$N$34:$AB$63,R$9,0) -> 48727 | S15: =VLOOKUP($N$15,$N$34:$AB$63,S$9,0) -> NY | T15: =VLOOKUP($N$15,$N$34:$AB$63,T$9,0) -> 100 | U15: =VLOOKUP($N$15,$N$34:$AB$63,U$9,0) -> Telecom
B16: GLD | C16: =D7 -> 0.03 | H16: =N16 -> YMCID | I16: =O16*$K$6 -> 0.086721605 | J16: 0.073837934 | K16: =J16*I16 -> 0.0064033442 | N16: =R8 -> YMCID | O16: =Q16/$Q$17 -> 0.089403717 | P16: =VLOOKUP($N$16,$N$34:$AB$63,P$9,0) -> 0.068874144 | Q16: =VLOOKUP($N$16,$N$34:$AB$63,Q$9,0) -> 2.0286628 | R16: =VLOOKUP($N$16,$N$34:$AB$63,R$9,0) -> 47299 | S16: =VLOOKUP($N$16,$N$34:$AB$63,S$9,0) -> NY | T16: =VLOOKUP($N$16,$N$34:$AB$63,T$9,0) -> 1 | U16: =VLOOKUP($N$16,$N$34:$AB$63,U$9,0) -> YPF
C17: =SUM(C11:C16) -> 1 | E17: =SUM(E11:E16) -> 0.085063088 | H17: GLD | I17: =J7 -> 0.03 | J17: 0 | O17: =SUM(O11:O16) -> 1 | Q17: =SUM(Q11:Q16) -> 22.691035
I18: =SUM(I11:I17) -> 1 | K18: =SUM(K11:K17) -> 0.076889887
M19: $10.000
M20: 45931 | N20: 45962 | O20: 45992 | P20: 46023 | Q20: 46082 | R20: 46113 | S20: 46143 | T20: 46174 | U20: 46204 | V20: 46235 | W20: 46266 | X20: 46296 | Y20: 46327 | Z20: 46357 | AA20: 46388 | AB20: 46419 | AC20: 46447 | AD20: 46478 | AE20: 46508 | AF20: 46539 | AG20: 46569 | AH20: 46631 | AI20: 46661 | AJ20: 46692 | AK20: 46722 | AL20: 46753 | AM20: 46813 | AN20: 46844 | AO20: 46874 | AP20: 46905 | AQ20: 46935 | AR20: 46997 | AS20: 47027 | AT20: 47058 | AU20: 47119 | AV20: 47178 | AW20: 47209 | AX20: 47239 | AY20: 47300 | AZ20: 47362 | BA20: 47392 | BB20: 47423 | BC20: 47484 | BD20: 47543 | BE20: 47574 | BF20: 47604 | BG20: 47665 | BH20: 47727 | BI20: 47757 | BJ20: 47788 | BK20: 47849 | BL20: 47908 | BM20: 47939 | BN20: 47969 | BO20: 48030 | BP20: 48092 | BQ20: 48122 | BR20: 48153 | BS20: 48214 | BT20: 48335 | BU20: 48396 | BV20: 48519 | BW20: 48580 | BX20: 48700 | BY20: 48761 | BZ20: 48945
M21: 65.9 | N21: 101.4 | O21: 39.7 | P21: 99.9 | Q21: 104 | R21: 65.4 | S21: 101.4 | T21: 165.6 | U21: 99.9 | V21: 21.2 | W21: 82.4 | X21: 65.9 | Y21: 101.4 | Z21: 160 | AA21: 99.9 | AB21: 633.6 | AC21: 82.4 | AD21: 65.4 | AE21: 101.4 | AF21: 154.2 | AG21: 99.9 | AH21: 82.4 | AI21: 65.9 | AJ21: 101.4 | AK21: 148.6 | AL21: 99.9 | AM21: 82.4 | AN21: 65.9 | AO21: 101.4 | AP21: 142.9 | AQ21: 99.9 | AR21: 82.4 | AS21: 65.9 | AT21: 101.4 | AU21: 237.2 | AV21: 82.4 | AW21: 65.4 | AX21: 101.4 | AY21: 231.9 | AZ21: 458.5 | BA21: 632.5 | BB21: 101.4 | BC21: 99.9 | BD21: 65.8 | BE21: 44 | BF21: 101.4 | BG21: 99.9 | BH21: 441.9 | BI21: 610.7 | BJ21: 101.4 | BK21: 99.9 | BL21: 49.5 | BM21: 22.3 | BN21: 101.4 | BO21: 99.9 | BP21: 1177.8 | BQ21: 606.1 | BR21: 101.4 | BS21: 825.3 | BT21: 1196.7 | BU21: 69.9 | BV21: 50.6 | BW21: 795.4 | BX21: 1145.8 | BY21: 39.9 | BZ21: 1007.2
M31: =IFERROR(__xludf.DUMMYFUNCTION("IMPORTRANGE(""https://docs.google.com/spreadsheets/d/1QFB2kh2cYM7XonEBR7QFtdA5P63irew36fgS54qRFHA/edit?gid=443985142#gid=443985142"" , ""ONs NY!A:O"")"),45938.0) -> 45938 | AE31: =IFERROR(__xludf.DUMMYFUNCTION("IMPORTRANGE(""https://docs.google.com/spreadsheets/d/1QFB2kh2cYM7XonEBR7QFtdA5P63irew36fgS54qRFHA/edit?gid=443985142#gid=443985142"" , ""ONs ARG!A:O"")"),45938.0) -> 45938
N32: =IFERROR(__xludf.DUMMYFUNCTION("""COMPUTED_VALUE"""),"CORPORATIVOS LEY NY") -> CORPORATIVOS LEY NY | AF32: =IFERROR(__xludf.DUMMYFUNCTION("""COMPUTED_VALUE"""),"CORPORATIVO LEY ARGENTINA") -> CORPORATIVO LEY ARGENTINA
N33: =IFERROR(__xludf.DUMMYFUNCTION("""COMPUTED_VALUE"""),"Ticker") -> Ticker | O33: =IFERROR(__xludf.DUMMYFUNCTION("""COMPUTED_VALUE"""),"Empresa") -> Empresa | P33: =IFERROR(__xludf.DUMMYFUNCTION("""COMPUTED_VALUE"""),"Vencimiento") -> Vencimiento | Q33: =IFERROR(__xludf.DUMMYFUNCTION("""COMPUTED_VALUE"""),"Tasa") -> Tasa | R33: =IFERROR(__xludf.DUMMYFUNCTION("""COMPUTED_VALUE"""),"Precio") -> Precio | S33: =IFERROR(__xludf.DUMMYFUNCTION("""COMPUTED_VALUE"""),"TIR") -> TIR | T33: =IFERROR(__xludf.DUMMYFUNCTION("""COMPUTED_VALUE"""),"Var. Diaria%") -> Var. Diaria% | U33: =IFERROR(__xludf.DUMMYFUNCTION("""COMPUTED_VALUE"""),"Duration") -> Duration | V33: =IFERROR(__xludf.DUMMYFUNCTION("""COMPUTED_VALUE"""),"Cupones") -> Cupones | W33: =IFERROR(__xludf.DUMMYFUNCTION("""COMPUTED_VALUE"""),"Tipo") -> Tipo | X33: =IFERROR(__xludf.DUMMYFUNCTION("""COMPUTED_VALUE"""),"Ley") -> Ley | Y33: =IFERROR(__xludf.DUMMYFUNCTION("""COMPUTED_VALUE"""),"Lam Minima") -> Lam Minima | Z33: =IFERROR(__xludf.DUMMYFUNCTION("""COMPUTED_VALUE"""),"Prox Cupón (días)") -> Prox Cupón (días) | AA33: =IFERROR(__xludf.DUMMYFUNCTION("""COMPUTED_VALUE"""),"Paridad") -> Paridad | AF33: =IFERROR(__xludf.DUMMYFUNCTION("""COMPUTED_VALUE"""),"Ticker") -> Ticker | AG33: =IFERROR(__xludf.DUMMYFUNCTION("""COMPUTED_VALUE"""),"Empresa") -> Empresa | AH33: =IFERROR(__xludf.DUMMYFUNCTION("""COMPUTED_VALUE"""),"Vencimiento") -> Vencimiento | AI33: =IFERROR(__xludf.DUMMYFUNCTION("""COMPUTED_VALUE"""),"Tasa") -> Tasa | AJ33: =IFERROR(__xludf.DUMMYFUNCTION("""COMPUTED_VALUE"""),"Precio") -> Precio | AK33: =IFERROR(__xludf.DUMMYFUNCTION("""COMPUTED_VALUE"""),"TIR") -> TIR | AL33: =IFERROR(__xludf.DUMMYFUNCTION("""COMPUTED_VALUE"""),"Var. Diaria%") -> Var. Diaria% | AM33: =IFERROR(__xludf.DUMMYFUNCTION("""COMPUTED_VALUE"""),"Duration") -> Duration | AN33: =IFERROR(__xludf.DUMMYFUNCTION("""COMPUTED_VALUE"""),"Cupones") -> Cupones | AO33: =IFERROR(__xludf.DUMMYFUNCTION("""COMPUTED_VALUE"""),"Tipo") -> Tipo | AP33: =IFERROR(__xludf.DUMMYFUNCTION("""COMPUTED_VALUE"""),"Ley") -> Ley | AQ33: =IFERROR(__xludf.DUMMYFUNCTION("""COMPUTED_VALUE"""),"Lam Minima") -> Lam Minima | AR33: =IFERROR(__xludf.DUMMYFUNCTION("""COMPUTED_VALUE"""),"Prox Cupón (días)") -> Prox Cupón (días) | AS33: =IFERROR(__xludf.DUMMYFUNCTION("""COMPUTED_VALUE"""),"Paridad") -> Paridad
N34: =IFERROR(__xludf.DUMMYFUNCTION("""COMPUTED_VALUE"""),"NPCBD") -> NPCBD | O34: =IFERROR(__xludf.DUMMYFUNCTION("""COMPUTED_VALUE"""),"Central Puerto") -> Central Puerto | P34: =IFERROR(__xludf.DUMMYFUNCTION("""COMPUTED_VALUE"""),45947.0) -> 45947 | Q34: =IFERROR(__xludf.DUMMYFUNCTION("""COMPUTED_VALUE"""),0.1) -> 0.1 | R34: =IFERROR(__xludf.DUMMYFUNCTION("""COMPUTED_VALUE"""),106.2) -> 106.2 | S34: =IFERROR(__xludf.DUMMYFUNCTION("""COMPUTED_VALUE"""),-0.3692612611849655) -> -0.36926126 | T34: =IFERROR(__xludf.DUMMYFUNCTION("""COMPUTED_VALUE"""),0.0023) -> 0.0023 | U34: =IFERROR(__xludf.DUMMYFUNCTION("""COMPUTED_VALUE"""),0.02500394606092653) -> 0.025003946 | V34: =IFERROR(__xludf.DUMMYFUNCTION("""COMPUTED_VALUE"""),"Semestral") -> Semestral | W34: =IFERROR(__xludf.DUMMYFUNCTION("""COMPUTED_VALUE"""),"Bullet") -> Bullet | X34: =IFERROR(__xludf.DUMMYFUNCTION("""COMPUTED_VALUE"""),"NY") -> NY | Y34: =IFERROR(__xludf.DUMMYFUNCTION("""COMPUTED_VALUE"""),1000.0) -> 1000 | Z34: =IFERROR(__xludf.DUMMYFUNCTION("""COMPUTED_VALUE"""),9.0) -> 9 | AA34: =IFERROR(__xludf.DUMMYFUNCTION("""COMPUTED_VALUE"""),1.01276821192053) -> 1.0127682 | AF34: =IFERROR(__xludf.DUMMYFUNCTION("""COMPUTED_VALUE"""),"MGCHD") -> MGCHD | AG34: =IFERROR(__xludf.DUMMYFUNCTION("""COMPUTED_VALUE"""),"Pampa Energia") -> Pampa Energia | AH34: =IFERROR(__xludf.DUMMYFUNCTION("""COMPUTED_VALUE"""),45965.0) -> 45965 | AI34: =IFERROR(__xludf.DUMMYFUNCTION("""COMPUTED_VALUE"""),0.0499) -> 0.0499 | AJ34: =IFERROR(__xludf.DUMMYFUNCTION("""COMPUTED_VALUE"""),103.6) -> 103.6 | AK34: =IFERROR(__xludf.DUMMYFUNCTION("""COMPUTED_VALUE"""),-0.13680534017964144) -> -0.13680534 | AL34: =IFERROR(__xludf.DUMMYFUNCTION("""COMPUTED_VALUE"""),0.0087) -> 0.0087 | AM34: =IFERROR(__xludf.DUMMYFUNCTION("""COMPUTED_VALUE"""),0.07223273475948583) -> 0.072232735 | AN34: =IFERROR(__xludf.DUMMYFUNCTION("""COMPUTED_VALUE"""),"Semestral") -> Semestral | AO34: =IFERROR(__xludf.DUMMYFUNCTION("""COMPUTED_VALUE"""),"Bullet") -> Bullet | AP34: =IFERROR(__xludf.DUMMYFUNCTION("""COMPUTED_VALUE"""),"ARG") -> ARG | AQ34: =IFERROR(__xludf.DUMMYFUNCTION("""COMPUTED_VALUE"""),100.0) -> 100 | AR34: =IFERROR(__xludf.DUMMYFUNCTION("""COMPUTED_VALUE"""),27.0) -> 27 | AS34: =IFERROR(__xludf.DUMMYFUNCTION("""COMPUTED_VALUE"""),1.0140949924936482) -> 1.014095
N35: =IFERROR(__xludf.DUMMYFUNCTION("""COMPUTED_VALUE"""),"YMCHD") -> YMCHD | O35: =IFERROR(__xludf.DUMMYFUNCTION("""COMPUTED_VALUE"""),"YPF") -> YPF | P35: =IFERROR(__xludf.DUMMYFUNCTION("""COMPUTED_VALUE"""),46065.0) -> 46065 | Q35: =IFERROR(__xludf.DUMMYFUNCTION("""COMPUTED_VALUE"""),0.04) -> 0.04 | R35: =IFERROR(__xludf.DUMMYFUNCTION("""COMPUTED_VALUE"""),16.36) -> 16.36 | S35: =IFERROR(__xludf.DUMMYFUNCTION("""COMPUTED_VALUE"""),-0.12221745916049007) -> -0.12221746 | T35: =IFERROR(__xludf.DUMMYFUNCTION("""COMPUTED_VALUE"""),0.0073) -> 0.0073 | U35: =IFERROR(__xludf.DUMMYFUNCTION("""COMPUTED_VALUE"""),0.22299269945896666) -> 0.2229927 | V35: =IFERROR(__xludf.DUMMYFUNCTION("""COMPUTED_VALUE"""),"Trimestral") -> Trimestral | W35: =IFERROR(__xludf.DUMMYFUNCTION("""COMPUTED_VALUE"""),"Sinkable") -> Sinkable | X35: =IFERROR(__xludf.DUMMYFUNCTION("""COMPUTED_VALUE"""),"NY") -> NY | Y35: =IFERROR(__xludf.DUMMYFUNCTION("""COMPUTED_VALUE"""),1.0) -> 1 | Z35: =IFERROR(__xludf.DUMMYFUNCTION("""COMPUTED_VALUE"""),35.0) -> 35 | AA35: =IFERROR(__xludf.DUMMYFUNCTION("""COMPUTED_VALUE"""),1.0485156389696602) -> 1.0485156 | AF35: =IFERROR(__xludf.DUMMYFUNCTION("""COMPUTED_VALUE"""),"RCCMD") -> RCCMD | AG35: =IFERROR(__xludf.DUMMYFUNCTION("""COMPUTED_VALUE"""),"Arcor") -> Arcor | AH35: =IFERROR(__xludf.DUMMYFUNCTION("""COMPUTED_VALUE"""),45983.0) -> 45983 | AI35: =IFERROR(__xludf.DUMMYFUNCTION("""COMPUTED_VALUE"""),0.035) -> 0.035 | AJ35: =IFERROR(__xludf.DUMMYFUNCTION("""COMPUTED_VALUE"""),101.6) -> 101.6 | AK35: =IFERROR(__xludf.DUMMYFUNCTION("""COMPUTED_VALUE"""),0.01313900030921174) -> 0.013139 | AL35: =IFERROR(__xludf.DUMMYFUNCTION("""COMPUTED_VALUE"""),9.0E-4) -> 0.0009 | AM35: =IFERROR(__xludf.DUMMYFUNCTION("""COMPUTED_VALUE"""),0.12221955107719504) -> 0.12221955 | AN35: =IFERROR(__xludf.DUMMYFUNCTION("""COMPUTED_VALUE"""),"Semestral") -> Semestral | AO35: =IFERROR(__xludf.DUMMYFUNCTION("""COMPUTED_VALUE"""),"Bullet") -> Bullet | AP35: =IFERROR(__xludf.DUMMYFUNCTION("""COMPUTED_VALUE"""),"ARG") -> ARG | AQ35: =IFERROR(__xludf.DUMMYFUNCTION("""COMPUTED_VALUE"""),100.0) -> 100 | AR35: =IFERROR(__xludf.DUMMYFUNCTION("""COMPUTED_VALUE"""),45.0) -> 45 | AS35: =IFERROR(__xludf.DUMMYFUNCTION("""COMPUTED_VALUE"""),1.0025412273587455) -> 1.0025412
N36: =IFERROR(__xludf.DUMMYFUNCTION("""COMPUTED_VALUE"""),"MTCGD") -> MTCGD | O36: =IFERROR(__xludf.DUMMYFUNCTION("""COMPUTED_VALUE"""),"Mastellone") -> Mastellone | P36: =IFERROR(__xludf.DUMMYFUNCTION("""COMPUTED_VALUE"""),46203.0) -> 46203 | Q36: =IFERROR(__xludf.DUMMYFUNCTION("""COMPUTED_VALUE"""),0.1095) -> 0.1095 | R36: =IFERROR(__xludf.DUMMYFUNCTION("""COMPUTED_VALUE"""),101.5) -> 101.5 | S36: =IFERROR(__xludf.DUMMYFUNCTION("""COMPUTED_VALUE"""),0.09534594734110474) -> 0.095345947 | T36: =IFERROR(__xludf.DUMMYFUNCTION("""COMPUTED_VALUE"""),0.011899999999999999) -> 0.0119 | U36: =IFERROR(__xludf.DUMMYFUNCTION("""COMPUTED_VALUE"""),0.7127086800293023) -> 0.71270868 | V36: =IFERROR(__xludf.DUMMYFUNCTION("""COMPUTED_VALUE"""),"Trimestral") -> Trimestral | W36: =IFERROR(__xludf.DUMMYFUNCTION("""COMPUTED_VALUE"""),"Bullet") -> Bullet | X36: =IFERROR(__xludf.DUMMYFUNCTION("""COMPUTED_VALUE"""),"NY") -> NY | Y36: =IFERROR(__xludf.DUMMYFUNCTION("""COMPUTED_VALUE"""),1.0) -> 1 | Z36: =IFERROR(__xludf.DUMMYFUNCTION("""COMPUTED_VALUE"""),83.0) -> 83 | AA36: =IFERROR(__xludf.DUMMYFUNCTION("""COMPUTED_VALUE"""),1.0122290230494022) -> 1.012229 | AF36: =IFERROR(__xludf.DUMMYFUNCTION("""COMPUTED_VALUE"""),"YMCQD") -> YMCQD | AG36: =IFERROR(__xludf.DUMMYFUNCTION("""COMPUTED_VALUE"""),"YPF") -> YPF | AH36: =IFERROR(__xludf.DUMMYFUNCTION("""COMPUTED_VALUE"""),46066.0) -> 46066 | AI36: =IFERROR(__xludf.DUMMYFUNCTION("""COMPUTED_VALUE"""),0.05) -> 0.05 | AJ36: =IFERROR(__xludf.DUMMYFUNCTION("""COMPUTED_VALUE"""),102.15) -> 102.15 | AK36: =IFERROR(__xludf.DUMMYFUNCTION("""COMPUTED_VALUE"""),0.03484411957581255) -> 0.03484412 | AL36: =IFERROR(__xludf.DUMMYFUNCTION("""COMPUTED_VALUE"""),-0.0034000000000000002) -> -0.0034 | AM36: =IFERROR(__xludf.DUMMYFUNCTION("""COMPUTED_VALUE"""),0.3485143823001787) -> 0.34851438 | AN36: =IFERROR(__xludf.DUMMYFUNCTION("""COMPUTED_VALUE"""),"Semestral") -> Semestral | AO36: =IFERROR(__xludf.DUMMYFUNCTION("""COMPUTED_VALUE"""),"Bullet") -> Bullet | AP36: =IFERROR(__xludf.DUMMYFUNCTION("""COMPUTED_VALUE"""),"ARG") -> ARG | AQ36: =IFERROR(__xludf.DUMMYFUNCTION("""COMPUTED_VALUE"""),100.0) -> 100 | AR36: =IFERROR(__xludf.DUMMYFUNCTION("""COMPUTED_VALUE"""),66.0) -> 66 | AS36: =IFERROR(__xludf.DUMMYFUNCTION("""COMPUTED_VALUE"""),1.0052507414397414) -> 1.0052507
N37: =IFERROR(__xludf.DUMMYFUNCTION("""COMPUTED_VALUE"""),"MGC9D") -> MGC9D | O37: =IFERROR(__xludf.DUMMYFUNCTION("""COMPUTED_VALUE"""),"Pampa Energia") -> Pampa Energia | P37: =IFERROR(__xludf.DUMMYFUNCTION("""COMPUTED_VALUE"""),46364.0) -> 46364 | Q37: =IFERROR(__xludf.DUMMYFUNCTION("""COMPUTED_VALUE"""),0.095) -> 0.095 | R37: =IFERROR(__xludf.DUMMYFUNCTION("""COMPUTED_VALUE"""),71.2) -> 71.2 | S37: =IFERROR(__xludf.DUMMYFUNCTION("""COMPUTED_VALUE"""),0.04779948184699389) -> 0.047799482 | T37: =IFERROR(__xludf.DUMMYFUNCTION("""COMPUTED_VALUE"""),-0.0055000000000000005) -> -0.0055 | U37: =IFERROR(__xludf.DUMMYFUNCTION("""COMPUTED_VALUE"""),0.6604825150010593) -> 0.66048251 | V37: =IFERROR(__xludf.DUMMYFUNCTION("""COMPUTED_VALUE"""),"Semestral") -> Semestral | W37: =IFERROR(__xludf.DUMMYFUNCTION("""COMPUTED_VALUE"""),"Sinkable") -> Sinkable | X37: =IFERROR(__xludf.DUMMYFUNCTION("""COMPUTED_VALUE"""),"NY") -> NY | Y37: =IFERROR(__xludf.DUMMYFUNCTION("""COMPUTED_VALUE"""),1.0) -> 1 | Z37: =IFERROR(__xludf.DUMMYFUNCTION("""COMPUTED_VALUE"""),61.0) -> 61 | AA37: =IFERROR(__xludf.DUMMYFUNCTION("""COMPUTED_VALUE"""),1.029277921301921) -> 1.0292779 | AF37: =IFERROR(__xludf.DUMMYFUNCTION("""COMPUTED_VALUE"""),"CP34D") -> CP34D | AG37: =IFERROR(__xludf.DUMMYFUNCTION("""COMPUTED_VALUE"""),"CGC") -> CGC | AH37: =IFERROR(__xludf.DUMMYFUNCTION("""COMPUTED_VALUE"""),46076.0) -> 46076 | AI37: =IFERROR(__xludf.DUMMYFUNCTION("""COMPUTED_VALUE"""),0.07) -> 0.07 | AJ37: =IFERROR(__xludf.DUMMYFUNCTION("""COMPUTED_VALUE"""),94.4) -> 94.4 | AK37: =IFERROR(__xludf.DUMMYFUNCTION("""COMPUTED_VALUE"""),0.278852233744313) -> 0.27885223 | AL37: =IFERROR(__xludf.DUMMYFUNCTION("""COMPUTED_VALUE"""),-0.0063) -> -0.0063 | AM37: =IFERROR(__xludf.DUMMYFUNCTION("""COMPUTED_VALUE"""),0.3800679096048698) -> 0.38006791 | AN37: =IFERROR(__xludf.DUMMYFUNCTION("""COMPUTED_VALUE"""),"Semestral") -> Semestral | AO37: =IFERROR(__xludf.DUMMYFUNCTION("""COMPUTED_VALUE"""),"Bullet") -> Bullet | AP37: =IFERROR(__xludf.DUMMYFUNCTION("""COMPUTED_VALUE"""),"ARG") -> ARG | AQ37: =IFERROR(__xludf.DUMMYFUNCTION("""COMPUTED_VALUE"""),50.0) -> 50 | AR37: =IFERROR(__xludf.DUMMYFUNCTION("""COMPUTED_VALUE"""),138.0) -> 138 | AS37: =IFERROR(__xludf.DUMMYFUNCTION("""COMPUTED_VALUE"""),0.9355670802899889) -> 0.93556708
N38: =IFERROR(__xludf.DUMMYFUNCTION("""COMPUTED_VALUE"""),"PNDCD") -> PNDCD | O38: =IFERROR(__xludf.DUMMYFUNCTION("""COMPUTED_VALUE"""),"Pan American Energy") -> Pan American Energy | P38: =IFERROR(__xludf.DUMMYFUNCTION("""COMPUTED_VALUE"""),46507.0) -> 46507 | Q38: =IFERROR(__xludf.DUMMYFUNCTION("""COMPUTED_VALUE"""),0.0913) -> 0.0913 | R38: =IFERROR(__xludf.DUMMYFUNCTION("""COMPUTED_VALUE"""),86.5) -> 86.5 | S38: =IFERROR(__xludf.DUMMYFUNCTION("""COMPUTED_VALUE"""),0.03924871575088921) -> 0.039248716 | T38: =IFERROR(__xludf.DUMMYFUNCTION("""COMPUTED_VALUE"""),-0.017) -> -0.017 | U38: =IFERROR(__xludf.DUMMYFUNCTION("""COMPUTED_VALUE"""),0.7822434263638092) -> 0.78224343 | V38: =IFERROR(__xludf.DUMMYFUNCTION("""COMPUTED_VALUE"""),"Semestral") -> Semestral | W38: =IFERROR(__xludf.DUMMYFUNCTION("""COMPUTED_VALUE"""),"Sinkable") -> Sinkable | X38: =IFERROR(__xludf.DUMMYFUNCTION("""COMPUTED_VALUE"""),"NY") -> NY | Y38: =IFERROR(__xludf.DUMMYFUNCTION("""COMPUTED_VALUE"""),1000.0) -> 1000 | Z38: =IFERROR(__xludf.DUMMYFUNCTION("""COMPUTED_VALUE"""),22.0) -> 22 | AA38: =IFERROR(__xludf.DUMMYFUNCTION("""COMPUTED_VALUE"""),1.0386023893858438) -> 1.0386024 | AF38: =IFERROR(__xludf.DUMMYFUNCTION("""COMPUTED_VALUE"""),"LOC3D") -> LOC3D | AG38: =IFERROR(__xludf.DUMMYFUNCTION("""COMPUTED_VALUE"""),"Loma Negra") -> Loma Negra | AH38: =IFERROR(__xludf.DUMMYFUNCTION("""COMPUTED_VALUE"""),46092.0) -> 46092 | AI38: =IFERROR(__xludf.DUMMYFUNCTION("""COMPUTED_VALUE"""),0.0749) -> 0.0749 | AJ38: =IFERROR(__xludf.DUMMYFUNCTION("""COMPUTED_VALUE"""),102.5) -> 102.5 | AK38: =IFERROR(__xludf.DUMMYFUNCTION("""COMPUTED_VALUE"""),0.02839263666752153) -> 0.028392637 | AL38: =IFERROR(__xludf.DUMMYFUNCTION("""COMPUTED_VALUE"""),0.0138) -> 0.0138 | AM38: =IFERROR(__xludf.DUMMYFUNCTION("""COMPUTED_VALUE"""),0.42493073215633376) -> 0.42493073 | AN38: =IFERROR(__xludf.DUMMYFUNCTION("""COMPUTED_VALUE"""),"Semestral") -> Semestral | AO38: =IFERROR(__xludf.DUMMYFUNCTION("""COMPUTED_VALUE"""),"Bullet") -> Bullet | AP38: =IFERROR(__xludf.DUMMYFUNCTION("""COMPUTED_VALUE"""),"ARG") -> ARG | AQ38: =IFERROR(__xludf.DUMMYFUNCTION("""COMPUTED_VALUE"""),100.0) -> 100 | AR38: =IFERROR(__xludf.DUMMYFUNCTION("""COMPUTED_VALUE"""),154.0) -> 154 | AS38: =IFERROR(__xludf.DUMMYFUNCTION("""COMPUTED_VALUE"""),1.0191442484442812) -> 1.0191442
N39: =IFERROR(__xludf.DUMMYFUNCTION("""COMPUTED_VALUE"""),"YCAMD") -> YCAMD | O39: =IFERROR(__xludf.DUMMYFUNCTION("""COMPUTED_VALUE"""),"YPF") -> YPF | P39: =IFERROR(__xludf.DUMMYFUNCTION("""COMPUTED_VALUE"""),46589.0) -> 46589 | Q39: =IFERROR(__xludf.DUMMYFUNCTION("""COMPUTED_VALUE"""),0.0695) -> 0.0695 | R39: =IFERROR(__xludf.DUMMYFUNCTION("""COMPUTED_VALUE"""),102.25) -> 102.25 | S39: =IFERROR(__xludf.DUMMYFUNCTION("""COMPUTED_VALUE"""),0.06619237840504184) -> 0.066192378 | T39: =IFERROR(__xludf.DUMMYFUNCTION("""COMPUTED_VALUE"""),0.0) -> 0 | U39: =IFERROR(__xludf.DUMMYFUNCTION("""COMPUTED_VALUE"""),1.7036405613044903) -> 1.7036406 | V39: =IFERROR(__xludf.DUMMYFUNCTION("""COMPUTED_VALUE"""),"Semestral") -> Semestral | W39: =IFERROR(__xludf.DUMMYFUNCTION("""COMPUTED_VALUE"""),"Bullet") -> Bullet | X39: =IFERROR(__xludf.DUMMYFUNCTION("""COMPUTED_VALUE"""),"NY") -> NY | Y39: =IFERROR(__xludf.DUMMYFUNCTION("""COMPUTED_VALUE"""),10000.0) -> 10000 | Z39: =IFERROR(__xludf.DUMMYFUNCTION("""COMPUTED_VALUE"""),105.0) -> 105 | AA39: =IFERROR(__xludf.DUMMYFUNCTION("""COMPUTED_VALUE"""),1.006948243790349) -> 1.0069482 | AF39: =IFERROR(__xludf.DUMMYFUNCTION("""COMPUTED_VALUE"""),"NPCAD") -> NPCAD | AG39: =IFERROR(__xludf.DUMMYFUNCTION("""COMPUTED_VALUE"""),"Central Puerto") -> Central Puerto | AH39: =IFERROR(__xludf.DUMMYFUNCTION("""COMPUTED_VALUE"""),46095.0) -> 46095 | AI39: =IFERROR(__xludf.DUMMYFUNCTION("""COMPUTED_VALUE"""),0.07) -> 0.07 | AJ39: =IFERROR(__xludf.DUMMYFUNCTION("""COMPUTED_VALUE"""),101.55) -> 101.55 | AK39: =IFERROR(__xludf.DUMMYFUNCTION("""COMPUTED_VALUE"""),0.044798869890516506) -> 0.04479887 | AL39: =IFERROR(__xludf.DUMMYFUNCTION("""COMPUTED_VALUE"""),-0.0014000000000000002) -> -0.0014 | AM39: =IFERROR(__xludf.DUMMYFUNCTION("""COMPUTED_VALUE"""),0.4332206185697374) -> 0.43322062 | AN39: =IFERROR(__xludf.DUMMYFUNCTION("""COMPUTED_VALUE"""),"Semestral") -> Semestral | AO39: =IFERROR(__xludf.DUMMYFUNCTION("""COMPUTED_VALUE"""),"Bullet") -> Bullet | AP39: =IFERROR(__xludf.DUMMYFUNCTION("""COMPUTED_VALUE"""),"ARG") -> ARG | AQ39: =IFERROR(__xludf.DUMMYFUNCTION("""COMPUTED_VALUE"""),100.0) -> 100 | AR39: =IFERROR(__xludf.DUMMYFUNCTION("""COMPUTED_VALUE"""),157.0) -> 157 | AS39: =IFERROR(__xludf.DUMMYFUNCTION("""COMPUTED_VALUE"""),0.9763651450096147) -> 0.97636515
N40: =IFERROR(__xludf.DUMMYFUNCTION("""COMPUTED_VALUE"""),"GNCXD") -> GNCXD | O40: =IFERROR(__xludf.DUMMYFUNCTION("""COMPUTED_VALUE"""),"Genneia") -> Genneia | P40: =IFERROR(__xludf.DUMMYFUNCTION("""COMPUTED_VALUE"""),46632.0) -> 46632 | Q40: =IFERROR(__xludf.DUMMYFUNCTION("""COMPUTED_VALUE"""),0.0875) -> 0.0875 | R40: =IFERROR(__xludf.DUMMYFUNCTION("""COMPUTED_VALUE"""),40.89) -> 40.89 | S40: =IFERROR(__xludf.DUMMYFUNCTION("""COMPUTED_VALUE"""),0.07634798914958861) -> 0.076347989 | T40: =IFERROR(__xludf.DUMMYFUNCTION("""COMPUTED_VALUE"""),0.0070999999999999995) -> 0.0071 | U40: =IFERROR(__xludf.DUMMYFUNCTION("""COMPUTED_VALUE"""),1.1154498500735563) -> 1.1154499 | V40: =IFERROR(__xludf.DUMMYFUNCTION("""COMPUTED_VALUE"""),"Semestral") -> Semestral | W40: =IFERROR(__xludf.DUMMYFUNCTION("""COMPUTED_VALUE"""),"Sinkable") -> Sinkable | X40: =IFERROR(__xludf.DUMMYFUNCTION("""COMPUTED_VALUE"""),"NY") -> NY | Y40: =IFERROR(__xludf.DUMMYFUNCTION("""COMPUTED_VALUE"""),1000.0) -> 1000 | Z40: =IFERROR(__xludf.DUMMYFUNCTION("""COMPUTED_VALUE"""),145.0) -> 145 | AA40: =IFERROR(__xludf.DUMMYFUNCTION("""COMPUTED_VALUE"""),0.8105110292852472) -> 0.81051103 | AF40: =IFERROR(__xludf.DUMMYFUNCTION("""COMPUTED_VALUE"""),"TTC7D") -> TTC7D | AG40: =IFERROR(__xludf.DUMMYFUNCTION("""COMPUTED_VALUE"""),"Tecpetrol") -> Tecpetrol | AH40: =IFERROR(__xludf.DUMMYFUNCTION("""COMPUTED_VALUE"""),46134.0) -> 46134 | AI40: =IFERROR(__xludf.DUMMYFUNCTION("""COMPUTED_VALUE"""),0.0598) -> 0.0598 | AJ40: =IFERROR(__xludf.DUMMYFUNCTION("""COMPUTED_VALUE"""),103.5) -> 103.5 | AK40: =IFERROR(__xludf.DUMMYFUNCTION("""COMPUTED_VALUE"""),0.046591110618864895) -> 0.046591111 | AL40: =IFERROR(__xludf.DUMMYFUNCTION("""COMPUTED_VALUE"""),-9.0E-4) -> -0.0009 | AM40: =IFERROR(__xludf.DUMMYFUNCTION("""COMPUTED_VALUE"""),0.5268589050449201) -> 0.5268589 | AN40: =IFERROR(__xludf.DUMMYFUNCTION("""COMPUTED_VALUE"""),"Semestral") -> Semestral | AO40: =IFERROR(__xludf.DUMMYFUNCTION("""COMPUTED_VALUE"""),"Bullet") -> Bullet | AP40: =IFERROR(__xludf.DUMMYFUNCTION("""COMPUTED_VALUE"""),"ARG") -> ARG | AQ40: =IFERROR(__xludf.DUMMYFUNCTION("""COMPUTED_VALUE"""),1.0) -> 1 | AR40: =IFERROR(__xludf.DUMMYFUNCTION("""COMPUTED_VALUE"""),14.0) -> 14 | AS40: =IFERROR(__xludf.DUMMYFUNCTION("""COMPUTED_VALUE"""),1.0069542549164903) -> 1.0069543
N41: =IFERROR(__xludf.DUMMYFUNCTION("""COMPUTED_VALUE"""),"IRCFD") -> IRCFD | O41: =IFERROR(__xludf.DUMMYFUNCTION("""COMPUTED_VALUE"""),"Irsa") -> Irsa | P41: =IFERROR(__xludf.DUMMYFUNCTION("""COMPUTED_VALUE"""),46926.0) -> 46926 | Q41: =IFERROR(__xludf.DUMMYFUNCTION("""COMPUTED_VALUE"""),0.0875) -> 0.0875 | R41: =IFERROR(__xludf.DUMMYFUNCTION("""COMPUTED_VALUE"""),69.79) -> 69.79 | S41: =IFERROR(__xludf.DUMMYFUNCTION("""COMPUTED_VALUE"""),0.060872134275639526) -> 0.060872134 | T41: =IFERROR(__xludf.DUMMYFUNCTION("""COMPUTED_VALUE"""),-0.0012) -> -0.0012 | U41: =IFERROR(__xludf.DUMMYFUNCTION("""COMPUTED_VALUE"""),1.7631168587831665) -> 1.7631169 | V41: =IFERROR(__xludf.DUMMYFUNCTION("""COMPUTED_VALUE"""),"Semestral") -> Semestral | W41: =IFERROR(__xludf.DUMMYFUNCTION("""COMPUTED_VALUE"""),"Sinkable") -> Sinkable | X41: =IFERROR(__xludf.DUMMYFUNCTION("""COMPUTED_VALUE"""),"NY") -> NY | Y41: =IFERROR(__xludf.DUMMYFUNCTION("""COMPUTED_VALUE"""),1.0) -> 1 | Z41: =IFERROR(__xludf.DUMMYFUNCTION("""COMPUTED_VALUE"""),75.0) -> 75 | AA41: =IFERROR(__xludf.DUMMYFUNCTION("""COMPUTED_VALUE"""),1.0459810730148655) -> 1.0459811 | AF41: =IFERROR(__xludf.DUMMYFUNCTION("""COMPUTED_VALUE"""),"YMCVD") -> YMCVD | AG41: =IFERROR(__xludf.DUMMYFUNCTION("""COMPUTED_VALUE"""),"YPF") -> YPF | AH41: =IFERROR(__xludf.DUMMYFUNCTION("""COMPUTED_VALUE"""),46168.0) -> 46168 | AI41: =IFERROR(__xludf.DUMMYFUNCTION("""COMPUTED_VALUE"""),0.06) -> 0.06 | AJ41: =IFERROR(__xludf.DUMMYFUNCTION("""COMPUTED_VALUE"""),102.3) -> 102.3 | AK41: =IFERROR(__xludf.DUMMYFUNCTION("""COMPUTED_VALUE"""),0.03447512662747291) -> 0.034475127 | AL41: =IFERROR(__xludf.DUMMYFUNCTION("""COMPUTED_VALUE"""),-0.0019) -> -0.0019 | AM41: =IFERROR(__xludf.DUMMYFUNCTION("""COMPUTED_VALUE"""),0.6304917317972469) -> 0.63049173 | AN41: =IFERROR(__xludf.DUMMYFUNCTION("""COMPUTED_VALUE"""),"Trimestral") -> Trimestral | AO41: =IFERROR(__xludf.DUMMYFUNCTION("""COMPUTED_VALUE"""),"Bullet") -> Bullet | AP41: =IFERROR(__xludf.DUMMYFUNCTION("""COMPUTED_VALUE"""),"ARG") -> ARG | AQ41: =IFERROR(__xludf.DUMMYFUNCTION("""COMPUTED_VALUE"""),1.0) -> 1 | AR41: =IFERROR(__xludf.DUMMYFUNCTION("""COMPUTED_VALUE"""),51.0) -> 51 | AS41: =IFERROR(__xludf.DUMMYFUNCTION("""COMPUTED_VALUE"""),1.0159855245973008) -> 1.0159855
N42: =IFERROR(__xludf.DUMMYFUNCTION("""COMPUTED_VALUE"""),"CAC5D") -> CAC5D | O42: =IFERROR(__xludf.DUMMYFUNCTION("""COMPUTED_VALUE"""),"Capex") -> Capex | P42: =IFERROR(__xludf.DUMMYFUNCTION("""COMPUTED_VALUE"""),46990.0) -> 46990 | Q42: =IFERROR(__xludf.DUMMYFUNCTION("""COMPUTED_VALUE"""),0.0925) -> 0.0925 | R42: =IFERROR(__xludf.DUMMYFUNCTION("""COMPUTED_VALUE"""),75.72) -> 75.72 | S42: =IFERROR(__xludf.DUMMYFUNCTION("""COMPUTED_VALUE"""),0.09544429307870247) -> 0.095444293 | T42: =IFERROR(__xludf.DUMMYFUNCTION("""COMPUTED_VALUE"""),-0.0076) -> -0.0076 | U42: =IFERROR(__xludf.DUMMYFUNCTION("""COMPUTED_VALUE"""),1.5251915772927287) -> 1.5251916 | V42: =IFERROR(__xludf.DUMMYFUNCTION("""COMPUTED_VALUE"""),"Semestral") -> Semestral | W42: =IFERROR(__xludf.DUMMYFUNCTION("""COMPUTED_VALUE"""),"Sinkable") -> Sinkable | X42: =IFERROR(__xludf.DUMMYFUNCTION("""COMPUTED_VALUE"""),"NY") -> NY | Y42: =IFERROR(__xludf.DUMMYFUNCTION("""COMPUTED_VALUE"""),1.0) -> 1 | Z42: =IFERROR(__xludf.DUMMYFUNCTION("""COMPUTED_VALUE"""),140.0) -> 140 | AA42: =IFERROR(__xludf.DUMMYFUNCTION("""COMPUTED_VALUE"""),0.855479941745002) -> 0.85547994 | AF42: =IFERROR(__xludf.DUMMYFUNCTION("""COMPUTED_VALUE"""),"NBS1D") -> NBS1D | AG42: =IFERROR(__xludf.DUMMYFUNCTION("""COMPUTED_VALUE"""),"Balanz") -> Balanz | AH42: =IFERROR(__xludf.DUMMYFUNCTION("""COMPUTED_VALUE"""),46179.0) -> 46179 | AI42: =IFERROR(__xludf.DUMMYFUNCTION("""COMPUTED_VALUE"""),0.05) -> 0.05 | AJ42: =IFERROR(__xludf.DUMMYFUNCTION("""COMPUTED_VALUE"""),100.1) -> 100.1 | AK42: =IFERROR(__xludf.DUMMYFUNCTION("""COMPUTED_VALUE"""),0.049747183950032546) -> 0.049747184 | AL42: =IFERROR(__xludf.DUMMYFUNCTION("""COMPUTED_VALUE"""),9.0E-4) -> 0.0009 | AM42: =IFERROR(__xludf.DUMMYFUNCTION("""COMPUTED_VALUE"""),0.6608689911221886) -> 0.66086899 | AN42: =IFERROR(__xludf.DUMMYFUNCTION("""COMPUTED_VALUE"""),"Cuatrimestral") -> Cuatrimestral | AO42: =IFERROR(__xludf.DUMMYFUNCTION("""COMPUTED_VALUE"""),"Bullet") -> Bullet | AP42: =IFERROR(__xludf.DUMMYFUNCTION("""COMPUTED_VALUE"""),"ARG") -> ARG | AQ42: =IFERROR(__xludf.DUMMYFUNCTION("""COMPUTED_VALUE"""),500.0) -> 500 | AR42: =IFERROR(__xludf.DUMMYFUNCTION("""COMPUTED_VALUE"""),121.0) -> 121 | AS42: =IFERROR(__xludf.DUMMYFUNCTION("""COMPUTED_VALUE"""),0.9841481481481481) -> 0.98414815
N43: =IFERROR(__xludf.DUMMYFUNCTION("""COMPUTED_VALUE"""),"BYCHD") -> BYCHD | O43: =IFERROR(__xludf.DUMMYFUNCTION("""COMPUTED_VALUE"""),"Galicia") -> Galicia | P43: =IFERROR(__xludf.DUMMYFUNCTION("""COMPUTED_VALUE"""),47036.0) -> 47036 | Q43: =IFERROR(__xludf.DUMMYFUNCTION("""COMPUTED_VALUE"""),0.0775) -> 0.0775 | R43: =IFERROR(__xludf.DUMMYFUNCTION("""COMPUTED_VALUE"""),105.8) -> 105.8 | S43: =IFERROR(__xludf.DUMMYFUNCTION("""COMPUTED_VALUE"""),0.07149077584364663) -> 0.071490776 | T43: =IFERROR(__xludf.DUMMYFUNCTION("""COMPUTED_VALUE"""),-0.0014000000000000002) -> -0.0014 | U43: =IFERROR(__xludf.DUMMYFUNCTION("""COMPUTED_VALUE"""),2.6701754812302956) -> 2.6701755 | V43: =IFERROR(__xludf.DUMMYFUNCTION("""COMPUTED_VALUE"""),"Semestral") -> Semestral | W43: =IFERROR(__xludf.DUMMYFUNCTION("""COMPUTED_VALUE"""),"Bullet") -> Bullet | X43: =IFERROR(__xludf.DUMMYFUNCTION("""COMPUTED_VALUE"""),"NY") -> NY | Y43: =IFERROR(__xludf.DUMMYFUNCTION("""COMPUTED_VALUE"""),2000.0) -> 2000 | Z43: =IFERROR(__xludf.DUMMYFUNCTION("""COMPUTED_VALUE"""),2.0) -> 2 | AA43: =IFERROR(__xludf.DUMMYFUNCTION("""COMPUTED_VALUE"""),1.0181098889349247) -> 1.0181099 | AF43: =IFERROR(__xludf.DUMMYFUNCTION("""COMPUTED_VALUE"""),"DNC3D") -> DNC3D | AG43: =IFERROR(__xludf.DUMMYFUNCTION("""COMPUTED_VALUE"""),"Edenor") -> Edenor | AH43: =IFERROR(__xludf.DUMMYFUNCTION("""COMPUTED_VALUE"""),46348.0) -> 46348 | AI43: =IFERROR(__xludf.DUMMYFUNCTION("""COMPUTED_VALUE"""),0.0975) -> 0.0975 | AJ43: =IFERROR(__xludf.DUMMYFUNCTION("""COMPUTED_VALUE"""),96.4) -> 96.4 | AK43: =IFERROR(__xludf.DUMMYFUNCTION("""COMPUTED_VALUE"""),0.17933486867534926) -> 0.17933487 | AL43: =IFERROR(__xludf.DUMMYFUNCTION("""COMPUTED_VALUE"""),-0.026099999999999998) -> -0.0261 | AM43: =IFERROR(__xludf.DUMMYFUNCTION("""COMPUTED_VALUE"""),1.059574168462664) -> 1.0595742 | AN43: =IFERROR(__xludf.DUMMYFUNCTION("""COMPUTED_VALUE"""),"Semestral") -> Semestral | AO43: =IFERROR(__xludf.DUMMYFUNCTION("""COMPUTED_VALUE"""),"Bullet") -> Bullet | AP43: =IFERROR(__xludf.DUMMYFUNCTION("""COMPUTED_VALUE"""),"ARG") -> ARG | AQ43: =IFERROR(__xludf.DUMMYFUNCTION("""COMPUTED_VALUE"""),1.0) -> 1 | AR43: =IFERROR(__xludf.DUMMYFUNCTION("""COMPUTED_VALUE"""),45.0) -> 45 | AS43: =IFERROR(__xludf.DUMMYFUNCTION("""COMPUTED_VALUE"""),0.9292486465073287) -> 0.92924865
N44: =IFERROR(__xludf.DUMMYFUNCTION("""COMPUTED_VALUE"""),"BACGD") -> BACGD | O44: =IFERROR(__xludf.DUMMYFUNCTION("""COMPUTED_VALUE"""),"Banco Macro") -> Banco Macro | P44: =IFERROR(__xludf.DUMMYFUNCTION("""COMPUTED_VALUE"""),47292.0) -> 47292 | Q44: =IFERROR(__xludf.DUMMYFUNCTION("""COMPUTED_VALUE"""),0.08) -> 0.08 | R44: =IFERROR(__xludf.DUMMYFUNCTION("""COMPUTED_VALUE"""),102.25) -> 102.25 | S44: =IFERROR(__xludf.DUMMYFUNCTION("""COMPUTED_VALUE"""),0.08185903892745386) -> 0.081859039 | T44: =IFERROR(__xludf.DUMMYFUNCTION("""COMPUTED_VALUE"""),0.0024) -> 0.0024 | U44: =IFERROR(__xludf.DUMMYFUNCTION("""COMPUTED_VALUE"""),3.2393086080317754) -> 3.2393086 | V44: =IFERROR(__xludf.DUMMYFUNCTION("""COMPUTED_VALUE"""),"Semestral") -> Semestral | W44: =IFERROR(__xludf.DUMMYFUNCTION("""COMPUTED_VALUE"""),"Bullet") -> Bullet | X44: =IFERROR(__xludf.DUMMYFUNCTION("""COMPUTED_VALUE"""),"NY") -> NY | Y44: =IFERROR(__xludf.DUMMYFUNCTION("""COMPUTED_VALUE"""),1000.0) -> 1000 | Z44: =IFERROR(__xludf.DUMMYFUNCTION("""COMPUTED_VALUE"""),76.0) -> 76 | AA44: =IFERROR(__xludf.DUMMYFUNCTION("""COMPUTED_VALUE"""),0.99853515625) -> 0.99853516 | AF44: =IFERROR(__xludf.DUMMYFUNCTION("""COMPUTED_VALUE"""),"ZZC1D") -> ZZC1D | AG44: =IFERROR(__xludf.DUMMYFUNCTION("""COMPUTED_VALUE"""),"Camuzzi") -> Camuzzi | AH44: =IFERROR(__xludf.DUMMYFUNCTION("""COMPUTED_VALUE"""),46439.0) -> 46439 | AI44: =IFERROR(__xludf.DUMMYFUNCTION("""COMPUTED_VALUE"""),0.0795) -> 0.0795 | AJ44: =IFERROR(__xludf.DUMMYFUNCTION("""COMPUTED_VALUE"""),98.99) -> 98.99 | AK44: =IFERROR(__xludf.DUMMYFUNCTION("""COMPUTED_VALUE"""),0.09820802889139084) -> 0.098208029 | AL44: =IFERROR(__xludf.DUMMYFUNCTION("""COMPUTED_VALUE"""),0.0111) -> 0.0111 | AM44: =IFERROR(__xludf.DUMMYFUNCTION("""COMPUTED_VALUE"""),1.3281283170595968) -> 1.3281283 | AN44: =IFERROR(__xludf.DUMMYFUNCTION("""COMPUTED_VALUE"""),"Semestral") -> Semestral | AO44: =IFERROR(__xludf.DUMMYFUNCTION("""COMPUTED_VALUE"""),"Bullet") -> Bullet | AP44: =IFERROR(__xludf.DUMMYFUNCTION("""COMPUTED_VALUE"""),"ARG") -> ARG | AQ44: =IFERROR(__xludf.DUMMYFUNCTION("""COMPUTED_VALUE"""),100.0) -> 100 | AR44: =IFERROR(__xludf.DUMMYFUNCTION("""COMPUTED_VALUE"""),136.0) -> 136 | AS44: =IFERROR(__xludf.DUMMYFUNCTION("""COMPUTED_VALUE"""),0.979446753891007) -> 0.97944675
N45: =IFERROR(__xludf.DUMMYFUNCTION("""COMPUTED_VALUE"""),"YMCID") -> YMCID | O45: =IFERROR(__xludf.DUMMYFUNCTION("""COMPUTED_VALUE"""),"YPF") -> YPF | P45: =IFERROR(__xludf.DUMMYFUNCTION("""COMPUTED_VALUE"""),47299.0) -> 47299 | Q45: =IFERROR(__xludf.DUMMYFUNCTION("""COMPUTED_VALUE"""),0.09) -> 0.09 | R45: =IFERROR(__xludf.DUMMYFUNCTION("""COMPUTED_VALUE"""),106.95) -> 106.95 | S45: =IFERROR(__xludf.DUMMYFUNCTION("""COMPUTED_VALUE"""),0.06887414421954087) -> 0.068874144 | T45: =IFERROR(__xludf.DUMMYFUNCTION("""COMPUTED_VALUE"""),0.0042) -> 0.0042 | U45: =IFERROR(__xludf.DUMMYFUNCTION("""COMPUTED_VALUE"""),2.028662833438036) -> 2.0286628 | V45: =IFERROR(__xludf.DUMMYFUNCTION("""COMPUTED_VALUE"""),"Semestral") -> Semestral | W45: =IFERROR(__xludf.DUMMYFUNCTION("""COMPUTED_VALUE"""),"Sinkable") -> Sinkable | X45: =IFERROR(__xludf.DUMMYFUNCTION("""COMPUTED_VALUE"""),"NY") -> NY | Y45: =IFERROR(__xludf.DUMMYFUNCTION("""COMPUTED_VALUE"""),1.0) -> 1 | Z45: =IFERROR(__xludf.DUMMYFUNCTION("""COMPUTED_VALUE"""),83.0) -> 83 | AA45: =IFERROR(__xludf.DUMMYFUNCTION("""COMPUTED_VALUE"""),1.0431602048280906) -> 1.0431602 | AF45: =IFERROR(__xludf.DUMMYFUNCTION("""COMPUTED_VALUE"""),"IRCJD") -> IRCJD | AG45: =IFERROR(__xludf.DUMMYFUNCTION("""COMPUTED_VALUE"""),"IRSA") -> IRSA | AH45: =IFERROR(__xludf.DUMMYFUNCTION("""COMPUTED_VALUE"""),46446.0) -> 46446 | AI45: =IFERROR(__xludf.DUMMYFUNCTION("""COMPUTED_VALUE"""),0.07) -> 0.07 | AJ45: =IFERROR(__xludf.DUMMYFUNCTION("""COMPUTED_VALUE"""),101.5) -> 101.5 | AK45: =IFERROR(__xludf.DUMMYFUNCTION("""COMPUTED_VALUE"""),0.06566631506126516) -> 0.065666315 | AL45: =IFERROR(__xludf.DUMMYFUNCTION("""COMPUTED_VALUE"""),0.0034000000000000002) -> 0.0034 | AM45: =IFERROR(__xludf.DUMMYFUNCTION("""COMPUTED_VALUE"""),1.3557767620899839) -> 1.3557768 | AN45: =IFERROR(__xludf.DUMMYFUNCTION("""COMPUTED_VALUE"""),"Semestral") -> Semestral | AO45: =IFERROR(__xludf.DUMMYFUNCTION("""COMPUTED_VALUE"""),"Bullet") -> Bullet | AP45: =IFERROR(__xludf.DUMMYFUNCTION("""COMPUTED_VALUE"""),"ARG") -> ARG | AQ45: =IFERROR(__xludf.DUMMYFUNCTION("""COMPUTED_VALUE"""),100.0) -> 100 | AR45: =IFERROR(__xludf.DUMMYFUNCTION("""COMPUTED_VALUE"""),143.0) -> 143 | AS45: =IFERROR(__xludf.DUMMYFUNCTION("""COMPUTED_VALUE"""),1.0068897102788499) -> 1.0068897
N46: =IFERROR(__xludf.DUMMYFUNCTION("""COMPUTED_VALUE"""),"DNC7D") -> DNC7D | O46: =IFERROR(__xludf.DUMMYFUNCTION("""COMPUTED_VALUE"""),"Edenor") -> Edenor | P46: =IFERROR(__xludf.DUMMYFUNCTION("""COMPUTED_VALUE"""),47780.0) -> 47780 | Q46: =IFERROR(__xludf.DUMMYFUNCTION("""COMPUTED_VALUE"""),0.0975) -> 0.0975 | R46: =IFERROR(__xludf.DUMMYFUNCTION("""COMPUTED_VALUE"""),100.45) -> 100.45 | S46: =IFERROR(__xludf.DUMMYFUNCTION("""COMPUTED_VALUE"""),0.11324817794294945) -> 0.11324818 | T46: =IFERROR(__xludf.DUMMYFUNCTION("""COMPUTED_VALUE"""),-0.0024) -> -0.0024 | U46: =IFERROR(__xludf.DUMMYFUNCTION("""COMPUTED_VALUE"""),3.2704911426029253) -> 3.2704911 | V46: =IFERROR(__xludf.DUMMYFUNCTION("""COMPUTED_VALUE"""),"Semestral") -> Semestral | W46: =IFERROR(__xludf.DUMMYFUNCTION("""COMPUTED_VALUE"""),"Sinkable") -> Sinkable | X46: =IFERROR(__xludf.DUMMYFUNCTION("""COMPUTED_VALUE"""),"NY") -> NY | Y46: =IFERROR(__xludf.DUMMYFUNCTION("""COMPUTED_VALUE"""),100.0) -> 100 | Z46: =IFERROR(__xludf.DUMMYFUNCTION("""COMPUTED_VALUE"""),16.0) -> 16 | AA46: =IFERROR(__xludf.DUMMYFUNCTION("""COMPUTED_VALUE"""),0.9607843137254902) -> 0.96078431 | AF46: =IFERROR(__xludf.DUMMYFUNCTION("""COMPUTED_VALUE"""),"LMS8D") -> LMS8D | AG46: =IFERROR(__xludf.DUMMYFUNCTION("""COMPUTED_VALUE"""),"Aluar") -> Aluar | AH46: =IFERROR(__xludf.DUMMYFUNCTION("""COMPUTED_VALUE"""),46467.0) -> 46467 | AI46: =IFERROR(__xludf.DUMMYFUNCTION("""COMPUTED_VALUE"""),0.0625) -> 0.0625 | AJ46: =IFERROR(__xludf.DUMMYFUNCTION("""COMPUTED_VALUE"""),104.65) -> 104.65 | AK46: =IFERROR(__xludf.DUMMYFUNCTION("""COMPUTED_VALUE"""),0.03777120130206783) -> 0.037771201 | AL46: =IFERROR(__xludf.DUMMYFUNCTION("""COMPUTED_VALUE"""),0.0356) -> 0.0356 | AM46: =IFERROR(__xludf.DUMMYFUNCTION("""COMPUTED_VALUE"""),1.040752340099151) -> 1.0407523 | AN46: =IFERROR(__xludf.DUMMYFUNCTION("""COMPUTED_VALUE"""),"Trimestral") -> Trimestral | AO46: =IFERROR(__xludf.DUMMYFUNCTION("""COMPUTED_VALUE"""),"Sinkable") -> Sinkable | AP46: =IFERROR(__xludf.DUMMYFUNCTION("""COMPUTED_VALUE"""),"ARG") -> ARG | AQ46: =IFERROR(__xludf.DUMMYFUNCTION("""COMPUTED_VALUE"""),50.0) -> 50 | AR46: =IFERROR(__xludf.DUMMYFUNCTION("""COMPUTED_VALUE"""),-17.0) -> -17 | AS46: =IFERROR(__xludf.DUMMYFUNCTION("""COMPUTED_VALUE"""),1.0432843974052577) -> 1.0432844
N47: =IFERROR(__xludf.DUMMYFUNCTION("""COMPUTED_VALUE"""),"RUCDD") -> RUCDD | O47: =IFERROR(__xludf.DUMMYFUNCTION("""COMPUTED_VALUE"""),"MSU Energy") -> MSU Energy | P47: =IFERROR(__xludf.DUMMYFUNCTION("""COMPUTED_VALUE"""),47822.0) -> 47822 | Q47: =IFERROR(__xludf.DUMMYFUNCTION("""COMPUTED_VALUE"""),0.0975) -> 0.0975 | R47: =IFERROR(__xludf.DUMMYFUNCTION("""COMPUTED_VALUE"""),91.2) -> 91.2 | S47: =IFERROR(__xludf.DUMMYFUNCTION("""COMPUTED_VALUE"""),0.1381500807351918) -> 0.13815008 | T47: =IFERROR(__xludf.DUMMYFUNCTION("""COMPUTED_VALUE"""),-0.013999999999999999) -> -0.014 | U47: =IFERROR(__xludf.DUMMYFUNCTION("""COMPUTED_VALUE"""),3.629989032153328) -> 3.629989 | V47: =IFERROR(__xludf.DUMMYFUNCTION("""COMPUTED_VALUE"""),"Semestral") -> Semestral | W47: =IFERROR(__xludf.DUMMYFUNCTION("""COMPUTED_VALUE"""),"Sinkable") -> Sinkable | X47: =IFERROR(__xludf.DUMMYFUNCTION("""COMPUTED_VALUE"""),"NY") -> NY | Y47: =IFERROR(__xludf.DUMMYFUNCTION("""COMPUTED_VALUE"""),1.0) -> 1 | Z47: =IFERROR(__xludf.DUMMYFUNCTION("""COMPUTED_VALUE"""),58.0) -> 58 | AA47: =IFERROR(__xludf.DUMMYFUNCTION("""COMPUTED_VALUE"""),0.8819049921431162) -> 0.88190499 | AF47: =IFERROR(__xludf.DUMMYFUNCTION("""COMPUTED_VALUE"""),"OTS2D") -> OTS2D | AG47: =IFERROR(__xludf.DUMMYFUNCTION("""COMPUTED_VALUE"""),"OilTanking") -> OilTanking | AH47: =IFERROR(__xludf.DUMMYFUNCTION("""COMPUTED_VALUE"""),46501.0) -> 46501 | AI47: =IFERROR(__xludf.DUMMYFUNCTION("""COMPUTED_VALUE"""),0.07) -> 0.07 | AJ47: =IFERROR(__xludf.DUMMYFUNCTION("""COMPUTED_VALUE"""),101.5) -> 101.5 | AK47: =IFERROR(__xludf.DUMMYFUNCTION("""COMPUTED_VALUE"""),0.0716396132529734) -> 0.071639613 | AL47: =IFERROR(__xludf.DUMMYFUNCTION("""COMPUTED_VALUE"""),0.0049) -> 0.0049 | AM47: =IFERROR(__xludf.DUMMYFUNCTION("""COMPUTED_VALUE"""),1.4700307559006967) -> 1.4700308 | AN47: =IFERROR(__xludf.DUMMYFUNCTION("""COMPUTED_VALUE"""),"Semestral") -> Semestral | AO47: =IFERROR(__xludf.DUMMYFUNCTION("""COMPUTED_VALUE"""),"Bullet") -> Bullet | AP47: =IFERROR(__xludf.DUMMYFUNCTION("""COMPUTED_VALUE"""),"ARG") -> ARG | AQ47: =IFERROR(__xludf.DUMMYFUNCTION("""COMPUTED_VALUE"""),1.0) -> 1 | AR47: =IFERROR(__xludf.DUMMYFUNCTION("""COMPUTED_VALUE"""),16.0) -> 16 | AS47: =IFERROR(__xludf.DUMMYFUNCTION("""COMPUTED_VALUE"""),1.0002294878371447) -> 1.0002295
N48: =IFERROR(__xludf.DUMMYFUNCTION("""COMPUTED_VALUE"""),"TLCMD") -> TLCMD | O48: =IFERROR(__xludf.DUMMYFUNCTION("""COMPUTED_VALUE"""),"Telecom") -> Telecom | P48: =IFERROR(__xludf.DUMMYFUNCTION("""COMPUTED_VALUE"""),48047.0) -> 48047 | Q48: =IFERROR(__xludf.DUMMYFUNCTION("""COMPUTED_VALUE"""),0.095) -> 0.095 | R48: =IFERROR(__xludf.DUMMYFUNCTION("""COMPUTED_VALUE"""),103.7) -> 103.7 | S48: =IFERROR(__xludf.DUMMYFUNCTION("""COMPUTED_VALUE"""),0.0928674814932401) -> 0.092867481 | T48: =IFERROR(__xludf.DUMMYFUNCTION("""COMPUTED_VALUE"""),-0.0028000000000000004) -> -0.0028 | U48: =IFERROR(__xludf.DUMMYFUNCTION("""COMPUTED_VALUE"""),3.8979568160861335) -> 3.8979568 | V48: =IFERROR(__xludf.DUMMYFUNCTION("""COMPUTED_VALUE"""),"Semestral") -> Semestral | W48: =IFERROR(__xludf.DUMMYFUNCTION("""COMPUTED_VALUE"""),"Sinkable") -> Sinkable | X48: =IFERROR(__xludf.DUMMYFUNCTION("""COMPUTED_VALUE"""),"NY") -> NY | Y48: =IFERROR(__xludf.DUMMYFUNCTION("""COMPUTED_VALUE"""),1000.0) -> 1000 | Z48: =IFERROR(__xludf.DUMMYFUNCTION("""COMPUTED_VALUE"""),102.0) -> 102 | AA48: =IFERROR(__xludf.DUMMYFUNCTION("""COMPUTED_VALUE"""),1.014773638501162) -> 1.0147736 | AF48: =IFERROR(__xludf.DUMMYFUNCTION("""COMPUTED_VALUE"""),"YM37D") -> YM37D | AG48: =IFERROR(__xludf.DUMMYFUNCTION("""COMPUTED_VALUE"""),"YPF") -> YPF | AH48: =IFERROR(__xludf.DUMMYFUNCTION("""COMPUTED_VALUE"""),46514.0) -> 46514 | AI48: =IFERROR(__xludf.DUMMYFUNCTION("""COMPUTED_VALUE"""),0.07) -> 0.07 | AJ48: =IFERROR(__xludf.DUMMYFUNCTION("""COMPUTED_VALUE"""),103.4) -> 103.4 | AK48: =IFERROR(__xludf.DUMMYFUNCTION("""COMPUTED_VALUE"""),0.056351938054802604) -> 0.056351938 | AL48: =IFERROR(__xludf.DUMMYFUNCTION("""COMPUTED_VALUE"""),-9.0E-4) -> -0.0009 | AM48: =IFERROR(__xludf.DUMMYFUNCTION("""COMPUTED_VALUE"""),1.508101843380355) -> 1.5081018 | AN48: =IFERROR(__xludf.DUMMYFUNCTION("""COMPUTED_VALUE"""),"Trimestral") -> Trimestral | AO48: =IFERROR(__xludf.DUMMYFUNCTION("""COMPUTED_VALUE"""),"Bullet") -> Bullet | AP48: =IFERROR(__xludf.DUMMYFUNCTION("""COMPUTED_VALUE"""),"ARG") -> ARG | AQ48: =IFERROR(__xludf.DUMMYFUNCTION("""COMPUTED_VALUE"""),100.0) -> 100 | AR48: =IFERROR(__xludf.DUMMYFUNCTION("""COMPUTED_VALUE"""),30.0) -> 30 | AS48: =IFERROR(__xludf.DUMMYFUNCTION("""COMPUTED_VALUE"""),1.021656154408381) -> 1.0216562
N49: =IFERROR(__xludf.DUMMYFUNCTION("""COMPUTED_VALUE"""),"TSC3D") -> TSC3D | O49: =IFERROR(__xludf.DUMMYFUNCTION("""COMPUTED_VALUE"""),"TGS") -> TGS | P49: =IFERROR(__xludf.DUMMYFUNCTION("""COMPUTED_VALUE"""),48053.0) -> 48053 | Q49: =IFERROR(__xludf.DUMMYFUNCTION("""COMPUTED_VALUE"""),0.085) -> 0.085 | R49: =IFERROR(__xludf.DUMMYFUNCTION("""COMPUTED_VALUE"""),107.2) -> 107.2 | S49: =IFERROR(__xludf.DUMMYFUNCTION("""COMPUTED_VALUE"""),0.07462369421868527) -> 0.074623694 | T49: =IFERROR(__xludf.DUMMYFUNCTION("""COMPUTED_VALUE"""),-0.0046) -> -0.0046 | U49: =IFERROR(__xludf.DUMMYFUNCTION("""COMPUTED_VALUE"""),4.690068652262308) -> 4.6900687 | V49: =IFERROR(__xludf.DUMMYFUNCTION("""COMPUTED_VALUE"""),"Semestral") -> Semestral | W49: =IFERROR(__xludf.DUMMYFUNCTION("""COMPUTED_VALUE"""),"Bullet") -> Bullet | X49: =IFERROR(__xludf.DUMMYFUNCTION("""COMPUTED_VALUE"""),"NY") -> NY | Y49: =IFERROR(__xludf.DUMMYFUNCTION("""COMPUTED_VALUE"""),10000.0) -> 10000 | Z49: =IFERROR(__xludf.DUMMYFUNCTION("""COMPUTED_VALUE"""),108.0) -> 108 | AA49: =IFERROR(__xludf.DUMMYFUNCTION("""COMPUTED_VALUE"""),1.052858448485179) -> 1.0528584 | AF49: =IFERROR(__xludf.DUMMYFUNCTION("""COMPUTED_VALUE"""),"RCCRD") -> RCCRD | AG49: =IFERROR(__xludf.DUMMYFUNCTION("""COMPUTED_VALUE"""),"Arcor") -> Arcor | AH49: =IFERROR(__xludf.DUMMYFUNCTION("""COMPUTED_VALUE"""),46516.0) -> 46516 | AI49: =IFERROR(__xludf.DUMMYFUNCTION("""COMPUTED_VALUE"""),0.0675) -> 0.0675 | AJ49: =IFERROR(__xludf.DUMMYFUNCTION("""COMPUTED_VALUE"""),103.75) -> 103.75 | AK49: =IFERROR(__xludf.DUMMYFUNCTION("""COMPUTED_VALUE"""),0.06219173015559117) -> 0.06219173 | AL49: =IFERROR(__xludf.DUMMYFUNCTION("""COMPUTED_VALUE"""),0.0053) -> 0.0053 | AM49: =IFERROR(__xludf.DUMMYFUNCTION("""COMPUTED_VALUE"""),1.5043250393367078) -> 1.504325 | AN49: =IFERROR(__xludf.DUMMYFUNCTION("""COMPUTED_VALUE"""),"Semestral") -> Semestral | AO49: =IFERROR(__xludf.DUMMYFUNCTION("""COMPUTED_VALUE"""),"Bullet") -> Bullet | AP49: =IFERROR(__xludf.DUMMYFUNCTION("""COMPUTED_VALUE"""),"ARG") -> ARG | AQ49: =IFERROR(__xludf.DUMMYFUNCTION("""COMPUTED_VALUE"""),100.0) -> 100 | AR49: =IFERROR(__xludf.DUMMYFUNCTION("""COMPUTED_VALUE"""),32.0) -> 32 | AS49: =IFERROR(__xludf.DUMMYFUNCTION("""COMPUTED_VALUE"""),1.008952181761262) -> 1.0089522
N50: =IFERROR(__xludf.DUMMYFUNCTION("""COMPUTED_VALUE"""),"ARC1D") -> ARC1D | O50: =IFERROR(__xludf.DUMMYFUNCTION("""COMPUTED_VALUE"""),"Aeropuertos 2000") -> Aeropuertos 2000 | P50: =IFERROR(__xludf.DUMMYFUNCTION("""COMPUTED_VALUE"""),48061.0) -> 48061 | Q50: =IFERROR(__xludf.DUMMYFUNCTION("""COMPUTED_VALUE"""),0.085) -> 0.085 | R50: =IFERROR(__xludf.DUMMYFUNCTION("""COMPUTED_VALUE"""),106.75) -> 106.75 | S50: =IFERROR(__xludf.DUMMYFUNCTION("""COMPUTED_VALUE"""),0.0706169294415442) -> 0.070616929 | T50: =IFERROR(__xludf.DUMMYFUNCTION("""COMPUTED_VALUE"""),-0.0161) -> -0.0161 | U50: =IFERROR(__xludf.DUMMYFUNCTION("""COMPUTED_VALUE"""),3.2122134385327046) -> 3.2122134 | V50: =IFERROR(__xludf.DUMMYFUNCTION("""COMPUTED_VALUE"""),"Trimestral") -> Trimestral | W50: =IFERROR(__xludf.DUMMYFUNCTION("""COMPUTED_VALUE"""),"Sinkable") -> Sinkable | X50: =IFERROR(__xludf.DUMMYFUNCTION("""COMPUTED_VALUE"""),"NY") -> NY | Y50: =IFERROR(__xludf.DUMMYFUNCTION("""COMPUTED_VALUE"""),1000.0) -> 1000 | Z50: =IFERROR(__xludf.DUMMYFUNCTION("""COMPUTED_VALUE"""),24.0) -> 24 | AA50: =IFERROR(__xludf.DUMMYFUNCTION("""COMPUTED_VALUE"""),1.0503874379894225) -> 1.0503874 | AF50: =IFERROR(__xludf.DUMMYFUNCTION("""COMPUTED_VALUE"""),"CIC9D") -> CIC9D | AG50: =IFERROR(__xludf.DUMMYFUNCTION("""COMPUTED_VALUE"""),"CNH Industrial") -> CNH Industrial | AH50: =IFERROR(__xludf.DUMMYFUNCTION("""COMPUTED_VALUE"""),46528.0) -> 46528 | AI50: =IFERROR(__xludf.DUMMYFUNCTION("""COMPUTED_VALUE"""),0.0825) -> 0.0825 | AJ50: =IFERROR(__xludf.DUMMYFUNCTION("""COMPUTED_VALUE"""),100.0) -> 100 | AK50: =IFERROR(__xludf.DUMMYFUNCTION("""COMPUTED_VALUE"""),0.1070626142170394) -> 0.10706261 | AL50: =IFERROR(__xludf.DUMMYFUNCTION("""COMPUTED_VALUE"""),0.0) -> 0 | AM50: =IFERROR(__xludf.DUMMYFUNCTION("""COMPUTED_VALUE"""),1.5127639625766744) -> 1.512764 | AN50: =IFERROR(__xludf.DUMMYFUNCTION("""COMPUTED_VALUE"""),"Semestral") -> Semestral | AO50: =IFERROR(__xludf.DUMMYFUNCTION("""COMPUTED_VALUE"""),"Bullet") -> Bullet | AP50: =IFERROR(__xludf.DUMMYFUNCTION("""COMPUTED_VALUE"""),"ARG") -> ARG | AQ50: =IFERROR(__xludf.DUMMYFUNCTION("""COMPUTED_VALUE"""),100.0) -> 100 | AR50: =IFERROR(__xludf.DUMMYFUNCTION("""COMPUTED_VALUE"""),44.0) -> 44 | AS50: =IFERROR(__xludf.DUMMYFUNCTION("""COMPUTED_VALUE"""),0.9691144550722522) -> 0.96911446
N51: =IFERROR(__xludf.DUMMYFUNCTION("""COMPUTED_VALUE"""),"MGCMD") -> MGCMD | O51: =IFERROR(__xludf.DUMMYFUNCTION("""COMPUTED_VALUE"""),"Pampa Energia") -> Pampa Energia | P51: =IFERROR(__xludf.DUMMYFUNCTION("""COMPUTED_VALUE"""),48101.0) -> 48101 | Q51: =IFERROR(__xludf.DUMMYFUNCTION("""COMPUTED_VALUE"""),0.0795) -> 0.0795 | R51: =IFERROR(__xludf.DUMMYFUNCTION("""COMPUTED_VALUE"""),103.7) -> 103.7 | S51: =IFERROR(__xludf.DUMMYFUNCTION("""COMPUTED_VALUE"""),0.07441493850747857) -> 0.074414939 | T51: =IFERROR(__xludf.DUMMYFUNCTION("""COMPUTED_VALUE"""),0.0019) -> 0.0019 | U51: =IFERROR(__xludf.DUMMYFUNCTION("""COMPUTED_VALUE"""),4.8671100069722595) -> 4.86711 | V51: =IFERROR(__xludf.DUMMYFUNCTION("""COMPUTED_VALUE"""),"Semestral") -> Semestral | W51: =IFERROR(__xludf.DUMMYFUNCTION("""COMPUTED_VALUE"""),"Bullet") -> Bullet | X51: =IFERROR(__xludf.DUMMYFUNCTION("""COMPUTED_VALUE"""),"NY") -> NY | Y51: =IFERROR(__xludf.DUMMYFUNCTION("""COMPUTED_VALUE"""),10000.0) -> 10000 | Z51: =IFERROR(__xludf.DUMMYFUNCTION("""COMPUTED_VALUE"""),153.0) -> 153 | AA51: =IFERROR(__xludf.DUMMYFUNCTION("""COMPUTED_VALUE"""),0.9904134283633586) -> 0.99041343 | AF51: =IFERROR(__xludf.DUMMYFUNCTION("""COMPUTED_VALUE"""),"HJCID") -> HJCID | AG51: =IFERROR(__xludf.DUMMYFUNCTION("""COMPUTED_VALUE"""),"Jhon Deere Credit") -> Jhon Deere Credit | AH51: =IFERROR(__xludf.DUMMYFUNCTION("""COMPUTED_VALUE"""),46534.0) -> 46534 | AI51: =IFERROR(__xludf.DUMMYFUNCTION("""COMPUTED_VALUE"""),0.075) -> 0.075 | AJ51: =IFERROR(__xludf.DUMMYFUNCTION("""COMPUTED_VALUE"""),100.05) -> 100.05 | AK51: =IFERROR(__xludf.DUMMYFUNCTION("""COMPUTED_VALUE"""),0.09546184844791719) -> 0.095461848 | AL51: =IFERROR(__xludf.DUMMYFUNCTION("""COMPUTED_VALUE"""),-0.009399999999999999) -> -0.0094 | AM51: =IFERROR(__xludf.DUMMYFUNCTION("""COMPUTED_VALUE"""),1.485398697994833) -> 1.4853987 | AN51: =IFERROR(__xludf.DUMMYFUNCTION("""COMPUTED_VALUE"""),"Semestral") -> Semestral | AO51: =IFERROR(__xludf.DUMMYFUNCTION("""COMPUTED_VALUE"""),"Bullet") -> Bullet | AP51: =IFERROR(__xludf.DUMMYFUNCTION("""COMPUTED_VALUE"""),"ARG") -> ARG | AQ51: =IFERROR(__xludf.DUMMYFUNCTION("""COMPUTED_VALUE"""),1200.0) -> 1200 | AR51: =IFERROR(__xludf.DUMMYFUNCTION("""COMPUTED_VALUE"""),50.0) -> 50 | AS51: =IFERROR(__xludf.DUMMYFUNCTION("""COMPUTED_VALUE"""),0.9734955014995) -> 0.9734955
N52: =IFERROR(__xludf.DUMMYFUNCTION("""COMPUTED_VALUE"""),"YMCXD") -> YMCXD | O52: =IFERROR(__xludf.DUMMYFUNCTION("""COMPUTED_VALUE"""),"YPF") -> YPF | P52: =IFERROR(__xludf.DUMMYFUNCTION("""COMPUTED_VALUE"""),48102.0) -> 48102 | Q52: =IFERROR(__xludf.DUMMYFUNCTION("""COMPUTED_VALUE"""),0.0875) -> 0.0875 | R52: =IFERROR(__xludf.DUMMYFUNCTION("""COMPUTED_VALUE"""),104.3) -> 104.3 | S52: =IFERROR(__xludf.DUMMYFUNCTION("""COMPUTED_VALUE"""),0.08058538599984179) -> 0.080585386 | T52: =IFERROR(__xludf.DUMMYFUNCTION("""COMPUTED_VALUE"""),0.0028000000000000004) -> 0.0028 | U52: =IFERROR(__xludf.DUMMYFUNCTION("""COMPUTED_VALUE"""),4.382994151768527) -> 4.3829942 | V52: =IFERROR(__xludf.DUMMYFUNCTION("""COMPUTED_VALUE"""),"Semestral") -> Semestral | W52: =IFERROR(__xludf.DUMMYFUNCTION("""COMPUTED_VALUE"""),"Sinkable") -> Sinkable | X52: =IFERROR(__xludf.DUMMYFUNCTION("""COMPUTED_VALUE"""),"NY") -> NY | Y52: =IFERROR(__xludf.DUMMYFUNCTION("""COMPUTED_VALUE"""),1.0) -> 1 | Z52: =IFERROR(__xludf.DUMMYFUNCTION("""COMPUTED_VALUE"""),154.0) -> 154 | AA52: =IFERROR(__xludf.DUMMYFUNCTION("""COMPUTED_VALUE"""),0.9918901069871879) -> 0.99189011 | AF52: =IFERROR(__xludf.DUMMYFUNCTION("""COMPUTED_VALUE"""),"MCC2D") -> MCC2D | AG52: =IFERROR(__xludf.DUMMYFUNCTION("""COMPUTED_VALUE"""),"PECOM") -> PECOM | AH52: =IFERROR(__xludf.DUMMYFUNCTION("""COMPUTED_VALUE"""),46540.0) -> 46540 | AI52: =IFERROR(__xludf.DUMMYFUNCTION("""COMPUTED_VALUE"""),0.075) -> 0.075 | AJ52: =IFERROR(__xludf.DUMMYFUNCTION("""COMPUTED_VALUE"""),97.99) -> 97.99 | AK52: =IFERROR(__xludf.DUMMYFUNCTION("""COMPUTED_VALUE"""),0.10930010647202155) -> 0.10930011 | AL52: =IFERROR(__xludf.DUMMYFUNCTION("""COMPUTED_VALUE"""),-1.0E-4) -> -0.0001 | AM52: =IFERROR(__xludf.DUMMYFUNCTION("""COMPUTED_VALUE"""),1.4686718152004765) -> 1.4686718 | AN52: =IFERROR(__xludf.DUMMYFUNCTION("""COMPUTED_VALUE"""),"Semestral") -> Semestral | AO52: =IFERROR(__xludf.DUMMYFUNCTION("""COMPUTED_VALUE"""),"Bullet") -> Bullet | AP52: =IFERROR(__xludf.DUMMYFUNCTION("""COMPUTED_VALUE"""),"ARG") -> ARG | AQ52: =IFERROR(__xludf.DUMMYFUNCTION("""COMPUTED_VALUE"""),100.0) -> 100 | AR52: =IFERROR(__xludf.DUMMYFUNCTION("""COMPUTED_VALUE"""),55.0) -> 55 | AS52: =IFERROR(__xludf.DUMMYFUNCTION("""COMPUTED_VALUE"""),0.954596650430373) -> 0.95459665
N53: =IFERROR(__xludf.DUMMYFUNCTION("""COMPUTED_VALUE"""),"PNXCD") -> PNXCD | O53: =IFERROR(__xludf.DUMMYFUNCTION("""COMPUTED_VALUE"""),"Pan American Energy") -> Pan American Energy | P53: =IFERROR(__xludf.DUMMYFUNCTION("""COMPUTED_VALUE"""),48334.0) -> 48334 | Q53: =IFERROR(__xludf.DUMMYFUNCTION("""COMPUTED_VALUE"""),0.085) -> 0.085 | R53: =IFERROR(__xludf.DUMMYFUNCTION("""COMPUTED_VALUE"""),111.0) -> 111 | S53: =IFERROR(__xludf.DUMMYFUNCTION("""COMPUTED_VALUE"""),0.07017365195080114) -> 0.070173652 | T53: =IFERROR(__xludf.DUMMYFUNCTION("""COMPUTED_VALUE"""),-9.0E-4) -> -0.0009 | U53: =IFERROR(__xludf.DUMMYFUNCTION("""COMPUTED_VALUE"""),4.458917181881186) -> 4.4589172 | V53: =IFERROR(__xludf.DUMMYFUNCTION("""COMPUTED_VALUE"""),"Semestral") -> Semestral | W53: =IFERROR(__xludf.DUMMYFUNCTION("""COMPUTED_VALUE"""),"Sinkable") -> Sinkable | X53: =IFERROR(__xludf.DUMMYFUNCTION("""COMPUTED_VALUE"""),"NY") -> NY | Y53: =IFERROR(__xludf.DUMMYFUNCTION("""COMPUTED_VALUE"""),1000.0) -> 1000 | Z53: =IFERROR(__xludf.DUMMYFUNCTION("""COMPUTED_VALUE"""),22.0) -> 22 | AA53: =IFERROR(__xludf.DUMMYFUNCTION("""COMPUTED_VALUE"""),1.0691066698771972) -> 1.0691067 | AF53: =IFERROR(__xludf.DUMMYFUNCTION("""COMPUTED_VALUE"""),"YM38D") -> YM38D | AG53: =IFERROR(__xludf.DUMMYFUNCTION("""COMPUTED_VALUE"""),"YPF") -> YPF | AH53: =IFERROR(__xludf.DUMMYFUNCTION("""COMPUTED_VALUE"""),46590.0) -> 46590 | AI53: =IFERROR(__xludf.DUMMYFUNCTION("""COMPUTED_VALUE"""),0.075) -> 0.075 | AJ53: =IFERROR(__xludf.DUMMYFUNCTION("""COMPUTED_VALUE"""),102.25) -> 102.25 | AK53: =IFERROR(__xludf.DUMMYFUNCTION("""COMPUTED_VALUE"""),0.07313964492127493) -> 0.073139645 | AL53: =IFERROR(__xludf.DUMMYFUNCTION("""COMPUTED_VALUE"""),"#N/A") -> #N/A | AM53: =IFERROR(__xludf.DUMMYFUNCTION("""COMPUTED_VALUE"""),1.6800774124479907) -> 1.6800774 | AN53: =IFERROR(__xludf.DUMMYFUNCTION("""COMPUTED_VALUE"""),"Trimestral") -> Trimestral | AO53: =IFERROR(__xludf.DUMMYFUNCTION("""COMPUTED_VALUE"""),"Bullet") -> Bullet | AP53: =IFERROR(__xludf.DUMMYFUNCTION("""COMPUTED_VALUE"""),"ARG") -> ARG | AQ53: =IFERROR(__xludf.DUMMYFUNCTION("""COMPUTED_VALUE"""),100.0) -> 100 | AR53: =IFERROR(__xludf.DUMMYFUNCTION("""COMPUTED_VALUE"""),14.0) -> 14 | AS53: =IFERROR(__xludf.DUMMYFUNCTION("""COMPUTED_VALUE"""),1.0059438409510146) -> 1.0059438
N54: =IFERROR(__xludf.DUMMYFUNCTION("""COMPUTED_VALUE"""),"YFCJD") -> YFCJD | O54: =IFERROR(__xludf.DUMMYFUNCTION("""COMPUTED_VALUE"""),"YPF Luz") -> YPF Luz | P54: =IFERROR(__xludf.DUMMYFUNCTION("""COMPUTED_VALUE"""),48503.0) -> 48503 | Q54: =IFERROR(__xludf.DUMMYFUNCTION("""COMPUTED_VALUE"""),0.0788) -> 0.0788 | R54: =IFERROR(__xludf.DUMMYFUNCTION("""COMPUTED_VALUE"""),102.8) -> 102.8 | S54: =IFERROR(__xludf.DUMMYFUNCTION("""COMPUTED_VALUE"""),0.08249727097335856) -> 0.082497271 | T54: =IFERROR(__xludf.DUMMYFUNCTION("""COMPUTED_VALUE"""),9.0E-4) -> 0.0009 | U54: =IFERROR(__xludf.DUMMYFUNCTION("""COMPUTED_VALUE"""),4.74795016936165) -> 4.7479502 | V54: =IFERROR(__xludf.DUMMYFUNCTION("""COMPUTED_VALUE"""),"Semestral") -> Semestral | W54: =IFERROR(__xludf.DUMMYFUNCTION("""COMPUTED_VALUE"""),"Sinkable") -> Sinkable | X54: =IFERROR(__xludf.DUMMYFUNCTION("""COMPUTED_VALUE"""),"NY") -> NY | Y54: =IFERROR(__xludf.DUMMYFUNCTION("""COMPUTED_VALUE"""),1000.0) -> 1000 | Z54: =IFERROR(__xludf.DUMMYFUNCTION("""COMPUTED_VALUE"""),8.0) -> 8 | AA54: =IFERROR(__xludf.DUMMYFUNCTION("""COMPUTED_VALUE"""),0.9898892633606163) -> 0.98988926 | AF54: =IFERROR(__xludf.DUMMYFUNCTION("""COMPUTED_VALUE"""),"PN38D") -> PN38D | AG54: =IFERROR(__xludf.DUMMYFUNCTION("""COMPUTED_VALUE"""),"Pan American Energy") -> Pan American Energy | AH54: =IFERROR(__xludf.DUMMYFUNCTION("""COMPUTED_VALUE"""),46610.0) -> 46610 | AI54: =IFERROR(__xludf.DUMMYFUNCTION("""COMPUTED_VALUE"""),0.065) -> 0.065 | AJ54: =IFERROR(__xludf.DUMMYFUNCTION("""COMPUTED_VALUE"""),103.7) -> 103.7 | AK54: =IFERROR(__xludf.DUMMYFUNCTION("""COMPUTED_VALUE"""),0.05031010767795059) -> 0.050310108 | AL54: =IFERROR(__xludf.DUMMYFUNCTION("""COMPUTED_VALUE"""),0.0166) -> 0.0166 | AM54: =IFERROR(__xludf.DUMMYFUNCTION("""COMPUTED_VALUE"""),1.7685853153757178) -> 1.7685853 | AN54: =IFERROR(__xludf.DUMMYFUNCTION("""COMPUTED_VALUE"""),"Semestral") -> Semestral | AO54: =IFERROR(__xludf.DUMMYFUNCTION("""COMPUTED_VALUE"""),"Bullet") -> Bullet | AP54: =IFERROR(__xludf.DUMMYFUNCTION("""COMPUTED_VALUE"""),"ARG") -> ARG | AQ54: =IFERROR(__xludf.DUMMYFUNCTION("""COMPUTED_VALUE"""),50.0) -> 50 | AR54: =IFERROR(__xludf.DUMMYFUNCTION("""COMPUTED_VALUE"""),126.0) -> 126 | AS54: =IFERROR(__xludf.DUMMYFUNCTION("""COMPUTED_VALUE"""),1.0262176854148874) -> 1.0262177
N55: =IFERROR(__xludf.DUMMYFUNCTION("""COMPUTED_VALUE"""),"PLC4D") -> PLC4D | O55: =IFERROR(__xludf.DUMMYFUNCTION("""COMPUTED_VALUE"""),"Pluspetrol") -> Pluspetrol | P55: =IFERROR(__xludf.DUMMYFUNCTION("""COMPUTED_VALUE"""),48364.0) -> 48364 | Q55: =IFERROR(__xludf.DUMMYFUNCTION("""COMPUTED_VALUE"""),0.085) -> 0.085 | R55: =IFERROR(__xludf.DUMMYFUNCTION("""COMPUTED_VALUE"""),104.75) -> 104.75 | S55: =IFERROR(__xludf.DUMMYFUNCTION("""COMPUTED_VALUE"""),0.08323104363093586) -> 0.083231044 | T55: =IFERROR(__xludf.DUMMYFUNCTION("""COMPUTED_VALUE"""),-0.004699999999999999) -> -0.0047 | U55: =IFERROR(__xludf.DUMMYFUNCTION("""COMPUTED_VALUE"""),5.1114625564212) -> 5.1114626 | V55: =IFERROR(__xludf.DUMMYFUNCTION("""COMPUTED_VALUE"""),"Semestral") -> Semestral | W55: =IFERROR(__xludf.DUMMYFUNCTION("""COMPUTED_VALUE"""),"Bullet") -> Bullet | X55: =IFERROR(__xludf.DUMMYFUNCTION("""COMPUTED_VALUE"""),"NY") -> NY | Y55: =IFERROR(__xludf.DUMMYFUNCTION("""COMPUTED_VALUE"""),1000.0) -> 1000 | Z55: =IFERROR(__xludf.DUMMYFUNCTION("""COMPUTED_VALUE"""),53.0) -> 53 | AA55: =IFERROR(__xludf.DUMMYFUNCTION("""COMPUTED_VALUE"""),1.015839663811217) -> 1.0158397 | AF55: =IFERROR(__xludf.DUMMYFUNCTION("""COMPUTED_VALUE"""),"CRCJD") -> CRCJD | AG55: =IFERROR(__xludf.DUMMYFUNCTION("""COMPUTED_VALUE"""),"Celulosa") -> Celulosa | AH55: =IFERROR(__xludf.DUMMYFUNCTION("""COMPUTED_VALUE"""),46889.0) -> 46889 | AI55: =IFERROR(__xludf.DUMMYFUNCTION("""COMPUTED_VALUE"""),0.0925) -> 0.0925 | AJ55: =IFERROR(__xludf.DUMMYFUNCTION("""COMPUTED_VALUE"""),"-") -> - | AK55: =IFERROR(__xludf.DUMMYFUNCTION("""COMPUTED_VALUE"""),"-%") -> -% | AL55: =IFERROR(__xludf.DUMMYFUNCTION("""COMPUTED_VALUE"""),"#N/A") -> #N/A | AM55: =IFERROR(__xludf.DUMMYFUNCTION("""COMPUTED_VALUE"""),"-") -> - | AN55: =IFERROR(__xludf.DUMMYFUNCTION("""COMPUTED_VALUE"""),"Trimestral") -> Trimestral | AO55: =IFERROR(__xludf.DUMMYFUNCTION("""COMPUTED_VALUE"""),"Sinkable") -> Sinkable | AP55: =IFERROR(__xludf.DUMMYFUNCTION("""COMPUTED_VALUE"""),"ARG") -> ARG | AQ55: =IFERROR(__xludf.DUMMYFUNCTION("""COMPUTED_VALUE"""),1.0) -> 1 | AR55: =IFERROR(__xludf.DUMMYFUNCTION("""COMPUTED_VALUE"""),-53.0) -> -53 | AS55: =IFERROR(__xludf.DUMMYFUNCTION("""COMPUTED_VALUE"""),"#N/A") -> #N/A
N56: =IFERROR(__xludf.DUMMYFUNCTION("""COMPUTED_VALUE"""),"TTCAD") -> TTCAD | O56: =IFERROR(__xludf.DUMMYFUNCTION("""COMPUTED_VALUE"""),"Tecpetrol") -> Tecpetrol | P56: =IFERROR(__xludf.DUMMYFUNCTION("""COMPUTED_VALUE"""),48601.0) -> 48601 | Q56: =IFERROR(__xludf.DUMMYFUNCTION("""COMPUTED_VALUE"""),0.0763) -> 0.0763 | R56: =IFERROR(__xludf.DUMMYFUNCTION("""COMPUTED_VALUE"""),105.45) -> 105.45 | S56: =IFERROR(__xludf.DUMMYFUNCTION("""COMPUTED_VALUE"""),0.0697006756604922) -> 0.069700676 | T56: =IFERROR(__xludf.DUMMYFUNCTION("""COMPUTED_VALUE"""),0.0042) -> 0.0042 | U56: =IFERROR(__xludf.DUMMYFUNCTION("""COMPUTED_VALUE"""),5.098153000107035) -> 5.098153 | V56: =IFERROR(__xludf.DUMMYFUNCTION("""COMPUTED_VALUE"""),"Semestral") -> Semestral | W56: =IFERROR(__xludf.DUMMYFUNCTION("""COMPUTED_VALUE"""),"Sinkable") -> Sinkable | X56: =IFERROR(__xludf.DUMMYFUNCTION("""COMPUTED_VALUE"""),"NY") -> NY | Y56: =IFERROR(__xludf.DUMMYFUNCTION("""COMPUTED_VALUE"""),1000.0) -> 1000 | Z56: =IFERROR(__xludf.DUMMYFUNCTION("""COMPUTED_VALUE"""),106.0) -> 106 | AA56: =IFERROR(__xludf.DUMMYFUNCTION("""COMPUTED_VALUE"""),1.037145813625482) -> 1.0371458 | AF56: =IFERROR(__xludf.DUMMYFUNCTION("""COMPUTED_VALUE"""),"OLC5D") -> OLC5D | AG56: =IFERROR(__xludf.DUMMYFUNCTION("""COMPUTED_VALUE"""),"Oleoductos del Valle") -> Oleoductos del Valle | AH56: =IFERROR(__xludf.DUMMYFUNCTION("""COMPUTED_VALUE"""),46916.0) -> 46916 | AI56: =IFERROR(__xludf.DUMMYFUNCTION("""COMPUTED_VALUE"""),0.0789) -> 0.0789 | AJ56: =IFERROR(__xludf.DUMMYFUNCTION("""COMPUTED_VALUE"""),102.3) -> 102.3 | AK56: =IFERROR(__xludf.DUMMYFUNCTION("""COMPUTED_VALUE"""),0.08160539725249184) -> 0.081605397 | AL56: =IFERROR(__xludf.DUMMYFUNCTION("""COMPUTED_VALUE"""),-0.0067) -> -0.0067 | AM56: =IFERROR(__xludf.DUMMYFUNCTION("""COMPUTED_VALUE"""),2.431634654788335) -> 2.4316347 | AN56: =IFERROR(__xludf.DUMMYFUNCTION("""COMPUTED_VALUE"""),"Semestral") -> Semestral | AO56: =IFERROR(__xludf.DUMMYFUNCTION("""COMPUTED_VALUE"""),"Bullet") -> Bullet | AP56: =IFERROR(__xludf.DUMMYFUNCTION("""COMPUTED_VALUE"""),"ARG") -> ARG | AQ56: =IFERROR(__xludf.DUMMYFUNCTION("""COMPUTED_VALUE"""),100.0) -> 100 | AR56: =IFERROR(__xludf.DUMMYFUNCTION("""COMPUTED_VALUE"""),65.0) -> 65 | AS56: =IFERROR(__xludf.DUMMYFUNCTION("""COMPUTED_VALUE"""),0.9973447410728571) -> 0.99734474
N57: =IFERROR(__xludf.DUMMYFUNCTION("""COMPUTED_VALUE"""),"YMCJD") -> YMCJD | O57: =IFERROR(__xludf.DUMMYFUNCTION("""COMPUTED_VALUE"""),"YPF") -> YPF | P57: =IFERROR(__xludf.DUMMYFUNCTION("""COMPUTED_VALUE"""),48852.0) -> 48852 | Q57: =IFERROR(__xludf.DUMMYFUNCTION("""COMPUTED_VALUE"""),0.07) -> 0.07 | R57: =IFERROR(__xludf.DUMMYFUNCTION("""COMPUTED_VALUE"""),95.21) -> 95.21 | S57: =IFERROR(__xludf.DUMMYFUNCTION("""COMPUTED_VALUE"""),0.08160710044950233) -> 0.0816071 | T57: =IFERROR(__xludf.DUMMYFUNCTION("""COMPUTED_VALUE"""),0.004699999999999999) -> 0.0047 | U57: =IFERROR(__xludf.DUMMYFUNCTION("""COMPUTED_VALUE"""),5.275965287084322) -> 5.2759653 | V57: =IFERROR(__xludf.DUMMYFUNCTION("""COMPUTED_VALUE"""),"Semestral") -> Semestral | W57: =IFERROR(__xludf.DUMMYFUNCTION("""COMPUTED_VALUE"""),"Sinkable") -> Sinkable | X57: =IFERROR(__xludf.DUMMYFUNCTION("""COMPUTED_VALUE"""),"NY") -> NY | Y57: =IFERROR(__xludf.DUMMYFUNCTION("""COMPUTED_VALUE"""),1.0) -> 1 | Z57: =IFERROR(__xludf.DUMMYFUNCTION("""COMPUTED_VALUE"""),173.0) -> 173 | AA57: =IFERROR(__xludf.DUMMYFUNCTION("""COMPUTED_VALUE"""),0.9504367357125031) -> 0.95043674 | AF57: =IFERROR(__xludf.DUMMYFUNCTION("""COMPUTED_VALUE"""),"DNC5D") -> DNC5D | AG57: =IFERROR(__xludf.DUMMYFUNCTION("""COMPUTED_VALUE"""),"Edenor") -> Edenor | AH57: =IFERROR(__xludf.DUMMYFUNCTION("""COMPUTED_VALUE"""),46970.0) -> 46970 | AI57: =IFERROR(__xludf.DUMMYFUNCTION("""COMPUTED_VALUE"""),0.095) -> 0.095 | AJ57: =IFERROR(__xludf.DUMMYFUNCTION("""COMPUTED_VALUE"""),87.4) -> 87.4 | AK57: =IFERROR(__xludf.DUMMYFUNCTION("""COMPUTED_VALUE"""),0.1660100071793759) -> 0.16601001 | AL57: =IFERROR(__xludf.DUMMYFUNCTION("""COMPUTED_VALUE"""),-0.0374) -> -0.0374 | AM57: =IFERROR(__xludf.DUMMYFUNCTION("""COMPUTED_VALUE"""),2.4922995056647474) -> 2.4922995 | AN57: =IFERROR(__xludf.DUMMYFUNCTION("""COMPUTED_VALUE"""),"Semestral") -> Semestral | AO57: =IFERROR(__xludf.DUMMYFUNCTION("""COMPUTED_VALUE"""),"Bullet") -> Bullet | AP57: =IFERROR(__xludf.DUMMYFUNCTION("""COMPUTED_VALUE"""),"ARG") -> ARG | AQ57: =IFERROR(__xludf.DUMMYFUNCTION("""COMPUTED_VALUE"""),100.0) -> 100 | AR57: =IFERROR(__xludf.DUMMYFUNCTION("""COMPUTED_VALUE"""),120.0) -> 120 | AS57: =IFERROR(__xludf.DUMMYFUNCTION("""COMPUTED_VALUE"""),0.8594598235333738) -> 0.85945982
N58: =IFERROR(__xludf.DUMMYFUNCTION("""COMPUTED_VALUE"""),"TLCPD") -> TLCPD | O58: =IFERROR(__xludf.DUMMYFUNCTION("""COMPUTED_VALUE"""),"Telecom") -> Telecom | P58: =IFERROR(__xludf.DUMMYFUNCTION("""COMPUTED_VALUE"""),48727.0) -> 48727 | Q58: =IFERROR(__xludf.DUMMYFUNCTION("""COMPUTED_VALUE"""),0.0925) -> 0.0925 | R58: =IFERROR(__xludf.DUMMYFUNCTION("""COMPUTED_VALUE"""),102.0) -> 102 | S58: =IFERROR(__xludf.DUMMYFUNCTION("""COMPUTED_VALUE"""),0.09747772156634352) -> 0.097477722 | T58: =IFERROR(__xludf.DUMMYFUNCTION("""COMPUTED_VALUE"""),-0.0048) -> -0.0048 | U58: =IFERROR(__xludf.DUMMYFUNCTION("""COMPUTED_VALUE"""),5.213219007752955) -> 5.213219 | V58: =IFERROR(__xludf.DUMMYFUNCTION("""COMPUTED_VALUE"""),"Semestral") -> Semestral | W58: =IFERROR(__xludf.DUMMYFUNCTION("""COMPUTED_VALUE"""),"Sinkable") -> Sinkable | X58: =IFERROR(__xludf.DUMMYFUNCTION("""COMPUTED_VALUE"""),"NY") -> NY | Y58: =IFERROR(__xludf.DUMMYFUNCTION("""COMPUTED_VALUE"""),100.0) -> 100 | Z58: =IFERROR(__xludf.DUMMYFUNCTION("""COMPUTED_VALUE"""),51.0) -> 51 | AA58: =IFERROR(__xludf.DUMMYFUNCTION("""COMPUTED_VALUE"""),0.9860497589924676) -> 0.98604976 | AF58: =IFERROR(__xludf.DUMMYFUNCTION("""COMPUTED_VALUE"""),"LMS7D") -> LMS7D | AG58: =IFERROR(__xludf.DUMMYFUNCTION("""COMPUTED_VALUE"""),"Aluar") -> Aluar | AH58: =IFERROR(__xludf.DUMMYFUNCTION("""COMPUTED_VALUE"""),47038.0) -> 47038 | AI58: =IFERROR(__xludf.DUMMYFUNCTION("""COMPUTED_VALUE"""),0.07) -> 0.07 | AJ58: =IFERROR(__xludf.DUMMYFUNCTION("""COMPUTED_VALUE"""),102.65) -> 102.65 | AK58: =IFERROR(__xludf.DUMMYFUNCTION("""COMPUTED_VALUE"""),0.07911987416406309) -> 0.079119874 | AL58: =IFERROR(__xludf.DUMMYFUNCTION("""COMPUTED_VALUE"""),-0.0129) -> -0.0129 | AM58: =IFERROR(__xludf.DUMMYFUNCTION("""COMPUTED_VALUE"""),1.48993487386376) -> 1.4899349 | AN58: =IFERROR(__xludf.DUMMYFUNCTION("""COMPUTED_VALUE"""),"Trimestral") -> Trimestral | AO58: =IFERROR(__xludf.DUMMYFUNCTION("""COMPUTED_VALUE"""),"Sinkable") -> Sinkable | AP58: =IFERROR(__xludf.DUMMYFUNCTION("""COMPUTED_VALUE"""),"ARG") -> ARG | AQ58: =IFERROR(__xludf.DUMMYFUNCTION("""COMPUTED_VALUE"""),1.0) -> 1 | AR58: =IFERROR(__xludf.DUMMYFUNCTION("""COMPUTED_VALUE"""),96.0) -> 96 | AS58: =IFERROR(__xludf.DUMMYFUNCTION("""COMPUTED_VALUE"""),0.9922470868644068) -> 0.99224709
N59: =IFERROR(__xludf.DUMMYFUNCTION("""COMPUTED_VALUE"""),"VSCVD") -> VSCVD | O59: =IFERROR(__xludf.DUMMYFUNCTION("""COMPUTED_VALUE"""),"Vista Energy") -> Vista Energy | P59: =IFERROR(__xludf.DUMMYFUNCTION("""COMPUTED_VALUE"""),48740.0) -> 48740 | Q59: =IFERROR(__xludf.DUMMYFUNCTION("""COMPUTED_VALUE"""),0.085) -> 0.085 | R59: =IFERROR(__xludf.DUMMYFUNCTION("""COMPUTED_VALUE"""),106.0) -> 106 | S59: =IFERROR(__xludf.DUMMYFUNCTION("""COMPUTED_VALUE"""),0.08023538487148903) -> 0.080235385 | T59: =IFERROR(__xludf.DUMMYFUNCTION("""COMPUTED_VALUE"""),0.004699999999999999) -> 0.0047 | U59: =IFERROR(__xludf.DUMMYFUNCTION("""COMPUTED_VALUE"""),5.14696178862725) -> 5.1469618 | V59: =IFERROR(__xludf.DUMMYFUNCTION("""COMPUTED_VALUE"""),"Semestral") -> Semestral | W59: =IFERROR(__xludf.DUMMYFUNCTION("""COMPUTED_VALUE"""),"Sinkable") -> Sinkable | X59: =IFERROR(__xludf.DUMMYFUNCTION("""COMPUTED_VALUE"""),"NY") -> NY | Y59: =IFERROR(__xludf.DUMMYFUNCTION("""COMPUTED_VALUE"""),1000.0) -> 1000 | Z59: =IFERROR(__xludf.DUMMYFUNCTION("""COMPUTED_VALUE"""),63.0) -> 63 | AA59: =IFERROR(__xludf.DUMMYFUNCTION("""COMPUTED_VALUE"""),1.03055754351378) -> 1.0305575 | AF59: =IFERROR(__xludf.DUMMYFUNCTION("""COMPUTED_VALUE"""),"PECGD") -> PECGD | AG59: =IFERROR(__xludf.DUMMYFUNCTION("""COMPUTED_VALUE"""),"Petrolera Aconcagua Eenergia") -> Petrolera Aconcagua Eenergia | AH59: =IFERROR(__xludf.DUMMYFUNCTION("""COMPUTED_VALUE"""),47054.0) -> 47054 | AI59: =IFERROR(__xludf.DUMMYFUNCTION("""COMPUTED_VALUE"""),0.09) -> 0.09 | AJ59: =IFERROR(__xludf.DUMMYFUNCTION("""COMPUTED_VALUE"""),"#N/A") -> #N/A | AK59: =IFERROR(__xludf.DUMMYFUNCTION("""COMPUTED_VALUE"""),"#N/A") -> #N/A | AL59: =IFERROR(__xludf.DUMMYFUNCTION("""COMPUTED_VALUE"""),"#N/A") -> #N/A | AM59: =IFERROR(__xludf.DUMMYFUNCTION("""COMPUTED_VALUE"""),"-") -> - | AN59: =IFERROR(__xludf.DUMMYFUNCTION("""COMPUTED_VALUE"""),"Semestral") -> Semestral | AO59: =IFERROR(__xludf.DUMMYFUNCTION("""COMPUTED_VALUE"""),"Bullet") -> Bullet | AP59: =IFERROR(__xludf.DUMMYFUNCTION("""COMPUTED_VALUE"""),"ARG") -> ARG | AQ59: =IFERROR(__xludf.DUMMYFUNCTION("""COMPUTED_VALUE"""),1.0) -> 1 | AR59: =IFERROR(__xludf.DUMMYFUNCTION("""COMPUTED_VALUE"""),20.0) -> 20 | AS59: =IFERROR(__xludf.DUMMYFUNCTION("""COMPUTED_VALUE"""),"#N/A") -> #N/A
N60: =IFERROR(__xludf.DUMMYFUNCTION("""COMPUTED_VALUE"""),"YM34D") -> YM34D | O60: =IFERROR(__xludf.DUMMYFUNCTION("""COMPUTED_VALUE"""),"YPF") -> YPF | P60: =IFERROR(__xludf.DUMMYFUNCTION("""COMPUTED_VALUE"""),48961.0) -> 48961 | Q60: =IFERROR(__xludf.DUMMYFUNCTION("""COMPUTED_VALUE"""),0.0825) -> 0.0825 | R60: =IFERROR(__xludf.DUMMYFUNCTION("""COMPUTED_VALUE"""),100.7) -> 100.7 | S60: =IFERROR(__xludf.DUMMYFUNCTION("""COMPUTED_VALUE"""),0.08647523168979138) -> 0.086475232 | T60: =IFERROR(__xludf.DUMMYFUNCTION("""COMPUTED_VALUE"""),-0.0078000000000000005) -> -0.0078 | U60: =IFERROR(__xludf.DUMMYFUNCTION("""COMPUTED_VALUE"""),5.573419365572477) -> 5.5734194 | V60: =IFERROR(__xludf.DUMMYFUNCTION("""COMPUTED_VALUE"""),"Semestral") -> Semestral | W60: =IFERROR(__xludf.DUMMYFUNCTION("""COMPUTED_VALUE"""),"Sinkable") -> Sinkable | X60: =IFERROR(__xludf.DUMMYFUNCTION("""COMPUTED_VALUE"""),"NY") -> NY | Y60: =IFERROR(__xludf.DUMMYFUNCTION("""COMPUTED_VALUE"""),1.0) -> 1 | Z60: =IFERROR(__xludf.DUMMYFUNCTION("""COMPUTED_VALUE"""),101.0) -> 101 | AA60: =IFERROR(__xludf.DUMMYFUNCTION("""COMPUTED_VALUE"""),0.987981358842286) -> 0.98798136 | AF60: =IFERROR(__xludf.DUMMYFUNCTION("""COMPUTED_VALUE"""),"VSCPD") -> VSCPD | AG60: =IFERROR(__xludf.DUMMYFUNCTION("""COMPUTED_VALUE"""),"Vista Oil") -> Vista Oil | AH60: =IFERROR(__xludf.DUMMYFUNCTION("""COMPUTED_VALUE"""),47241.0) -> 47241 | AI60: =IFERROR(__xludf.DUMMYFUNCTION("""COMPUTED_VALUE"""),0.08) -> 0.08 | AJ60: =IFERROR(__xludf.DUMMYFUNCTION("""COMPUTED_VALUE"""),106.8) -> 106.8 | AK60: =IFERROR(__xludf.DUMMYFUNCTION("""COMPUTED_VALUE"""),0.06793145089821298) -> 0.067931451 | AL60: =IFERROR(__xludf.DUMMYFUNCTION("""COMPUTED_VALUE"""),-0.0046) -> -0.0046 | AM60: =IFERROR(__xludf.DUMMYFUNCTION("""COMPUTED_VALUE"""),2.521749945629113) -> 2.5217499 | AN60: =IFERROR(__xludf.DUMMYFUNCTION("""COMPUTED_VALUE"""),"Semestral") -> Semestral | AO60: =IFERROR(__xludf.DUMMYFUNCTION("""COMPUTED_VALUE"""),"Sinkable") -> Sinkable | AP60: =IFERROR(__xludf.DUMMYFUNCTION("""COMPUTED_VALUE"""),"ARG") -> ARG | AQ60: =IFERROR(__xludf.DUMMYFUNCTION("""COMPUTED_VALUE"""),100.0) -> 100 | AR60: =IFERROR(__xludf.DUMMYFUNCTION("""COMPUTED_VALUE"""),26.0) -> 26 | AS60: =IFERROR(__xludf.DUMMYFUNCTION("""COMPUTED_VALUE"""),1.0320343111299375) -> 1.0320343
N61: =IFERROR(__xludf.DUMMYFUNCTION("""COMPUTED_VALUE"""),"MGCOD") -> MGCOD | O61: =IFERROR(__xludf.DUMMYFUNCTION("""COMPUTED_VALUE"""),"Pampa Energia") -> Pampa Energia | P61: =IFERROR(__xludf.DUMMYFUNCTION("""COMPUTED_VALUE"""),49294.0) -> 49294 | Q61: =IFERROR(__xludf.DUMMYFUNCTION("""COMPUTED_VALUE"""),0.0788) -> 0.0788 | R61: =IFERROR(__xludf.DUMMYFUNCTION("""COMPUTED_VALUE"""),102.0) -> 102 | S61: =IFERROR(__xludf.DUMMYFUNCTION("""COMPUTED_VALUE"""),0.08104000521943708) -> 0.081040005 | T61: =IFERROR(__xludf.DUMMYFUNCTION("""COMPUTED_VALUE"""),-9.0E-4) -> -0.0009 | U61: =IFERROR(__xludf.DUMMYFUNCTION("""COMPUTED_VALUE"""),6.576337094089589) -> 6.5763371 | V61: =IFERROR(__xludf.DUMMYFUNCTION("""COMPUTED_VALUE"""),"Semestral") -> Semestral | W61: =IFERROR(__xludf.DUMMYFUNCTION("""COMPUTED_VALUE"""),"Bullet") -> Bullet | X61: =IFERROR(__xludf.DUMMYFUNCTION("""COMPUTED_VALUE"""),"NY") -> NY | Y61: =IFERROR(__xludf.DUMMYFUNCTION("""COMPUTED_VALUE"""),10000.0) -> 10000 | Z61: =IFERROR(__xludf.DUMMYFUNCTION("""COMPUTED_VALUE"""),69.0) -> 69 | AA61: =IFERROR(__xludf.DUMMYFUNCTION("""COMPUTED_VALUE"""),0.9577745825875172) -> 0.95777458 | AF61: =IFERROR(__xludf.DUMMYFUNCTION("""COMPUTED_VALUE"""),"PN35D") -> PN35D | AG61: =IFERROR(__xludf.DUMMYFUNCTION("""COMPUTED_VALUE"""),"Pan American Energy") -> Pan American Energy | AH61: =IFERROR(__xludf.DUMMYFUNCTION("""COMPUTED_VALUE"""),47388.0) -> 47388 | AI61: =IFERROR(__xludf.DUMMYFUNCTION("""COMPUTED_VALUE"""),0.07) -> 0.07 | AJ61: =IFERROR(__xludf.DUMMYFUNCTION("""COMPUTED_VALUE"""),102.5) -> 102.5 | AK61: =IFERROR(__xludf.DUMMYFUNCTION("""COMPUTED_VALUE"""),0.06438929106951667) -> 0.064389291 | AL61: =IFERROR(__xludf.DUMMYFUNCTION("""COMPUTED_VALUE"""),-0.0034000000000000002) -> -0.0034 | AM61: =IFERROR(__xludf.DUMMYFUNCTION("""COMPUTED_VALUE"""),3.5699921055884207) -> 3.5699921 | AN61: =IFERROR(__xludf.DUMMYFUNCTION("""COMPUTED_VALUE"""),"Semestral") -> Semestral | AO61: =IFERROR(__xludf.DUMMYFUNCTION("""COMPUTED_VALUE"""),"Bullet") -> Bullet | AP61: =IFERROR(__xludf.DUMMYFUNCTION("""COMPUTED_VALUE"""),"ARG") -> ARG | AQ61: =IFERROR(__xludf.DUMMYFUNCTION("""COMPUTED_VALUE"""),1.0) -> 1 | AR61: =IFERROR(__xludf.DUMMYFUNCTION("""COMPUTED_VALUE"""),170.0) -> 170 | AS61: =IFERROR(__xludf.DUMMYFUNCTION("""COMPUTED_VALUE"""),1.022646512136453) -> 1.0226465
N62: =IFERROR(__xludf.DUMMYFUNCTION("""COMPUTED_VALUE"""),"IRCPD") -> IRCPD | O62: =IFERROR(__xludf.DUMMYFUNCTION("""COMPUTED_VALUE"""),"IRSA") -> IRSA | P62: =IFERROR(__xludf.DUMMYFUNCTION("""COMPUTED_VALUE"""),49399.0) -> 49399 | Q62: =IFERROR(__xludf.DUMMYFUNCTION("""COMPUTED_VALUE"""),0.08) -> 0.08 | R62: =IFERROR(__xludf.DUMMYFUNCTION("""COMPUTED_VALUE"""),101.0) -> 101 | S62: =IFERROR(__xludf.DUMMYFUNCTION("""COMPUTED_VALUE"""),0.08018455933001999) -> 0.080184559 | T62: =IFERROR(__xludf.DUMMYFUNCTION("""COMPUTED_VALUE"""),-0.0044) -> -0.0044 | U62: =IFERROR(__xludf.DUMMYFUNCTION("""COMPUTED_VALUE"""),6.342041482649829) -> 6.3420415 | V62: =IFERROR(__xludf.DUMMYFUNCTION("""COMPUTED_VALUE"""),"Semestral") -> Semestral | W62: =IFERROR(__xludf.DUMMYFUNCTION("""COMPUTED_VALUE"""),"Sinkable") -> Sinkable | X62: =IFERROR(__xludf.DUMMYFUNCTION("""COMPUTED_VALUE"""),"NY") -> NY | Y62: =IFERROR(__xludf.DUMMYFUNCTION("""COMPUTED_VALUE"""),1.0) -> 1 | Z62: =IFERROR(__xludf.DUMMYFUNCTION("""COMPUTED_VALUE"""),174.0) -> 174 | AA62: =IFERROR(__xludf.DUMMYFUNCTION("""COMPUTED_VALUE"""),1.0079840319361277) -> 1.007984 | AF62: =IFERROR(__xludf.DUMMYFUNCTION("""COMPUTED_VALUE"""),"IRCOD") -> IRCOD | AG62: =IFERROR(__xludf.DUMMYFUNCTION("""COMPUTED_VALUE"""),"IRSA") -> IRSA | AH62: =IFERROR(__xludf.DUMMYFUNCTION("""COMPUTED_VALUE"""),47414.0) -> 47414 | AI62: =IFERROR(__xludf.DUMMYFUNCTION("""COMPUTED_VALUE"""),0.0725) -> 0.0725 | AJ62: =IFERROR(__xludf.DUMMYFUNCTION("""COMPUTED_VALUE"""),102.7) -> 102.7 | AK62: =IFERROR(__xludf.DUMMYFUNCTION("""COMPUTED_VALUE"""),0.07037748230088652) -> 0.070377482 | AL62: =IFERROR(__xludf.DUMMYFUNCTION("""COMPUTED_VALUE"""),-0.0029) -> -0.0029 | AM62: =IFERROR(__xludf.DUMMYFUNCTION("""COMPUTED_VALUE"""),3.560871967646005) -> 3.560872 | AN62: =IFERROR(__xludf.DUMMYFUNCTION("""COMPUTED_VALUE"""),"Semestral") -> Semestral | AO62: =IFERROR(__xludf.DUMMYFUNCTION("""COMPUTED_VALUE"""),"Bullet") -> Bullet | AP62: =IFERROR(__xludf.DUMMYFUNCTION("""COMPUTED_VALUE"""),"ARG") -> ARG | AQ62: =IFERROR(__xludf.DUMMYFUNCTION("""COMPUTED_VALUE"""),1.0) -> 1 | AR62: =IFERROR(__xludf.DUMMYFUNCTION("""COMPUTED_VALUE"""),107.0) -> 107 | AS62: =IFERROR(__xludf.DUMMYFUNCTION("""COMPUTED_VALUE"""),1.0113312919021733) -> 1.0113313
N63: =IFERROR(__xludf.DUMMYFUNCTION("""COMPUTED_VALUE"""),"VSCTD") -> VSCTD | O63: =IFERROR(__xludf.DUMMYFUNCTION("""COMPUTED_VALUE"""),"Vista Energy") -> Vista Energy | P63: =IFERROR(__xludf.DUMMYFUNCTION("""COMPUTED_VALUE"""),49653.0) -> 49653 | Q63: =IFERROR(__xludf.DUMMYFUNCTION("""COMPUTED_VALUE"""),0.0763) -> 0.0763 | R63: =IFERROR(__xludf.DUMMYFUNCTION("""COMPUTED_VALUE"""),99.9) -> 99.9 | S63: =IFERROR(__xludf.DUMMYFUNCTION("""COMPUTED_VALUE"""),0.0818604390915039) -> 0.081860439 | T63: =IFERROR(__xludf.DUMMYFUNCTION("""COMPUTED_VALUE"""),-0.0044) -> -0.0044 | U63: =IFERROR(__xludf.DUMMYFUNCTION("""COMPUTED_VALUE"""),6.5851280860201555) -> 6.5851281 | V63: =IFERROR(__xludf.DUMMYFUNCTION("""COMPUTED_VALUE"""),"Semestral") -> Semestral | W63: =IFERROR(__xludf.DUMMYFUNCTION("""COMPUTED_VALUE"""),"Sinkable") -> Sinkable | X63: =IFERROR(__xludf.DUMMYFUNCTION("""COMPUTED_VALUE"""),"NY") -> NY | Y63: =IFERROR(__xludf.DUMMYFUNCTION("""COMPUTED_VALUE"""),10000.0) -> 10000 | Z63: =IFERROR(__xludf.DUMMYFUNCTION("""COMPUTED_VALUE"""),63.0) -> 63 | AA63: =IFERROR(__xludf.DUMMYFUNCTION("""COMPUTED_VALUE"""),0.9387535360851988) -> 0.93875354 | AF63: =IFERROR(__xludf.DUMMYFUNCTION("""COMPUTED_VALUE"""),"TTC9D") -> TTC9D | AG63: =IFERROR(__xludf.DUMMYFUNCTION("""COMPUTED_VALUE"""),"Tecpetrol") -> Tecpetrol | AH63: =IFERROR(__xludf.DUMMYFUNCTION("""COMPUTED_VALUE"""),47415.0) -> 47415 | AI63: =IFERROR(__xludf.DUMMYFUNCTION("""COMPUTED_VALUE"""),0.068) -> 0.068 | AJ63: =IFERROR(__xludf.DUMMYFUNCTION("""COMPUTED_VALUE"""),104.7) -> 104.7 | AK63: =IFERROR(__xludf.DUMMYFUNCTION("""COMPUTED_VALUE"""),0.06453796011338711) -> 0.06453796 | AL63: =IFERROR(__xludf.DUMMYFUNCTION("""COMPUTED_VALUE"""),0.015) -> 0.015 | AM63: =IFERROR(__xludf.DUMMYFUNCTION("""COMPUTED_VALUE"""),3.5365084959104034) -> 3.5365085 | AN63: =IFERROR(__xludf.DUMMYFUNCTION("""COMPUTED_VALUE"""),"Semestral") -> Semestral | AO63: =IFERROR(__xludf.DUMMYFUNCTION("""COMPUTED_VALUE"""),"Bullet") -> Bullet | AP63: =IFERROR(__xludf.DUMMYFUNCTION("""COMPUTED_VALUE"""),"ARG") -> ARG | AQ63: =IFERROR(__xludf.DUMMYFUNCTION("""COMPUTED_VALUE"""),1.0) -> 1 | AR63: =IFERROR(__xludf.DUMMYFUNCTION("""COMPUTED_VALUE"""),16.0) -> 16 | AS63: =IFERROR(__xludf.DUMMYFUNCTION("""COMPUTED_VALUE"""),1.0152248528255372) -> 1.0152249
AF64: =IFERROR(__xludf.DUMMYFUNCTION("""COMPUTED_VALUE"""),"OT42D") -> OT42D | AG64: =IFERROR(__xludf.DUMMYFUNCTION("""COMPUTED_VALUE"""),"OilTanking") -> OilTanking | AH64: =IFERROR(__xludf.DUMMYFUNCTION("""COMPUTED_VALUE"""),47500.0) -> 47500 | AI64: =IFERROR(__xludf.DUMMYFUNCTION("""COMPUTED_VALUE"""),0.08) -> 0.08 | AJ64: =IFERROR(__xludf.DUMMYFUNCTION("""COMPUTED_VALUE"""),103.95) -> 103.95 | AK64: =IFERROR(__xludf.DUMMYFUNCTION("""COMPUTED_VALUE"""),0.08795735285675439) -> 0.087957353 | AL64: =IFERROR(__xludf.DUMMYFUNCTION("""COMPUTED_VALUE"""),-4.0E-4) -> -0.0004 | AM64: =IFERROR(__xludf.DUMMYFUNCTION("""COMPUTED_VALUE"""),3.485372759800234) -> 3.4853728 | AN64: =IFERROR(__xludf.DUMMYFUNCTION("""COMPUTED_VALUE"""),"trimestral") -> trimestral | AO64: =IFERROR(__xludf.DUMMYFUNCTION("""COMPUTED_VALUE"""),"Bullet") -> Bullet | AP64: =IFERROR(__xludf.DUMMYFUNCTION("""COMPUTED_VALUE"""),"ARG") -> ARG | AQ64: =IFERROR(__xludf.DUMMYFUNCTION("""COMPUTED_VALUE"""),100.0) -> 100 | AR64: =IFERROR(__xludf.DUMMYFUNCTION("""COMPUTED_VALUE"""),9.0) -> 9 | AS64: =IFERROR(__xludf.DUMMYFUNCTION("""COMPUTED_VALUE"""),0.9824378560331434) -> 0.98243786
