Workbook

Sheet Multi-mercado
A1: Ticker | B1: COPX | C1: 24
B3: Cierre | C3: {=_xll.PrecioBD(B1,C1,"PREVIOUS","N")} -> 9240 | D3: Último | E3: {=_xll.PrecioBD(B1,C1,"LAST","N")} -> 8855 | F3: Var | G3: {=_xll.PrecioBD(B1,C1,"IMBALANCE","N")} -> -0.0416
B4: Vwap | C4: {=_xll.PrecioBD(B1,C1,"VWAP","N")} -> 8892.4331 | D4: Nominales | E4: {=_xll.PrecioBD(B1,C1,"TRADE VOLUME","N")} -> 97948 | F4: Monto $ | G4: {=_xll.PrecioBD(B1,C1,"VOLUME AMOUNT","N")} -> 869723240
B6: {=_xll.PrecioBD(B1,C1,"BID","N")} -> 8815 | E6: {=_xll.PrecioBD(B1,C1,"ASK","N")} -> 9050
A7: {=_xll.ProfundidadBD(B1,C1)} -> COPX - 24hs | B7: ORD. | C7: CANT. | D7: PRECIO | E7: PRECIO | F7: CANT. | G7: ORD.
I14: Pase
A15: Ticker | B15: =B1 -> COPX | C15: CI | J15: Venta CI - Compra T1 | K15: Compra CI - Venta T1
I16: Arbitraje | J16: =D22/E8-1 -> #DIV/0! | K16: =D8/E22-1 -> #DIV/0!
B17: Cierre | C17: {=_xll.PrecioBD(B15,C15,"PREVIOUS","N")} -> 9240 | D17: Último | E17: {=_xll.PrecioBD(B15,C15,"LAST","N")} -> 8815 | F17: Var | G17: {=_xll.PrecioBD(B15,C15,"IMBALANCE","N")} -> -0.0459 | I17: TNA | J17: =+J16*365 -> #DIV/0! | K17: =+K16*365 -> #DIV/0!
B18: Vwap | C18: {=_xll.PrecioBD(B15,C15,"VWAP","N")} -> 8892.4331 | D18: Nominales | E18: {=_xll.PrecioBD(B15,C15,"TRADE VOLUME","N")} -> 7102 | F18: Monto $ | G18: {=_xll.PrecioBD(B15,C15,"VOLUME AMOUNT","N")} -> 63154060
B20: {=_xll.PrecioBD(B15,C15,"BID","N")} -> 8815 | E20: {=_xll.PrecioBD(B15,C15,"ASK","N")} -> 9170
A21: {=_xll.ProfundidadBD(B15,C15)} -> COPX - CI | B21: ORD. | C21: CANT. | D21: PRECIO | E21: PRECIO | F21: CANT. | G21: ORD.

Sheet Main
A1: Fecha de liq | B1: =TODAY()+1 -> 46060
A4: Caución | B4: Moneda | C4: Plazo | D4: Tasa | E4: Bid | F4: Ask | G4: VWAP | I4: Soberanos HD | J4: Ticker | K4: TIR | L4: Ask price | M4: MD | N4: Variación | P4: ARGY | Q4: Ticker | R4: Precio | S4: Total volume | T4: Variación
B5: USD | C5: 1 | D5: =VLOOKUP(C5,Caucho!$E$2:$N$65,3,FALSE) -> #N/A | E5: =VLOOKUP(C5,Caucho!$E$2:$N$65,7,FALSE) -> #N/A | F5: =VLOOKUP(C5,Caucho!$E$2:$N$65,8,FALSE) -> #N/A | G5: =VLOOKUP(C5,Caucho!$E$2:$N$65,10,FALSE) -> #N/A | J5: AE38D | K5: =VLOOKUP(Tabla9[[#This Row],[Ticker]],ONs_NY8[[Ticker]:[Variación]],2,FALSE) -> 0.096076125 | L5: {=_xll.PrecioBD(Tabla9[[#This Row],[Ticker]],24,"ASK","N")} -> 80.05 | M5: =VLOOKUP(Tabla9[[#This Row],[Ticker]],ONs_NY8[[Ticker]:[Variación]],5,FALSE) -> 4.9019119 | N5: {=_xll.PrecioBD(Tabla9[[#This Row],[Ticker]],24,"IMBALANCE","N")} -> -0.0007 | Q5: TRAN | R5: {=_xll.PrecioBD(Q5,24,"ASK","N")} -> 3870 | S5: {=_xll.PrecioBD(Q5,24,"VOLUME AMOUNT","N")} -> 2.969431e+09 | T5: {=_xll.PrecioBD(Q5,24,"IMBALANCE","N")} -> -0.019
B6: USD | C6: 7 | D6: =VLOOKUP(C6,Caucho!$E$2:$N$65,3,FALSE) -> 0.018 | E6: =VLOOKUP(C6,Caucho!$E$2:$N$65,7,FALSE) -> 0.005 | F6: =VLOOKUP(C6,Caucho!$E$2:$N$65,8,FALSE) -> 0.018 | G6: =VLOOKUP(C6,Caucho!$E$2:$N$65,10,FALSE) -> 0.018 | J6: AL29D | K6: =VLOOKUP(Tabla9[[#This Row],[Ticker]],ONs_NY8[[Ticker]:[Variación]],2,FALSE) -> 0.088069263 | L6: {=_xll.PrecioBD(Tabla9[[#This Row],[Ticker]],24,"ASK","N")} -> 60.97 | M6: =VLOOKUP(Tabla9[[#This Row],[Ticker]],ONs_NY8[[Ticker]:[Variación]],5,FALSE) -> 0.5 | N6: {=_xll.PrecioBD(Tabla9[[#This Row],[Ticker]],24,"IMBALANCE","N")} -> 0.0013 | Q6: YPFD | R6: {=_xll.PrecioBD(Q6,24,"ASK","N")} -> 56500 | S6: {=_xll.PrecioBD(Q6,24,"VOLUME AMOUNT","N")} -> 16604746650 | T6: {=_xll.PrecioBD(Q6,24,"IMBALANCE","N")} -> -0.0342
B7: USD | C7: 30 | D7: =VLOOKUP(C7,Caucho!$E$2:$N$65,3,FALSE) -> #N/A | E7: =VLOOKUP(C7,Caucho!$E$2:$N$65,7,FALSE) -> #N/A | F7: =VLOOKUP(C7,Caucho!$E$2:$N$65,8,FALSE) -> #N/A | G7: =VLOOKUP(C7,Caucho!$E$2:$N$65,10,FALSE) -> #N/A | J7: AL30D | K7: =VLOOKUP(Tabla9[[#This Row],[Ticker]],ONs_NY8[[Ticker]:[Variación]],2,FALSE) -> 0.09034898 | L7: {=_xll.PrecioBD(Tabla9[[#This Row],[Ticker]],24,"ASK","N")} -> 60.58 | M7: =VLOOKUP(Tabla9[[#This Row],[Ticker]],ONs_NY8[[Ticker]:[Variación]],5,FALSE) -> 2.1755694 | N7: {=_xll.PrecioBD(Tabla9[[#This Row],[Ticker]],24,"IMBALANCE","N")} -> 0.0048 | Q7: TXAR | R7: {=_xll.PrecioBD(Q7,24,"ASK","N")} -> 684.5 | S7: {=_xll.PrecioBD(Q7,24,"VOLUME AMOUNT","N")} -> 765643230 | T7: {=_xll.PrecioBD(Q7,24,"IMBALANCE","N")} -> -0.0228
B8: ARS | C8: 1 | D8: =VLOOKUP(C8,Caucho!$E$66:$N$141,3,FALSE) -> #N/A | E8: =VLOOKUP(C8,Caucho!$E$66:$N$141,7,FALSE) -> #N/A | F8: =VLOOKUP(C8,Caucho!$E$66:$N$141,8,FALSE) -> #N/A | G8: =VLOOKUP(C8,Caucho!$E$66:$N$141,10,FALSE) -> #N/A | J8: AL35D | K8: =VLOOKUP(Tabla9[[#This Row],[Ticker]],ONs_NY8[[Ticker]:[Variación]],2,FALSE) -> 0.091250238 | L8: {=_xll.PrecioBD(Tabla9[[#This Row],[Ticker]],24,"ASK","N")} -> 78.67 | M8: =VLOOKUP(Tabla9[[#This Row],[Ticker]],ONs_NY8[[Ticker]:[Variación]],5,FALSE) -> 5.6790308 | N8: {=_xll.PrecioBD(Tabla9[[#This Row],[Ticker]],24,"IMBALANCE","N")} -> -0.0005 | Q8: PAMP | R8: {=_xll.PrecioBD(Q8,24,"ASK","N")} -> 4922.5 | S8: {=_xll.PrecioBD(Q8,24,"VOLUME AMOUNT","N")} -> 3104521655 | T8: {=_xll.PrecioBD(Q8,24,"IMBALANCE","N")} -> -0.008
B9: ARS | C9: 7 | D9: =VLOOKUP(C9,Caucho!$E$66:$N$141,3,FALSE) -> 0.2 | E9: =VLOOKUP(C9,Caucho!$E$66:$N$141,7,FALSE) -> 0.21 | F9: =VLOOKUP(C9,Caucho!$E$66:$N$141,8,FALSE) -> 0.238 | G9: =VLOOKUP(C9,Caucho!$E$66:$N$141,10,FALSE) -> 0.27097955 | J9: AL41D | K9: =VLOOKUP(Tabla9[[#This Row],[Ticker]],ONs_NY8[[Ticker]:[Variación]],2,FALSE) -> 0.069507185 | L9: {=_xll.PrecioBD(Tabla9[[#This Row],[Ticker]],24,"ASK","N")} -> 73.35 | M9: =VLOOKUP(Tabla9[[#This Row],[Ticker]],ONs_NY8[[Ticker]:[Variación]],5,FALSE) -> 7.5551069 | N9: {=_xll.PrecioBD(Tabla9[[#This Row],[Ticker]],24,"IMBALANCE","N")} -> -0.0083 | Q9: TGNO4 | R9: {=_xll.PrecioBD(Q9,24,"ASK","N")} -> 4000 | S9: {=_xll.PrecioBD(Q9,24,"VOLUME AMOUNT","N")} -> 1.4425626e+09 | T9: {=_xll.PrecioBD(Q9,24,"IMBALANCE","N")} -> -0.0308
B10: ARS | C10: 30 | D10: =VLOOKUP(C10,Caucho!$E$66:$N$141,3,FALSE) -> #N/A | E10: =VLOOKUP(C10,Caucho!$E$66:$N$141,7,FALSE) -> #N/A | F10: =VLOOKUP(C10,Caucho!$E$66:$N$141,8,FALSE) -> #N/A | G10: =VLOOKUP(C10,Caucho!$E$66:$N$141,10,FALSE) -> #N/A | J10: GD29D | K10: =VLOOKUP(Tabla9[[#This Row],[Ticker]],ONs_NY8[[Ticker]:[Variación]],2,FALSE) -> 0.06248239 | L10: {=_xll.PrecioBD(Tabla9[[#This Row],[Ticker]],24,"ASK","N")} -> 63.7 | M10: =VLOOKUP(Tabla9[[#This Row],[Ticker]],ONs_NY8[[Ticker]:[Variación]],5,FALSE) -> 1.7972543 | N10: {=_xll.PrecioBD(Tabla9[[#This Row],[Ticker]],24,"IMBALANCE","N")} -> 0 | Q10: BYMA | R10: {=_xll.PrecioBD(Q10,24,"ASK","N")} -> 329.75 | S10: {=_xll.PrecioBD(Q10,24,"VOLUME AMOUNT","N")} -> 1.8223637e+09 | T10: {=_xll.PrecioBD(Q10,24,"IMBALANCE","N")} -> -0.0119
J11: GD30D | K11: =VLOOKUP(Tabla9[[#This Row],[Ticker]],ONs_NY8[[Ticker]:[Variación]],2,FALSE) -> 0.070274821 | L11: {=_xll.PrecioBD(Tabla9[[#This Row],[Ticker]],24,"ASK","N")} -> 63.21 | M11: =VLOOKUP(Tabla9[[#This Row],[Ticker]],ONs_NY8[[Ticker]:[Variación]],5,FALSE) -> 2.2254087 | N11: {=_xll.PrecioBD(Tabla9[[#This Row],[Ticker]],24,"IMBALANCE","N")} -> 0.0017 | Q11: VALO | R11: {=_xll.PrecioBD(Q11,24,"ASK","N")} -> 584 | S11: {=_xll.PrecioBD(Q11,24,"VOLUME AMOUNT","N")} -> 1418758887 | T11: {=_xll.PrecioBD(Q11,24,"IMBALANCE","N")} -> -0.0143
A12: {=_xll.TiposCambioBD()} -> TIPO CAMBIO | B12: VENCIMIENTO | C12: ESPECIE | D12: SIMBOLO | E12: COMPRA | F12: VENTA | G12: ULTIMO | J12: GD35D | K12: =VLOOKUP(Tabla9[[#This Row],[Ticker]],ONs_NY8[[Ticker]:[Variación]],2,FALSE) -> 0.088632891 | L12: {=_xll.PrecioBD(Tabla9[[#This Row],[Ticker]],24,"ASK","N")} -> 79.8 | M12: =VLOOKUP(Tabla9[[#This Row],[Ticker]],ONs_NY8[[Ticker]:[Variación]],5,FALSE) -> 5.6982618 | N12: {=_xll.PrecioBD(Tabla9[[#This Row],[Ticker]],24,"IMBALANCE","N")} -> -0.0023 | Q12: CRES | R12: {=_xll.PrecioBD(Q12,24,"ASK","N")} -> 1911 | S12: {=_xll.PrecioBD(Q12,24,"VOLUME AMOUNT","N")} -> 328995806 | T12: {=_xll.PrecioBD(Q12,24,"IMBALANCE","N")} -> -0.0204
J13: GD38D | K13: =VLOOKUP(Tabla9[[#This Row],[Ticker]],ONs_NY8[[Ticker]:[Variación]],2,FALSE) -> 0.088778743 | L13: {=_xll.PrecioBD(Tabla9[[#This Row],[Ticker]],24,"ASK","N")} -> 82.86 | M13: =VLOOKUP(Tabla9[[#This Row],[Ticker]],ONs_NY8[[Ticker]:[Variación]],5,FALSE) -> 4.9813448 | N13: {=_xll.PrecioBD(Tabla9[[#This Row],[Ticker]],24,"IMBALANCE","N")} -> -0.0016 | Q13: ALUA | R13: {=_xll.PrecioBD(Q13,24,"ASK","N")} -> 980 | S13: {=_xll.PrecioBD(Q13,24,"VOLUME AMOUNT","N")} -> 1054451303 | T13: {=_xll.PrecioBD(Q13,24,"IMBALANCE","N")} -> 0.0046
B14: 2026-02-04 | C14: GD30/GD30C | D14: GD30/GD30C (CI) | E14: 1494 | F14: 1495.8 | G14: 1493.3 | J14: GD41D | K14: =VLOOKUP(Tabla9[[#This Row],[Ticker]],ONs_NY8[[Ticker]:[Variación]],2,FALSE) -> 0.067179868 | L14: {=_xll.PrecioBD(Tabla9[[#This Row],[Ticker]],24,"ASK","N")} -> 74.28 | M14: =VLOOKUP(Tabla9[[#This Row],[Ticker]],ONs_NY8[[Ticker]:[Variación]],5,FALSE) -> 7.6189885 | N14: {=_xll.PrecioBD(Tabla9[[#This Row],[Ticker]],24,"IMBALANCE","N")} -> -0.0022 | Q14: GGAL | R14: {=_xll.PrecioBD(Q14,24,"ASK","N")} -> 7525 | S14: {=_xll.PrecioBD(Q14,24,"VOLUME AMOUNT","N")} -> 38345100540 | T14: {=_xll.PrecioBD(Q14,24,"IMBALANCE","N")} -> -0.0334
B15: 2026-02-04 | C15: GD30/GD30D | D15: GD30/GD30D (CI) | E15: 1455.7 | F15: 1457.3 | G15: 1456.9 | Q15: COME | R15: {=_xll.PrecioBD(Q15,24,"ASK","N")} -> 50.4 | S15: {=_xll.PrecioBD(Q15,24,"VOLUME AMOUNT","N")} -> 9.4522398e+08 | T15: {=_xll.PrecioBD(Q15,24,"IMBALANCE","N")} -> -0.0472
B16: 2026-02-04 | C16: MAE | D16: Dolar Mayorista Bancos - Argentina | E16: 1437 | F16: 1446 | G16: 1446 | J16: Spread | K16: Delta | Q16: TGSU2 | R16: {=_xll.PrecioBD(Q16,24,"ASK","N")} -> 8790 | S16: {=_xll.PrecioBD(Q16,24,"VOLUME AMOUNT","N")} -> 1388241715 | T16: {=_xll.PrecioBD(Q16,24,"IMBALANCE","N")} -> -0.0184
B17: 2026-02-04 | C17: USB | D17: Dolar Banco Nacion Billete - Argentina | E17: 1415 | F17: 1465 | G17: 1465 | J17: AL29/GD29 | K17: {=_xll.PrecioBD("GD29D",24,"ASK","N")/_xll.PrecioBD("AL29D",24,"ASK","N")-1} -> 0.044776119 | Q17: METR | R17: {=_xll.PrecioBD(Q17,24,"ASK","N")} -> 2250 | S17: {=_xll.PrecioBD(Q17,24,"VOLUME AMOUNT","N")} -> 1826416388 | T17: {=_xll.PrecioBD(Q17,24,"IMBALANCE","N")} -> 0.0363
B18: 2026-02-04 | C18: USD | D18: Dolar x Peso Argentino BNA | E18: 1437 | F18: 1446 | G18: 1446 | J18: AL30/GD30 | K18: {=_xll.PrecioBD("GD30D",24,"ASK","N")/_xll.PrecioBD("AL30D",24,"ASK","N")-1} -> 0.043413668 | Q18: LOMA | R18: {=_xll.PrecioBD(Q18,24,"ASK","N")} -> 3230 | S18: {=_xll.PrecioBD(Q18,24,"VOLUME AMOUNT","N")} -> 1480430810 | T18: {=_xll.PrecioBD(Q18,24,"IMBALANCE","N")} -> 0.0189
J19: AL35/GD35 | K19: {=_xll.PrecioBD("GD35D",24,"ASK","N")/_xll.PrecioBD("AL35D",24,"ASK","N")-1} -> 0.014363798 | Q19: BMA | R19: {=_xll.PrecioBD(Q19,24,"ASK","N")} -> 13390 | S19: {=_xll.PrecioBD(Q19,24,"VOLUME AMOUNT","N")} -> 4901909650 | T19: {=_xll.PrecioBD(Q19,24,"IMBALANCE","N")} -> -0.0471
B20: Plazo fijo | C20: PF - Caucho | D20: PF - Lecap | F20: MEP | G20: CCL | J20: AE38/GD38 | K20: {=_xll.PrecioBD("GD38D",24,"ASK","N")/_xll.PrecioBD("AE38D",24,"ASK","N")-1} -> 0.035103061 | Q20: SUPV | R20: {=_xll.PrecioBD(Q20,24,"ASK","N")} -> 3160 | S20: {=_xll.PrecioBD(Q20,24,"VOLUME AMOUNT","N")} -> 3276570805 | T20: {=_xll.PrecioBD(Q20,24,"IMBALANCE","N")} -> -0.0474
B21: 0.26 | C21: =E8-B21 -> #N/A | F21: {=(1+_xll.PrecioBD("AL30","CI","IMBALANCE","N"))/(1+_xll.PrecioBD("AL30D","CI","IMBALANCE","N"))-1} -> 0.0023906764 | G21: {=(1+_xll.PrecioBD("AL30","CI","IMBALANCE","N"))/(1+_xll.PrecioBD("AL30C","CI","IMBALANCE","N"))-1} -> 0.0071056845 | J21: AL41/GD41 | K21: {=_xll.PrecioBD("GD41D",24,"ASK","N")/_xll.PrecioBD("AL41D",24,"ASK","N")-1} -> 0.012678937 | Q21: CEPU | R21: {=_xll.PrecioBD(Q21,24,"ASK","N")} -> 2330 | S21: {=_xll.PrecioBD(Q21,24,"VOLUME AMOUNT","N")} -> 1204640889 | T21: {=_xll.PrecioBD(Q21,24,"IMBALANCE","N")} -> -0.0197
Q22: EDN | R22: {=_xll.PrecioBD(Q22,24,"ASK","N")} -> 2018 | S22: {=_xll.PrecioBD(Q22,24,"VOLUME AMOUNT","N")} -> 1027865902 | T22: {=_xll.PrecioBD(Q22,24,"IMBALANCE","N")} -> -0.0208
Q23: TECO2 | R23: {=_xll.PrecioBD(Q23,24,"ASK","N")} -> 3490 | S23: {=_xll.PrecioBD(Q23,24,"VOLUME AMOUNT","N")} -> 531370580 | T23: {=_xll.PrecioBD(Q23,24,"IMBALANCE","N")} -> -0.0398
Q24: BBAR | R24: {=_xll.PrecioBD(Q24,24,"ASK","N")} -> 8820 | S24: {=_xll.PrecioBD(Q24,24,"VOLUME AMOUNT","N")} -> 2162042740 | T24: {=_xll.PrecioBD(Q24,24,"IMBALANCE","N")} -> -0.0564
A26: CEDEARs | B26: Ticker | C26: Precio | D26: Total volume | E26: Variación | I26: Indices | J26: Ticker | K26: Precio | L26: Total volume | M26: Variación
B27: LLY | C27: {=_xll.PrecioBD(B27,24,"ASK","N")} -> 27680 | D27: {=_xll.PrecioBD(B27,24,"VOLUME AMOUNT","N")} -> 605226780 | E27: {=_xll.PrecioBD(B27,24,"IMBALANCE","N")} -> -0.0683 | J27: SLV | K27: {=_xll.PrecioBD(J27,24,"ASK","N")} -> 17080 | L27: {=_xll.PrecioBD(J27,24,"VOLUME AMOUNT","N")} -> 9368501220 | M27: {=_xll.PrecioBD(J27,24,"IMBALANCE","N")} -> -0.1353
B28: GSK | C28: {=_xll.PrecioBD(B28,24,"ASK","N")} -> 22420 | D28: {=_xll.PrecioBD(B28,24,"VOLUME AMOUNT","N")} -> 32991220 | E28: {=_xll.PrecioBD(B28,24,"IMBALANCE","N")} -> 0.0401 | J28: USO | K28: {=_xll.PrecioBD(J28,24,"ASK","N")} -> 7750 | L28: {=_xll.PrecioBD(J28,24,"VOLUME AMOUNT","N")} -> 10757595 | M28: {=_xll.PrecioBD(J28,24,"IMBALANCE","N")} -> -0.0083
B29: AMGN | C29: {=_xll.PrecioBD(B29,24,"ASK","N")} -> 18450 | D29: {=_xll.PrecioBD(B29,24,"VOLUME AMOUNT","N")} -> 50834290 | E29: {=_xll.PrecioBD(B29,24,"IMBALANCE","N")} -> 0.0027 | J29: XLE | K29: {=_xll.PrecioBD(J29,24,"ASK","N")} -> 39500 | L29: {=_xll.PrecioBD(J29,24,"VOLUME AMOUNT","N")} -> 596468420 | M29: {=_xll.PrecioBD(J29,24,"IMBALANCE","N")} -> 0.003
B30: ARCO | C30: {=_xll.PrecioBD(B30,24,"ASK","N")} -> 25880 | D30: {=_xll.PrecioBD(B30,24,"VOLUME AMOUNT","N")} -> 345206600 | E30: {=_xll.PrecioBD(B30,24,"IMBALANCE","N")} -> -0.0271 | J30: IJH | K30: {=_xll.PrecioBD(J30,24,"ASK","N")} -> 8800 | L30: {=_xll.PrecioBD(J30,24,"VOLUME AMOUNT","N")} -> 6035760 | M30: {=_xll.PrecioBD(J30,24,"IMBALANCE","N")} -> -0.0034
B31: DOW | C31: {=_xll.PrecioBD(B31,24,"ASK","N")} -> 7690 | D31: {=_xll.PrecioBD(B31,24,"VOLUME AMOUNT","N")} -> 114358905 | E31: {=_xll.PrecioBD(B31,24,"IMBALANCE","N")} -> -0.057 | J31: GLD | K31: {=_xll.PrecioBD(J31,24,"ASK","N")} -> 13370 | L31: {=_xll.PrecioBD(J31,24,"VOLUME AMOUNT","N")} -> 2767549920 | M31: {=_xll.PrecioBD(J31,24,"IMBALANCE","N")} -> -0.0161
B32: IP | C32: {=_xll.PrecioBD(B32,24,"ASK","N")} -> 17000 | D32: {=_xll.PrecioBD(B32,24,"VOLUME AMOUNT","N")} -> 224784100 | E32: {=_xll.PrecioBD(B32,24,"IMBALANCE","N")} -> -0.0112 | J32: DIA | K32: {=_xll.PrecioBD(J32,24,"ASK","N")} -> 36960 | L32: {=_xll.PrecioBD(J32,24,"VOLUME AMOUNT","N")} -> 868964960 | M32: {=_xll.PrecioBD(J32,24,"IMBALANCE","N")} -> -0.0064
B33: PSX | C33: {=_xll.PrecioBD(B33,24,"ASK","N")} -> 39260 | D33: {=_xll.PrecioBD(B33,24,"VOLUME AMOUNT","N")} -> 7041540 | E33: {=_xll.PrecioBD(B33,24,"IMBALANCE","N")} -> 0.0041 | J33: VEA | K33: {=_xll.PrecioBD(J33,24,"ASK","N")} -> 0 | L33: {=_xll.PrecioBD(J33,24,"VOLUME AMOUNT","N")} -> 92175345 | M33: {=_xll.PrecioBD(J33,24,"IMBALANCE","N")} -> -0.0104
B34: AAP | C34: {=_xll.PrecioBD(B34,24,"ASK","N")} -> 5720 | D34: {=_xll.PrecioBD(B34,24,"VOLUME AMOUNT","N")} -> 96757585 | E34: {=_xll.PrecioBD(B34,24,"IMBALANCE","N")} -> -0.0181 | J34: IEUR | K34: {=_xll.PrecioBD(J34,24,"ASK","N")} -> 10140 | L34: {=_xll.PrecioBD(J34,24,"VOLUME AMOUNT","N")} -> 36890210 | M34: {=_xll.PrecioBD(J34,24,"IMBALANCE","N")} -> -0.0078
B35: XROX | C35: {=_xll.PrecioBD(B35,24,"ASK","N")} -> 3395 | D35: {=_xll.PrecioBD(B35,24,"VOLUME AMOUNT","N")} -> 404035740 | E35: {=_xll.PrecioBD(B35,24,"IMBALANCE","N")} -> -0.0548 | J35: VXX | K35: {=_xll.PrecioBD(J35,24,"ASK","N")} -> 8665 | L35: {=_xll.PrecioBD(J35,24,"VOLUME AMOUNT","N")} -> 673293070 | M35: {=_xll.PrecioBD(J35,24,"IMBALANCE","N")} -> 0.0523
B36: BKR | C36: {=_xll.PrecioBD(B36,24,"ASK","N")} -> 12300 | D36: {=_xll.PrecioBD(B36,24,"VOLUME AMOUNT","N")} -> 451800 | E36: {=_xll.PrecioBD(B36,24,"IMBALANCE","N")} -> -0.0144 | J36: SPY | K36: {=_xll.PrecioBD(J36,24,"ASK","N")} -> 51100 | L36: {=_xll.PrecioBD(J36,24,"VOLUME AMOUNT","N")} -> 6013950575 | M36: {=_xll.PrecioBD(J36,24,"IMBALANCE","N")} -> -0.0082
B37: HPQ | C37: {=_xll.PrecioBD(B37,24,"ASK","N")} -> 30000 | D37: {=_xll.PrecioBD(B37,24,"VOLUME AMOUNT","N")} -> 177274720 | E37: {=_xll.PrecioBD(B37,24,"IMBALANCE","N")} -> -0.0407 | J37: IEMG | K37: {=_xll.PrecioBD(J37,24,"ASK","N")} -> 0 | L37: {=_xll.PrecioBD(J37,24,"VOLUME AMOUNT","N")} -> 30049325 | M37: {=_xll.PrecioBD(J37,24,"IMBALANCE","N")} -> 0.0005
B38: CAR | C38: {=_xll.PrecioBD(B38,24,"ASK","N")} -> 7340 | D38: {=_xll.PrecioBD(B38,24,"VOLUME AMOUNT","N")} -> 6055140 | E38: {=_xll.PrecioBD(B38,24,"IMBALANCE","N")} -> -0.0901 | J38: IWM | K38: {=_xll.PrecioBD(J38,24,"ASK","N")} -> 39140 | L38: {=_xll.PrecioBD(J38,24,"VOLUME AMOUNT","N")} -> 328708760 | M38: {=_xll.PrecioBD(J38,24,"IMBALANCE","N")} -> -0.0123
... B45: HMC | C45: {=_xll.PrecioBD(B45,24,"ASK","N")} -> 56000 | D45: {=_xll.PrecioBD(B45,24,"VOLUME AMOUNT","N")} -> 15724700 | E45: {=_xll.PrecioBD(B45,24,"IMBALANCE","N")} -> -0.005 | J45: URA | K45: {=_xll.PrecioBD(J45,24,"ASK","N")} -> 15100 | L45: {=_xll.PrecioBD(J45,24,"VOLUME AMOUNT","N")} -> 562502000 | M45: {=_xll.PrecioBD(J45,24,"IMBALANCE","N")} -> -0.0396
B46: GLOB | C46: {=_xll.PrecioBD(B46,24,"ASK","N")} -> 4725 | D46: {=_xll.PrecioBD(B46,24,"VOLUME AMOUNT","N")} -> 5.8005604e+08 | E46: {=_xll.PrecioBD(B46,24,"IMBALANCE","N")} -> -0.0566
B47: AVY | C47: {=_xll.PrecioBD(B47,24,"ASK","N")} -> 16360 | D47: {=_xll.PrecioBD(B47,24,"VOLUME AMOUNT","N")} -> 1971020 | E47: {=_xll.PrecioBD(B47,24,"IMBALANCE","N")} -> 0.0155
B48: MFG | C48: {=_xll.PrecioBD(B48,24,"ASK","N")} -> 13800 | D48: {=_xll.PrecioBD(B48,24,"VOLUME AMOUNT","N")} -> 5248160 | E48: {=_xll.PrecioBD(B48,24,"IMBALANCE","N")} -> -0.0195
B49: ARM | C49: {=_xll.PrecioBD(B49,24,"ASK","N")} -> 6490 | D49: {=_xll.PrecioBD(B49,24,"VOLUME AMOUNT","N")} -> 176602010 | E49: {=_xll.PrecioBD(B49,24,"IMBALANCE","N")} -> 0.0823
B50: NKE | C50: {=_xll.PrecioBD(B50,24,"ASK","N")} -> 7890 | D50: {=_xll.PrecioBD(B50,24,"VOLUME AMOUNT","N")} -> 346820705 | E50: {=_xll.PrecioBD(B50,24,"IMBALANCE","N")} -> -0.0125
B51: DE | C51: {=_xll.PrecioBD(B51,24,"ASK","N")} -> 21450 | D51: {=_xll.PrecioBD(B51,24,"VOLUME AMOUNT","N")} -> 60965990 | E51: {=_xll.PrecioBD(B51,24,"IMBALANCE","N")} -> 0.0075
B52: BIIB | C52: {=_xll.PrecioBD(B52,24,"ASK","N")} -> 21620 | D52: {=_xll.PrecioBD(B52,24,"VOLUME AMOUNT","N")} -> 80369420 | E52: {=_xll.PrecioBD(B52,24,"IMBALANCE","N")} -> 0
B53: PFE | C53: {=_xll.PrecioBD(B53,24,"ASK","N")} -> 10120 | D53: {=_xll.PrecioBD(B53,24,"VOLUME AMOUNT","N")} -> 434640290 | E53: {=_xll.PrecioBD(B53,24,"IMBALANCE","N")} -> 0.0105
B54: AKO.B | C54: {=_xll.PrecioBD(B54,24,"ASK","N")} -> 49900 | D54: {=_xll.PrecioBD(B54,24,"VOLUME AMOUNT","N")} -> 870700 | E54: {=_xll.PrecioBD(B54,24,"IMBALANCE","N")} -> -0.0298
B55: SWKS | C55: {=_xll.PrecioBD(B55,24,"ASK","N")} -> 4400 | D55: {=_xll.PrecioBD(B55,24,"VOLUME AMOUNT","N")} -> 1386325 | E55: {=_xll.PrecioBD(B55,24,"IMBALANCE","N")} -> 0.0109
B56: STLA | C56: {=_xll.PrecioBD(B56,24,"ASK","N")} -> 2925 | D56: {=_xll.PrecioBD(B56,24,"VOLUME AMOUNT","N")} -> 1.0148724e+08 | E56: {=_xll.PrecioBD(B56,24,"IMBALANCE","N")} -> -0.0515
B57: SLB | C57: {=_xll.PrecioBD(B57,24,"ASK","N")} -> 25000 | D57: {=_xll.PrecioBD(B57,24,"VOLUME AMOUNT","N")} -> 60195670 | E57: {=_xll.PrecioBD(B57,24,"IMBALANCE","N")} -> -0.0149
... B430: AMD | C430: {=_xll.PrecioBD(B430,24,"ASK","N")} -> 28800 | D430: {=_xll.PrecioBD(B430,24,"VOLUME AMOUNT","N")} -> 3612326860 | E430: {=_xll.PrecioBD(B430,24,"IMBALANCE","N")} -> -0.0564
B431: WBA | C431: {=_xll.PrecioBD(B431,24,"ASK","N")} -> 0 | D431: {=_xll.PrecioBD(B431,24,"VOLUME AMOUNT","N")} -> 0

Sheet Opciones
A1: =_xll.PanelOpcionesBD() -> OPCIONES | B1: SIMBOLO | C1: VTO. | D1: MONEDA | E1: C.CPRA. | F1: P.CPRA. | G1: P.VTA. | H1: C.VTA. | I1: APERTURA | J1: MINIMO | K1: MAXIMO | L1: ULTIMO | M1: CIERRE ANT. | N1: VAR. | O1: VOLUMEN | P1: VOL.MONTO | Q1: VWAP | R1: CIERRE | S1: HORA
B2: A30C90000A | C2: 24hs | D2: ARS | E2: 0 | F2: 0 | G2: 0 | H2: 0 | I2: 0 | J2: 0 | K2: 0 | L2: 0 | M2: 0 | N2: 0 | O2: 0 | P2: 0 | Q2: 0 | R2: 0
B3: A30C90000F | C3: 24hs | D3: ARS | E3: 0 | F3: 0 | G3: 0 | H3: 0 | I3: 0 | J3: 0 | K3: 0 | L3: 0 | M3: 0 | N3: 0 | O3: 0 | P3: 0 | Q3: 0 | R3: 0
B4: A30C90000M | C4: 24hs | D4: ARS | E4: 0 | F4: 0 | G4: 0 | H4: 0 | I4: 0 | J4: 0 | K4: 0 | L4: 0 | M4: 0 | N4: 0 | O4: 0 | P4: 0 | Q4: 0 | R4: 0
B5: A30C92000A | C5: 24hs | D5: ARS | E5: 0 | F5: 0 | G5: 0 | H5: 0 | I5: 0 | J5: 0 | K5: 0 | L5: 0 | M5: 0 | N5: 0 | O5: 0 | P5: 0 | Q5: 0 | R5: 0
B6: A30C92000F | C6: 24hs | D6: ARS | E6: 0 | F6: 0 | G6: 0 | H6: 0 | I6: 0 | J6: 0 | K6: 0 | L6: 0 | M6: 0 | N6: 0 | O6: 0 | P6: 0 | Q6: 0 | R6: 0
B7: A30C92000M | C7: 24hs | D7: ARS | E7: 0 | F7: 0 | G7: 0 | H7: 0 | I7: 0 | J7: 0 | K7: 0 | L7: 0 | M7: 0 | N7: 0 | O7: 0 | P7: 0 | Q7: 0 | R7: 0
B8: A30V90000A | C8: 24hs | D8: ARS | E8: 0 | F8: 0 | G8: 0 | H8: 0 | I8: 0 | J8: 0 | K8: 0 | L8: 0 | M8: 0 | N8: 0 | O8: 0 | P8: 0 | Q8: 0 | R8: 0
B9: A30V90000F | C9: 24hs | D9: ARS | E9: 0 | F9: 0 | G9: 0 | H9: 0 | I9: 0 | J9: 0 | K9: 0 | L9: 0 | M9: 0 | N9: 0 | O9: 0 | P9: 0 | Q9: 0 | R9: 0
B10: A30V90000M | C10: 24hs | D10: ARS | E10: 0 | F10: 0 | G10: 0 | H10: 0 | I10: 0 | J10: 0 | K10: 0 | L10: 0 | M10: 0 | N10: 0 | O10: 0 | P10: 0 | Q10: 0 | R10: 0
B11: A30V92000A | C11: 24hs | D11: ARS | E11: 0 | F11: 0 | G11: 0 | H11: 0 | I11: 0 | J11: 0 | K11: 0 | L11: 0 | M11: 0 | N11: 0 | O11: 0 | P11: 0 | Q11: 0 | R11: 0
B12: A30V92000F | C12: 24hs | D12: ARS | E12: 0 | F12: 0 | G12: 0 | H12: 0 | I12: 0 | J12: 0 | K12: 0 | L12: 0 | M12: 0 | N12: 0 | O12: 0 | P12: 0 | Q12: 0 | R12: 0
B13: A30V92000M | C13: 24hs | D13: ARS | E13: 0 | F13: 0 | G13: 0 | H13: 0 | I13: 0 | J13: 0 | K13: 0 | L13: 0 | M13: 0 | N13: 0 | O13: 0 | P13: 0 | Q13: 0 | R13: 0
... B4206: TRAC4000AB | C4206: 24hs | D4206: ARS | E4206: 0 | F4206: 0 | G4206: 0 | H4206: 0 | I4206: 0 | J4206: 0 | K4206: 0 | L4206: 0 | M4206: 950 | N4206: 0 | O4206: 0 | P4206: 0 | Q4206: 0 | R4206: 950
B4207: TRAC4000FE | C4207: 24hs | D4207: ARS | E4207: 0 | F4207: 0 | G4207: 185 | H4207: 7 | I4207: 130 | J4207: 130 | K4207: 130 | L4207: 130 | M4207: 120 | N4207: 0.0833 | O4207: 5 | P4207: 65000 | Q4207: 130 | R4207: 130 | S4207: 13:06:14
B4208: TRAC4000JU | C4208: 24hs | D4208: ARS | E4208: 1 | F4208: 422.1 | G4208: 718.8 | H4208: 10 | I4208: 0 | J4208: 0 | K4208: 0 | L4208: 0 | M4208: 400 | N4208: 0 | O4208: 0 | P4208: 0 | Q4208: 0 | R4208: 400
B4209: TRAC4000MA | C4209: 24hs | D4209: ARS | E4209: 0 | F4209: 0 | G4209: 0 | H4209: 0 | I4209: 0 | J4209: 0 | K4209: 0 | L4209: 0 | M4209: 0 | N4209: 0 | O4209: 0 | P4209: 0 | Q4209: 0 | R4209: 0
B4210: TRAC4200AB | C4210: 24hs | D4210: ARS | E4210: 0 | F4210: 0 | G4210: 0 | H4210: 0 | I4210: 0 | J4210: 0 | K4210: 0 | L4210: 0 | M4210: 0 | N4210: 0 | O4210: 0 | P4210: 0 | Q4210: 0 | R4210: 0
B4211: TRAC4200FE | C4211: 24hs | D4211: ARS | E4211: 0 | F4211: 0 | G4211: 0 | H4211: 0 | I4211: 0 | J4211: 0 | K4211: 0 | L4211: 0 | M4211: 0 | N4211: 0 | O4211: 0 | P4211: 0 | Q4211: 0 | R4211: 0
B4212: TRAC4200JU | C4212: 24hs | D4212: ARS | E4212: 1 | F4212: 343.6 | G4212: 0 | H4212: 0 | I4212: 0 | J4212: 0 | K4212: 0 | L4212: 0 | M4212: 0 | N4212: 0 | O4212: 0 | P4212: 0 | Q4212: 0 | R4212: 0
B4213: TRAC4200MA | C4213: 24hs | D4213: ARS | E4213: 0 | F4213: 0 | G4213: 0 | H4213: 0 | I4213: 0 | J4213: 0 | K4213: 0 | L4213: 0 | M4213: 0 | N4213: 0 | O4213: 0 | P4213: 0 | Q4213: 0 | R4213: 0
B4214: TRAC4400AB | C4214: 24hs | D4214: ARS | E4214: 0 | F4214: 0 | G4214: 0 | H4214: 0 | I4214: 0 | J4214: 0 | K4214: 0 | L4214: 0 | M4214: 0 | N4214: 0 | O4214: 0 | P4214: 0 | Q4214: 0 | R4214: 0
B4215: TRAC4400FE | C4215: 24hs | D4215: ARS | E4215: 0 | F4215: 0 | G4215: 0 | H4215: 0 | I4215: 0 | J4215: 0 | K4215: 0 | L4215: 0 | M4215: 0 | N4215: 0 | O4215: 0 | P4215: 0 | Q4215: 0 | R4215: 0
B4216: TRAC4400JU | C4216: 24hs | D4216: ARS | E4216: 0 | F4216: 0 | G4216: 0 | H4216: 0 | I4216: 0 | J4216: 0 | K4216: 0 | L4216: 0 | M4216: 0 | N4216: 0 | O4216: 0 | P4216: 0 | Q4216: 0 | R4216: 0
B4217: TRAC4400MA | C4217: 24hs | D4217: ARS | E4217: 0 | F4217: 0 | G4217: 0 | H4217: 0 | I4217: 0 | J4217: 0 | K4217: 0 | L4217: 0 | M4217: 0 | N4217: 0 | O4217: 0 | P4217: 0 | Q4217: 0 | R4217: 0
B4218: TRAC4600AB | C4218: 24hs | D4218: ARS | E4218: 0 | F4218: 0 | G4218: 0 | H4218: 0 | I4218: 0 | J4218: 0 | K4218: 0 | L4218: 0 | M4218: 0 | N4218: 0 | O4218: 0 | P4218: 0 | Q4218: 0 | R4218: 0
B4219: TRAC4600FE | C4219: 24hs | D4219: ARS | E4219: 0 | F4219: 0 | G4219: 0 | H4219: 0 | I4219: 0 | J4219: 0 | K4219: 0 | L4219: 0 | M4219: 0 | N4219: 0 | O4219: 0 | P4219: 0 | Q4219: 0 | R4219: 0
... B4333: TXAC54.0JU | C4333: 24hs | D4333: ARS | E4333: 0 | F4333: 0 | G4333: 0 | H4333: 0 | I4333: 0 | J4333: 0 | K4333: 0 | L4333: 0 | M4333: 0 | N4333: 0 | O4333: 0 | P4333: 0 | Q4333: 0 | R4333: 0
B4334: TXAC54807F | C4334: 24hs | D4334: ARS | E4334: 0 | F4334: 0 | G4334: 202 | H4334: 10 | I4334: 163 | J4334: 160 | K4334: 163 | L4334: 160 | M4334: 164.5 | N4334: -0.0273 | O4334: 20 | P4334: 323000 | Q4334: 161.5 | R4334: 161.5 | S4334: 15:16:51
B4335: TXAC550.FE | C4335: 24hs | D4335: ARS | E4335: 0 | F4335: 0 | G4335: 0 | H4335: 0 | I4335: 0 | J4335: 0 | K4335: 0 | L4335: 0 | M4335: 0 | N4335: 0 | O4335: 0 | P4335: 0 | Q4335: 0 | R4335: 0
B4336: TXAC56.0AB | C4336: 24hs | D4336: ARS | E4336: 0 | F4336: 0 | G4336: 0 | H4336: 0 | I4336: 0 | J4336: 0 | K4336: 0 | L4336: 0 | M4336: 0 | N4336: 0 | O4336: 0 | P4336: 0 | Q4336: 0 | R4336: 0
B4337: TXAC56.0AG | C4337: 24hs | D4337: ARS | E4337: 0 | F4337: 0 | G4337: 0 | H4337: 0 | I4337: 0 | J4337: 0 | K4337: 0 | L4337: 0 | M4337: 0 | N4337: 0 | O4337: 0 | P4337: 0 | Q4337: 0 | R4337: 0
B4338: TXAC56.0FE | C4338: 24hs | D4338: ARS | E4338: 0 | F4338: 0 | G4338: 0 | H4338: 0 | I4338: 0 | J4338: 0 | K4338: 0 | L4338: 0 | M4338: 0 | N4338: 0 | O4338: 0 | P4338: 0 | Q4338: 0 | R4338: 0
B4339: TXAC56.0JU | C4339: 24hs | D4339: ARS | E4339: 0 | F4339: 0 | G4339: 0 | H4339: 0 | I4339: 0 | J4339: 0 | K4339: 0 | L4339: 0 | M4339: 0 | N4339: 0 | O4339: 0 | P4339: 0 | Q4339: 0 | R4339: 0
B4340: TXAC56.0OC | C4340: 24hs | D4340: ARS | E4340: 0 | F4340: 0 | G4340: 0 | H4340: 0 | I4340: 0 | J4340: 0 | K4340: 0 | L4340: 0 | M4340: 0 | N4340: 0 | O4340: 0 | P4340: 0 | Q4340: 0 | R4340: 0
B4341: TXAC58.0AB | C4341: 24hs | D4341: ARS | E4341: 0 | F4341: 0 | G4341: 0 | H4341: 0 | I4341: 0 | J4341: 0 | K4341: 0 | L4341: 0 | M4341: 0 | N4341: 0 | O4341: 0 | P4341: 0 | Q4341: 0 | R4341: 0
B4342: TXAC58.0AG | C4342: 24hs | D4342: ARS | E4342: 0 | F4342: 0 | G4342: 0 | H4342: 0 | I4342: 0 | J4342: 0 | K4342: 0 | L4342: 0 | M4342: 0 | N4342: 0 | O4342: 0 | P4342: 0 | Q4342: 0 | R4342: 0
B4343: TXAC59807F | C4343: 24hs | D4343: ARS | E4343: 0 | F4343: 0 | G4343: 0 | H4343: 0 | I4343: 0 | J4343: 0 | K4343: 0 | L4343: 0 | M4343: 130.27 | N4343: 0 | O4343: 0 | P4343: 0 | Q4343: 0 | R4343: 130.27
B4344: TXAC60.0AB | C4344: 24hs | D4344: ARS | E4344: 0 | F4344: 0 | G4344: 0 | H4344: 0 | I4344: 0 | J4344: 0 | K4344: 0 | L4344: 0 | M4344: 0 | N4344: 0 | O4344: 0 | P4344: 0 | Q4344: 0 | R4344: 0
B4345: TXAC60.0AG | C4345: 24hs | D4345: ARS | E4345: 0 | F4345: 0 | G4345: 0 | H4345: 0 | I4345: 0 | J4345: 0 | K4345: 0 | L4345: 0 | M4345: 0 | N4345: 0 | O4345: 0 | P4345: 0 | Q4345: 0 | R4345: 0
B4346: TXAC60.0FE | C4346: 24hs | D4346: ARS | E4346: 0 | F4346: 0 | G4346: 0 | H4346: 0 | I4346: 0 | J4346: 0 | K4346: 0 | L4346: 0 | M4346: 0 | N4346: 0 | O4346: 0 | P4346: 0 | Q4346: 0 | R4346: 0
... B4367: TXAC68.0OC | C4367: 24hs | D4367: ARS | E4367: 0 | F4367: 0 | G4367: 0 | H4367: 0 | I4367: 0 | J4367: 0 | K4367: 0 | L4367: 0 | M4367: 0 | N4367: 0 | O4367: 0 | P4367: 0 | Q4367: 0 | R4367: 0
B4368: TXAC69807F | C4368: 24hs | D4368: ARS | E4368: 30 | F4368: 14 | G4368: 45 | H4368: 33 | I4368: 39 | J4368: 39 | K4368: 39 | L4368: 39 | M4368: 45 | N4368: -0.1333 | O4368: 10 | P4368: 39000 | Q4368: 39 | R4368: 39 | S4368: 13:52:19
B4369: TXAC70.0AG | C4369: 24hs | D4369: ARS | E4369: 0 | F4369: 0 | G4369: 0 | H4369: 0 | I4369: 0 | J4369: 0 | K4369: 0 | L4369: 0 | M4369: 0 | N4369: 0 | O4369: 0 | P4369: 0 | Q4369: 0 | R4369: 0
B4370: TXAC70.0JU | C4370: 24hs | D4370: ARS | E4370: 0 | F4370: 0 | G4370: 0 | H4370: 0 | I4370: 0 | J4370: 0 | K4370: 0 | L4370: 0 | M4370: 0 | N4370: 0 | O4370: 0 | P4370: 0 | Q4370: 0 | R4370: 0
B4371: TXAC70.0OC | C4371: 24hs | D4371: ARS | E4371: 0 | F4371: 0 | G4371: 0 | H4371: 0 | I4371: 0 | J4371: 0 | K4371: 0 | L4371: 0 | M4371: 0 | N4371: 0 | O4371: 0 | P4371: 0 | Q4371: 0 | R4371: 0
B4372: TXAC700.AB | C4372: 24hs | D4372: ARS | E4372: 30 | F4372: 50 | G4372: 100 | H4372: 60 | I4372: 0 | J4372: 0 | K4372: 0 | L4372: 0 | M4372: 0 | N4372: 0 | O4372: 0 | P4372: 0 | Q4372: 0 | R4372: 0
B4373: TXAC700.FE | C4373: 24hs | D4373: ARS | E4373: 0 | F4373: 0 | G4373: 0 | H4373: 0 | I4373: 0 | J4373: 0 | K4373: 0 | L4373: 0 | M4373: 0 | N4373: 0 | O4373: 0 | P4373: 0 | Q4373: 0 | R4373: 0
B4374: TXAC700.JU | C4374: 24hs | D4374: ARS | E4374: 0 | F4374: 0 | G4374: 0 | H4374: 0 | I4374: 0 | J4374: 0 | K4374: 0 | L4374: 0 | M4374: 0 | N4374: 0 | O4374: 0 | P4374: 0 | Q4374: 0 | R4374: 0
B4375: TXAC700.MA | C4375: 24hs | D4375: ARS | E4375: 0 | F4375: 0 | G4375: 0 | H4375: 0 | I4375: 0 | J4375: 0 | K4375: 0 | L4375: 0 | M4375: 0 | N4375: 0 | O4375: 0 | P4375: 0 | Q4375: 0 | R4375: 0
B4376: TXAC72.0AG | C4376: 24hs | D4376: ARS | E4376: 0 | F4376: 0 | G4376: 0 | H4376: 0 | I4376: 0 | J4376: 0 | K4376: 0 | L4376: 0 | M4376: 0 | N4376: 0 | O4376: 0 | P4376: 0 | Q4376: 0 | R4376: 0
B4377: TXAC72.0OC | C4377: 24hs | D4377: ARS | E4377: 0 | F4377: 0 | G4377: 0 | H4377: 0 | I4377: 0 | J4377: 0 | K4377: 0 | L4377: 0 | M4377: 0 | N4377: 0 | O4377: 0 | P4377: 0 | Q4377: 0 | R4377: 0
B4378: TXAC74.0AG | C4378: 24hs | D4378: ARS | E4378: 0 | F4378: 0 | G4378: 0 | H4378: 0 | I4378: 0 | J4378: 0 | K4378: 0 | L4378: 0 | M4378: 0 | N4378: 0 | O4378: 0 | P4378: 0 | Q4378: 0 | R4378: 0
B4379: TXAC74.0OC | C4379: 24hs | D4379: ARS | E4379: 0 | F4379: 0 | G4379: 0 | H4379: 0 | I4379: 0 | J4379: 0 | K4379: 0 | L4379: 0 | M4379: 0 | N4379: 0 | O4379: 0 | P4379: 0 | Q4379: 0 | R4379: 0
B4380: TXAC74807A | C4380: 24hs | D4380: ARS | E4380: 3 | F4380: 30.4 | G4380: 110 | H4380: 1 | I4380: 0 | J4380: 0 | K4380: 0 | L4380: 0 | M4380: 166.1 | N4380: 0 | O4380: 0 | P4380: 0 | Q4380: 0 | R4380: 166.1
B4381: TXAC74807F | C4381: 24hs | D4381: ARS | E4381: 5 | F4381: 2 | G4381: 6 | H4381: 46 | I4381: 6 | J4381: 6 | K4381: 6 | L4381: 6 | M4381: 9 | N4381: -0.3333 | O4381: 170 | P4381: 102000 | Q4381: 6 | R4381: 6 | S4381: 14:13:18
B4382: TXAC750.AB | C4382: 24hs | D4382: ARS | E4382: 4 | F4382: 28 | G4382: 0 | H4382: 0 | I4382: 0 | J4382: 0 | K4382: 0 | L4382: 0 | M4382: 0 | N4382: 0 | O4382: 0 | P4382: 0 | Q4382: 0 | R4382: 0
B4383: TXAC750.FE | C4383: 24hs | D4383: ARS | E4383: 0 | F4383: 0 | G4383: 0 | H4383: 0 | I4383: 0 | J4383: 0 | K4383: 0 | L4383: 0 | M4383: 0 | N4383: 0 | O4383: 0 | P4383: 0 | Q4383: 0 | R4383: 0
B4384: TXAC750.JU | C4384: 24hs | D4384: ARS | E4384: 2 | F4384: 53.9 | G4384: 0 | H4384: 0 | I4384: 0 | J4384: 0 | K4384: 0 | L4384: 0 | M4384: 0 | N4384: 0 | O4384: 0 | P4384: 0 | Q4384: 0 | R4384: 0
B4385: TXAC750.MA | C4385: 24hs | D4385: ARS | E4385: 0 | F4385: 0 | G4385: 0 | H4385: 0 | I4385: 0 | J4385: 0 | K4385: 0 | L4385: 0 | M4385: 0 | N4385: 0 | O4385: 0 | P4385: 0 | Q4385: 0 | R4385: 0
B4386: TXAC76.0AG | C4386: 24hs | D4386: ARS | E4386: 0 | F4386: 0 | G4386: 0 | H4386: 0 | I4386: 0 | J4386: 0 | K4386: 0 | L4386: 0 | M4386: 0 | N4386: 0 | O4386: 0 | P4386: 0 | Q4386: 0 | R4386: 0
B4387: TXAC76.0OC | C4387: 24hs | D4387: ARS | E4387: 0 | F4387: 0 | G4387: 0 | H4387: 0 | I4387: 0 | J4387: 0 | K4387: 0 | L4387: 0 | M4387: 0 | N4387: 0 | O4387: 0 | P4387: 0 | Q4387: 0 | R4387: 0
B4388: TXAC78.0AG | C4388: 24hs | D4388: ARS | E4388: 0 | F4388: 0 | G4388: 0 | H4388: 0 | I4388: 0 | J4388: 0 | K4388: 0 | L4388: 0 | M4388: 0 | N4388: 0 | O4388: 0 | P4388: 0 | Q4388: 0 | R4388: 0
B4389: TXAC78.0OC | C4389: 24hs | D4389: ARS | E4389: 0 | F4389: 0 | G4389: 0 | H4389: 0 | I4389: 0 | J4389: 0 | K4389: 0 | L4389: 0 | M4389: 0 | N4389: 0 | O4389: 0 | P4389: 0 | Q4389: 0 | R4389: 0
B4390: TXAC79807F | C4390: 24hs | D4390: ARS | E4390: 6 | F4390: 1 | G4390: 4.5 | H4390: 100 | I4390: 0 | J4390: 0 | K4390: 0 | L4390: 0 | M4390: 8 | N4390: 0 | O4390: 0 | P4390: 0 | Q4390: 0 | R4390: 8
B4391: TXAC80.0AG | C4391: 24hs | D4391: ARS | E4391: 0 | F4391: 0 | G4391: 0 | H4391: 0 | I4391: 0 | J4391: 0 | K4391: 0 | L4391: 0 | M4391: 0 | N4391: 0 | O4391: 0 | P4391: 0 | Q4391: 0 | R4391: 0
B4392: TXAC80.0OC | C4392: 24hs | D4392: ARS | E4392: 0 | F4392: 0 | G4392: 0 | H4392: 0 | I4392: 0 | J4392: 0 | K4392: 0 | L4392: 0 | M4392: 0 | N4392: 0 | O4392: 0 | P4392: 0 | Q4392: 0 | R4392: 0
B4393: TXAC800.AB | C4393: 24hs | D4393: ARS | E4393: 5 | F4393: 16.43 | G4393: 75 | H4393: 50 | I4393: 0 | J4393: 0 | K4393: 0 | L4393: 0 | M4393: 78 | N4393: 0 | O4393: 0 | P4393: 0 | Q4393: 0 | R4393: 78
... B4400: TXAC84.0OC | C4400: 24hs | D4400: ARS | E4400: 0 | F4400: 0 | G4400: 0 | H4400: 0 | I4400: 0 | J4400: 0 | K4400: 0 | L4400: 0 | M4400: 0 | N4400: 0 | O4400: 0 | P4400: 0 | Q4400: 0 | R4400: 0
B4401: TXAC84807F | C4401: 24hs | D4401: ARS | E4401: 100 | F4401: 0.5 | G4401: 1 | H4401: 4239 | I4401: 1 | J4401: 1 | K4401: 1 | L4401: 1 | M4401: 1 | N4401: 0 | O4401: 17 | P4401: 1700 | Q4401: 1 | R4401: 1 | S4401: 16:49:50
B4402: TXAC850.AB | C4402: 24hs | D4402: ARS | E4402: 0 | F4402: 0 | G4402: 0 | H4402: 0 | I4402: 0 | J4402: 0 | K4402: 0 | L4402: 0 | M4402: 0 | N4402: 0 | O4402: 0 | P4402: 0 | Q4402: 0 | R4402: 0
B4403: TXAC850.FE | C4403: 24hs | D4403: ARS | E4403: 0 | F4403: 0 | G4403: 0 | H4403: 0 | I4403: 0 | J4403: 0 | K4403: 0 | L4403: 0 | M4403: 0 | N4403: 0 | O4403: 0 | P4403: 0 | Q4403: 0 | R4403: 0
B4404: TXAC850.JU | C4404: 24hs | D4404: ARS | E4404: 4 | F4404: 30.4 | G4404: 0 | H4404: 0 | I4404: 0 | J4404: 0 | K4404: 0 | L4404: 0 | M4404: 0 | N4404: 0 | O4404: 0 | P4404: 0 | Q4404: 0 | R4404: 0
B4405: TXAC850.MA | C4405: 24hs | D4405: ARS | E4405: 0 | F4405: 0 | G4405: 0 | H4405: 0 | I4405: 0 | J4405: 0 | K4405: 0 | L4405: 0 | M4405: 0 | N4405: 0 | O4405: 0 | P4405: 0 | Q4405: 0 | R4405: 0
B4406: TXAC86.0AG | C4406: 24hs | D4406: ARS | E4406: 0 | F4406: 0 | G4406: 0 | H4406: 0 | I4406: 0 | J4406: 0 | K4406: 0 | L4406: 0 | M4406: 0 | N4406: 0 | O4406: 0 | P4406: 0 | Q4406: 0 | R4406: 0
B4407: TXAC86.0OC | C4407: 24hs | D4407: ARS | E4407: 0 | F4407: 0 | G4407: 0 | H4407: 0 | I4407: 0 | J4407: 0 | K4407: 0 | L4407: 0 | M4407: 0 | N4407: 0 | O4407: 0 | P4407: 0 | Q4407: 0 | R4407: 0
B4408: TXAC88.0AG | C4408: 24hs | D4408: ARS | E4408: 0 | F4408: 0 | G4408: 0 | H4408: 0 | I4408: 0 | J4408: 0 | K4408: 0 | L4408: 0 | M4408: 0 | N4408: 0 | O4408: 0 | P4408: 0 | Q4408: 0 | R4408: 0
B4409: TXAC88.0OC | C4409: 24hs | D4409: ARS | E4409: 0 | F4409: 0 | G4409: 0 | H4409: 0 | I4409: 0 | J4409: 0 | K4409: 0 | L4409: 0 | M4409: 0 | N4409: 0 | O4409: 0 | P4409: 0 | Q4409: 0 | R4409: 0
B4410: TXAC90.0AG | C4410: 24hs | D4410: ARS | E4410: 0 | F4410: 0 | G4410: 0 | H4410: 0 | I4410: 0 | J4410: 0 | K4410: 0 | L4410: 0 | M4410: 0 | N4410: 0 | O4410: 0 | P4410: 0 | Q4410: 0 | R4410: 0
B4411: TXAC90.0OC | C4411: 24hs | D4411: ARS | E4411: 0 | F4411: 0 | G4411: 0 | H4411: 0 | I4411: 0 | J4411: 0 | K4411: 0 | L4411: 0 | M4411: 0 | N4411: 0 | O4411: 0 | P4411: 0 | Q4411: 0 | R4411: 0
B4412: TXAC900.AB | C4412: 24hs | D4412: ARS | E4412: 0 | F4412: 0 | G4412: 25 | H4412: 250 | I4412: 20 | J4412: 20 | K4412: 20 | L4412: 20 | M4412: 20 | N4412: 0 | O4412: 700 | P4412: 1400000 | Q4412: 20 | R4412: 20 | S4412: 16:31:55
B4413: TXAC900.FE | C4413: 24hs | D4413: ARS | E4413: 0 | F4413: 0 | G4413: 0 | H4413: 0 | I4413: 0 | J4413: 0 | K4413: 0 | L4413: 0 | M4413: 0 | N4413: 0 | O4413: 0 | P4413: 0 | Q4413: 0 | R4413: 0
B4414: TXAC900.JU | C4414: 24hs | D4414: ARS | E4414: 5 | F4414: 21.2 | G4414: 0 | H4414: 0 | I4414: 0 | J4414: 0 | K4414: 0 | L4414: 0 | M4414: 0 | N4414: 0 | O4414: 0 | P4414: 0 | Q4414: 0 | R4414: 0
B4415: TXAC900.MA | C4415: 24hs | D4415: ARS | E4415: 0 | F4415: 0 | G4415: 0 | H4415: 0 | I4415: 0 | J4415: 0 | K4415: 0 | L4415: 0 | M4415: 0 | N4415: 0 | O4415: 0 | P4415: 0 | Q4415: 0 | R4415: 0
B4416: TXAC92.0OC | C4416: 24hs | D4416: ARS | E4416: 0 | F4416: 0 | G4416: 0 | H4416: 0 | I4416: 0 | J4416: 0 | K4416: 0 | L4416: 0 | M4416: 0 | N4416: 0 | O4416: 0 | P4416: 0 | Q4416: 0 | R4416: 0
B4417: TXAC950.AB | C4417: 24hs | D4417: ARS | E4417: 0 | F4417: 0 | G4417: 0 | H4417: 0 | I4417: 0 | J4417: 0 | K4417: 0 | L4417: 0 | M4417: 0 | N4417: 0 | O4417: 0 | P4417: 0 | Q4417: 0 | R4417: 0
B4418: TXAC950.FE | C4418: 24hs | D4418: ARS | E4418: 100 | F4418: 0.003 | G4418: 6 | H4418: 84 | I4418: 0 | J4418: 0 | K4418: 0 | L4418: 0 | M4418: 9 | N4418: 0 | O4418: 0 | P4418: 0 | Q4418: 0 | R4418: 9
B4419: TXAC950.JU | C4419: 24hs | D4419: ARS | E4419: 0 | F4419: 0 | G4419: 0 | H4419: 0 | I4419: 0 | J4419: 0 | K4419: 0 | L4419: 0 | M4419: 0 | N4419: 0 | O4419: 0 | P4419: 0 | Q4419: 0 | R4419: 0
B4420: TXAC950.MA | C4420: 24hs | D4420: ARS | E4420: 0 | F4420: 0 | G4420: 0 | H4420: 0 | I4420: 0 | J4420: 0 | K4420: 0 | L4420: 0 | M4420: 0 | N4420: 0 | O4420: 0 | P4420: 0 | Q4420: 0 | R4420: 0
B4421: TXAC96.0OC | C4421: 24hs | D4421: ARS | E4421: 0 | F4421: 0 | G4421: 0 | H4421: 0 | I4421: 0 | J4421: 0 | K4421: 0 | L4421: 0 | M4421: 0 | N4421: 0 | O4421: 0 | P4421: 0 | Q4421: 0 | R4421: 0
B4422: TXAC98.0OC | C4422: 24hs | D4422: ARS | E4422: 0 | F4422: 0 | G4422: 0 | H4422: 0 | I4422: 0 | J4422: 0 | K4422: 0 | L4422: 0 | M4422: 0 | N4422: 0 | O4422: 0 | P4422: 0 | Q4422: 0 | R4422: 0
B4423: TXAC98.0SE | C4423: 24hs | D4423: ARS | E4423: 0 | F4423: 0 | G4423: 0 | H4423: 0 | I4423: 0 | J4423: 0 | K4423: 0 | L4423: 0 | M4423: 0 | N4423: 0 | O4423: 0 | P4423: 0 | Q4423: 0 | R4423: 0
B4424: TXAV1000.M | C4424: 24hs | D4424: ARS | E4424: 0 | F4424: 0 | G4424: 0 | H4424: 0 | I4424: 0 | J4424: 0 | K4424: 0 | L4424: 0 | M4424: 0 | N4424: 0 | O4424: 0 | P4424: 0 | Q4424: 0 | R4424: 0
... B4755: YPFC47500A | C4755: 24hs | D4755: ARS | E4755: 0 | F4755: 0 | G4755: 0 | H4755: 0 | I4755: 0 | J4755: 0 | K4755: 0 | L4755: 0 | M4755: 0 | N4755: 0 | O4755: 0 | P4755: 0 | Q4755: 0 | R4755: 0
B4756: YPFC47500F | C4756: 24hs | D4756: ARS | E4756: 0 | F4756: 0 | G4756: 11505.1 | H4756: 2 | I4756: 11766.71 | J4756: 11766.71 | K4756: 11766.71 | L4756: 11766.71 | M4756: 11294.1 | N4756: 0.0418 | O4756: 2 | P4756: 2353342 | Q4756: 11766.71 | R4756: 11766.71 | S4756: 11:42:21
B4757: YPFC47500J | C4757: 24hs | D4757: ARS | E4757: 0 | F4757: 0 | G4757: 0 | H4757: 0 | I4757: 0 | J4757: 0 | K4757: 0 | L4757: 0 | M4757: 0 | N4757: 0 | O4757: 0 | P4757: 0 | Q4757: 0 | R4757: 0
B4758: YPFC47500M | C4758: 24hs | D4758: ARS | E4758: 0 | F4758: 0 | G4758: 0 | H4758: 0 | I4758: 0 | J4758: 0 | K4758: 0 | L4758: 0 | M4758: 0 | N4758: 0 | O4758: 0 | P4758: 0 | Q4758: 0 | R4758: 0
B4759: YPFC49000A | C4759: 24hs | D4759: ARS | E4759: 0 | F4759: 0 | G4759: 0 | H4759: 0 | I4759: 0 | J4759: 0 | K4759: 0 | L4759: 0 | M4759: 0 | N4759: 0 | O4759: 0 | P4759: 0 | Q4759: 0 | R4759: 0
B4760: YPFC49000F | C4760: 24hs | D4760: ARS | E4760: 0 | F4760: 0 | G4760: 10019.57 | H4760: 2 | I4760: 0 | J4760: 0 | K4760: 0 | L4760: 0 | M4760: 11378.732 | N4760: 0 | O4760: 0 | P4760: 0 | Q4760: 0 | R4760: 11378.732
B4761: YPFC49000J | C4761: 24hs | D4761: ARS | E4761: 0 | F4761: 0 | G4761: 0 | H4761: 0 | I4761: 0 | J4761: 0 | K4761: 0 | L4761: 0 | M4761: 0 | N4761: 0 | O4761: 0 | P4761: 0 | Q4761: 0 | R4761: 0
...

Sheet Caucho
A1: {=_xll.PanelCaucionesBD("S")} -> CAUCIONES | B1: SIMBOLO | C1: ESPECIE | D1: MONEDA | E1: PLAZO | F1: VTO. | G1: TASA | H1: CANT.OPER | I1: MONTO | J1: M.TOM | K1: T.TOM | L1: T.COL | M1: M.COL | N1: VWAP
B2: DOLAR-0203-U-CT-USD | D2: USD | E2: 24 | F2: 2026-03-02 | G2: 0 | H2: 0 | I2: 0 | J2: 50000 | K2: 0.0063 | L2: 0.03 | M2: 800 | N2: 0
B3: DOLAR-0206-U-CT-USD | D3: USD | E3: 116 | F3: 2026-06-02 | G3: 0 | H3: 0 | I3: 0 | J3: 0 | K3: 0 | L3: 0 | M3: 0 | N3: 0
B4: DOLAR-0303-U-CT-USD | D4: USD | E4: 25 | F4: 2026-03-03 | G4: 0 | H4: 0 | I4: 0 | J4: 25000 | K4: 0.0073 | L4: 0.03 | M4: 800 | N4: 0
B5: DOLAR-0403-U-CT-USD | D5: USD | E5: 26 | F5: 2026-03-04 | G5: 0.0075 | H5: 0 | I5: 588.33 | J5: 49412 | K5: 0.0075 | L5: 0.0299 | M5: 18312 | N5: 0.0075
B6: DOLAR-0405-U-CT-USD | D6: USD | E6: 87 | F6: 2026-05-04 | G6: 0 | H6: 0 | I6: 0 | J6: 50000 | K6: 0.007 | L6: 0 | M6: 0 | N6: 0
B7: DOLAR-0406-U-CT-USD | D7: USD | E7: 118 | F7: 2026-06-04 | G7: 0 | H7: 0 | I7: 0 | J7: 0 | K7: 0 | L7: 0 | M7: 0 | N7: 0
B8: DOLAR-0503-U-CT-USD | D8: USD | E8: 27 | F8: 2026-03-05 | G8: 0 | H8: 0 | I8: 0 | J8: 25000 | K8: 0.0068 | L8: 0.0295 | M8: 317 | N8: 0
B9: DOLAR-0505-U-CT-USD | D9: USD | E9: 88 | F9: 2026-05-05 | G9: 0 | H9: 0 | I9: 0 | J9: 0 | K9: 0 | L9: 0 | M9: 0 | N9: 0
B10: DOLAR-0506-U-CT-USD | D10: USD | E10: 119 | F10: 2026-06-05 | G10: 0.03 | H10: 0 | I10: 93845.07 | J10: 0 | K10: 0 | L10: 0.035 | M10: 60567 | N10: 0.03021523
B11: DOLAR-0602-U-CT-USD | D11: USD | E11: 0 | F11: 2026-02-06 | G11: 0.005 | H11: 0 | I11: 7.9885928e+08 | J11: 122529 | K11: 0.005 | L11: 0.008 | M11: 12212 | N11: 0.01079838
B12: DOLAR-0603-U-CT-USD | D12: USD | E12: 28 | F12: 2026-03-06 | G12: 0.026 | H12: 0 | I12: 15503.94 | J12: 18168 | K12: 0.011 | L12: 0.026 | M12: 51306 | N12: 0.02680447
B13: DOLAR-0604-U-CT-USD | D13: USD | E13: 59 | F13: 2026-04-06 | G13: 0.025 | H13: 0 | I13: 440804.11 | J13: 0 | K13: 0 | L13: 0 | M13: 0 | N13: 0.025
... B144: PESOS-3103-U-CT-ARS | D144: ARS | E144: 53 | F144: 2026-03-31 | G144: 0.211 | H144: 0 | I144: 207171.38 | J144: 299100 | K144: 0.211 | L144: 0 | M144: 0 | N144: 0.211
B145: PESOS-3103-U-CT-ARS | C145: PESOS | D145: ARS | E145: 55 | F145: 2026-03-31 | G145: 0 | H145: 0 | I145: 0 | J145: 0 | K145: 0 | L145: 0 | M145: 0 | N145: 0

Sheet Soberanos HD
F1: Comisión | G1: 1
F2: Fecha de liquidación | G2: =Main!B1 -> 46060
B4: Ticker | C4: TIR | D4: Precio con comisión | E4: Precio sin comisión | F4: MD | G4: Variación | H4: Bid | I4: Ask | J4: Bid Volume | K4: Ask volume | L4: Total volume | M4: Vto | N4: Ley | O4: Periodicidad | P4: Lamina minima | Q4: Tipo
B5: AL29D | C5: =AL29D!K4 -> 0.088069263 | D5: =E5*$G$1 -> 60.97 | E5: {=_xll.PrecioBD(ONs_NY8[[#This Row],[Ticker]],24,"ASK","N")} -> 60.97 | F5: =AL30D!K2 -> 0.5 | G5: {=_xll.PrecioBD(ONs_NY8[[#This Row],[Ticker]],24,"IMBALANCE","N")} -> 0.0013 | H5: {=_xll.PrecioBD(ONs_NY8[[#This Row],[Ticker]],"24","BID","N")} -> 60.88 | I5: {=_xll.PrecioBD(ONs_NY8[[#This Row],[Ticker]],"24","ASK","N")} -> 60.97 | J5: {=_xll.PrecioBD(ONs_NY8[[#This Row],[Ticker]],24,"QUANTITY BID","N")} -> 1732 | K5: {=_xll.PrecioBD(ONs_NY8[[#This Row],[Ticker]],24,"QUANTITY ASK","N")} -> 3095 | L5: {=_xll.PrecioBD(ONs_NY8[[#This Row],[Ticker]],24,"VOLUME AMOUNT","N")} -> 915582.46 | N5: ARG
B6: AL30D | C6: =AL30D!K4 -> 0.09034898 | D6: =E6*$G$1 -> 60.58 | E6: {=_xll.PrecioBD(ONs_NY8[[#This Row],[Ticker]],24,"ASK","N")} -> 60.58 | F6: =AL30D!K3 -> 2.1755694 | G6: {=_xll.PrecioBD(ONs_NY8[[#This Row],[Ticker]],24,"IMBALANCE","N")} -> 0.0048 | H6: {=_xll.PrecioBD(ONs_NY8[[#This Row],[Ticker]],"24","BID","N")} -> 60.54 | I6: {=_xll.PrecioBD(ONs_NY8[[#This Row],[Ticker]],"24","ASK","N")} -> 60.58 | J6: {=_xll.PrecioBD(ONs_NY8[[#This Row],[Ticker]],24,"QUANTITY BID","N")} -> 4723 | K6: {=_xll.PrecioBD(ONs_NY8[[#This Row],[Ticker]],24,"QUANTITY ASK","N")} -> 16351 | L6: {=_xll.PrecioBD(ONs_NY8[[#This Row],[Ticker]],24,"VOLUME AMOUNT","N")} -> 62804134 | N6: ARG
B7: AL35D | C7: =AL35D!K4 -> 0.091250238 | D7: =E7*$G$1 -> 78.67 | E7: {=_xll.PrecioBD(ONs_NY8[[#This Row],[Ticker]],24,"ASK","N")} -> 78.67 | F7: =AL35D!K3 -> 5.6790308 | G7: {=_xll.PrecioBD(ONs_NY8[[#This Row],[Ticker]],24,"IMBALANCE","N")} -> -0.0005 | H7: {=_xll.PrecioBD(ONs_NY8[[#This Row],[Ticker]],"24","BID","N")} -> 78.45 | I7: {=_xll.PrecioBD(ONs_NY8[[#This Row],[Ticker]],"24","ASK","N")} -> 78.67 | J7: {=_xll.PrecioBD(ONs_NY8[[#This Row],[Ticker]],24,"QUANTITY BID","N")} -> 2003 | K7: {=_xll.PrecioBD(ONs_NY8[[#This Row],[Ticker]],24,"QUANTITY ASK","N")} -> 500 | L7: {=_xll.PrecioBD(ONs_NY8[[#This Row],[Ticker]],24,"VOLUME AMOUNT","N")} -> 3641468.5 | N7: ARG
B8: AE38D | C8: =AE38D!K4 -> 0.096076125 | D8: =E8*$G$1 -> 80.05 | E8: {=_xll.PrecioBD(ONs_NY8[[#This Row],[Ticker]],24,"ASK","N")} -> 80.05 | F8: =AE38D!K3 -> 4.9019119 | G8: {=_xll.PrecioBD(ONs_NY8[[#This Row],[Ticker]],24,"IMBALANCE","N")} -> -0.0007 | H8: {=_xll.PrecioBD(ONs_NY8[[#This Row],[Ticker]],"24","BID","N")} -> 79.9 | I8: {=_xll.PrecioBD(ONs_NY8[[#This Row],[Ticker]],"24","ASK","N")} -> 80.05 | J8: {=_xll.PrecioBD(ONs_NY8[[#This Row],[Ticker]],24,"QUANTITY BID","N")} -> 8 | K8: {=_xll.PrecioBD(ONs_NY8[[#This Row],[Ticker]],24,"QUANTITY ASK","N")} -> 10000 | L8: {=_xll.PrecioBD(ONs_NY8[[#This Row],[Ticker]],24,"VOLUME AMOUNT","N")} -> 3809578.6 | N8: ARG
B9: AL41D | C9: =AL41D!K4 -> 0.069507185 | D9: =E9*$G$1 -> 73.35 | E9: {=_xll.PrecioBD(ONs_NY8[[#This Row],[Ticker]],24,"ASK","N")} -> 73.35 | F9: =AL41D!K3 -> 7.5551069 | G9: {=_xll.PrecioBD(ONs_NY8[[#This Row],[Ticker]],24,"IMBALANCE","N")} -> -0.0083 | H9: {=_xll.PrecioBD(ONs_NY8[[#This Row],[Ticker]],"24","BID","N")} -> 73.14 | I9: {=_xll.PrecioBD(ONs_NY8[[#This Row],[Ticker]],"24","ASK","N")} -> 73.35 | J9: {=_xll.PrecioBD(ONs_NY8[[#This Row],[Ticker]],24,"QUANTITY BID","N")} -> 1367 | K9: {=_xll.PrecioBD(ONs_NY8[[#This Row],[Ticker]],24,"QUANTITY ASK","N")} -> 114 | L9: {=_xll.PrecioBD(ONs_NY8[[#This Row],[Ticker]],24,"VOLUME AMOUNT","N")} -> 747448.48 | N9: ARG
B10: GD29D | C10: =GD29D!K4 -> 0.06248239 | D10: =E10*$G$1 -> 63.7 | E10: {=_xll.PrecioBD(ONs_NY8[[#This Row],[Ticker]],24,"ASK","N")} -> 63.7 | F10: =GD29D!K3 -> 1.7972543 | G10: {=_xll.PrecioBD(ONs_NY8[[#This Row],[Ticker]],24,"IMBALANCE","N")} -> 0 | H10: {=_xll.PrecioBD(ONs_NY8[[#This Row],[Ticker]],"24","BID","N")} -> 63.35 | I10: {=_xll.PrecioBD(ONs_NY8[[#This Row],[Ticker]],"24","ASK","N")} -> 63.7 | J10: {=_xll.PrecioBD(ONs_NY8[[#This Row],[Ticker]],24,"QUANTITY BID","N")} -> 7023 | K10: {=_xll.PrecioBD(ONs_NY8[[#This Row],[Ticker]],24,"QUANTITY ASK","N")} -> 12163 | L10: {=_xll.PrecioBD(ONs_NY8[[#This Row],[Ticker]],24,"VOLUME AMOUNT","N")} -> 267963.14 | N10: NY
B11: GD30D | C11: =GD30D!K4 -> 0.070274821 | D11: =E11*$G$1 -> 63.21 | E11: {=_xll.PrecioBD(ONs_NY8[[#This Row],[Ticker]],24,"ASK","N")} -> 63.21 | F11: =GD30D!K3 -> 2.2254087 | G11: {=_xll.PrecioBD(ONs_NY8[[#This Row],[Ticker]],24,"IMBALANCE","N")} -> 0.0017 | H11: {=_xll.PrecioBD(ONs_NY8[[#This Row],[Ticker]],"24","BID","N")} -> 62.25 | I11: {=_xll.PrecioBD(ONs_NY8[[#This Row],[Ticker]],"24","ASK","N")} -> 63.21 | J11: {=_xll.PrecioBD(ONs_NY8[[#This Row],[Ticker]],24,"QUANTITY BID","N")} -> 7891 | K11: {=_xll.PrecioBD(ONs_NY8[[#This Row],[Ticker]],24,"QUANTITY ASK","N")} -> 4 | L11: {=_xll.PrecioBD(ONs_NY8[[#This Row],[Ticker]],24,"VOLUME AMOUNT","N")} -> 2590984.1 | N11: NY
B12: GD35D | C12: =GD35D!K4 -> 0.088632891 | D12: =E12*$G$1 -> 79.8 | E12: {=_xll.PrecioBD(ONs_NY8[[#This Row],[Ticker]],24,"ASK","N")} -> 79.8 | F12: =GD35D!K3 -> 5.6982618 | G12: {=_xll.PrecioBD(ONs_NY8[[#This Row],[Ticker]],24,"IMBALANCE","N")} -> -0.0023 | H12: {=_xll.PrecioBD(ONs_NY8[[#This Row],[Ticker]],"24","BID","N")} -> 79.2 | I12: {=_xll.PrecioBD(ONs_NY8[[#This Row],[Ticker]],"24","ASK","N")} -> 79.8 | J12: {=_xll.PrecioBD(ONs_NY8[[#This Row],[Ticker]],24,"QUANTITY BID","N")} -> 3672 | K12: {=_xll.PrecioBD(ONs_NY8[[#This Row],[Ticker]],24,"QUANTITY ASK","N")} -> 11000 | L12: {=_xll.PrecioBD(ONs_NY8[[#This Row],[Ticker]],24,"VOLUME AMOUNT","N")} -> 3080649 | N12: NY
B13: GD38D | C13: =GD38D!K4 -> 0.088778743 | D13: =E13*$G$1 -> 82.86 | E13: {=_xll.PrecioBD(ONs_NY8[[#This Row],[Ticker]],24,"ASK","N")} -> 82.86 | F13: =GD38D!K3 -> 4.9813448 | G13: {=_xll.PrecioBD(ONs_NY8[[#This Row],[Ticker]],24,"IMBALANCE","N")} -> -0.0016 | H13: {=_xll.PrecioBD(ONs_NY8[[#This Row],[Ticker]],"24","BID","N")} -> 82.7 | I13: {=_xll.PrecioBD(ONs_NY8[[#This Row],[Ticker]],"24","ASK","N")} -> 82.86 | J13: {=_xll.PrecioBD(ONs_NY8[[#This Row],[Ticker]],24,"QUANTITY BID","N")} -> 2856 | K13: {=_xll.PrecioBD(ONs_NY8[[#This Row],[Ticker]],24,"QUANTITY ASK","N")} -> 44241 | L13: {=_xll.PrecioBD(ONs_NY8[[#This Row],[Ticker]],24,"VOLUME AMOUNT","N")} -> 222622 | N13: NY
B14: GD41D | C14: =GD41D!K4 -> 0.067179868 | D14: =E14*$G$1 -> 74.28 | E14: {=_xll.PrecioBD(ONs_NY8[[#This Row],[Ticker]],24,"ASK","N")} -> 74.28 | F14: =GD41D!K3 -> 7.6189885 | G14: {=_xll.PrecioBD(ONs_NY8[[#This Row],[Ticker]],24,"IMBALANCE","N")} -> -0.0022 | H14: {=_xll.PrecioBD(ONs_NY8[[#This Row],[Ticker]],"24","BID","N")} -> 74.08 | I14: {=_xll.PrecioBD(ONs_NY8[[#This Row],[Ticker]],"24","ASK","N")} -> 74.28 | J14: {=_xll.PrecioBD(ONs_NY8[[#This Row],[Ticker]],24,"QUANTITY BID","N")} -> 200 | K14: {=_xll.PrecioBD(ONs_NY8[[#This Row],[Ticker]],24,"QUANTITY ASK","N")} -> 5000 | L14: {=_xll.PrecioBD(ONs_NY8[[#This Row],[Ticker]],24,"VOLUME AMOUNT","N")} -> 1153333.2 | N14: NY

Sheet ONS NY
G1: Comisión | H1: 1
G2: Fecha de liquidación | H2: =Main!B1 -> 46060
B4: Empresa | C4: Ticker | D4: TIR | E4: Precio con comisión | F4: Precio sin comisión | G4: MD | H4: Vto | I4: Bid | J4: Ask | K4: Bid Volume | L4: Ask volume | M4: Total volume | N4: Variación | O4: Ley | P4: Periodicidad | Q4: Lamina minima | R4: Tipo
B5: YPF | C5: YMCHD | D5: =YMCHO!K4 -> #NUM! | E5: =F5*$H$1 -> 0 | F5: {=_xll.PrecioBD(ONs_NY[[#This Row],[Ticker]],24,"ASK","N")} -> 0 | G5: =YMCHO!K3 -> #NUM! | H5: 46065 | I5: {=_xll.PrecioBD(ONs_NY[[#This Row],[Ticker]],"24","BID","N")} -> 0 | J5: {=_xll.PrecioBD(ONs_NY[[#This Row],[Ticker]],"24","ASK","N")} -> 0 | K5: {=_xll.PrecioBD(ONs_NY[[#This Row],[Ticker]],24,"QUANTITY BID","N")} -> 0 | L5: {=_xll.PrecioBD(ONs_NY[[#This Row],[Ticker]],24,"QUANTITY ASK","N")} -> 0 | M5: {=_xll.PrecioBD(ONs_NY[[#This Row],[Ticker]],24,"VOLUME AMOUNT","N")} -> 0 | N5: {=_xll.PrecioBD(ONs_NY[[#This Row],[Ticker]],24,"IMBALANCE","N")} -> 0 | O5: NY | P5: Trimestral | Q5: 1 | R5: Sinkable
B6: Genneia | C6: GNCXD | D6: =GNCXD!K4 -> #NUM! | E6: =F6*$H$1 -> 0 | F6: {=_xll.PrecioBD(ONs_NY[[#This Row],[Ticker]],24,"ASK","N")} -> 0 | G6: =GNCXD!K3 -> #NUM! | H6: 46632 | I6: {=_xll.PrecioBD(ONs_NY[[#This Row],[Ticker]],"24","BID","N")} -> 0 | J6: {=_xll.PrecioBD(ONs_NY[[#This Row],[Ticker]],"24","ASK","N")} -> 0 | K6: {=_xll.PrecioBD(ONs_NY[[#This Row],[Ticker]],24,"QUANTITY BID","N")} -> 0 | L6: {=_xll.PrecioBD(ONs_NY[[#This Row],[Ticker]],24,"QUANTITY ASK","N")} -> 0 | M6: {=_xll.PrecioBD(ONs_NY[[#This Row],[Ticker]],24,"VOLUME AMOUNT","N")} -> 0 | N6: {=_xll.PrecioBD(ONs_NY[[#This Row],[Ticker]],24,"IMBALANCE","N")} -> 0 | O6: NY | P6: Semestral | Q6: 1000 | R6: Sinkable
B7: Arcor | C7: RCCJD | D7: =RCCJD!K4 -> #NUM! | E7: =F7*$H$1 -> 0 | F7: {=_xll.PrecioBD(ONs_NY[[#This Row],[Ticker]],24,"ASK","N")} -> 0 | G7: =RCCJD!K3 -> #NUM! | H7: 46669 | I7: {=_xll.PrecioBD(ONs_NY[[#This Row],[Ticker]],"24","BID","N")} -> 0 | J7: {=_xll.PrecioBD(ONs_NY[[#This Row],[Ticker]],"24","ASK","N")} -> 0 | K7: {=_xll.PrecioBD(ONs_NY[[#This Row],[Ticker]],24,"QUANTITY BID","N")} -> 0 | L7: {=_xll.PrecioBD(ONs_NY[[#This Row],[Ticker]],24,"QUANTITY ASK","N")} -> 0 | M7: {=_xll.PrecioBD(ONs_NY[[#This Row],[Ticker]],24,"VOLUME AMOUNT","N")} -> 0 | N7: {=_xll.PrecioBD(ONs_NY[[#This Row],[Ticker]],24,"IMBALANCE","N")} -> 0 | O7: NY
B8: Pampa energia | C8: MGC9D | D8: =MGC9D!K4 -> #NUM! | E8: =F8*$H$1 -> 0 | F8: {=_xll.PrecioBD(ONs_NY[[#This Row],[Ticker]],24,"ASK","N")} -> 0 | G8: =MGC9D!K3 -> #NUM! | H8: 46364 | I8: {=_xll.PrecioBD(ONs_NY[[#This Row],[Ticker]],"24","BID","N")} -> 0 | J8: {=_xll.PrecioBD(ONs_NY[[#This Row],[Ticker]],"24","ASK","N")} -> 0 | K8: {=_xll.PrecioBD(ONs_NY[[#This Row],[Ticker]],24,"QUANTITY BID","N")} -> 0 | L8: {=_xll.PrecioBD(ONs_NY[[#This Row],[Ticker]],24,"QUANTITY ASK","N")} -> 0 | M8: {=_xll.PrecioBD(ONs_NY[[#This Row],[Ticker]],24,"VOLUME AMOUNT","N")} -> 0 | N8: {=_xll.PrecioBD(ONs_NY[[#This Row],[Ticker]],24,"IMBALANCE","N")} -> 0 | O8: NY | P8: Semestral | Q8: 1 | R8: Sinkable
B9: MSU Energy | C9: RUCDD | D9: =RUCDO!K4 -> 0.09084594 | E9: =F9*$H$1 -> 104.7 | F9: {=_xll.PrecioBD(ONs_NY[[#This Row],[Ticker]],24,"ASK","N")} -> 104.7 | G9: =RUCDO!K3 -> 3.4036364 | H9: 47822 | I9: {=_xll.PrecioBD(ONs_NY[[#This Row],[Ticker]],"24","BID","N")} -> 104.35 | J9: {=_xll.PrecioBD(ONs_NY[[#This Row],[Ticker]],"24","ASK","N")} -> 104.7 | K9: {=_xll.PrecioBD(ONs_NY[[#This Row],[Ticker]],24,"QUANTITY BID","N")} -> 514 | L9: {=_xll.PrecioBD(ONs_NY[[#This Row],[Ticker]],24,"QUANTITY ASK","N")} -> 2596 | M9: {=_xll.PrecioBD(ONs_NY[[#This Row],[Ticker]],24,"VOLUME AMOUNT","N")} -> 140759.64 | N9: {=_xll.PrecioBD(ONs_NY[[#This Row],[Ticker]],24,"IMBALANCE","N")} -> 0.0004 | O9: NY | P9: Semestral | Q9: 1 | R9: Sinkable
B10: Edenor | C10: DNC7D | D10: =DNC7D!K4 -> 0.088900277 | E10: =F10*$H$1 -> 106.05 | F10: {=_xll.PrecioBD(ONs_NY[[#This Row],[Ticker]],24,"ASK","N")} -> 106.05 | G10: =DNC7D!K3 -> 2.9828026 | H10: 47780 | I10: {=_xll.PrecioBD(ONs_NY[[#This Row],[Ticker]],"24","BID","N")} -> 105.85 | J10: {=_xll.PrecioBD(ONs_NY[[#This Row],[Ticker]],"24","ASK","N")} -> 106.05 | K10: {=_xll.PrecioBD(ONs_NY[[#This Row],[Ticker]],24,"QUANTITY BID","N")} -> 1000 | L10: {=_xll.PrecioBD(ONs_NY[[#This Row],[Ticker]],24,"QUANTITY ASK","N")} -> 2900 | M10: {=_xll.PrecioBD(ONs_NY[[#This Row],[Ticker]],24,"VOLUME AMOUNT","N")} -> 314361.7 | N10: {=_xll.PrecioBD(ONs_NY[[#This Row],[Ticker]],24,"IMBALANCE","N")} -> 0.0014 | O10: NY | P10: Semestral | Q10: 100 | R10: Sinkable
B11: Telecom | C11: TLCTD | D11: =TLCTD!K4 -> 0.078768 | E11: =F11*$H$1 -> 105.5 | F11: {=_xll.PrecioBD(ONs_NY[[#This Row],[Ticker]],24,"ASK","N")} -> 105.5 | G11: =TLCTD!K3 -> 6.4810689 | H11: 49695 | I11: {=_xll.PrecioBD(ONs_NY[[#This Row],[Ticker]],"24","BID","N")} -> 105.4 | J11: {=_xll.PrecioBD(ONs_NY[[#This Row],[Ticker]],"24","ASK","N")} -> 105.5 | K11: {=_xll.PrecioBD(ONs_NY[[#This Row],[Ticker]],24,"QUANTITY BID","N")} -> 2918 | L11: {=_xll.PrecioBD(ONs_NY[[#This Row],[Ticker]],24,"QUANTITY ASK","N")} -> 1650 | M11: {=_xll.PrecioBD(ONs_NY[[#This Row],[Ticker]],24,"VOLUME AMOUNT","N")} -> 556489.95 | N11: {=_xll.PrecioBD(ONs_NY[[#This Row],[Ticker]],24,"IMBALANCE","N")} -> 0.0004 | O11: NY
B12: Telecom | C12: TLCPD | D12: =TLCPD!K4 -> 0.078323558 | E12: =F12*$H$1 -> 110.65 | F12: {=_xll.PrecioBD(ONs_NY[[#This Row],[Ticker]],24,"ASK","N")} -> 110.65 | G12: =TLCPD!K3 -> 4.9773841 | H12: 48726 | I12: {=_xll.PrecioBD(ONs_NY[[#This Row],[Ticker]],"24","BID","N")} -> 110.3 | J12: {=_xll.PrecioBD(ONs_NY[[#This Row],[Ticker]],"24","ASK","N")} -> 110.65 | K12: {=_xll.PrecioBD(ONs_NY[[#This Row],[Ticker]],24,"QUANTITY BID","N")} -> 1500 | L12: {=_xll.PrecioBD(ONs_NY[[#This Row],[Ticker]],24,"QUANTITY ASK","N")} -> 9401 | M12: {=_xll.PrecioBD(ONs_NY[[#This Row],[Ticker]],24,"VOLUME AMOUNT","N")} -> 289294.74 | N12: {=_xll.PrecioBD(ONs_NY[[#This Row],[Ticker]],24,"IMBALANCE","N")} -> -0.0018 | O12: NY | P12: Semestral | Q12: 100 | R12: Sinkable
B13: Pampa energia | C13: MGCRD | D13: =MGCRD!K4 -> 0.074627194 | E13: =F13*$H$1 -> 105.1 | F13: {=_xll.PrecioBD(ONs_NY[[#This Row],[Ticker]],24,"ASK","N")} -> 105.1 | G13: =MGCRD!K3 -> 7.5846465 | H13: 50360 | I13: {=_xll.PrecioBD(ONs_NY[[#This Row],[Ticker]],"24","BID","N")} -> 104.8 | J13: {=_xll.PrecioBD(ONs_NY[[#This Row],[Ticker]],"24","ASK","N")} -> 105.1 | K13: {=_xll.PrecioBD(ONs_NY[[#This Row],[Ticker]],24,"QUANTITY BID","N")} -> 10000 | L13: {=_xll.PrecioBD(ONs_NY[[#This Row],[Ticker]],24,"QUANTITY ASK","N")} -> 10000 | M13: {=_xll.PrecioBD(ONs_NY[[#This Row],[Ticker]],24,"VOLUME AMOUNT","N")} -> 146740 | N13: {=_xll.PrecioBD(ONs_NY[[#This Row],[Ticker]],24,"IMBALANCE","N")} -> -0.0019 | O13: NY | P13: Semestral | Q13: 10000 | R13: Bullet
B14: YPF | C14: YM34D | D14: =YM34D!K4 -> 0.072824374 | E14: =F14*$H$1 -> 106.45 | F14: {=_xll.PrecioBD(ONs_NY[[#This Row],[Ticker]],24,"ASK","N")} -> 106.45 | G14: =YM34D!K3 -> 5.3076418 | H14: 48961 | I14: {=_xll.PrecioBD(ONs_NY[[#This Row],[Ticker]],"24","BID","N")} -> 106.15 | J14: {=_xll.PrecioBD(ONs_NY[[#This Row],[Ticker]],"24","ASK","N")} -> 106.45 | K14: {=_xll.PrecioBD(ONs_NY[[#This Row],[Ticker]],24,"QUANTITY BID","N")} -> 35 | L14: {=_xll.PrecioBD(ONs_NY[[#This Row],[Ticker]],24,"QUANTITY ASK","N")} -> 1999 | M14: {=_xll.PrecioBD(ONs_NY[[#This Row],[Ticker]],24,"VOLUME AMOUNT","N")} -> 920344.59 | N14: {=_xll.PrecioBD(ONs_NY[[#This Row],[Ticker]],24,"IMBALANCE","N")} -> 0.0033 | O14: NY | P14: Semestral | Q14: 1 | R14: Sinkable
B15: Pluspetrol | C15: PLC4D | D15: =PCL4D!K4 -> 0.073033872 | E15: =F15*$H$1 -> 108.2 | F15: {=_xll.PrecioBD(ONs_NY[[#This Row],[Ticker]],24,"ASK","N")} -> 108.2 | G15: =PCL4D!K3 -> 4.8172422 | H15: 48364 | I15: {=_xll.PrecioBD(ONs_NY[[#This Row],[Ticker]],"24","BID","N")} -> 107.8 | J15: {=_xll.PrecioBD(ONs_NY[[#This Row],[Ticker]],"24","ASK","N")} -> 108.2 | K15: {=_xll.PrecioBD(ONs_NY[[#This Row],[Ticker]],24,"QUANTITY BID","N")} -> 1000 | L15: {=_xll.PrecioBD(ONs_NY[[#This Row],[Ticker]],24,"QUANTITY ASK","N")} -> 2000 | M15: {=_xll.PrecioBD(ONs_NY[[#This Row],[Ticker]],24,"VOLUME AMOUNT","N")} -> 405314.5 | N15: {=_xll.PrecioBD(ONs_NY[[#This Row],[Ticker]],24,"IMBALANCE","N")} -> 0.0027 | O15: NY | P15: Semestral | Q15: 1000 | R15: Bullet
B16: TGS | C16: TSC4D | D16: =TSC4D!K4 -> 0.073101494 | E16: =F16*$H$1 -> 105.65 | F16: {=_xll.PrecioBD(ONs_NY[[#This Row],[Ticker]],24,"ASK","N")} -> 105.65 | G16: =TSC4D!K3 -> 2.0859148 | H16: 49633 | I16: {=_xll.PrecioBD(ONs_NY[[#This Row],[Ticker]],"24","BID","N")} -> 105.4 | J16: {=_xll.PrecioBD(ONs_NY[[#This Row],[Ticker]],"24","ASK","N")} -> 105.65 | K16: {=_xll.PrecioBD(ONs_NY[[#This Row],[Ticker]],24,"QUANTITY BID","N")} -> 4000 | L16: {=_xll.PrecioBD(ONs_NY[[#This Row],[Ticker]],24,"QUANTITY ASK","N")} -> 39000 | M16: {=_xll.PrecioBD(ONs_NY[[#This Row],[Ticker]],24,"VOLUME AMOUNT","N")} -> 462528 | N16: {=_xll.PrecioBD(ONs_NY[[#This Row],[Ticker]],24,"IMBALANCE","N")} -> 0.0023 | O16: NY | P16: Semestral | Q16: 1000 | R16: Bullet
B17: IRSA | C17: IRCPD | D17: =IRCPD!K4 -> 0.072899458 | E17: =F17*$H$1 -> 107.9 | F17: {=_xll.PrecioBD(ONs_NY[[#This Row],[Ticker]],24,"ASK","N")} -> 107.9 | G17: =IRCPD!K3 -> 5.8223554 | H17: 49399 | I17: {=_xll.PrecioBD(ONs_NY[[#This Row],[Ticker]],"24","BID","N")} -> 107.85 | J17: {=_xll.PrecioBD(ONs_NY[[#This Row],[Ticker]],"24","ASK","N")} -> 107.9 | K17: {=_xll.PrecioBD(ONs_NY[[#This Row],[Ticker]],24,"QUANTITY BID","N")} -> 277 | L17: {=_xll.PrecioBD(ONs_NY[[#This Row],[Ticker]],24,"QUANTITY ASK","N")} -> 15927 | M17: {=_xll.PrecioBD(ONs_NY[[#This Row],[Ticker]],24,"VOLUME AMOUNT","N")} -> 897177.97 | N17: {=_xll.PrecioBD(ONs_NY[[#This Row],[Ticker]],24,"IMBALANCE","N")} -> -0.0027 | O17: NY | P17: Semestral | Q17: 1 | R17: Sinkable
B18: Pluspetrol | C18: PLC5D | D18: =PLC5D!K4 -> 0.071448514 | E18: =F18*$H$1 -> 106.55 | F18: {=_xll.PrecioBD(ONs_NY[[#This Row],[Ticker]],24,"ASK","N")} -> 106.55 | G18: =PLC5D!K3 -> 4.2018316 | H18: 47987 | I18: {=_xll.PrecioBD(ONs_NY[[#This Row],[Ticker]],"24","BID","N")} -> 106.25 | J18: {=_xll.PrecioBD(ONs_NY[[#This Row],[Ticker]],"24","ASK","N")} -> 106.55 | K18: {=_xll.PrecioBD(ONs_NY[[#This Row],[Ticker]],24,"QUANTITY BID","N")} -> 11000 | L18: {=_xll.PrecioBD(ONs_NY[[#This Row],[Ticker]],24,"QUANTITY ASK","N")} -> 4000 | M18: {=_xll.PrecioBD(ONs_NY[[#This Row],[Ticker]],24,"VOLUME AMOUNT","N")} -> 451908.5 | N18: {=_xll.PrecioBD(ONs_NY[[#This Row],[Ticker]],24,"IMBALANCE","N")} -> 0.0037 | O18: NY | P18: Semestral | Q18: 1000 | R18: Bullet
B19: Pampa energia | C19: MGCOD | D19: =MGCOD!K4 -> 0.072397116 | E19: =F19*$H$1 -> 106.05 | F19: {=_xll.PrecioBD(ONs_NY[[#This Row],[Ticker]],24,"ASK","N")} -> 106.05 | G19: =MGCOD!K3 -> 6.3137661 | H19: 49294 | I19: {=_xll.PrecioBD(ONs_NY[[#This Row],[Ticker]],"24","BID","N")} -> 105.8 | J19: {=_xll.PrecioBD(ONs_NY[[#This Row],[Ticker]],"24","ASK","N")} -> 106.05 | K19: {=_xll.PrecioBD(ONs_NY[[#This Row],[Ticker]],24,"QUANTITY BID","N")} -> 12000 | L19: {=_xll.PrecioBD(ONs_NY[[#This Row],[Ticker]],24,"QUANTITY ASK","N")} -> 10000 | M19: {=_xll.PrecioBD(ONs_NY[[#This Row],[Ticker]],24,"VOLUME AMOUNT","N")} -> 258626.5 | N19: {=_xll.PrecioBD(ONs_NY[[#This Row],[Ticker]],24,"IMBALANCE","N")} -> 0.0004 | O19: NY | P19: Semestral | Q19: 10000 | R19: Bullet
B20: Vista Energy | C20: VSCVD | D20: =VSCVD!K4 -> 0.07252064 | E20: =F20*$H$1 -> 108.25 | F20: {=_xll.PrecioBD(ONs_NY[[#This Row],[Ticker]],24,"ASK","N")} -> 108.25 | G20: =VSCVD!K3 -> 4.8412903 | H20: 48740 | I20: {=_xll.PrecioBD(ONs_NY[[#This Row],[Ticker]],"24","BID","N")} -> 108.2 | J20: {=_xll.PrecioBD(ONs_NY[[#This Row],[Ticker]],"24","ASK","N")} -> 108.25 | K20: {=_xll.PrecioBD(ONs_NY[[#This Row],[Ticker]],24,"QUANTITY BID","N")} -> 6000 | L20: {=_xll.PrecioBD(ONs_NY[[#This Row],[Ticker]],24,"QUANTITY ASK","N")} -> 3000 | M20: {=_xll.PrecioBD(ONs_NY[[#This Row],[Ticker]],24,"VOLUME AMOUNT","N")} -> 646774 | N20: {=_xll.PrecioBD(ONs_NY[[#This Row],[Ticker]],24,"IMBALANCE","N")} -> -0.0009 | O20: NY | P20: Semestral | Q20: 1000 | R20: Sinkable
B21: YPF | C21: YMCXD | D21: =YMCXO!K4 -> 0.070930883 | E21: =F21*$H$1 -> 110.95 | F21: {=_xll.PrecioBD(ONs_NY[[#This Row],[Ticker]],24,"ASK","N")} -> 110.95 | G21: =YMCXO!K3 -> 3.9050166 | H21: 48102 | I21: {=_xll.PrecioBD(ONs_NY[[#This Row],[Ticker]],"24","BID","N")} -> 110.65 | J21: {=_xll.PrecioBD(ONs_NY[[#This Row],[Ticker]],"24","ASK","N")} -> 110.95 | K21: {=_xll.PrecioBD(ONs_NY[[#This Row],[Ticker]],24,"QUANTITY BID","N")} -> 12826 | L21: {=_xll.PrecioBD(ONs_NY[[#This Row],[Ticker]],24,"QUANTITY ASK","N")} -> 1000 | M21: {=_xll.PrecioBD(ONs_NY[[#This Row],[Ticker]],24,"VOLUME AMOUNT","N")} -> 678005.9 | N21: {=_xll.PrecioBD(ONs_NY[[#This Row],[Ticker]],24,"IMBALANCE","N")} -> 0.0031 | O21: NY | P21: Semestral | Q21: 1 | R21: Sinkable
B22: Genneia | C22: GN49D | D22: =GN49D!K4 -> 0.071020624 | E22: =F22*$H$1 -> 105.55 | F22: {=_xll.PrecioBD(ONs_NY[[#This Row],[Ticker]],24,"ASK","N")} -> 105.55 | G22: =GN49D!K3 -> 5.1975468 | H22: 48915 | I22: {=_xll.PrecioBD(ONs_NY[[#This Row],[Ticker]],"24","BID","N")} -> 104.75 | J22: {=_xll.PrecioBD(ONs_NY[[#This Row],[Ticker]],"24","ASK","N")} -> 105.55 | K22: {=_xll.PrecioBD(ONs_NY[[#This Row],[Ticker]],24,"QUANTITY BID","N")} -> 5000 | L22: {=_xll.PrecioBD(ONs_NY[[#This Row],[Ticker]],24,"QUANTITY ASK","N")} -> 1000 | M22: {=_xll.PrecioBD(ONs_NY[[#This Row],[Ticker]],24,"VOLUME AMOUNT","N")} -> 12566 | N22: {=_xll.PrecioBD(ONs_NY[[#This Row],[Ticker]],24,"IMBALANCE","N")} -> 0.0014 | O22: NY | P22: Semestral | Q22: 1000 | R22: Sinkable
B23: Vista Energy | C23: VSCTD | D23: =VSCTD!K4 -> 0.071004906 | E23: =F23*$H$1 -> 105.35 | F23: {=_xll.PrecioBD(ONs_NY[[#This Row],[Ticker]],24,"ASK","N")} -> 105.35 | G23: =VSCTD!K3 -> 6.3443598 | H23: 49653 | I23: {=_xll.PrecioBD(ONs_NY[[#This Row],[Ticker]],"24","BID","N")} -> 105 | J23: {=_xll.PrecioBD(ONs_NY[[#This Row],[Ticker]],"24","ASK","N")} -> 105.35 | K23: {=_xll.PrecioBD(ONs_NY[[#This Row],[Ticker]],24,"QUANTITY BID","N")} -> 10000 | L23: {=_xll.PrecioBD(ONs_NY[[#This Row],[Ticker]],24,"QUANTITY ASK","N")} -> 10000 | M23: {=_xll.PrecioBD(ONs_NY[[#This Row],[Ticker]],24,"VOLUME AMOUNT","N")} -> 31545 | N23: {=_xll.PrecioBD(ONs_NY[[#This Row],[Ticker]],24,"IMBALANCE","N")} -> -0.0056 | O23: NY | P23: Semestral | Q23: 10000 | R23: Bullet
B24: Telecom | C24: TLCMD | D24: =TLCMO!K4 -> 0.07096636 | E24: =F24*$H$1 -> 110 | F24: {=_xll.PrecioBD(ONs_NY[[#This Row],[Ticker]],24,"ASK","N")} -> 110 | G24: =TLCMO!K3 -> 3.6176546 | H24: 48047 | I24: {=_xll.PrecioBD(ONs_NY[[#This Row],[Ticker]],"24","BID","N")} -> 109.65 | J24: {=_xll.PrecioBD(ONs_NY[[#This Row],[Ticker]],"24","ASK","N")} -> 110 | K24: {=_xll.PrecioBD(ONs_NY[[#This Row],[Ticker]],24,"QUANTITY BID","N")} -> 2000 | L24: {=_xll.PrecioBD(ONs_NY[[#This Row],[Ticker]],24,"QUANTITY ASK","N")} -> 3000 | M24: {=_xll.PrecioBD(ONs_NY[[#This Row],[Ticker]],24,"VOLUME AMOUNT","N")} -> 418537.5 | N24: {=_xll.PrecioBD(ONs_NY[[#This Row],[Ticker]],24,"IMBALANCE","N")} -> -0.0095 | O24: NY | P24: Semestral | Q24: 1000 | R24: Sinkable
B25: Tecpetrol | C25: TTCDD | D25: =TTCDD!K4 -> 0.067098203 | E25: =F25*$H$1 -> 106.05 | F25: {=_xll.PrecioBD(ONs_NY[[#This Row],[Ticker]],24,"ASK","N")} -> 106.05 | G25: =TTCDD!K3 -> 3.8809856 | H25: 47791 | I25: {=_xll.PrecioBD(ONs_NY[[#This Row],[Ticker]],"24","BID","N")} -> 105.5 | J25: {=_xll.PrecioBD(ONs_NY[[#This Row],[Ticker]],"24","ASK","N")} -> 106.05 | K25: {=_xll.PrecioBD(ONs_NY[[#This Row],[Ticker]],24,"QUANTITY BID","N")} -> 5000 | L25: {=_xll.PrecioBD(ONs_NY[[#This Row],[Ticker]],24,"QUANTITY ASK","N")} -> 8000 | M25: {=_xll.PrecioBD(ONs_NY[[#This Row],[Ticker]],24,"VOLUME AMOUNT","N")} -> 420302 | N25: {=_xll.PrecioBD(ONs_NY[[#This Row],[Ticker]],24,"IMBALANCE","N")} -> 0.0042 | O25: NY | P25: Semestral | Q25: 1000 | R25: Bullet
B26: YPF Luz | C26: YFCJD | D26: =YFCJD!K4 -> 0.070742473 | E26: =F26*$H$1 -> 106.7 | F26: {=_xll.PrecioBD(ONs_NY[[#This Row],[Ticker]],24,"ASK","N")} -> 106.7 | G26: =YFCJD!K3 -> 4.4526979 | H26: 48503 | I26: {=_xll.PrecioBD(ONs_NY[[#This Row],[Ticker]],"24","BID","N")} -> 106.35 | J26: {=_xll.PrecioBD(ONs_NY[[#This Row],[Ticker]],"24","ASK","N")} -> 106.7 | K26: {=_xll.PrecioBD(ONs_NY[[#This Row],[Ticker]],24,"QUANTITY BID","N")} -> 1000 | L26: {=_xll.PrecioBD(ONs_NY[[#This Row],[Ticker]],24,"QUANTITY ASK","N")} -> 30000 | M26: {=_xll.PrecioBD(ONs_NY[[#This Row],[Ticker]],24,"VOLUME AMOUNT","N")} -> 60720.5 | N26: {=_xll.PrecioBD(ONs_NY[[#This Row],[Ticker]],24,"IMBALANCE","N")} -> -0.0009 | O26: NY | P26: Semestral | Q26: 1000 | R26: Sinkable
B27: YPF | C27: YMCJD | D27: =YMCJO!K4 -> 0.06732305 | E27: =F27*$H$1 -> 104.4 | F27: {=_xll.PrecioBD(ONs_NY[[#This Row],[Ticker]],24,"ASK","N")} -> 104.4 | G27: =YMCJO!K3 -> 4.9493416 | H27: 48852 | I27: {=_xll.PrecioBD(ONs_NY[[#This Row],[Ticker]],"24","BID","N")} -> 103.8 | J27: {=_xll.PrecioBD(ONs_NY[[#This Row],[Ticker]],"24","ASK","N")} -> 104.4 | K27: {=_xll.PrecioBD(ONs_NY[[#This Row],[Ticker]],24,"QUANTITY BID","N")} -> 751 | L27: {=_xll.PrecioBD(ONs_NY[[#This Row],[Ticker]],24,"QUANTITY ASK","N")} -> 17187 | M27: {=_xll.PrecioBD(ONs_NY[[#This Row],[Ticker]],24,"VOLUME AMOUNT","N")} -> 287778.93 | N27: {=_xll.PrecioBD(ONs_NY[[#This Row],[Ticker]],24,"IMBALANCE","N")} -> -0.0019 | O27: NY | P27: Semestral | Q27: 1 | R27: Sinkable
B28: Tecpetrol | C28: TTCAD | D28: =TTCAD!K4 -> 0.065453872 | E28: =F28*$H$1 -> 106.05 | F28: {=_xll.PrecioBD(ONs_NY[[#This Row],[Ticker]],24,"ASK","N")} -> 106.05 | G28: =TTCAD!K3 -> 4.7617205 | H28: 48601 | I28: {=_xll.PrecioBD(ONs_NY[[#This Row],[Ticker]],"24","BID","N")} -> 105.5 | J28: {=_xll.PrecioBD(ONs_NY[[#This Row],[Ticker]],"24","ASK","N")} -> 106.05 | K28: {=_xll.PrecioBD(ONs_NY[[#This Row],[Ticker]],24,"QUANTITY BID","N")} -> 15000 | L28: {=_xll.PrecioBD(ONs_NY[[#This Row],[Ticker]],24,"QUANTITY ASK","N")} -> 100000 | M28: {=_xll.PrecioBD(ONs_NY[[#This Row],[Ticker]],24,"VOLUME AMOUNT","N")} -> 9576 | N28: {=_xll.PrecioBD(ONs_NY[[#This Row],[Ticker]],24,"IMBALANCE","N")} -> 0.0033 | O28: NY | P28: Semestral | Q28: 1000 | R28: Sinkable
B29: TGS | C29: TSC3D | D29: =TSC3D!K4 -> 0.066055217 | E29: =F29*$H$1 -> 109.4 | F29: {=_xll.PrecioBD(ONs_NY[[#This Row],[Ticker]],24,"ASK","N")} -> 109.4 | G29: =TSC3D!K3 -> 4.3735015 | H29: 48053 | I29: {=_xll.PrecioBD(ONs_NY[[#This Row],[Ticker]],"24","BID","N")} -> 108 | J29: {=_xll.PrecioBD(ONs_NY[[#This Row],[Ticker]],"24","ASK","N")} -> 109.4 | K29: {=_xll.PrecioBD(ONs_NY[[#This Row],[Ticker]],24,"QUANTITY BID","N")} -> 10000 | L29: {=_xll.PrecioBD(ONs_NY[[#This Row],[Ticker]],24,"QUANTITY ASK","N")} -> 12000 | M29: {=_xll.PrecioBD(ONs_NY[[#This Row],[Ticker]],24,"VOLUME AMOUNT","N")} -> 229980 | N29: {=_xll.PrecioBD(ONs_NY[[#This Row],[Ticker]],24,"IMBALANCE","N")} -> -0.0004 | O29: NY | P29: Semestral | Q29: 10000 | R29: Bullet
B30: Pampa energia | C30: MGCMD | D30: =MGCMD!K4 -> 0.064987287 | E30: =F30*$H$1 -> 110.5 | F30: {=_xll.PrecioBD(ONs_NY[[#This Row],[Ticker]],24,"ASK","N")} -> 110.5 | G30: =MGCMD!K3 -> 4.3828069 | H30: 48101 | I30: {=_xll.PrecioBD(ONs_NY[[#This Row],[Ticker]],"24","BID","N")} -> 109.5 | J30: {=_xll.PrecioBD(ONs_NY[[#This Row],[Ticker]],"24","ASK","N")} -> 110.5 | K30: {=_xll.PrecioBD(ONs_NY[[#This Row],[Ticker]],24,"QUANTITY BID","N")} -> 50000 | L30: {=_xll.PrecioBD(ONs_NY[[#This Row],[Ticker]],24,"QUANTITY ASK","N")} -> 15000 | M30: {=_xll.PrecioBD(ONs_NY[[#This Row],[Ticker]],24,"VOLUME AMOUNT","N")} -> 298755.5 | N30: {=_xll.PrecioBD(ONs_NY[[#This Row],[Ticker]],24,"IMBALANCE","N")} -> 0.0027 | O30: NY | P30: Semestral | Q30: 10000 | R30: Bullet
B31: Pan American Energy | C31: PNXCD | D31: =PNXCD!K4 -> 0.064733049 | E31: =F31*$H$1 -> 111.6 | F31: {=_xll.PrecioBD(ONs_NY[[#This Row],[Ticker]],24,"ASK","N")} -> 111.6 | G31: =PNXCD!K3 -> 4.14447 | H31: 48334 | I31: {=_xll.PrecioBD(ONs_NY[[#This Row],[Ticker]],"24","BID","N")} -> 111.5 | J31: {=_xll.PrecioBD(ONs_NY[[#This Row],[Ticker]],"24","ASK","N")} -> 111.6 | K31: {=_xll.PrecioBD(ONs_NY[[#This Row],[Ticker]],24,"QUANTITY BID","N")} -> 8000 | L31: {=_xll.PrecioBD(ONs_NY[[#This Row],[Ticker]],24,"QUANTITY ASK","N")} -> 2000 | M31: {=_xll.PrecioBD(ONs_NY[[#This Row],[Ticker]],24,"VOLUME AMOUNT","N")} -> 91545.5 | N31: {=_xll.PrecioBD(ONs_NY[[#This Row],[Ticker]],24,"IMBALANCE","N")} -> 0.0008 | O31: NY | P31: Semestral | Q31: 1000 | R31: Sinkable
B32: Arcor | C32: ARC1D | D32: =ARC1D!K4 -> 0.061897132 | E32: =F32*$H$1 -> 106 | F32: {=_xll.PrecioBD(ONs_NY[[#This Row],[Ticker]],24,"ASK","N")} -> 106 | G32: =ARC1D!K3 -> 2.9888579 | H32: 48061 | I32: {=_xll.PrecioBD(ONs_NY[[#This Row],[Ticker]],"24","BID","N")} -> 105.5 | J32: {=_xll.PrecioBD(ONs_NY[[#This Row],[Ticker]],"24","ASK","N")} -> 106 | K32: {=_xll.PrecioBD(ONs_NY[[#This Row],[Ticker]],24,"QUANTITY BID","N")} -> 8000 | L32: {=_xll.PrecioBD(ONs_NY[[#This Row],[Ticker]],24,"QUANTITY ASK","N")} -> 1000 | M32: {=_xll.PrecioBD(ONs_NY[[#This Row],[Ticker]],24,"VOLUME AMOUNT","N")} -> 50772 | N32: {=_xll.PrecioBD(ONs_NY[[#This Row],[Ticker]],24,"IMBALANCE","N")} -> 0.0061 | O32: NY | P32: Trimestral | Q32: 1000 | R32: Sinkable
B33: Banco Macro | C33: BACGD | D33: =BACGD!K4 -> 0.06251196 | E33: =F33*$H$1 -> 106.5 | F33: {=_xll.PrecioBD(ONs_NY[[#This Row],[Ticker]],24,"ASK","N")} -> 106.5 | G33: =BACGD!K3 -> 2.9228418 | H33: 47292 | I33: {=_xll.PrecioBD(ONs_NY[[#This Row],[Ticker]],"24","BID","N")} -> 106.1 | J33: {=_xll.PrecioBD(ONs_NY[[#This Row],[Ticker]],"24","ASK","N")} -> 106.5 | K33: {=_xll.PrecioBD(ONs_NY[[#This Row],[Ticker]],24,"QUANTITY BID","N")} -> 3000 | L33: {=_xll.PrecioBD(ONs_NY[[#This Row],[Ticker]],24,"QUANTITY ASK","N")} -> 1000 | M33: {=_xll.PrecioBD(ONs_NY[[#This Row],[Ticker]],24,"VOLUME AMOUNT","N")} -> 135035 | N33: {=_xll.PrecioBD(ONs_NY[[#This Row],[Ticker]],24,"IMBALANCE","N")} -> -0.0028 | O33: NY | P33: Semestral | Q33: 1000 | R33: Bullet
B34: Galicia | C34: BYCHD | D34: =BYCHD!K4 -> 0.054009077 | E34: =F34*$H$1 -> 108.5 | F34: {=_xll.PrecioBD(ONs_NY[[#This Row],[Ticker]],24,"ASK","N")} -> 108.5 | G34: =BYCHD!K3 -> 2.3546277 | H34: 47036 | I34: {=_xll.PrecioBD(ONs_NY[[#This Row],[Ticker]],"24","BID","N")} -> 107.9 | J34: {=_xll.PrecioBD(ONs_NY[[#This Row],[Ticker]],"24","ASK","N")} -> 108.5 | K34: {=_xll.PrecioBD(ONs_NY[[#This Row],[Ticker]],24,"QUANTITY BID","N")} -> 10000 | L34: {=_xll.PrecioBD(ONs_NY[[#This Row],[Ticker]],24,"QUANTITY ASK","N")} -> 900 | M34: {=_xll.PrecioBD(ONs_NY[[#This Row],[Ticker]],24,"VOLUME AMOUNT","N")} -> 32981.08 | N34: {=_xll.PrecioBD(ONs_NY[[#This Row],[Ticker]],24,"IMBALANCE","N")} -> -0.0046 | O34: NY | P34: Semestral | Q34: 2000 | R34: Bullet
B35: YPF | C35: YMCID | D35: =YMCID!K4 -> 0.054492775 | E35: =F35*$H$1 -> 107.3 | F35: {=_xll.PrecioBD(ONs_NY[[#This Row],[Ticker]],24,"ASK","N")} -> 107.3 | G35: =YMCID!K3 -> 1.7203707 | H35: 47299 | I35: {=_xll.PrecioBD(ONs_NY[[#This Row],[Ticker]],"24","BID","N")} -> 107.05 | J35: {=_xll.PrecioBD(ONs_NY[[#This Row],[Ticker]],"24","ASK","N")} -> 107.3 | K35: {=_xll.PrecioBD(ONs_NY[[#This Row],[Ticker]],24,"QUANTITY BID","N")} -> 795 | L35: {=_xll.PrecioBD(ONs_NY[[#This Row],[Ticker]],24,"QUANTITY ASK","N")} -> 455 | M35: {=_xll.PrecioBD(ONs_NY[[#This Row],[Ticker]],24,"VOLUME AMOUNT","N")} -> 192851.62 | N35: {=_xll.PrecioBD(ONs_NY[[#This Row],[Ticker]],24,"IMBALANCE","N")} -> 0.0023 | O35: NY | P35: Semestral | Q35: 1 | R35: Sinkable
B36: Capex | C36: CAC5D | D36: =CAC5D!K4 -> 0.055308428 | E36: =F36*$H$1 -> 81.6 | F36: {=_xll.PrecioBD(ONs_NY[[#This Row],[Ticker]],24,"ASK","N")} -> 81.6 | G36: =CAC5D!K3 -> 1.1688311 | H36: 46990 | I36: {=_xll.PrecioBD(ONs_NY[[#This Row],[Ticker]],"24","BID","N")} -> 81.01 | J36: {=_xll.PrecioBD(ONs_NY[[#This Row],[Ticker]],"24","ASK","N")} -> 81.6 | K36: {=_xll.PrecioBD(ONs_NY[[#This Row],[Ticker]],24,"QUANTITY BID","N")} -> 857 | L36: {=_xll.PrecioBD(ONs_NY[[#This Row],[Ticker]],24,"QUANTITY ASK","N")} -> 2606 | M36: {=_xll.PrecioBD(ONs_NY[[#This Row],[Ticker]],24,"VOLUME AMOUNT","N")} -> 14501.94 | N36: {=_xll.PrecioBD(ONs_NY[[#This Row],[Ticker]],24,"IMBALANCE","N")} -> -0.007 | O36: NY | P36: Semestral | Q36: 1 | R36: Sinkable
B37: Irsa | C37: IRCFD | D37: =IRCFO!K4 -> 0.052728108 | E37: =F37*$H$1 -> 69.11 | F37: {=_xll.PrecioBD(ONs_NY[[#This Row],[Ticker]],24,"ASK","N")} -> 69.11 | G37: =IRCFO!K3 -> 1.4402295 | H37: 46926 | I37: {=_xll.PrecioBD(ONs_NY[[#This Row],[Ticker]],"24","BID","N")} -> 68.92 | J37: {=_xll.PrecioBD(ONs_NY[[#This Row],[Ticker]],"24","ASK","N")} -> 69.11 | K37: {=_xll.PrecioBD(ONs_NY[[#This Row],[Ticker]],24,"QUANTITY BID","N")} -> 3084 | L37: {=_xll.PrecioBD(ONs_NY[[#This Row],[Ticker]],24,"QUANTITY ASK","N")} -> 198 | M37: {=_xll.PrecioBD(ONs_NY[[#This Row],[Ticker]],24,"VOLUME AMOUNT","N")} -> 40033.42 | N37: {=_xll.PrecioBD(ONs_NY[[#This Row],[Ticker]],24,"IMBALANCE","N")} -> -0.0018 | O37: NY | P37: Semestral | Q37: 1 | R37: Sinkable
B38: Mastellone | C38: MTCGD | D38: =MTCGD!K4 -> 0.03866016 | E38: =F38*$H$1 -> 103.95 | F38: {=_xll.PrecioBD(ONs_NY[[#This Row],[Ticker]],24,"ASK","N")} -> 103.95 | G38: =MTCGD!K3 -> 0.38153679 | H38: 46203 | I38: {=_xll.PrecioBD(ONs_NY[[#This Row],[Ticker]],"24","BID","N")} -> 103.55 | J38: {=_xll.PrecioBD(ONs_NY[[#This Row],[Ticker]],"24","ASK","N")} -> 103.95 | K38: {=_xll.PrecioBD(ONs_NY[[#This Row],[Ticker]],24,"QUANTITY BID","N")} -> 7512 | L38: {=_xll.PrecioBD(ONs_NY[[#This Row],[Ticker]],24,"QUANTITY ASK","N")} -> 1959 | M38: {=_xll.PrecioBD(ONs_NY[[#This Row],[Ticker]],24,"VOLUME AMOUNT","N")} -> 53571.64 | N38: {=_xll.PrecioBD(ONs_NY[[#This Row],[Ticker]],24,"IMBALANCE","N")} -> 0.0048 | O38: NY | P38: Trimestral | Q38: 1 | R38: Bullet
B39: YPF | C39: YCAMD | D39: =YCAMO!K4 -> 0.022830907 | E39: =F39*$H$1 -> 107 | F39: {=_xll.PrecioBD(ONs_NY[[#This Row],[Ticker]],24,"ASK","N")} -> 107 | G39: =YCAMO!K3 -> 1.3856072 | H39: 46589 | I39: {=_xll.PrecioBD(ONs_NY[[#This Row],[Ticker]],"24","BID","N")} -> 101 | J39: {=_xll.PrecioBD(ONs_NY[[#This Row],[Ticker]],"24","ASK","N")} -> 107 | K39: {=_xll.PrecioBD(ONs_NY[[#This Row],[Ticker]],24,"QUANTITY BID","N")} -> 10000 | L39: {=_xll.PrecioBD(ONs_NY[[#This Row],[Ticker]],24,"QUANTITY ASK","N")} -> 50000 | M39: {=_xll.PrecioBD(ONs_NY[[#This Row],[Ticker]],24,"VOLUME AMOUNT","N")} -> 0 | N39: {=_xll.PrecioBD(ONs_NY[[#This Row],[Ticker]],24,"IMBALANCE","N")} -> 0 | O39: NY | P39: Semestral | Q39: 10000 | R39: Bullet
B40: Pan American | C40: PNDCD | D40: =PNDCD!K4 -> -0.0093629867 | E40: =F40*$H$1 -> 65.92 | F40: {=_xll.PrecioBD(ONs_NY[[#This Row],[Ticker]],24,"ASK","N")} -> 65.92 | G40: =PNDCD!K3 -> 0.71606679 | H40: 46507 | I40: {=_xll.PrecioBD(ONs_NY[[#This Row],[Ticker]],"24","BID","N")} -> 64.21 | J40: {=_xll.PrecioBD(ONs_NY[[#This Row],[Ticker]],"24","ASK","N")} -> 65.92 | K40: {=_xll.PrecioBD(ONs_NY[[#This Row],[Ticker]],24,"QUANTITY BID","N")} -> 2000 | L40: {=_xll.PrecioBD(ONs_NY[[#This Row],[Ticker]],24,"QUANTITY ASK","N")} -> 17000 | M40: {=_xll.PrecioBD(ONs_NY[[#This Row],[Ticker]],24,"VOLUME AMOUNT","N")} -> 5177.6 | N40: {=_xll.PrecioBD(ONs_NY[[#This Row],[Ticker]],24,"IMBALANCE","N")} -> -0.0087 | O40: NY | P40: Semestral | Q40: 1000 | R40: Sinkable

Sheet ONs Argentina
G1: Comision | H1: 1
G2: Dia de liquidacion | H2: =Main!B1 -> 46060
B4: Empresa | C4: Ticker | D4: TIR | E4: Precio | F4: Sin comision | G4: MD | H4: Vto | I4: Ask volume | J4: Total volume | K4: Ley | L4: Periodicidad | M4: Lamina minima | N4: Tipo
B5: Central Puerto | C5: NPCAD | D5: =NPCAD!K4 -> #NUM! | E5: =F5*$H$1 -> 0 | F5: {=_xll.PrecioBD(ONs_NY_2[[#This Row],[Ticker]],24,"ASK","N")} -> 0 | G5: =NPCAD!K3 -> #NUM! | I5: {=_xll.PrecioBD(ONs_NY_2[[#This Row],[Ticker]],24,"QUANTITY ASK","N")} -> 0 | J5: {=_xll.PrecioBD(ONs_NY_2[[#This Row],[Ticker]],24,"VOLUME AMOUNT","N")} -> 0 | U5: Genneia | V5: GN40D | W5: =GN40D!AQ4 -> 0 | X5: =Y5*$H$1 -> #REF! | Y5: =VLOOKUP(V5,#REF!,5,0) -> #REF! | Z5: =GN40D!AQ3 -> 0 | AA5: =VLOOKUP(V5,#REF!,3,0) -> #REF! | AB5: Argentina | AC5: =VLOOKUP(V5,#REF!,9,0) -> #REF! | AD5: 1 | AE5: =VLOOKUP(V5,#REF!,10,0) -> #REF! | AF5: =NOMINAL(W5,2) -> #NUM! | AG5: =(1 +W5 )^(1/12) - 1 -> 0
B6: Tecpetrol | C6: TTC7D | D6: =TTC7D!K4 -> #NUM! | E6: =F6*$H$1 -> 0 | F6: {=_xll.PrecioBD(ONs_NY_2[[#This Row],[Ticker]],24,"ASK","N")} -> 0 | G6: =TTC7D!K3 -> #NUM! | I6: {=_xll.PrecioBD(ONs_NY_2[[#This Row],[Ticker]],24,"QUANTITY ASK","N")} -> 0 | J6: {=_xll.PrecioBD(ONs_NY_2[[#This Row],[Ticker]],24,"VOLUME AMOUNT","N")} -> 0
B7: PCR | C7: PQCSD | D7: =PQCSD!K4 -> 0.082240602 | E7: =F7*$H$1 -> 103.55 | F7: {=_xll.PrecioBD(ONs_NY_2[[#This Row],[Ticker]],24,"ASK","N")} -> 103.55 | G7: =PQCSD!K3 -> 3.924396 | I7: {=_xll.PrecioBD(ONs_NY_2[[#This Row],[Ticker]],24,"QUANTITY ASK","N")} -> 2289 | J7: {=_xll.PrecioBD(ONs_NY_2[[#This Row],[Ticker]],24,"VOLUME AMOUNT","N")} -> 79909.18
B8: CNH Industrial | C8: CICAD | D8: =CICAD!K4 -> 0.078574619 | E8: =F8*$H$1 -> 102 | F8: {=_xll.PrecioBD(ONs_NY_2[[#This Row],[Ticker]],24,"ASK","N")} -> 102 | G8: =CICAD!K3 -> 2.0611481 | I8: {=_xll.PrecioBD(ONs_NY_2[[#This Row],[Ticker]],24,"QUANTITY ASK","N")} -> 260 | J8: {=_xll.PrecioBD(ONs_NY_2[[#This Row],[Ticker]],24,"VOLUME AMOUNT","N")} -> 51192.87
B9: Edenor | C9: DNC5D | D9: =DNC5D!K4 -> 0.076064351 | E9: =F9*$H$1 -> 104.6 | F9: {=_xll.PrecioBD(ONs_NY_2[[#This Row],[Ticker]],24,"ASK","N")} -> 104.6 | G9: =DNC5D!K3 -> 2.2278172 | I9: {=_xll.PrecioBD(ONs_NY_2[[#This Row],[Ticker]],24,"QUANTITY ASK","N")} -> 65 | J9: {=_xll.PrecioBD(ONs_NY_2[[#This Row],[Ticker]],24,"VOLUME AMOUNT","N")} -> 192381.55
B10: Oiltanking | C10: OT42D | D10: =OT42D!K4 -> 0.072685209 | E10: =F10*$H$1 -> 103.6 | F10: {=_xll.PrecioBD(ONs_NY_2[[#This Row],[Ticker]],24,"ASK","N")} -> 103.6 | G10: =OT42D!K3 -> 3.338671 | I10: {=_xll.PrecioBD(ONs_NY_2[[#This Row],[Ticker]],24,"QUANTITY ASK","N")} -> 229 | J10: {=_xll.PrecioBD(ONs_NY_2[[#This Row],[Ticker]],24,"VOLUME AMOUNT","N")} -> 12444.02
B11: Pecom | C11: MCC2D | D11: =MCC2D!K4 -> 0.07945601 | E11: =F11*$H$1 -> 101 | F11: {=_xll.PrecioBD(ONs_NY_2[[#This Row],[Ticker]],24,"ASK","N")} -> 101 | G11: =MCC2D!K3 -> 1.2141661 | I11: {=_xll.PrecioBD(ONs_NY_2[[#This Row],[Ticker]],24,"QUANTITY ASK","N")} -> 2500 | J11: {=_xll.PrecioBD(ONs_NY_2[[#This Row],[Ticker]],24,"VOLUME AMOUNT","N")} -> 215050.73
B12: YPF | C12: YM39D | D12: =YM39D!K4 -> 0.067519739 | E12: =F12*$H$1 -> 108.85 | F12: {=_xll.PrecioBD(ONs_NY_2[[#This Row],[Ticker]],24,"ASK","N")} -> 108.85 | G12: =YM39D!K3 -> 3.6728245 | I12: {=_xll.PrecioBD(ONs_NY_2[[#This Row],[Ticker]],24,"QUANTITY ASK","N")} -> 998 | J12: {=_xll.PrecioBD(ONs_NY_2[[#This Row],[Ticker]],24,"VOLUME AMOUNT","N")} -> 302446.53
B13: CNH Industrial | C13: CIC9D | D13: =CIC9D!K4 -> 0.069136474 | E13: =F13*$H$1 -> 103.5 | F13: {=_xll.PrecioBD(ONs_NY_2[[#This Row],[Ticker]],24,"ASK","N")} -> 103.5 | G13: =CIC9D!K3 -> 1.1842598 | I13: {=_xll.PrecioBD(ONs_NY_2[[#This Row],[Ticker]],24,"QUANTITY ASK","N")} -> 2500 | J13: {=_xll.PrecioBD(ONs_NY_2[[#This Row],[Ticker]],24,"VOLUME AMOUNT","N")} -> 238.11
B14: Oleoductos del Valle | C14: OLC6D | D14: =OLC6D!K4 -> 0.068953761 | E14: =F14*$H$1 -> 103.4 | F14: {=_xll.PrecioBD(ONs_NY_2[[#This Row],[Ticker]],24,"ASK","N")} -> 103.4 | G14: =OLC6D!K3 -> 2.8758664 | I14: {=_xll.PrecioBD(ONs_NY_2[[#This Row],[Ticker]],24,"QUANTITY ASK","N")} -> 1000 | J14: {=_xll.PrecioBD(ONs_NY_2[[#This Row],[Ticker]],24,"VOLUME AMOUNT","N")} -> 79951.6
B15: Edenor | C15: DNC3D | D15: =DNC3D!K4 -> 0.06271911 | E15: =F15*$H$1 -> 104.75 | F15: {=_xll.PrecioBD(ONs_NY_2[[#This Row],[Ticker]],24,"ASK","N")} -> 104.75 | G15: =DNC3D!K3 -> 0.74324279 | I15: {=_xll.PrecioBD(ONs_NY_2[[#This Row],[Ticker]],24,"QUANTITY ASK","N")} -> 243 | J15: {=_xll.PrecioBD(ONs_NY_2[[#This Row],[Ticker]],24,"VOLUME AMOUNT","N")} -> 105828.1
B16: Pluspetrol | C16: PLC2D | D16: =PLC2D!K4 -> 0.065908816 | E16: =F16*$H$1 -> 105.6 | F16: {=_xll.PrecioBD(ONs_NY_2[[#This Row],[Ticker]],24,"ASK","N")} -> 105.6 | G16: =PLC2D!K3 -> 3.3417985 | I16: {=_xll.PrecioBD(ONs_NY_2[[#This Row],[Ticker]],24,"QUANTITY ASK","N")} -> 3944 | J16: {=_xll.PrecioBD(ONs_NY_2[[#This Row],[Ticker]],24,"VOLUME AMOUNT","N")} -> 98522.64
B17: John Deere | C17: HJCID | D17: =HJCID!K4 -> 0.064154342 | E17: =F17*$H$1 -> 102.95 | F17: {=_xll.PrecioBD(ONs_NY_2[[#This Row],[Ticker]],24,"ASK","N")} -> 102.95 | G17: =HJCID!K3 -> 1.2075583 | I17: {=_xll.PrecioBD(ONs_NY_2[[#This Row],[Ticker]],24,"QUANTITY ASK","N")} -> 1200 | J17: {=_xll.PrecioBD(ONs_NY_2[[#This Row],[Ticker]],24,"VOLUME AMOUNT","N")} -> 119309.1
B18: IRSA | C18: IRCOD | D18: =IRCOD!K4 -> 0.065576461 | E18: =F18*$H$1 -> 102.9 | F18: {=_xll.PrecioBD(ONs_NY_2[[#This Row],[Ticker]],24,"ASK","N")} -> 102.9 | G18: =IRCOD!K3 -> 3.2104623 | I18: {=_xll.PrecioBD(ONs_NY_2[[#This Row],[Ticker]],24,"QUANTITY ASK","N")} -> 266 | J18: {=_xll.PrecioBD(ONs_NY_2[[#This Row],[Ticker]],24,"VOLUME AMOUNT","N")} -> 25842.8
B19: Pan American | C19: PN36D | D19: =PN36D!K4 -> 0.065952751 | E19: =F19*$H$1 -> 105.3 | F19: {=_xll.PrecioBD(ONs_NY_2[[#This Row],[Ticker]],24,"ASK","N")} -> 105.3 | G19: =PN36D!K3 -> 4.6091756 | I19: {=_xll.PrecioBD(ONs_NY_2[[#This Row],[Ticker]],24,"QUANTITY ASK","N")} -> 32264 | J19: {=_xll.PrecioBD(ONs_NY_2[[#This Row],[Ticker]],24,"VOLUME AMOUNT","N")} -> 145271.49
B20: Oleoductos del Valle | C20: OLC5D | D20: =OLC5D!K4 -> 0.057652792 | E20: =F20*$H$1 -> 106 | F20: {=_xll.PrecioBD(ONs_NY_2[[#This Row],[Ticker]],24,"ASK","N")} -> 106 | G20: =OLC5D!K3 -> 2.108082 | I20: {=_xll.PrecioBD(ONs_NY_2[[#This Row],[Ticker]],24,"QUANTITY ASK","N")} -> 1500 | J20: {=_xll.PrecioBD(ONs_NY_2[[#This Row],[Ticker]],24,"VOLUME AMOUNT","N")} -> 8719.92
B21: Pan American | C21: PN35D | D21: =PN35D!K4 -> 0.062201849 | E21: =F21*$H$1 -> 105.35 | F21: {=_xll.PrecioBD(ONs_NY_2[[#This Row],[Ticker]],24,"ASK","N")} -> 105.35 | G21: =PN35D!K3 -> 3.1079836 | I21: {=_xll.PrecioBD(ONs_NY_2[[#This Row],[Ticker]],24,"QUANTITY ASK","N")} -> 3137 | J21: {=_xll.PrecioBD(ONs_NY_2[[#This Row],[Ticker]],24,"VOLUME AMOUNT","N")} -> 97183.11
B22: Central Puerto | C22: NPCCD | D22: =NPCCD!K4 -> 0.061561695 | E22: =F22*$H$1 -> 109.7 | F22: {=_xll.PrecioBD(ONs_NY_2[[#This Row],[Ticker]],24,"ASK","N")} -> 109.7 | G22: =NPCCD!K3 -> 2.9810782 | I22: {=_xll.PrecioBD(ONs_NY_2[[#This Row],[Ticker]],24,"QUANTITY ASK","N")} -> 9137 | J22: {=_xll.PrecioBD(ONs_NY_2[[#This Row],[Ticker]],24,"VOLUME AMOUNT","N")} -> 93323.45
B23: Tecpetrol | C23: TTC9D | D23: =TTC9D!K4 -> 0.060247549 | E23: =F23*$H$1 -> 104.8 | F23: {=_xll.PrecioBD(ONs_NY_2[[#This Row],[Ticker]],24,"ASK","N")} -> 104.8 | G23: =TTC9D!K3 -> 3.1937361 | I23: {=_xll.PrecioBD(ONs_NY_2[[#This Row],[Ticker]],24,"QUANTITY ASK","N")} -> 200000 | J23: {=_xll.PrecioBD(ONs_NY_2[[#This Row],[Ticker]],24,"VOLUME AMOUNT","N")} -> 132144.77
B24: Vista Energy | C24: VSCRD | D24: =VSCRD!K4 -> 0.06623157 | E24: =F24*$H$1 -> 107 | F24: {=_xll.PrecioBD(ONs_NY_2[[#This Row],[Ticker]],24,"ASK","N")} -> 107 | G24: =VSCRD!K3 -> 3.8119873 | I24: {=_xll.PrecioBD(ONs_NY_2[[#This Row],[Ticker]],24,"QUANTITY ASK","N")} -> 29980 | J24: {=_xll.PrecioBD(ONs_NY_2[[#This Row],[Ticker]],24,"VOLUME AMOUNT","N")} -> 338646.01
B25: YPF | C25: YM40D | D25: =YM40D!K4 -> 0.061293909 | E25: =F25*$H$1 -> 105 | F25: {=_xll.PrecioBD(ONs_NY_2[[#This Row],[Ticker]],24,"ASK","N")} -> 105 | G25: =YM40D!K3 -> 2.2767466 | I25: {=_xll.PrecioBD(ONs_NY_2[[#This Row],[Ticker]],24,"QUANTITY ASK","N")} -> 9884 | J25: {=_xll.PrecioBD(ONs_NY_2[[#This Row],[Ticker]],24,"VOLUME AMOUNT","N")} -> 65592.11
B26: Pluspetrol | C26: PLC3D | D26: =PLC3D!K4 -> 0.059478983 | E26: =F26*$H$1 -> 103 | F26: {=_xll.PrecioBD(ONs_NY_2[[#This Row],[Ticker]],24,"ASK","N")} -> 103 | G26: =PLC3D!K3 -> 2.0391423 | I26: {=_xll.PrecioBD(ONs_NY_2[[#This Row],[Ticker]],24,"QUANTITY ASK","N")} -> 100 | J26: {=_xll.PrecioBD(ONs_NY_2[[#This Row],[Ticker]],24,"VOLUME AMOUNT","N")} -> 27936.94
B27: Profertil | C27: PFC2D | D27: =PFC2D!K4 -> 0.061773577 | E27: =F27*$H$1 -> 102.2 | F27: {=_xll.PrecioBD(ONs_NY_2[[#This Row],[Ticker]],24,"ASK","N")} -> 102.2 | G27: =PFC2D!K3 -> 1.337615 | I27: {=_xll.PrecioBD(ONs_NY_2[[#This Row],[Ticker]],24,"QUANTITY ASK","N")} -> 1353 | J27: {=_xll.PrecioBD(ONs_NY_2[[#This Row],[Ticker]],24,"VOLUME AMOUNT","N")} -> 14388.93
B28: Telecom | C28: TLCOD | D28: =TLCOD!K4 -> 0.060689834 | E28: =F28*$H$1 -> 103.95 | F28: {=_xll.PrecioBD(ONs_NY_2[[#This Row],[Ticker]],24,"ASK","N")} -> 103.95 | G28: =TLCOD!K3 -> 2.4949476 | I28: {=_xll.PrecioBD(ONs_NY_2[[#This Row],[Ticker]],24,"QUANTITY ASK","N")} -> 11672 | J28: {=_xll.PrecioBD(ONs_NY_2[[#This Row],[Ticker]],24,"VOLUME AMOUNT","N")} -> 40860.87
B29: Vista Energy | C29: VSCPD | D29: =VSCPD!K4 -> 0.059060559 | E29: =F29*$H$1 -> 107.05 | F29: {=_xll.PrecioBD(ONs_NY_2[[#This Row],[Ticker]],24,"ASK","N")} -> 107.05 | G29: =VSCPD!K3 -> 2.1977266 | I29: {=_xll.PrecioBD(ONs_NY_2[[#This Row],[Ticker]],24,"QUANTITY ASK","N")} -> 3769 | J29: {=_xll.PrecioBD(ONs_NY_2[[#This Row],[Ticker]],24,"VOLUME AMOUNT","N")} -> 39428.5
B30: Pan American | C30: PN41D | D30: =PN41D!K4 -> 0.065374085 | E30: =F30*$H$1 -> 106.7 | F30: {=_xll.PrecioBD(ONs_NY_2[[#This Row],[Ticker]],24,"ASK","N")} -> 106.7 | G30: =PN41D!K3 -> 2.9958278 | I30: {=_xll.PrecioBD(ONs_NY_2[[#This Row],[Ticker]],24,"QUANTITY ASK","N")} -> 68 | J30: {=_xll.PrecioBD(ONs_NY_2[[#This Row],[Ticker]],24,"VOLUME AMOUNT","N")} -> 25770.47
B31: OilTanking | C31: OTS2D | D31: =OTS2D!K4 -> 0.056252691 | E31: =F31*$H$1 -> 102 | F31: {=_xll.PrecioBD(ONs_NY_2[[#This Row],[Ticker]],24,"ASK","N")} -> 102 | G31: =OTS2D!K3 -> 1.1352231 | I31: {=_xll.PrecioBD(ONs_NY_2[[#This Row],[Ticker]],24,"QUANTITY ASK","N")} -> 1488 | J31: {=_xll.PrecioBD(ONs_NY_2[[#This Row],[Ticker]],24,"VOLUME AMOUNT","N")} -> 14561.29
B32: Arcor | C32: RCCRD | D32: =RCCRD!K4 -> 0.051357481 | E32: =F32*$H$1 -> 103.65 | F32: {=_xll.PrecioBD(ONs_NY_2[[#This Row],[Ticker]],24,"ASK","N")} -> 103.65 | G32: =RCCRD!K3 -> 1.174694 | I32: {=_xll.PrecioBD(ONs_NY_2[[#This Row],[Ticker]],24,"QUANTITY ASK","N")} -> 3866 | J32: {=_xll.PrecioBD(ONs_NY_2[[#This Row],[Ticker]],24,"VOLUME AMOUNT","N")} -> 86441.55
B33: Scania | C33: SBC1D | D33: =SBC1D!K4 -> 0.056514046 | E33: =F33*$H$1 -> 105.65 | F33: {=_xll.PrecioBD(ONs_NY_2[[#This Row],[Ticker]],24,"ASK","N")} -> 105.65 | G33: =SBC1D!K3 -> 0.77451223 | I33: {=_xll.PrecioBD(ONs_NY_2[[#This Row],[Ticker]],24,"QUANTITY ASK","N")} -> 226 | J33: {=_xll.PrecioBD(ONs_NY_2[[#This Row],[Ticker]],24,"VOLUME AMOUNT","N")} -> 4926.1
B34: YPF | C34: YM38D | D34: =YM38D!K4 -> 0.051008293 | E34: =F34*$H$1 -> 103.8 | F34: {=_xll.PrecioBD(ONs_NY_2[[#This Row],[Ticker]],24,"ASK","N")} -> 103.8 | G34: =YM38D!K3 -> 1.3523897 | I34: {=_xll.PrecioBD(ONs_NY_2[[#This Row],[Ticker]],24,"QUANTITY ASK","N")} -> 77936 | J34: {=_xll.PrecioBD(ONs_NY_2[[#This Row],[Ticker]],24,"VOLUME AMOUNT","N")} -> 246914.76
B35: Aluar | C35: LMS7D | D35: =LMS7D!K4 -> 0.050792941 | E35: =F35*$H$1 -> 94.75 | F35: {=_xll.PrecioBD(ONs_NY_2[[#This Row],[Ticker]],24,"ASK","N")} -> 94.75 | G35: =LMS7D!K3 -> 1.3354298 | I35: {=_xll.PrecioBD(ONs_NY_2[[#This Row],[Ticker]],24,"QUANTITY ASK","N")} -> 4067 | J35: {=_xll.PrecioBD(ONs_NY_2[[#This Row],[Ticker]],24,"VOLUME AMOUNT","N")} -> 12716.76
B36: YPF | C36: YM41D | D36: =YM41D!K4 -> 0.048438343 | E36: =F36*$H$1 -> 101.6 | F36: {=_xll.PrecioBD(ONs_NY_2[[#This Row],[Ticker]],24,"ASK","N")} -> 101.6 | G36: =YM41D!K3 -> 0.87504753 | I36: {=_xll.PrecioBD(ONs_NY_2[[#This Row],[Ticker]],24,"QUANTITY ASK","N")} -> 332 | J36: {=_xll.PrecioBD(ONs_NY_2[[#This Row],[Ticker]],24,"VOLUME AMOUNT","N")} -> 103708.88
B37: YPF | C37: YM37D | D37: =YM37D!K4 -> 0.052654067 | E37: =F37*$H$1 -> 103.95 | F37: {=_xll.PrecioBD(ONs_NY_2[[#This Row],[Ticker]],24,"ASK","N")} -> 103.95 | G37: =YM37D!K3 -> 1.152466 | I37: {=_xll.PrecioBD(ONs_NY_2[[#This Row],[Ticker]],24,"QUANTITY ASK","N")} -> 2589 | J37: {=_xll.PrecioBD(ONs_NY_2[[#This Row],[Ticker]],24,"VOLUME AMOUNT","N")} -> 133719.9
B38: Camuzzi | C38: ZZC1D | D38: =ZZC1D!K4 -> 0.068279955 | E38: =F38*$H$1 -> 104.9 | F38: {=_xll.PrecioBD(ONs_NY_2[[#This Row],[Ticker]],24,"ASK","N")} -> 104.9 | G38: =ZZC1D!K3 -> 0.95271821 | I38: {=_xll.PrecioBD(ONs_NY_2[[#This Row],[Ticker]],24,"QUANTITY ASK","N")} -> 1000 | J38: {=_xll.PrecioBD(ONs_NY_2[[#This Row],[Ticker]],24,"VOLUME AMOUNT","N")} -> 73732
B39: Tecpetrol | C39: TTCBD | D39: =TTCBD!K4 -> 0.050273177 | E39: =F39*$H$1 -> 104.45 | F39: {=_xll.PrecioBD(ONs_NY_2[[#This Row],[Ticker]],24,"ASK","N")} -> 104.45 | G39: =TTCBD!K3 -> 1.562856 | I39: {=_xll.PrecioBD(ONs_NY_2[[#This Row],[Ticker]],24,"QUANTITY ASK","N")} -> 5000 | J39: {=_xll.PrecioBD(ONs_NY_2[[#This Row],[Ticker]],24,"VOLUME AMOUNT","N")} -> 24870.39
B40: Vista Energy | C40: VSCWD | D40: =VSCWD!K4 -> 0.045735696 | E40: =F40*$H$1 -> 102.1 | F40: {=_xll.PrecioBD(ONs_NY_2[[#This Row],[Ticker]],24,"ASK","N")} -> 102.1 | G40: =VSCWD!K3 -> 1.1223397 | I40: {=_xll.PrecioBD(ONs_NY_2[[#This Row],[Ticker]],24,"QUANTITY ASK","N")} -> 1890 | J40: {=_xll.PrecioBD(ONs_NY_2[[#This Row],[Ticker]],24,"VOLUME AMOUNT","N")} -> 51220.82
B41: Balanz | C41: NBS1D | D41: =NBS1D!K4 -> 0.020760599 | E41: =F41*$H$1 -> 100.95 | F41: {=_xll.PrecioBD(ONs_NY_2[[#This Row],[Ticker]],24,"ASK","N")} -> 100.95 | G41: =NBS1D!K3 -> 0.32926655 | I41: {=_xll.PrecioBD(ONs_NY_2[[#This Row],[Ticker]],24,"QUANTITY ASK","N")} -> 10000 | J41: {=_xll.PrecioBD(ONs_NY_2[[#This Row],[Ticker]],24,"VOLUME AMOUNT","N")} -> 41101.25
B42: Pan American | C42: PN42D | D42: =PN42D!K4 -> 0.045869634 | E42: =F42*$H$1 -> 103.5 | F42: {=_xll.PrecioBD(ONs_NY_2[[#This Row],[Ticker]],24,"ASK","N")} -> 103.5 | G42: =PN42D!K3 -> 1.1261251 | I42: {=_xll.PrecioBD(ONs_NY_2[[#This Row],[Ticker]],24,"QUANTITY ASK","N")} -> 18612 | J42: {=_xll.PrecioBD(ONs_NY_2[[#This Row],[Ticker]],24,"VOLUME AMOUNT","N")} -> 19112.75
B43: IRSA | C43: IRCJD | D43: =IRCJDD!K4 -> 0.048717996 | E43: =F43*$H$1 -> 105.35 | F43: {=_xll.PrecioBD(ONs_NY_2[[#This Row],[Ticker]],24,"ASK","N")} -> 105.35 | G43: =IRCJDD!K3 -> 0.98444249 | I43: {=_xll.PrecioBD(ONs_NY_2[[#This Row],[Ticker]],24,"QUANTITY ASK","N")} -> 1685 | J43: {=_xll.PrecioBD(ONs_NY_2[[#This Row],[Ticker]],24,"VOLUME AMOUNT","N")} -> 6314.06
B44: Pan American | C44: PN38D | D44: =PN38D!K4 -> 0.04195632 | E44: =F44*$H$1 -> 106.6 | F44: {=_xll.PrecioBD(ONs_NY_2[[#This Row],[Ticker]],24,"ASK","N")} -> 106.6 | G44: =PN38D!K3 -> 1.3878073 | I44: {=_xll.PrecioBD(ONs_NY_2[[#This Row],[Ticker]],24,"QUANTITY ASK","N")} -> 3184 | J44: {=_xll.PrecioBD(ONs_NY_2[[#This Row],[Ticker]],24,"VOLUME AMOUNT","N")} -> 350358.34
B45: Arcor | C45: RC2CD | D45: ='RC2CD'!K4 -> 0.040442637 | E45: =F45*$H$1 -> 103.3 | F45: {=_xll.PrecioBD(ONs_NY_2[[#This Row],[Ticker]],24,"ASK","N")} -> 103.3 | G45: ='RC2CD'!K3 -> 0.63322357 | I45: {=_xll.PrecioBD(ONs_NY_2[[#This Row],[Ticker]],24,"QUANTITY ASK","N")} -> 8000 | J45: {=_xll.PrecioBD(ONs_NY_2[[#This Row],[Ticker]],24,"VOLUME AMOUNT","N")} -> 30853.85
B46: Aluar | C46: LMS8D | D46: =LMS8D!K4 -> 0.023767588 | E46: =F46*$H$1 -> 103.75 | F46: {=_xll.PrecioBD(ONs_NY_2[[#This Row],[Ticker]],24,"ASK","N")} -> 103.75 | G46: =LMS8D!K3 -> 0.71878347 | I46: {=_xll.PrecioBD(ONs_NY_2[[#This Row],[Ticker]],24,"QUANTITY ASK","N")} -> 3750 | J46: {=_xll.PrecioBD(ONs_NY_2[[#This Row],[Ticker]],24,"VOLUME AMOUNT","N")} -> 0
B47: YPF | C47: YMCVD | D47: =YMCVO!K4 -> 0.015477309 | E47: =F47*$H$1 -> 102.5 | F47: {=_xll.PrecioBD(ONs_NY_2[[#This Row],[Ticker]],24,"ASK","N")} -> 102.5 | G47: =YMCVO!K3 -> 0.29672036 | I47: {=_xll.PrecioBD(ONs_NY_2[[#This Row],[Ticker]],24,"QUANTITY ASK","N")} -> 1500 | J47: {=_xll.PrecioBD(ONs_NY_2[[#This Row],[Ticker]],24,"VOLUME AMOUNT","N")} -> 17979.76
B48: YPF | C48: YMCVD | D48: =YMCVD!K4 -> 0.015477309 | E48: =F48*$H$1 -> 102.5 | F48: {=_xll.PrecioBD(ONs_NY_2[[#This Row],[Ticker]],24,"ASK","N")} -> 102.5 | G48: =YMCVD!K3 -> 0.29558323 | I48: {=_xll.PrecioBD(ONs_NY_2[[#This Row],[Ticker]],24,"QUANTITY ASK","N")} -> 1500 | J48: {=_xll.PrecioBD(ONs_NY_2[[#This Row],[Ticker]],24,"VOLUME AMOUNT","N")} -> 17979.76
B49: CGC | C49: CP34D | D49: =CP34D!K4 -> -0.32071693 | E49: =F49*$H$1 -> 105.3 | F49: {=_xll.PrecioBD(ONs_NY_2[[#This Row],[Ticker]],24,"ASK","N")} -> 105.3 | G49: =CP34D!K3 -> 0.053186538 | I49: {=_xll.PrecioBD(ONs_NY_2[[#This Row],[Ticker]],24,"QUANTITY ASK","N")} -> 20 | J49: {=_xll.PrecioBD(ONs_NY_2[[#This Row],[Ticker]],24,"VOLUME AMOUNT","N")} -> 954294.23
B50: Loma Negra | C50: LOC3D | D50: =LOC3D!K4 -> -0.17732037 | E50: =F50*$H$1 -> 105.5 | F50: {=_xll.PrecioBD(ONs_NY_2[[#This Row],[Ticker]],24,"ASK","N")} -> 105.5 | G50: =LOC3D!K3 -> 0.096658876 | I50: {=_xll.PrecioBD(ONs_NY_2[[#This Row],[Ticker]],24,"QUANTITY ASK","N")} -> 4300 | J50: {=_xll.PrecioBD(ONs_NY_2[[#This Row],[Ticker]],24,"VOLUME AMOUNT","N")} -> 237011.85
B51: Cresud | C51: CS38D | D51: =CS38D!K4 -> -0.46939723 | E51: =F51*$H$1 -> 105.6 | F51: {=_xll.PrecioBD(ONs_NY_2[[#This Row],[Ticker]],24,"ASK","N")} -> 105.6 | G51: =CS38D!K3 -> 0.090267958 | I51: {=_xll.PrecioBD(ONs_NY_2[[#This Row],[Ticker]],24,"QUANTITY ASK","N")} -> 4613 | J51: {=_xll.PrecioBD(ONs_NY_2[[#This Row],[Ticker]],24,"VOLUME AMOUNT","N")} -> 156699.18
B52: YPF | C52: YMCQD | D52: =YMCQD!K4 -> -0.75371621 | E52: =F52*$H$1 -> 103.2 | F52: {=_xll.PrecioBD(ONs_NY_2[[#This Row],[Ticker]],24,"ASK","N")} -> 103.2 | G52: =YMCQD!K3 -> 0.033123824 | I52: {=_xll.PrecioBD(ONs_NY_2[[#This Row],[Ticker]],24,"QUANTITY ASK","N")} -> 367 | J52: {=_xll.PrecioBD(ONs_NY_2[[#This Row],[Ticker]],24,"VOLUME AMOUNT","N")} -> 1542166.4
C54: PECGD | E54: =F54*$H$1 -> 0 | F54: {=_xll.PrecioBD(ONs_NY_2[[#This Row],[Ticker]],24,"ASK","N")} -> 0 | I54: {=_xll.PrecioBD(ONs_NY_2[[#This Row],[Ticker]],24,"QUANTITY ASK","N")} -> 0 | J54: {=_xll.PrecioBD(ONs_NY_2[[#This Row],[Ticker]],24,"VOLUME AMOUNT","N")} -> 0

Sheet LECAPs
F1: Comisión | G1: 1
F2: Fecha de liquidación | G2: =Main!B1 -> 46060
B4: Ticker | C4: TNA | D4: Precio con comisión | E4: Precio sin comisión | F4: MD | G4: Variación | H4: Bid | I4: Ask | J4: Bid Volume | K4: Ask volume | L4: Total volume | M4: Vto | N4: Periodicidad
B5: T13F6 | C5: =T13F6!J5 -> 0.34392957 | D5: =E5*$G$1 -> 144.155 | E5: {=_xll.PrecioBD(ONs_NY85[[#This Row],[Ticker]],24,"ASK","N")} -> 144.155 | G5: {=_xll.PrecioBD(ONs_NY85[[#This Row],[Ticker]],24,"IMBALANCE","N")} -> 0.0011 | H5: {=_xll.PrecioBD(ONs_NY85[[#This Row],[Ticker]],"24","BID","N")} -> 144.15 | I5: {=_xll.PrecioBD(ONs_NY85[[#This Row],[Ticker]],"24","ASK","N")} -> 144.155 | J5: {=_xll.PrecioBD(ONs_NY85[[#This Row],[Ticker]],24,"QUANTITY BID","N")} -> 133127526 | K5: {=_xll.PrecioBD(ONs_NY85[[#This Row],[Ticker]],24,"QUANTITY ASK","N")} -> 997412056 | L5: {=_xll.PrecioBD(ONs_NY85[[#This Row],[Ticker]],24,"VOLUME AMOUNT","N")} -> 1.1830758e+11
B6: S27F6 | D6: =E6*$G$1 -> 123.6 | E6: {=_xll.PrecioBD(ONs_NY85[[#This Row],[Ticker]],24,"ASK","N")} -> 123.6 | G6: {=_xll.PrecioBD(ONs_NY85[[#This Row],[Ticker]],24,"IMBALANCE","N")} -> 0.0007 | H6: {=_xll.PrecioBD(ONs_NY85[[#This Row],[Ticker]],"24","BID","N")} -> 123.58 | I6: {=_xll.PrecioBD(ONs_NY85[[#This Row],[Ticker]],"24","ASK","N")} -> 123.6 | J6: {=_xll.PrecioBD(ONs_NY85[[#This Row],[Ticker]],24,"QUANTITY BID","N")} -> 34468142 | K6: {=_xll.PrecioBD(ONs_NY85[[#This Row],[Ticker]],24,"QUANTITY ASK","N")} -> 149397556 | L6: {=_xll.PrecioBD(ONs_NY85[[#This Row],[Ticker]],24,"VOLUME AMOUNT","N")} -> 4.2175246e+10
B7: S16M6 | D7: =E7*$G$1 -> 101.03 | E7: {=_xll.PrecioBD(ONs_NY85[[#This Row],[Ticker]],24,"ASK","N")} -> 101.03 | G7: {=_xll.PrecioBD(ONs_NY85[[#This Row],[Ticker]],24,"IMBALANCE","N")} -> 0.001 | H7: {=_xll.PrecioBD(ONs_NY85[[#This Row],[Ticker]],"24","BID","N")} -> 101.02 | I7: {=_xll.PrecioBD(ONs_NY85[[#This Row],[Ticker]],"24","ASK","N")} -> 101.03 | J7: {=_xll.PrecioBD(ONs_NY85[[#This Row],[Ticker]],24,"QUANTITY BID","N")} -> 1399951 | K7: {=_xll.PrecioBD(ONs_NY85[[#This Row],[Ticker]],24,"QUANTITY ASK","N")} -> 515051568 | L7: {=_xll.PrecioBD(ONs_NY85[[#This Row],[Ticker]],24,"VOLUME AMOUNT","N")} -> 1.8384293e+11
B8: S17A6 | D8: =E8*$G$1 -> 103.34 | E8: {=_xll.PrecioBD(ONs_NY85[[#This Row],[Ticker]],24,"ASK","N")} -> 103.34 | G8: {=_xll.PrecioBD(ONs_NY85[[#This Row],[Ticker]],24,"IMBALANCE","N")} -> 0.0008 | H8: {=_xll.PrecioBD(ONs_NY85[[#This Row],[Ticker]],"24","BID","N")} -> 103.29 | I8: {=_xll.PrecioBD(ONs_NY85[[#This Row],[Ticker]],"24","ASK","N")} -> 103.34 | J8: {=_xll.PrecioBD(ONs_NY85[[#This Row],[Ticker]],24,"QUANTITY BID","N")} -> 125000 | K8: {=_xll.PrecioBD(ONs_NY85[[#This Row],[Ticker]],24,"QUANTITY ASK","N")} -> 462153654 | L8: {=_xll.PrecioBD(ONs_NY85[[#This Row],[Ticker]],24,"VOLUME AMOUNT","N")} -> 2.2479222e+10
B9: S30A6 | D9: =E9*$G$1 -> 118.5 | E9: {=_xll.PrecioBD(ONs_NY85[[#This Row],[Ticker]],24,"ASK","N")} -> 118.5 | G9: {=_xll.PrecioBD(ONs_NY85[[#This Row],[Ticker]],24,"IMBALANCE","N")} -> -0.0008 | H9: {=_xll.PrecioBD(ONs_NY85[[#This Row],[Ticker]],"24","BID","N")} -> 118.472 | I9: {=_xll.PrecioBD(ONs_NY85[[#This Row],[Ticker]],"24","ASK","N")} -> 118.5 | J9: {=_xll.PrecioBD(ONs_NY85[[#This Row],[Ticker]],24,"QUANTITY BID","N")} -> 1690481 | K9: {=_xll.PrecioBD(ONs_NY85[[#This Row],[Ticker]],24,"QUANTITY ASK","N")} -> 3859 | L9: {=_xll.PrecioBD(ONs_NY85[[#This Row],[Ticker]],24,"VOLUME AMOUNT","N")} -> 7.3396999e+09
B10: S29Y6 | D10: =E10*$G$1 -> 119.55 | E10: {=_xll.PrecioBD(ONs_NY85[[#This Row],[Ticker]],24,"ASK","N")} -> 119.55 | G10: {=_xll.PrecioBD(ONs_NY85[[#This Row],[Ticker]],24,"IMBALANCE","N")} -> -0.0016 | H10: {=_xll.PrecioBD(ONs_NY85[[#This Row],[Ticker]],"24","BID","N")} -> 119.525 | I10: {=_xll.PrecioBD(ONs_NY85[[#This Row],[Ticker]],"24","ASK","N")} -> 119.55 | J10: {=_xll.PrecioBD(ONs_NY85[[#This Row],[Ticker]],24,"QUANTITY BID","N")} -> 3988100 | K10: {=_xll.PrecioBD(ONs_NY85[[#This Row],[Ticker]],24,"QUANTITY ASK","N")} -> 20427297 | L10: {=_xll.PrecioBD(ONs_NY85[[#This Row],[Ticker]],24,"VOLUME AMOUNT","N")} -> 7.3082688e+09
B11: T30J6 | D11: =E11*$G$1 -> 127.65 | E11: {=_xll.PrecioBD(ONs_NY85[[#This Row],[Ticker]],24,"ASK","N")} -> 127.65 | G11: {=_xll.PrecioBD(ONs_NY85[[#This Row],[Ticker]],24,"IMBALANCE","N")} -> -0.0035 | H11: {=_xll.PrecioBD(ONs_NY85[[#This Row],[Ticker]],"24","BID","N")} -> 127.25 | I11: {=_xll.PrecioBD(ONs_NY85[[#This Row],[Ticker]],"24","ASK","N")} -> 127.65 | J11: {=_xll.PrecioBD(ONs_NY85[[#This Row],[Ticker]],24,"QUANTITY BID","N")} -> 19441749 | K11: {=_xll.PrecioBD(ONs_NY85[[#This Row],[Ticker]],24,"QUANTITY ASK","N")} -> 500000000 | L11: {=_xll.PrecioBD(ONs_NY85[[#This Row],[Ticker]],24,"VOLUME AMOUNT","N")} -> 1.3854246e+10
B12: S31L6 | D12: =E12*$G$1 -> 100.6 | E12: {=_xll.PrecioBD(ONs_NY85[[#This Row],[Ticker]],24,"ASK","N")} -> 100.6 | G12: {=_xll.PrecioBD(ONs_NY85[[#This Row],[Ticker]],24,"IMBALANCE","N")} -> -0.0008 | H12: {=_xll.PrecioBD(ONs_NY85[[#This Row],[Ticker]],"24","BID","N")} -> 100.58 | I12: {=_xll.PrecioBD(ONs_NY85[[#This Row],[Ticker]],"24","ASK","N")} -> 100.6 | J12: {=_xll.PrecioBD(ONs_NY85[[#This Row],[Ticker]],24,"QUANTITY BID","N")} -> 19500000 | K12: {=_xll.PrecioBD(ONs_NY85[[#This Row],[Ticker]],24,"QUANTITY ASK","N")} -> 15000000 | L12: {=_xll.PrecioBD(ONs_NY85[[#This Row],[Ticker]],24,"VOLUME AMOUNT","N")} -> 1.1662344e+10
B13: S31G6 | D13: =E13*$G$1 -> 106.15 | E13: {=_xll.PrecioBD(ONs_NY85[[#This Row],[Ticker]],24,"ASK","N")} -> 106.15 | G13: {=_xll.PrecioBD(ONs_NY85[[#This Row],[Ticker]],24,"IMBALANCE","N")} -> 0.0028 | H13: {=_xll.PrecioBD(ONs_NY85[[#This Row],[Ticker]],"24","BID","N")} -> 106.044 | I13: {=_xll.PrecioBD(ONs_NY85[[#This Row],[Ticker]],"24","ASK","N")} -> 106.15 | J13: {=_xll.PrecioBD(ONs_NY85[[#This Row],[Ticker]],24,"QUANTITY BID","N")} -> 469900 | K13: {=_xll.PrecioBD(ONs_NY85[[#This Row],[Ticker]],24,"QUANTITY ASK","N")} -> 6147333 | L13: {=_xll.PrecioBD(ONs_NY85[[#This Row],[Ticker]],24,"VOLUME AMOUNT","N")} -> 2.3128085e+09
B14: S30O6 | D14: =E14*$G$1 -> 107.9 | E14: {=_xll.PrecioBD(ONs_NY85[[#This Row],[Ticker]],24,"ASK","N")} -> 107.9 | G14: {=_xll.PrecioBD(ONs_NY85[[#This Row],[Ticker]],24,"IMBALANCE","N")} -> -0.0023 | H14: {=_xll.PrecioBD(ONs_NY85[[#This Row],[Ticker]],"24","BID","N")} -> 107.899 | I14: {=_xll.PrecioBD(ONs_NY85[[#This Row],[Ticker]],"24","ASK","N")} -> 107.9 | J14: {=_xll.PrecioBD(ONs_NY85[[#This Row],[Ticker]],24,"QUANTITY BID","N")} -> 200000 | K14: {=_xll.PrecioBD(ONs_NY85[[#This Row],[Ticker]],24,"QUANTITY ASK","N")} -> 382854102 | L14: {=_xll.PrecioBD(ONs_NY85[[#This Row],[Ticker]],24,"VOLUME AMOUNT","N")} -> 75495755
B15: S30N6 | D15: =E15*$G$1 -> 101 | E15: {=_xll.PrecioBD(ONs_NY85[[#This Row],[Ticker]],24,"ASK","N")} -> 101 | G15: {=_xll.PrecioBD(ONs_NY85[[#This Row],[Ticker]],24,"IMBALANCE","N")} -> 0 | H15: {=_xll.PrecioBD(ONs_NY85[[#This Row],[Ticker]],"24","BID","N")} -> 100.9 | I15: {=_xll.PrecioBD(ONs_NY85[[#This Row],[Ticker]],"24","ASK","N")} -> 101 | J15: {=_xll.PrecioBD(ONs_NY85[[#This Row],[Ticker]],24,"QUANTITY BID","N")} -> 1982160 | K15: {=_xll.PrecioBD(ONs_NY85[[#This Row],[Ticker]],24,"QUANTITY ASK","N")} -> 49000312 | L15: {=_xll.PrecioBD(ONs_NY85[[#This Row],[Ticker]],24,"VOLUME AMOUNT","N")} -> 1.5266531e+08
B16: T15E7 | D16: =E16*$G$1 -> 120.3 | E16: {=_xll.PrecioBD(ONs_NY85[[#This Row],[Ticker]],24,"ASK","N")} -> 120.3 | G16: {=_xll.PrecioBD(ONs_NY85[[#This Row],[Ticker]],24,"IMBALANCE","N")} -> -0.0053 | H16: {=_xll.PrecioBD(ONs_NY85[[#This Row],[Ticker]],"24","BID","N")} -> 120.1 | I16: {=_xll.PrecioBD(ONs_NY85[[#This Row],[Ticker]],"24","ASK","N")} -> 120.3 | J16: {=_xll.PrecioBD(ONs_NY85[[#This Row],[Ticker]],24,"QUANTITY BID","N")} -> 195043979 | K16: {=_xll.PrecioBD(ONs_NY85[[#This Row],[Ticker]],24,"QUANTITY ASK","N")} -> 19364065 | L16: {=_xll.PrecioBD(ONs_NY85[[#This Row],[Ticker]],24,"VOLUME AMOUNT","N")} -> 1.1822626e+10
B17: T30A7 | D17: =E17*$G$1 -> 108.3 | E17: {=_xll.PrecioBD(ONs_NY85[[#This Row],[Ticker]],24,"ASK","N")} -> 108.3 | G17: {=_xll.PrecioBD(ONs_NY85[[#This Row],[Ticker]],24,"IMBALANCE","N")} -> -0.0041 | H17: {=_xll.PrecioBD(ONs_NY85[[#This Row],[Ticker]],"24","BID","N")} -> 108.2 | I17: {=_xll.PrecioBD(ONs_NY85[[#This Row],[Ticker]],"24","ASK","N")} -> 108.3 | J17: {=_xll.PrecioBD(ONs_NY85[[#This Row],[Ticker]],24,"QUANTITY BID","N")} -> 100000000 | K17: {=_xll.PrecioBD(ONs_NY85[[#This Row],[Ticker]],24,"QUANTITY ASK","N")} -> 17698974 | L17: {=_xll.PrecioBD(ONs_NY85[[#This Row],[Ticker]],24,"VOLUME AMOUNT","N")} -> 2.4917589e+10
... B20: TY30P | D20: =E20*$G$1 -> 116.6 | E20: {=_xll.PrecioBD(ONs_NY85[[#This Row],[Ticker]],24,"ASK","N")} -> 116.6 | G20: {=_xll.PrecioBD(ONs_NY85[[#This Row],[Ticker]],24,"IMBALANCE","N")} -> -0.0008 | H20: {=_xll.PrecioBD(ONs_NY85[[#This Row],[Ticker]],"24","BID","N")} -> 116.4 | I20: {=_xll.PrecioBD(ONs_NY85[[#This Row],[Ticker]],"24","ASK","N")} -> 116.6 | J20: {=_xll.PrecioBD(ONs_NY85[[#This Row],[Ticker]],24,"QUANTITY BID","N")} -> 14603426 | K20: {=_xll.PrecioBD(ONs_NY85[[#This Row],[Ticker]],24,"QUANTITY ASK","N")} -> 144790 | L20: {=_xll.PrecioBD(ONs_NY85[[#This Row],[Ticker]],24,"VOLUME AMOUNT","N")} -> 1.2828696e+09

Sheet T13F6
A1: T13F6 | B1: Fecha de Pago | C1: Interés | D1: Amortización | E1: Total
B2: ='ONS NY'!H2 -> 46060 | E2: =VLOOKUP(A1,ONs_NY85[[Ticker]:[Variación]],3,FALSE) -> 144.155 | J2: Periodo de intereses | K2: 0.5
A3: 1 | B3: 46066 | C3: 44.97 | D3: 100 | E3: =IF(B3<=$B$2,0,(C3+D3)) -> 144.97 | F3: =(E3*(B3-$B$2)/365)/(1+#REF!)^((B3-$B$2)/365)/-$E$2/(1+#REF!)^$K$2 -> #REF! | J3: MDUR | K3: =SUM(F3:F102) -> #REF!
J4: =+(1+(E3/E2-1))^(365/(B3-B2))-1 -> 0.40911379 | K4: TIR
J5: =+(E3/E2-1)/(B3-B2)*365 -> 0.34392957 | K5: TNA
J6: =+(1+J4)^(1/12)-1 -> 0.028992412 | K6: TEM

Sheet GD41D
A1: GD41D | B1: Fecha de Pago | C1: Interés | D1: Amortización | E1: Total
B2: ='ONS NY'!H2 -> 46060 | E2: =-VLOOKUP(A1,'Soberanos HD'!$B$5:$Q$14,3,0) -> -74.28 | J2: Periodo de intereses | K2: 0.5
A3: 11 | B3: 46213 | C3: 1.76 | D3: 0 | E3: =IF(B3<=$B$2,0,(C3+D3)) -> 1.76 | F3: =(E3*(B3-$B$2)/365)/(1+$K$4)^((B3-$B$2)/365)/-$E$2/(1+$K$4)^$K$2 -> 0.0093558647 | J3: MDUR | K3: =SUM(F3:F102) -> 7.6189885
A4: 12 | B4: 46398 | C4: 1.76 | D4: 0 | E4: =IF(B4<=$B$2,0,(C4+D4)) -> 1.76 | F4: =(E4*(B4-$B$2)/365)/(1+$K$4)^((B4-$B$2)/365)/-$E$2/(1+$K$4)^$K$2 -> 0.01999848 | J4: TIR | K4: =XIRR(E2:E26,B2:B26) -> 0.067179868
A5: 13 | B5: 46580 | C5: 1.76 | D5: 0 | E5: =IF(B5<=$B$2,0,(C5+D5)) -> 1.76 | F5: =(E5*(B5-$B$2)/365)/(1+$K$4)^((B5-$B$2)/365)/-$E$2/(1+$K$4)^$K$2 -> 0.029785404
A6: 14 | B6: 46762 | C6: 1.73 | D6: 3.57 | E6: =IF(B6<=$B$2,0,(C6+D6)) -> 5.3 | F6: =(E6*(B6-$B$2)/365)/(1+$K$4)^((B6-$B$2)/365)/-$E$2/(1+$K$4)^$K$2 -> 0.11722503
A7: 15 | B7: 46944 | C7: 1.69 | D7: 3.57 | E7: =IF(B7<=$B$2,0,(C7+D7)) -> 5.26 | F7: =(E7*(B7-$B$2)/365)/(1+$K$4)^((B7-$B$2)/365)/-$E$2/(1+$K$4)^$K$2 -> 0.14182906
A8: 16 | B8: 47127 | C8: 1.62 | D8: 3.57 | E8: =IF(B8<=$B$2,0,(C8+D8)) -> 5.19 | F8: =(E8*(B8-$B$2)/365)/(1+$K$4)^((B8-$B$2)/365)/-$E$2/(1+$K$4)^$K$2 -> 0.16349388
A9: 17 | B9: 47309 | C9: 1.57 | D9: 3.57 | E9: =IF(B9<=$B$2,0,(C9+D9)) -> 5.14 | F9: =(E9*(B9-$B$2)/365)/(1+$K$4)^((B9-$B$2)/365)/-$E$2/(1+$K$4)^$K$2 -> 0.18349117
A10: 18 | B10: 47492 | C10: 2.08 | D10: 3.57 | E10: =IF(B10<=$B$2,0,(C10+D10)) -> 5.65 | F10: =(E10*(B10-$B$2)/365)/(1+$K$4)^((B10-$B$2)/365)/-$E$2/(1+$K$4)^$K$2 -> 0.22383272
A11: 19 | B11: 47674 | C11: 2.01 | D11: 3.57 | E11: =IF(B11<=$B$2,0,(C11+D11)) -> 5.58 | F11: =(E11*(B11-$B$2)/365)/(1+$K$4)^((B11-$B$2)/365)/-$E$2/(1+$K$4)^$K$2 -> 0.24120689
A12: 20 | B12: 47857 | C12: 1.9 | D12: 3.57 | E12: =IF(B12<=$B$2,0,(C12+D12)) -> 5.47 | F12: =(E12*(B12-$B$2)/365)/(1+$K$4)^((B12-$B$2)/365)/-$E$2/(1+$K$4)^$K$2 -> 0.25481787
A13: 21 | B13: 48039 | C13: 1.84 | D13: 3.57 | E13: =IF(B13<=$B$2,0,(C13+D13)) -> 5.41 | F13: =(E13*(B13-$B$2)/365)/(1+$K$4)^((B13-$B$2)/365)/-$E$2/(1+$K$4)^$K$2 -> 0.26869366
A14: 22 | B14: 48222 | C14: 1.73 | D14: 3.57 | E14: =IF(B14<=$B$2,0,(C14+D14)) -> 5.3 | F14: =(E14*(B14-$B$2)/365)/(1+$K$4)^((B14-$B$2)/365)/-$E$2/(1+$K$4)^$K$2 -> 0.2783482
A15: 23 | B15: 48407 | C15: 1.68 | D15: 3.57 | E15: =IF(B15<=$B$2,0,(C15+D15)) -> 5.25 | F15: =(E15*(B15-$B$2)/365)/(1+$K$4)^((B15-$B$2)/365)/-$E$2/(1+$K$4)^$K$2 -> 0.28961232
A16: 24 | B16: 48589 | C16: 1.55 | D16: 3.57 | E16: =IF(B16<=$B$2,0,(C16+D16)) -> 5.12 | F16: =(E16*(B16-$B$2)/365)/(1+$K$4)^((B16-$B$2)/365)/-$E$2/(1+$K$4)^$K$2 -> 0.2946343
... A33: 41 | B33: 51692 | C33: 0.09 | D33: 3.61 | E33: =IF(B33<=$B$2,0,(C33+D33)) -> 3.7 | F33: =(E33*(B33-$B$2)/365)/(1+$K$4)^((B33-$B$2)/365)/-$E$2/(1+$K$4)^$K$2 -> 0.27281635

Sheet AL41D
A1: AL41D | B1: Fecha de Pago | C1: Interés | D1: Amortización | E1: Total
B2: ='ONS NY'!H2 -> 46060 | E2: =-VLOOKUP(A1,'Soberanos HD'!$B$5:$Q$14,3,0) -> -73.35 | J2: Periodo de intereses | K2: 0.5
A3: 11 | B3: 46213 | C3: 1.76 | D3: 0 | E3: =IF(B3<=$B$2,0,(C3+D3)) -> 1.76 | F3: =(E3*(B3-$B$2)/365)/(1+$K$4)^((B3-$B$2)/365)/-$E$2/(1+$K$4)^$K$2 -> 0.0094555347 | J3: MDUR | K3: =SUM(F3:F102) -> 7.5551069
A4: 12 | B4: 46398 | C4: 1.76 | D4: 0 | E4: =IF(B4<=$B$2,0,(C4+D4)) -> 1.76 | F4: =(E4*(B4-$B$2)/365)/(1+$K$4)^((B4-$B$2)/365)/-$E$2/(1+$K$4)^$K$2 -> 0.020189224 | J4: TIR | K4: =XIRR(E2:E26,B2:B26) -> 0.069507185
A5: 13 | B5: 46580 | C5: 1.76 | D5: 0 | E5: =IF(B5<=$B$2,0,(C5+D5)) -> 1.76 | F5: =(E5*(B5-$B$2)/365)/(1+$K$4)^((B5-$B$2)/365)/-$E$2/(1+$K$4)^$K$2 -> 0.03003685
A6: 14 | B6: 46762 | C6: 1.73 | D6: 3.57 | E6: =IF(B6<=$B$2,0,(C6+D6)) -> 5.3 | F6: =(E6*(B6-$B$2)/365)/(1+$K$4)^((B6-$B$2)/365)/-$E$2/(1+$K$4)^$K$2 -> 0.11808629
A7: 15 | B7: 46944 | C7: 1.69 | D7: 3.57 | E7: =IF(B7<=$B$2,0,(C7+D7)) -> 5.26 | F7: =(E7*(B7-$B$2)/365)/(1+$K$4)^((B7-$B$2)/365)/-$E$2/(1+$K$4)^$K$2 -> 0.14271599
A8: 16 | B8: 47127 | C8: 1.62 | D8: 3.57 | E8: =IF(B8<=$B$2,0,(C8+D8)) -> 5.19 | F8: =(E8*(B8-$B$2)/365)/(1+$K$4)^((B8-$B$2)/365)/-$E$2/(1+$K$4)^$K$2 -> 0.1643367
A9: 17 | B9: 47309 | C9: 1.57 | D9: 3.57 | E9: =IF(B9<=$B$2,0,(C9+D9)) -> 5.14 | F9: =(E9*(B9-$B$2)/365)/(1+$K$4)^((B9-$B$2)/365)/-$E$2/(1+$K$4)^$K$2 -> 0.18423684
A10: 18 | B10: 47492 | C10: 2.08 | D10: 3.57 | E10: =IF(B10<=$B$2,0,(C10+D10)) -> 5.65 | F10: =(E10*(B10-$B$2)/365)/(1+$K$4)^((B10-$B$2)/365)/-$E$2/(1+$K$4)^$K$2 -> 0.22449701
A11: 19 | B11: 47674 | C11: 2.01 | D11: 3.57 | E11: =IF(B11<=$B$2,0,(C11+D11)) -> 5.58 | F11: =(E11*(B11-$B$2)/365)/(1+$K$4)^((B11-$B$2)/365)/-$E$2/(1+$K$4)^$K$2 -> 0.2416601
A12: 20 | B12: 47857 | C12: 1.9 | D12: 3.57 | E12: =IF(B12<=$B$2,0,(C12+D12)) -> 5.47 | F12: =(E12*(B12-$B$2)/365)/(1+$K$4)^((B12-$B$2)/365)/-$E$2/(1+$K$4)^$K$2 -> 0.25501797
A13: 21 | B13: 48039 | C13: 1.84 | D13: 3.57 | E13: =IF(B13<=$B$2,0,(C13+D13)) -> 5.41 | F13: =(E13*(B13-$B$2)/365)/(1+$K$4)^((B13-$B$2)/365)/-$E$2/(1+$K$4)^$K$2 -> 0.26861271
A14: 22 | B14: 48222 | C14: 1.73 | D14: 3.57 | E14: =IF(B14<=$B$2,0,(C14+D14)) -> 5.3 | F14: =(E14*(B14-$B$2)/365)/(1+$K$4)^((B14-$B$2)/365)/-$E$2/(1+$K$4)^$K$2 -> 0.2779606
A15: 23 | B15: 48407 | C15: 1.68 | D15: 3.57 | E15: =IF(B15<=$B$2,0,(C15+D15)) -> 5.25 | F15: =(E15*(B15-$B$2)/365)/(1+$K$4)^((B15-$B$2)/365)/-$E$2/(1+$K$4)^$K$2 -> 0.28888988
A16: 24 | B16: 48589 | C16: 1.55 | D16: 3.57 | E16: =IF(B16<=$B$2,0,(C16+D16)) -> 5.12 | F16: =(E16*(B16-$B$2)/365)/(1+$K$4)^((B16-$B$2)/365)/-$E$2/(1+$K$4)^$K$2 -> 0.29358026
... A33: 41 | B33: 51692 | C33: 0.09 | D33: 3.61 | E33: =IF(B33<=$B$2,0,(C33+D33)) -> 3.7 | F33: =(E33*(B33-$B$2)/365)/(1+$K$4)^((B33-$B$2)/365)/-$E$2/(1+$K$4)^$K$2 -> 0.2668523

Sheet GD38D
A1: GD38D | B1: Fecha de Pago | C1: Interés | D1: Amortización | E1: Total
B2: ='ONS NY'!H2 -> 46060 | E2: =-VLOOKUP(A1,'Soberanos HD'!$B$5:$Q$14,3,0) -> -82.86 | J2: Periodo de intereses | K2: 0.5
A3: 11 | B3: 46213 | C3: 2.51 | D3: 0 | E3: =IF(B3<=$B$2,0,(C3+D3)) -> 2.51 | F3: =(E3*(B3-$B$2)/365)/(1+$K$4)^((B3-$B$2)/365)/-$E$2/(1+$K$4)^$K$2 -> 0.011742843 | J3: MDUR | K3: =SUM(F3:F102) -> 4.9813448
A4: 12 | B4: 46398 | C4: 2.51 | D4: 0 | E4: =IF(B4<=$B$2,0,(C4+D4)) -> 2.51 | F4: =(E4*(B4-$B$2)/365)/(1+$K$4)^((B4-$B$2)/365)/-$E$2/(1+$K$4)^$K$2 -> 0.0248471 | J4: TIR | K4: =XIRR(E2:E26,B2:B26) -> 0.088778743
A5: 13 | B5: 46580 | C5: 2.51 | D5: 4.54 | E5: =IF(B5<=$B$2,0,(C5+D5)) -> 7.05 | F5: =(E5*(B5-$B$2)/365)/(1+$K$4)^((B5-$B$2)/365)/-$E$2/(1+$K$4)^$K$2 -> 0.10291022
A6: 14 | B6: 46762 | C6: 2.36 | D6: 4.54 | E6: =IF(B6<=$B$2,0,(C6+D6)) -> 6.9 | F6: =(E6*(B6-$B$2)/365)/(1+$K$4)^((B6-$B$2)/365)/-$E$2/(1+$K$4)^$K$2 -> 0.1303266
A7: 15 | B7: 46944 | C7: 2.27 | D7: 4.54 | E7: =IF(B7<=$B$2,0,(C7+D7)) -> 6.81 | F7: =(E7*(B7-$B$2)/365)/(1+$K$4)^((B7-$B$2)/365)/-$E$2/(1+$K$4)^$K$2 -> 0.15524836
A8: 16 | B8: 47127 | C8: 2.15 | D8: 4.54 | E8: =IF(B8<=$B$2,0,(C8+D8)) -> 6.69 | F8: =(E8*(B8-$B$2)/365)/(1+$K$4)^((B8-$B$2)/365)/-$E$2/(1+$K$4)^$K$2 -> 0.17639966
A9: 17 | B9: 47309 | C9: 2.06 | D9: 4.54 | E9: =IF(B9<=$B$2,0,(C9+D9)) -> 6.6 | F9: =(E9*(B9-$B$2)/365)/(1+$K$4)^((B9-$B$2)/365)/-$E$2/(1+$K$4)^$K$2 -> 0.1952515
A10: 18 | B10: 47492 | C10: 1.92 | D10: 4.54 | E10: =IF(B10<=$B$2,0,(C10+D10)) -> 6.46 | F10: =(E10*(B10-$B$2)/365)/(1+$K$4)^((B10-$B$2)/365)/-$E$2/(1+$K$4)^$K$2 -> 0.20996317
A11: 19 | B11: 47674 | C11: 1.83 | D11: 4.54 | E11: =IF(B11<=$B$2,0,(C11+D11)) -> 6.37 | F11: =(E11*(B11-$B$2)/365)/(1+$K$4)^((B11-$B$2)/365)/-$E$2/(1+$K$4)^$K$2 -> 0.22366155
A12: 20 | B12: 47857 | C12: 1.7 | D12: 4.54 | E12: =IF(B12<=$B$2,0,(C12+D12)) -> 6.24 | F12: =(E12*(B12-$B$2)/365)/(1+$K$4)^((B12-$B$2)/365)/-$E$2/(1+$K$4)^$K$2 -> 0.23375484
A13: 21 | B13: 48039 | C13: 1.6 | D13: 4.54 | E13: =IF(B13<=$B$2,0,(C13+D13)) -> 6.14 | F13: =(E13*(B13-$B$2)/365)/(1+$K$4)^((B13-$B$2)/365)/-$E$2/(1+$K$4)^$K$2 -> 0.24278559
A14: 22 | B14: 48222 | C14: 1.47 | D14: 4.54 | E14: =IF(B14<=$B$2,0,(C14+D14)) -> 6.01 | F14: =(E14*(B14-$B$2)/365)/(1+$K$4)^((B14-$B$2)/365)/-$E$2/(1+$K$4)^$K$2 -> 0.24878173
A15: 23 | B15: 48407 | C15: 1.39 | D15: 4.54 | E15: =IF(B15<=$B$2,0,(C15+D15)) -> 5.93 | F15: =(E15*(B15-$B$2)/365)/(1+$K$4)^((B15-$B$2)/365)/-$E$2/(1+$K$4)^$K$2 -> 0.25523091
A16: 24 | B16: 48589 | C16: 1.24 | D16: 4.54 | E16: =IF(B16<=$B$2,0,(C16+D16)) -> 5.78 | F16: =(E16*(B16-$B$2)/365)/(1+$K$4)^((B16-$B$2)/365)/-$E$2/(1+$K$4)^$K$2 -> 0.25693481
... A26: 34 | B26: 50416 | C26: 0.12 | D26: 4.66 | E26: =IF(B26<=$B$2,0,(C26+D26)) -> 4.78 | F26: =(E26*(B26-$B$2)/365)/(1+$K$4)^((B26-$B$2)/365)/-$E$2/(1+$K$4)^$K$2 -> 0.23909003

Sheet AE38D
A1: AE38D | B1: Fecha de Pago | C1: Interés | D1: Amortización | E1: Total
B2: ='ONS NY'!H2 -> 46060 | E2: =-VLOOKUP(A1,'Soberanos HD'!$B$5:$Q$14,3,0) -> -80.05 | J2: Periodo de intereses | K2: 0.5
A3: 11 | B3: 46213 | C3: 2.51 | D3: 0 | E3: =IF(B3<=$B$2,0,(C3+D3)) -> 2.51 | F3: =(E3*(B3-$B$2)/365)/(1+$K$4)^((B3-$B$2)/365)/-$E$2/(1+$K$4)^$K$2 -> 0.012080648 | J3: MDUR | K3: =SUM(F3:F102) -> 4.9019119
A4: 12 | B4: 46398 | C4: 2.51 | D4: 0 | E4: =IF(B4<=$B$2,0,(C4+D4)) -> 2.51 | F4: =(E4*(B4-$B$2)/365)/(1+$K$4)^((B4-$B$2)/365)/-$E$2/(1+$K$4)^$K$2 -> 0.025475474 | J4: TIR | K4: =XIRR(E2:E26,B2:B26) -> 0.096076125
A5: 13 | B5: 46580 | C5: 2.51 | D5: 4.54 | E5: =IF(B5<=$B$2,0,(C5+D5)) -> 7.05 | F5: =(E5*(B5-$B$2)/365)/(1+$K$4)^((B5-$B$2)/365)/-$E$2/(1+$K$4)^$K$2 -> 0.10516192
A6: 14 | B6: 46762 | C6: 2.36 | D6: 4.54 | E6: =IF(B6<=$B$2,0,(C6+D6)) -> 6.9 | F6: =(E6*(B6-$B$2)/365)/(1+$K$4)^((B6-$B$2)/365)/-$E$2/(1+$K$4)^$K$2 -> 0.13273531
A7: 15 | B7: 46944 | C7: 2.27 | D7: 4.54 | E7: =IF(B7<=$B$2,0,(C7+D7)) -> 6.81 | F7: =(E7*(B7-$B$2)/365)/(1+$K$4)^((B7-$B$2)/365)/-$E$2/(1+$K$4)^$K$2 -> 0.15759189
A8: 16 | B8: 47127 | C8: 2.15 | D8: 4.54 | E8: =IF(B8<=$B$2,0,(C8+D8)) -> 6.69 | F8: =(E8*(B8-$B$2)/365)/(1+$K$4)^((B8-$B$2)/365)/-$E$2/(1+$K$4)^$K$2 -> 0.17846378
A9: 17 | B9: 47309 | C9: 2.06 | D9: 4.54 | E9: =IF(B9<=$B$2,0,(C9+D9)) -> 6.6 | F9: =(E9*(B9-$B$2)/365)/(1+$K$4)^((B9-$B$2)/365)/-$E$2/(1+$K$4)^$K$2 -> 0.19687934
A10: 18 | B10: 47492 | C10: 1.92 | D10: 4.54 | E10: =IF(B10<=$B$2,0,(C10+D10)) -> 6.46 | F10: =(E10*(B10-$B$2)/365)/(1+$K$4)^((B10-$B$2)/365)/-$E$2/(1+$K$4)^$K$2 -> 0.21100579
A11: 19 | B11: 47674 | C11: 1.83 | D11: 4.54 | E11: =IF(B11<=$B$2,0,(C11+D11)) -> 6.37 | F11: =(E11*(B11-$B$2)/365)/(1+$K$4)^((B11-$B$2)/365)/-$E$2/(1+$K$4)^$K$2 -> 0.22402476
A12: 20 | B12: 47857 | C12: 1.7 | D12: 4.54 | E12: =IF(B12<=$B$2,0,(C12+D12)) -> 6.24 | F12: =(E12*(B12-$B$2)/365)/(1+$K$4)^((B12-$B$2)/365)/-$E$2/(1+$K$4)^$K$2 -> 0.2333516
A13: 21 | B13: 48039 | C13: 1.6 | D13: 4.54 | E13: =IF(B13<=$B$2,0,(C13+D13)) -> 6.14 | F13: =(E13*(B13-$B$2)/365)/(1+$K$4)^((B13-$B$2)/365)/-$E$2/(1+$K$4)^$K$2 -> 0.24156083
A14: 22 | B14: 48222 | C14: 1.47 | D14: 4.54 | E14: =IF(B14<=$B$2,0,(C14+D14)) -> 6.01 | F14: =(E14*(B14-$B$2)/365)/(1+$K$4)^((B14-$B$2)/365)/-$E$2/(1+$K$4)^$K$2 -> 0.2466991
A15: 23 | B15: 48407 | C15: 1.39 | D15: 4.54 | E15: =IF(B15<=$B$2,0,(C15+D15)) -> 5.93 | F15: =(E15*(B15-$B$2)/365)/(1+$K$4)^((B15-$B$2)/365)/-$E$2/(1+$K$4)^$K$2 -> 0.25223883
A16: 24 | B16: 48589 | C16: 1.24 | D16: 4.54 | E16: =IF(B16<=$B$2,0,(C16+D16)) -> 5.78 | F16: =(E16*(B16-$B$2)/365)/(1+$K$4)^((B16-$B$2)/365)/-$E$2/(1+$K$4)^$K$2 -> 0.25307838
... A26: 34 | B26: 50416 | C26: 0.12 | D26: 4.66 | E26: =IF(B26<=$B$2,0,(C26+D26)) -> 4.78 | F26: =(E26*(B26-$B$2)/365)/(1+$K$4)^((B26-$B$2)/365)/-$E$2/(1+$K$4)^$K$2 -> 0.22775727

Sheet GD35D
A1: GD35D | B1: Fecha de Pago | C1: Interés | D1: Amortización | E1: Total
B2: ='ONS NY'!H2 -> 46060 | E2: =-VLOOKUP(A1,'Soberanos HD'!$B$5:$Q$14,3,0) -> -79.8 | J2: Periodo de intereses | K2: 0.5
A3: 11 | B3: 46213 | C3: 2.07 | D3: 0 | E3: =IF(B3<=$B$2,0,(C3+D3)) -> 2.07 | F3: =(E3*(B3-$B$2)/365)/(1+$K$4)^((B3-$B$2)/365)/-$E$2/(1+$K$4)^$K$2 -> 0.010056929 | J3: MDUR | K3: =SUM(F3:F102) -> 5.6982618
A4: 12 | B4: 46398 | C4: 2.05 | D4: 0 | E4: =IF(B4<=$B$2,0,(C4+D4)) -> 2.05 | F4: =(E4*(B4-$B$2)/365)/(1+$K$4)^((B4-$B$2)/365)/-$E$2/(1+$K$4)^$K$2 -> 0.021075644 | J4: TIR | K4: =XIRR(E2:E26,B2:B26) -> 0.088632891
A5: 13 | B5: 46580 | C5: 2.1 | D5: 0 | E5: =IF(B5<=$B$2,0,(C5+D5)) -> 2.1 | F5: =(E5*(B5-$B$2)/365)/(1+$K$4)^((B5-$B$2)/365)/-$E$2/(1+$K$4)^$K$2 -> 0.031837776
A6: 14 | B6: 46762 | C6: 2.35 | D6: 0 | E6: =IF(B6<=$B$2,0,(C6+D6)) -> 2.35 | F6: =(E6*(B6-$B$2)/365)/(1+$K$4)^((B6-$B$2)/365)/-$E$2/(1+$K$4)^$K$2 -> 0.046103601
A7: 15 | B7: 46944 | C7: 2.38 | D7: 0 | E7: =IF(B7<=$B$2,0,(C7+D7)) -> 2.38 | F7: =(E7*(B7-$B$2)/365)/(1+$K$4)^((B7-$B$2)/365)/-$E$2/(1+$K$4)^$K$2 -> 0.056359729
A8: 16 | B8: 47127 | C8: 2.49 | D8: 0 | E8: =IF(B8<=$B$2,0,(C8+D8)) -> 2.49 | F8: =(E8*(B8-$B$2)/365)/(1+$K$4)^((B8-$B$2)/365)/-$E$2/(1+$K$4)^$K$2 -> 0.068204369
A9: 17 | B9: 47309 | C9: 2.51 | D9: 0 | E9: =IF(B9<=$B$2,0,(C9+D9)) -> 2.51 | F9: =(E9*(B9-$B$2)/365)/(1+$K$4)^((B9-$B$2)/365)/-$E$2/(1+$K$4)^$K$2 -> 0.07714262
A10: 18 | B10: 47492 | C10: 2.49 | D10: 0 | E10: =IF(B10<=$B$2,0,(C10+D10)) -> 2.49 | F10: =(E10*(B10-$B$2)/365)/(1+$K$4)^((B10-$B$2)/365)/-$E$2/(1+$K$4)^$K$2 -> 0.084083221
A11: 19 | B11: 47674 | C11: 2.51 | D11: 0 | E11: =IF(B11<=$B$2,0,(C11+D11)) -> 2.51 | F11: =(E11*(B11-$B$2)/365)/(1+$K$4)^((B11-$B$2)/365)/-$E$2/(1+$K$4)^$K$2 -> 0.091570171
A12: 20 | B12: 47857 | C12: 2.49 | D12: 10 | E12: =IF(B12<=$B$2,0,(C12+D12)) -> 12.49 | F12: =(E12*(B12-$B$2)/365)/(1+$K$4)^((B12-$B$2)/365)/-$E$2/(1+$K$4)^$K$2 -> 0.48617882
A13: 21 | B13: 48039 | C13: 2.26 | D13: 10 | E13: =IF(B13<=$B$2,0,(C13+D13)) -> 12.26 | F13: =(E13*(B13-$B$2)/365)/(1+$K$4)^((B13-$B$2)/365)/-$E$2/(1+$K$4)^$K$2 -> 0.50376917
A14: 22 | B14: 48222 | C14: 1.99 | D14: 10 | E14: =IF(B14<=$B$2,0,(C14+D14)) -> 11.99 | F14: =(E14*(B14-$B$2)/365)/(1+$K$4)^((B14-$B$2)/365)/-$E$2/(1+$K$4)^$K$2 -> 0.51579716
A15: 23 | B15: 48407 | C15: 1.78 | D15: 10 | E15: =IF(B15<=$B$2,0,(C15+D15)) -> 11.78 | F15: =(E15*(B15-$B$2)/365)/(1+$K$4)^((B15-$B$2)/365)/-$E$2/(1+$K$4)^$K$2 -> 0.52694964
A16: 24 | B16: 48589 | C16: 1.48 | D16: 10 | E16: =IF(B16<=$B$2,0,(C16+D16)) -> 11.48 | F16: =(E16*(B16-$B$2)/365)/(1+$K$4)^((B16-$B$2)/365)/-$E$2/(1+$K$4)^$K$2 -> 0.53040944
... A21: 29 | B21: 49500 | C21: 0.25 | D21: 10 | E21: =IF(B21<=$B$2,0,(C21+D21)) -> 10.25 | F21: =(E21*(B21-$B$2)/365)/(1+$K$4)^((B21-$B$2)/365)/-$E$2/(1+$K$4)^$K$2 -> 0.52113564

Sheet AL35D
A1: AL35D | B1: Fecha de Pago | C1: Interés | D1: Amortización | E1: Total
B2: ='ONS NY'!H2 -> 46060 | E2: =-VLOOKUP(A1,'Soberanos HD'!$B$5:$Q$14,3,0) -> -78.67 | J2: Periodo de intereses | K2: 0.5
A3: 11 | B3: 46213 | C3: 2.07 | D3: 0 | E3: =IF(B3<=$B$2,0,(C3+D3)) -> 2.07 | F3: =(E3*(B3-$B$2)/365)/(1+$K$4)^((B3-$B$2)/365)/-$E$2/(1+$K$4)^$K$2 -> 0.010178893 | J3: MDUR | K3: =SUM(F3:F102) -> 5.6790308
A4: 12 | B4: 46398 | C4: 2.05 | D4: 0 | E4: =IF(B4<=$B$2,0,(C4+D4)) -> 2.05 | F4: =(E4*(B4-$B$2)/365)/(1+$K$4)^((B4-$B$2)/365)/-$E$2/(1+$K$4)^$K$2 -> 0.021305287 | J4: TIR | K4: =XIRR(E2:E26,B2:B26) -> 0.091250238
A5: 13 | B5: 46580 | C5: 2.1 | D5: 0 | E5: =IF(B5<=$B$2,0,(C5+D5)) -> 2.1 | F5: =(E5*(B5-$B$2)/365)/(1+$K$4)^((B5-$B$2)/365)/-$E$2/(1+$K$4)^$K$2 -> 0.03214617
A6: 14 | B6: 46762 | C6: 2.35 | D6: 0 | E6: =IF(B6<=$B$2,0,(C6+D6)) -> 2.35 | F6: =(E6*(B6-$B$2)/365)/(1+$K$4)^((B6-$B$2)/365)/-$E$2/(1+$K$4)^$K$2 -> 0.046494475
A7: 15 | B7: 46944 | C7: 2.38 | D7: 0 | E7: =IF(B7<=$B$2,0,(C7+D7)) -> 2.38 | F7: =(E7*(B7-$B$2)/365)/(1+$K$4)^((B7-$B$2)/365)/-$E$2/(1+$K$4)^$K$2 -> 0.056769539
A8: 16 | B8: 47127 | C8: 2.49 | D8: 0 | E8: =IF(B8<=$B$2,0,(C8+D8)) -> 2.49 | F8: =(E8*(B8-$B$2)/365)/(1+$K$4)^((B8-$B$2)/365)/-$E$2/(1+$K$4)^$K$2 -> 0.068617642
A9: 17 | B9: 47309 | C9: 2.51 | D9: 0 | E9: =IF(B9<=$B$2,0,(C9+D9)) -> 2.51 | F9: =(E9*(B9-$B$2)/365)/(1+$K$4)^((B9-$B$2)/365)/-$E$2/(1+$K$4)^$K$2 -> 0.077517178
A10: 18 | B10: 47492 | C10: 2.49 | D10: 0 | E10: =IF(B10<=$B$2,0,(C10+D10)) -> 2.49 | F10: =(E10*(B10-$B$2)/365)/(1+$K$4)^((B10-$B$2)/365)/-$E$2/(1+$K$4)^$K$2 -> 0.084389815
A11: 19 | B11: 47674 | C11: 2.51 | D11: 0 | E11: =IF(B11<=$B$2,0,(C11+D11)) -> 2.51 | F11: =(E11*(B11-$B$2)/365)/(1+$K$4)^((B11-$B$2)/365)/-$E$2/(1+$K$4)^$K$2 -> 0.091794085
A12: 20 | B12: 47857 | C12: 2.49 | D12: 10 | E12: =IF(B12<=$B$2,0,(C12+D12)) -> 12.49 | F12: =(E12*(B12-$B$2)/365)/(1+$K$4)^((B12-$B$2)/365)/-$E$2/(1+$K$4)^$K$2 -> 0.48678124
A13: 21 | B13: 48039 | C13: 2.26 | D13: 10 | E13: =IF(B13<=$B$2,0,(C13+D13)) -> 12.26 | F13: =(E13*(B13-$B$2)/365)/(1+$K$4)^((B13-$B$2)/365)/-$E$2/(1+$K$4)^$K$2 -> 0.50378979
A14: 22 | B14: 48222 | C14: 1.99 | D14: 10 | E14: =IF(B14<=$B$2,0,(C14+D14)) -> 11.99 | F14: =(E14*(B14-$B$2)/365)/(1+$K$4)^((B14-$B$2)/365)/-$E$2/(1+$K$4)^$K$2 -> 0.51519761
A15: 23 | B15: 48407 | C15: 1.78 | D15: 10 | E15: =IF(B15<=$B$2,0,(C15+D15)) -> 11.78 | F15: =(E15*(B15-$B$2)/365)/(1+$K$4)^((B15-$B$2)/365)/-$E$2/(1+$K$4)^$K$2 -> 0.5256969
A16: 24 | B16: 48589 | C16: 1.48 | D16: 10 | E16: =IF(B16<=$B$2,0,(C16+D16)) -> 11.48 | F16: =(E16*(B16-$B$2)/365)/(1+$K$4)^((B16-$B$2)/365)/-$E$2/(1+$K$4)^$K$2 -> 0.52851526
... A21: 29 | B21: 49500 | C21: 0.25 | D21: 10 | E21: =IF(B21<=$B$2,0,(C21+D21)) -> 10.25 | F21: =(E21*(B21-$B$2)/365)/(1+$K$4)^((B21-$B$2)/365)/-$E$2/(1+$K$4)^$K$2 -> 0.51617159

Sheet GD30D
A1: GD30D | B1: Fecha de Pago | C1: Interés | D1: Amortización | E1: Total
B2: ='ONS NY'!H2 -> 46060 | E2: =-VLOOKUP(A1,'Soberanos HD'!$B$5:$Q$14,3,0) -> -63.21 | J2: Periodo de intereses | K2: 0.5
A3: 11 | B3: 46213 | C3: 0.27 | D3: 8 | E3: =IF(B3<=$B$2,0,(C3+D3)) -> 8.27 | F3: =(E3*(B3-$B$2)/365)/(1+$K$4)^((B3-$B$2)/365)/-$E$2/(1+$K$4)^$K$2 -> 0.051523676 | J3: MDUR | K3: =SUM(F3:F102) -> 2.2254087
A4: 12 | B4: 46398 | C4: 0.24 | D4: 8 | E4: =IF(B4<=$B$2,0,(C4+D4)) -> 8.24 | F4: =(E4*(B4-$B$2)/365)/(1+$K$4)^((B4-$B$2)/365)/-$E$2/(1+$K$4)^$K$2 -> 0.10957315 | J4: TIR | K4: =XIRR(E2:E26,B2:B26) -> 0.070274821
A5: 13 | B5: 46580 | C5: 0.21 | D5: 8 | E5: =IF(B5<=$B$2,0,(C5+D5)) -> 8.21 | F5: =(E5*(B5-$B$2)/365)/(1+$K$4)^((B5-$B$2)/365)/-$E$2/(1+$K$4)^$K$2 -> 0.16236764
A6: 14 | B6: 46762 | C6: 0.42 | D6: 8 | E6: =IF(B6<=$B$2,0,(C6+D6)) -> 8.42 | F6: =(E6*(B6-$B$2)/365)/(1+$K$4)^((B6-$B$2)/365)/-$E$2/(1+$K$4)^$K$2 -> 0.21731762
A7: 15 | B7: 46944 | C7: 0.35 | D7: 8 | E7: =IF(B7<=$B$2,0,(C7+D7)) -> 8.35 | F7: =(E7*(B7-$B$2)/365)/(1+$K$4)^((B7-$B$2)/365)/-$E$2/(1+$K$4)^$K$2 -> 0.26234767
A8: 16 | B8: 47127 | C8: 0.28 | D8: 8 | E8: =IF(B8<=$B$2,0,(C8+D8)) -> 8.28 | F8: =(E8*(B8-$B$2)/365)/(1+$K$4)^((B8-$B$2)/365)/-$E$2/(1+$K$4)^$K$2 -> 0.30349055
A9: 17 | B9: 47309 | C9: 0.21 | D9: 8 | E9: =IF(B9<=$B$2,0,(C9+D9)) -> 8.21 | F9: =(E9*(B9-$B$2)/365)/(1+$K$4)^((B9-$B$2)/365)/-$E$2/(1+$K$4)^$K$2 -> 0.34052481
A10: 18 | B10: 47492 | C10: 0.14 | D10: 8 | E10: =IF(B10<=$B$2,0,(C10+D10)) -> 8.14 | F10: =(E10*(B10-$B$2)/365)/(1+$K$4)^((B10-$B$2)/365)/-$E$2/(1+$K$4)^$K$2 -> 0.37413
A11: 19 | B11: 47674 | C11: 0.07 | D11: 8 | E11: =IF(B11<=$B$2,0,(C11+D11)) -> 8.07 | F11: =(E11*(B11-$B$2)/365)/(1+$K$4)^((B11-$B$2)/365)/-$E$2/(1+$K$4)^$K$2 -> 0.40413357

Sheet AL30D
A1: AL30D | B1: Fecha de Pago | C1: Interés | D1: Amortización | E1: Total
B2: ='ONS NY'!H2 -> 46060 | E2: =-VLOOKUP(A1,'Soberanos HD'!$B$5:$Q$14,3,0) -> -60.58 | J2: Periodo de intereses | K2: 0.5
A3: 11 | B3: 46213 | C3: 0.27 | D3: 8 | E3: =IF(B3<=$B$2,0,(C3+D3)) -> 8.27 | F3: =(E3*(B3-$B$2)/365)/(1+$K$4)^((B3-$B$2)/365)/-$E$2/(1+$K$4)^$K$2 -> 0.05285005 | J3: MDUR | K3: =SUM(F3:F102) -> 2.1755694
A4: 12 | B4: 46398 | C4: 0.24 | D4: 8 | E4: =IF(B4<=$B$2,0,(C4+D4)) -> 8.24 | F4: =(E4*(B4-$B$2)/365)/(1+$K$4)^((B4-$B$2)/365)/-$E$2/(1+$K$4)^$K$2 -> 0.11134028 | J4: TIR | K4: =XIRR(E2:E26,B2:B26) -> 0.09034898
A5: 13 | B5: 46580 | C5: 0.21 | D5: 8 | E5: =IF(B5<=$B$2,0,(C5+D5)) -> 8.21 | F5: =(E5*(B5-$B$2)/365)/(1+$K$4)^((B5-$B$2)/365)/-$E$2/(1+$K$4)^$K$2 -> 0.16346456
A6: 14 | B6: 46762 | C6: 0.42 | D6: 8 | E6: =IF(B6<=$B$2,0,(C6+D6)) -> 8.42 | F6: =(E6*(B6-$B$2)/365)/(1+$K$4)^((B6-$B$2)/365)/-$E$2/(1+$K$4)^$K$2 -> 0.21676792
A7: 15 | B7: 46944 | C7: 0.35 | D7: 8 | E7: =IF(B7<=$B$2,0,(C7+D7)) -> 8.35 | F7: =(E7*(B7-$B$2)/365)/(1+$K$4)^((B7-$B$2)/365)/-$E$2/(1+$K$4)^$K$2 -> 0.25927058
A8: 16 | B8: 47127 | C8: 0.28 | D8: 8 | E8: =IF(B8<=$B$2,0,(C8+D8)) -> 8.28 | F8: =(E8*(B8-$B$2)/365)/(1+$K$4)^((B8-$B$2)/365)/-$E$2/(1+$K$4)^$K$2 -> 0.29714952
A9: 17 | B9: 47309 | C9: 0.21 | D9: 8 | E9: =IF(B9<=$B$2,0,(C9+D9)) -> 8.21 | F9: =(E9*(B9-$B$2)/365)/(1+$K$4)^((B9-$B$2)/365)/-$E$2/(1+$K$4)^$K$2 -> 0.33033499
A10: 18 | B10: 47492 | C10: 0.14 | D10: 8 | E10: =IF(B10<=$B$2,0,(C10+D10)) -> 8.14 | F10: =(E10*(B10-$B$2)/365)/(1+$K$4)^((B10-$B$2)/365)/-$E$2/(1+$K$4)^$K$2 -> 0.35956895
A11: 19 | B11: 47674 | C11: 0.07 | D11: 8 | E11: =IF(B11<=$B$2,0,(C11+D11)) -> 8.07 | F11: =(E11*(B11-$B$2)/365)/(1+$K$4)^((B11-$B$2)/365)/-$E$2/(1+$K$4)^$K$2 -> 0.38482256

Sheet GD29D
A1: GD29D | B1: Fecha de Pago | C1: Interés | D1: Amortización | E1: Total
B2: ='ONS NY'!H2 -> 46060 | E2: =-VLOOKUP(A1,'Soberanos HD'!$B$5:$Q$14,3,0) -> -63.7 | J2: Periodo de intereses | K2: 0.5
A3: 11 | B3: 46213 | C3: 0.35 | D3: 10 | E3: =IF(B3<=$B$2,0,(C3+D3)) -> 10.35 | F3: =(E3*(B3-$B$2)/365)/(1+$K$4)^((B3-$B$2)/365)/-$E$2/(1+$K$4)^$K$2 -> 0.064417686 | J3: MDUR | K3: =SUM(F3:F102) -> 1.7972543
A4: 12 | B4: 46398 | C4: 0.3 | D4: 10 | E4: =IF(B4<=$B$2,0,(C4+D4)) -> 10.3 | F4: =(E4*(B4-$B$2)/365)/(1+$K$4)^((B4-$B$2)/365)/-$E$2/(1+$K$4)^$K$2 -> 0.13733654 | J4: TIR | K4: =XIRR(E2:E26,B2:B26) -> 0.06248239
A5: 13 | B5: 46580 | C5: 0.25 | D5: 10 | E5: =IF(B5<=$B$2,0,(C5+D5)) -> 10.25 | F5: =(E5*(B5-$B$2)/365)/(1+$K$4)^((B5-$B$2)/365)/-$E$2/(1+$K$4)^$K$2 -> 0.20400207
A6: 14 | B6: 46762 | C6: 0.2 | D6: 10 | E6: =IF(B6<=$B$2,0,(C6+D6)) -> 10.2 | F6: =(E6*(B6-$B$2)/365)/(1+$K$4)^((B6-$B$2)/365)/-$E$2/(1+$K$4)^$K$2 -> 0.26590092
A7: 15 | B7: 46944 | C7: 0.15 | D7: 10 | E7: =IF(B7<=$B$2,0,(C7+D7)) -> 10.15 | F7: =(E7*(B7-$B$2)/365)/(1+$K$4)^((B7-$B$2)/365)/-$E$2/(1+$K$4)^$K$2 -> 0.32327792
A8: 16 | B8: 47127 | C8: 0.1 | D8: 10 | E8: =IF(B8<=$B$2,0,(C8+D8)) -> 10.1 | F8: =(E8*(B8-$B$2)/365)/(1+$K$4)^((B8-$B$2)/365)/-$E$2/(1+$K$4)^$K$2 -> 0.37665749
A9: 17 | B9: 47309 | C9: 0.05 | D9: 10 | E9: =IF(B9<=$B$2,0,(C9+D9)) -> 10.05 | F9: =(E9*(B9-$B$2)/365)/(1+$K$4)^((B9-$B$2)/365)/-$E$2/(1+$K$4)^$K$2 -> 0.42566163

Sheet AL29D
A1: AL29D | B1: Fecha de Pago | C1: Interés | D1: Amortización | E1: Total
B2: ='ONS NY'!H2 -> 46060 | E2: =-VLOOKUP(A1,'Soberanos HD'!$B$5:$Q$14,3,0) -> -60.97 | J2: Periodo de intereses | K2: 0.5
A3: 11 | B3: 46213 | C3: 0.35 | D3: 10 | E3: =IF(B3<=$B$2,0,(C3+D3)) -> 10.35 | F3: =(E3*(B3-$B$2)/365)/(1+$K$4)^((B3-$B$2)/365)/-$E$2/(1+$K$4)^$K$2 -> 0.065845914 | J3: MDUR | K3: =SUM(F3:F102) -> 1.7532753
A4: 12 | B4: 46398 | C4: 0.3 | D4: 10 | E4: =IF(B4<=$B$2,0,(C4+D4)) -> 10.3 | F4: =(E4*(B4-$B$2)/365)/(1+$K$4)^((B4-$B$2)/365)/-$E$2/(1+$K$4)^$K$2 -> 0.13869846 | J4: TIR | K4: =XIRR(E2:E26,B2:B26) -> 0.088069263
A5: 13 | B5: 46580 | C5: 0.25 | D5: 10 | E5: =IF(B5<=$B$2,0,(C5+D5)) -> 10.25 | F5: =(E5*(B5-$B$2)/365)/(1+$K$4)^((B5-$B$2)/365)/-$E$2/(1+$K$4)^$K$2 -> 0.20359488
A6: 14 | B6: 46762 | C6: 0.2 | D6: 10 | E6: =IF(B6<=$B$2,0,(C6+D6)) -> 10.2 | F6: =(E6*(B6-$B$2)/365)/(1+$K$4)^((B6-$B$2)/365)/-$E$2/(1+$K$4)^$K$2 -> 0.26223996
A7: 15 | B7: 46944 | C7: 0.15 | D7: 10 | E7: =IF(B7<=$B$2,0,(C7+D7)) -> 10.15 | F7: =(E7*(B7-$B$2)/365)/(1+$K$4)^((B7-$B$2)/365)/-$E$2/(1+$K$4)^$K$2 -> 0.31506622
A8: 16 | B8: 47127 | C8: 0.1 | D8: 10 | E8: =IF(B8<=$B$2,0,(C8+D8)) -> 10.1 | F8: =(E8*(B8-$B$2)/365)/(1+$K$4)^((B8-$B$2)/365)/-$E$2/(1+$K$4)^$K$2 -> 0.36273615
A9: 17 | B9: 47309 | C9: 0.05 | D9: 10 | E9: =IF(B9<=$B$2,0,(C9+D9)) -> 10.05 | F9: =(E9*(B9-$B$2)/365)/(1+$K$4)^((B9-$B$2)/365)/-$E$2/(1+$K$4)^$K$2 -> 0.40509371

Sheet MCC2D
A1: MCC2D | B1: Fecha de Pago | C1: Interés | D1: Amortización | E1: Total
B2: ='ONS NY'!H2 -> 46060 | E2: =-VLOOKUP(A1,'ONs Argentina'!$C$5:$N$68,3,0) -> -101 | J2: Periodo de intereses | K2: 0.5
A3: 2 | B3: 46175 | C3: 3.74 | D3: 0 | E3: =IF(B3<=$B$2,0,(C3+D3)) -> 3.74 | F3: =(E3*(B3-$B$2)/365)/(1+$K$4)^((B3-$B$2)/365)/-$E$2/(1+$K$4)^$K$2 -> 0.010962028 | J3: MDUR | K3: =SUM(F3:F102) -> 1.2141661
A4: 3 | B4: 46358 | C4: 3.76 | D4: 0 | E4: =IF(B4<=$B$2,0,(C4+D4)) -> 3.76 | F4: =(E4*(B4-$B$2)/365)/(1+$K$4)^((B4-$B$2)/365)/-$E$2/(1+$K$4)^$K$2 -> 0.027483852 | J4: TIR | K4: =XIRR(E2:E26,B2:B26) -> 0.07945601
A5: 4 | B5: 46540 | C5: 3.74 | D5: 100 | E5: =IF(B5<=$B$2,0,(C5+D5)) -> 103.74 | F5: =(E5*(B5-$B$2)/365)/(1+$K$4)^((B5-$B$2)/365)/-$E$2/(1+$K$4)^$K$2 -> 1.1757202
E9: =IF(B9<=$B$2,0,(C9+D9)) -> 0 | F9: =(E9*(B9-$B$2)/365)/(1+$K$4)^((B9-$B$2)/365)/-$E$2/(1+$K$4)^$K$2 -> 0

Sheet PFC2D
A1: PFC2D | B1: Fecha de Pago | C1: Interés | D1: Amortización | E1: Total
B2: ='ONS NY'!H2 -> 46060 | E2: =-VLOOKUP(A1,'ONs Argentina'!$C$5:$N$68,3,0) -> -102.2 | J2: Periodo de intereses | K2: 0.5
A3: 2 | B3: 46217 | C3: 3.65 | D3: 0 | E3: =IF(B3<=$B$2,0,(C3+D3)) -> 3.65 | F3: =(E3*(B3-$B$2)/365)/(1+$K$4)^((B3-$B$2)/365)/-$E$2/(1+$K$4)^$K$2 -> 0.014528993 | J3: MDUR | K3: =SUM(F3:F102) -> 1.337615
A4: 3 | B4: 46401 | C4: 3.71 | D4: 0 | E4: =IF(B4<=$B$2,0,(C4+D4)) -> 3.71 | F4: =(E4*(B4-$B$2)/365)/(1+$K$4)^((B4-$B$2)/365)/-$E$2/(1+$K$4)^$K$2 -> 0.031120628 | J4: TIR | K4: =XIRR(E2:E26,B2:B26) -> 0.061773577
A5: 4 | B5: 46582 | C5: 3.65 | D5: 100 | E5: =IF(B5<=$B$2,0,(C5+D5)) -> 103.65 | F5: =(E5*(B5-$B$2)/365)/(1+$K$4)^((B5-$B$2)/365)/-$E$2/(1+$K$4)^$K$2 -> 1.2919654
E9: =IF(B9<=$B$2,0,(C9+D9)) -> 0 | F9: =(E9*(B9-$B$2)/365)/(1+$K$4)^((B9-$B$2)/365)/-$E$2/(1+$K$4)^$K$2 -> 0

Sheet YM38D
A1: YM38D | B1: Fecha de Pago | C1: Interés | D1: Amortización | E1: Total
B2: ='ONS NY'!H2 -> 46060 | E2: =-VLOOKUP(A1,'ONs Argentina'!$C$5:$N$68,3,0) -> -103.8 | J2: Periodo de intereses | K2: 0.5
A3: 3 | B3: 46134 | C3: 1.85 | D3: 0 | E3: =IF(B3<=$B$2,0,(C3+D3)) -> 1.85 | F3: =(E3*(B3-$B$2)/365)/(1+$K$4)^((B3-$B$2)/365)/-$E$2/(1+$K$4)^$K$2 -> 0.0034892311 | J3: MDUR | K3: =SUM(F3:F102) -> 1.3523897
A4: 4 | B4: 46225 | C4: 1.87 | D4: 0 | E4: =IF(B4<=$B$2,0,(C4+D4)) -> 1.87 | F4: =(E4*(B4-$B$2)/365)/(1+$K$4)^((B4-$B$2)/365)/-$E$2/(1+$K$4)^$K$2 -> 0.007767211 | J4: TIR | K4: =XIRR(E2:E26,B2:B26) -> 0.051008293
A5: 5 | B5: 46317 | C5: 1.89 | D5: 0 | E5: =IF(B5<=$B$2,0,(C5+D5)) -> 1.89 | F5: =(E5*(B5-$B$2)/365)/(1+$K$4)^((B5-$B$2)/365)/-$E$2/(1+$K$4)^$K$2 -> 0.012075039 | J5: ONS
A6: 6 | B6: 46409 | C6: 1.89 | D6: 0 | E6: =IF(B6<=$B$2,0,(C6+D6)) -> 1.89 | F6: =(E6*(B6-$B$2)/365)/(1+$K$4)^((B6-$B$2)/365)/-$E$2/(1+$K$4)^$K$2 -> 0.016193283
A7: 7 | B7: 46499 | C7: 1.85 | D7: 0 | E7: =IF(B7<=$B$2,0,(C7+D7)) -> 1.85 | F7: =(E7*(B7-$B$2)/365)/(1+$K$4)^((B7-$B$2)/365)/-$E$2/(1+$K$4)^$K$2 -> 0.019695018
A8: 8 | B8: 46590 | C8: 1.87 | D8: 100 | E8: =IF(B8<=$B$2,0,(C8+D8)) -> 101.87 | F8: =(E8*(B8-$B$2)/365)/(1+$K$4)^((B8-$B$2)/365)/-$E$2/(1+$K$4)^$K$2 -> 1.2931699
E9: =IF(B9<=$B$2,0,(C9+D9)) -> 0 | F9: =(E9*(B9-$B$2)/365)/(1+$K$4)^((B9-$B$2)/365)/-$E$2/(1+$K$4)^$K$2 -> 0

Sheet PN38D
A1: PN38D | B1: Fecha de Pago | C1: Interés | D1: Amortización | E1: Total
B2: ='ONS NY'!H2 -> 46060 | E2: =-VLOOKUP(A1,'ONs Argentina'!$C$5:$N$68,3,0) -> -106.6 | J2: Periodo de intereses | K2: 0.5
A3: 2 | B3: 46064 | C3: 3.28 | D3: 0 | E3: =IF(B3<=$B$2,0,(C3+D3)) -> 3.28 | F3: =(E3*(B3-$B$2)/365)/(1+$K$4)^((B3-$B$2)/365)/-$E$2/(1+$K$4)^$K$2 -> 0.00033018961 | J3: MDUR | K3: =SUM(F3:F102) -> 1.3878073
A4: 3 | B4: 46245 | C4: 3.22 | D4: 0 | E4: =IF(B4<=$B$2,0,(C4+D4)) -> 3.22 | F4: =(E4*(B4-$B$2)/365)/(1+$K$4)^((B4-$B$2)/365)/-$E$2/(1+$K$4)^$K$2 -> 0.014689458 | J4: TIR | K4: =XIRR(E2:E26,B2:B26) -> 0.04195632
A5: 4 | B5: 46429 | C5: 3.28 | D5: 0 | E5: =IF(B5<=$B$2,0,(C5+D5)) -> 3.28 | F5: =(E5*(B5-$B$2)/365)/(1+$K$4)^((B5-$B$2)/365)/-$E$2/(1+$K$4)^$K$2 -> 0.029233463 | J5: ONS
A6: 5 | B6: 46610 | C6: 3.22 | D6: 100 | E6: =IF(B6<=$B$2,0,(C6+D6)) -> 103.22 | F6: =(E6*(B6-$B$2)/365)/(1+$K$4)^((B6-$B$2)/365)/-$E$2/(1+$K$4)^$K$2 -> 1.3435542
E7: =IF(B7<=$B$2,0,(C7+D7)) -> 0 | F7: =(E7*(B7-$B$2)/365)/(1+$K$4)^((B7-$B$2)/365)/-$E$2/(1+$K$4)^$K$2 -> 0
E8: =IF(B8<=$B$2,0,(C8+D8)) -> 0 | F8: =(E8*(B8-$B$2)/365)/(1+$K$4)^((B8-$B$2)/365)/-$E$2/(1+$K$4)^$K$2 -> 0
E9: =IF(B9<=$B$2,0,(C9+D9)) -> 0 | F9: =(E9*(B9-$B$2)/365)/(1+$K$4)^((B9-$B$2)/365)/-$E$2/(1+$K$4)^$K$2 -> 0

Sheet SBC1D
A1: SBC1D | B1: Fecha de Pago | C1: Interés | D1: Amortización | E1: Total
B2: ='ONS NY'!H2 -> 46060 | E2: =-VLOOKUP(A1,'ONs Argentina'!$C$5:$N$68,3,0) -> -105.65 | J2: Periodo de intereses | K2: 0.5
A3: 1 | B3: 46086 | C3: 3.62 | D3: 14 | E3: =IF(B3<=$B$2,0,(C3+D3)) -> 17.62 | F3: =(E3*(B3-$B$2)/365)/(1+$K$4)^((B3-$B$2)/365)/-$E$2/(1+$K$4)^$K$2 -> 0.011512736 | J3: MDUR | K3: =SUM(F3:F102) -> 0.77451223
A4: 2 | B4: 46178 | C4: 1.92 | D4: 14 | E4: =IF(B4<=$B$2,0,(C4+D4)) -> 15.92 | F4: =(E4*(B4-$B$2)/365)/(1+$K$4)^((B4-$B$2)/365)/-$E$2/(1+$K$4)^$K$2 -> 0.046559305 | J4: TIR | K4: =XIRR(E2:E26,B2:B26) -> 0.056514046
A5: 3 | B5: 46272 | C5: 1.61 | D5: 14 | E5: =IF(B5<=$B$2,0,(C5+D5)) -> 15.61 | F5: =(E5*(B5-$B$2)/365)/(1+$K$4)^((B5-$B$2)/365)/-$E$2/(1+$K$4)^$K$2 -> 0.080867027 | J5: ONS
A6: 4 | B6: 46363 | C6: 1.28 | D6: 14 | E6: =IF(B6<=$B$2,0,(C6+D6)) -> 15.28 | F6: =(E6*(B6-$B$2)/365)/(1+$K$4)^((B6-$B$2)/365)/-$E$2/(1+$K$4)^$K$2 -> 0.11159538
A7: 5 | B7: 46451 | C7: 0.96 | D7: 14 | E7: =IF(B7<=$B$2,0,(C7+D7)) -> 14.96 | F7: =(E7*(B7-$B$2)/365)/(1+$K$4)^((B7-$B$2)/365)/-$E$2/(1+$K$4)^$K$2 -> 0.13913371
A8: 6 | B8: 46545 | C8: 0.67 | D8: 14 | E8: =IF(B8<=$B$2,0,(C8+D8)) -> 14.67 | F8: =(E8*(B8-$B$2)/365)/(1+$K$4)^((B8-$B$2)/365)/-$E$2/(1+$K$4)^$K$2 -> 0.16685805
A9: 7 | B9: 46636 | C9: 0.36 | D9: 16 | E9: =IF(B9<=$B$2,0,(C9+D9)) -> 16.36 | F9: =(E9*(B9-$B$2)/365)/(1+$K$4)^((B9-$B$2)/365)/-$E$2/(1+$K$4)^$K$2 -> 0.21798602

Sheet TTCBD
A1: TTCBD | B1: Fecha de Pago | C1: Interés | D1: Amortización | E1: Total
B2: ='ONS NY'!H2 -> 46060 | E2: =-VLOOKUP(A1,'ONs Argentina'!$C$5:$N$68,3,0) -> -104.45 | J2: Periodo de intereses | K2: 0.5
A3: 1 | B3: 46128 | C3: 3.24 | D3: 0 | E3: =IF(B3<=$B$2,0,(C3+D3)) -> 3.24 | F3: =(E3*(B3-$B$2)/365)/(1+$K$4)^((B3-$B$2)/365)/-$E$2/(1+$K$4)^$K$2 -> 0.0055876968 | J3: MDUR | K3: =SUM(F3:F102) -> 1.562856
A4: 2 | B4: 46311 | C4: 3.26 | D4: 0 | E4: =IF(B4<=$B$2,0,(C4+D4)) -> 3.26 | F4: =(E4*(B4-$B$2)/365)/(1+$K$4)^((B4-$B$2)/365)/-$E$2/(1+$K$4)^$K$2 -> 0.020248363 | J4: TIR | K4: =XIRR(E2:E26,B2:B26) -> 0.050273177
A5: 3 | B5: 46493 | C5: 3.24 | D5: 0 | E5: =IF(B5<=$B$2,0,(C5+D5)) -> 3.24 | F5: =(E5*(B5-$B$2)/365)/(1+$K$4)^((B5-$B$2)/365)/-$E$2/(1+$K$4)^$K$2 -> 0.033877359 | J5: ONS
A6: 4 | B6: 46678 | C6: 3.26 | D6: 100 | E6: =IF(B6<=$B$2,0,(C6+D6)) -> 103.26 | F6: =(E6*(B6-$B$2)/365)/(1+$K$4)^((B6-$B$2)/365)/-$E$2/(1+$K$4)^$K$2 -> 1.5031426

Sheet TLCOD
A1: TLCOD | B1: Fecha de Pago | C1: Interés | D1: Amortización | E1: Total
B2: ='ONS NY'!H2 -> 46060 | E2: =-VLOOKUP(A1,'ONs Argentina'!$C$5:$N$68,3,0) -> -103.95 | J2: Periodo de intereses | K2: 0.5
A3: 3 | B3: 46170 | C3: 3.47 | D3: 0 | E3: =IF(B3<=$B$2,0,(C3+D3)) -> 3.47 | F3: =(E3*(B3-$B$2)/365)/(1+$K$4)^((B3-$B$2)/365)/-$E$2/(1+$K$4)^$K$2 -> 0.0095961941 | J3: MDUR | K3: =SUM(F3:F102) -> 2.4949476
A4: 4 | B4: 46356 | C4: 3.53 | D4: 0 | E4: =IF(B4<=$B$2,0,(C4+D4)) -> 3.53 | F4: =(E4*(B4-$B$2)/365)/(1+$K$4)^((B4-$B$2)/365)/-$E$2/(1+$K$4)^$K$2 -> 0.025491988 | J4: TIR | K4: =XIRR(E2:E26,B2:B26) -> 0.060689834
A5: 5 | B5: 46535 | C5: 3.47 | D5: 0 | E5: =IF(B5<=$B$2,0,(C5+D5)) -> 3.47 | F5: =(E5*(B5-$B$2)/365)/(1+$K$4)^((B5-$B$2)/365)/-$E$2/(1+$K$4)^$K$2 -> 0.039067133 | J5: ONS
A6: 6 | B6: 46720 | C6: 3.53 | D6: 0 | E6: =IF(B6<=$B$2,0,(C6+D6)) -> 3.53 | F6: =(E6*(B6-$B$2)/365)/(1+$K$4)^((B6-$B$2)/365)/-$E$2/(1+$K$4)^$K$2 -> 0.053596648
A7: 7 | B7: 46902 | C7: 3.49 | D7: 0 | E7: =IF(B7<=$B$2,0,(C7+D7)) -> 3.49 | F7: =(E7*(B7-$B$2)/365)/(1+$K$4)^((B7-$B$2)/365)/-$E$2/(1+$K$4)^$K$2 -> 0.065644351
A8: 8 | B8: 47085 | C8: 3.53 | D8: 100 | E8: =IF(B8<=$B$2,0,(C8+D8)) -> 103.53 | F8: =(E8*(B8-$B$2)/365)/(1+$K$4)^((B8-$B$2)/365)/-$E$2/(1+$K$4)^$K$2 -> 2.3015513

Sheet PLC3D
A1: PLC3D | B1: Fecha de Pago | C1: Interés | D1: Amortización | E1: Total
B2: ='ONS NY'!H2 -> 46060 | E2: =-VLOOKUP(A1,'ONs Argentina'!$C$5:$N$68,3,0) -> -103 | J2: Periodo de intereses | K2: 0.5
A3: 2 | B3: 46233 | C3: 3.6 | D3: 0 | E3: =IF(B3<=$B$2,0,(C3+D3)) -> 3.6 | F3: =(E3*(B3-$B$2)/365)/(1+$K$4)^((B3-$B$2)/365)/-$E$2/(1+$K$4)^$K$2 -> 0.015659549 | J3: MDUR | K3: =SUM(F3:F102) -> 2.0391423
A4: 3 | B4: 46419 | C4: 3.65 | D4: 0 | E4: =IF(B4<=$B$2,0,(C4+D4)) -> 3.65 | F4: =(E4*(B4-$B$2)/365)/(1+$K$4)^((B4-$B$2)/365)/-$E$2/(1+$K$4)^$K$2 -> 0.031991248 | J4: TIR | K4: =XIRR(E2:E26,B2:B26) -> 0.059478983
A5: 4 | B5: 46598 | C5: 3.6 | D5: 0 | E5: =IF(B5<=$B$2,0,(C5+D5)) -> 3.6 | F5: =(E5*(B5-$B$2)/365)/(1+$K$4)^((B5-$B$2)/365)/-$E$2/(1+$K$4)^$K$2 -> 0.045964558 | J5: ONS
A6: 5 | B6: 46783 | C6: 3.65 | D6: 0 | E6: =IF(B6<=$B$2,0,(C6+D6)) -> 3.65 | F6: =(E6*(B6-$B$2)/365)/(1+$K$4)^((B6-$B$2)/365)/-$E$2/(1+$K$4)^$K$2 -> 0.060820702
A7: 6 | B7: 46875 | C7: 1.81 | D7: 100 | E7: =IF(B7<=$B$2,0,(C7+D7)) -> 101.81 | F7: =(E7*(B7-$B$2)/365)/(1+$K$4)^((B7-$B$2)/365)/-$E$2/(1+$K$4)^$K$2 -> 1.8847062

Sheet OLC5D
A1: OLC5D | B1: Fecha de Pago | C1: Interés | D1: Amortización | E1: Total
B2: ='ONS NY'!H2 -> 46060 | E2: =-VLOOKUP(A1,'ONs Argentina'!$C$5:$N$68,3,0) -> -106 | J2: Periodo de intereses | K2: 0.5
A3: 2 | B3: 46185 | C3: 3.93 | D3: 0 | E3: =IF(B3<=$B$2,0,(C3+D3)) -> 3.93 | F3: =(E3*(B3-$B$2)/365)/(1+$K$4)^((B3-$B$2)/365)/-$E$2/(1+$K$4)^$K$2 -> 0.012111435 | J3: MDUR | K3: =SUM(F3:F102) -> 2.108082
A4: 3 | B4: 46370 | C4: 3.96 | D4: 0 | E4: =IF(B4<=$B$2,0,(C4+D4)) -> 3.96 | F4: =(E4*(B4-$B$2)/365)/(1+$K$4)^((B4-$B$2)/365)/-$E$2/(1+$K$4)^$K$2 -> 0.029417896 | J4: TIR | K4: =XIRR(E2:E26,B2:B26) -> 0.057652792
A5: 4 | B5: 46552 | C5: 3.93 | D5: 0 | E5: =IF(B5<=$B$2,0,(C5+D5)) -> 3.93 | F5: =(E5*(B5-$B$2)/365)/(1+$K$4)^((B5-$B$2)/365)/-$E$2/(1+$K$4)^$K$2 -> 0.045058235 | J5: ONS
A6: 5 | B6: 46734 | C6: 3.96 | D6: 0 | E6: =IF(B6<=$B$2,0,(C6+D6)) -> 3.96 | F6: =(E6*(B6-$B$2)/365)/(1+$K$4)^((B6-$B$2)/365)/-$E$2/(1+$K$4)^$K$2 -> 0.060483009
A7: 6 | B7: 46916 | C7: 3.96 | D7: 100 | E7: =IF(B7<=$B$2,0,(C7+D7)) -> 103.96 | F7: =(E7*(B7-$B$2)/365)/(1+$K$4)^((B7-$B$2)/365)/-$E$2/(1+$K$4)^$K$2 -> 1.9610114

Sheet CICAD
A1: CICAD | B1: Fecha de Pago | C1: Interés | D1: Amortización | E1: Total
B2: ='ONS NY'!H2 -> 46060 | E2: =-VLOOKUP(A1,'ONs Argentina'!$C$5:$N$68,3,0) -> -102 | J2: Periodo de intereses | K2: 0.5
A3: 1 | B3: 46176 | C3: 3.99 | D3: 0 | E3: =IF(B3<=$B$2,0,(C3+D3)) -> 3.99 | F3: =(E3*(B3-$B$2)/365)/(1+$K$4)^((B3-$B$2)/365)/-$E$2/(1+$K$4)^$K$2 -> 0.011686183 | J3: MDUR | K3: =SUM(F3:F102) -> 2.0611481
A4: 2 | B4: 46359 | C4: 4.01 | D4: 0 | E4: =IF(B4<=$B$2,0,(C4+D4)) -> 4.01 | F4: =(E4*(B4-$B$2)/365)/(1+$K$4)^((B4-$B$2)/365)/-$E$2/(1+$K$4)^$K$2 -> 0.029146557 | J4: TIR | K4: =XIRR(E2:E26,B2:B26) -> 0.078574619
A5: 3 | B5: 46541 | C5: 3.99 | D5: 0 | E5: =IF(B5<=$B$2,0,(C5+D5)) -> 3.99 | F5: =(E5*(B5-$B$2)/365)/(1+$K$4)^((B5-$B$2)/365)/-$E$2/(1+$K$4)^$K$2 -> 0.044927223 | J5: ONS
A6: 4 | B6: 46724 | C6: 4.01 | D6: 0 | E6: =IF(B6<=$B$2,0,(C6+D6)) -> 4.01 | F6: =(E6*(B6-$B$2)/365)/(1+$K$4)^((B6-$B$2)/365)/-$E$2/(1+$K$4)^$K$2 -> 0.060011428
A7: 5 | B7: 46909 | C7: 4.01 | D7: 100 | E7: =IF(B7<=$B$2,0,(C7+D7)) -> 104.01 | F7: =(E7*(B7-$B$2)/365)/(1+$K$4)^((B7-$B$2)/365)/-$E$2/(1+$K$4)^$K$2 -> 1.9153767
E8: =IF(B8<=$B$2,0,(C8+D8)) -> 0 | F8: =(E8*(B8-$B$2)/365)/(1+$K$4)^((B8-$B$2)/365)/-$E$2/(1+$K$4)^$K$2 -> 0

Sheet YM40D
A1: YM40D | B1: Fecha de Pago | C1: Interés | D1: Amortización | E1: Total
B2: ='ONS NY'!H2 -> 46060 | E2: =-VLOOKUP(A1,'ONs Argentina'!$C$5:$N$68,3,0) -> -105 | J2: Periodo de intereses | K2: 0.333
A3: 2 | B3: 46083 | C3: 1.89 | D3: 0 | E3: =IF(B3<=$B$2,0,(C3+D3)) -> 1.89 | F3: =(E3*(B3-$B$2)/365)/(1+$K$4)^((B3-$B$2)/365)/-$E$2/(1+$K$4)^$K$2 -> 0.0011078378 | J3: MDUR | K3: =SUM(F3:F102) -> 2.2767466
A4: 3 | B4: 46170 | C4: 1.83 | D4: 0 | E4: =IF(B4<=$B$2,0,(C4+D4)) -> 1.83 | F4: =(E4*(B4-$B$2)/365)/(1+$K$4)^((B4-$B$2)/365)/-$E$2/(1+$K$4)^$K$2 -> 0.0050579233 | J4: TIR | K4: =XIRR(E2:E26,B2:B26) -> 0.061293909
A5: 4 | B5: 46262 | C5: 1.89 | D5: 0 | E5: =IF(B5<=$B$2,0,(C5+D5)) -> 1.89 | F5: =(E5*(B5-$B$2)/365)/(1+$K$4)^((B5-$B$2)/365)/-$E$2/(1+$K$4)^$K$2 -> 0.0094499527 | J5: ONS
A6: 5 | B6: 46356 | C6: 1.89 | D6: 0 | E6: =IF(B6<=$B$2,0,(C6+D6)) -> 1.89 | F6: =(E6*(B6-$B$2)/365)/(1+$K$4)^((B6-$B$2)/365)/-$E$2/(1+$K$4)^$K$2 -> 0.013636924
A7: 6 | B7: 46447 | C7: 1.89 | D7: 0 | E7: =IF(B7<=$B$2,0,(C7+D7)) -> 1.89 | F7: =(E7*(B7-$B$2)/365)/(1+$K$4)^((B7-$B$2)/365)/-$E$2/(1+$K$4)^$K$2 -> 0.017566872
A8: 7 | B8: 46535 | C8: 1.83 | D8: 0 | E8: =IF(B8<=$B$2,0,(C8+D8)) -> 1.83 | F8: =(E8*(B8-$B$2)/365)/(1+$K$4)^((B8-$B$2)/365)/-$E$2/(1+$K$4)^$K$2 -> 0.020579627
A9: 8 | B9: 46629 | C9: 1.89 | D9: 0 | E9: =IF(B9<=$B$2,0,(C9+D9)) -> 1.89 | F9: =(E9*(B9-$B$2)/365)/(1+$K$4)^((B9-$B$2)/365)/-$E$2/(1+$K$4)^$K$2 -> 0.025073404
A10: 9 | B10: 46720 | C10: 1.89 | D10: 0 | E10: =IF(B10<=$B$2,0,(C10+D10)) -> 1.89 | F10: =(E10*(B10-$B$2)/365)/(1+$K$4)^((B10-$B$2)/365)/-$E$2/(1+$K$4)^$K$2 -> 0.02865522
A11: 10 | B11: 46811 | C11: 1.89 | D11: 0 | E11: =IF(B11<=$B$2,0,(C11+D11)) -> 1.89 | F11: =(E11*(B11-$B$2)/365)/(1+$K$4)^((B11-$B$2)/365)/-$E$2/(1+$K$4)^$K$2 -> 0.032126138
A12: 11 | B12: 46902 | C12: 1.85 | D12: 0 | E12: =IF(B12<=$B$2,0,(C12+D12)) -> 1.85 | F12: =(E12*(B12-$B$2)/365)/(1+$K$4)^((B12-$B$2)/365)/-$E$2/(1+$K$4)^$K$2 -> 0.034737565
A13: 12 | B13: 46993 | C13: 1.89 | D13: 100 | E13: =IF(B13<=$B$2,0,(C13+D13)) -> 101.89 | F13: =(E13*(B13-$B$2)/365)/(1+$K$4)^((B13-$B$2)/365)/-$E$2/(1+$K$4)^$K$2 -> 2.0887552

Sheet LMS7D
A1: LMS7D | B1: Fecha de Pago | C1: Interés | D1: Amortización | E1: Total
B2: ='ONS NY'!H2 -> 46060 | E2: =-VLOOKUP(A1,'ONs Argentina'!$C$5:$N$68,3,0) -> -94.75 | J2: Periodo de intereses | K2: 0.333
A3: 9 | B3: 46125 | C3: 1.6 | D3: 8.33 | E3: =IF(B3<=$B$2,0,(C3+D3)) -> 9.93 | F3: =(E3*(B3-$B$2)/365)/(1+$K$4)^((B3-$B$2)/365)/-$E$2/(1+$K$4)^$K$2 -> 0.018196736 | J3: MDUR | K3: =SUM(F3:F102) -> 1.3354298
A4: 10 | B4: 46216 | C4: 1.47 | D4: 8.33 | E4: =IF(B4<=$B$2,0,(C4+D4)) -> 9.8 | F4: =(E4*(B4-$B$2)/365)/(1+$K$4)^((B4-$B$2)/365)/-$E$2/(1+$K$4)^$K$2 -> 0.04257131 | J4: TIR | K4: =XIRR(E2:E26,B2:B26) -> 0.050792941
A5: 11 | B5: 46308 | C5: 1.34 | D5: 8.33 | E5: =IF(B5<=$B$2,0,(C5+D5)) -> 9.67 | F5: =(E5*(B5-$B$2)/365)/(1+$K$4)^((B5-$B$2)/365)/-$E$2/(1+$K$4)^$K$2 -> 0.06595094 | J5: ONS
A6: 12 | B6: 46399 | C6: 1.19 | D6: 8.33 | E6: =IF(B6<=$B$2,0,(C6+D6)) -> 9.52 | F6: =(E6*(B6-$B$2)/365)/(1+$K$4)^((B6-$B$2)/365)/-$E$2/(1+$K$4)^$K$2 -> 0.087662719
A7: 13 | B7: 46489 | C7: 1.02 | D7: 8.33 | E7: =IF(B7<=$B$2,0,(C7+D7)) -> 9.35 | F7: =(E7*(B7-$B$2)/365)/(1+$K$4)^((B7-$B$2)/365)/-$E$2/(1+$K$4)^$K$2 -> 0.10763205
A8: 14 | B8: 46580 | C8: 0.89 | D8: 8.33 | E8: =IF(B8<=$B$2,0,(C8+D8)) -> 9.22 | F8: =(E8*(B8-$B$2)/365)/(1+$K$4)^((B8-$B$2)/365)/-$E$2/(1+$K$4)^$K$2 -> 0.12706982
A9: 15 | B9: 46672 | C9: 0.75 | D9: 8.33 | E9: =IF(B9<=$B$2,0,(C9+D9)) -> 9.08 | F9: =(E9*(B9-$B$2)/365)/(1+$K$4)^((B9-$B$2)/365)/-$E$2/(1+$K$4)^$K$2 -> 0.14545274
A10: 16 | B10: 46764 | C10: 0.6 | D10: 8.33 | E10: =IF(B10<=$B$2,0,(C10+D10)) -> 8.93 | F10: =(E10*(B10-$B$2)/365)/(1+$K$4)^((B10-$B$2)/365)/-$E$2/(1+$K$4)^$K$2 -> 0.16251193
A11: 17 | B11: 46855 | C11: 0.44 | D11: 8.33 | E11: =IF(B11<=$B$2,0,(C11+D11)) -> 8.77 | F11: =(E11*(B11-$B$2)/365)/(1+$K$4)^((B11-$B$2)/365)/-$E$2/(1+$K$4)^$K$2 -> 0.17801775
A12: 18 | B12: 46946 | C12: 0.3 | D12: 8.33 | E12: =IF(B12<=$B$2,0,(C12+D12)) -> 8.63 | F12: =(E12*(B12-$B$2)/365)/(1+$K$4)^((B12-$B$2)/365)/-$E$2/(1+$K$4)^$K$2 -> 0.19283087
A13: 19 | B13: 47038 | C13: 0.15 | D13: 8.37 | E13: =IF(B13<=$B$2,0,(C13+D13)) -> 8.52 | F13: =(E13*(B13-$B$2)/365)/(1+$K$4)^((B13-$B$2)/365)/-$E$2/(1+$K$4)^$K$2 -> 0.20753292

Sheet VSCPD
A1: VSCPD | B1: Fecha de Pago | C1: Interés | D1: Amortización | E1: Total
B2: ='ONS NY'!H2 -> 46060 | E2: =-VLOOKUP(A1,'ONs Argentina'!$C$5:$N$68,3,0) -> -107.05 | J2: Periodo de intereses | K2: 0.5
A3: 4 | B3: 46146 | C3: 3.97 | D3: 0 | E3: =IF(B3<=$B$2,0,(C3+D3)) -> 3.97 | F3: =(E3*(B3-$B$2)/365)/(1+$K$4)^((B3-$B$2)/365)/-$E$2/(1+$K$4)^$K$2 -> 0.0083767832 | J3: MDUR | K3: =SUM(F3:F102) -> 2.1977266
A4: 5 | B4: 46329 | C4: 4.03 | D4: 0 | E4: =IF(B4<=$B$2,0,(C4+D4)) -> 4.03 | F4: =(E4*(B4-$B$2)/365)/(1+$K$4)^((B4-$B$2)/365)/-$E$2/(1+$K$4)^$K$2 -> 0.025843487 | J4: TIR | K4: =XIRR(E2:E26,B2:B26) -> 0.059060559
A5: 6 | B5: 46510 | C5: 3.97 | D5: 0 | E5: =IF(B5<=$B$2,0,(C5+D5)) -> 3.97 | F5: =(E5*(B5-$B$2)/365)/(1+$K$4)^((B5-$B$2)/365)/-$E$2/(1+$K$4)^$K$2 -> 0.041394136 | J5: ONS
A6: 7 | B6: 46694 | C6: 4.03 | D6: 25 | E6: =IF(B6<=$B$2,0,(C6+D6)) -> 29.03 | F6: =(E6*(B6-$B$2)/365)/(1+$K$4)^((B6-$B$2)/365)/-$E$2/(1+$K$4)^$K$2 -> 0.41429461
A7: 8 | B7: 46876 | C7: 2.99 | D7: 25 | E7: =IF(B7<=$B$2,0,(C7+D7)) -> 27.99 | F7: =(E7*(B7-$B$2)/365)/(1+$K$4)^((B7-$B$2)/365)/-$E$2/(1+$K$4)^$K$2 -> 0.49961997
A8: 9 | B8: 47060 | C8: 2.02 | D8: 25 | E8: =IF(B8<=$B$2,0,(C8+D8)) -> 27.02 | F8: =(E8*(B8-$B$2)/365)/(1+$K$4)^((B8-$B$2)/365)/-$E$2/(1+$K$4)^$K$2 -> 0.57420803
A9: 10 | B9: 47241 | C9: 0.99 | D9: 25 | E9: =IF(B9<=$B$2,0,(C9+D9)) -> 25.99 | F9: =(E9*(B9-$B$2)/365)/(1+$K$4)^((B9-$B$2)/365)/-$E$2/(1+$K$4)^$K$2 -> 0.63398957

Sheet OLC6D
A1: OLC6D | B1: Fecha de Pago | C1: Interés | D1: Amortización | E1: Total
B2: ='ONS NY'!H2 -> 46060 | E2: =-VLOOKUP(A1,'ONs Argentina'!$C$5:$N$68,3,0) -> -103.4 | J2: Periodo de intereses | K2: 0.5
A3: 1 | B3: 46178 | C3: 3.75 | D3: 0 | E3: =IF(B3<=$B$2,0,(C3+D3)) -> 3.75 | F3: =(E3*(B3-$B$2)/365)/(1+$K$4)^((B3-$B$2)/365)/-$E$2/(1+$K$4)^$K$2 -> 0.011098348 | J3: MDUR | K3: =SUM(F3:F102) -> 2.8758664
A4: 2 | B4: 46363 | C4: 3.75 | D4: 0 | E4: =IF(B4<=$B$2,0,(C4+D4)) -> 3.75 | F4: =(E4*(B4-$B$2)/365)/(1+$K$4)^((B4-$B$2)/365)/-$E$2/(1+$K$4)^$K$2 -> 0.027551241 | J4: TIR | K4: =XIRR(E2:E26,B2:B26) -> 0.068953761
A5: 3 | B5: 46545 | C5: 3.75 | D5: 0 | E5: =IF(B5<=$B$2,0,(C5+D5)) -> 3.75 | F5: =(E5*(B5-$B$2)/365)/(1+$K$4)^((B5-$B$2)/365)/-$E$2/(1+$K$4)^$K$2 -> 0.042657999 | J5: ONS
A6: 4 | B6: 46727 | C6: 3.75 | D6: 0 | E6: =IF(B6<=$B$2,0,(C6+D6)) -> 3.75 | F6: =(E6*(B6-$B$2)/365)/(1+$K$4)^((B6-$B$2)/365)/-$E$2/(1+$K$4)^$K$2 -> 0.056747246
A7: 5 | B7: 46909 | C7: 3.75 | D7: 0 | E7: =IF(B7<=$B$2,0,(C7+D7)) -> 3.75 | F7: =(E7*(B7-$B$2)/365)/(1+$K$4)^((B7-$B$2)/365)/-$E$2/(1+$K$4)^$K$2 -> 0.069869374
A8: 6 | B8: 47092 | C8: 3.75 | D8: 0 | E8: =IF(B8<=$B$2,0,(C8+D8)) -> 3.75 | F8: =(E8*(B8-$B$2)/365)/(1+$K$4)^((B8-$B$2)/365)/-$E$2/(1+$K$4)^$K$2 -> 0.082137169
A9: 7 | B9: 47274 | C9: 3.75 | D9: 100 | E9: =IF(B9<=$B$2,0,(C9+D9)) -> 103.75 | F9: =(E9*(B9-$B$2)/365)/(1+$K$4)^((B9-$B$2)/365)/-$E$2/(1+$K$4)^$K$2 -> 2.585805

Sheet NPCCD
A1: NPCCD | B1: Fecha de Pago | C1: Interés | D1: Amortización | E1: Total
B2: ='ONS NY'!H2 -> 46060 | E2: =-VLOOKUP(A1,'ONs Argentina'!$C$5:$N$68,3,0) -> -109.7 | J2: Periodo de intereses | K2: 0.5
A3: 1 | B3: 46078 | C3: 4.03 | D3: 0 | E3: =IF(B3<=$B$2,0,(C3+D3)) -> 4.03 | F3: =(E3*(B3-$B$2)/365)/(1+$K$4)^((B3-$B$2)/365)/-$E$2/(1+$K$4)^$K$2 -> 0.0017531777 | J3: MDUR | K3: =SUM(F3:F102) -> 2.9810782
A4: 2 | B4: 46259 | C4: 3.97 | D4: 0 | E4: =IF(B4<=$B$2,0,(C4+D4)) -> 3.97 | F4: =(E4*(B4-$B$2)/365)/(1+$K$4)^((B4-$B$2)/365)/-$E$2/(1+$K$4)^$K$2 -> 0.018536425 | J4: TIR | K4: =XIRR(E2:E26,B2:B26) -> 0.061561695
A5: 3 | B5: 46443 | C5: 4.03 | D5: 0 | E5: =IF(B5<=$B$2,0,(C5+D5)) -> 4.03 | F5: =(E5*(B5-$B$2)/365)/(1+$K$4)^((B5-$B$2)/365)/-$E$2/(1+$K$4)^$K$2 -> 0.035140422 | J5: ONS
A6: 4 | B6: 46624 | C6: 3.97 | D6: 0 | E6: =IF(B6<=$B$2,0,(C6+D6)) -> 3.97 | F6: =(E6*(B6-$B$2)/365)/(1+$K$4)^((B6-$B$2)/365)/-$E$2/(1+$K$4)^$K$2 -> 0.049488783
A7: 5 | B7: 46808 | C7: 4.03 | D7: 0 | E7: =IF(B7<=$B$2,0,(C7+D7)) -> 4.03 | F7: =(E7*(B7-$B$2)/365)/(1+$K$4)^((B7-$B$2)/365)/-$E$2/(1+$K$4)^$K$2 -> 0.06464941
A8: 6 | B8: 46990 | C8: 3.99 | D8: 0 | E8: =IF(B8<=$B$2,0,(C8+D8)) -> 3.99 | F8: =(E8*(B8-$B$2)/365)/(1+$K$4)^((B8-$B$2)/365)/-$E$2/(1+$K$4)^$K$2 -> 0.077246122
A9: 7 | B9: 47175 | C9: 4.03 | D9: 0 | E9: =IF(B9<=$B$2,0,(C9+D9)) -> 4.03 | F9: =(E9*(B9-$B$2)/365)/(1+$K$4)^((B9-$B$2)/365)/-$E$2/(1+$K$4)^$K$2 -> 0.090750793
A10: 8 | B10: 47357 | C10: 3.97 | D10: 100 | E10: =IF(B10<=$B$2,0,(C10+D10)) -> 103.97 | F10: =(E10*(B10-$B$2)/365)/(1+$K$4)^((B10-$B$2)/365)/-$E$2/(1+$K$4)^$K$2 -> 2.643513

Sheet PN41D
A1: PN41D | B1: Fecha de Pago | C1: Interés | D1: Amortización | E1: Total
B2: ='ONS NY'!H2 -> 46060 | E2: =-VLOOKUP(A1,'ONs Argentina'!$C$5:$N$68,3,0) -> -106.7 | J2: Periodo de intereses | K2: 0.5
A3: 1 | B3: 46080 | C3: 3.78 | D3: 0 | E3: =IF(B3<=$B$2,0,(C3+D3)) -> 3.78 | F3: =(E3*(B3-$B$2)/365)/(1+$K$4)^((B3-$B$2)/365)/-$E$2/(1+$K$4)^$K$2 -> 0.0018741592 | J3: MDUR | K3: =SUM(F3:F102) -> 2.9958278
A4: 2 | B4: 46261 | C4: 3.72 | D4: 0 | E4: =IF(B4<=$B$2,0,(C4+D4)) -> 3.72 | F4: =(E4*(B4-$B$2)/365)/(1+$K$4)^((B4-$B$2)/365)/-$E$2/(1+$K$4)^$K$2 -> 0.01796328 | J4: TIR | K4: =XIRR(E2:E26,B2:B26) -> 0.065374085
A5: 3 | B5: 46447 | C5: 3.78 | D5: 0 | E5: =IF(B5<=$B$2,0,(C5+D5)) -> 3.78 | F5: =(E5*(B5-$B$2)/365)/(1+$K$4)^((B5-$B$2)/365)/-$E$2/(1+$K$4)^$K$2 -> 0.034027859 | J5: ONS
A6: 4 | B6: 46626 | C6: 3.72 | D6: 0 | E6: =IF(B6<=$B$2,0,(C6+D6)) -> 3.72 | F6: =(E6*(B6-$B$2)/365)/(1+$K$4)^((B6-$B$2)/365)/-$E$2/(1+$K$4)^$K$2 -> 0.047479254
A7: 5 | B7: 46811 | C7: 3.78 | D7: 0 | E7: =IF(B7<=$B$2,0,(C7+D7)) -> 3.78 | F7: =(E7*(B7-$B$2)/365)/(1+$K$4)^((B7-$B$2)/365)/-$E$2/(1+$K$4)^$K$2 -> 0.061992167
A8: 6 | B8: 46993 | C8: 3.74 | D8: 0 | E8: =IF(B8<=$B$2,0,(C8+D8)) -> 3.74 | F8: =(E8*(B8-$B$2)/365)/(1+$K$4)^((B8-$B$2)/365)/-$E$2/(1+$K$4)^$K$2 -> 0.073832052
A9: 7 | B9: 47176 | C9: 3.78 | D9: 0 | E9: =IF(B9<=$B$2,0,(C9+D9)) -> 3.78 | F9: =(E9*(B9-$B$2)/365)/(1+$K$4)^((B9-$B$2)/365)/-$E$2/(1+$K$4)^$K$2 -> 0.086468703
A10: 8 | B10: 47357 | C10: 3.72 | D10: 100 | E10: =IF(B10<=$B$2,0,(C10+D10)) -> 103.72 | F10: =(E10*(B10-$B$2)/365)/(1+$K$4)^((B10-$B$2)/365)/-$E$2/(1+$K$4)^$K$2 -> 2.6721904

Sheet PN35D
A1: PN35D | B1: Fecha de Pago | C1: Interés | D1: Amortización | E1: Total
B2: ='ONS NY'!H2 -> 46060 | E2: =-VLOOKUP(A1,'ONs Argentina'!$C$5:$N$68,3,0) -> -105.35 | J2: Periodo de intereses | K2: 0.5
A3: 3 | B3: 46108 | C3: 3.47 | D3: 0 | E3: =IF(B3<=$B$2,0,(C3+D3)) -> 3.47 | F3: =(E3*(B3-$B$2)/365)/(1+$K$4)^((B3-$B$2)/365)/-$E$2/(1+$K$4)^$K$2 -> 0.0041695902 | J3: MDUR | K3: =SUM(F3:F102) -> 3.1079836
A4: 4 | B4: 46293 | C4: 3.53 | D4: 0 | E4: =IF(B4<=$B$2,0,(C4+D4)) -> 3.53 | F4: =(E4*(B4-$B$2)/365)/(1+$K$4)^((B4-$B$2)/365)/-$E$2/(1+$K$4)^$K$2 -> 0.019969641 | J4: TIR | K4: =XIRR(E2:E26,B2:B26) -> 0.062201849
A5: 5 | B5: 46475 | C5: 3.47 | D5: 0 | E5: =IF(B5<=$B$2,0,(C5+D5)) -> 3.47 | F5: =(E5*(B5-$B$2)/365)/(1+$K$4)^((B5-$B$2)/365)/-$E$2/(1+$K$4)^$K$2 -> 0.033927322 | J5: ONS
A6: 6 | B6: 46657 | C6: 3.53 | D6: 0 | E6: =IF(B6<=$B$2,0,(C6+D6)) -> 3.53 | F6: =(E6*(B6-$B$2)/365)/(1+$K$4)^((B6-$B$2)/365)/-$E$2/(1+$K$4)^$K$2 -> 0.048178516
A7: 7 | B7: 46839 | C7: 3.49 | D7: 0 | E7: =IF(B7<=$B$2,0,(C7+D7)) -> 3.49 | F7: =(E7*(B7-$B$2)/365)/(1+$K$4)^((B7-$B$2)/365)/-$E$2/(1+$K$4)^$K$2 -> 0.060311432
A8: 8 | B8: 47023 | C8: 3.53 | D8: 0 | E8: =IF(B8<=$B$2,0,(C8+D8)) -> 3.53 | F8: =(E8*(B8-$B$2)/365)/(1+$K$4)^((B8-$B$2)/365)/-$E$2/(1+$K$4)^$K$2 -> 0.073152054
A9: 9 | B9: 47204 | C9: 3.47 | D9: 0 | E9: =IF(B9<=$B$2,0,(C9+D9)) -> 3.47 | F9: =(E9*(B9-$B$2)/365)/(1+$K$4)^((B9-$B$2)/365)/-$E$2/(1+$K$4)^$K$2 -> 0.082905855
A10: 10 | B10: 47388 | C10: 3.53 | D10: 100 | E10: =IF(B10<=$B$2,0,(C10+D10)) -> 103.53 | F10: =(E10*(B10-$B$2)/365)/(1+$K$4)^((B10-$B$2)/365)/-$E$2/(1+$K$4)^$K$2 -> 2.7853692

Sheet IRCOD
A1: IRCOD | B1: Fecha de Pago | C1: Interés | D1: Amortización | E1: Total
B2: ='ONS NY'!H2 -> 46060 | E2: =-VLOOKUP(A1,'ONs Argentina'!$C$5:$N$68,3,0) -> -102.9 | J2: Periodo de intereses | K2: 0.5
A3: 3 | B3: 46226 | C3: 3.6 | D3: 0 | E3: =IF(B3<=$B$2,0,(C3+D3)) -> 3.6 | F3: =(E3*(B3-$B$2)/365)/(1+$K$4)^((B3-$B$2)/365)/-$E$2/(1+$K$4)^$K$2 -> 0.014974927 | J3: MDUR | K3: =SUM(F3:F102) -> 3.2104623
A4: 4 | B4: 46412 | C4: 3.65 | D4: 0 | E4: =IF(B4<=$B$2,0,(C4+D4)) -> 3.65 | F4: =(E4*(B4-$B$2)/365)/(1+$K$4)^((B4-$B$2)/365)/-$E$2/(1+$K$4)^$K$2 -> 0.031169715 | J4: TIR | K4: =XIRR(E2:E26,B2:B26) -> 0.065576461
A5: 5 | B5: 46591 | C5: 3.6 | D5: 0 | E5: =IF(B5<=$B$2,0,(C5+D5)) -> 3.6 | F5: =(E5*(B5-$B$2)/365)/(1+$K$4)^((B5-$B$2)/365)/-$E$2/(1+$K$4)^$K$2 -> 0.044953812 | J5: ONS
A6: 6 | B6: 46776 | C6: 3.65 | D6: 0 | E6: =IF(B6<=$B$2,0,(C6+D6)) -> 3.65 | F6: =(E6*(B6-$B$2)/365)/(1+$K$4)^((B6-$B$2)/365)/-$E$2/(1+$K$4)^$K$2 -> 0.059510574
A7: 7 | B7: 46958 | C7: 3.62 | D7: 0 | E7: =IF(B7<=$B$2,0,(C7+D7)) -> 3.62 | F7: =(E7*(B7-$B$2)/365)/(1+$K$4)^((B7-$B$2)/365)/-$E$2/(1+$K$4)^$K$2 -> 0.071716426
A8: 8 | B8: 47141 | C8: 3.65 | D8: 0 | E8: =IF(B8<=$B$2,0,(C8+D8)) -> 3.65 | F8: =(E8*(B8-$B$2)/365)/(1+$K$4)^((B8-$B$2)/365)/-$E$2/(1+$K$4)^$K$2 -> 0.084318369
A9: 9 | B9: 47322 | C9: 3.6 | D9: 0 | E9: =IF(B9<=$B$2,0,(C9+D9)) -> 3.6 | F9: =(E9*(B9-$B$2)/365)/(1+$K$4)^((B9-$B$2)/365)/-$E$2/(1+$K$4)^$K$2 -> 0.094077668
A10: 10 | B10: 47414 | C10: 1.83 | D10: 100 | E10: =IF(B10<=$B$2,0,(C10+D10)) -> 101.83 | F10: =(E10*(B10-$B$2)/365)/(1+$K$4)^((B10-$B$2)/365)/-$E$2/(1+$K$4)^$K$2 -> 2.8097408

Sheet TTC9D
A1: TTC9D | B1: Fecha de Pago | C1: Interés | D1: Amortización | E1: Total
B2: ='ONS NY'!H2 -> 46060 | E2: =-VLOOKUP(A1,'ONs Argentina'!$C$5:$N$68,3,0) -> -104.8 | J2: Periodo de intereses | K2: 0.5
A3: 3 | B3: 46136 | C3: 3.39 | D3: 0 | E3: =IF(B3<=$B$2,0,(C3+D3)) -> 3.39 | F3: =(E3*(B3-$B$2)/365)/(1+$K$4)^((B3-$B$2)/365)/-$E$2/(1+$K$4)^$K$2 -> 0.0064619742 | J3: MDUR | K3: =SUM(F3:F102) -> 3.1937361
A4: 4 | B4: 46321 | C4: 3.41 | D4: 0 | E4: =IF(B4<=$B$2,0,(C4+D4)) -> 3.41 | F4: =(E4*(B4-$B$2)/365)/(1+$K$4)^((B4-$B$2)/365)/-$E$2/(1+$K$4)^$K$2 -> 0.021670511 | J4: TIR | K4: =XIRR(E2:E26,B2:B26) -> 0.060247549
A5: 5 | B5: 46503 | C5: 3.39 | D5: 0 | E5: =IF(B5<=$B$2,0,(C5+D5)) -> 3.39 | F5: =(E5*(B5-$B$2)/365)/(1+$K$4)^((B5-$B$2)/365)/-$E$2/(1+$K$4)^$K$2 -> 0.035514758 | J5: ONS
A6: 6 | B6: 46685 | C6: 3.41 | D6: 0 | E6: =IF(B6<=$B$2,0,(C6+D6)) -> 3.41 | F6: =(E6*(B6-$B$2)/365)/(1+$K$4)^((B6-$B$2)/365)/-$E$2/(1+$K$4)^$K$2 -> 0.048952063
A7: 7 | B7: 46867 | C7: 3.41 | D7: 0 | E7: =IF(B7<=$B$2,0,(C7+D7)) -> 3.41 | F7: =(E7*(B7-$B$2)/365)/(1+$K$4)^((B7-$B$2)/365)/-$E$2/(1+$K$4)^$K$2 -> 0.061389724
A8: 8 | B8: 47050 | C8: 3.41 | D8: 0 | E8: =IF(B8<=$B$2,0,(C8+D8)) -> 3.41 | F8: =(E8*(B8-$B$2)/365)/(1+$K$4)^((B8-$B$2)/365)/-$E$2/(1+$K$4)^$K$2 -> 0.073133928
A9: 9 | B9: 47232 | C9: 3.39 | D9: 0 | E9: =IF(B9<=$B$2,0,(C9+D9)) -> 3.39 | F9: =(E9*(B9-$B$2)/365)/(1+$K$4)^((B9-$B$2)/365)/-$E$2/(1+$K$4)^$K$2 -> 0.083596443
A10: 10 | B10: 47415 | C10: 3.41 | D10: 100 | E10: =IF(B10<=$B$2,0,(C10+D10)) -> 103.41 | F10: =(E10*(B10-$B$2)/365)/(1+$K$4)^((B10-$B$2)/365)/-$E$2/(1+$K$4)^$K$2 -> 2.8630167

Sheet OT42D
A1: OT42D | B1: Fecha de Pago | C1: Interés | D1: Amortización | E1: Total
B2: ='ONS NY'!H2 -> 46060 | E2: =-VLOOKUP(A1,'ONs Argentina'!$C$5:$N$68,3,0) -> -103.6 | J2: Periodo de intereses | K2: 0.333
A3: 3 | B3: 46129 | C3: 1.97 | D3: 0 | E3: =IF(B3<=$B$2,0,(C3+D3)) -> 1.97 | F3: =(E3*(B3-$B$2)/365)/(1+$K$4)^((B3-$B$2)/365)/-$E$2/(1+$K$4)^$K$2 -> 0.0034654123 | J3: MDUR | K3: =SUM(F3:F102) -> 3.338671
A4: 4 | B4: 46220 | C4: 1.99 | D4: 0 | E4: =IF(B4<=$B$2,0,(C4+D4)) -> 1.99 | F4: =(E4*(B4-$B$2)/365)/(1+$K$4)^((B4-$B$2)/365)/-$E$2/(1+$K$4)^$K$2 -> 0.0079765566 | J4: TIR | K4: =XIRR(E2:E26,B2:B26) -> 0.072685209
A5: 5 | B5: 46314 | C5: 2.02 | D5: 0 | E5: =IF(B5<=$B$2,0,(C5+D5)) -> 2.02 | F5: =(E5*(B5-$B$2)/365)/(1+$K$4)^((B5-$B$2)/365)/-$E$2/(1+$K$4)^$K$2 -> 0.012623501 | J5: ONS
A6: 6 | B6: 46405 | C6: 2.02 | D6: 0 | E6: =IF(B6<=$B$2,0,(C6+D6)) -> 2.02 | F6: =(E6*(B6-$B$2)/365)/(1+$K$4)^((B6-$B$2)/365)/-$E$2/(1+$K$4)^$K$2 -> 0.016848762
A7: 7 | B7: 46496 | C7: 1.97 | D7: 0 | E7: =IF(B7<=$B$2,0,(C7+D7)) -> 1.97 | F7: =(E7*(B7-$B$2)/365)/(1+$K$4)^((B7-$B$2)/365)/-$E$2/(1+$K$4)^$K$2 -> 0.020405773
A8: 8 | B8: 46587 | C8: 1.99 | D8: 0 | E8: =IF(B8<=$B$2,0,(C8+D8)) -> 1.99 | F8: =(E8*(B8-$B$2)/365)/(1+$K$4)^((B8-$B$2)/365)/-$E$2/(1+$K$4)^$K$2 -> 0.024483123
A9: 9 | B9: 46678 | C9: 2.02 | D9: 0 | E9: =IF(B9<=$B$2,0,(C9+D9)) -> 2.02 | F9: =(E9*(B9-$B$2)/365)/(1+$K$4)^((B9-$B$2)/365)/-$E$2/(1+$K$4)^$K$2 -> 0.028638203
A10: 10 | B10: 46769 | C10: 2.02 | D10: 0 | E10: =IF(B10<=$B$2,0,(C10+D10)) -> 2.02 | F10: =(E10*(B10-$B$2)/365)/(1+$K$4)^((B10-$B$2)/365)/-$E$2/(1+$K$4)^$K$2 -> 0.032285412
A11: 11 | B11: 46860 | C11: 1.99 | D11: 0 | E11: =IF(B11<=$B$2,0,(C11+D11)) -> 1.99 | F11: =(E11*(B11-$B$2)/365)/(1+$K$4)^((B11-$B$2)/365)/-$E$2/(1+$K$4)^$K$2 -> 0.035265869
A12: 12 | B12: 46951 | C12: 1.99 | D12: 0 | E12: =IF(B12<=$B$2,0,(C12+D12)) -> 1.99 | F12: =(E12*(B12-$B$2)/365)/(1+$K$4)^((B12-$B$2)/365)/-$E$2/(1+$K$4)^$K$2 -> 0.038596249
A13: 13 | B13: 47043 | C13: 2.02 | D13: 0 | E13: =IF(B13<=$B$2,0,(C13+D13)) -> 2.02 | F13: =(E13*(B13-$B$2)/365)/(1+$K$4)^((B13-$B$2)/365)/-$E$2/(1+$K$4)^$K$2 -> 0.042465723
A14: 14 | B14: 47135 | C14: 2.02 | D14: 0 | E14: =IF(B14<=$B$2,0,(C14+D14)) -> 2.02 | F14: =(E14*(B14-$B$2)/365)/(1+$K$4)^((B14-$B$2)/365)/-$E$2/(1+$K$4)^$K$2 -> 0.04562604
A15: 15 | B15: 47225 | C15: 1.97 | D15: 0 | E15: =IF(B15<=$B$2,0,(C15+D15)) -> 1.97 | F15: =(E15*(B15-$B$2)/365)/(1+$K$4)^((B15-$B$2)/365)/-$E$2/(1+$K$4)^$K$2 -> 0.047394875
A16: 16 | B16: 47316 | C16: 1.99 | D16: 0 | E16: =IF(B16<=$B$2,0,(C16+D16)) -> 1.99 | F16: =(E16*(B16-$B$2)/365)/(1+$K$4)^((B16-$B$2)/365)/-$E$2/(1+$K$4)^$K$2 -> 0.050720642
A17: 17 | B17: 47408 | C17: 2.02 | D17: 0 | E17: =IF(B17<=$B$2,0,(C17+D17)) -> 2.02 | F17: =(E17*(B17-$B$2)/365)/(1+$K$4)^((B17-$B$2)/365)/-$E$2/(1+$K$4)^$K$2 -> 0.054287845
A18: 18 | B18: 47500 | C18: 2.02 | D18: 100 | E18: =IF(B18<=$B$2,0,(C18+D18)) -> 102.02 | F18: =(E18*(B18-$B$2)/365)/(1+$K$4)^((B18-$B$2)/365)/-$E$2/(1+$K$4)^$K$2 -> 2.877587

Sheet PLC2D
A1: PLC2D | B1: Fecha de Pago | C1: Interés | D1: Amortización | E1: Total
B2: ='ONS NY'!H2 -> 46060 | E2: =-VLOOKUP(A1,'ONs Argentina'!$C$5:$N$68,3,0) -> -105.6 | J2: Periodo de intereses | K2: 0.5
A3: 2 | B3: 46139 | C3: 3.74 | D3: 0 | E3: =IF(B3<=$B$2,0,(C3+D3)) -> 3.74 | F3: =(E3*(B3-$B$2)/365)/(1+$K$4)^((B3-$B$2)/365)/-$E$2/(1+$K$4)^$K$2 -> 0.0073228848 | J3: MDUR | K3: =SUM(F3:F102) -> 3.3417985
A4: 3 | B4: 46322 | C4: 3.76 | D4: 0 | E4: =IF(B4<=$B$2,0,(C4+D4)) -> 3.76 | F4: =(E4*(B4-$B$2)/365)/(1+$K$4)^((B4-$B$2)/365)/-$E$2/(1+$K$4)^$K$2 -> 0.023646923 | J4: TIR | K4: =XIRR(E2:E26,B2:B26) -> 0.065908816
A5: 4 | B5: 46504 | C5: 3.74 | D5: 0 | E5: =IF(B5<=$B$2,0,(C5+D5)) -> 3.74 | F5: =(E5*(B5-$B$2)/365)/(1+$K$4)^((B5-$B$2)/365)/-$E$2/(1+$K$4)^$K$2 -> 0.03861162 | J5: ONS
A6: 5 | B6: 46687 | C6: 3.76 | D6: 0 | E6: =IF(B6<=$B$2,0,(C6+D6)) -> 3.76 | F6: =(E6*(B6-$B$2)/365)/(1+$K$4)^((B6-$B$2)/365)/-$E$2/(1+$K$4)^$K$2 -> 0.053090992
A7: 6 | B7: 46870 | C7: 3.76 | D7: 0 | E7: =IF(B7<=$B$2,0,(C7+D7)) -> 3.76 | F7: =(E7*(B7-$B$2)/365)/(1+$K$4)^((B7-$B$2)/365)/-$E$2/(1+$K$4)^$K$2 -> 0.066426339
A8: 7 | B8: 47053 | C8: 3.76 | D8: 0 | E8: =IF(B8<=$B$2,0,(C8+D8)) -> 3.76 | F8: =(E8*(B8-$B$2)/365)/(1+$K$4)^((B8-$B$2)/365)/-$E$2/(1+$K$4)^$K$2 -> 0.078869039
A9: 8 | B9: 47235 | C9: 3.74 | D9: 0 | E9: =IF(B9<=$B$2,0,(C9+D9)) -> 3.74 | F9: =(E9*(B9-$B$2)/365)/(1+$K$4)^((B9-$B$2)/365)/-$E$2/(1+$K$4)^$K$2 -> 0.089920118
A10: 9 | B10: 47420 | C10: 3.76 | D10: 0 | E10: =IF(B10<=$B$2,0,(C10+D10)) -> 3.76 | F10: =(E10*(B10-$B$2)/365)/(1+$K$4)^((B10-$B$2)/365)/-$E$2/(1+$K$4)^$K$2 -> 0.10130346
A11: 10 | B11: 47511 | C11: 1.89 | D11: 100 | E11: =IF(B11<=$B$2,0,(C11+D11)) -> 101.89 | F11: =(E11*(B11-$B$2)/365)/(1+$K$4)^((B11-$B$2)/365)/-$E$2/(1+$K$4)^$K$2 -> 2.8826071
F12: =(E12*(B12-$B$2)/365)/(1+$K$4)^((B12-$B$2)/365)/-$E$2/(1+$K$4)^$K$2 -> 0
F13: =(E13*(B13-$B$2)/365)/(1+$K$4)^((B13-$B$2)/365)/-$E$2/(1+$K$4)^$K$2 -> 0
F14: =(E14*(B14-$B$2)/365)/(1+$K$4)^((B14-$B$2)/365)/-$E$2/(1+$K$4)^$K$2 -> 0
E15: =IF(B15<=$B$2,0,(C15+D15)) -> 0
E16: =IF(B16<=$B$2,0,(C16+D16)) -> 0
E17: =IF(B17<=$B$2,0,(C17+D17)) -> 0
E18: =IF(B18<=$B$2,0,(C18+D18)) -> 0

Sheet PQCSD
A1: PQCSD | B1: Fecha de Pago | C1: Interés | D1: Amortización | E1: Total
B2: ='ONS NY'!H2 -> 46060 | E2: =-VLOOKUP(A1,'ONs Argentina'!$C$5:$N$68,3,0) -> -103.55 | J2: Periodo de intereses | K2: 0.5
A3: 2 | B3: 46070 | C3: 4.03 | D3: 0 | E3: =IF(B3<=$B$2,0,(C3+D3)) -> 4.03 | F3: =(E3*(B3-$B$2)/365)/(1+$K$4)^((B3-$B$2)/365)/-$E$2/(1+$K$4)^$K$2 -> 0.0010227272 | J3: MDUR | K3: =SUM(F3:F102) -> 3.924396
A4: 3 | B4: 46252 | C4: 3.97 | D4: 0 | E4: =IF(B4<=$B$2,0,(C4+D4)) -> 3.97 | F4: =(E4*(B4-$B$2)/365)/(1+$K$4)^((B4-$B$2)/365)/-$E$2/(1+$K$4)^$K$2 -> 0.018596516 | J4: TIR | K4: =XIRR(E2:E26,B2:B26) -> 0.082240602
A5: 4 | B5: 46435 | C5: 4.03 | D5: 0 | E5: =IF(B5<=$B$2,0,(C5+D5)) -> 4.03 | F5: =(E5*(B5-$B$2)/365)/(1+$K$4)^((B5-$B$2)/365)/-$E$2/(1+$K$4)^$K$2 -> 0.035437839 | J5: ONS
A6: 5 | B6: 46616 | C6: 3.97 | D6: 0 | E6: =IF(B6<=$B$2,0,(C6+D6)) -> 3.97 | F6: =(E6*(B6-$B$2)/365)/(1+$K$4)^((B6-$B$2)/365)/-$E$2/(1+$K$4)^$K$2 -> 0.049770885
A7: 6 | B7: 46800 | C7: 4.03 | D7: 0 | E7: =IF(B7<=$B$2,0,(C7+D7)) -> 4.03 | F7: =(E7*(B7-$B$2)/365)/(1+$K$4)^((B7-$B$2)/365)/-$E$2/(1+$K$4)^$K$2 -> 0.064616564
A8: 7 | B8: 46982 | C8: 3.99 | D8: 0 | E8: =IF(B8<=$B$2,0,(C8+D8)) -> 3.99 | F8: =(E8*(B8-$B$2)/365)/(1+$K$4)^((B8-$B$2)/365)/-$E$2/(1+$K$4)^$K$2 -> 0.076629505
A9: 8 | B9: 47168 | C9: 4.03 | D9: 0 | E9: =IF(B9<=$B$2,0,(C9+D9)) -> 4.03 | F9: =(E9*(B9-$B$2)/365)/(1+$K$4)^((B9-$B$2)/365)/-$E$2/(1+$K$4)^$K$2 -> 0.089340003
A10: 9 | B10: 47347 | C10: 3.97 | D10: 0 | E10: =IF(B10<=$B$2,0,(C10+D10)) -> 3.97 | F10: =(E10*(B10-$B$2)/365)/(1+$K$4)^((B10-$B$2)/365)/-$E$2/(1+$K$4)^$K$2 -> 0.098341637
A11: 10 | B11: 47532 | C11: 4.03 | D11: 0 | E11: =IF(B11<=$B$2,0,(C11+D11)) -> 4.03 | F11: =(E11*(B11-$B$2)/365)/(1+$K$4)^((B11-$B$2)/365)/-$E$2/(1+$K$4)^$K$2 -> 0.10969434
A12: 11 | B12: 47715 | C12: 3.97 | D12: 0 | E12: =IF(B12<=$B$2,0,(C12+D12)) -> 3.97 | F12: =(E12*(B12-$B$2)/365)/(1+$K$4)^((B12-$B$2)/365)/-$E$2/(1+$K$4)^$K$2 -> 0.11677529
A13: 12 | B13: 47896 | C13: 4.03 | D13: 100 | E13: =IF(B13<=$B$2,0,(C13+D13)) -> 104.03 | F13: =(E13*(B13-$B$2)/365)/(1+$K$4)^((B13-$B$2)/365)/-$E$2/(1+$K$4)^$K$2 -> 3.2641707
F14: =(E14*(B14-$B$2)/365)/(1+$K$4)^((B14-$B$2)/365)/-$E$2/(1+$K$4)^$K$2 -> 0
E15: =IF(B15<=$B$2,0,(C15+D15)) -> 0
E16: =IF(B16<=$B$2,0,(C16+D16)) -> 0
E17: =IF(B17<=$B$2,0,(C17+D17)) -> 0
E18: =IF(B18<=$B$2,0,(C18+D18)) -> 0

Sheet VSCRD
A1: VSCRD | B1: Fecha de Pago | C1: Interés | D1: Amortización | E1: Total
B2: ='ONS NY'!H2 -> 46060 | E2: =-VLOOKUP(A1,'ONs Argentina'!$C$5:$N$68,3,0) -> -107 | J2: Periodo de intereses | K2: 0.5
A3: 3 | B3: 46122 | C3: 3.81 | D3: 0 | E3: =IF(B3<=$B$2,0,(C3+D3)) -> 3.81 | F3: =(E3*(B3-$B$2)/365)/(1+$K$4)^((B3-$B$2)/365)/-$E$2/(1+$K$4)^$K$2 -> 0.0057940643 | J3: MDUR | K3: =SUM(F3:F102) -> 3.8119873
A4: 4 | B4: 46308 | C4: 3.84 | D4: 0 | E4: =IF(B4<=$B$2,0,(C4+D4)) -> 3.84 | F4: =(E4*(B4-$B$2)/365)/(1+$K$4)^((B4-$B$2)/365)/-$E$2/(1+$K$4)^$K$2 -> 0.022607717 | J4: TIR | K4: =XIRR(E2:E26,B2:B26) -> 0.06623157
A5: 5 | B5: 46489 | C5: 3.81 | D5: 0 | E5: =IF(B5<=$B$2,0,(C5+D5)) -> 3.81 | F5: =(E5*(B5-$B$2)/365)/(1+$K$4)^((B5-$B$2)/365)/-$E$2/(1+$K$4)^$K$2 -> 0.037587614 | J5: ONS
A6: 6 | B6: 46672 | C6: 3.84 | D6: 0 | E6: =IF(B6<=$B$2,0,(C6+D6)) -> 3.84 | F6: =(E6*(B6-$B$2)/365)/(1+$K$4)^((B6-$B$2)/365)/-$E$2/(1+$K$4)^$K$2 -> 0.052333673
A7: 7 | B7: 46853 | C7: 3.84 | D7: 0 | E7: =IF(B7<=$B$2,0,(C7+D7)) -> 3.84 | F7: =(E7*(B7-$B$2)/365)/(1+$K$4)^((B7-$B$2)/365)/-$E$2/(1+$K$4)^$K$2 -> 0.065688852
A8: 8 | B8: 47036 | C8: 3.84 | D8: 0 | E8: =IF(B8<=$B$2,0,(C8+D8)) -> 3.84 | F8: =(E8*(B8-$B$2)/365)/(1+$K$4)^((B8-$B$2)/365)/-$E$2/(1+$K$4)^$K$2 -> 0.078289656
A9: 9 | B9: 47218 | C9: 3.81 | D9: 0 | E9: =IF(B9<=$B$2,0,(C9+D9)) -> 3.81 | F9: =(E9*(B9-$B$2)/365)/(1+$K$4)^((B9-$B$2)/365)/-$E$2/(1+$K$4)^$K$2 -> 0.089262544
A10: 10 | B10: 47401 | C10: 3.84 | D10: 33 | E10: =IF(B10<=$B$2,0,(C10+D10)) -> 36.84 | F10: =(E10*(B10-$B$2)/365)/(1+$K$4)^((B10-$B$2)/365)/-$E$2/(1+$K$4)^$K$2 -> 0.96787708
A11: 11 | B11: 47583 | C11: 2.56 | D11: 0 | E11: =IF(B11<=$B$2,0,(C11+D11)) -> 2.56 | F11: =(E11*(B11-$B$2)/365)/(1+$K$4)^((B11-$B$2)/365)/-$E$2/(1+$K$4)^$K$2 -> 0.073981658
A12: 12 | B12: 47766 | C12: 2.57 | D12: 33 | E12: =IF(B12<=$B$2,0,(C12+D12)) -> 35.57 | F12: =(E12*(B12-$B$2)/365)/(1+$K$4)^((B12-$B$2)/365)/-$E$2/(1+$K$4)^$K$2 -> 1.1150213
A13: 13 | B13: 47948 | C13: 1.3 | D13: 0 | E13: =IF(B13<=$B$2,0,(C13+D13)) -> 1.3 | F13: =(E13*(B13-$B$2)/365)/(1+$K$4)^((B13-$B$2)/365)/-$E$2/(1+$K$4)^$K$2 -> 0.043679534
A14: 14 | B14: 48131 | C14: 1.3 | D14: 34 | E14: =IF(B14<=$B$2,0,(C14+D14)) -> 35.3 | F14: =(E14*(B14-$B$2)/365)/(1+$K$4)^((B14-$B$2)/365)/-$E$2/(1+$K$4)^$K$2 -> 1.2598636
E15: =IF(B15<=$B$2,0,(C15+D15)) -> 0
E16: =IF(B16<=$B$2,0,(C16+D16)) -> 0
E17: =IF(B17<=$B$2,0,(C17+D17)) -> 0
E18: =IF(B18<=$B$2,0,(C18+D18)) -> 0

Sheet PN36D
A1: PN36D | B1: Fecha de Pago | C1: Interés | D1: Amortización | E1: Total
B2: ='ONS NY'!H2 -> 46060 | E2: =-VLOOKUP(A1,'ONs Argentina'!$C$5:$N$68,3,0) -> -105.3 | J2: Periodo de intereses | K2: 0.5
A3: 3 | B3: 46155 | C3: 3.6 | D3: 0 | E3: =IF(B3<=$B$2,0,(C3+D3)) -> 3.6 | F3: =(E3*(B3-$B$2)/365)/(1+$K$4)^((B3-$B$2)/365)/-$E$2/(1+$K$4)^$K$2 -> 0.0084764972 | J3: MDUR | K3: =SUM(F3:F102) -> 4.6091756
A4: 4 | B4: 46339 | C4: 3.65 | D4: 0 | E4: =IF(B4<=$B$2,0,(C4+D4)) -> 3.65 | F4: =(E4*(B4-$B$2)/365)/(1+$K$4)^((B4-$B$2)/365)/-$E$2/(1+$K$4)^$K$2 -> 0.024440181 | J4: TIR | K4: =XIRR(E2:E26,B2:B26) -> 0.065952751
A5: 5 | B5: 46520 | C5: 3.6 | D5: 0 | E5: =IF(B5<=$B$2,0,(C5+D5)) -> 3.6 | F5: =(E5*(B5-$B$2)/365)/(1+$K$4)^((B5-$B$2)/365)/-$E$2/(1+$K$4)^$K$2 -> 0.038504607 | J5: ONS
A6: 6 | B6: 46706 | C6: 3.65 | D6: 0 | E6: =IF(B6<=$B$2,0,(C6+D6)) -> 3.65 | F6: =(E6*(B6-$B$2)/365)/(1+$K$4)^((B6-$B$2)/365)/-$E$2/(1+$K$4)^$K$2 -> 0.05306923
A7: 7 | B7: 46888 | C7: 3.62 | D7: 0 | E7: =IF(B7<=$B$2,0,(C7+D7)) -> 3.62 | F7: =(E7*(B7-$B$2)/365)/(1+$K$4)^((B7-$B$2)/365)/-$E$2/(1+$K$4)^$K$2 -> 0.065346952
A8: 8 | B8: 47070 | C8: 3.65 | D8: 0 | E8: =IF(B8<=$B$2,0,(C8+D8)) -> 3.65 | F8: =(E8*(B8-$B$2)/365)/(1+$K$4)^((B8-$B$2)/365)/-$E$2/(1+$K$4)^$K$2 -> 0.077851984
A9: 9 | B9: 47252 | C9: 3.6 | D9: 0 | E9: =IF(B9<=$B$2,0,(C9+D9)) -> 3.6 | F9: =(E9*(B9-$B$2)/365)/(1+$K$4)^((B9-$B$2)/365)/-$E$2/(1+$K$4)^$K$2 -> 0.087781545
A10: 10 | B10: 47435 | C10: 3.65 | D10: 0 | E10: =IF(B10<=$B$2,0,(C10+D10)) -> 3.65 | F10: =(E10*(B10-$B$2)/365)/(1+$K$4)^((B10-$B$2)/365)/-$E$2/(1+$K$4)^$K$2 -> 0.099428996
A11: 11 | B11: 47616 | C11: 3.6 | D11: 0 | E11: =IF(B11<=$B$2,0,(C11+D11)) -> 3.6 | F11: =(E11*(B11-$B$2)/365)/(1+$K$4)^((B11-$B$2)/365)/-$E$2/(1+$K$4)^$K$2 -> 0.10751637
A12: 12 | B12: 47800 | C12: 3.65 | D12: 0 | E12: =IF(B12<=$B$2,0,(C12+D12)) -> 3.65 | F12: =(E12*(B12-$B$2)/365)/(1+$K$4)^((B12-$B$2)/365)/-$E$2/(1+$K$4)^$K$2 -> 0.11803795
A13: 13 | B13: 47981 | C13: 3.6 | D13: 0 | E13: =IF(B13<=$B$2,0,(C13+D13)) -> 3.6 | F13: =(E13*(B13-$B$2)/365)/(1+$K$4)^((B13-$B$2)/365)/-$E$2/(1+$K$4)^$K$2 -> 0.12452439
A14: 14 | B14: 48165 | C14: 3.65 | D14: 100 | E14: =IF(B14<=$B$2,0,(C14+D14)) -> 103.65 | F14: =(E14*(B14-$B$2)/365)/(1+$K$4)^((B14-$B$2)/365)/-$E$2/(1+$K$4)^$K$2 -> 3.8041969
E15: =IF(B15<=$B$2,0,(C15+D15)) -> 0
E16: =IF(B16<=$B$2,0,(C16+D16)) -> 0
E17: =IF(B17<=$B$2,0,(C17+D17)) -> 0
E18: =IF(B18<=$B$2,0,(C18+D18)) -> 0

Sheet HJCID
A1: HJCID | B1: Fecha de Pago | C1: Interés | D1: Amortización | E1: Total
B2: ='ONS NY'!H2 -> 46060 | E2: =-VLOOKUP(A1,'ONs Argentina'!$C$5:$N$68,3,0) -> -102.95 | J2: Periodo de intereses | K2: 0.5
A3: 2 | B3: 46169 | C3: 3.75 | D3: 0 | E3: =IF(B3<=$B$2,0,(C3+D3)) -> 3.75 | F3: =(E3*(B3-$B$2)/365)/(1+$K$4)^((B3-$B$2)/365)/-$E$2/(1+$K$4)^$K$2 -> 0.010350751 | J3: MDUR | K3: =SUM(F3:F102) -> 1.2075583
A4: 3 | B4: 46353 | C4: 3.75 | D4: 0 | E4: =IF(B4<=$B$2,0,(C4+D4)) -> 3.75 | F4: =(E4*(B4-$B$2)/365)/(1+$K$4)^((B4-$B$2)/365)/-$E$2/(1+$K$4)^$K$2 -> 0.026964954 | J4: TIR | K4: =XIRR(E2:E26,B2:B26) -> 0.064154342
A5: 4 | B5: 46534 | C5: 3.75 | D5: 100 | E5: =IF(B5<=$B$2,0,(C5+D5)) -> 103.75 | F5: =(E5*(B5-$B$2)/365)/(1+$K$4)^((B5-$B$2)/365)/-$E$2/(1+$K$4)^$K$2 -> 1.1702426 | J5: ONS
E6: =IF(B6<=$B$2,0,(C6+D6)) -> 0 | F6: =(E6*(B6-$B$2)/365)/(1+$K$4)^((B6-$B$2)/365)/-$E$2/(1+$K$4)^$K$2 -> 0
E7: =IF(B7<=$B$2,0,(C7+D7)) -> 0 | F7: =(E7*(B7-$B$2)/365)/(1+$K$4)^((B7-$B$2)/365)/-$E$2/(1+$K$4)^$K$2 -> 0
E8: =IF(B8<=$B$2,0,(C8+D8)) -> 0 | F8: =(E8*(B8-$B$2)/365)/(1+$K$4)^((B8-$B$2)/365)/-$E$2/(1+$K$4)^$K$2 -> 0
E9: =IF(B9<=$B$2,0,(C9+D9)) -> 0
E10: =IF(B10<=$B$2,0,(C10+D10)) -> 0
E11: =IF(B11<=$B$2,0,(C11+D11)) -> 0
E12: =IF(B12<=$B$2,0,(C12+D12)) -> 0
E13: =IF(B13<=$B$2,0,(C13+D13)) -> 0
E14: =IF(B14<=$B$2,0,(C14+D14)) -> 0
E15: =IF(B15<=$B$2,0,(C15+D15)) -> 0
E16: =IF(B16<=$B$2,0,(C16+D16)) -> 0
E17: =IF(B17<=$B$2,0,(C17+D17)) -> 0
E18: =IF(B18<=$B$2,0,(C18+D18)) -> 0

Sheet PNDCD
A1: PNDCD | C1: Interés | D1: Amortización | E1: Total
B2: ='ONS NY'!H2 -> 46060 | E2: =-VLOOKUP(A1,'ONS NY'!$C$5:$R$589,3,0) -> -65.92 | J2: Periodo de intereses | K2: 0.5
A3: 10 | B3: 46142 | C3: 2.74 | D3: 20 | E3: =IF(B3<=$B$2,0,(C3+D3)) -> 22.74 | F3: =(E3*(B3-$B$2)/365)/(1+$K$4)^((B3-$B$2)/365)/-$E$2/(1+$K$4)^$K$2 -> 0.078028777 | J3: MDUR | K3: =SUM(F3:F19) -> 0.71606679
A4: 11 | B4: 46325 | C4: 1.83 | D4: 20 | E4: =IF(B4<=$B$2,0,(C4+D4)) -> 21.83 | F4: =(E4*(B4-$B$2)/365)/(1+$K$4)^((B4-$B$2)/365)/-$E$2/(1+$K$4)^$K$2 -> 0.24321952 | J4: TIR | K4: =XIRR(E2:E22,B2:B22) -> -0.0093629867
A5: 12 | B5: 46507 | C5: 0.91 | D5: 20 | E5: =IF(B5<=$B$2,0,(C5+D5)) -> 20.91 | F5: =(E5*(B5-$B$2)/365)/(1+$K$4)^((B5-$B$2)/365)/-$E$2/(1+$K$4)^$K$2 -> 0.3948185
E6: =IF(B6<=$B$2,0,(C6+D6)) -> 0 | F6: =(E6*(B6-$B$2)/365)/(1+$K$4)^((B6-$B$2)/365)/-$E$2/(1+$K$4)^$K$2 -> 0
E7: =IF(B7<=$B$2,0,(C7+D7)) -> 0 | F7: =(E7*(B7-$B$2)/365)/(1+$K$4)^((B7-$B$2)/365)/-$E$2/(1+$K$4)^$K$2 -> 0
E8: =IF(B8<=$B$2,0,(C8+D8)) -> 0
E9: =IF(B9<=$B$2,0,(C9+D9)) -> 0
E10: =IF(B10<=$B$2,0,(C10+D10)) -> 0
E11: =IF(B11<=$B$2,0,(C11+D11)) -> 0
E12: =IF(B12<=$B$2,0,(C12+D12)) -> 0
E13: =IF(B13<=$B$2,0,(C13+D13)) -> 0
E14: =IF(B14<=$B$2,0,(C14+D14)) -> 0
E15: =IF(B15<=$B$2,0,(C15+D15)) -> 0
E16: =IF(B16<=$B$2,0,(C16+D16)) -> 0
E17: =IF(B17<=$B$2,0,(C17+D17)) -> 0
E18: =IF(B18<=$B$2,0,(C18+D18)) -> 0
E19: =IF(B19<=$B$2,0,(C19+D19)) -> 0
... E24: =IF(B24<=$B$2,0,(C24+D24)) -> 0

Sheet TLCTD
A1: TLCTD | C1: Interés | D1: Amortización
B2: ='ONS NY'!H2 -> 46060 | E2: =-VLOOKUP(A1,'ONS NY'!$C$5:$R$589,3,0) -> -105.5 | J2: Periodo de intereses | K2: 0.5
A3: 1 | B3: 46223 | C3: 4.22 | D3: 0 | E3: =IF(B3<=$B$2,0,(C3+D3)) -> 4.22 | F3: =(E3*(B3-$B$2)/365)/(1+$K$4)^((B3-$B$2)/365)/-$E$2/(1+$K$4)^$K$2 -> 0.016625926 | J3: MDUR | K3: =SUM(F3:F102) -> 6.4810689
A4: 2 | B4: 46407 | C4: 4.28 | D4: 0 | E4: =IF(B4<=$B$2,0,(C4+D4)) -> 4.28 | F4: =(E4*(B4-$B$2)/365)/(1+$K$4)^((B4-$B$2)/365)/-$E$2/(1+$K$4)^$K$2 -> 0.034550926 | J4: TIR | K4: =XIRR(E2:E22,B2:B22) -> 0.078768
A5: 3 | B5: 46588 | C5: 4.22 | D5: 0 | E5: =IF(B5<=$B$2,0,(C5+D5)) -> 4.22 | F5: =(E5*(B5-$B$2)/365)/(1+$K$4)^((B5-$B$2)/365)/-$E$2/(1+$K$4)^$K$2 -> 0.049923395 | J5: ONS
A6: 4 | B6: 46772 | C6: 4.28 | D6: 0 | E6: =IF(B6<=$B$2,0,(C6+D6)) -> 4.28 | F6: =(E6*(B6-$B$2)/365)/(1+$K$4)^((B6-$B$2)/365)/-$E$2/(1+$K$4)^$K$2 -> 0.065717669
A7: 5 | B7: 46954 | C7: 4.24 | D7: 0 | E7: =IF(B7<=$B$2,0,(C7+D7)) -> 4.24 | F7: =(E7*(B7-$B$2)/365)/(1+$K$4)^((B7-$B$2)/365)/-$E$2/(1+$K$4)^$K$2 -> 0.078712343
A8: 6 | B8: 47140 | C8: 4.28 | D8: 0 | E8: =IF(B8<=$B$2,0,(C8+D8)) -> 4.28 | F8: =(E8*(B8-$B$2)/365)/(1+$K$4)^((B8-$B$2)/365)/-$E$2/(1+$K$4)^$K$2 -> 0.092347941
A9: 7 | B9: 47319 | C9: 4.22 | D9: 0 | E9: =IF(B9<=$B$2,0,(C9+D9)) -> 4.22 | F9: =(E9*(B9-$B$2)/365)/(1+$K$4)^((B9-$B$2)/365)/-$E$2/(1+$K$4)^$K$2 -> 0.10227031
A10: 8 | B10: 47504 | C10: 4.28 | D10: 0 | E10: =IF(B10<=$B$2,0,(C10+D10)) -> 4.28 | F10: =(E10*(B10-$B$2)/365)/(1+$K$4)^((B10-$B$2)/365)/-$E$2/(1+$K$4)^$K$2 -> 0.11448084
A11: 9 | B11: 47686 | C11: 4.22 | D11: 0 | E11: =IF(B11<=$B$2,0,(C11+D11)) -> 4.22 | F11: =(E11*(B11-$B$2)/365)/(1+$K$4)^((B11-$B$2)/365)/-$E$2/(1+$K$4)^$K$2 -> 0.12238718
A12: 10 | B12: 47868 | C12: 4.28 | D12: 0 | E12: =IF(B12<=$B$2,0,(C12+D12)) -> 4.28 | F12: =(E12*(B12-$B$2)/365)/(1+$K$4)^((B12-$B$2)/365)/-$E$2/(1+$K$4)^$K$2 -> 0.13290037
A13: 11 | B13: 48050 | C13: 4.22 | D13: 0 | E13: =IF(B13<=$B$2,0,(C13+D13)) -> 4.22 | F13: =(E13*(B13-$B$2)/365)/(1+$K$4)^((B13-$B$2)/365)/-$E$2/(1+$K$4)^$K$2 -> 0.13887709
A14: 12 | B14: 48233 | C14: 4.28 | D14: 0 | E14: =IF(B14<=$B$2,0,(C14+D14)) -> 4.28 | F14: =(E14*(B14-$B$2)/365)/(1+$K$4)^((B14-$B$2)/365)/-$E$2/(1+$K$4)^$K$2 -> 0.1480674
A15: 13 | B15: 48415 | C15: 4.24 | D15: 0 | E15: =IF(B15<=$B$2,0,(C15+D15)) -> 4.24 | F15: =(E15*(B15-$B$2)/365)/(1+$K$4)^((B15-$B$2)/365)/-$E$2/(1+$K$4)^$K$2 -> 0.15307131
A16: 14 | B16: 48599 | C16: 4.28 | D16: 0 | E16: =IF(B16<=$B$2,0,(C16+D16)) -> 4.28 | F16: =(E16*(B16-$B$2)/365)/(1+$K$4)^((B16-$B$2)/365)/-$E$2/(1+$K$4)^$K$2 -> 0.16034084
A17: 15 | B17: 48780 | C17: 4.22 | D17: 0 | E17: =IF(B17<=$B$2,0,(C17+D17)) -> 4.22 | F17: =(E17*(B17-$B$2)/365)/(1+$K$4)^((B17-$B$2)/365)/-$E$2/(1+$K$4)^$K$2 -> 0.16311366
... A22: 20 | B22: 49695 | C22: 2.14 | D22: 50 | E22: =IF(B22<=$B$2,0,(C22+D22)) -> 52.14 | F22: =(E22*(B22-$B$2)/365)/(1+$K$4)^((B22-$B$2)/365)/-$E$2/(1+$K$4)^$K$2 -> 2.227095
E24: =IF(B24<=$B$2,0,(C24+D24)) -> 0

Sheet CIC9D
A1: CIC9D | B1: Fecha de Pago | C1: Interés | D1: Amortización | E1: Total
B2: ='ONS NY'!H2 -> 46060 | E2: =-VLOOKUP(A1,'ONs Argentina'!$C$5:$N$68,3,0) -> -103.5 | J2: Periodo de intereses | K2: 0.5
A3: 2 | B3: 46163 | C3: 4.09 | D3: 0 | E3: =IF(B3<=$B$2,0,(C3+D3)) -> 4.09 | F3: =(E3*(B3-$B$2)/365)/(1+$K$4)^((B3-$B$2)/365)/-$E$2/(1+$K$4)^$K$2 -> 0.01058322 | J3: MDUR | K3: =SUM(F3:F102) -> 1.1842598
A4: 3 | B4: 46350 | C4: 4.23 | D4: 0 | E4: =IF(B4<=$B$2,0,(C4+D4)) -> 4.23 | F4: =(E4*(B4-$B$2)/365)/(1+$K$4)^((B4-$B$2)/365)/-$E$2/(1+$K$4)^$K$2 -> 0.029779757 | J4: TIR | K4: =XIRR(E2:E26,B2:B26) -> 0.069136474
A5: 4 | B5: 46528 | C5: 4.02 | D5: 100 | E5: =IF(B5<=$B$2,0,(C5+D5)) -> 104.02 | F5: =(E5*(B5-$B$2)/365)/(1+$K$4)^((B5-$B$2)/365)/-$E$2/(1+$K$4)^$K$2 -> 1.1438968 | J5: ONS
E6: =IF(B6<=$B$2,0,(C6+D6)) -> 0 | F6: =(E6*(B6-$B$2)/365)/(1+$K$4)^((B6-$B$2)/365)/-$E$2/(1+$K$4)^$K$2 -> 0
E7: =IF(B7<=$B$2,0,(C7+D7)) -> 0 | F7: =(E7*(B7-$B$2)/365)/(1+$K$4)^((B7-$B$2)/365)/-$E$2/(1+$K$4)^$K$2 -> 0
E8: =IF(B8<=$B$2,0,(C8+D8)) -> 0 | F8: =(E8*(B8-$B$2)/365)/(1+$K$4)^((B8-$B$2)/365)/-$E$2/(1+$K$4)^$K$2 -> 0
E9: =IF(B9<=$B$2,0,(C9+D9)) -> 0
E10: =IF(B10<=$B$2,0,(C10+D10)) -> 0
E11: =IF(B11<=$B$2,0,(C11+D11)) -> 0
E12: =IF(B12<=$B$2,0,(C12+D12)) -> 0
E13: =IF(B13<=$B$2,0,(C13+D13)) -> 0
E14: =IF(B14<=$B$2,0,(C14+D14)) -> 0
E15: =IF(B15<=$B$2,0,(C15+D15)) -> 0
E16: =IF(B16<=$B$2,0,(C16+D16)) -> 0
E17: =IF(B17<=$B$2,0,(C17+D17)) -> 0
E18: =IF(B18<=$B$2,0,(C18+D18)) -> 0

Sheet RCCRD
A1: RCCRD | B1: Fecha de Pago | C1: Interés | D1: Amortización | E1: Total
B2: ='ONS NY'!H2 -> 46060 | E2: =-VLOOKUP(A1,'ONs Argentina'!$C$5:$N$68,3,0) -> -103.65 | J2: Periodo de intereses | K2: 0.5
A3: 2 | B3: 46153 | C3: 3.35 | D3: 0 | E3: =IF(B3<=$B$2,0,(C3+D3)) -> 3.35 | F3: =(E3*(B3-$B$2)/365)/(1+$K$4)^((B3-$B$2)/365)/-$E$2/(1+$K$4)^$K$2 -> 0.0079295491 | J3: MDUR | K3: =SUM(F3:F102) -> 1.174694
A4: 3 | B4: 46335 | C4: 3.4 | D4: 0 | E4: =IF(B4<=$B$2,0,(C4+D4)) -> 3.4 | F4: =(E4*(B4-$B$2)/365)/(1+$K$4)^((B4-$B$2)/365)/-$E$2/(1+$K$4)^$K$2 -> 0.023210631 | J4: TIR | K4: =XIRR(E2:E26,B2:B26) -> 0.051357481
A5: 4 | B5: 46517 | C5: 3.35 | D5: 100 | E5: =IF(B5<=$B$2,0,(C5+D5)) -> 103.35 | F5: =(E5*(B5-$B$2)/365)/(1+$K$4)^((B5-$B$2)/365)/-$E$2/(1+$K$4)^$K$2 -> 1.1435538 | J5: ONS
E6: =IF(B6<=$B$2,0,(C6+D6)) -> 0 | F6: =(E6*(B6-$B$2)/365)/(1+$K$4)^((B6-$B$2)/365)/-$E$2/(1+$K$4)^$K$2 -> 0
E7: =IF(B7<=$B$2,0,(C7+D7)) -> 0 | F7: =(E7*(B7-$B$2)/365)/(1+$K$4)^((B7-$B$2)/365)/-$E$2/(1+$K$4)^$K$2 -> 0
E8: =IF(B8<=$B$2,0,(C8+D8)) -> 0 | F8: =(E8*(B8-$B$2)/365)/(1+$K$4)^((B8-$B$2)/365)/-$E$2/(1+$K$4)^$K$2 -> 0
E9: =IF(B9<=$B$2,0,(C9+D9)) -> 0
E10: =IF(B10<=$B$2,0,(C10+D10)) -> 0
E11: =IF(B11<=$B$2,0,(C11+D11)) -> 0
E12: =IF(B12<=$B$2,0,(C12+D12)) -> 0
E13: =IF(B13<=$B$2,0,(C13+D13)) -> 0
E14: =IF(B14<=$B$2,0,(C14+D14)) -> 0
E15: =IF(B15<=$B$2,0,(C15+D15)) -> 0
E16: =IF(B16<=$B$2,0,(C16+D16)) -> 0
E17: =IF(B17<=$B$2,0,(C17+D17)) -> 0
E18: =IF(B18<=$B$2,0,(C18+D18)) -> 0

Sheet YM37D
A1: YM37D | B1: Fecha de Pago | C1: Interés | D1: Amortización | E1: Total
B2: ='ONS NY'!H2 -> 46060 | E2: =-VLOOKUP(A1,'ONs Argentina'!$C$5:$N$68,3,0) -> -103.95 | J2: Periodo de intereses | K2: 0.5
A3: 3 | B3: 46062 | C3: 1.76 | D3: 0 | E3: =IF(B3<=$B$2,0,(C3+D3)) -> 1.76 | F3: =(E3*(B3-$B$2)/365)/(1+$K$4)^((B3-$B$2)/365)/-$E$2/(1+$K$4)^$K$2 -> 9.0398319e-05 | J3: MDUR | K3: =SUM(F3:F102) -> 1.152466
A4: 4 | B4: 46149 | C4: 1.71 | D4: 0 | E4: =IF(B4<=$B$2,0,(C4+D4)) -> 1.71 | F4: =(E4*(B4-$B$2)/365)/(1+$K$4)^((B4-$B$2)/365)/-$E$2/(1+$K$4)^$K$2 -> 0.0038609296 | J4: TIR | K4: =XIRR(E2:E26,B2:B26) -> 0.052654067
A5: 5 | B5: 46241 | C5: 1.76 | D5: 0 | E5: =IF(B5<=$B$2,0,(C5+D5)) -> 1.76 | F5: =(E5*(B5-$B$2)/365)/(1+$K$4)^((B5-$B$2)/365)/-$E$2/(1+$K$4)^$K$2 -> 0.0079777385 | J5: ONS
A6: 6 | B6: 46335 | C6: 1.76 | D6: 0 | E6: =IF(B6<=$B$2,0,(C6+D6)) -> 1.76 | F6: =(E6*(B6-$B$2)/365)/(1+$K$4)^((B6-$B$2)/365)/-$E$2/(1+$K$4)^$K$2 -> 0.011961746
A7: 7 | B7: 46426 | C7: 1.76 | D7: 0 | E7: =IF(B7<=$B$2,0,(C7+D7)) -> 1.76 | F7: =(E7*(B7-$B$2)/365)/(1+$K$4)^((B7-$B$2)/365)/-$E$2/(1+$K$4)^$K$2 -> 0.015717622
A8: 8 | B8: 46514 | C8: 1.71 | D8: 100 | E8: =IF(B8<=$B$2,0,(C8+D8)) -> 101.71 | F8: =(E8*(B8-$B$2)/365)/(1+$K$4)^((B8-$B$2)/365)/-$E$2/(1+$K$4)^$K$2 -> 1.1128576
E9: =IF(B9<=$B$2,0,(C9+D9)) -> 0
E10: =IF(B10<=$B$2,0,(C10+D10)) -> 0
E11: =IF(B11<=$B$2,0,(C11+D11)) -> 0
E12: =IF(B12<=$B$2,0,(C12+D12)) -> 0
E13: =IF(B13<=$B$2,0,(C13+D13)) -> 0
E14: =IF(B14<=$B$2,0,(C14+D14)) -> 0
E15: =IF(B15<=$B$2,0,(C15+D15)) -> 0
E16: =IF(B16<=$B$2,0,(C16+D16)) -> 0
E17: =IF(B17<=$B$2,0,(C17+D17)) -> 0
E18: =IF(B18<=$B$2,0,(C18+D18)) -> 0

Sheet OTS2D
A1: OTS2D | B1: Fecha de Pago | C1: Interés | D1: Amortización | E1: Total
B2: ='ONS NY'!H2 -> 46060 | E2: =-VLOOKUP(A1,'ONs Argentina'!$C$5:$N$68,3,0) -> -102 | J2: Periodo de intereses | K2: 0.5
A3: 5 | B3: 46048 | C3: 1.76 | D3: 0 | E3: =IF(B3<=$B$2,0,(C3+D3)) -> 0 | F3: =(E3*(B3-$B$2)/365)/(1+$K$4)^((B3-$B$2)/365)/-$E$2/(1+$K$4)^$K$2 -> 0 | J3: MDUR | K3: =SUM(F3:F102) -> 1.1352231
A4: 6 | B4: 46136 | C4: 1.73 | D4: 0 | E4: =IF(B4<=$B$2,0,(C4+D4)) -> 1.73 | F4: =(E4*(B4-$B$2)/365)/(1+$K$4)^((B4-$B$2)/365)/-$E$2/(1+$K$4)^$K$2 -> 0.0033972994 | J4: TIR | K4: =XIRR(E2:E26,B2:B26) -> 0.056252691
A5: 7 | B5: 46227 | C5: 1.75 | D5: 0 | E5: =IF(B5<=$B$2,0,(C5+D5)) -> 1.75 | F5: =(E5*(B5-$B$2)/365)/(1+$K$4)^((B5-$B$2)/365)/-$E$2/(1+$K$4)^$K$2 -> 0.0074490858 | J5: ONS
A6: 8 | B6: 46321 | C6: 1.76 | D6: 0 | E6: =IF(B6<=$B$2,0,(C6+D6)) -> 1.76 | F6: =(E6*(B6-$B$2)/365)/(1+$K$4)^((B6-$B$2)/365)/-$E$2/(1+$K$4)^$K$2 -> 0.011544645
A7: 9 | B7: 46412 | C7: 1.76 | D7: 0 | E7: =IF(B7<=$B$2,0,(C7+D7)) -> 1.76 | F7: =(E7*(B7-$B$2)/365)/(1+$K$4)^((B7-$B$2)/365)/-$E$2/(1+$K$4)^$K$2 -> 0.015358793
A8: 10 | B8: 46501 | C8: 1.73 | D8: 100 | E8: =IF(B8<=$B$2,0,(C8+D8)) -> 101.73 | F8: =(E8*(B8-$B$2)/365)/(1+$K$4)^((B8-$B$2)/365)/-$E$2/(1+$K$4)^$K$2 -> 1.0974732
E9: =IF(B9<=$B$2,0,(C9+D9)) -> 0
E10: =IF(B10<=$B$2,0,(C10+D10)) -> 0
E11: =IF(B11<=$B$2,0,(C11+D11)) -> 0
E12: =IF(B12<=$B$2,0,(C12+D12)) -> 0
E13: =IF(B13<=$B$2,0,(C13+D13)) -> 0
E14: =IF(B14<=$B$2,0,(C14+D14)) -> 0
E15: =IF(B15<=$B$2,0,(C15+D15)) -> 0
E16: =IF(B16<=$B$2,0,(C16+D16)) -> 0
E17: =IF(B17<=$B$2,0,(C17+D17)) -> 0
E18: =IF(B18<=$B$2,0,(C18+D18)) -> 0

Sheet PN42D
A1: PN42D | B1: Fecha de Pago | C1: Interés | D1: Amortización | E1: Total
B2: ='ONS NY'!H2 -> 46060 | E2: =-VLOOKUP(A1,'ONs Argentina'!$C$5:$N$68,3,0) -> -103.5 | J2: Periodo de intereses | K2: 0.5
A3: 1 | B3: 46129 | C3: 2.99 | D3: 0 | E3: =IF(B3<=$B$2,0,(C3+D3)) -> 2.99 | F3: =(E3*(B3-$B$2)/365)/(1+$K$4)^((B3-$B$2)/365)/-$E$2/(1+$K$4)^$K$2 -> 0.0052950032 | J3: MDUR | K3: =SUM(F3:F102) -> 1.1261251
A4: 2 | B4: 46314 | C4: 3.01 | D4: 0 | E4: =IF(B4<=$B$2,0,(C4+D4)) -> 3.01 | F4: =(E4*(B4-$B$2)/365)/(1+$K$4)^((B4-$B$2)/365)/-$E$2/(1+$K$4)^$K$2 -> 0.019181121 | J4: TIR | K4: =XIRR(E2:E26,B2:B26) -> 0.045869634
A5: 3 | B5: 46496 | C5: 2.99 | D5: 100 | E5: =IF(B5<=$B$2,0,(C5+D5)) -> 102.99 | F5: =(E5*(B5-$B$2)/365)/(1+$K$4)^((B5-$B$2)/365)/-$E$2/(1+$K$4)^$K$2 -> 1.1016489 | J5: ONS
E6: =IF(B6<=$B$2,0,(C6+D6)) -> 0 | F6: =(E6*(B6-$B$2)/365)/(1+$K$4)^((B6-$B$2)/365)/-$E$2/(1+$K$4)^$K$2 -> 0
E7: =IF(B7<=$B$2,0,(C7+D7)) -> 0 | F7: =(E7*(B7-$B$2)/365)/(1+$K$4)^((B7-$B$2)/365)/-$E$2/(1+$K$4)^$K$2 -> 0
E8: =IF(B8<=$B$2,0,(C8+D8)) -> 0
E9: =IF(B9<=$B$2,0,(C9+D9)) -> 0
E10: =IF(B10<=$B$2,0,(C10+D10)) -> 0
E11: =IF(B11<=$B$2,0,(C11+D11)) -> 0
E12: =IF(B12<=$B$2,0,(C12+D12)) -> 0
E13: =IF(B13<=$B$2,0,(C13+D13)) -> 0
E14: =IF(B14<=$B$2,0,(C14+D14)) -> 0
E15: =IF(B15<=$B$2,0,(C15+D15)) -> 0
E16: =IF(B16<=$B$2,0,(C16+D16)) -> 0
E17: =IF(B17<=$B$2,0,(C17+D17)) -> 0
E18: =IF(B18<=$B$2,0,(C18+D18)) -> 0

Sheet VSCWD
A1: VSCWD | B1: Fecha de Pago | C1: Interés | D1: Amortización | E1: Total
B2: ='ONS NY'!H2 -> 46060 | E2: =-VLOOKUP(A1,'ONs Argentina'!$C$5:$N$68,3,0) -> -102.1 | J2: Periodo de intereses | K2: 0.5
A3: 2 | B3: 46127 | C3: 1.48 | D3: 0 | E3: =IF(B3<=$B$2,0,(C3+D3)) -> 1.48 | F3: =(E3*(B3-$B$2)/365)/(1+$K$4)^((B3-$B$2)/365)/-$E$2/(1+$K$4)^$K$2 -> 0.0025807256 | J3: MDUR | K3: =SUM(F3:F102) -> 1.1223397
A4: 3 | B4: 46218 | C4: 1.5 | D4: 0 | E4: =IF(B4<=$B$2,0,(C4+D4)) -> 1.5 | F4: =(E4*(B4-$B$2)/365)/(1+$K$4)^((B4-$B$2)/365)/-$E$2/(1+$K$4)^$K$2 -> 0.0060997421 | J4: TIR | K4: =XIRR(E2:E26,B2:B26) -> 0.045735696
A5: 4 | B5: 46310 | C5: 1.51 | D5: 0 | E5: =IF(B5<=$B$2,0,(C5+D5)) -> 1.51 | F5: =(E5*(B5-$B$2)/365)/(1+$K$4)^((B5-$B$2)/365)/-$E$2/(1+$K$4)^$K$2 -> 0.0096069314 | J5: ONS
A6: 5 | B6: 46402 | C6: 1.51 | D6: 0 | E6: =IF(B6<=$B$2,0,(C6+D6)) -> 1.51 | F6: =(E6*(B6-$B$2)/365)/(1+$K$4)^((B6-$B$2)/365)/-$E$2/(1+$K$4)^$K$2 -> 0.012994973
A7: 6 | B7: 46492 | C7: 1.48 | D7: 100 | E7: =IF(B7<=$B$2,0,(C7+D7)) -> 101.48 | F7: =(E7*(B7-$B$2)/365)/(1+$K$4)^((B7-$B$2)/365)/-$E$2/(1+$K$4)^$K$2 -> 1.0910573
E8: =IF(B8<=$B$2,0,(C8+D8)) -> 0
E9: =IF(B9<=$B$2,0,(C9+D9)) -> 0
E10: =IF(B10<=$B$2,0,(C10+D10)) -> 0
E11: =IF(B11<=$B$2,0,(C11+D11)) -> 0
E12: =IF(B12<=$B$2,0,(C12+D12)) -> 0
E13: =IF(B13<=$B$2,0,(C13+D13)) -> 0
E14: =IF(B14<=$B$2,0,(C14+D14)) -> 0
E15: =IF(B15<=$B$2,0,(C15+D15)) -> 0
E16: =IF(B16<=$B$2,0,(C16+D16)) -> 0
E17: =IF(B17<=$B$2,0,(C17+D17)) -> 0
E18: =IF(B18<=$B$2,0,(C18+D18)) -> 0

Sheet LMS8D
A1: LMS8D | B1: Fecha de Pago | C1: Interés | D1: Amortización | E1: Total
B2: ='ONS NY'!H2 -> 46060 | E2: =-VLOOKUP(A1,'ONs Argentina'!$C$5:$N$68,3,0) -> -103.75 | J2: Periodo de intereses | K2: 0.5
A3: 7 | B3: 46104 | C3: 1.56 | D3: 0 | E3: =IF(B3<=$B$2,0,(C3+D3)) -> 1.56 | F3: =(E3*(B3-$B$2)/365)/(1+$K$4)^((B3-$B$2)/365)/-$E$2/(1+$K$4)^$K$2 -> 0.0017863472 | J3: MDUR | K3: =SUM(F3:F102) -> 0.71878347
A4: 8 | B4: 46195 | C4: 1.6 | D4: 25 | E4: =IF(B4<=$B$2,0,(C4+D4)) -> 26.6 | F4: =(E4*(B4-$B$2)/365)/(1+$K$4)^((B4-$B$2)/365)/-$E$2/(1+$K$4)^$K$2 -> 0.09290961 | J4: TIR | K4: =XIRR(E2:E26,B2:B26) -> 0.023767588
A5: 9 | B5: 46286 | C5: 1.2 | D5: 25 | E5: =IF(B5<=$B$2,0,(C5+D5)) -> 26.2 | F5: =(E5*(B5-$B$2)/365)/(1+$K$4)^((B5-$B$2)/365)/-$E$2/(1+$K$4)^$K$2 -> 0.1523041 | J5: ONS
A6: 10 | B6: 46377 | C6: 0.79 | D6: 25 | E6: =IF(B6<=$B$2,0,(C6+D6)) -> 25.79 | F6: =(E6*(B6-$B$2)/365)/(1+$K$4)^((B6-$B$2)/365)/-$E$2/(1+$K$4)^$K$2 -> 0.20905912
A7: 11 | B7: 46467 | C7: 0.39 | D7: 25 | E7: =IF(B7<=$B$2,0,(C7+D7)) -> 25.39 | F7: =(E7*(B7-$B$2)/365)/(1+$K$4)^((B7-$B$2)/365)/-$E$2/(1+$K$4)^$K$2 -> 0.26272429
E8: =IF(B8<=$B$2,0,(C8+D8)) -> 0
E9: =IF(B9<=$B$2,0,(C9+D9)) -> 0
E10: =IF(B10<=$B$2,0,(C10+D10)) -> 0
E11: =IF(B11<=$B$2,0,(C11+D11)) -> 0
E12: =IF(B12<=$B$2,0,(C12+D12)) -> 0
E13: =IF(B13<=$B$2,0,(C13+D13)) -> 0
E14: =IF(B14<=$B$2,0,(C14+D14)) -> 0
E15: =IF(B15<=$B$2,0,(C15+D15)) -> 0
E16: =IF(B16<=$B$2,0,(C16+D16)) -> 0
E17: =IF(B17<=$B$2,0,(C17+D17)) -> 0
E18: =IF(B18<=$B$2,0,(C18+D18)) -> 0

Sheet IRCJDD
A1: IRCJD | B1: Fecha de Pago | C1: Interés | D1: Amortización | E1: Total
B2: ='ONS NY'!H2 -> 46060 | E2: =-VLOOKUP(A1,'ONs Argentina'!$C$5:$N$68,3,0) -> -105.35 | J2: Periodo de intereses | K2: 0.5
A3: 4 | B3: 46083 | C3: 3.53 | D3: 0 | E3: =IF(B3<=$B$2,0,(C3+D3)) -> 3.53 | F3: =(E3*(B3-$B$2)/365)/(1+$K$4)^((B3-$B$2)/365)/-$E$2/(1+$K$4)^$K$2 -> 0.0020556255 | J3: MDUR | K3: =SUM(F3:F102) -> 0.98444249
A4: 5 | B4: 46262 | C4: 3.47 | D4: 0 | E4: =IF(B4<=$B$2,0,(C4+D4)) -> 3.47 | F4: =(E4*(B4-$B$2)/365)/(1+$K$4)^((B4-$B$2)/365)/-$E$2/(1+$K$4)^$K$2 -> 0.017337682 | J4: TIR | K4: =XIRR(E2:E26,B2:B26) -> 0.048717996
A5: 6 | B5: 46446 | C5: 3.53 | D5: 100 | E5: =IF(B5<=$B$2,0,(C5+D5)) -> 103.53 | F5: =(E5*(B5-$B$2)/365)/(1+$K$4)^((B5-$B$2)/365)/-$E$2/(1+$K$4)^$K$2 -> 0.96504919 | J5: ONS
E8: =IF(B8<=$B$2,0,(C8+D8)) -> 0
E9: =IF(B9<=$B$2,0,(C9+D9)) -> 0
E10: =IF(B10<=$B$2,0,(C10+D10)) -> 0
E11: =IF(B11<=$B$2,0,(C11+D11)) -> 0
E12: =IF(B12<=$B$2,0,(C12+D12)) -> 0
E13: =IF(B13<=$B$2,0,(C13+D13)) -> 0
E14: =IF(B14<=$B$2,0,(C14+D14)) -> 0
E15: =IF(B15<=$B$2,0,(C15+D15)) -> 0
E16: =IF(B16<=$B$2,0,(C16+D16)) -> 0
E17: =IF(B17<=$B$2,0,(C17+D17)) -> 0
E18: =IF(B18<=$B$2,0,(C18+D18)) -> 0

Sheet ZZC1D
A1: ZZC1D | B1: Fecha de Pago | C1: Interés | D1: Amortización | E1: Total
B2: ='ONS NY'!H2 -> 46060 | E2: =-VLOOKUP(A1,'ONs Argentina'!$C$5:$N$68,3,0) -> -104.9 | J2: Periodo de intereses | K2: 0.5
A3: 2 | B3: 46076 | C3: 4.01 | D3: 0 | E3: =IF(B3<=$B$2,0,(C3+D3)) -> 4.01 | F3: =(E3*(B3-$B$2)/365)/(1+$K$4)^((B3-$B$2)/365)/-$E$2/(1+$K$4)^$K$2 -> 0.0016165757 | J3: MDUR | K3: =SUM(F3:F102) -> 0.95271821
A4: 3 | B4: 46255 | C4: 3.94 | D4: 0 | E4: =IF(B4<=$B$2,0,(C4+D4)) -> 3.94 | F4: =(E4*(B4-$B$2)/365)/(1+$K$4)^((B4-$B$2)/365)/-$E$2/(1+$K$4)^$K$2 -> 0.018741098 | J4: TIR | K4: =XIRR(E2:E26,B2:B26) -> 0.068279955
A5: 4 | B5: 46440 | C5: 4.01 | D5: 100 | E5: =IF(B5<=$B$2,0,(C5+D5)) -> 104.01 | F5: =(E5*(B5-$B$2)/365)/(1+$K$4)^((B5-$B$2)/365)/-$E$2/(1+$K$4)^$K$2 -> 0.93236054 | J5: ONS
E8: =IF(B8<=$B$2,0,(C8+D8)) -> 0
E9: =IF(B9<=$B$2,0,(C9+D9)) -> 0
E10: =IF(B10<=$B$2,0,(C10+D10)) -> 0
E11: =IF(B11<=$B$2,0,(C11+D11)) -> 0
E12: =IF(B12<=$B$2,0,(C12+D12)) -> 0
E13: =IF(B13<=$B$2,0,(C13+D13)) -> 0
E14: =IF(B14<=$B$2,0,(C14+D14)) -> 0
E15: =IF(B15<=$B$2,0,(C15+D15)) -> 0
E16: =IF(B16<=$B$2,0,(C16+D16)) -> 0
E17: =IF(B17<=$B$2,0,(C17+D17)) -> 0
E18: =IF(B18<=$B$2,0,(C18+D18)) -> 0

Sheet YM41D
A1: YM41D | B1: Fecha de Pago | C1: Interés | D1: Amortización | E1: Total
B2: ='ONS NY'!H2 -> 46060 | E2: =-VLOOKUP(A1,'ONs Argentina'!$C$5:$N$68,3,0) -> -101.6 | J2: Periodo de intereses | K2: 0.5
A3: 2 | B3: 46120 | C3: 1.48 | D3: 0 | E3: =IF(B3<=$B$2,0,(C3+D3)) -> 1.48 | F3: =(E3*(B3-$B$2)/365)/(1+$K$4)^((B3-$B$2)/365)/-$E$2/(1+$K$4)^$K$2 -> 0.0023204811 | J3: MDUR | K3: =SUM(F3:F102) -> 0.87504753
A4: 3 | B4: 46211 | C4: 1.5 | D4: 0 | E4: =IF(B4<=$B$2,0,(C4+D4)) -> 1.5 | F4: =(E4*(B4-$B$2)/365)/(1+$K$4)^((B4-$B$2)/365)/-$E$2/(1+$K$4)^$K$2 -> 0.005849404 | J4: TIR | K4: =XIRR(E2:E26,B2:B26) -> 0.048438343
A5: 4 | B5: 46303 | C5: 1.51 | D5: 0 | E5: =IF(B5<=$B$2,0,(C5+D5)) -> 1.51 | F5: =(E5*(B5-$B$2)/365)/(1+$K$4)^((B5-$B$2)/365)/-$E$2/(1+$K$4)^$K$2 -> 0.009363726 | J5: ONS
A6: 5 | B6: 46395 | C6: 1.51 | D6: 100 | E6: =IF(B6<=$B$2,0,(C6+D6)) -> 101.51 | F6: =(E6*(B6-$B$2)/365)/(1+$K$4)^((B6-$B$2)/365)/-$E$2/(1+$K$4)^$K$2 -> 0.85751392
E8: =IF(B8<=$B$2,0,(C8+D8)) -> 0
E9: =IF(B9<=$B$2,0,(C9+D9)) -> 0
E10: =IF(B10<=$B$2,0,(C10+D10)) -> 0
E11: =IF(B11<=$B$2,0,(C11+D11)) -> 0
E12: =IF(B12<=$B$2,0,(C12+D12)) -> 0
E13: =IF(B13<=$B$2,0,(C13+D13)) -> 0
E14: =IF(B14<=$B$2,0,(C14+D14)) -> 0
E15: =IF(B15<=$B$2,0,(C15+D15)) -> 0
E16: =IF(B16<=$B$2,0,(C16+D16)) -> 0
E17: =IF(B17<=$B$2,0,(C17+D17)) -> 0
E18: =IF(B18<=$B$2,0,(C18+D18)) -> 0

Sheet DNC3D
A1: DNC3D | B1: Fecha de Pago | C1: Interés | D1: Amortización | E1: Total
B2: ='ONS NY'!H2 -> 46060 | E2: =-VLOOKUP(A1,'ONs Argentina'!$C$5:$N$68,3,0) -> -104.75 | J2: Periodo de intereses | K2: 0.5
A3: 5 | B3: 46164 | C3: 4.83 | D3: 0 | E3: =IF(B3<=$B$2,0,(C3+D3)) -> 4.83 | F3: =(E3*(B3-$B$2)/365)/(1+$K$4)^((B3-$B$2)/365)/-$E$2/(1+$K$4)^$K$2 -> 0.012525552 | J3: MDUR | K3: =SUM(F3:F102) -> 0.74324279
A4: 6 | B4: 46348 | C4: 4.92 | D4: 100 | E4: =IF(B4<=$B$2,0,(C4+D4)) -> 104.92 | F4: =(E4*(B4-$B$2)/365)/(1+$K$4)^((B4-$B$2)/365)/-$E$2/(1+$K$4)^$K$2 -> 0.73071724 | J4: TIR | K4: =XIRR(E2:E26,B2:B26) -> 0.06271911
J5: ONS
E8: =IF(B8<=$B$2,0,(C8+D8)) -> 0
E9: =IF(B9<=$B$2,0,(C9+D9)) -> 0
E10: =IF(B10<=$B$2,0,(C10+D10)) -> 0
E11: =IF(B11<=$B$2,0,(C11+D11)) -> 0
E12: =IF(B12<=$B$2,0,(C12+D12)) -> 0
E13: =IF(B13<=$B$2,0,(C13+D13)) -> 0
E14: =IF(B14<=$B$2,0,(C14+D14)) -> 0
E15: =IF(B15<=$B$2,0,(C15+D15)) -> 0
E16: =IF(B16<=$B$2,0,(C16+D16)) -> 0
E17: =IF(B17<=$B$2,0,(C17+D17)) -> 0
E18: =IF(B18<=$B$2,0,(C18+D18)) -> 0

Sheet RC2CD
A1: RC2CD | B1: Fecha de Pago | C1: Interés | D1: Amortización | E1: Total
B2: ='ONS NY'!H2 -> 46060 | E2: =-VLOOKUP(A1,'ONs Argentina'!$C$5:$N$68,3,0) -> -103.3 | J2: Periodo de intereses | K2: 0.5
A3: 1 | B3: 46118 | C3: 2.98 | D3: 0 | E3: =IF(B3<=$B$2,0,(C3+D3)) -> 2.98 | F3: =(E3*(B3-$B$2)/365)/(1+$K$4)^((B3-$B$2)/365)/-$E$2/(1+$K$4)^$K$2 -> 0.0044658689 | J3: MDUR | K3: =SUM(F3:F102) -> 0.63322357
A4: 2 | B4: 46301 | C4: 3 | D4: 100 | E4: =IF(B4<=$B$2,0,(C4+D4)) -> 103 | F4: =(E4*(B4-$B$2)/365)/(1+$K$4)^((B4-$B$2)/365)/-$E$2/(1+$K$4)^$K$2 -> 0.62875771 | J4: TIR | K4: =XIRR(E2:E26,B2:B26) -> 0.040442637
J5: ONS
E8: =IF(B8<=$B$2,0,(C8+D8)) -> 0
E9: =IF(B9<=$B$2,0,(C9+D9)) -> 0
E10: =IF(B10<=$B$2,0,(C10+D10)) -> 0
E11: =IF(B11<=$B$2,0,(C11+D11)) -> 0
E12: =IF(B12<=$B$2,0,(C12+D12)) -> 0
E13: =IF(B13<=$B$2,0,(C13+D13)) -> 0
E14: =IF(B14<=$B$2,0,(C14+D14)) -> 0
E15: =IF(B15<=$B$2,0,(C15+D15)) -> 0
E16: =IF(B16<=$B$2,0,(C16+D16)) -> 0
E17: =IF(B17<=$B$2,0,(C17+D17)) -> 0
E18: =IF(B18<=$B$2,0,(C18+D18)) -> 0

Sheet YMCVD
A1: YMCVD | B1: Fecha de Pago | C1: Interés | D1: Amortización | E1: Total
B2: ='ONS NY'!H2 -> 46060 | E2: =-VLOOKUP(A1,'ONs Argentina'!$C$5:$N$68,3,0) -> -102.5 | J2: Periodo de intereses | K2: 0.5
A3: 6 | B3: 46083 | C3: 1.51 | D3: 0 | E3: =IF(B3<=$B$2,0,(C3+D3)) -> 1.51 | F3: =(E3*(B3-$B$2)/365)/(1+$K$4)^((B3-$B$2)/365)/-$E$2/(1+$K$4)^$K$2 -> 0.00092030679 | J3: MDUR | K3: =SUM(F3:F102) -> 0.29558323
A4: 7 | B4: 46170 | C4: 1.46 | D4: 100 | E4: =IF(B4<=$B$2,0,(C4+D4)) -> 101.46 | F4: =(E4*(B4-$B$2)/365)/(1+$K$4)^((B4-$B$2)/365)/-$E$2/(1+$K$4)^$K$2 -> 0.29466293 | J4: TIR | K4: =XIRR(E2:E26,B2:B26) -> 0.015477309
E5: =IF(B5<=$B$2,0,(C5+D5)) -> 0 | J5: ONS
E6: =IF(B6<=$B$2,0,(C6+D6)) -> 0
E7: =IF(B7<=$B$2,0,(C7+D7)) -> 0
E8: =IF(B8<=$B$2,0,(C8+D8)) -> 0
E9: =IF(B9<=$B$2,0,(C9+D9)) -> 0
E10: =IF(B10<=$B$2,0,(C10+D10)) -> 0
E11: =IF(B11<=$B$2,0,(C11+D11)) -> 0
E12: =IF(B12<=$B$2,0,(C12+D12)) -> 0
E13: =IF(B13<=$B$2,0,(C13+D13)) -> 0
E14: =IF(B14<=$B$2,0,(C14+D14)) -> 0
E15: =IF(B15<=$B$2,0,(C15+D15)) -> 0
E16: =IF(B16<=$B$2,0,(C16+D16)) -> 0
E17: =IF(B17<=$B$2,0,(C17+D17)) -> 0
E18: =IF(B18<=$B$2,0,(C18+D18)) -> 0

Sheet GN49D
A1: GN49D | B1: Fecha de Pago | C1: Interés | D1: Amortización | E1: Total
B2: ='ONS NY'!H2 -> 46060 | E2: =-VLOOKUP(A1,'ONS NY'!$C$5:$R$589,3,0) -> -105.55 | J2: Periodo de intereses | K2: 0.5
A3: 1 | B3: 46175 | C3: 3.88 | D3: 0 | E3: =IF(B3<=$B$2,0,(C3+D3)) -> 3.88 | F3: =(E3*(B3-$B$2)/365)/(1+$K$4)^((B3-$B$2)/365)/-$E$2/(1+$K$4)^$K$2 -> 0.010951943 | J3: MDUR | K3: =SUM(F3:F102) -> 5.1975468
A4: 2 | B4: 46358 | C4: 3.88 | D4: 0 | E4: =IF(B4<=$B$2,0,(C4+D4)) -> 3.88 | F4: =(E4*(B4-$B$2)/365)/(1+$K$4)^((B4-$B$2)/365)/-$E$2/(1+$K$4)^$K$2 -> 0.027420153 | J4: TIR | K4: =XIRR(E2:E26,B2:B26) -> 0.071020624
A5: 3 | B5: 46540 | C5: 3.88 | D5: 0 | E5: =IF(B5<=$B$2,0,(C5+D5)) -> 3.88 | F5: =(E5*(B5-$B$2)/365)/(1+$K$4)^((B5-$B$2)/365)/-$E$2/(1+$K$4)^$K$2 -> 0.042681213 | J5: ONS
A6: 4 | B6: 46723 | C6: 3.88 | D6: 0 | E6: =IF(B6<=$B$2,0,(C6+D6)) -> 3.88 | F6: =(E6*(B6-$B$2)/365)/(1+$K$4)^((B6-$B$2)/365)/-$E$2/(1+$K$4)^$K$2 -> 0.056959912
A7: 5 | B7: 46906 | C7: 3.88 | D7: 0 | E7: =IF(B7<=$B$2,0,(C7+D7)) -> 3.88 | F7: =(E7*(B7-$B$2)/365)/(1+$K$4)^((B7-$B$2)/365)/-$E$2/(1+$K$4)^$K$2 -> 0.070224136
A8: 6 | B8: 47091 | C8: 3.88 | D8: 0 | E8: =IF(B8<=$B$2,0,(C8+D8)) -> 3.88 | F8: =(E8*(B8-$B$2)/365)/(1+$K$4)^((B8-$B$2)/365)/-$E$2/(1+$K$4)^$K$2 -> 0.082655488
A9: 7 | B9: 47273 | C9: 3.88 | D9: 0 | E9: =IF(B9<=$B$2,0,(C9+D9)) -> 3.88 | F9: =(E9*(B9-$B$2)/365)/(1+$K$4)^((B9-$B$2)/365)/-$E$2/(1+$K$4)^$K$2 -> 0.093975736
A10: 8 | B10: 47455 | C10: 3.88 | D10: 0 | E10: =IF(B10<=$B$2,0,(C10+D10)) -> 3.88 | F10: =(E10*(B10-$B$2)/365)/(1+$K$4)^((B10-$B$2)/365)/-$E$2/(1+$K$4)^$K$2 -> 0.104441
A11: 9 | B11: 47637 | C11: 3.88 | D11: 0 | E11: =IF(B11<=$B$2,0,(C11+D11)) -> 3.88 | F11: =(E11*(B11-$B$2)/365)/(1+$K$4)^((B11-$B$2)/365)/-$E$2/(1+$K$4)^$K$2 -> 0.114096
A12: 10 | B12: 47819 | C12: 3.88 | D12: 0 | E12: =IF(B12<=$B$2,0,(C12+D12)) -> 3.88 | F12: =(E12*(B12-$B$2)/365)/(1+$K$4)^((B12-$B$2)/365)/-$E$2/(1+$K$4)^$K$2 -> 0.1229834
A13: 11 | B13: 48001 | C13: 3.88 | D13: 0 | E13: =IF(B13<=$B$2,0,(C13+D13)) -> 3.88 | F13: =(E13*(B13-$B$2)/365)/(1+$K$4)^((B13-$B$2)/365)/-$E$2/(1+$K$4)^$K$2 -> 0.13114389
A14: 12 | B14: 48184 | C14: 3.88 | D14: 33 | E14: =IF(B14<=$B$2,0,(C14+D14)) -> 36.88 | F14: =(E14*(B14-$B$2)/365)/(1+$K$4)^((B14-$B$2)/365)/-$E$2/(1+$K$4)^$K$2 -> 1.3179426
A15: 13 | B15: 48367 | C15: 2.6 | D15: 0 | E15: =IF(B15<=$B$2,0,(C15+D15)) -> 2.6 | F15: =(E15*(B15-$B$2)/365)/(1+$K$4)^((B15-$B$2)/365)/-$E$2/(1+$K$4)^$K$2 -> 0.097506212
A16: 14 | B16: 48550 | C16: 2.6 | D16: 33 | E16: =IF(B16<=$B$2,0,(C16+D16)) -> 35.6 | F16: =(E16*(B16-$B$2)/365)/(1+$K$4)^((B16-$B$2)/365)/-$E$2/(1+$K$4)^$K$2 -> 1.3922619
A17: 15 | B17: 48732 | C17: 1.32 | D17: 0 | E17: =IF(B17<=$B$2,0,(C17+D17)) -> 1.32 | F17: =(E17*(B17-$B$2)/365)/(1+$K$4)^((B17-$B$2)/365)/-$E$2/(1+$K$4)^$K$2 -> 0.053533285
A18: 16 | B18: 48915 | C18: 1.32 | D18: 34 | E18: =IF(B18<=$B$2,0,(C18+D18)) -> 35.32 | F18: =(E18*(B18-$B$2)/365)/(1+$K$4)^((B18-$B$2)/365)/-$E$2/(1+$K$4)^$K$2 -> 1.4787698

Sheet PLC5D
A1: PLC5D | B1: Fecha de Pago | C1: Interés | D1: Amortización | E1: Total
B2: ='ONS NY'!H2 -> 46060 | E2: =-VLOOKUP(A1,'ONS NY'!$C$5:$R$589,3,0) -> -106.55 | J2: Periodo de intereses | K2: 0.5
A3: 1 | B3: 46160 | C3: 4.06 | D3: 0 | E3: =IF(B3<=$B$2,0,(C3+D3)) -> 4.06 | F3: =(E3*(B3-$B$2)/365)/(1+$K$4)^((B3-$B$2)/365)/-$E$2/(1+$K$4)^$K$2 -> 0.0098965254 | J3: MDUR | K3: =SUM(F3:F102) -> 4.2018316
A4: 2 | B4: 46344 | C4: 4.06 | D4: 0 | E4: =IF(B4<=$B$2,0,(C4+D4)) -> 4.06 | F4: =(E4*(B4-$B$2)/365)/(1+$K$4)^((B4-$B$2)/365)/-$E$2/(1+$K$4)^$K$2 -> 0.027145151 | J4: TIR | K4: =XIRR(E2:E26,B2:B26) -> 0.071448514
A5: 3 | B5: 46525 | C5: 4.06 | D5: 0 | E5: =IF(B5<=$B$2,0,(C5+D5)) -> 4.06 | F5: =(E5*(B5-$B$2)/365)/(1+$K$4)^((B5-$B$2)/365)/-$E$2/(1+$K$4)^$K$2 -> 0.042950121 | J5: ONS
A6: 4 | B6: 46709 | C6: 4.06 | D6: 0 | E6: =IF(B6<=$B$2,0,(C6+D6)) -> 4.06 | F6: =(E6*(B6-$B$2)/365)/(1+$K$4)^((B6-$B$2)/365)/-$E$2/(1+$K$4)^$K$2 -> 0.057895834
A7: 5 | B7: 46891 | C7: 4.06 | D7: 0 | E7: =IF(B7<=$B$2,0,(C7+D7)) -> 4.06 | F7: =(E7*(B7-$B$2)/365)/(1+$K$4)^((B7-$B$2)/365)/-$E$2/(1+$K$4)^$K$2 -> 0.071624078
A8: 6 | B8: 47078 | C8: 4.06 | D8: 0 | E8: =IF(B8<=$B$2,0,(C8+D8)) -> 4.06 | F8: =(E8*(B8-$B$2)/365)/(1+$K$4)^((B8-$B$2)/365)/-$E$2/(1+$K$4)^$K$2 -> 0.084693608
A9: 7 | B9: 47256 | C9: 4.06 | D9: 0 | E9: =IF(B9<=$B$2,0,(C9+D9)) -> 4.06 | F9: =(E9*(B9-$B$2)/365)/(1+$K$4)^((B9-$B$2)/365)/-$E$2/(1+$K$4)^$K$2 -> 0.096209485
A10: 8 | B10: 47442 | C10: 4.06 | D10: 0 | E10: =IF(B10<=$B$2,0,(C10+D10)) -> 4.06 | F10: =(E10*(B10-$B$2)/365)/(1+$K$4)^((B10-$B$2)/365)/-$E$2/(1+$K$4)^$K$2 -> 0.10733014
A11: 9 | B11: 47623 | C11: 4.06 | D11: 0 | E11: =IF(B11<=$B$2,0,(C11+D11)) -> 4.06 | F11: =(E11*(B11-$B$2)/365)/(1+$K$4)^((B11-$B$2)/365)/-$E$2/(1+$K$4)^$K$2 -> 0.11730328
A12: 10 | B12: 47806 | C12: 4.06 | D12: 0 | E12: =IF(B12<=$B$2,0,(C12+D12)) -> 4.06 | F12: =(E12*(B12-$B$2)/365)/(1+$K$4)^((B12-$B$2)/365)/-$E$2/(1+$K$4)^$K$2 -> 0.12658105
A13: 11 | B13: 47987 | C13: 4.06 | D13: 100 | E13: =IF(B13<=$B$2,0,(C13+D13)) -> 104.06 | F13: =(E13*(B13-$B$2)/365)/(1+$K$4)^((B13-$B$2)/365)/-$E$2/(1+$K$4)^$K$2 -> 3.4602023

Sheet TTCDD
A1: TTCDD | B1: Fecha de Pago | C1: Interés | D1: Amortización | E1: Total
B2: ='ONS NY'!H2 -> 46060 | E2: =-VLOOKUP(A1,'ONS NY'!$C$5:$R$589,3,0) -> -106.05 | J2: Periodo de intereses | K2: 0.5
A3: 1 | B3: 46146 | C3: 3.81 | D3: 0 | E3: =IF(B3<=$B$2,0,(C3+D3)) -> 3.81 | F3: =(E3*(B3-$B$2)/365)/(1+$K$4)^((B3-$B$2)/365)/-$E$2/(1+$K$4)^$K$2 -> 0.0080699766 | J3: MDUR | K3: =SUM(F3:F102) -> 3.8809856
A4: 2 | B4: 46329 | C4: 3.81 | D4: 0 | E4: =IF(B4<=$B$2,0,(C4+D4)) -> 3.81 | F4: =(E4*(B4-$B$2)/365)/(1+$K$4)^((B4-$B$2)/365)/-$E$2/(1+$K$4)^$K$2 -> 0.024433477 | J4: TIR | K4: =XIRR(E2:E26,B2:B26) -> 0.067098203
A5: 3 | B5: 46510 | C5: 3.81 | D5: 0 | E5: =IF(B5<=$B$2,0,(C5+D5)) -> 3.81 | F5: =(E5*(B5-$B$2)/365)/(1+$K$4)^((B5-$B$2)/365)/-$E$2/(1+$K$4)^$K$2 -> 0.03957849 | J5: ONS
A6: 4 | B6: 46694 | C6: 3.81 | D6: 0 | E6: =IF(B6<=$B$2,0,(C6+D6)) -> 3.81 | F6: =(E6*(B6-$B$2)/365)/(1+$K$4)^((B6-$B$2)/365)/-$E$2/(1+$K$4)^$K$2 -> 0.053965706
A7: 5 | B7: 46876 | C7: 3.81 | D7: 0 | E7: =IF(B7<=$B$2,0,(C7+D7)) -> 3.81 | F7: =(E7*(B7-$B$2)/365)/(1+$K$4)^((B7-$B$2)/365)/-$E$2/(1+$K$4)^$K$2 -> 0.067244258
A8: 6 | B8: 47060 | C8: 3.81 | D8: 0 | E8: =IF(B8<=$B$2,0,(C8+D8)) -> 3.81 | F8: =(E8*(B8-$B$2)/365)/(1+$K$4)^((B8-$B$2)/365)/-$E$2/(1+$K$4)^$K$2 -> 0.079752985
A9: 7 | B9: 47241 | C9: 3.81 | D9: 0 | E9: =IF(B9<=$B$2,0,(C9+D9)) -> 3.81 | F9: =(E9*(B9-$B$2)/365)/(1+$K$4)^((B9-$B$2)/365)/-$E$2/(1+$K$4)^$K$2 -> 0.091203301
A10: 8 | B10: 47427 | C10: 3.81 | D10: 0 | E10: =IF(B10<=$B$2,0,(C10+D10)) -> 3.81 | F10: =(E10*(B10-$B$2)/365)/(1+$K$4)^((B10-$B$2)/365)/-$E$2/(1+$K$4)^$K$2 -> 0.10213075
A11: 9 | B11: 47606 | C11: 3.81 | D11: 0 | E11: =IF(B11<=$B$2,0,(C11+D11)) -> 3.81 | F11: =(E11*(B11-$B$2)/365)/(1+$K$4)^((B11-$B$2)/365)/-$E$2/(1+$K$4)^$K$2 -> 0.11188343
A12: 10 | B12: 47791 | C12: 3.81 | D12: 100 | E12: =IF(B12<=$B$2,0,(C12+D12)) -> 103.81 | F12: =(E12*(B12-$B$2)/365)/(1+$K$4)^((B12-$B$2)/365)/-$E$2/(1+$K$4)^$K$2 -> 3.3027232

Sheet MGCRD
A1: MGCRD | B1: Fecha de Pago | C1: Interés | D1: Amortización | E1: Total
B2: ='ONS NY'!H2 -> 46060 | E2: =-VLOOKUP(A1,'ONS NY'!$C$5:$R$589,3,0) -> -105.1 | J2: Periodo de intereses | K2: 0.5
A3: 1 | B3: 46156 | C3: 3.88 | D3: 0 | E3: =IF(B3<=$B$2,0,(C3+D3)) -> 3.88 | F3: =(E3*(B3-$B$2)/365)/(1+$K$4)^((B3-$B$2)/365)/-$E$2/(1+$K$4)^$K$2 -> 0.0091908828 | J3: MDUR | K3: =SUM(F3:F102) -> 7.5846465
A4: 2 | B4: 46342 | C4: 3.88 | D4: 0 | E4: =IF(B4<=$B$2,0,(C4+D4)) -> 3.88 | F4: =(E4*(B4-$B$2)/365)/(1+$K$4)^((B4-$B$2)/365)/-$E$2/(1+$K$4)^$K$2 -> 0.026025942 | J4: TIR | K4: =XIRR(E2:E26,B2:B26) -> 0.074627194
A5: 3 | B5: 46521 | C5: 3.88 | D5: 0 | E5: =IF(B5<=$B$2,0,(C5+D5)) -> 3.88 | F5: =(E5*(B5-$B$2)/365)/(1+$K$4)^((B5-$B$2)/365)/-$E$2/(1+$K$4)^$K$2 -> 0.041070415 | J5: ONS
A6: 4 | B6: 46706 | C6: 3.88 | D6: 0 | E6: =IF(B6<=$B$2,0,(C6+D6)) -> 3.88 | F6: =(E6*(B6-$B$2)/365)/(1+$K$4)^((B6-$B$2)/365)/-$E$2/(1+$K$4)^$K$2 -> 0.055490377
A7: 5 | B7: 46888 | C7: 3.88 | D7: 0 | E7: =IF(B7<=$B$2,0,(C7+D7)) -> 3.88 | F7: =(E7*(B7-$B$2)/365)/(1+$K$4)^((B7-$B$2)/365)/-$E$2/(1+$K$4)^$K$2 -> 0.068616633
A8: 6 | B8: 47071 | C8: 3.88 | D8: 0 | E8: =IF(B8<=$B$2,0,(C8+D8)) -> 3.88 | F8: =(E8*(B8-$B$2)/365)/(1+$K$4)^((B8-$B$2)/365)/-$E$2/(1+$K$4)^$K$2 -> 0.08081249
A9: 7 | B9: 47252 | C9: 3.88 | D9: 0 | E9: =IF(B9<=$B$2,0,(C9+D9)) -> 3.88 | F9: =(E9*(B9-$B$2)/365)/(1+$K$4)^((B9-$B$2)/365)/-$E$2/(1+$K$4)^$K$2 -> 0.091939711
A10: 8 | B10: 47436 | C10: 3.88 | D10: 0 | E10: =IF(B10<=$B$2,0,(C10+D10)) -> 3.88 | F10: =(E10*(B10-$B$2)/365)/(1+$K$4)^((B10-$B$2)/365)/-$E$2/(1+$K$4)^$K$2 -> 0.10235002
